Workbook
Name _Hlk503992398: 'SPML POML'!$C$3
Name CDﾚｰﾄ: #REF!
Name DATA: [1]DATA!$C:$J
Name DB_◆新マスタ09値: #REF!
Name DB_AF07Bコード: #REF!
Name DB_AF07Bコード新: #REF!
Name DB_NEW: #REF!
Name DB_SK07Bコード現: #REF!
Name JL0004_1月: "DB_JAL07便別情報"
Name MMレート: #REF!
Name Newagain: #REF!
Name Newagains: #REF!
Name Newcc: #REF!
Name Newname: #REF!
Name NEWSAS: #REF!

Sheet PL spec codes C1-3
A1: Caterer: TBD | Station: ATL | B1: Concept: 01JUN24 | Version: 1 | Updated: 05DEC23
A2: C1-C4 Overview all spec Codes
A3: SAS IFX Spec Code | B3: SAS IFX Description | C3: Weight / Pc | D3: Unit of M | E3: Quality, supplier, origin, comments | F3: Direct Material | G3: Direct Labor | H3: Selling Price ex contrubtion | I3: Class | J3: Loading Instructions (Widebody) | K3: Note
A4: 4ATL-411050 | B4: IC C S1 CUTLERY C1-4 | F4: =SUM(F5:F13) -> 0 | G4: =SUM(G5:G13) -> 0 | H4: =SUM(F4:G4) -> 0 | I4: C | J4: Fix Qty 40
A5: 2ATL-411011 | B5: IC C S1 SALAD C1 | I5: C | J5: Load Scale IC-27
A6: 2ATL-411012 | B6: IC C S1 SALAD C2 | I6: C | J6: Load Scale IC-27
A7: 2ATL-411013 | B7: IC C S1 SALAD C3 | I7: C | J7: Load Scale IC-27
A8: 2ATL-411031 | B8: IC C S1 SA GARNISH C1 | I8: C | J8: Fix Qty 2
A9: 2ATL-411050 | B9: IC C S1+S2 BUTTER C1-4 | I9: C | J9: 1
A10: 2ATL-411061 | B10: IC C S1 ST-A MEAT C1 | I10: C | J10: 60% (U)
A11: 2ATL-411071 | B11: IC C S1 ST-B FISH C1 | I11: C | J11: 60% (D)
A12: 2ATL-411081 | B12: IC C S1 ST GARNISH C1 | I12: C | J12: Fix Qty 2 | M12: =SUM(M13:M21) -> 0 | N12: =SUM(N13:N21) -> 0
A13: 2ATL-411091 | B13: IC C S1 HM-A MEAT C1 | I13: C | J13: 30% (U)
A14: 2ATL-411101 | B14: IC C S1 HM-B FISH C1 | I14: C | J14: 35% (D)
A15: 2ATL-411111 | B15: IC C S1 HM-C POULTRY C1 | I15: C | J15: 35% (D)
A16: 2ATL-411121 | B16: IC C S1 HM-D VEG C1 | I16: C | J16: 20% (U)
A17: 2ATL-411131 | B17: IC C S1 HM GARNISH C1 | I17: C | J17: Fix Qty 2
A18: 2ATL-411141 | B18: IC C S1 DE CHEESE C1 | I18: C | J18: Load Scale IC-27
A19: 2ATL-411151 | B19: IC C S1 DE CAKE C1 | I19: C | J19: Load Scale IC-27
A20: 2ATL-411161 | B20: IC C S1 DE CAKE GARNISH C1 | I20: C | J20: Fix Qty 2
A21: 2ATL-411171 | B21: IC C S1 DE ICE CREAM C1 | I21: C | J21: 60% (N)
A22: 2ATL-411180 | B22: IC C S1 DE FRUIT C1 | I22: C | J22: Load Scale IC-27
A23: 2ATL-411181 | B23: IC C S1 DE FRUIT C2 | I23: C | J23: Load Scale IC-27
A24: 2ATL-411182 | B24: IC C S1 DE FRUIT C3 | I24: C | J24: Load Scale IC-27
A25: 4ATL-411010 | B25: IC C S1 BRD Type 1 C1-4 | I25: C | J25: 75% (N) | K25: Min qty 5.
A26: 4ATL-411020 | B26: IC C S1+S2 BRD Type 2 C1-4 | I26: C | J26: 75% (N) | K26: Min qty 5.
A27: 4ATL-411030 | B27: IC C S1 BRD Type 3 C1-4 | I27: C | J27: Fix Qty 2
A28: 2ATL-411032 | B28: IC C S1 SA GARNISH C2 | I28: C | J28: Fix Qty 2
A29: 2ATL-411062 | B29: IC C S1 ST-A MEAT C2 | I29: C | J29: 60% (U)
A30: 2ATL-411072 | B30: IC C S1 ST-B FISH C2 | I30: C | J30: 60% (D)
A31: 2ATL-411082 | B31: IC C S1 ST GARNISH C2 | I31: C | J31: Fix Qty 2
A32: 2ATL-411092 | B32: IC C S1 HM-A MEAT C2 | I32: C | J32: 30% (U)
A33: 2ATL-411102 | B33: IC C S1 HM-B FISH C2 | I33: C | J33: 35% (D)
A34: 2ATL-411112 | B34: IC C S1 HM-C POULTRY C2 | I34: C | J34: 35% (D)
A35: 2ATL-411122 | B35: IC C S1 HM-D VEG C2 | I35: C | J35: 20% (U)
A36: 2ATL-411132 | B36: IC C S1 HM GARNISH C2 | I36: C | J36: Fix Qty 2
A37: 2ATL-411142 | B37: IC C S1 DE CHEESE C2 | I37: C | J37: Load Scale IC-27
A38: 2ATL-411152 | B38: IC C S1 DE CAKE C2 | I38: C | J38: Load Scale IC-27
... A53: 2ATL-411173 | B53: IC C S1 DE ICE CREAM C3 | I53: C | J53: 60% (N)
A54: 3ATL-412010 | B54: IC C S2 TSU C1 | I54: C | J54: 1
A55: 3ATL-412011 | B55: IC C S2 TSU C2 | I55: C | J55: 1
A56: 3ATL-412012 | B56: IC C S2 TSU C3 | I56: C | J56: 1
A57: 4ATL-412040 | B57: IC C S2 CUTLERY C1-4 | I57: C | J57: 1
A58: 2ATL-412011 | B58: IC C S2 COLD CUTS C1 | I58: C | J58: 1
A59: 2ATL-411050 | B59: IC C S1+S2 BUTTER C1-4 | I59: C | J59: 1
A60: 2ATL-412030 | B60: IC C S2 FRUIT C1 | I60: C | J60: 1
A61: 2ATL-412031 | B61: IC C S2 FRUIT C2 | I61: C | J61: 1
A62: 2ATL-412032 | B62: IC C S2 FRUIT C3 | I62: C | J62: 1
A63: 2ATL-412040 | B63: IC C S2 YOGHURT C1 | I63: C | J63: 80% (N)
A64: 2ATL-412041 | B64: IC C S2 YOGHURT C2 | I64: C | J64: 80% (N)
A65: 2ATL-412042 | B65: IC C S2 YOGHURT C3 | I65: C | J65: 80% (N)
A66: 4ATL-412010 | B66: IC C S2 BRD Type 1 C1-4 | I66: C | J66: 60% (N) | K66: Min qty 5.
A67: 4ATL-411020 | B67: IC C S1+S2 BRD Type 2 C1-4 | I67: C | J67: 60% (N) | K67: Min qty 5.
A68: 4ATL-412020 | B68: IC C S2 BRD Croissant C1-4 | I68: C | J68: 1 | K68: Min qty 5.
A69: 2ATL-412012 | B69: IC C S2 COLD CUTS C2 | I69: C | J69: 1
A70: 2ATL-412013 | B70: IC C S2 COLD CUTS C3 | I70: C | J70: 1
A71: 2ATL-413011 | B71: IC C IBS SW C1 | I71: C | J71: 50% (N) | K71: Min qty 5.
A72: 2ATL-413012 | B72: IC C IBS SW C2 | I72: C | J72: 50% (N) | K72: Min qty 5.
A73: 2ATL-413013 | B73: IC C IBS SW C3 | I73: C | J73: 50% (N) | K73: Min qty 5.
A74: 3ATL-421010 | B74: IC Y S1 TSU C1 | I74: Y | J74: 1
A75: 3ATL-421011 | B75: IC Y S1 TSU C2 | I75: Y | J75: 1
A76: 3ATL-421012 | B76: IC Y S1 TSU C3 | I76: Y | J76: 1
A77: 2ATL-421011 | B77: IC Y S1 ST C1 | I77: Y | J77: 1
A78: 2ATL-421021 | B78: IC Y S1 HM-A C1 | I78: Y | J78: 60% (D)
A79: 2ATL-421031 | B79: IC Y/M S1 HM-B C1 | I79: Y | J79: 40% (U) | K79: Also used for M.
A80: 2ATL-421040 | B80: IC Y S1 DE C1 | I80: Y | J80: 1
A81: 2ATL-421041 | B81: IC Y S1 DE C2 | I81: Y | J81: 1
A82: 2ATL-421042 | B82: IC Y S1 DE C3 | I82: Y | J82: 1
A83: 4ATL-421010 | B83: IC Y/M S1+S2 BRD Type 1 C1-4 | I83: Y | J83: 120% (N) | K83: Min qty 10.
A84: 2ATL-421012 | B84: IC Y S1 ST C2 | I84: Y | J84: 1
A85: 2ATL-421022 | B85: IC Y S1 HM-A C2 | I85: Y | J85: 60% (D)
A86: 2ATL-421032 | B86: IC Y/M S1 HM-B C2 | I86: Y | J86: 40% (U) | K86: Also used for M.
A87: 2ATL-421013 | B87: IC Y S1 ST C3 | I87: Y | J87: 1
A88: 2ATL-421023 | B88: IC Y S1 HM-A C3 | I88: Y | J88: 60% (D)
A89: 2ATL-421033 | B89: IC Y/M S1 HM-B C3 | I89: Y | J89: 40% (U) | K89: Also used for M.
A90: 3ATL-422010 | B90: IC Y S2 TSU C1 | I90: Y | J90: 1
A91: 3ATL-422011 | B91: IC Y S2 TSU C2 | I91: Y | J91: 1
A92: 3ATL-422012 | B92: IC Y S2 TSU C3 | I92: Y | J92: 1
A93: 2ATL-422011 | B93: IC Y S2 BREAKFAST PLATE C1 | I93: Y | J93: 1
A94: 4ATL-421010 | B94: IC Y/M S1+S2 BRD Type 1 C1-4 | I94: Y | J94: 120% (N) | K94: Min qty 10.
A95: 2ATL-422012 | B95: IC Y S2 BREAKFAST PLATE C2 | I95: Y | J95: 1
A96: 2ATL-422013 | B96: IC Y S2 BREAKFAST PLATE C3 | I96: Y | J96: 1
A97: 3ATL-431010 | B97: IC M S1 TSU C1 | I97: M | J97: 1
A98: 3ATL-431011 | B98: IC M S1 TSU C2 | I98: M | J98: 1
A99: 3ATL-431012 | B99: IC M S1 TSU C3 | I99: M | J99: 1
A100: 2ATL-431011 | B100: IC M S1 SALAD C1 | I100: M | J100: 1
A101: 2ATL-421031 | B101: IC Y/M S1 HM-B C1 | I101: M | J101: 1 | K101: Also used for Y.
A102: 2ATL-431020 | B102: IC M S1 DE C1 | I102: M | J102: 1
A103: 2ATL-431021 | B103: IC M S1 DE C2 | I103: M | J103: 1
A104: 2ATL-431022 | B104: IC M S1 DE C3 | I104: M | J104: 1
A105: 4ATL-421010 | B105: IC Y/M S1+S2 BRD Type 1 C1-4 | I105: M | J105: 120% (N) | K105: Min qty 10.
A106: 2ATL-431012 | B106: IC M S1 SALAD C2 | I106: M | J106: 1
A107: 2ATL-421032 | B107: IC Y/M S1 HM-B C2 | I107: M | J107: 1 | K107: Also used for Y.
A108: 2ATL-431013 | B108: IC M S1 SALAD C3 | I108: M | J108: 1
A109: 2ATL-421033 | B109: IC Y/M S1 HM-B C3 | I109: M | J109: 1 | K109: Also used for Y.
A110: 2ATL-432020 | B110: IC M S2 SW C1-4 | I110: M | J110: 1
A111: 4ATL-432010 | B111: IC M S2 JUICE C1-4 | I111: M | J111: 1
A112: 3ATL-9110BK3 | B112: IC C S1 BKML C3 | I112: C | J112: -
A113: 3ATL-9120BK3 | B113: IC C S2 BKML C3 | I113: C | J113: -
A114: 3ATL-9210BK3 | B114: IC Y S1 BKML C3 | I114: Y | J114: -
...

Sheet SPML POML
B2: SPECIAL MEALS (SPML) | D2: SPECIAL MEALS (SPML) | F2: PRE-ORDER MEALS (POML) | H2: SPECIAL MEALS (SPML) | I2: Note | J2: Description of meal
B3: LH Business & Plus class | D3: LH Go class | F3: LH for GO pax | H3: LH for CREW
B6: AVML | D6: ADML | F6: - | H6: - | I6: 1st & 2nd Service | J6: Asian vegetarian, spicy (may contain eggs and/or dairy)
B7: CHML | D7: CDML | F7: - | H7: - | I7: 1st & 2nd Service | J7: Child meal
B8: LGML | D8: GCML | F8: - | H8: LGML | I8: 1st & 2nd Service | J8: A meal adapted to gluten and lactose intolerance
B9: VLML | D9: EVML | F9: - | H9: VLML | I9: 1st & 2nd Service | J9: A lacto-ovo vegetarian meal (contains eggs and/or dairy)
B10: VGML | D10: VVML | F10: - | H10: VGML | I10: 1st & 2nd Service | J10: A vegan vegetarian meal
B11: - | D11: - | F11: FIML | H11: - | I11: ONLY 1st Service | J11: SAS Premium Menu – Fish, N.B. only available in SAS GO | K11: Plus TSU with Business class Hot meal in YM Disposable casserole
B12: - | D12: - | F12: MEML | H12: - | I12: ONLY 1st Service | J12: SAS Premium Menu – Meat, N.B. only available in SAS GO | K12: Plus TSU with Business class Hot meal in YM Disposable casserole
B13: - | D13: - | F13: CKML | H13: - | I13: ONLY 1st Service | J13: SAS Premium Menu – Poultry, N.B. only available in SAS GO | K13: Plus TSU with Business class Hot meal in YM Disposable casserole
B14: - | D14: - | F14: GHML | H14: - | I14: 1st & 2nd Service | J14: SAS Premium Menu – Green, N.B. only available in SAS GO, Lacto ovo veg For 2nd service when ordering GHML - EVML should be provided (vegetarian lacto-ovo meal) | K14: Plus TSU with Business class Hot meal in YM Disposable casserole

Sheet Read First
B1: READ FIRST - Instructions
B3: To be able to fill in the quotation in this RFP overview it is of importance to understand SAS by reading and understanding the below information:
B4: Please study supporting documentation in suggested order in the RFP intro letter.
B5: SAS Gastronomic Guidelines. The document that describes the main frame work for SAS Gastronomical values and guidelines.
B6: How to fill out the cost sheets:
B7: Cycle 1 is only as a guiding reference as for the meals and shall not be calculated.
B8: For cycle 2 and 3, Please fill in your proposals of suggested meals, products and rawmaterials into SAS framework of concept of equipment per your optimizied sourcing, supply chain and production methods.
B9: Cycle 2 is set with a total cost with a cap per pax per class with an A350 configuration and load factor.
B10: Cycle 2 Max cost for Business Class for all services including contribution for a regular meal of 40 USD.
B11: Cycle 2 Max cost for SAS Plus for all services including contributionfor are for a regular meal of 22 USD.
B12: Cycle 2 Max cost for SAS Go all services including contribution for a regular meal of 15 USD.
B13: Cycle 3 is your proposed menu without any budget cap of max cost. The total cost per pax per class for all regular may be higher or lower and than cycle 2.
... B29: All other cells shall not be changed or altered.
B43: Brand/Origin/Quality grade | C43: This information is fundamental to understand in what extent the product choosen relate to SAS Gastronomic Guidelines
B44: Nominated SAS owned product | C44: Owned and supplied by SAS
B45: Selected SAS nominated product | C45: Purchased by caterer and supplied direct to the units by the nominated supplier. Invoiced to SAS by caterer as part of the meal cost.
B47: Abbreviations
B48: IC | C48: Long Haul, Intercontinental routes to/from the North America and Asia according SAS traffic program
B49: P | C49: Flight deck Crew meal, 2 flight deck crew meal per flight as present standard. Crew can chose to opt out crew meal.
B50: K | C50: Cabin Crew meal, 8 crew for A330 and 9 crew for A350 per flight as present standard. Crew can chose to opt out crew meal.
B51: C | C51: SAS Business class
B52: Y | C52: SAS class equivallent to premium economy class
B53: M | C53: SAS class equivallent to economy class
B54: C, C1-4 (C1, C2 etc) | C54: Cycle or menu. The naming of a certain menu running for a set period
B55: CB | C55: Cold Breakfast
B56: HB | C56: Hot Breakfast
B57: CM | C57: Cold Meal
B58: HM | C58: Hot Meal
B59: TSU | C59: Tray setup
... B68: Selling price | C68: Total dM and total dL summarized
B71: Evaluation
B72: Evaluation of the submission in this RFP document will be on total dM, total dL and how the gastromomic guidelines are adheard to and described in the column Brand/Origin/Quality grade
B73: If a generic product on a raw material is used describe it as generic and origin.
B75: Note
B76: Approximately 10% of crew meals are special meals.
B78: SAS Special meals and Pre order meal codes:
B96: MEML SAS Premium Menu – Meat, N.B. only available in SAS GO. SAS Plus 1st serving Tray setup with the Business class Hot meal Meat portioned the aluminium disposable casserole 973113 and lid 973114. Regular 2nd service
B97: CKML SAS Premium Menu – Poultry, N.B. only available in SAS GO. SAS Plus 1st serving Tray setup with the Business class Hot meal Chicken portioned the aluminium disposable casserole 973113 and lid 973114. Regular 2nd service
B98: GHML SAS Premium Menu – Green, N.B. only available in SAS GO, Lacto ovo veg. SAS Plus 1st serving Tray setup with the Business class Hot meal fish portioned the aluminium disposable casserole 973113 and lid 973114 and 2nd serivce EVML

Sheet CS C C1-3
A1: Caterer: TBD | B1: Station: ATL | C1: Concept: 01JUN24 | Version: 1 | Updated: 15DEC23 Currency USD
B2: CS C spec codes C1-3 | C2: BUSINESS CLASS
A3: Supplier, please fill in name of Company in the first row | B3: SAS IFX Spec Code | C3: SAS IFX Description | D3: Weight / Pc | E3: Unit of M | F3: Quality, brand, supplier, origin, comments | G3: Direct Material | H3: Direct Labor | I3: Selling Price ex contrubtion | J3: Class | K3: Loading Instructions N.B only information | L3: Note | M3: Cycle / Menu | N3: Dish Name
A4: Please fill in Supplier Name | B4: 4ATL-411050C2 | C4: IC C S1 CUTLERY C2 | G4: =SUM(G5:G13) -> 0 | H4: =SUM(H5:H13) -> 1.04 | I4: =SUM(G4:H4) -> 1.04 | J4: C | K4: Fix Qty 40 | M4: C2 | N4: Cutlery pack
C5: Napkin/Tablecloth, Poly/Cotton, Grey | D5: 1 | E5: Pc | G5: 0 | H5: 0.09 | L5: 972062
C6: Knife, Stainless, RS | D6: 3 | E6: Pc | G6: 0 | H6: 0.27 | L6: 971090
C7: Fork, Stainless, RS | D7: 3 | E7: Pc | G7: 0 | H7: 0.27 | L7: 971091
C8: Spoon, Stainless, Dessert/Soup, RS | D8: 1 | E8: Pc | G8: 0 | H8: 0.27 | L8: 971093
C9: Salt & Pepper, Twinpack | D9: 1 | E9: Pc | G9: 0 | H9: 0.09 | L9: 973034
C10: Toothpick, Individually Packed | D10: 1 | E10: Pc | G10: 0 | H10: 0.05 | L10: 973020
A15: =$A$4 -> Please fill in Supplier Name | B15: 4ATL-411050C3 | C15: IC C S1 CUTLERY C3 | G15: =SUM(G16:G24) -> 0 | H15: =SUM(H16:H24) -> 1.04 | I15: =SUM(G15:H15) -> 1.04 | J15: C | K15: Fix Qty 40 | M15: C3 | N15: Cutlery pack
C16: Napkin/Tablecloth, Poly/Cotton, Grey | D16: 1 | E16: Pc | G16: 0 | H16: 0.09 | L16: 972062
C17: Knife, Stainless, RS | D17: 3 | E17: Pc | G17: 0 | H17: 0.27 | L17: 971090
C18: Fork, Stainless, RS | D18: 3 | E18: Pc | G18: 0 | H18: 0.27 | L18: 971091
C19: Spoon, Stainless, Dessert/Soup, RS | D19: 1 | E19: Pc | G19: 0 | H19: 0.27 | L19: 971093
C20: Salt & Pepper, Twinpack | D20: 1 | E20: Pc | G20: 0 | H20: 0.09 | L20: 973034
C21: Toothpick, Individually Packed | D21: 1 | E21: Pc | G21: 0 | H21: 0.05 | L21: 973020
A26: =$A$4 -> Please fill in Supplier Name | B26: 2ATL-411011 | C26: IC C S1 SALAD C1 | G26: =SUM(G27:G29) -> 0 | H26: =SUM(H27:H29) -> 0 | I26: =SUM(G26:H26) -> 0 | J26: C | K26: Load Scale IC-27 | M26: C1 | N26: Starter salad
C27: Mixed salad leaves | D27: 15 | E27: gm | F27: Seasonal
A31: =$A$4 -> Please fill in Supplier Name | B31: 2ATL-411012 | C31: IC C S1 SALAD C2 | G31: =SUM(G32:G34) -> 0 | H31: =SUM(H32:H34) -> 0 | I31: =SUM(G31:H31) -> 0 | J31: C | K31: Load Scale IC-27 | M31: C2 | N31: Starter salad
C32: Mesclun Mixed Greens | D32: 15 | E32: gm
C33: Heirloom Cherry/Grape tomato | D33: 15 | E33: gm
C34: Cucumber Slices | D34: 2 | E34: each
A36: =$A$4 -> Please fill in Supplier Name | B36: 2ATL-411013 | C36: IC C S1 SALAD C3 | G36: =SUM(G37:G39) -> 0 | H36: =SUM(H37:H39) -> 0 | I36: =SUM(G36:H36) -> 0 | J36: C | K36: Load Scale IC-27 | M36: C3 | N36: Starter salad
C37: Baby Arugula | D37: 15 | E37: gm
C38: Aromatic Poached Bosc Pear | D38: 15 | E38: gm | F38: Premium Produced Product Locally Produced
C39: Goat Cheese | D39: 10 | E39: gm
A41: =$A$4 -> Please fill in Supplier Name | B41: 2ATL-411031 | C41: IC C S1 SA GARNISH C1 | G41: =SUM(G42:G44) -> 0 | H41: =SUM(H42:H44) -> 0 | I41: =SUM(G41:H41) -> 0 | J41: C | K41: Fix Qty 2 | M41: C1 | N41: Salad side garnish
C42: Shaved watermelon radish 1 mm | D42: 3 | E42: Gm
A46: =$A$4 -> Please fill in Supplier Name | B46: 2ATL-411032 | C46: IC C S1 SA GARNISH C2 | G46: =SUM(G47:G49) -> 0 | H46: =SUM(H47:H49) -> 0 | I46: =SUM(G46:H46) -> 0 | J46: C | K46: Fix Qty 2 | M46: C2 | N46: Salad garnish
C47: Toasted Sunflower Seeds | D47: 3 | E47: gm
A51: =$A$4 -> Please fill in Supplier Name | B51: 2ATL-411033 | C51: IC C S1 SA GARNISH C3 | G51: =SUM(G52:G54) -> 0 | H51: =SUM(H52:H54) -> 0 | I51: =SUM(G51:H51) -> 0 | J51: C | K51: Fix Qty 2 | M51: C3 | N51: Garnish
C52: Toasted Pepitas | D52: 3 | E52: gm
A56: =$A$4 -> Please fill in Supplier Name | B56: 2ATL-411050 | C56: IC C S1+S2 BUTTER C1 | G56: =SUM(G57:G59) -> 0 | H56: =SUM(H57:H59) -> 0 | I56: =SUM(G56:H56) -> 0 | J56: C | K56: 1 | M56: C1 | N56: Butter
C57: Butter puck salted | D57: 10 | E57: gm | F57: Organic valley
A61: =$A$4 -> Please fill in Supplier Name | B61: 2ATL-411050C2 | C61: IC C S1+S2 BUTTER C2 | G61: =SUM(G62:G64) -> 0 | H61: =SUM(H62:H64) -> 0 | I61: =SUM(G61:H61) -> 0 | J61: C | K61: 1 | M61: C2 | N61: Butter
C62: Banner Butter | D62: 1 | E62: each | F62: Locally Sourced Sustainable Butter 1/2 oz. UW
A66: =$A$4 -> Please fill in Supplier Name | B66: 2ATL-411050C3 | C66: IC C S1+S2 BUTTER C3 | G66: =SUM(G67:G69) -> 0 | H66: =SUM(H67:H69) -> 0 | I66: =SUM(G66:H66) -> 0 | J66: C | K66: 1 | M66: C3 | N66: Butter
C67: Banner Butter | D67: 1 | E67: each | F67: Locally Sourced Sustainable Butter 1/2 oz. UW
A71: =$A$4 -> Please fill in Supplier Name | B71: 2ATL-411061 | C71: IC C S1 ST-A MEAT C1 | G71: =SUM(G72:G80) -> 0 | H71: =SUM(H72:H80) -> 0 | I71: =SUM(G71:H71) -> 0 | J71: C | K71: 60% (U) | M71: C1 | N71: Butcher board
C72: Truffle saucisson sec | D72: 3 x 4 | E72: gm
C73: Pork pate de campagne with pistachio | D73: 20 | E73: gm
C74: Duck prosciutto | D74: 10 | E74: gm
C75: Upland cress | D75: 2 | E75: gm
C76: Cornichons | D76: 1 | E76: pc
C77: Cracked black Tellecherry pepper | D77: 1 | E77: gm
A82: =$A$4 -> Please fill in Supplier Name | B82: 2ATL-411062 | C82: IC C S1 ST-A MEAT C2 | G82: =SUM(G83:G91) -> 0 | H82: =SUM(H83:H91) -> 0 | I82: =SUM(G82:H82) -> 0 | J82: C | K82: 60% (U) | M82: C2
C83: Beef Pastrami | D83: 12 | E83: gm | F83: Heywoods Provisions (Local Vendor)
C84: Duck Rillet | D84: 10 | E84: gm | F84: Heywoods Provisions (Local Vendor)
C85: Soppressata | D85: 20 | E85: gm | F85: Heywoods Provisions (Local Vendor)
C86: Fig Jam | D86: 2 | E86: pc
C87: Mesculin Lettuce | D87: 10 | E87: gm
A93: =$A$4 -> Please fill in Supplier Name | B93: 2ATL-411063 | C93: IC C S1 ST-A MEAT C3 | G93: =SUM(G94:G102) -> 0 | H93: =SUM(H94:H102) -> 0 | I93: =SUM(G93:H93) -> 0 | J93: C | K93: 60% (U) | M93: C3
C94: Italian Salami Slice | D94: 3 pc x 5 | E94: gm | F94: Heywoods Provisions (Local Vendor)
C95: Pork Proscuitto | D95: 20 | E95: gm | F95: Heywoods Provisions (Local Vendor)
C96: Waygu Bressola | D96: 10 | E96: gm | F96: Heywoods Provisions (Local Vendor)
C97: Baby Arugula | D97: 5 | E97: gm
C98: Castelvetrano Olives | D98: 2 | E98: pc
A104: =$A$4 -> Please fill in Supplier Name | B104: 2ATL-411071 | C104: IC C S1 ST-B FISH C1 | G104: =SUM(G105:G113) -> 0 | H104: =SUM(H105:H113) -> 0 | I104: =SUM(G104:H104) -> 0 | J104: C | K104: 60% (D) | M104: C1 | N104: Cured salmon with baked beets and goat cheese
C105: Herb cured salmon (rosemary, thyme & chives) | D105: 2x20 | E105: gm
C106: Red beet roasted in wedges | D106: 2x10 | E106: gm
C107: Humbold fog goat cheese (in "knuckles") | D107: 3x4 | E107: gm
C108: chiaggia beets ( sliced/ cut) 1 mm | D108: 2x2 | E108: gm
C109: Yellow beets roasted in wedges | D109: 2x10 | E109: gm
C110: Baby spinach leaves as garnish | D110: 2x20 | E110: gm
A115: =$A$4 -> Please fill in Supplier Name | B115: 2ATL-411072 | C115: IC C S1 ST-B FISH C2 | G115: =SUM(G116:G124) -> 0 | H115: =SUM(H116:H124) -> 0 | I115: =SUM(G115:H115) -> 0 | J115: C | K115: 60% (D) | M115: C2
C116: Smoked Trout | D116: 40 | E116: gm | F116: INLAND SEAFOOD
C117: Horseradish Dill Aioli | D117: 20 | E117: gm
C118: Cucumber Apple Salad | D118: 20 | E118: gm
C119: Cornichons | D119: 20 | E119: gm
C120: Mesclun Mixed Greens | D120: 20 | E120: gm
C121: House Made Bagel Chips Everything in Indv Packet | D121: 20 | E121: gm
A126: =$A$4 -> Please fill in Supplier Name | B126: 2ATL-411073 | C126: IC C S1 ST-B FISH C3 | G126: =SUM(G127:G135) -> 0 | H126: =SUM(H127:H135) -> 0 | I126: =SUM(G126:H126) -> 0 | J126: C | K126: 60% (D) | M126: C3
C127: Smoked Salmon | D127: 40 | E127: gm | F127: Premium Quality
C128: Everything Cream Cheese | D128: 15 | E128: gm
C129: Chopped Hard Boiled Egg | D129: 30 | E129: gm
C130: Diced Red Onion | D130: 15 | E130: gm
C131: Capers | D131: 10 | E131: gm
C132: House Made Bagel Chips Everything in Indv Packet | D132: 20 | E132: gm
A137: =$A$4 -> Please fill in Supplier Name | B137: 2ATL-411081 | C137: IC C S1 ST GARNISH C1 | G137: =SUM(G138:G140) -> 0 | H137: =SUM(H138:H140) -> 0 | I137: =SUM(G137:H137) -> 0 | J137: C | K137: Fix Qty 2 | M137: C1 | N137: Starter side garnish for Cured salmon
C138: Argan oil (for IC C S1 ST-B FISH C1) | D138: 5 | E138: gm
A142: =$A$4 -> Please fill in Supplier Name | B142: 2ATL-411082 | C142: IC C S1 ST GARNISH C2 | G142: =SUM(G143:G145) -> 0 | H142: =SUM(H143:H145) -> 0 | I142: =SUM(G142:H142) -> 0 | J142: C | K142: Fix Qty 2 | M142: C2 | N142: Starter garnish to either A or B
C143: Chive batons | D143: 5 | E143: gm
A147: =$A$4 -> Please fill in Supplier Name | B147: 2ATL-411083 | C147: IC C S1 ST GARNISH C3 | G147: =SUM(G148:G150) -> 0 | H147: =SUM(H148:H150) -> 0 | I147: =SUM(G147:H147) -> 0 | J147: C | K147: Fix Qty 2 | M147: C3 | N147: Starter garnish to either A or B
C148: Dill Sprigs | D148: 5 | E148: gm
A152: =$A$4 -> Please fill in Supplier Name | B152: 2ATL-411091 | C152: IC C S1 HM-A MEAT C1 | G152: =SUM(G153:G161) -> 0 | H152: =SUM(H153:H161) -> 0 | I152: =SUM(G152:H152) -> 0 | J152: C | K152: 50% (U) | M152: C1 | N152: Truffle braised Kurobuta pork cheeks, celery root puree and grilled king oyster mushrooms
C153: Truffle braised kurobuta pork cheeks | D153: 90
C154: Braising liquid/sauce | D154: 40
C155: Celery root mashed | D155: 70
C156: Rapini ( sauteed) | D156: 40
C157: King oyster mushrooms ( grilled) | D157: 25
A163: =$A$4 -> Please fill in Supplier Name | B163: 2ATL-411092 | C163: IC C S1 HM-A MEAT C2 | G163: =SUM(G164:G172) -> 0 | H163: =SUM(H164:H172) -> 0 | I163: =SUM(G163:H163) -> 0 | J163: C | K163: 50% (U) | M163: C2
C164: Grilled Beef Tenderloin | D164: 90 | E164: gm
C165: Smoked Tomato Jam | D165: 30 | E165: gm | F165: Housemade
C166: Herb Roasted Fingeling Potatoes | D166: 90 | E166: gm
C167: Roasted Asparagus | D167: 60 | E167: gm
A174: =$A$4 -> Please fill in Supplier Name | B174: 2ATL-411093 | C174: IC C S1 HM-A MEAT C3 | G174: =SUM(G175:G183) -> 0 | H174: =SUM(H175:H183) -> 0 | I174: =SUM(G174:H174) -> 0 | J174: C | K174: 50% (U) | M174: C3
C175: Smoked Braised Short Rib | D175: 90 | E175: gm | F175: Fox Brothers , local
C176: BBQ jus | D176: 30 | E176: gm | F176: Fox Brothers , local
C177: Garlic Thyme Mash Potatoes | D177: 90 | E177: gm
...

Sheet CS Y C1-3
A1: Caterer: TBD | B1: | Station: ATL | C1: Concept: 01JUN24 | Version: 1 | Updated: 15DEC23 Currency USD
B2: CS Y spec codes C1-3 | C2: PLUS (PREMIUM ECO)
A3: Supplier, please fill in name of Company in the first row | B3: SAS IFX Spec Code | C3: SAS IFX Description | D3: Weight / Pc | E3: Unit of M | F3: Quality, brand, supplier, origin, comments | G3: Direct Material | H3: Direct Labor | I3: Selling Price ex contrubtion | J3: Class | K3: Loading Instructions N.B only information | L3: Note | M3: Cycle / Menu | N3: Dish Name
A4: ='CS C C1-3'!$A$4 -> Please fill in Supplier Name | B4: 3ATL-421010C2 | C4: IC Y S1 TSU C2 | G4: =SUM(G5:G18) -> 0 | H4: =SUM(H5:H18) -> 1.06 | I4: =SUM(G4:H4) -> 1.06 | J4: Y | K4: 1 | M4: C2 | N4: Tray setup
C5: Tray, Food, Large, ATLAS | D5: 1 | E5: Pc | G5: 0 | H5: 0.09 | L5: 971168
C6: Traymat, Large, Black, Disposable | D6: 1 | E6: Pc | G6: 0 | H6: 0.05 | L6: 973186
C7: Bag, For Cutlery | D7: 1 | E7: Pc | G7: 0 | H7: 0.05 | L7: 973012
C8: 1 x Fork, Stainless, RS | D8: 1 | E8: Pc | G8: 0 | H8: 0.09 | L8: 971091
C9: 1 x Spoon, Stainless, Coffee/Tea, RS | D9: 1 | E9: Pc | G9: 0 | H9: 0.09 | L9: 971092
C10: 1 x Spoon, Stainless, Dessert/Soup, RS | D10: 1 | E10: Pc | G10: 0 | H10: 0.09 | L10: 971093
C11: 1 x Knife, Stainless, RS | D11: 1 | E11: Pc | G11: 0 | H11: 0.09 | L11: 971090
C12: 1 x Napkin, Paper, White | D12: 1 | E12: Pc | G12: 0 | H12: 0.05 | L12: 973099
C13: 1 x Sugar, Portion Packed | D13: 1 | E13: Pc | G13: 0 | H13: 0.05 | L13: 973023
C14: 1 x Salt & Pepper, Twinpack | D14: 1 | E14: Pc | G14: 0 | H14: 0.09 | L14: 973034
C15: 1 x Toothpick, Individually Packed | D15: 1 | E15: Pc | G15: 0 | H15: 0.05
C16: Portioned packed butter 10-15 gm | D16: 1 | E16: Pc | H16: 0.09
C17: Portioned packed cracker | D17: 1 | E17: Pc | H17: 0.09
C18: Portioned packed cheese 15 g | D18: 1 | E18: Pc | H18: 0.09 | L18: 973020
A20: =$A$4 -> Please fill in Supplier Name | B20: 3ATL-421010C3 | C20: IC Y S1 TSU C3 | G20: =SUM(G21:G33) -> 0 | H20: =SUM(H21:H33) -> 1.01 | I20: =SUM(G20:H20) -> 1.01 | J20: Y | K20: 1 | M20: C3 | N20: Tray setup
C21: Tray, Food, Large, ATLAS | D21: 1 | E21: Pc | G21: 0 | H21: 0.09 | L21: 971168
C22: Traymat, Large, Black, Disposable | D22: 1 | E22: Pc | G22: 0 | H22: 0.05 | L22: 973186
C23: Bag, For Cutlery | D23: 1 | E23: Pc | G23: 0 | H23: 0.05 | L23: 973012
C24: 1 x Fork, Stainless, RS | D24: 1 | E24: Pc | G24: 0 | H24: 0.09 | L24: 971091
C25: 1 x Spoon, Stainless, Coffee/Tea, RS | D25: 1 | E25: Pc | G25: 0 | H25: 0.09 | L25: 971092
C26: 1 x Spoon, Stainless, Dessert/Soup, RS | D26: 1 | E26: Pc | G26: 0 | H26: 0.09 | L26: 971093
C27: 1 x Knife, Stainless, RS | D27: 1 | E27: Pc | G27: 0 | H27: 0.09 | L27: 971090
C28: 1 x Napkin, Paper, White | D28: 1 | E28: Pc | G28: 0 | H28: 0.05 | L28: 973099
C29: 1 x Sugar, Portion Packed | D29: 1 | E29: Pc | G29: 0 | H29: 0.05 | L29: 973023
C30: 1 x Salt & Pepper, Twinpack | D30: 1 | E30: Pc | G30: 0 | H30: 0.09 | L30: 973034
C31: Portioned packed butter 10-15 gm | D31: 1 | E31: Pc | H31: 0.09
C32: Portioned packed cracker | D32: 1 | E32: Pc | H32: 0.09
C33: Portioned packed cheese 15 g | D33: 1 | E33: Pc | H33: 0.09
A35: =$A$4 -> Please fill in Supplier Name | B35: 2ATL-421011 | C35: IC Y S1 ST C1 | G35: =SUM(G36:G44) -> 0 | H35: =SUM(H36:H44) -> 0 | I35: =SUM(G35:H35) -> 0 | J35: Y | K35: 1 | M35: C1 | N35: Local air dried ham with broccoli slaw and kale grain salad
C36: Local air dried ham x 2 slices | D36: 15 | E36: Gm
C37: Kale grain salad | D37: 20 | E37: Gm
C38: Broccoli slaw | D38: 35 | E38: Gm
A46: =$A$4 -> Please fill in Supplier Name | B46: 2ATL-421012 | C46: IC Y S1 ST C2 | G46: =SUM(G47:G55) -> 0 | H46: =SUM(H47:H55) -> 0 | I46: =SUM(G46:H46) -> 0 | J46: Y | K46: 1 | M46: C2
C47: Black Forest Ham Slice | D47: 2pc x 15 | E47: gm
C48: Farro Salad | D48: 30 | E48: gm
C49: Horseradish Slaw | D49: 30 | E49: gm
A57: =$A$4 -> Please fill in Supplier Name | B57: 2ATL-421013 | C57: IC Y S1 ST C3 | G57: =SUM(G58:G66) -> 0 | H57: =SUM(H58:H66) -> 0 | I57: =SUM(G57:H57) -> 0 | J57: Y | K57: 1 | M57: C3 | N57: Starter
C58: Smoked Turkey Slices | D58: 2pc x 15 | E58: gm
C59: Quinoa Lentil Salad | D59: 30 | E59: gm
C60: Shaved Fennel Slaw | D60: 30 | E60: gm
A68: =$A$4 -> Please fill in Supplier Name | B68: 2ATL-421021 | C68: IC Y S1 HM-A C1 | G68: =SUM(G69:G77) -> 0 | H68: =SUM(H69:H77) -> 0 | I68: =SUM(G68:H68) -> 0 | J68: Y | K68: 60% (D) | M68: C1 | N68: Hake fish with farro, white wine sauce and sauteed zucchini and cherry tomatoes
C69: Hake fish fillet | D69: 4 | E69: Oz
C70: White wine cream sauce | D70: 30 | E70: Ml
C71: Farro with fresh herbes | D71: 80 | E71: Gm
C72: Sauteed fresh zucchini & mixed tomatoes | D72: 60 | E72: Gm
A79: =$A$4 -> Please fill in Supplier Name | B79: 2ATL-421022 | C79: IC Y S1 HM-A C2 | G79: =SUM(G80:G88) -> 0 | H79: =SUM(H80:H88) -> 0 | I79: =SUM(G79:H79) -> 0 | J79: Y | K79: 60% (D) | M79: C2
C80: Cod Almondine | D80: 90 | E80: gm
C81: Tarragon Cream Sauce | D81: 30 | E81: gm
C82: Wild Rice Pilaf | D82: 90 | E82: gm
C83: Garlic Roasted Caulliflower | D83: 60 | E83: gm
C84: Roasted Cherry Tomato | D84: 1 | E84: pc
A90: =$A$4 -> Please fill in Supplier Name | B90: 2ATL-421023 | C90: IC Y S1 HM-A C3 | G90: =SUM(G91:G99) -> 0 | H90: =SUM(H91:H99) -> 0 | I90: =SUM(G90:H90) -> 0 | J90: Y | K90: 60% (D) | M90: C3
C91: Roasted Seabass | D91: 90 | E91: gm
C92: Boullabaise Sauce | D92: 30 | E92: gm
C93: Saffron Coucous | D93: 90 | E93: gm
C94: Roasted Summer Vegetables (eggplant, zuchini, yellow squash, red onion) | D94: 60 | E94: gm
A101: =$A$4 -> Please fill in Supplier Name | B101: 2ATL-421031 | C101: IC Y/M S1 HM-B C1 | G101: =SUM(G102:G110) -> 0 | H101: =SUM(H102:H110) -> 0 | I101: =SUM(G101:H101) -> 0 | J101: Y | K101: 40% (U) | L101: Also used for M. | M101: C1 | N101: Oven roasted chicken with mashed sweet potatoes and spring vegetables
C102: Oven roasted chicken ( half thigh/ half breast) Wellfare | D102: 100 | E102: Gm
C103: Chicken jus | D103: 30 | E103: Ml
C104: Mashed orange sweet potatoes | D104: 80 | E104: Gm
C105: Sauteed spring vegetables | D105: 40 | E105: Gm
C106: (green beans, peas, snow peas & mexican onions) | D106: 0
A112: =$A$4 -> Please fill in Supplier Name | B112: 2ATL-421032 | C112: IC Y/M S1 HM-B C2 | G112: =SUM(G113:G121) -> 0 | H112: =SUM(H113:H121) -> 0 | I112: =SUM(G112:H112) -> 0 | J112: Y | K112: 40% (U) | L112: Also used for M. | M112: C2
C113: Sous Vide Airline Chicken Breast | D113: 90 | E113: gm | F113: Bell and Evans Organic
C114: Wild Mushroom Sauce | D114: 30 | E114: gm
C115: Sauteed Spinach with Garlic | D115: 30 | E115: gm
C116: Parmesan Risotto | D116: 60 | E116: gm
C117: Roasted Baby Carrot half x2 | D117: 2x15 | E117: gm
A123: =$A$4 -> Please fill in Supplier Name | B123: 2ATL-421033 | C123: IC Y/M S1 HM-B C3 | G123: =SUM(G124:G132) -> 0 | H123: =SUM(H124:H132) -> 0 | I123: =SUM(G123:H123) -> 0 | J123: Y | K123: 40% (U) | L123: Also used for M. | M123: C3
C124: Roast Lemon Chicken Thigh | D124: 90 | E124: gm | F124: Bell and Evans Organic
C125: Piccata Sauce | D125: 30 | E125: gm
C126: Herb Roasted Fingerling Potatoes | D126: 60 | E126: gm
C127: Marinated Steamed Broccolini | D127: 30 | E127: gm
C128: Grilled Yellow Squash | D128: 30 | E128: gm
A134: =$A$4 -> Please fill in Supplier Name | B134: 2ATL-421040 | C134: IC Y S1 DE C1 | G134: =SUM(G135:G137) -> 0 | H134: =SUM(H135:H137) -> 0 | I134: =SUM(G134:H134) -> 0 | J134: Y | K134: 1 | M134: C1 | N134: Dark chocolate mousse w/salted caramel sauce & cockie crumbles
C135: Dark chocolate mousse | D135: 40 | E135: Gm
C136: Salty caramel sauce | D136: 20 | E136: Gm
C137: Cockie crumbles | D137: 10 | E137: Gm
A139: =$A$4 -> Please fill in Supplier Name | B139: 2ATL-421041 | C139: IC Y S1 DE C2 | G139: =SUM(G140:G142) -> 0 | H139: =SUM(H140:H142) -> 0 | I139: =SUM(G139:H139) -> 0 | J139: Y | K139: 1 | M139: C2
C140: Peach Cobbler Tart | D140: 60 | E140: gm | F140: In House Bakery
C141: Blackberry Pastry Cream | D141: 10 | E141: gm
A144: =$A$4 -> Please fill in Supplier Name | B144: 2ATL-421042 | C144: IC Y S1 DE C3 | G144: =SUM(G145:G147) -> 0 | H144: =SUM(H145:H147) -> 0 | I144: =SUM(G144:H144) -> 0 | J144: Y | K144: 1 | M144: C3 | N144: Dessert
C145: Lemon Blueberry Cheese Cake | D145: 60 | E145: gm | F145: In House Bakery
C146: Strawberry Quarter | D146: 2 | E146: ea
C147: blueberry | D147: 3 | E147: ea
A149: =$A$4 -> Please fill in Supplier Name | B149: 4ATL-421010 | C149: IC Y/M S1+S2 BRD Type 1 C1 | G149: =SUM(G150:G152) -> 0 | H149: =SUM(H150:H152) -> 0 | I149: =SUM(G149:H149) -> 0 | J149: Y | K149: 120% (N) | L149: Min qty 10. | M149: C1 | N149: Bread rolls
C150: Ciabatta roll | D150: 40 | E150: Gm
A154: =$A$4 -> Please fill in Supplier Name | B154: 4ATL-421010C2 | C154: IC Y/M S1+S2 BRD Type 1 C2 | G154: =SUM(G155:G157) -> 0 | H154: =SUM(H155:H157) -> 0 | I154: =SUM(G154:H154) -> 0 | J154: Y | K154: 120% (N) | L154: Min qty 10. | M154: C2 | N154: Bread rolls
C155: Herb Foccacia Roll | D155: 40 | E155: gm | F155: In House Bakery
A159: =$A$4 -> Please fill in Supplier Name | B159: 4ATL-421010C3 | C159: IC Y/M S1+S2 BRD Type 1 C3 | G159: =SUM(G160:G162) -> 0 | H159: =SUM(H160:H162) -> 0 | I159: =SUM(G159:H159) -> 0 | J159: Y | K159: 120% (N) | L159: Min qty 10. | M159: C3 | N159: Bread rolls
C160: Multi Grain Beer and Cheese Roll | D160: 40 | E160: gm | F160: In House Bakery
A164: =$A$4 -> Please fill in Supplier Name | B164: 3ATL-422010C2 | C164: IC Y S2 TSU C2 | G164: =SUM(G165:G174) -> 0 | H164: =SUM(H165:H174) -> 0 | I164: =SUM(G164:H164) -> 0 | J164: Y | K164: 1 | M164: C2 | N164: Tray setup
C165: Tray, Food, Medium, ATLAS | D165: 1 | E165: Pc | G165: 0
C166: 1 x Traymat, Medium, Black, Disposable | D166: 1 | E166: Pc | G166: 0
C167: 1 x Plate, Melamine | D167: 1 | E167: Pc | G167: 0
C168: 1 x Glass, Water/Champagne, RS | D168: 1 | E168: Pc | G168: 0
...

Sheet CS M C1-3
A1: Caterer: TBD | B1: Station: ATL | C1: Concept: 01JUN24 | Version: 1 | Updated: 15DEC23 Currency USD
B2: CS M spec codes C1-3 | C2: GO (ECONOMY)
A3: Supplier, please fill in name of Company in the first row | B3: SAS IFX Spec Code | C3: SAS IFX Description | D3: Weight / Pc | E3: Unit of M | F3: Quality, brand, supplier, origin, comments | G3: Direct Material | H3: Direct Labor | I3: Selling Price ex contrubtion | J3: Class | K3: Loading Instructions N.B only information | L3: Note | M3: Cycle / Menu | N3: Dish Name
A4: ='CS C C1-3'!$A$4 -> Please fill in Supplier Name | B4: 3ATL-431010C2 | C4: IC M S1 TSU C2 | G4: =SUM(G5:G14) -> 0 | H4: =SUM(H5:H14) -> 0.62 | I4: =SUM(G4:H4) -> 0.62 | J4: M | K4: 1 | M4: C1 | N4: Tray Setup
C5: Tray, Food, Medium, ATLAS | D5: 1 | E5: Pc | G5: 0 | H5: 0.09 | L5: 971167
C6: 1 x Traymat, Medium, Anti-Skid, Disposable | D6: 1 | E6: Pc | G6: 0 | H6: 0.05 | L6: 973172
C7: 1 x Cutlery, Type 4/1, Disp, Neutral | D7: 1 | E7: Pc | G7: 0 | H7: 0.05 | L7: 973605
C8: 1 x Insert, For Casserole, Disposable | D8: 1 | E8: Pc | G8: 0 | H8: 0.05 | L8: 973045
C9: 1 x Insert, X-Large, Disposable (for salad) | D9: 1 | E9: Pc | G9: 0 | H9: 0.05 | L9: 971205
C10: 1 x Lid, For 971205, Disposable | D10: 1 | E10: Pc | G10: 0 | H10: 0.05 | L10: 971206
C11: 1 x Insert, Small, Disposable (for dessert) | D11: 1 | E11: Pc | G11: 0 | H11: 0.05 | L11: 971207
C12: 1 x Lid , For 971207, Disposable, Small | D12: 1 | E12: Pc | G12: 0 | H12: 0.05
C13: Portioned packed butter 10-15 g | D13: 1 | E13: Pc | H13: 0.09 | L13: 971208
C14: Portioned packed milk jigger | D14: 1 | E14: Pc | H14: 0.09
A16: =$A$4 -> Please fill in Supplier Name | B16: 3ATL-431010C3 | C16: IC M S1 TSU C3 | G16: =SUM(G17:G26) -> 0 | H16: =SUM(H17:H26) -> 0.62 | I16: =SUM(G16:H16) -> 0.62 | J16: M | K16: 1 | M16: C1 | N16: Tray Setup
C17: Tray, Food, Medium, ATLAS | D17: 1 | E17: Pc | G17: 0 | H17: 0.09 | L17: 971167
C18: 1 x Traymat, Medium, Anti-Skid, Disposable | D18: 1 | E18: Pc | G18: 0 | H18: 0.05 | L18: 973172
C19: 1 x Cutlery, Type 4/1, Disp, Neutral | D19: 1 | E19: Pc | G19: 0 | H19: 0.05 | L19: 973605
C20: 1 x Insert, For Casserole, Disposable | D20: 1 | E20: Pc | G20: 0 | H20: 0.05 | L20: 973045
C21: 1 x Insert, X-Large, Disposable (for salad) | D21: 1 | E21: Pc | G21: 0 | H21: 0.05 | L21: 971205
C22: 1 x Lid, For 971205, Disposable | D22: 1 | E22: Pc | G22: 0 | H22: 0.05 | L22: 971206
C23: 1 x Insert, Small, Disposable (for dessert) | D23: 1 | E23: Pc | G23: 0 | H23: 0.05 | L23: 971207
C24: 1 x Lid , For 971207, Disposable, Small | D24: 1 | E24: Pc | G24: 0 | H24: 0.05 | L24: 971208
C25: Portioned packed butter 10-15 g | D25: 1 | E25: Pc | H25: 0.09
C26: Portioned packed milk jigger | D26: 1 | E26: Pc | H26: 0.09
A28: =$A$4 -> Please fill in Supplier Name | B28: 2ATL-431011 | C28: IC M S1 SALAD C1 | G28: =SUM(G29:G37) -> 0 | H28: =SUM(H29:H37) -> 0 | I28: =SUM(G28:H28) -> 0 | J28: M | K28: 1 | M28: C1 | N28: Mixed starter salad
C29: Mesclun mix | D29: 10 | E29: Gm
C30: Blue cheese crumbled | D30: 10 | E30: Gm
C31: Shredded carrots (julienned) | D31: 10 | E31: Gm
C32: Toasted pepitas | D32: 3 | E32: Gm
A39: =$A$4 -> Please fill in Supplier Name | B39: 2ATL-431012 | C39: IC M S1 SALAD C2 | G39: =SUM(G40:G48) -> 0 | H39: =SUM(H40:H48) -> 0 | I39: =SUM(G39:H39) -> 0 | J39: M | K39: 1 | M39: C2
C40: Mesclun Mixed Green Mix | D40: 10 | E40: gm
C41: English Cucumber Slice | D41: 15 | E41: Gm
C42: Shredded carrots (julienned) | D42: 10 | E42: gm
A50: =$A$4 -> Please fill in Supplier Name | B50: 2ATL-431013 | C50: IC M S1 SALAD C3 | G50: =SUM(G51:G59) -> 0 | H50: =SUM(H51:H59) -> 0 | I50: =SUM(G50:H50) -> 0 | J50: M | K50: 1 | M50: C3
C51: Baby Arugula | D51: 10 | E51: gm
C52: Strawberry quartered | D52: 15 | E52: gm
C53: Feta | D53: 10 | E53: gm
A61: =$A$4 -> Please fill in Supplier Name | B61: 2ATL-421031 | C61: IC Y/M S1 HM-B C1 | G61: =SUM(G62:G70) -> 0 | H61: =SUM(H62:H70) -> 0 | I61: =SUM(G61:H61) -> 0 | J61: M | K61: 1 | L61: Also used for Y. | M61: C1 | N61: Oven roasted chicken with mashed sweet potatoes
C62: Oven roasted chicken ( half thigh/ half breast) Wellfare | D62: 100 | E62: Gm
C63: Chicken jus | D63: 30 | E63: Ml
C64: Mashed orange sweet potatoes | D64: 80 | E64: Gm
C65: Sauteed spring vegetables | D65: 40 | E65: Gm
C66: (green beans, peas, snow peas & mexican onions)
A72: =$A$4 -> Please fill in Supplier Name | B72: 2ATL-421032 | C72: IC Y/M S1 HM-B C2 | G72: =SUM(G73:G81) -> 0 | H72: =SUM(H73:H81) -> 0 | I72: =SUM(G72:H72) -> 0 | J72: M | K72: 1 | L72: Also used for Y. | M72: C2
C73: Herb Roast Chicken | D73: 90 | E73: gm
C74: Lemon Buerre Blanc | D74: 30 | E74: gm
C75: Potato Caponata | D75: 90 | E75: gm
C76: Steamed Broccoli | D76: 30 | E76: gm
C77: Steamed Carrot | D77: 15 | E77: gm
A83: =$A$4 -> Please fill in Supplier Name | B83: 2ATL-421033 | C83: IC Y/M S1 HM-B C3 | G83: =SUM(G84:G92) -> 0 | H83: =SUM(H84:H92) -> 0 | I83: =SUM(G83:H83) -> 0 | J83: M | K83: 1 | L83: Also used for Y. | M83: C3
C84: BBQ Chicken Thigh | D84: 90 | E84: gm
C85: BBQ Sauce | D85: 30 | E85: gm
C86: Sauteed Green Beans | D86: 60 | E86: gm
C87: Garlic Thyme Mash Potatoes | D87: 90 | E87: gm
A94: =$A$4 -> Please fill in Supplier Name | B94: 2ATL-431020 | C94: IC M S1 DE C1 | G94: =SUM(G95:G97) -> 0 | H94: =SUM(H95:H97) -> 0 | I94: =SUM(G94:H94) -> 0 | J94: M | K94: 1 | M94: C1 | N94: Appe cheese cake with vanilla sauce
C95: Apple cheese cake | D95: 50 | E95: Gm
C96: Vanilla sauce | D96: 10 | E96: Gm
A99: =$A$4 -> Please fill in Supplier Name | B99: 2ATL-431021 | C99: IC M S1 DE C2 | G99: =SUM(G100:G102) -> 0 | H99: =SUM(H100:H102) -> 0 | I99: =SUM(G99:H99) -> 0 | J99: M | K99: 1 | M99: C2
C100: Chocoloate Mousse | D100: 60 | E100: gm
C101: White Chocolate Curls | D101: 15 | E101: gm
A104: =$A$4 -> Please fill in Supplier Name | B104: 2ATL-431022 | C104: IC M S1 DE C3 | G104: =SUM(G105:G107) -> 0 | H104: =SUM(H105:H107) -> 0 | I104: =SUM(G104:H104) -> 0 | J104: M | K104: 1 | M104: C3
C105: Passion Fruit Mousse | D105: 60 | E105: gm
C106: Blueberry Coulis | D106: 15 | E106: gm
A109: =$A$4 -> Please fill in Supplier Name | B109: 4ATL-421010 | C109: IC Y/M S1+S2 BRD Type 1 C1 | G109: =SUM(G110:G112) -> 0 | H109: =SUM(H110:H112) -> 0 | I109: =SUM(G109:H109) -> 0 | J109: Y | K109: 120% (N) | L109: Min qty 10. | M109: C1 | N109: Bread rolls
C110: Ciabatta roll | D110: 40 | E110: Gm
A114: =$A$4 -> Please fill in Supplier Name | B114: 4ATL-421010C2 | C114: IC Y/M S1+S2 BRD Type 1 C2 | G114: =SUM(G115:G117) -> 0 | H114: =SUM(H115:H117) -> 0 | I114: =SUM(G114:H114) -> 0 | J114: Y | K114: 120% (N) | L114: Min qty 10. | M114: C2 | N114: Bread rolls
C115: Honey Wheat Roll | D115: 40 | E115: gm
A119: =$A$4 -> Please fill in Supplier Name | B119: 4ATL-421010C3 | C119: IC Y/M S1+S2 BRD Type 1 C3 | G119: =SUM(G120:G122) -> 0 | H119: =SUM(H120:H122) -> 0 | I119: =SUM(G119:H119) -> 0 | J119: Y | K119: 120% (N) | L119: Min qty 10. | M119: C3 | N119: Bread rolls
C120: Wheat Potato Roll | D120: 40 | E120: gm
A124: =$A$4 -> Please fill in Supplier Name | B124: 4ATL-432010 | C124: IC M S2 JUICE C1 | G124: =SUM(G125:G127) -> 0 | H124: =SUM(H125:H127) -> 0 | I124: =SUM(G124:H124) -> 0 | J124: M | K124: 1 | M124: C1
C125: PP Orange juice cup | D125: 1 | E125: Pc
A129: =$A$4 -> Please fill in Supplier Name | B129: 4ATL-432010C2 | C129: IC M S2 JUICE C2 | G129: =SUM(G130:G132) -> 0 | H129: =SUM(H130:H132) -> 0 | I129: =SUM(G129:H129) -> 0 | J129: M | K129: 1 | M129: C2
C130: PP Apple Juice | D130: 1 | E130: pc
A134: =$A$4 -> Please fill in Supplier Name | B134: 4ATL-432010C3 | C134: IC M S2 JUICE C3 | G134: =SUM(G135:G137) -> 0 | H134: =SUM(H135:H137) -> 0 | I134: =SUM(G134:H134) -> 0 | J134: M | K134: 1 | M134: C3
C135: Cranberry Juice | D135: 1 | E135: pc
A139: =$A$4 -> Please fill in Supplier Name | B139: 2ATL-432020 | C139: IC M S2 SW | G139: =SUM(G140:G142) -> 0 | H139: =SUM(H140:H142) -> 0 | I139: =SUM(G139:H139) -> 0 | J139: M | K139: 1 | M139: C1
C140: Hot Breakfast Toast/ Eng. Muffin with Turkey & Cheese | D140: 1 | E140: Pc
A144: =$A$4 -> Please fill in Supplier Name | B144: 2ATL-432020C2 | C144: IC M S2 SW | G144: =SUM(G145:G147) -> 0 | H144: =SUM(H145:H147) -> 0 | I144: =SUM(G144:H144) -> 0 | J144: M | K144: 1 | M144: C2
C145: Challah Toast | D145: 2 | E145: pc
C146: Ham Slice | D146: 40 | E146: gm
C147: Swiss Cheese Slice | D147: 20 | E147: gm
A149: =$A$4 -> Please fill in Supplier Name | B149: 2ATL-432020C3 | C149: IC M S2 SW | G149: =SUM(G150:G152) -> 0 | H149: =SUM(H150:H152) -> 0 | I149: =SUM(G149:H149) -> 0 | J149: M | K149: 1 | M149: C3
C150: Buttermilk Bisuit | D150: 1 | E150: pc
C151: Turkey Sausage Patty | D151: 50 | E151: gm
C152: American Cheese Slice | D152: 15 | E152: gm
A154: =$A$4 -> Please fill in Supplier Name | B154: 3ATL-9310ME2 | C154: IC M S1 MEML C2 | G154: =SUM(G155:G163) -> 10 | H154: =SUM(H155:H163) -> 10 | I154: =SUM(G154:H154) -> 20 | J154: M | K154: 1 | M154: C3
C155: IC Y S1 TSU C2 | D155: 1 | E155: Pc | G155: 10 | H155: 10
C156: IC Y S1 ST C2 | D156: 1 | E156: Pc
C157: IC Y S1 DE C2 | D157: 1 | E157: Pc
C158: IC C S1 HM-A MEAT C2 | D158: 1 | E158: Pc
C159: IC Y S1 TSU C2 | D159: 1 | E159: Pc
A165: =$A$4 -> Please fill in Supplier Name | B165: 3ATL-9310ME3 | C165: IC M S1 MEML C3 | G165: =SUM(G166:G174) -> 10 | H165: =SUM(H166:H174) -> 10 | I165: =SUM(G165:H165) -> 20 | J165: M | K165: 1 | M165: C3 | N165: MEML SAS Premium Menu – Meat, N.B. only available in SAS GO. SAS Plus 1st serving Tray setup with the Business class Hot meal Meat portioned the aluminium disposable casserole 973113 and lid 973114. Regular 2nd service
C166: IC Y S1 TSU C3 | D166: 1 | E166: Pc | G166: 10 | H166: 10
C167: IC Y S1 ST C3 | D167: 1 | E167: Pc
C168: IC Y S1 DE C3 | D168: 1 | E168: Pc
C169: IC C S1 HM-A MEAT C3 | D169: 1 | E169: Pc
C170: IC Y S1 TSU C3 | D170: 1 | E170: Pc
A176: =$A$4 -> Please fill in Supplier Name | B176: 3ATL-9310CK2 | C176: IC M S1 CKML C2 | G176: =SUM(G177:G185) -> 0 | H176: =SUM(H177:H185) -> 0 | I176: =SUM(G176:H176) -> 0 | J176: M | K176: 1 | M176: C3
C177: IC Y S1 TSU C2 | D177: 1 | E177: Pc
...

Sheet CS P K C3
A1: Caterer: TBD | B1: Station: ATL | C1: Concept: 01JUN24 | Version: 1 | Updated: 15DEC23 Currency USD
B2: CS PKspec codes | C2: Crew Meals
A3: Supplier, please fill in name of Company in the first row | B3: SAS IFX Spec Code | C3: SAS IFX Description | D3: Weight / Pc | E3: Unit of M | F3: Quality, brand, supplier, origin, comments | G3: Direct Material | H3: Direct Labor | I3: Selling Price ex contrubtion | J3: Class | K3: Loading Instructions N.B only information | L3: Note
A4: ='CS C C1-3'!$A$4 -> Please fill in Supplier Name | B4: 3ATL-550003 | C4: CRW P CM TSU | G4: =SUM(G5:G13) -> 0 | H4: =SUM(H5:H13) -> 0 | I4: =SUM(G4:H4) -> 0 | J4: P | K4: 1
C5: SK Disposable cutlery | D5: 1 | E5: Pc | G5: 0
C6: Portion packed local butter | D6: 1 | E6: Pc
C7: Bread roll multigrain | D7: 1 | E7: Pc
A15: =$A$4 -> Please fill in Supplier Name | B15: 3ATL-560003 | C15: CRW K CM A | G15: =SUM(G16:G24) -> 0 | H15: =SUM(H16:H24) -> 0 | I15: =SUM(G15:H15) -> 0 | J15: K | K15: 0.5
C16: Roast beef x 2 slices | D16: 30 | E16: Gm
C17: Mayo (top and bottom) | D17: 10 | E17: Gm
C18: Red pepper stripes x 2 | D18: 20 | E18: Gm
C19: Ronman lettuce liner | D19: 3 | E19: Gm
C20: Ciabatta bread (50-60gr) | D20: 1 | E20: Pc
A26: =$A$4 -> Please fill in Supplier Name | B26: 3ATL-560004 | C26: CRW K CM B | G26: =SUM(G27:G35) -> 0 | H26: =SUM(H27:H35) -> 0 | I26: =SUM(G26:H26) -> 0 | J26: M | K26: 0.5
C27: Monterey jack cheese x 2 | D27: 20 | E27: Gm
C28: Cream cheese (top and bottom) | D28: 10 | E28: Gm
C29: Tomato spread | D29: 50 | E29: Gm
C30: Roman lettuce liner | D30: 3 | E30: Gm
C31: Wheat pullman bread slices | D31: 2 | E31: Pc
A37: =$A$4 -> Please fill in Supplier Name | B37: 2ATL-550025 | C37: CRW P CM - Poultry or Salmon A | G37: =SUM(G38:G46) -> 0 | H37: =SUM(H38:H46) -> 0 | I37: =SUM(G37:H37) -> 0 | J37: P | K37: 0.5
C38: Smoked salmon slices | D38: 40 | E38: Gm
C39: Blue cheese 3x10gm | D39: 30 | E39: Gm
C40: Mesclun mix | D40: 4 | E40: Gm
C41: Frisee salad | D41: 5 | E41: Gm
C42: Yellow cherry tomato | D42: 1 | E42: Pc
C43: Red cherry tomato | D43: 1 | E43: Pc
C44: Caper berry | D44: 1 | E44: Pc
A48: =$A$4 -> Please fill in Supplier Name | B48: 2ATL-550026 | C48: CRW P CM - Meat B | G48: =SUM(G49:G57) -> 0 | H48: =SUM(H49:H57) -> 0 | I48: =SUM(G48:H48) -> 0 | J48: P | K48: 1
C49: Air dried ham US | D49: 10 | E49: Gm
C50: Ham cured "81" | D50: 13 | E50: Gm
C51: Swiss cheese x 3 | D51: 30 | E51: Gm
C52: Mesclun mix | D52: 4 | E52: Gm
C53: Frisee salad | D53: 3 | E53: Gm
C54: cherry tomato | D54: 1 | E54: Pc
C55: Black olives | D55: 3 | E55: Pc
C56: Red grapes x 4 | D56: 30 | E56: Gm
A59: =$A$4 -> Please fill in Supplier Name | B59: 3ATL-550001 | C59: CRW P HM TSU | G59: =SUM(G60:G68) -> 0 | H59: =SUM(H60:H68) -> 0 | I59: =SUM(G59:H59) -> 0 | J59: P | K59: 1
C60: Vinaigrette dressing | D60: 1 | E60: Pc
C61: PP local butter | D61: 1 | E61: Pc
C62: Bread | D62: 1 | E62: Pc
C63: SK disposable cutlery | D63: 1 | E63: Pc
A70: =$A$4 -> Please fill in Supplier Name | B70: 3ATL-560001 | C70: CRW K HM TSU | G70: =SUM(G71:G79) -> 0 | H70: =SUM(H71:H79) -> 0 | I70: =SUM(G70:H70) -> 0 | J70: K | K70: 1
C71: Vinaigrette dressing | D71: 1 | E71: Pc
C72: PP local butter | D72: 1 | E72: Pc
C73: Bread | D73: 1 | E73: Pc
C74: SK disposable cutlery | D74: 1 | E74: Pc
A81: =$A$4 -> Please fill in Supplier Name | B81: 2ATL-550001 | C81: CRW P HM Salad | G81: =SUM(G82:G90) -> 0 | H81: =SUM(H82:H90) -> 0 | I81: =SUM(G81:H81) -> 0 | J81: P | K81: 1
C82: Chopped romaine lettuce | D82: 25 | E82: Gm
C83: Cucumber slices | D83: 15 | E83: Gm
C84: Carrot julienne | D84: 5 | E84: Gm
C85: Cherry tomato stemlesss | D85: 1 | E85: Pc
A92: =$A$4 -> Please fill in Supplier Name | B92: 2ATL-560001 | C92: CRW K HM Salad | G92: =SUM(G93:G101) -> 0 | H92: =SUM(H93:H101) -> 0 | I92: =SUM(G92:H92) -> 0 | J92: K | K92: 1
C93: Chopped romaine lettuce | D93: 25 | E93: Gm
C94: Cucumber slices | D94: 15 | E94: Gm
C95: Carrot julienne | D95: 5 | E95: Gm
C96: Cherry tomato stemlesss | D96: 1 | E96: Pc
A103: =$A$4 -> Please fill in Supplier Name | B103: 2ATL-550010 | C103: CRW P HM A | G103: =SUM(G104:G112) -> 0 | H103: =SUM(H104:H112) -> 0 | I103: =SUM(G103:H103) -> 0 | J103: P | K103: 1
C104: Sous Vide Airline Chicken Breast | D104: 90 | E104: gm | F104: Bell and Evans Organic | L104: Use the Chicken dish as in current Business hot meal option
C105: Wild Mushroom Sauce | D105: 30 | E105: gm
C106: Sauteed Spinach with Garlic | D106: 30 | E106: gm
C107: Parmesan Risotto | D107: 60 | E107: gm
C108: Roasted Baby Carrot half x2 | D108: 2x15 | E108: gm
A114: =$A$4 -> Please fill in Supplier Name | B114: 2ATL-560010 | C114: CRW K HM A | G114: =SUM(G115:G123) -> 0 | H114: =SUM(H115:H123) -> 0 | I114: =SUM(G114:H114) -> 0 | J114: K | K114: 0.5
C115: Roast Lemon Chicken Leg Quarter | D115: 1 | E115: pc | F115: Bell and Evans Organic | L115: Use the Chicken dish as in current Business hot meal option
C116: Piccata Sauce | D116: 30 | E116: gm
C117: Herb Roasted Fingerling Potatoes | D117: 60 | E117: gm
C118: Marinated Steamed Broccolini | D118: 30 | E118: gm
C119: Grilled Yellow Squash | D119: 30 | E119: gm
A125: =$A$4 -> Please fill in Supplier Name | B125: 2ATL-550011 | C125: CRW P HM B | G125: =SUM(G126:G134) -> 0 | H125: =SUM(H126:H134) -> 0 | I125: =SUM(G125:H125) -> 0 | J125: P | K125: 0.5
C126: Grilled Beef Tenderloin | D126: 90 | E126: gm | L126: Use the Meat dish as in current Business hot meal option
C127: Smoked Tomato Jam | D127: 30 | E127: gm | F127: Housemade
C128: Herb Roasted Fingeling Potatoes | D128: 90 | E128: gm
C129: Roasted Asparagus | D129: 60 | E129: gm
A136: =$A$4 -> Please fill in Supplier Name | B136: 2ATL-560011 | C136: CRW K HM B | G136: =SUM(G137:G145) -> 0 | H136: =SUM(H137:H145) -> 0 | I136: =SUM(G136:H136) -> 0 | J136: K | K136: 0.5
C137: Smoked Braised Short Rib | D137: 90 | E137: gm | F137: Fox Brothers , local | L137: Use the Meat dish as in current Business hot meal option
C138: BBQ jus | D138: 30 | E138: gm | F138: Fox Brothers , local
C139: Garlic Thyme Mash Potatoes | D139: 90 | E139: gm
C140: Sauteed Green Beans | D140: 60 | E140: gm
C141: Roasted Cherry Tomatoes | D141: 20 | E141: gm
A147: =$A$4 -> Please fill in Supplier Name | B147: 3ATL-550002 | C147: CRW P HB TSU | G147: =SUM(G148:G156) -> 0 | H147: =SUM(H148:H156) -> 0 | I147: =SUM(G147:H147) -> 0 | J147: P | K147: 0.5
C148: SK Disposable cutlery | D148: 1 | E148: Pc
C149: Portion packed local plain full fat yoghurt | D149: 1 | E149: Pc
C150: Portion packed local cheese | D150: 1 | E150: Pc
C151: Bread | D151: 2 | E151: Pc
C152: Portion packed local butter | D152: 1 | E152: Pc
A158: =$A$4 -> Please fill in Supplier Name | B158: 3ATL-560002 | C158: CRW K HB TSU | G158: =SUM(G159:G167) -> 0 | H158: =SUM(H159:H167) -> 0 | I158: =SUM(G158:H158) -> 0 | J158: M | K158: 1
C159: SK Disposable cutlery | D159: 1 | E159: Pc
C160: Portion packed local plain full fat yoghurt | D160: 1 | E160: Pc
C161: Portion packed local cheese | D161: 1 | E161: Pc
C162: Bread | D162: 2 | E162: Pc
C163: Portion packed local butter | D163: 1 | E163: Pc
A169: =$A$4 -> Please fill in Supplier Name | B169: 2ATL-550020 | C169: CRW P HB | G169: =SUM(G170:G178) -> 0 | H169: =SUM(H170:H178) -> 0 | I169: =SUM(G169:H169) -> 0 | J169: P | K169: 1
C170: Cheese chive omelet | D170: 100 | E170: Gm
C171: Sauteed mushrooms | D171: 15 | E171: Gm
C172: Roasted tomatoes | D172: 1 | E172: Pc
C173: Veal chipolata sausage | D173: 1 | E173: Pc
C174: Tri color potatoes | D174: 60 | E174: Gm
A180: =$A$4 -> Please fill in Supplier Name | B180: 2ATL-560020 | C180: CRW K HB | G180: =SUM(G181:G189) -> 0 | H180: =SUM(H181:H189) -> 0 | I180: =SUM(G180:H180) -> 0 | J180: K | K180: 1
C181: Cheese chive omelet | D181: 100 | E181: Gm
C182: Sauteed mushrooms | D182: 15 | E182: Gm
...

Sheet CS X
A1: Caterer: TBD | B1: Caterer: TBD | Station: ATL | C1: Concept: 01JUN24 | Version: 1 | Updated: 15DEC23 Currency USD
B2: CS X spec codes C1-3 | C2: HANDLING & STANDARD ITEMS
A3: Supplier, please fill in name of Company in the first row | B3: SAS IFX Spec Code | C3: SAS IFX Description | D3: Weight / Pc | E3: Unit of M | F3: Quality, supplier, origin, comments | G3: Direct Material | H3: Direct Labor | I3: Selling Price ex contrubtion | J3: Class | K3: Loading Instructions N.B only information | L3: Note
A4: ='CS C C1-3'!$A$4 -> Please fill in Supplier Name | B4: 3333-IC954 | C4: SK0930 | G4: 0 | H4: 0 | I4: =SUM(G4:H4) -> 0 | J4: X | K4: - | L4: Turnaround
A5: =$A$4 -> Please fill in Supplier Name | B5: 3333-IC954-T | C5: SK0930 | G5: 0 | H5: 0 | I5: =SUM(G5:H5) -> 0 | J5: X | K5: - | L5: Strip
A6: =$A$4 -> Please fill in Supplier Name | B6: 3333-IC954-OR | C6: SK0930 | G6: 0 | H6: 0 | I6: =SUM(G6:H6) -> 0 | J6: X | K6: - | L6: Load
A7: =$A$4 -> Please fill in Supplier Name | B7: 3334-IC954 | C7: SK0930 | G7: 0 | H7: 0 | I7: =SUM(G7:H7) -> 0 | J7: X | K7: - | L7: Turnaround
A8: =$A$4 -> Please fill in Supplier Name | B8: 3333-IC954-T | C8: SK0930 | G8: 0 | H8: 0 | I8: =SUM(G8:H8) -> 0 | J8: X | K8: - | L8: Strip
A9: =$A$4 -> Please fill in Supplier Name | B9: 3333-IC954-OR | C9: SK0930 | G9: 0 | H9: 0 | I9: =SUM(G9:H9) -> 0 | J9: X | K9: - | L9: Load
A10: =$A$4 -> Please fill in Supplier Name | B10: 3591-IC954 | C10: SK0930 | G10: 0 | H10: 0 | I10: =SUM(G10:H10) -> 0 | J10: X | K10: - | L10: Turnaround
A11: =$A$4 -> Please fill in Supplier Name | B11: 3591-IC954-T | C11: SK0930 | G11: 0 | H11: 0 | I11: =SUM(G11:H11) -> 0 | J11: X | K11: - | L11: Strip
A12: =$A$4 -> Please fill in Supplier Name | B12: 3591-IC954-OR | C12: SK0930 | G12: 0 | H12: 0 | I12: =SUM(G12:H12) -> 0 | J12: X | K12: - | L12: Load
A13: =$A$4 -> Please fill in Supplier Name | B13: 8ALL-WETICE | C13: Wet ice | I13: 0 | J13: X | K13: -
A14: =$A$4 -> Please fill in Supplier Name | B14: 8ALL-DRYICE | C14: Dry Ice | I14: 0 | J14: X | K14: -
A15: =$A$4 -> Please fill in Supplier Name | B15: 8ALL-GARBAGE3333 | C15: International Garbage Charge (3333) | I15: 0 | J15: X | K15: -
A16: =$A$4 -> Please fill in Supplier Name | B16: 8ALL-GARBAGE3334 | C16: International Garbage Charge (3334) | I16: 0 | J16: X | K16: -
A17: =$A$4 -> Please fill in Supplier Name | B17: 8ALL-GARBAGE3591 | C17: International Garbage Charge (3591) | I17: 0 | J17: X | K17: -
A18: =$A$4 -> Please fill in Supplier Name | B18: 8ALL-ACDELIVERY | C18: Aircraft Delivery Charge | I18: 0 | J18: X | K18: -
A19: =$A$4 -> Please fill in Supplier Name | B19: Water Still 1.5L | E19: Pc | I19: 0 | J19: X | K19: -
A20: =$A$4 -> Please fill in Supplier Name | B20: Water Still 0.5L/16oz | E20: Pc | I20: 0 | J20: X | K20: -
A21: =$A$4 -> Please fill in Supplier Name | B21: Water Sparkling 1.0L/32oz | E21: Pc | I21: 0 | J21: X | K21: -
A22: =$A$4 -> Please fill in Supplier Name | B22: Milk whole 0.25L/8oz | E22: Pc | I22: 0 | J22: X | K22: -
A23: =$A$4 -> Please fill in Supplier Name | B23: Creamer portion packed 0.25oz | E23: Pc | I23: 0 | J23: X | K23: -
A24: =$A$4 -> Please fill in Supplier Name | B24: Apple Juice 1L/32oz | E24: Pc | I24: 0 | J24: X | K24: -
A25: =$A$4 -> Please fill in Supplier Name | B25: Tomato Juice Aseptic 1L/32oz | E25: Pc | I25: 0 | J25: X | K25: -
A26: =$A$4 -> Please fill in Supplier Name | B26: Orange Juice Aseptic 1L/32oz | E26: Pc | I26: 0 | J26: X | K26: -
A27: =$A$4 -> Please fill in Supplier Name | B27: Celery Stick 6in x10 | E27: Pc | I27: 0 | J27: X | K27: -
A28: =$A$4 -> Please fill in Supplier Name | B28: Lime Wedges (1lime cut in 8 wedges) in plastic glass | E28: Pc | I28: 0 | J28: X | K28: -
A29: =$A$4 -> Please fill in Supplier Name | B29: Lemon Wedges (1 lemon cut in 8 wegdes) in plastic glass | E29: Pc | I29: 0 | J29: X | K29: -
A30: =$A$4 -> Please fill in Supplier Name | B30: Lemon Slice (1 lemon cut in 20 1/2 wheel slices) | E30: Pc | I30: 0 | J30: X | K30: -
... A36: =$A$4 -> Please fill in Supplier Name | B36: Soda Sprite 12oz Can (Crew request only) | E36: Pc | I36: 0 | J36: X | K36: -

Sheet CS M Alt
A1: Caterer: TBD | B1: Station: ATL | C1: Concept: 01JUN24 | Version: 1 | Updated: 15DEC23 Currency USD
B2: CS M spec codes C1-3 | C2: GO (ECONOMY) DISHWASH EQ & NOMINATED SK OWNED MEALS and Dessert
A3: Supplier, please fill in name of Company in the first row | B3: SAS IFX Spec Code | C3: SAS IFX Description | D3: Weight / Pc | E3: Unit of M | F3: Quality, brand, supplier, origin, comments | G3: Direct Material | H3: Direct Labor | I3: Selling Price ex contrubtion | J3: Class | K3: Loading Instructions N.B only information | L3: Note | M3: Cycle / Menu | N3: Dish Name
A4: ='CS C C1-3'!$A$4 -> Please fill in Supplier Name | B4: 2ATL-431020N | C4: IC M S1 DE C1 | G4: =SUM(G5:G6) -> 0 | H4: =SUM(H5:H6) -> 0 | I4: =SUM(G4:H4) -> 0 | J4: M | K4: 1 | M4: C1
C5: Frozen Dessert, SAS Nominated and SAS owned | G5: 0
C6: Defrost and trayset | G6: 0
A8: =$A$4 -> Please fill in Supplier Name | B8: 2ATL-432020N | C8: IC M S2 SW C1-4 | G8: =SUM(G9:G10) -> 0 | H8: =SUM(H9:H10) -> 0 | I8: =SUM(G8:H8) -> 0 | J8: M | K8: 1
C9: Frozen Sandwich, SAS Nominated and SAS owned | D9: 1 | E9: Pc | G9: 0 | N9: Breakfast sandwich
C10: Defrost and load | G10: 0
A12: =$A$4 -> Please fill in Supplier Name | B12: 2ATL-421031N | C12: IC Y/M S1 HM-B C1 | G12: =SUM(G13:G14) -> 0 | H12: =SUM(H13:H14) -> 0 | I12: =SUM(G12:H12) -> 0 | J12: M | K12: 1 | L12: Also used for Y. | M12: C1
C13: Frozen Hot Meal, SAS Nominated and SAS owned | D13: 1 | E13: Pc | G13: 0
C14: Defrost and load | G14: 0
A16: =$A$4 -> Please fill in Supplier Name | B16: 8ATL-OVERHEAD-NM | C16: IC M Overhead Nominated | J16: M | K16: 1

Sheet C Cost_Pax
A1: Caterer: TBD | B1: Station: ATL | C1: Concept: 01JUN24 | Version: 1 | Updated: 15DEC23 Currency USD
B2: CS C spec codes C1-3 | C2: BUSINESS CLASS
A3: Supplier, please fill in name of Company in the first row | B3: SAS IFX Spec Code | C3: SAS IFX Description | D3: Weight / Pc | E3: Unit of M | F3: Quality, brand, supplier, origin, comments | G3: Direct Material | H3: Direct Labor | I3: Selling Price ex contrubtion | J3: Class | K3: Loading Instructions N.B only information | N3: Note | O3: Cycle / Menu | P3: Dish Name
A4: ='CS C C1-3'!$A$4 -> Please fill in Supplier Name | B4: 4ATL-411050C2 | C4: IC C S1 CUTLERY C2 | G4: ='CS C C1-3'!G4 -> 0 | H4: ='CS C C1-3'!H4 -> 1.04 | I4: ='CS C C1-3'!I4 -> 1.04 | J4: C | K4: Fix Qty 40 | L4: 40 | M4: =I4*L4 -> 41.6 | O4: C2 | P4: Cutlery pack
C5: Napkin/Tablecloth, Poly/Cotton, Grey | D5: 1 | E5: Pc | G5: 0 | N5: 972062
C6: Knife, Stainless, RS | D6: 3 | E6: Pc | G6: 0 | N6: 971090
C7: Fork, Stainless, RS | D7: 3 | E7: Pc | G7: 0 | N7: 971091
C8: Spoon, Stainless, Dessert/Soup, RS | D8: 1 | E8: Pc | G8: 0 | N8: 971093
C9: Salt & Pepper, Twinpack | D9: 1 | E9: Pc | G9: 0 | N9: 973034
C10: Toothpick, Individually Packed | D10: 1 | E10: Pc | G10: 0 | N10: 973020
A15: =$A$4 -> Please fill in Supplier Name | B15: 4ATL-411050C3 | C15: IC C S1 CUTLERY C3 | G15: ='CS C C1-3'!G15 -> 0 | H15: ='CS C C1-3'!H15 -> 1.04 | I15: ='CS C C1-3'!I15 -> 1.04 | J15: C | K15: Fix Qty 40 | L15: 40 | M15: =I15*L15 -> 41.6 | O15: C3 | P15: Cutlery pack
C16: Napkin/Tablecloth, Poly/Cotton, Grey | D16: 1 | E16: Pc | G16: 0 | N16: 972062
C17: Knife, Stainless, RS | D17: 3 | E17: Pc | G17: 0 | N17: 971090
C18: Fork, Stainless, RS | D18: 3 | E18: Pc | G18: 0 | N18: 971091
C19: Spoon, Stainless, Dessert/Soup, RS | D19: 1 | E19: Pc | G19: 0 | N19: 971093
C20: Salt & Pepper, Twinpack | D20: 1 | E20: Pc | G20: 0 | N20: 973034
C21: Toothpick, Individually Packed | D21: 1 | E21: Pc | G21: 0 | N21: 973020
A26: =$A$4 -> Please fill in Supplier Name | B26: 2ATL-411011 | C26: IC C S1 SALAD C1 | G26: =SUM(G27:G29) -> 0 | H26: =SUM(H27:H29) -> 0 | I26: =SUM(G26:H26) -> 0 | J26: C | K26: Load Scale IC-27 | L26: 4 | M26: =I26*L26 -> 0 | O26: C1 | P26: Starter salad
C27: Mixed salad leaves | D27: 15 | E27: gm | F27: Seasonal
A31: =$A$4 -> Please fill in Supplier Name | B31: 2ATL-411012 | C31: IC C S1 SALAD C2 | G31: ='CS C C1-3'!G31 -> 0 | H31: ='CS C C1-3'!H31 -> 0 | I31: ='CS C C1-3'!I31 -> 0 | J31: C | K31: Load Scale IC-27 | L31: 4 | M31: =I31*L31 -> 0 | O31: C2 | P31: Starter salad
A36: =$A$4 -> Please fill in Supplier Name | B36: 2ATL-411013 | C36: IC C S1 SALAD C3 | G36: ='CS C C1-3'!G36 -> 0 | H36: ='CS C C1-3'!H36 -> 0 | I36: ='CS C C1-3'!I36 -> 0 | J36: C | K36: Load Scale IC-27 | L36: 4 | M36: =I36*L36 -> 0 | O36: C3 | P36: Starter salad
A41: =$A$4 -> Please fill in Supplier Name | B41: 2ATL-411031 | C41: IC C S1 SA GARNISH C1 | G41: =SUM(G42:G44) -> 0 | H41: =SUM(H42:H44) -> 0 | I41: =SUM(G41:H41) -> 0 | J41: C | K41: Fix Qty 2 | L41: 2 | M41: =I41*L41 -> 0 | O41: C1 | P41: Salad side garnish
C42: Shaved watermelon radish 1 mm | D42: 3 | E42: Gm
A46: =$A$4 -> Please fill in Supplier Name | B46: 2ATL-411032 | C46: IC C S1 SA GARNISH C2 | G46: ='CS C C1-3'!G46 -> 0 | H46: ='CS C C1-3'!H46 -> 0 | I46: ='CS C C1-3'!I46 -> 0 | J46: C | K46: Fix Qty 2 | L46: 2 | M46: =I46*L46 -> 0 | O46: C2 | P46: Salad garnish
A51: =$A$4 -> Please fill in Supplier Name | B51: 2ATL-411033 | C51: IC C S1 SA GARNISH C3 | G51: ='CS C C1-3'!G51 -> 0 | H51: ='CS C C1-3'!H51 -> 0 | I51: ='CS C C1-3'!I51 -> 0 | J51: C | K51: Fix Qty 2 | L51: 2 | M51: =I51*L51 -> 0 | O51: C3 | P51: Garnish
A56: =$A$4 -> Please fill in Supplier Name | B56: 2ATL-411050 | C56: IC C S1+S2 BUTTER C1 | G56: =SUM(G57:G59) -> 0 | H56: =SUM(H57:H59) -> 0 | I56: =SUM(G56:H56) -> 0 | J56: C | K56: 1 | L56: 1 | M56: =I56*L56 -> 0 | O56: C1 | P56: Butter
C57: Butter puck salted | D57: 10 | E57: gm | F57: Organic valley
A61: =$A$4 -> Please fill in Supplier Name | B61: 2ATL-411050C2 | C61: IC C S1+S2 BUTTER C2 | G61: ='CS C C1-3'!G61 -> 0 | H61: ='CS C C1-3'!H61 -> 0 | I61: ='CS C C1-3'!I61 -> 0 | J61: C | K61: 1 | L61: 1 | M61: =I61*L61*$K$576 -> 0 | O61: C2 | P61: Butter
A66: =$A$4 -> Please fill in Supplier Name | B66: 2ATL-411050C3 | C66: IC C S1+S2 BUTTER C3 | G66: ='CS C C1-3'!G66 -> 0 | H66: ='CS C C1-3'!H66 -> 0 | I66: ='CS C C1-3'!I66 -> 0 | J66: C | K66: 1 | L66: 1 | M66: =I66*L66*$K$576 -> 0 | O66: C3 | P66: Butter
A71: =$A$4 -> Please fill in Supplier Name | B71: 2ATL-411061 | C71: IC C S1 ST-A MEAT C1 | G71: =SUM(G72:G80) -> 0 | H71: =SUM(H72:H80) -> 0 | I71: =SUM(G71:H71) -> 0 | J71: C | K71: 60% (U) | L71: 0.6 | M71: =I71*L71*$K$576 -> 0 | O71: C1 | P71: Butcher board
C72: Truffle saucisson sec | D72: 3 x 4 | E72: gm
C73: Pork pate de campagne with pistachio | D73: 20 | E73: gm
C74: Duck prosciutto | D74: 10 | E74: gm
C75: Upland cress | D75: 2 | E75: gm
C76: Cornichons | D76: 1 | E76: pc
C77: Cracked black Tellecherry pepper | D77: 1 | E77: gm
A82: =$A$4 -> Please fill in Supplier Name | B82: 2ATL-411062 | C82: IC C S1 ST-A MEAT C2 | G82: ='CS C C1-3'!G82 -> 0 | H82: ='CS C C1-3'!H82 -> 0 | I82: ='CS C C1-3'!I82 -> 0 | J82: C | K82: 60% (U) | L82: 0.6 | M82: =I82*L82*$K$576 -> 0 | O82: C2
A93: =$A$4 -> Please fill in Supplier Name | B93: 2ATL-411063 | C93: IC C S1 ST-A MEAT C3 | G93: ='CS C C1-3'!G93 -> 0 | H93: ='CS C C1-3'!H93 -> 0 | I93: ='CS C C1-3'!I93 -> 0 | J93: C | K93: 60% (U) | L93: 0.6 | M93: =I93*L93*$K$576 -> 0 | O93: C3
A104: =$A$4 -> Please fill in Supplier Name | B104: 2ATL-411071 | C104: IC C S1 ST-B FISH C1 | G104: =SUM(G105:G113) -> 0 | H104: =SUM(H105:H113) -> 0 | I104: =SUM(G104:H104) -> 0 | J104: C | K104: 60% (D) | L104: 0.6 | M104: =I104*L104*$K$576 -> 0 | O104: C1 | P104: Cured salmon with baked beets and goat cheese
C105: Herb cured salmon (rosemary, thyme & chives) | D105: 2x20 | E105: gm
C106: Red beet roasted in wedges | D106: 2x10 | E106: gm
C107: Humbold fog goat cheese (in "knuckles") | D107: 3x4 | E107: gm
C108: chiaggia beets ( sliced/ cut) 1 mm | D108: 2x2 | E108: gm
C109: Yellow beets roasted in wedges | D109: 2x10 | E109: gm
C110: Baby spinach leaves as garnish | D110: 2x20 | E110: gm
A115: =$A$4 -> Please fill in Supplier Name | B115: 2ATL-411072 | C115: IC C S1 ST-B FISH C2 | G115: ='CS C C1-3'!G115 -> 0 | H115: ='CS C C1-3'!H115 -> 0 | I115: ='CS C C1-3'!I115 -> 0 | J115: C | K115: 60% (D) | L115: 0.6 | M115: =I115*L115*$K$576 -> 0 | O115: C2
A126: =$A$4 -> Please fill in Supplier Name | B126: 2ATL-411073 | C126: IC C S1 ST-B FISH C3 | G126: ='CS C C1-3'!G126 -> 0 | H126: ='CS C C1-3'!H126 -> 0 | I126: ='CS C C1-3'!I126 -> 0 | J126: C | K126: 60% (D) | L126: 0.6 | M126: =I126*L126*$K$576 -> 0 | O126: C3
A137: =$A$4 -> Please fill in Supplier Name | B137: 2ATL-411081 | C137: IC C S1 ST GARNISH C1 | G137: =SUM(G138:G140) -> 0 | H137: =SUM(H138:H140) -> 0 | I137: =SUM(G137:H137) -> 0 | J137: C | K137: Fix Qty 2 | L137: 2 | M137: =I137*L137 -> 0 | O137: C1 | P137: Starter side garnish for Cured salmon
C138: Argan oil (for IC C S1 ST-B FISH C1) | D138: 5 | E138: gm
A142: =$A$4 -> Please fill in Supplier Name | B142: 2ATL-411082 | C142: IC C S1 ST GARNISH C2 | G142: ='CS C C1-3'!G142 -> 0 | H142: ='CS C C1-3'!H142 -> 0 | I142: ='CS C C1-3'!I142 -> 0 | J142: C | K142: Fix Qty 2 | L142: 2 | M142: =I142*L142 -> 0 | O142: C2 | P142: Starter garnish to either A or B
A147: =$A$4 -> Please fill in Supplier Name | B147: 2ATL-411083 | C147: IC C S1 ST GARNISH C3 | G147: ='CS C C1-3'!G147 -> 0 | H147: ='CS C C1-3'!H147 -> 0 | I147: ='CS C C1-3'!I147 -> 0 | J147: C | K147: Fix Qty 2 | L147: 2 | M147: =I147*L147 -> 0 | O147: C3 | P147: Starter garnish to either A or B
A152: =$A$4 -> Please fill in Supplier Name | B152: 2ATL-411091 | C152: IC C S1 HM-A MEAT C1 | G152: =SUM(G153:G161) -> 0 | H152: =SUM(H153:H161) -> 0 | I152: =SUM(G152:H152) -> 0 | J152: C | K152: 50% (U) | L152: 0.5 | M152: =I152*L152*$K$576 -> 0 | O152: C1 | P152: Truffle braised Kurobuta pork cheeks, celery root puree and grilled king oyster mushrooms
C153: Truffle braised kurobuta pork cheeks | D153: 90
C154: Braising liquid/sauce | D154: 40
C155: Celery root mashed | D155: 70
C156: Rapini ( sauteed) | D156: 40
C157: King oyster mushrooms ( grilled) | D157: 25
A163: =$A$4 -> Please fill in Supplier Name | B163: 2ATL-411092 | C163: IC C S1 HM-A MEAT C2 | G163: ='CS C C1-3'!G163 -> 0 | H163: ='CS C C1-3'!H163 -> 0 | I163: ='CS C C1-3'!I163 -> 0 | J163: C | K163: 50% (U) | L163: 0.5 | M163: =I163*L163*$K$576 -> 0 | O163: C2
A174: =$A$4 -> Please fill in Supplier Name | B174: 2ATL-411093 | C174: IC C S1 HM-A MEAT C3 | G174: ='CS C C1-3'!G174 -> 0 | H174: ='CS C C1-3'!H174 -> 0 | I174: ='CS C C1-3'!I174 -> 0 | J174: C | K174: 50% (U) | L174: 0.5 | M174: =I174*L174*$K$576 -> 0 | O174: C3
A185: =$A$4 -> Please fill in Supplier Name | B185: 2ATL-411111 | C185: IC C S1 HM-C POULTRY C1 | G185: =SUM(G186:G194) -> 0 | H185: =SUM(H186:H194) -> 0 | I185: =SUM(G185:H185) -> 0 | J185: C | K185: 50% (D) | L185: 0.5 | M185: =I185*L185*$K$576 -> 0 | O185: C1 | P185: Duck leg confit with spring vegetable cassoulet
C186: Duck leg confit | D186: 1 | E186: Pc
C187: White beans cassoulet | D187: 60 | E187: Gm
C188: Spring vegetables (baby turnips, fava beans - | D188: 60 | E188: Gm
C189: - baby carrots and baby leeks)
C190: Cassoulet juice | D190: 30 | E190: Gm
A196: =$A$4 -> Please fill in Supplier Name | B196: 2ATL-411112 | C196: IC C S1 HM-C POULTRY C2 | G196: ='CS C C1-3'!G196 -> 0 | H196: ='CS C C1-3'!H196 -> 0 | I196: ='CS C C1-3'!I196 -> 0 | J196: C | K196: 50% (D) | L196: 0.5 | M196: =I196*L196*$K$576 -> 0 | O196: C2
A207: =$A$4 -> Please fill in Supplier Name | B207: 2ATL-411113 | C207: IC C S1 HM-C POULTRY C3 | G207: ='CS C C1-3'!G207 -> 0 | H207: ='CS C C1-3'!H207 -> 0 | I207: ='CS C C1-3'!I207 -> 0 | J207: C | K207: 50% (D) | L207: 0.5 | M207: =I207*L207*$K$576 -> 0 | O207: C3
A218: =$A$4 -> Please fill in Supplier Name | B218: 2ATL-411121 | C218: IC C S1 HM-D VEG C1 | G218: =SUM(G219:G227) -> 0 | H218: =SUM(H219:H227) -> 0 | I218: =SUM(G218:H218) -> 0 | J218: C | K218: 20% (U) | L218: 0.2 | M218: =I218*L218*$K$576 -> 0 | O218: C1 | P218: Cauliflower "steak" with pumpkin coulis and picalilli pickles
C219: Cauliflower steak (whole slice) | D219: 100 | E219: Gm
C220: Pumpkin coulis | D220: 50 | E220: Ml
C221: Piccalilli pickles | D221: 30 | E221: Gm
A229: =$A$4 -> Please fill in Supplier Name | B229: 2ATL-411122 | C229: IC C S1 HM-D VEG C2 | G229: ='CS C C1-3'!G229 -> 0 | H229: ='CS C C1-3'!H229 -> 0 | I229: ='CS C C1-3'!I229 -> 0 | J229: C | K229: 20% (U) | L229: 0.2 | M229: =I229*L229*$K$576 -> 0 | O229: C2
A240: =$A$4 -> Please fill in Supplier Name | B240: 2ATL-411123 | C240: IC C S1 HM-D VEG C3 | G240: ='CS C C1-3'!G240 -> 0 | H240: ='CS C C1-3'!H240 -> 0 | I240: ='CS C C1-3'!I240 -> 0 | J240: C | K240: 20% (U) | L240: 0.2 | M240: =I240*L240*$K$576 -> 0 | O240: C3
A251: =$A$4 -> Please fill in Supplier Name | B251: 2ATL-411131 | C251: IC C S1 HM GARNISH C1 | G251: =SUM(G252:G254) -> 0 | H251: =SUM(H252:H254) -> 0 | I251: =SUM(G251:H251) -> 0 | J251: C | K251: Fix Qty 2 | L251: 2 | M251: =I251*L251 -> 0 | O251: C1 | P251: Hot meal side garnish for Cauliflower steak
C252: Hemp seed granola | D252: 15 | E252: Gm
A256: =$A$4 -> Please fill in Supplier Name | B256: 2ATL-411132 | C256: IC C S1 HM GARNISH C2 | G256: ='CS C C1-3'!G256 -> 0 | H256: ='CS C C1-3'!H256 -> 0 | I256: ='CS C C1-3'!I256 -> 0 | J256: C | K256: Fix Qty 2 | L256: 2 | M256: =I256*L256 -> 0 | O256: C2 | P256: Garnish
A261: =$A$4 -> Please fill in Supplier Name | B261: 2ATL-411133 | C261: IC C S1 HM GARNISH C3 | G261: ='CS C C1-3'!G261 -> 0 | H261: ='CS C C1-3'!H261 -> 0 | I261: ='CS C C1-3'!I261 -> 0 | J261: C | K261: Fix Qty 2 | L261: 2 | M261: =I261*L261 -> 0 | O261: C3
A266: =$A$4 -> Please fill in Supplier Name | B266: 2ATL-411141 | C266: IC C S1 DE CHEESE C1 | G266: =SUM(G267:G269) -> 0 | H266: =SUM(H267:H269) -> 0 | I266: =SUM(G266:H266) -> 0 | J266: C | K266: Load Scale IC-27 | L266: 4 | M266: =I266*L266 -> 0 | O266: C1 | P266: Cheese assortment
C267: Humbolt Fog | D267: 20 | E267: Gm
C268: Comte (locally produced) | D268: 20 | E268: Gm
A271: =$A$4 -> Please fill in Supplier Name | B271: 2ATL-411142 | C271: IC C S1 DE CHEESE C2 | G271: ='CS C C1-3'!G271 -> 0 | H271: ='CS C C1-3'!H271 -> 0 | I271: ='CS C C1-3'!I271 -> 0 | J271: C | K271: Load Scale IC-27 | L271: 4 | M271: =I271*L271 -> 0 | O271: C2 | P271: Assorted cheese
P272: Assorted cheese
A276: =$A$4 -> Please fill in Supplier Name | B276: 2ATL-411143 | C276: IC C S1 DE CHEESE C3 | G276: ='CS C C1-3'!G276 -> 0 | H276: ='CS C C1-3'!H276 -> 0 | I276: ='CS C C1-3'!I276 -> 0 | J276: C | K276: Load Scale IC-27 | L276: 4 | M276: =I276*L276 -> 0 | O276: C3
A281: =$A$4 -> Please fill in Supplier Name | B281: 2ATL-411151 | C281: IC C S1 DE CAKE C1 | G281: =SUM(G282:G284) -> 0 | H281: =SUM(H282:H284) -> 0 | I281: =SUM(G281:H281) -> 0 | J281: C | K281: Load Scale IC-29 | L281: 3 | M281: =I281*L281 -> 0 | O281: C1 | P281: Cherry Clafoutis
C282: Cheery Clafoutis (baked in oven dish #971089) | D282: 40 | E282: Gm
A286: =$A$4 -> Please fill in Supplier Name | B286: 2ATL-411152 | C286: IC C S1 DE CAKE C2 | G286: ='CS C C1-3'!G286 -> 0 | H286: ='CS C C1-3'!H286 -> 0 | I286: ='CS C C1-3'!I286 -> 0 | J286: C | K286: Load Scale IC-29 | L286: 3 | M286: =I286*L286 -> 0 | O286: C2
A291: =$A$4 -> Please fill in Supplier Name | B291: 2ATL-411153 | C291: IC C S1 DE CAKE C3 | G291: ='CS C C1-3'!G291 -> 0 | H291: ='CS C C1-3'!H291 -> 0 | I291: ='CS C C1-3'!I291 -> 0 | J291: C | K291: Load Scale IC-29 | L291: 3 | M291: =I291*L291 -> 0 | O291: C3
A296: =$A$4 -> Please fill in Supplier Name | B296: 2ATL-411161 | C296: IC C S1 DE CAKE GARNISH C1 | G296: =SUM(G297:G299) -> 0 | H296: =SUM(H297:H299) -> 0 | I296: =SUM(G296:H296) -> 0 | J296: C | K296: Fix Qty 2 | L296: 2 | M296: =I296*L296 -> 0 | O296: C1 | P296: Dessert side garnish for Cherry Clafoutis
C297: Vanilla bean sauce | D297: 25 | E297: Gm
A301: =$A$4 -> Please fill in Supplier Name | B301: 2ATL-411162 | C301: IC C S1 DE CAKE GARNISH C2 | G301: ='CS C C1-3'!G301 -> 0 | H301: ='CS C C1-3'!H301 -> 0 | I301: ='CS C C1-3'!I301 -> 0 | J301: C | K301: Fix Qty 2 | L301: 2 | M301: =I301*L301 -> 0 | O301: C2
A306: =$A$4 -> Please fill in Supplier Name | B306: 2ATL-411163 | C306: IC C S1 DE CAKE GARNISH C3 | G306: ='CS C C1-3'!G306 -> 0 | H306: ='CS C C1-3'!H306 -> 0 | I306: ='CS C C1-3'!I306 -> 0 | J306: C | K306: Fix Qty 2 | L306: 2 | M306: =I306*L306 -> 0 | O306: C3
A311: =$A$4 -> Please fill in Supplier Name | B311: 2ATL-411180 | C311: IC C S1 DE FRUIT C1 | G311: =SUM(G312:G320) -> 0 | H311: =SUM(H312:H320) -> 0 | I311: =SUM(G311:H311) -> 0 | J311: C | K311: Load Scale IC-29 | L311: 3 | M311: =I311*L311 -> 0 | O311: C1 | P311: Fresh cut seasonal fruit
C312: Cantaloupe (0,75 inch cubes) | D312: 150 | E312: Gm
C313: Watermelon(0,75 inch cubes) | D313: 150 | E313: Gm
C314: Pineapple (0,75 inch cubes) | D314: 150 | E314: Gm
C315: Honeydew (0,75 inch cubes) | D315: 150 | E315: Gm
A322: =$A$4 -> Please fill in Supplier Name | B322: 2ATL-411180C2 | C322: IC C S1 DE FRUIT C2 | G322: ='CS C C1-3'!G322 -> 0 | H322: ='CS C C1-3'!H322 -> 0 | I322: ='CS C C1-3'!I322 -> 0 | J322: C | K322: Load Scale IC-29 | L322: 3 | M322: =I322*L322 -> 0 | O322: C2 | P322: Fresh cut seasonal fruit
A333: =$A$4 -> Please fill in Supplier Name | B333: 2ATL-411180C3 | C333: IC C S1 DE FRUIT C3 | G333: ='CS C C1-3'!G333 -> 0 | H333: ='CS C C1-3'!H333 -> 0 | I333: ='CS C C1-3'!I333 -> 0 | J333: C | K333: Load Scale IC-29 | L333: 3 | M333: =I333*L333 -> 0 | O333: C3 | P333: Fresh cut seasonal fruit
A344: =$A$4 -> Please fill in Supplier Name | B344: 4ATL-411010 | C344: IC C S1 BRD Type 1 C1 | G344: =SUM(G345:G347) -> 0 | H344: =SUM(H345:H347) -> 0 | I344: =SUM(G344:H344) -> 0 | J344: C | K344: 75% (N) | L344: 0.75 | M344: =I344*L344*$K$576 -> 0 | N344: Min qty 5. | O344: C1 | P344: Assorted bread (rolls and slices)
C345: Brioche roll (Locally baked) | D345: 40 | E345: Gm
...

Sheet Y Cost_Pax
A1: Caterer: TBD | B1: | Station: ATL | C1: Concept: 01JUN24 | Version: 1 | Updated: 15DEC23 Currency USD
B2: CS Y spec codes C1-3 | C2: PLUS (PREMIUM ECO)
A3: Supplier, please fill in name of Company in the first row | B3: SAS IFX Spec Code | C3: SAS IFX Description | D3: Weight / Pc | E3: Unit of M | F3: Quality, brand, supplier, origin, comments | G3: Direct Material | H3: Direct Labor | I3: Selling Price ex contrubtion | J3: Class | K3: Loading Instructions N.B only information | N3: Note | O3: Cycle / Menu | P3: Dish Name
A4: ='CS Y C1-3'!$A$4 -> Please fill in Supplier Name | B4: 3ATL-421010C2 | C4: IC Y S1 TSU C2 | G4: ='CS Y C1-3'!G4 -> 0 | H4: ='CS Y C1-3'!H4 -> 1.06 | I4: ='CS Y C1-3'!I4 -> 1.06 | J4: Y | K4: 1 | L4: 1 | M4: =I4*L4*$K$233 -> 28.62 | O4: C2 | P4: Tray setup
C5: Tray, Food, Large, ATLAS | D5: 1 | E5: Pc | G5: 0 | N5: 971168
C6: Traymat, Large, Black, Disposable | D6: 1 | E6: Pc | G6: 0 | N6: 973186
C7: Bag, For Cutlery | D7: 1 | E7: Pc | G7: 0 | N7: 973012
C8: 1 x Fork, Stainless, RS | D8: 1 | E8: Pc | G8: 0 | N8: 971091
C9: 1 x Spoon, Stainless, Coffee/Tea, RS | D9: 1 | E9: Pc | G9: 0 | N9: 971092
C10: 1 x Spoon, Stainless, Dessert/Soup, RS | D10: 1 | E10: Pc | G10: 0 | N10: 971093
C11: 1 x Knife, Stainless, RS | D11: 1 | E11: Pc | G11: 0 | N11: 971090
C12: 1 x Napkin, Paper, White | D12: 1 | E12: Pc | G12: 0 | N12: 973099
C13: 1 x Sugar, Portion Packed | D13: 1 | E13: Pc | G13: 0 | N13: 973023
C14: 1 x Salt & Pepper, Twinpack | D14: 1 | E14: Pc | G14: 0 | N14: 973034
C15: 1 x Toothpick, Individually Packed | D15: 1 | E15: Pc | G15: 0 | N15: 973020
A17: =$A$4 -> Please fill in Supplier Name | B17: 3ATL-421010C3 | C17: IC Y S1 TSU C3 | G17: ='CS Y C1-3'!G20 -> 0 | H17: ='CS Y C1-3'!H20 -> 1.01 | I17: ='CS Y C1-3'!I20 -> 1.01 | J17: Y | K17: 1 | L17: 1 | M17: =I17*L17*$K$233 -> 27.27 | O17: C3 | P17: Tray setup
C18: Tray, Food, Large, ATLAS | D18: 1 | E18: Pc | G18: 0 | N18: 971168
C19: Traymat, Large, Black, Disposable | D19: 1 | E19: Pc | G19: 0 | N19: 973186
C20: Bag, For Cutlery | D20: 1 | E20: Pc | G20: 0 | N20: 973012
C21: 1 x Fork, Stainless, RS | D21: 1 | E21: Pc | G21: 0 | N21: 971091
C22: 1 x Spoon, Stainless, Coffee/Tea, RS | D22: 1 | E22: Pc | G22: 0 | N22: 971092
C23: 1 x Spoon, Stainless, Dessert/Soup, RS | D23: 1 | E23: Pc | G23: 0 | N23: 971093
C24: 1 x Knife, Stainless, RS | D24: 1 | E24: Pc | G24: 0 | N24: 971090
C25: 1 x Napkin, Paper, White | D25: 1 | E25: Pc | G25: 0 | N25: 973099
C26: 1 x Sugar, Portion Packed | D26: 1 | E26: Pc | G26: 0 | N26: 973023
C27: 1 x Salt & Pepper, Twinpack | D27: 1 | E27: Pc | G27: 0 | N27: 973034
C28: 1 x Toothpick, Individually Packed | D28: 1 | E28: Pc | G28: 0 | N28: 973020
A30: =$A$4 -> Please fill in Supplier Name | B30: 2ATL-421011 | C30: IC Y S1 ST C1 | G30: =SUM(G31:G39) -> 0 | H30: =SUM(H31:H39) -> 0 | I30: =SUM(G30:H30) -> 0 | J30: Y | K30: 1 | M30: =I30*L30 -> 0 | O30: C1 | P30: Local air dried ham with broccoli slaw and kale grain salad
C31: Local air dried ham x 2 slices | D31: 15 | E31: Gm
C32: Kale grain salad | D32: 20 | E32: Gm
C33: Broccoli slaw | D33: 35 | E33: Gm
A41: =$A$4 -> Please fill in Supplier Name | B41: 2ATL-421012 | C41: IC Y S1 ST C2 | G41: ='CS Y C1-3'!G46 -> 0 | H41: ='CS Y C1-3'!H46 -> 0 | I41: ='CS Y C1-3'!I46 -> 0 | J41: Y | K41: 1 | L41: 1 | M41: =I41*L41*$K$233 -> 0 | O41: C2 | P41: Couscous salad with feta cheese
A52: =$A$4 -> Please fill in Supplier Name | B52: 2ATL-421013 | C52: IC Y S1 ST C3 | G52: ='CS Y C1-3'!G57 -> 0 | H52: ='CS Y C1-3'!H57 -> 0 | I52: ='CS Y C1-3'!I57 -> 0 | J52: Y | K52: 1 | L52: 1 | M52: =I52*L52*$K$233 -> 0 | O52: C3 | P52: Starter
A63: =$A$4 -> Please fill in Supplier Name | B63: 2ATL-421021 | C63: IC Y S1 HM-A C1 | G63: =SUM(G64:G72) -> 0 | H63: =SUM(H64:H72) -> 0 | I63: =SUM(G63:H63) -> 0 | J63: Y | K63: 60% (D) | M63: =I63*L63 -> 0 | O63: C1 | P63: Hake fish with farro, white wine sauce and sauteed zucchini and cherry tomatoes
C64: Hake fish fillet | D64: 4 | E64: Oz
C65: White wine cream sauce | D65: 30 | E65: Ml
C66: Farro with fresh herbes | D66: 80 | E66: Gm
C67: Sauteed fresh zucchini & mixed tomatoes | D67: 60 | E67: Gm
A74: =$A$4 -> Please fill in Supplier Name | B74: 2ATL-421022 | C74: IC Y S1 HM-A C2 | G74: ='CS Y C1-3'!G79 -> 0 | H74: ='CS Y C1-3'!H79 -> 0 | I74: ='CS Y C1-3'!I79 -> 0 | J74: Y | K74: 60% (D) | L74: 0.6 | M74: =I74*L74*$K$233 -> 0 | O74: C2 | P74: Beef Provencale with roasted Yukon wedges and roasted carrots
A85: =$A$4 -> Please fill in Supplier Name | B85: 2ATL-421023 | C85: IC Y S1 HM-A C3 | G85: ='CS Y C1-3'!G90 -> 0 | H85: ='CS Y C1-3'!H90 -> 0 | I85: ='CS Y C1-3'!I90 -> 0 | J85: Y | K85: 60% (D) | L85: 0.6 | M85: =I85*L85*$K$233 -> 0 | O85: C3
A96: =$A$4 -> Please fill in Supplier Name | B96: 2ATL-421031 | C96: IC Y/M S1 HM-B C1 | G96: =SUM(G97:G105) -> 0 | H96: =SUM(H97:H105) -> 0 | I96: =SUM(G96:H96) -> 0 | J96: Y | K96: 40% (U) | M96: =I96*L96 -> 0 | N96: Also used for M. | O96: C1 | P96: Oven roasted chicken with mashed sweet potatoes and spring vegetables
C97: Oven roasted chicken ( half thigh/ half breast) Wellfare | D97: 100 | E97: Gm
C98: Chicken jus | D98: 30 | E98: Ml
C99: Mashed orange sweet potatoes | D99: 80 | E99: Gm
C100: Sauteed spring vegetables | D100: 40 | E100: Gm
C101: (green beans, peas, snow peas & mexican onions) | D101: 0
A107: =$A$4 -> Please fill in Supplier Name | B107: 2ATL-421032 | C107: IC Y/M S1 HM-B C2 | G107: ='CS Y C1-3'!G112 -> 0 | H107: ='CS Y C1-3'!H112 -> 0 | I107: ='CS Y C1-3'!I112 -> 0 | J107: Y | K107: 40% (U) | L107: 0.4 | M107: =I107*L107*$K$233 -> 0 | N107: Also used for M. | O107: C2 | P107: Chicken in Marsala wine sauce with Gimelli pasta
A118: =$A$4 -> Please fill in Supplier Name | B118: 2ATL-421033 | C118: IC Y/M S1 HM-B C3 | G118: ='CS Y C1-3'!G123 -> 0 | H118: ='CS Y C1-3'!H123 -> 0 | I118: ='CS Y C1-3'!I123 -> 0 | J118: Y | K118: 40% (U) | L118: 0.4 | M118: =I118*L118*$K$233 -> 0 | N118: Also used for M. | O118: C3
A129: =$A$4 -> Please fill in Supplier Name | B129: 2ATL-421040 | C129: IC Y S1 DE C1 | G129: =SUM(G130:G132) -> 0 | H129: =SUM(H130:H132) -> 0 | I129: =SUM(G129:H129) -> 0 | J129: Y | K129: 1 | L129: 1 | M129: =I129*L129 -> 0 | O129: C1 | P129: Dark chocolate mousse w/salted caramel sauce & cockie crumbles
C130: Dark chocolate mousse | D130: 40 | E130: Gm
C131: Salty caramel sauce | D131: 20 | E131: Gm
C132: Cockie crumbles | D132: 10 | E132: Gm
A134: =$A$4 -> Please fill in Supplier Name | B134: 2ATL-421041 | C134: IC Y S1 DE C2 | G134: ='CS Y C1-3'!G139 -> 0 | H134: ='CS Y C1-3'!H139 -> 0 | I134: ='CS Y C1-3'!I139 -> 0 | J134: Y | K134: 1 | L134: 1 | M134: =I134*L134*$K$233 -> 0 | O134: C2 | P134: Cherry crumble pie with vanilla sauce
A139: =$A$4 -> Please fill in Supplier Name | B139: 2ATL-421042 | C139: IC Y S1 DE C3 | G139: ='CS Y C1-3'!G144 -> 0 | H139: ='CS Y C1-3'!H144 -> 0 | I139: ='CS Y C1-3'!I144 -> 0 | J139: Y | K139: 1 | L139: 1 | M139: =I139*L139*$K$233 -> 0 | O139: C3 | P139: Dessert
A144: =$A$4 -> Please fill in Supplier Name | B144: 4ATL-421010 | C144: IC Y/M S1+S2 BRD Type 1 C1 | G144: =SUM(G145:G147) -> 0 | H144: =SUM(H145:H147) -> 0 | I144: =SUM(G144:H144) -> 0 | J144: Y | K144: 120% (N) | L144: 1.2 | M144: =I144*L144 -> 0 | N144: Min qty 10. | O144: C1 | P144: Bread rolls
C145: Ciabatta roll | D145: 40 | E145: Gm
A149: =$A$4 -> Please fill in Supplier Name | B149: 4ATL-421010C2 | C149: IC Y/M S1+S2 BRD Type 1 C2 | G149: ='CS Y C1-3'!G154 -> 0 | H149: ='CS Y C1-3'!H154 -> 0 | I149: ='CS Y C1-3'!I154 -> 0 | J149: Y | K149: 120% (N) | L149: 1.2 | M149: =I149*L149*$K$233 -> 0 | N149: Min qty 10. | O149: C2 | P149: Bread rolls
A154: =$A$4 -> Please fill in Supplier Name | B154: 4ATL-421010C3 | C154: IC Y/M S1+S2 BRD Type 1 C3 | G154: ='CS Y C1-3'!G159 -> 0 | H154: ='CS Y C1-3'!H159 -> 0 | I154: ='CS Y C1-3'!I159 -> 0 | J154: Y | K154: 120% (N) | L154: 1.2 | M154: =I154*L154*$K$233 -> 0 | N154: Min qty 10. | O154: C3 | P154: Bread rolls
A159: =$A$4 -> Please fill in Supplier Name | B159: 3ATL-422010C2 | C159: IC Y S2 TSU C2 | G159: ='CS Y C1-3'!G164 -> 0 | H159: ='CS Y C1-3'!H164 -> 0 | I159: ='CS Y C1-3'!I164 -> 0 | J159: Y | K159: 1 | L159: 1 | M159: =I159*L159*$K$233 -> 0 | O159: C2 | P159: Tray setup
C160: Tray, Food, Medium, ATLAS | D160: 1 | E160: Pc | G160: 0
C161: 1 x Traymat, Medium, Black, Disposable | D161: 1 | E161: Pc | G161: 0
C162: 1 x Plate, Melamine | D162: 1 | E162: Pc | G162: 0
C163: 1 x Glass, Water/Champagne, RS | D163: 1 | E163: Pc | G163: 0
C164: 1 x Lid, For 971173, Disposable | D164: 1 | E164: Pc | G164: 0
C165: Cutlery pack S2 | D165: 1 | E165: Pc | G165: 0
A170: =$A$4 -> Please fill in Supplier Name | B170: 3ATL-422010C3 | C170: IC Y S2 TSU C3 | G170: ='CS Y C1-3'!G176 -> 0 | H170: ='CS Y C1-3'!H176 -> 0 | I170: ='CS Y C1-3'!I176 -> 0 | J170: Y | K170: 1 | L170: 1 | M170: =I170*L170*$K$233 -> 0 | O170: C3 | P170: Tray setup
C171: Tray, Food, Medium, ATLAS | D171: 1 | E171: Pc | G171: 0
C172: 1 x Traymat, Medium, Black, Disposable | D172: 1 | E172: Pc | G172: 0
C173: 1 x Plate, Melamine | D173: 1 | E173: Pc | G173: 0
C174: 1 x Glass, Water/Champagne, RS | D174: 1 | E174: Pc | G174: 0
C175: 1 x Lid, For 971173, Disposable | D175: 1 | E175: Pc | G175: 0
C176: Cutlery pack S2 | D176: 1 | E176: Pc | G176: 0
A181: =$A$4 -> Please fill in Supplier Name | B181: 2ATL-422011 | C181: IC Y S2 BREAKFAST PLATE C1 | G181: =SUM(G182:G190) -> 0 | H181: =SUM(H182:H190) -> 0 | I181: =SUM(G181:H181) -> 0 | J181: Y | K181: 1 | L181: 1 | M181: =I181*L181 -> 0 | O181: C1 | P181: Cold cut breakfast plate
C182: Black forest ham | D182: 30 | E182: Gm
C183: Cheddar cheese 15gm x 2 | D183: 30 | E183: Gm
C184: Hard boiled egg half | D184: 1 | E184: Pc
C185: Cherry tomato stemless | D185: 1 | E185: Pc
C186: Roman lettuce liner | D186: 12 | E186: Gm
C187: Pineapple slice | D187: 25 | E187: Gm
C188: Watermelon chunk | D188: 25 | E188: Gm
A192: =$A$4 -> Please fill in Supplier Name | B192: 2ATL-422012 | C192: IC Y S2 BREAKFAST PLATE C2 | G192: ='CS Y C1-3'!G198 -> 0 | H192: ='CS Y C1-3'!H198 -> 0 | I192: ='CS Y C1-3'!I198 -> 0 | J192: Y | K192: 1 | L192: 1 | M192: =I192*L192*$K$233 -> 0 | O192: C2 | P192: Cold cut breakfast plate
A203: =$A$4 -> Please fill in Supplier Name | B203: 2ATL-422013 | C203: IC Y S2 BREAKFAST PLATE C3 | G203: ='CS Y C1-3'!G209 -> 0 | H203: ='CS Y C1-3'!H209 -> 0 | I203: ='CS Y C1-3'!I209 -> 0 | J203: Y | K203: 1 | L203: 1 | M203: =I203*L203*$K$233 -> 0 | O203: C3 | P203: Cold cut breakfast plate
A214: =$A$4 -> Please fill in Supplier Name | B214: 3ATL-9210AV3 | C214: IC Y S1 AVML C3 | D214: 1 | E214: Pc | G214: ='CS Y C1-3'!G220 -> 0 | H214: ='CS Y C1-3'!H220 -> 0 | I214: ='CS Y C1-3'!I220 -> 0 | J214: Y | K214: 1 | L214: 1 | M214: =I214*L214*$K$233 -> 0 | O214: C3 | P214: Catering suggestion - equal service as far as possible with regular meal but all i a single code
A215: =$A$4 -> Please fill in Supplier Name | B215: 3ATL-9210CH3 | C215: IC Y S1 CHML C3 | D215: 1 | E215: Pc | G215: ='CS Y C1-3'!G221 -> 0 | H215: ='CS Y C1-3'!H221 -> 0 | I215: ='CS Y C1-3'!I221 -> 0 | J215: Y | K215: 1 | L215: 1 | M215: =I215*L215*$K$233 -> 0 | O215: C3 | P215: Catering suggestion - equal service as far as possible with regular meal but all i a single code
A216: =$A$4 -> Please fill in Supplier Name | B216: 3ATL-9210LG3 | C216: IC Y S1 LGML C3 | D216: 1 | E216: Pc | G216: ='CS Y C1-3'!G222 -> 0 | H216: ='CS Y C1-3'!H222 -> 0 | I216: ='CS Y C1-3'!I222 -> 0 | J216: Y | K216: 1 | L216: 1 | M216: =I216*L216*$K$233 -> 0 | O216: C3 | P216: Catering suggestion - equal service as far as possible with regular meal but all i a single code
A217: =$A$4 -> Please fill in Supplier Name | B217: 3ATL-9210VG3 | C217: IC Y S1 VGML C3 | D217: 1 | E217: Pc | G217: ='CS Y C1-3'!G223 -> 0 | H217: ='CS Y C1-3'!H223 -> 0 | I217: ='CS Y C1-3'!I223 -> 0 | J217: Y | K217: 1 | L217: 1 | M217: =I217*L217*$K$233 -> 0 | O217: C3 | P217: Catering suggestion - equal service as far as possible with regular meal but all i a single code
A218: =$A$4 -> Please fill in Supplier Name | B218: 3ATL-9210VL3 | C218: IC Y S1 VLML C3 | D218: 1 | E218: Pc | G218: ='CS Y C1-3'!G224 -> 0 | H218: ='CS Y C1-3'!H224 -> 0 | I218: ='CS Y C1-3'!I224 -> 0 | J218: Y | K218: 1 | L218: 1 | M218: =I218*L218*$K$233 -> 0 | O218: C3 | P218: Catering suggestion - equal service as far as possible with regular meal but all i a single code
A219: =$A$4 -> Please fill in Supplier Name | B219: 3ATL-9220AV3 | C219: IC Y S2 AVML C3 | D219: 1 | E219: Pc | G219: ='CS Y C1-3'!G225 -> 0 | H219: ='CS Y C1-3'!H225 -> 0 | I219: ='CS Y C1-3'!I225 -> 0 | J219: Y | K219: 1 | L219: 1 | M219: =I219*L219*$K$233 -> 0 | O219: C3 | P219: Catering suggestion - equal service as far as possible with regular meal but all i a single code
A220: =$A$4 -> Please fill in Supplier Name | B220: 3ATL-9220CH3 | C220: IC Y S2 CHML C3 | D220: 1 | E220: Pc | G220: ='CS Y C1-3'!G226 -> 0 | H220: ='CS Y C1-3'!H226 -> 0 | I220: ='CS Y C1-3'!I226 -> 0 | J220: Y | K220: 1 | L220: 1 | M220: =I220*L220*$K$233 -> 0 | O220: C3 | P220: Catering suggestion - equal service as far as possible with regular meal but all i a single code
A221: =$A$4 -> Please fill in Supplier Name | B221: 3ATL-9220LG3 | C221: IC Y S2 LGML C3 | D221: 1 | E221: Pc | G221: ='CS Y C1-3'!G227 -> 0 | H221: ='CS Y C1-3'!H227 -> 0 | I221: ='CS Y C1-3'!I227 -> 0 | J221: Y | K221: 1 | L221: 1 | M221: =I221*L221*$K$233 -> 0 | O221: C3 | P221: Catering suggestion - equal service as far as possible with regular meal but all i a single code
A222: =$A$4 -> Please fill in Supplier Name | B222: 3ATL-9220VG3 | C222: IC Y S2 VGML C3 | D222: 1 | E222: Pc | G222: ='CS Y C1-3'!G228 -> 0 | H222: ='CS Y C1-3'!H228 -> 0 | I222: ='CS Y C1-3'!I228 -> 0 | J222: Y | K222: 1 | L222: 1 | M222: =I222*L222*$K$233 -> 0 | O222: C3 | P222: Catering suggestion - equal service as far as possible with regular meal but all i a single code
A223: =$A$4 -> Please fill in Supplier Name | B223: 3ATL-9220VL3 | C223: IC Y S2 VLML C3 | D223: 1 | E223: Pc | G223: ='CS Y C1-3'!G229 -> 0 | H223: ='CS Y C1-3'!H229 -> 0 | I223: ='CS Y C1-3'!I229 -> 0 | J223: Y | K223: 1 | L223: 1 | M223: =I223*L223*$K$233 -> 0 | O223: C3 | P223: Catering suggestion - equal service as far as possible with regular meal but all i a single code
A224: =$A$4 -> Please fill in Supplier Name | B224: 3ATL-9210BK3 | C224: IC Y S1 BKML C3 | D224: 1 | E224: Pc | G224: ='CS Y C1-3'!G230 -> 0 | H224: ='CS Y C1-3'!H230 -> 0 | I224: ='CS Y C1-3'!I230 -> 0 | J224: Y | K224: 1 | L224: 1 | M224: =I224*L224*$K$233 -> 0 | O224: C3 | P224: Bank Meal
A225: =$A$4 -> Please fill in Supplier Name | B225: 3ATL-9220BK3 | C225: IC Y S2 BKML C3 | D225: 1 | E225: Pc | G225: ='CS Y C1-3'!G231 -> 0 | H225: ='CS Y C1-3'!H231 -> 0 | I225: ='CS Y C1-3'!I231 -> 0 | J225: Y | K225: 1 | L225: 1 | M225: =I225*L225*$K$233 -> 0 | O225: C3 | P225: Bank Meal
A226: =$A$4 -> Please fill in Supplier Name | B226: 8ATL-OVERHEAD-Y | C226: IC Y Overhead | D226: 1 | E226: Pc | I226: ='CS Y C1-3'!I232 -> 0 | J226: Y | K226: 1 | L226: 1 | M226: =I226*L226*$K$233 -> 0 | O226: C2, C3
I231: Loadfactor | J231: AC | K231: Y | L231: Max | M231: =M4+M41+M74+M107+M134+M149+M159+M192+M226 -> 28.62 | N231: Total Cost SAS Plus - 85% loadfactor
I232: 0.85 | J232: 330 | K232: 48 | L232: 22 | M232: =M231/$K$233 -> 1.06 | N232: Cost Per SAS Plus Pax Cycle 2
J233: 350 | K233: 27
M234: =M17+M52+M85+M118+M139+M154+M170+M203+M226 -> 27.27 | N234: Total Cost SAS Plus - 85% loadfactor
M235: =M234/$K$233 -> 1.01 | N235: Cost Per SAS Plus Pax Cycle 3

Sheet M Cost_Pax
A1: Caterer: TBD | B1: Station: ATL | C1: Concept: 01JUN24 | Version: 1 | Updated: 15DEC23 Currency USD
B2: CS M spec codes C1-3 | C2: GO (ECONOMY)
A3: Supplier, please fill in name of Company in the first row | B3: SAS IFX Spec Code | C3: SAS IFX Description | D3: Weight / Pc | E3: Unit of M | F3: Quality, brand, supplier, origin, comments | G3: Direct Material | H3: Direct Labor | I3: Selling Price ex contrubtion | J3: Class | K3: Loading Instructions N.B only information | N3: Note | O3: Cycle / Menu | P3: Dish Name
A4: ='CS M C1-3'!$A$4 -> Please fill in Supplier Name | B4: 3ATL-431010C2 | C4: IC M S1 TSU C2 | G4: ='CS M C1-3'!G4 -> 0 | H4: ='CS M C1-3'!H4 -> 0.62 | I4: ='CS M C1-3'!I4 -> 0.62 | J4: M | K4: 1 | L4: 1 | M4: =I4*L4*$K$235 -> 120.28 | O4: C2 | P4: Tray Setup
C5: Tray, Food, Medium, ATLAS | D5: 1 | G5: 0 | N5: 971167
C6: 1 x Traymat, Medium, Anti-Skid, Disposable | D6: 1 | G6: 0 | N6: 973172
C7: 1 x Cutlery, Type 4/1, Disp, Neutral | D7: 1 | G7: 0 | N7: 973605
C8: 1 x Insert, For Casserole, Disposable | D8: 1 | G8: 0 | N8: 973045
C9: 1 x Insert, X-Large, Disposable (for salad) | D9: 1 | G9: 0 | N9: 971205
C10: 1 x Lid, For 971205, Disposable | D10: 1 | G10: 0 | N10: 971206
C11: 1 x Insert, Small, Disposable (for dessert) | D11: 1 | G11: 0 | N11: 971207
C12: 1 x Lid , For 971207, Disposable, Small | D12: 1 | G12: 0 | N12: 971208
G13: 0
A15: =$A$4 -> Please fill in Supplier Name | B15: 3ATL-431010C3 | C15: IC M S1 TSU C3 | G15: ='C Cost_Pax'!G15 -> 0 | H15: ='CS M C1-3'!H16 -> 0.62 | I15: ='CS M C1-3'!I16 -> 0.62 | J15: M | K15: 1 | L15: 1 | M15: =I15*L15*$K$235 -> 120.28 | O15: C3 | P15: Tray Setup
C16: Tray, Food, Medium, ATLAS | D16: 1 | G16: 0 | N16: 971167
C17: 1 x Traymat, Medium, Anti-Skid, Disposable | D17: 1 | G17: 0 | N17: 973172
C18: 1 x Cutlery, Type 4/1, Disp, Neutral | D18: 1 | G18: 0 | N18: 973605
C19: 1 x Insert, For Casserole, Disposable | D19: 1 | G19: 0 | N19: 973045
C20: 1 x Insert, X-Large, Disposable (for salad) | D20: 1 | G20: 0 | N20: 971205
C21: 1 x Lid, For 971205, Disposable | D21: 1 | G21: 0 | N21: 971206
C22: 1 x Insert, Small, Disposable (for dessert) | D22: 1 | G22: 0 | N22: 971207
C23: 1 x Lid , For 971207, Disposable, Small | D23: 1 | G23: 0 | N23: 971208
G24: 0
A26: =$A$4 -> Please fill in Supplier Name | B26: 2ATL-431011 | C26: IC M S1 SALAD C1 | G26: =SUM(G27:G35) -> 0 | H26: ='CS M C1-3'!H28 -> 0 | I26: ='CS M C1-3'!I28 -> 0 | J26: M | K26: 1 | L26: 1 | M26: =I26*K26 -> 0 | O26: C1 | P26: Mixed starter salad
C27: Mesclun mix | D27: 10
C28: Blue cheese crumbled | D28: 10
C29: Shredded carrots (julienned) | D29: 10
C30: Toasted pepitas | D30: 3
A37: =$A$4 -> Please fill in Supplier Name | B37: 2ATL-431012 | C37: IC M S1 SALAD C2 | G37: ='CS M C1-3'!G39 -> 0 | H37: ='CS M C1-3'!H39 -> 0 | I37: ='CS M C1-3'!I39 -> 0 | J37: M | K37: 1 | L37: 1 | M37: =I37*L37*$K$235 -> 0 | O37: C2
A48: =$A$4 -> Please fill in Supplier Name | B48: 2ATL-431013 | C48: IC M S1 SALAD C3 | G48: ='CS M C1-3'!G50 -> 0 | H48: ='CS M C1-3'!H50 -> 0 | I48: ='CS M C1-3'!I50 -> 0 | J48: M | K48: 1 | L48: 1 | M48: =I48*L48*$K$235 -> 0 | O48: C3
A59: =$A$4 -> Please fill in Supplier Name | B59: 2ATL-421031 | C59: IC Y/M S1 HM-B C1 | G59: =SUM(G60:G68) -> 0 | H59: ='CS M C1-3'!H61 -> 0 | I59: ='CS M C1-3'!I61 -> 0 | J59: M | K59: 1 | L59: 1 | M59: =I59*K59 -> 0 | N59: Also used for Y. | O59: C1 | P59: Oven roasted chicken with mashed sweet potatoes
C60: Oven roasted chicken ( half thigh/ half breast) Wellfare | D60: 100 | E60: Gm
C61: Chicken jus | D61: 30 | E61: Ml
C62: Mashed orange sweet potatoes | D62: 80 | E62: Gm
C63: Sauteed spring vegetables | D63: 40 | E63: Gm
C64: (green beans, peas, snow peas & mexican onions) | D64: 0
A70: =$A$4 -> Please fill in Supplier Name | B70: 2ATL-421032 | C70: IC Y/M S1 HM-B C2 | G70: ='CS M C1-3'!G72 -> 0 | H70: ='CS M C1-3'!H72 -> 0 | I70: ='CS M C1-3'!I72 -> 0 | J70: M | K70: 1 | L70: 1 | M70: =I70*L70*$K$235 -> 0 | N70: Also used for Y. | O70: C2
A81: =$A$4 -> Please fill in Supplier Name | B81: 2ATL-421033 | C81: IC Y/M S1 HM-B C3 | G81: ='CS M C1-3'!G83 -> 0 | H81: ='CS M C1-3'!H83 -> 0 | I81: ='CS M C1-3'!I83 -> 0 | J81: M | K81: 1 | L81: 1 | M81: =I81*L81*$K$235 -> 0 | N81: Also used for Y. | O81: C3
A92: =$A$4 -> Please fill in Supplier Name | B92: 2ATL-431020 | C92: IC M S1 DE C1 | G92: =SUM(G93:G95) -> 0 | H92: ='CS M C1-3'!H94 -> 0 | I92: ='CS M C1-3'!I94 -> 0 | J92: M | K92: 1 | L92: 1 | M92: =I92*K92 -> 0 | O92: C1 | P92: Appe cheese cake with vanilla sauce
C93: Apple cheese cake | D93: 50 | E93: Gm
C94: Vanilla sauce | D94: 10 | E94: Gm
A97: =$A$4 -> Please fill in Supplier Name | B97: 2ATL-431021 | C97: IC M S1 DE C2 | G97: ='CS M C1-3'!G99 -> 0 | H97: ='CS M C1-3'!H99 -> 0 | I97: ='CS M C1-3'!I99 -> 0 | J97: M | K97: 1 | L97: 1 | M97: =I97*L97*$K$235 -> 0 | O97: C2
A102: =$A$4 -> Please fill in Supplier Name | B102: 2ATL-431022 | C102: IC M S1 DE C3 | G102: ='CS M C1-3'!G104 -> 0 | H102: ='CS M C1-3'!H104 -> 0 | I102: ='CS M C1-3'!I104 -> 0 | J102: M | K102: 1 | L102: 1 | M102: =I102*L102*$K$235 -> 0 | O102: C3
A107: =$A$4 -> Please fill in Supplier Name | B107: 4ATL-421010 | C107: IC Y/M S1+S2 BRD Type 1 C1 | G107: ='CS M C1-3'!G109 -> 0 | H107: ='CS M C1-3'!H109 -> 0 | I107: ='CS M C1-3'!I109 -> 0 | J107: Y | K107: 120% (N) | L107: 1.2 | M107: =I107*L107 -> 0 | N107: Min qty 10. | O107: C1 | P107: Bread rolls
C108: Ciabatta roll | D108: 40 | E108: Gm
A112: =$A$4 -> Please fill in Supplier Name | B112: 4ATL-421010C2 | C112: IC Y/M S1+S2 BRD Type 1 C2 | G112: =SUM(G113:G115) -> 0 | H112: ='CS M C1-3'!H114 -> 0 | I112: ='CS M C1-3'!I114 -> 0 | J112: Y | K112: 120% (N) | L112: 1.2 | M112: =I112*L112*$K$235 -> 0 | N112: Min qty 10. | O112: C2 | P112: Bread rolls
A117: =$A$4 -> Please fill in Supplier Name | B117: 4ATL-421010C3 | C117: IC Y/M S1+S2 BRD Type 1 C3 | G117: ='CS M C1-3'!G114 -> 0 | H117: ='CS M C1-3'!H119 -> 0 | I117: ='CS M C1-3'!I119 -> 0 | J117: Y | K117: 120% (N) | L117: 1.2 | M117: =I117*L117*$K$235 -> 0 | N117: Min qty 10. | O117: C3 | P117: Bread rolls
A122: =$A$4 -> Please fill in Supplier Name | B122: 4ATL-432010 | C122: IC M S2 JUICE C1 | G122: =SUM(G123:G125) -> 0 | H122: ='CS M C1-3'!H124 -> 0 | I122: ='CS M C1-3'!I124 -> 0 | J122: M | K122: 1 | L122: 1 | M122: =I122*K122 -> 0 | O122: C1
C123: PP Orange juice cup | D123: 1 | E123: Pc
A127: =$A$4 -> Please fill in Supplier Name | B127: 4ATL-432010C2 | C127: IC M S2 JUICE C2 | G127: ='CS M C1-3'!G129 -> 0 | H127: ='CS M C1-3'!H129 -> 0 | I127: ='CS M C1-3'!I129 -> 0 | J127: M | K127: 1 | L127: 1 | M127: =I127*L127*$K$235 -> 0 | O127: C2
A132: =$A$4 -> Please fill in Supplier Name | B132: 4ATL-432010C3 | C132: IC M S2 JUICE C3 | G132: ='CS M C1-3'!G134 -> 0 | H132: ='CS M C1-3'!H134 -> 0 | I132: ='CS M C1-3'!I134 -> 0 | J132: M | K132: 1 | L132: 1 | M132: =I132*L132*$K$235 -> 0 | O132: C3
A137: =$A$4 -> Please fill in Supplier Name | B137: 2ATL-432020 | C137: IC M S2 SW | G137: =SUM(G138:G140) -> 0 | H137: ='CS M C1-3'!H139 -> 0 | I137: ='CS M C1-3'!I139 -> 0 | J137: M | K137: 1 | L137: 1 | M137: =I137*K137 -> 0 | O137: C1
C138: Hot Breakfast Toast/ Eng. Muffin with Turkey & Cheese | D138: 1 | E138: Pc
A142: =$A$4 -> Please fill in Supplier Name | B142: 2ATL-432020C2 | C142: IC M S2 SW | G142: ='CS M C1-3'!G144 -> 0 | H142: ='CS M C1-3'!H144 -> 0 | I142: ='CS M C1-3'!I144 -> 0 | J142: M | K142: 1 | L142: 1 | M142: =I142*L142*$K$235 -> 0 | O142: C2
A147: =$A$4 -> Please fill in Supplier Name | B147: 2ATL-432020C3 | C147: IC M S2 SW | G147: ='CS M C1-3'!G149 -> 0 | H147: ='CS M C1-3'!H149 -> 0 | I147: ='CS M C1-3'!I149 -> 0 | J147: M | K147: 1 | L147: 1 | M147: =I147*L147*$K$235 -> 0 | O147: C3
A152: =$A$4 -> Please fill in Supplier Name | B152: 3ATL-9310ME2 | C152: IC M S1 MEML C2 | G152: ='CS M C1-3'!G154 -> 10 | H152: ='CS M C1-3'!H154 -> 10 | I152: ='CS M C1-3'!I154 -> 20 | J152: M | K152: 1 | L152: 1 | M152: =I152*L152 -> 20 | O152: C3
C153: IC Y S1 TSU C2 | D153: 1 | E153: Pc
C154: IC Y S1 ST C2 | D154: 1 | E154: Pc
C155: IC Y S1 DE C2 | D155: 1 | E155: Pc
C156: IC C S1 HM-A MEAT C2 | D156: 1 | E156: Pc
C157: IC Y S1 TSU C2 | D157: 1 | E157: Pc
A163: =$A$4 -> Please fill in Supplier Name | B163: 3ATL-9310ME3 | C163: IC M S1 MEML C3 | G163: ='CS M C1-3'!G165 -> 10 | H163: ='CS M C1-3'!H165 -> 10 | I163: ='CS M C1-3'!I165 -> 20 | J163: M | K163: 1 | L163: 1 | M163: =I163*L163 -> 20 | O163: C3 | P163: MEML SAS Premium Menu – Meat, N.B. only available in SAS GO. SAS Plus 1st serving Tray setup with the Business class Hot meal Meat portioned the aluminium disposable casserole 973113 and lid 973114. Regular 2nd service
C164: IC Y S1 TSU C3 | D164: 1 | E164: Pc
C165: IC Y S1 ST C3 | D165: 1 | E165: Pc
C166: IC Y S1 DE C3 | D166: 1 | E166: Pc
C167: IC C S1 HM-A MEAT C3 | D167: 1 | E167: Pc
C168: IC Y S1 TSU C3 | D168: 1 | E168: Pc
A174: =$A$4 -> Please fill in Supplier Name | B174: 3ATL-9310CK2 | C174: IC M S1 CKML C2 | G174: ='CS M C1-3'!G176 -> 0 | H174: ='CS M C1-3'!H176 -> 0 | I174: ='CS M C1-3'!I176 -> 0 | J174: M | K174: 1 | L174: 1 | M174: =I174*L174 -> 0 | O174: C3
C175: IC Y S1 TSU C2 | D175: 1 | E175: Pc
C176: IC Y S1 ST C2 | D176: 1 | E176: Pc
C177: IC Y S1 DE C2 | D177: 1 | E177: Pc
C178: IC C S1 HM-C POULTRY C2 | D178: 1 | E178: Pc
C179: IC Y S1 TSU C2 | D179: 1 | E179: Pc
A185: =$A$4 -> Please fill in Supplier Name | B185: 3ATL-9310CK3 | C185: IC M S1 CKML C3 | G185: ='CS M C1-3'!G187 -> 0 | H185: ='CS M C1-3'!H187 -> 0 | I185: ='CS M C1-3'!I187 -> 0 | J185: M | K185: 1 | L185: 1 | M185: =I185*L185 -> 0 | O185: C3 | P185: CKML SAS Premium Menu – Poultry, N.B. only available in SAS GO. SAS Plus 1st serving Tray setup with the Business class Hot meal Chicken portioned the aluminium disposable casserole 973113 and lid 973114. Regular 2nd service
C186: IC Y S1 TSU C3 | D186: 1 | E186: Pc
C187: IC Y S1 ST C3 | D187: 1 | E187: Pc
C188: IC Y S1 DE C3 | D188: 1 | E188: Pc
C189: IC C S1 HM-C POULTRY C3 | D189: 1 | E189: Pc
C190: IC Y S1 TSU C3 | D190: 1 | E190: Pc
A196: =$A$4 -> Please fill in Supplier Name | B196: 3ATL-9310GH2 | C196: IC M S1 GHML C2 | G196: ='CS M C1-3'!G198 -> 0 | H196: ='CS M C1-3'!H198 -> 0 | I196: ='CS M C1-3'!I198 -> 0 | J196: M | K196: 1 | L196: 1 | M196: =I196*L196 -> 0 | O196: C3
C197: IC Y S1 TSU C2 | D197: 1 | E197: Pc
C198: IC Y S1 ST C2 | D198: 1 | E198: Pc
C199: IC Y S1 DE C2 | D199: 1 | E199: Pc
C200: IC C S1 HM-D VEG C2 | D200: 1 | E200: Pc
C201: IC Y S1 TSU C2 | D201: 1 | E201: Pc
A207: =$A$4 -> Please fill in Supplier Name | B207: 3ATL-9310GH3 | C207: IC M S1 GHML C3 | G207: ='CS M C1-3'!G209 -> 0 | H207: ='CS M C1-3'!H209 -> 0 | I207: ='CS M C1-3'!I209 -> 0 | J207: M | K207: 1 | L207: 1 | M207: =I207*L207 -> 0 | O207: C3 | P207: GHML SAS Premium Menu – Green, N.B. only available in SAS GO, Lacto ovo veg. SAS Plus 1st serving Tray setup with the Business class Hot meal fish portioned the aluminium disposable casserole 973113 and lid 973114 and 2nd serivce EVML
C208: IC Y S1 TSU C3 | D208: 1 | E208: Pc
C209: IC Y S1 ST C3 VVML | D209: 1 | E209: Pc
C210: IC Y S1 DE C3 | D210: 1 | E210: Pc
C211: IC C S1 HM-D VEG C3 | D211: 1 | E211: Pc
C212: IC Y S1 TSU C3 | D212: 1 | E212: Pc
A218: =$A$4 -> Please fill in Supplier Name | B218: 3ATL-9310CD3 | C218: IC M S1 CDML C3 | D218: 1 | E218: Pc | G218: ='CS M C1-3'!G220 -> 0 | H218: ='CS M C1-3'!H220 -> 0 | I218: ='CS M C1-3'!I220 -> 0 | J218: M | K218: 1 | L218: 1 | M218: =I218*L218 -> 0 | O218: C3 | P218: Catering suggestion - equal service as far as possible with regular meal but all i a single code
A219: =$A$4 -> Please fill in Supplier Name | B219: 3ATL-9310GC3 | C219: IC M S1 GCML C3 | D219: 1 | E219: Pc | G219: ='CS M C1-3'!G221 -> 0 | H219: ='CS M C1-3'!H221 -> 0 | I219: ='CS M C1-3'!I221 -> 0 | J219: M | K219: 1 | L219: 1 | M219: =I219*L219 -> 0 | O219: C3 | P219: Catering suggestion - equal service as far as possible with regular meal but all i a single code
A220: =$A$4 -> Please fill in Supplier Name | B220: 3ATL-9310VV3 | C220: IC M S1 VVML C3 | D220: 1 | E220: Pc | G220: ='CS M C1-3'!G222 -> 0 | H220: ='CS M C1-3'!H222 -> 0 | I220: ='CS M C1-3'!I222 -> 0 | J220: M | K220: 1 | L220: 1 | M220: =I220*L220 -> 0 | O220: C3 | P220: Catering suggestion - equal service as far as possible with regular meal but all i a single code
A221: =$A$4 -> Please fill in Supplier Name | B221: 3ATL-9310EV3 | C221: IC M S1 EVML C3 | D221: 1 | E221: Pc | G221: ='CS M C1-3'!G223 -> 0 | H221: ='CS M C1-3'!H223 -> 0 | I221: ='CS M C1-3'!I223 -> 0 | J221: M | K221: 1 | L221: 1 | M221: =I221*L221 -> 0 | O221: C3 | P221: Catering suggestion - equal service as far as possible with regular meal but all i a single code
A222: =$A$4 -> Please fill in Supplier Name | B222: 3ATL-9320AD3 | C222: IC M S2 ADML C3 | D222: 1 | E222: Pc | G222: ='CS M C1-3'!G224 -> 0 | H222: ='CS M C1-3'!H224 -> 0 | I222: ='CS M C1-3'!I224 -> 0 | J222: M | K222: 1 | L222: 1 | M222: =I222*L222 -> 0 | O222: C3 | P222: Catering suggestion - equal service as far as possible with regular meal but all i a single code
A223: =$A$4 -> Please fill in Supplier Name | B223: 3ATL-9320CD3 | C223: IC M S2 CDML C3 | D223: 1 | E223: Pc | G223: ='CS M C1-3'!G225 -> 0 | H223: ='CS M C1-3'!H225 -> 0 | I223: ='CS M C1-3'!I225 -> 0 | J223: M | K223: 1 | L223: 1 | M223: =I223*L223 -> 0 | O223: C3 | P223: Catering suggestion - equal service as far as possible with regular meal but all i a single code
A224: =$A$4 -> Please fill in Supplier Name | B224: 3ATL-9320GC3 | C224: IC M S2 GCML C3 | D224: 1 | E224: Pc | G224: ='CS M C1-3'!G226 -> 0 | H224: ='CS M C1-3'!H226 -> 0 | I224: ='CS M C1-3'!I226 -> 0 | J224: M | K224: 1 | L224: 1 | M224: =I224*L224 -> 0 | O224: C3 | P224: Catering suggestion - equal service as far as possible with regular meal but all i a single code
A225: =$A$4 -> Please fill in Supplier Name | B225: 3ATL-9320VV3 | C225: IC M S2 VVML C3 | D225: 1 | E225: Pc | G225: ='CS M C1-3'!G227 -> 0 | H225: ='CS M C1-3'!H227 -> 0 | I225: ='CS M C1-3'!I227 -> 0 | J225: M | K225: 1 | L225: 1 | M225: =I225*L225 -> 0 | O225: C3 | P225: Catering suggestion - equal service as far as possible with regular meal but all i a single code
A226: =$A$4 -> Please fill in Supplier Name | B226: 3ATL-9320EV3 | C226: IC M S2 EVML C3 | D226: 1 | E226: Pc | G226: ='CS M C1-3'!G228 -> 0 | H226: ='CS M C1-3'!H228 -> 0 | I226: ='CS M C1-3'!I228 -> 0 | J226: M | K226: 1 | L226: 1 | M226: =I226*L226 -> 0 | O226: C3 | P226: Catering suggestion - equal service as far as possible with regular meal but all i a single code
...

Sheet IC-27
A1: LOAD SCALE
H3: Description | I3: : | K3: 1-20=2/21-32=3/33-40=4/41-46=5
B4: Load Scale Code | D4: : | E4: IC-27
B7: Version | D7: : | E7: 2 | H7: Is Used (Y/N) | I7: :
B9: Eff Date | D9: : | E9: 10/05/2023 | H9: End Date | I9: :
C10: Pax Interval or Pax Count | F10: Board Quantity
C11: 1 | F11: 2
C12: 2 | F12: 2
C13: 3 | F13: 2
C14: 4 | F14: 2
C15: 5 | F15: 2
C16: 6 | F16: 2
C17: 7 | F17: 2
C18: 8 | F18: 2
C19: 9 | F19: 2
C20: 10 | F20: 2
C21: 11 | F21: 2
... C56: 46 | F56: 5

Sheet IC-29
A1: LOAD SCALE
H3: Description | I3: : | K3: 1-24=2/25-40=3
B4: Load Scale Code | D4: : | E4: IC-29
B6: Version | D6: : | E6: 1 | H6: Is Used (Y/N) | I6: : | K6: N
B7: Eff Date | D7: : | E7: 01/02/2024 | H7: End Date | I7: :
C8: Pax Interval or Pax Count | F8: Board Quantity
C9: 1 | F9: 2
C10: 2 | F10: 2
C11: 3 | F11: 2
C12: 4 | F12: 2
C13: 5 | F13: 2
C14: 6 | F14: 2
C15: 7 | F15: 2
C16: 8 | F16: 2
C17: 9 | F17: 2
C18: 10 | F18: 2
C19: 11 | F19: 2
... C48: 40 | F48: 3

Sheet CF
B2: Config | C2: AC | D2: C | E2: Y | F2: M
C3: 330 | D3: 32 | E3: 56 | F3: 174
C4: 350 | D4: 40 | E4: 32 | F4: 228
B6: Loadfactor | C6: AC | D6: C | E6: Y | F6: M
B7: 0.85 | C7: 330 | D7: =D3*B7 -> 27.2 | E7: =E3*B7 -> 47.6 | F7: =F3*B7 -> 147.9
C8: 350 | D8: =D4*B7 -> 34 | E8: =E4*B7 -> 27.2 | F8: =F4*B7 -> 193.8
