Workbook
Name COMMERCIAL_ITEMS: [2]POLICY!$G$3:$G$348
Name COMMERCIAL_ITEMS: [3]POLICY!$G$3:$G$317

Sheet P&L
P2: 7 | Q2: Flights Per Week
P3: =FlightConfig!K17 -> 364 | Q3: Flights Annually
P4: 0.8 | Q4: Load
B5: Description | C5: Grand Total | E5: SAS | G5: Unit Central Cost | P5: 3 | Q5: Cycle
C6: $ | D6: % | E6: $ | F6: % | G6: $ | H6: % | P6: 0 | Q6: Discount
B7: Revenue Meals | C7: =SUM(E7,G7) -> 4460170.2 | D7: =C7/$C$12 -> 0.89904749 | E7: =SUM('Summary '!J11:J14) -> 1285870.2 | F7: =E7/$E$12 -> 0.71969201 | G7: =529050*6 -> 3174300 | H7: =G7/$G$12 -> 1
B8: Revenue Handling | C8: =SUM(E8,G8) -> 276600.9 | D8: =C8/$C$12 -> 0.055755126 | E8: =SUM('Summary '!J16:J17) -> 276600.9 | F8: =E8/$E$12 -> 0.15481148 | H8: =G8/$G$12 -> 0 | P8: 0.13 | Q8: Mark up on Food
B9: Revenue Overheads | C9: =SUM(E9,G9) -> 224224 | D9: =C9/$C$12 -> 0.045197384 | E9: ='Summary '!J10 -> 224224 | F9: =E9/$E$12 -> 0.12549651 | H9: =G9/$G$12 -> 0 | P9: 0.13 | Q9: Mark up on Labor
B10: Revenue Other | C10: =SUM(E10,G10) -> 0 | D10: =C10/$C$12 -> 0 | E10: ='Summary '!J15 -> 0 | F10: =E10/$E$12 -> 0 | H10: =G10/$G$12 -> 0 | P10: 0.087 | Q10: Mark up on Handling
B11: Discount | C11: =SUM(E11,G11) -> 0 | D11: =C11/$C$12 -> 0 | E11: =SUM(E7:E9)*P6 -> 0 | F11: =E11/$E$12 -> 0 | H11: =G11/$G$12 -> 0 | P11: 0 | Q11: Mark up on TRASH REMOVAL
B12: Net Revenue | C12: =SUM(C7:C11) -> 4960995.1 | D12: =C12/$C$12 -> 1 | E12: =SUM(E7:E11) -> 1786695.1 | F12: =E12/$E$12 -> 1 | G12: =SUM(G7:G11) -> 3174300 | H12: =G12/$G$12 -> 1 | I12: =E12/12 -> 148891.26
B13: Food Cost | C13: =SUM(E13,G13) -> 1430652.4 | D13: =C13/$C$12 -> 0.28838013 | E13: ='Summary '!J11 -> 672414.41 | F13: =E13/$E$12 -> 0.37634536 | G13: =126373*6 -> 758238 | H13: =G13/$G$12 -> 0.23886778 | I13: 30245 - 2 weeks | P13: SAS HANDLING
B14: Other product cost | C14: =SUM(E14,G14) -> 0 | D14: =C14/$C$12 -> 0 | E14: 0 | F14: =E14/$E$12 -> 0 | G14: =0+E14 -> 0 | H14: =G14/$G$12 -> 0 | I14: =E13/12 -> 56034.534 | P14: =Handling!C24 -> 559.89259 | Q14: SAS 330/350 TURNAROUND
B15: Total Direct Materials | C15: =SUM(C13:C14) -> 1430652.4 | D15: =C15/$C$12 -> 0.28838013 | E15: =SUM(E13:E14) -> 672414.41 | F15: =E15/$E$12 -> 0.37634536 | G15: =SUM(G13:G14) -> 758238 | H15: =G15/$G$12 -> 0.23886778
B16: Direct Labor - Wages | C16: =SUM(E16,G16) -> 1919837.2 | D16: =C16/$C$12 -> 0.38698631 | E16: ='Summary '!L17 -> 579235.56 | F16: =E16/$E$12 -> 0.32419385 | G16: =223433.6*6 -> 1340601.6 | H16: =G16/$G$12 -> 0.42232984 | P16: SAS HANDLING
B17: Direct Labor - OT Premium | C17: =SUM(E17,G17) -> 0 | D17: =C17/$C$12 -> 0 | E17: 0 | F17: =E17/$E$12 -> 0 | G17: =0+E17 -> 0 | H17: =G17/$G$12 -> 0 | P17: =Handling!C28 -> 200 | Q17: INTERNATIONAL GARBAGE
B18: Direct Labor - Benefit Cost | C18: =SUM(E18,G18) -> 464959.29 | D18: =C18/$C$12 -> 0.09372299 | E18: ='Summary '!L18 -> 144808.89 | F18: =E18/$E$12 -> 0.081048463 | G18: =53358.4*6 -> 320150.4 | H18: =G18/$G$12 -> 0.10085701
B19: Direct Labor - Other | C19: =SUM(E19,G19) -> 0 | D19: =C19/$C$12 -> 0 | E19: 0 | F19: =E19/$E$12 -> 0 | H19: =G19/$G$12 -> 0
B20: Direct Management Labor Cost | C20: =SUM(E20,G20) -> 0 | D20: =C20/$C$12 -> 0 | E20: 0 | F20: =E20/$E$12 -> 0 | H20: =G20/$G$12 -> 0
B21: Total Direct Labor | C21: =SUM(C16:C20) -> 2384796.4 | D21: =C21/$C$12 -> 0.4807093 | E21: =SUM(E16:E20) -> 724044.45 | F21: =E21/$E$12 -> 0.40524231 | G21: =SUM(G16:G20) -> 1660752 | H21: =G21/$G$12 -> 0.52318684 | I21: =(41000-22000)*4 -> 76000 | J21: =E21/12 -> 60337.037
B22: Gross Profit Margin (CM1) | C22: =C12-C15-C21 -> 1145546.2 | D22: =C22/$C$12 -> 0.23091057 | E22: =E12-E15-E21 -> 390236.22 | F22: =E22/$E$12 -> 0.21841232 | G22: =G12-G15-G21 -> 755310 | H22: =G22/$G$12 -> 0.23794537
J23: SAS Avg. Revenue Per Flight | N23: ='Summary '!H18 -> 4908.503
B24: Indirect Management Labor Cost | C24: =SUM(E24,G24) -> 551988.29 | D24: =C24/$C$12 -> 0.11126564 | F24: =E24/E12 -> 0 | G24: =91998.048*6 -> 551988.29 | H24: =G24/$G$12 -> 0.17389292 | J24: A
B25: Indirect Hourly Labor Cost | C25: =SUM(E25,G25) -> 0 | D25: =C25/$C$12 -> 0 | E25: 0 | F25: =E25/$E$12 -> 0 | H25: =G25/$G$12 -> 0 | J25: FC | K25: BC | L25: PY | M25: EY | N25: TC | O25: CY
B26: Total Indirect Labor | C26: =SUM(C24:C25) -> 551988.29 | D26: =C26/$C$12 -> 0.11126564 | E26: =SUM(E24:E25) -> 0 | F26: =E26/$E$12 -> 0 | G26: =SUM(G24:G25) -> 551988.29 | H26: =G26/$G$12 -> 0.17389292 | J26: ='Summary '!B28 -> 0 | K26: ='Summary '!C28 -> 37.008577 | L26: ='Summary '!D28 -> 24.716885 | M26: ='Summary '!E28 -> 13.422623 | N26: ='Summary '!F28 -> 20.841802 | O26: ='Summary '!G28 -> 21.896664
B27: Operating Expense-Variable | C27: =SUM(E27,G27) -> 930840 | D27: =C27/$C$12 -> 0.18763171 | E27: =G27/10+270000/3 -> 166440 | F27: =E27/E12 -> 0.093155235 | G27: =63700*12 -> 764400 | H27: =G27/$G$12 -> 0.240809 | I27: =E27/12 -> 13870 | K27: 40 | L27: 22 | M27: 15
B28: Operating Expense-Fixed | C28: =SUM(E28,G28) -> 0 | D28: =C28/$C$12 -> 0 | F28: 0 | H28: =G28/$G$12 -> 0 | J28: Overhead
B29: Other OPEX Cost | C29: =SUM(C27:C28) -> 930840 | D29: =C29/$C$12 -> 0.18763171 | E29: =SUM(E27:E28) -> 166440 | F29: =E29/E12 -> 0.093155235 | G29: =SUM(G27:G28) -> 764400 | H29: =G29/$G$12 -> 0.240809 | J29: FC | K29: BC | L29: PY | M29: YC | N29: TC | O29: CC
B30: EBITDA | C30: =C22-C26-C29 -> -337282.07 | D30: =C30/$C$12 -> -0.067986777 | E30: =E22-E26-E29 -> 223796.22 | F30: =E30/$E$12 -> 0.12525709 | G30: =G22-G26-G29 -> -561078.29 | H30: =G30/$G$12 -> -0.17675654 | I30: =E30/12 -> 18649.685 | J30: 0 | K30: 4 | L30: 3 | M30: 2.5 | N30: 3 | O30: 3
B32: Note - On the P&L we can update the Flights per week, AC type, Load Factor, Cycle & Mark up's | L32: =35.12*27+21.27*48+10.99*148+29*2+20*8+670+220 -> 4703.72
K33: =K27*32 -> 1280 | L33: =22*53 -> 1166 | M33: =M27*176 -> 2640
G36: =180000*12 -> 2160000
G37: =G16+G24+G18 -> 2212740.3
G38: Refrigrated truck $270,000

Sheet Bid Assumption 
A1: Bid Fact Sheet
A2: Airline Name | B2: NEOS
A3: City Code and Unit Number | B3: JFK
A4: Date Bid Preparation Begins
A5: Period used for Annualization
A6: Access Fee %
A7: Trade Discount %
A8: Cash Discount %
A9: Start Up Date
A12: Aircraft Type | B12: 787
A13: Configuration: First Class | B13: =+FlightConfig!B3 -> 0
A14: Business Class | B14: =+FlightConfig!C3 -> 32
A15: Tourist Class | B15: =SUM(FlightConfig!D3:E3) -> 230
A16: ETA | B16: 0.26736111
A17: ETD | B17: 0.93402778
A18: Frequency (days of operations) | B18: =+FlightConfig!K2 -> 7
A19: Total No. of Flights per Year | B19: =+FlightConfig!K3 -> 364
A20: Load Factor %
A21: Source of Load Factor | B21: Flight Config
A22: Account Rep. | B22: Kathy Shi
A23: Reason For Bid | B23: New Unit | E23: Food Markup
A24: Incumbent | E24: Ancillary Markup
A25: New or Old Route | B25: New | E25: Service Markup
A26: Credit Established/Payment Status
A27: Was Account Previously Bid | E27: Overhead Recovery per Pax F/C
A28: Outcome | E28: Overhead Recovery per Pax B/C
A29: Is there a Global Agreement | E29: Overhead Recovery per Pax E/U
A30: Date Building Lease expires | E30: Overhead Recovery per Pax Y/C
E31: Overhead Recovery per Pax C/Y
E32: Overhead Recovery per Pax C/C
A33: Investment | B33: Amount | C33: No. Years | D33: $ per Year | E33: Overhead Recovery per Pax T/C
A34: Building | C34: 0 | D34: =+B34/C34 -> #DIV/0!
A35: Land | C35: N/A | D35: N/A
A36: Building - Leasehold Improvements | C36: 0 | D36: =+B36/C36 -> #DIV/0!
A37: Trucks - Highlifts | C37: 0 | D37: =+B37/C37 -> #DIV/0!
A38: Trucks - Vans/Utility Vehicles | C38: 0 | D38: =+B38/C38 -> #DIV/0!
A39: Equipment | C39: 0 | D39: =+B39/C39 -> #DIV/0!
A40: Rent of Property | C40: 0 | D40: =+B40/C40 -> #DIV/0!
A42: Other Cities that Dnata serves this Customer and Discounts applied:
A43: SFO
A47: Pricing Assumptions:
A48: Methodology: fc+lc+mu=sp
A49: Contract length:
A50: # of Trucks/price - ea:
A51: # of Vans/Utility Vehicles/price - ea:
A52: Equipment descriptions:

Sheet Summary 
A2: Customer | G2: Flights Per week | H2: =FlightConfig!K16 -> 7 | L2: AC type | M2: Cycle
E3: AC Type | F3: 737 | G3: Flights Per Month | H3: =H4/2 -> 182 | J3: Total Revenues | L3: 330 | M3: 1
E4: Load | F4: ='P&L'!P4 -> 0.8 | G4: Annual Flights | H4: =FlightConfig!K3 -> 364 | J4: =H18*H4 -> 1786695.1 | M4: 2
A5: Summary | M5: 3
A6: BNA | B6: FC | C6: BC | D6: PY | E6: EY | F6: TC | G6: CY | H6: Total | I6: Hnd
A7: FLIGHT CONFIG | B7: =+FlightConfig!B17 -> 0 | C7: =+FlightConfig!C17 -> 32 | D7: =+FlightConfig!D17 -> 56 | E7: =+FlightConfig!E17 -> 174 | F7: =+FlightConfig!F17 -> 2 | G7: =+FlightConfig!G17 -> 8 | H7: =SUM(B7:G7) -> 272
A8: Load Factor | B8: =ROUNDUP(B7*$F$4,0) -> 0 | C8: =ROUNDUP(C7*$F$4,0) -> 26 | D8: =ROUNDUP(D7*$F$4,0) -> 45 | E8: =ROUNDUP(E7*$F$4,0) -> 140 | F8: =ROUNDUP(F7*$F$4,0) -> 2 | G8: =ROUNDUP(G7*$F$4,0) -> 7 | H8: =SUM(B8:G8) -> 220
B9: FIRST CLASS | C9: BUSINESS CLASS | D9: PREMIUM ECONOMY CLASS | E9: ECONOMY CLASS | F9: TECH CREW CLASS | G9: cABIN CREW CLASS | H9: Per Flight | J9: Annual
A10: OVERHEAD | B10: =Summary!B10 -> 0 | C10: =Summary!C10 -> 104 | D10: =Summary!D10 -> 135 | E10: =Summary!E10 -> 350 | F10: =Summary!F10 -> 6 | G10: =Summary!G10 -> 21 | H10: =SUM(B10:G10) -> 616 | J10: =H10*$H$4 -> 224224
A11: Food Cost (DM) | B11: =Summary!B11 -> 0 | C11: =Summary!C11 -> 479.5082 | D11: =Summary!D11 -> 549.19246 | E11: =Summary!E11 -> 708.7566 | F11: =Summary!F11 -> 21.93841 | G11: =Summary!G11 -> 87.89665 | H11: =SUM(B11:G11) -> 1847.2923 | J11: =H11*$H$4 -> 672414.41
A12: Wage Cost (DL) | B12: =Summary!B12 -> 0 | C12: =Summary!C12 -> 274.2675 | D12: =Summary!D12 -> 325.83214 | E12: =Summary!E12 -> 619.93287 | F12: =Summary!F12 -> 9.64 | G12: =Summary!G12 -> 44.38 | H12: =SUM(B12:G12) -> 1274.0525 | J12: =H12*$H$4 -> 463755.12
A13: Food Mark up | B13: =Summary!B13 | C13: =Summary!C13 -> 68.792523 | D13: =Summary!D13 -> 59.877061 | E13: =Summary!E13 -> 107.64987 | F13: =Summary!F13 -> 2.8519933 | G13: =Summary!G13 -> 0 | H13: =SUM(B13:G13) -> 239.17145 | J13: =H13*$H$4 -> 87058.406
A14: Labor Mark up | B14: =Summary!B14 | C14: =Summary!C14 -> 35.654775 | D14: =Summary!D14 -> 42.358179 | E14: =Summary!E14 -> 92.827917 | F14: =Summary!F14 -> 1.2532 | G14: =Summary!G14 -> 0 | H14: =SUM(B14:G14) -> 172.09407 | J14: =H14*$H$4 -> 62642.242
A15: Extra Revenue/Loss | B15: =IFERROR(B46*$E$8,0) -> 0 | C15: =IFERROR(C47*C$8,0) -> 0 | D15: =IFERROR(D47*D$8,0) -> 0 | E15: =IFERROR(E47*E$8,0) -> 0 | F15: =IFERROR(F47*F$8,0) -> 0 | G15: =IFERROR(G47*G$8,0) -> 0 | H15: =SUM(B15:G15) -> 0 | J15: =H15*$H$4 -> 0 | L15: Direct Labour
A16: Handling Cost | B16: =Summary!B15 -> 0 | C16: =Summary!C15 -> 0 | D16: =Summary!D15 -> 0 | E16: =Summary!E15 -> 715.08058 | F16: =Summary!F15 -> 0 | G16: =Summary!G15 -> 0 | H16: =SUM(B16:G16) -> 715.08058 | J16: =H16*$H$4 -> 260289.33 | L16: =J12+J16 -> 724044.45 | M16: 1
A17: Handling Mark up | B17: =Summary!B16 -> 0 | C17: =Summary!C16 -> 0 | D17: =Summary!D16 -> 0 | E17: =Summary!E16+C26 -> 44.812011 | F17: =Summary!F16 -> 0 | G17: =Summary!G16 -> 0 | H17: =SUM(B17:G17) -> 44.812011 | J17: =H17*$H$4 -> 16311.572 | L17: =L16*M17 -> 579235.56 | M17: 0.8
A18: Total Per Flight | B18: =SUM(B11:B17) -> 0 | C18: =SUM(C11:C17) -> 858.223 | D18: =SUM(D10:D17) -> 1112.2598 | E18: =SUM(E10:E17) -> 2639.0599 | F18: =SUM(F10:F17) -> 41.683603 | G18: =SUM(G10:G17) -> 153.27665 | H18: =SUM(H10:H17) -> 4908.503 | I18: 862832.68 | J18: =SUM(J10:J17) -> 1786695.1 | L18: =L16*M18 -> 144808.89 | M18: 0.2
B19: =B18 -> 0 | C19: =C18 -> 858.223 | D19: =D18 -> 1112.2598 | E19: =E18-E16-E17 -> 1879.1673 | F19: =F18 -> 41.683603 | G19: =G18 -> 153.27665 | I19: =E16+E17 -> 759.89259
A20: Handling | B20: Cost | C20: Mark Up | D20: Price | I20: =E17 -> 44.812011
A21: 330 Handling | B21: =Handling!C22 -> 515.08058 | C21: =Handling!C23 -> 44.812011 | D21: =SUM(B21:C21) -> 559.89259
A22: B777 Handling | B22: =Handling!#REF! -> #REF! | C22: =Handling!#REF! -> #REF! | D22: =Handling!#REF! -> #REF!
A23: A380 Handling | B23: =Handling!#REF! -> #REF! | C23: =Handling!#REF! -> #REF! | D23: =Handling!#REF! -> #REF!
A25: TRASH REMOVACL | B25: Cost | C25: Mark Up | D25: Price | I25: =E21 -> 0
A26: 330 | B26: =Handling!C26 -> 200 | C26: =B26*'P&L'!$P$11 -> 0 | D26: =SUM(B26:C26) -> 200
A28: Avg Price Per Pax | B28: =IFERROR(((B11+B12+B13+B14)/B8),0) -> 0 | C28: =IFERROR(((+C10+C11+C12+C13+C14)/C8),0) -> 37.008577 | D28: =IFERROR(((D10+D11+D12+D13+D14)/D8),0) -> 24.716885 | E28: =IFERROR(((E10+E11+E12+E13+E14)/E8),0) -> 13.422623 | F28: =IFERROR(((F10+F11+F12+F13+F14)/F8),0) -> 20.841802 | G28: =IFERROR(((G10+G11+G12+G13+G14)/G8),0) -> 21.896664
A29: Avg Mark up Per Pax | B29: =IFERROR(((B13+B14)/B8),0) -> 0 | C29: =IFERROR(((C13+C14)/C8),0) -> 4.0172038 | D29: =IFERROR(((D13+D14)/D8),0) -> 2.2718942 | E29: =IFERROR(((E13+E14)/E8),0) -> 1.4319842 | F29: =IFERROR(((F13+F14)/F8),0) -> 2.0525966 | G29: =IFERROR(((G13+G14)/G8),0) -> 0
A30: Over head Per Pax | B30: =IFERROR((B10/B8),0) -> 0 | C30: =IFERROR((C10/C8),0) -> 4 | D30: =IFERROR((D10/D8),0) -> 3 | E30: =IFERROR((E10/E8),0) -> 2.5 | F30: =IFERROR((F10/F8),0) -> 3 | G30: =IFERROR((G10/G8),0) -> 3
B32: CYCLE | C32: FLT
A33: Config | B33: =Summary!B34 -> 3
A34: OVERHEAD | B34: =B42*B8 -> 0 | C34: =C42*C8 -> 104 | D34: =D42*D8 -> 135 | E34: =E42*E8 -> 350 | F34: =F42*F8 -> 6 | G34: =G42*G8 -> 21
A35: Food Cost (DM) | B35: =Summary!B36 -> 0 | C35: =Summary!C36 -> 590.16394 | D35: =Summary!D36 -> 683.43951 | E35: =Summary!E36 -> 880.88321 | F35: =Summary!F36 -> 21.93841 | G35: =Summary!G36 -> 100.45331
A36: Wage Cost (DL) | B36: =Summary!B37 -> 0 | C36: =Summary!C37 -> 337.56 | D36: =Summary!D37 -> 405.48 | E36: =Summary!E37 -> 770.488 | F36: =Summary!F37 -> 9.64 | G36: =Summary!G37 -> 50.72
A37: Markup Food | B37: =Summary!B38 -> 0 | C37: =Summary!C38 -> 84.66772 | D37: =Summary!D38 -> 74.513676 | E37: =Summary!E38 -> 133.79341 | F37: =Summary!F38 -> 2.8519933 | G37: =Summary!G38 -> 2.3732394
A38: Markup Labor | B38: =Summary!B39 -> 0 | C38: =Summary!C39 -> 43.8828 | D38: =Summary!D39 -> 52.7124 | E38: =Summary!E39 -> 115.37184 | F38: =Summary!F39 -> 1.2532 | G38: =Summary!G39 -> 1.3312
A39: Extra Profit or Loss | B39: =Summary!B40 -> 0 | C39: =Summary!C40 | D39: =Summary!D40 | E39: =Summary!E40 | F39: =Summary!F40 | G39: =Summary!G40
A41: Per Pax Avg
A42: OVERHEAD | B42: ='P&L'!$J$30 -> 0 | C42: ='P&L'!$K$30 -> 4 | D42: ='P&L'!$L$30 -> 3 | E42: ='P&L'!$M$30 -> 2.5 | F42: ='P&L'!$N$30 -> 3 | G42: ='P&L'!$O$30 -> 3
A43: Food Cost (DM) | B43: =IFERROR(B35/B7," ") | C43: =IFERROR(C35/C7," ") -> 18.442623 | D43: =IFERROR(D35/D7," ") -> 12.204277 | E43: =IFERROR(E35/E7," ") -> 5.0625472 | F43: =IFERROR(F35/F7," ") -> 10.969205 | G43: =IFERROR(G35/G7," ") -> 12.556664
A44: Wage Cost (DL) | B44: =IFERROR(B36/B7," ") | C44: =IFERROR(C36/C7," ") -> 10.54875 | D44: =IFERROR(D36/D7," ") -> 7.2407143 | E44: =IFERROR(E36/E7," ") -> 4.428092 | F44: =IFERROR(F36/F7," ") -> 4.82 | G44: =IFERROR(G36/G7," ") -> 6.34
A45: Markup Food | B45: =IFERROR(B37/B8," ") | C45: =IFERROR(C37/C7," ") -> 2.6458663 | D45: =IFERROR(D37/D7," ") -> 1.3306014 | E45: =IFERROR(E37/E7," ") -> 0.76892763 | F45: =IFERROR(F37/F7," ") -> 1.4259966 | G45: =IFERROR(G37/G7," ") -> 0.29665492
A46: Markup Labor | B46: =IFERROR(B38/B7," ") | C46: =IFERROR(C38/C7," ") -> 1.3713375 | D46: =IFERROR(D38/D7," ") -> 0.94129286 | E46: =IFERROR(E38/E7," ") -> 0.66305655 | F46: =IFERROR(F38/F7," ") -> 0.6266 | G46: =IFERROR(G38/G7," ") -> 0.1664
A47: Extra Profit or Loss | B47: =IFERROR(B39/B8," ") | C47: =IFERROR(C39/C8," ") | D47: =IFERROR(D39/D8," ") | E47: =IFERROR(E39/E8," ") | F47: =IFERROR(F39/F8," ") | G47: =IFERROR(G39/G8," ")
A114: 388
A115: 787

Sheet Summary Short Haul
A2: Customer | G2: Flights Per week | H2: ='Summary 735'!H2+'Summary 2221'!H2+'Summary 2439'!H2+'Summary 2682'!H2+'Summary 2855'!H2 -> 0 | L2: AC type | M2: Cycle
E3: AC Type | F3: 737 | G3: Flights Per Month | H3: =H4/12 -> 0 | J3: Total Revenues | L3: 737 | M3: 1
E4: Load | F4: ='P&L'!P4 -> 0.8 | G4: Annual Flights | H4: =H2*52 -> 0 | J4: =H17*H4 -> #REF!
A5: Summary
A6: BNA | B6: FC | C6: BC | D6: PY | E6: EY | F6: TC | G6: CY | H6: Total | I6: Hnd
A7: FLIGHT CONFIG | B7: =+FlightConfig!B17 -> 0 | C7: =+FlightConfig!C17 -> 32 | D7: =+FlightConfig!D17 -> 56 | E7: =+FlightConfig!E17 -> 174 | F7: =+FlightConfig!F17 -> 2 | G7: =+FlightConfig!G17 -> 8 | H7: =SUM(B7:G7) -> 272
A8: Load Factor | B8: =ROUNDUP(B7*$F$4,0) -> 0 | C8: =ROUNDUP(C7*$F$4,0) -> 26 | D8: =ROUNDUP(D7*$F$4,0) -> 45 | E8: =ROUNDUP(E7*$F$4,0) -> 140 | F8: =ROUNDUP(F7*$F$4,0) -> 2 | G8: =ROUNDUP(G7*$F$4,0) -> 7 | H8: =SUM(B8:G8) -> 220
B9: FIRST CLASS | C9: BUSINESS CLASS | D9: PREMIUM ECONOMY CLASS | E9: ECONOMY CLASS | F9: TECH CREW CLASS | G9: cABIN CREW CLASS | H9: Per Flight | J9: Annual
A10: OVERHEAD | B10: =B37*B8 -> 0 | C10: =('Summary 735'!C10+'Summary 2221'!C10+'Summary 2439'!C10+'Summary 2682'!C10+'Summary 2855'!C10+Summary!C10+#REF!+#REF!+#REF!+#REF!+#REF!+'Summary 2037'!C10+'Summary 2817'!C10)/13 -> #REF! | D10: =('Summary 735'!D10+'Summary 2221'!D10+'Summary 2439'!D10+'Summary 2682'!D10+'Summary 2855'!D10+Summary!D10+#REF!+#REF!+#REF!+#REF!+#REF!+'Summary 2037'!D10+'Summary 2817'!D10)/13 -> #REF! | E10: =('Summary 735'!E10+'Summary 2221'!E10+'Summary 2439'!E10+'Summary 2682'!E10+'Summary 2855'!E10+Summary!E10+#REF!+#REF!+#REF!+#REF!+#REF!+'Summary 2037'!E10+'Summary 2817'!E10)/13 -> #REF! | F10: =('Summary 735'!F10+'Summary 2221'!F10+'Summary 2439'!F10+'Summary 2682'!F10+'Summary 2855'!F10+Summary!F10+#REF!+#REF!+#REF!+#REF!+#REF!+'Summary 2037'!F10+'Summary 2817'!F10)/13 -> #REF! | G10: =('Summary 735'!G10+'Summary 2221'!G10+'Summary 2439'!G10+'Summary 2682'!G10+'Summary 2855'!G10+Summary!G10+#REF!+#REF!+#REF!+#REF!+#REF!+'Summary 2037'!G10+'Summary 2817'!G10)/13 -> #REF! | H10: =SUM(B10:G10) -> #REF! | J10: =H10*$H$4 -> #REF!
A11: Food Cost (DM) | B11: =('Summary 735'!B11+'Summary 2221'!B11+'Summary 2439'!B11+'Summary 2682'!B11+'Summary 2855'!B11)/5 -> 0 | C11: =('Summary 735'!C11+'Summary 2221'!C11+'Summary 2439'!C11+'Summary 2682'!C11+'Summary 2855'!C11)/5 -> 0 | D11: =('Summary 735'!D11+'Summary 2221'!D11+'Summary 2439'!D11+'Summary 2682'!D11+'Summary 2855'!D11)/5 -> 0 | E11: =('Summary 735'!E11+'Summary 2221'!E11+'Summary 2439'!E11+'Summary 2682'!E11+'Summary 2855'!E11)/5 -> 0 | F11: =('Summary 735'!F11+'Summary 2221'!F11+'Summary 2439'!F11+'Summary 2682'!F11+'Summary 2855'!F11)/5 -> 0 | G11: =('Summary 735'!G11+'Summary 2221'!G11+'Summary 2439'!G11+'Summary 2682'!G11+'Summary 2855'!G11)/5 -> 0 | H11: =SUM(B11:G11) -> 0 | I11: =I12*45% -> #REF! | J11: =H11*$H$4 -> 0
A12: Wage Cost (DL) | B12: =('Summary 735'!B12+'Summary 2221'!B12+'Summary 2439'!B12+'Summary 2682'!B12+'Summary 2855'!B12+Summary!B12+#REF!+#REF!+#REF!+#REF!+#REF!+'Summary 2037'!B12+'Summary 2817'!B12)/13 -> #REF! | C12: =('Summary 735'!C12+'Summary 2221'!C12+'Summary 2439'!C12+'Summary 2682'!C12+'Summary 2855'!C12)/5 -> 0 | D12: =('Summary 735'!D12+'Summary 2221'!D12+'Summary 2439'!D12+'Summary 2682'!D12+'Summary 2855'!D12)/5 -> 0 | E12: =('Summary 735'!E12+'Summary 2221'!E12+'Summary 2439'!E12+'Summary 2682'!E12+'Summary 2855'!E12)/5 -> 0 | F12: =('Summary 735'!F12+'Summary 2221'!F12+'Summary 2439'!F12+'Summary 2682'!F12+'Summary 2855'!F12)/5 -> 0 | G12: =('Summary 735'!G12+'Summary 2221'!G12+'Summary 2439'!G12+'Summary 2682'!G12+'Summary 2855'!G12)/5 -> 0 | H12: =SUM(B12:G12) -> #REF! | I12: =H11+H12 -> #REF! | J12: =H12*$H$4 -> #REF!
A13: Food Mark up | B13: =('Summary 735'!B13+'Summary 2221'!B13+'Summary 2439'!B13+'Summary 2682'!B13+'Summary 2855'!B13+Summary!B13+#REF!+#REF!+#REF!+#REF!+#REF!+'Summary 2037'!B13+'Summary 2817'!B13)/13 -> #VALUE! | C13: =('Summary 735'!C13+'Summary 2221'!C13+'Summary 2439'!C13+'Summary 2682'!C13+'Summary 2855'!C13)/5 -> 0 | D13: =('Summary 735'!D13+'Summary 2221'!D13+'Summary 2439'!D13+'Summary 2682'!D13+'Summary 2855'!D13)/5 -> 0 | E13: =('Summary 735'!E13+'Summary 2221'!E13+'Summary 2439'!E13+'Summary 2682'!E13+'Summary 2855'!E13)/5 -> 0 | F13: =('Summary 735'!F13+'Summary 2221'!F13+'Summary 2439'!F13+'Summary 2682'!F13+'Summary 2855'!F13)/5 -> 0 | G13: =('Summary 735'!G13+'Summary 2221'!G13+'Summary 2439'!G13+'Summary 2682'!G13+'Summary 2855'!G13)/5 -> 0 | H13: =SUM(B13:G13) -> #VALUE! | J13: =H13*$H$4 -> #VALUE!
A14: Labor Mark up | B14: =('Summary 735'!B14+'Summary 2221'!B14+'Summary 2439'!B14+'Summary 2682'!B14+'Summary 2855'!B14+Summary!B14+#REF!+#REF!+#REF!+#REF!+#REF!+'Summary 2037'!B14+'Summary 2817'!B14)/13 -> #VALUE! | C14: =('Summary 735'!C14+'Summary 2221'!C14+'Summary 2439'!C14+'Summary 2682'!C14+'Summary 2855'!C14)/5 -> 0 | D14: =('Summary 735'!D14+'Summary 2221'!D14+'Summary 2439'!D14+'Summary 2682'!D14+'Summary 2855'!D14)/5 -> 0 | E14: =('Summary 735'!E14+'Summary 2221'!E14+'Summary 2439'!E14+'Summary 2682'!E14+'Summary 2855'!E14)/5 -> 0 | F14: =('Summary 735'!F14+'Summary 2221'!F14+'Summary 2439'!F14+'Summary 2682'!F14+'Summary 2855'!F14)/5 -> 0 | G14: =('Summary 735'!G14+'Summary 2221'!G14+'Summary 2439'!G14+'Summary 2682'!G14+'Summary 2855'!G14)/5 -> 0 | H14: =SUM(B14:G14) -> #VALUE! | J14: =H14*$H$4 -> #VALUE! | L14: Direct Labour
A15: Handling Cost | B15: =SUM('Summary 735'!B15+'Summary 2221'!B15+'Summary 2221'!B15+'Summary 2439'!B15+'Summary 2682'!B15+'Summary 2855'!B15+Summary!B15+#REF!+#REF!+#REF!+#REF!+#REF!+'Summary 2037'!B15+'Summary 2817'!B15)/13 -> #REF! | C15: =('Summary 735'!C15+'Summary 2221'!C15+'Summary 2439'!C15+'Summary 2682'!C15+'Summary 2855'!C15)/5 -> 0 | D15: =('Summary 735'!D15+'Summary 2221'!D15+'Summary 2439'!D15+'Summary 2682'!D15+'Summary 2855'!D15)/5 -> 0 | E15: =('Summary 735'!E15+'Summary 2221'!E15+'Summary 2439'!E15+'Summary 2682'!E15+'Summary 2855'!E15)/5 -> 0 | F15: =('Summary 735'!F15+'Summary 2221'!F15+'Summary 2439'!F15+'Summary 2682'!F15+'Summary 2855'!F15)/5 -> 0 | G15: =('Summary 735'!G15+'Summary 2221'!G15+'Summary 2439'!G15+'Summary 2682'!G15+'Summary 2855'!G15)/5 -> 0 | H15: =SUM(B15:G15) -> #REF! | J15: =H15*$H$4 -> #REF! | L15: =J12+J15 -> #REF! | M15: 1
A16: Handling Mark up | B16: =SUM('Summary 735'!B16+'Summary 2221'!B16+'Summary 2221'!B16+'Summary 2439'!B16+'Summary 2682'!B16+'Summary 2855'!B16+Summary!B16+#REF!+#REF!+#REF!+#REF!+#REF!+'Summary 2037'!B16+'Summary 2817'!B16)/13 -> #REF! | C16: =('Summary 735'!C16+'Summary 2221'!C16+'Summary 2439'!C16+'Summary 2682'!C16+'Summary 2855'!C16)/5 -> 0 | D16: =('Summary 735'!D16+'Summary 2221'!D16+'Summary 2439'!D16+'Summary 2682'!D16+'Summary 2855'!D16)/5 -> 0 | E16: =('Summary 735'!E16+'Summary 2221'!E16+'Summary 2439'!E16+'Summary 2682'!E16+'Summary 2855'!E16)/5 -> 0 | F16: =('Summary 735'!F16+'Summary 2221'!F16+'Summary 2439'!F16+'Summary 2682'!F16+'Summary 2855'!F16)/5 -> 0 | G16: =('Summary 735'!G16+'Summary 2221'!G16+'Summary 2439'!G16+'Summary 2682'!G16+'Summary 2855'!G16)/5 -> 0 | H16: =SUM(B16:G16) -> #REF! | J16: =H16*$H$4 -> #REF! | L16: =L15*M16 -> #REF! | M16: 0.8
A17: Total Per Flight | B17: =SUM(B11:B16) -> #REF! | C17: =SUM(C11:C16) -> 0 | D17: =SUM(D10:D16) -> #REF! | E17: =SUM(E10:E16) -> #REF! | F17: =SUM(F10:F16) -> #REF! | G17: =SUM(G10:G16) -> #REF! | H17: =SUM(H10:H16) -> #REF! | J17: =H17*$H$4 -> #REF! | L17: =L15*M17 -> #REF! | M17: 0.2
B18: =B17 -> #REF! | C18: =C17 -> 0 | D18: =D17 -> #REF! | E18: =E17-E15-E16 -> #REF! | F18: =F17 -> #REF! | G18: =G17 -> #REF! | I18: =E15+E16 -> 0
A19: Handling | B19: Cost | C19: Mark Up | D19: Price | I19: =E16 -> 0
A20: 737 Handling | B20: =SUM('Summary 735'!B20+'Summary 2221'!B20+'Summary 2221'!B20+'Summary 2439'!B20+'Summary 2682'!B20+'Summary 2855'!B20+Summary!B21+#REF!+#REF!+#REF!+#REF!+#REF!+'Summary 2037'!B20+'Summary 2817'!B20)/13 -> #REF! | C20: =B20*'P&L'!$P$10 -> #REF! | D20: =SUM(B20:C20) -> #REF!
A21: B777 Handling | B21: =Handling!#REF! -> #REF! | C21: =Handling!#REF! -> #REF! | D21: =Handling!#REF! -> #REF!
A22: A380 Handling | B22: =Handling!#REF! -> #REF! | C22: =Handling!#REF! -> #REF! | D22: =Handling!#REF! -> #REF!
A24: Avg Price Per Pax | B24: =IFERROR(((B11+B12+B13+B14)/B8),0) -> 0 | C24: =IFERROR(((C11+C12+C13+C14)/C8),0) -> 0 | D24: =IFERROR(((D10+D11+D12+D13+D14)/D8),0) -> 0 | E24: =IFERROR(((E10+E11+E12+E13+E14)/E8),0) -> 0 | F24: =IFERROR(((F10+F11+F12+F13+F14)/F8),0) -> 0 | G24: =IFERROR(((G10+G11+G12+G13+G14)/G8),0) -> 0
A25: Avg Mark up Per Pax | B25: =IFERROR(((B13+B14)/B8),0) -> 0 | C25: =IFERROR(((C13+C14)/C8),0) -> 0 | D25: =IFERROR(((D13+D14)/D8),0) -> 0 | E25: =IFERROR(((E13+E14)/E8),0) -> 0 | F25: =IFERROR(((F13+F14)/F8),0) -> 0 | G25: =IFERROR(((G13+G14)/G8),0) -> 0
A26: Over head Per Pax | B26: =IFERROR((B10/B8),0) -> 0 | C26: =IFERROR((C10/C8),0) -> 0 | D26: =IFERROR((D10/D8),0) -> 0 | E26: =IFERROR((E10/E8),0) -> 0 | F26: =IFERROR((F10/F8),0) -> 0 | G26: =IFERROR((G10/G8),0) -> 0
B28: CYCLE | C28: FLT
A29: Config | B29: ='P&L'!P5 -> 3
A30: OVERHEAD | B30: =B37*B8 -> 0 | C30: =C37*C8 -> 104 | D30: =D37*D8 -> 135 | E30: =E37*E8 -> 350 | F30: =F37*F8 -> 6 | G30: =G37*G8 -> 21
A31: Food Cost (DM) | B31: =('Summary 735'!B31+'Summary 2221'!B31+'Summary 2439'!B31+'Summary 2682'!B31+'Summary 2855'!B31)/5 -> 0 | C31: =('Summary 735'!C31+'Summary 2221'!C31+'Summary 2439'!C31+'Summary 2682'!C31+'Summary 2855'!C31+Summary!C36+#REF!+#REF!+#REF!+#REF!+#REF!+'Summary 2037'!C31+'Summary 2817'!C31)/13 -> #REF! | D31: =('Summary 735'!D31+'Summary 2221'!D31+'Summary 2439'!D31+'Summary 2682'!D31+'Summary 2855'!D31+Summary!D36+#REF!+#REF!+#REF!+#REF!+#REF!+'Summary 2037'!D31+'Summary 2817'!D31)/13 -> #REF! | E31: =('Summary 735'!E31+'Summary 2221'!E31+'Summary 2439'!E31+'Summary 2682'!E31+'Summary 2855'!E31)/5 -> 0 | F31: =('Summary 735'!F31+'Summary 2221'!F31+'Summary 2439'!F31+'Summary 2682'!F31+'Summary 2855'!F31+Summary!F36+#REF!+#REF!+#REF!+#REF!+#REF!+'Summary 2037'!F31+'Summary 2817'!F31)/13 -> #REF! | G31: =('Summary 735'!G31+'Summary 2221'!G31+'Summary 2439'!G31+'Summary 2682'!G31+'Summary 2855'!G31+Summary!G36+#REF!+#REF!+#REF!+#REF!+#REF!+'Summary 2037'!G31+'Summary 2817'!G31)/13 -> #REF!
A32: Wage Cost (DL) | B32: =('Summary 735'!B32+'Summary 2221'!B32+'Summary 2439'!B32+'Summary 2682'!B32+'Summary 2855'!B32)/5 -> 0 | C32: =('Summary 735'!C32+'Summary 2221'!C32+'Summary 2439'!C32+'Summary 2682'!C32+'Summary 2855'!C32+Summary!C37+#REF!+#REF!+#REF!+#REF!+#REF!+'Summary 2037'!C32+'Summary 2817'!C32)/13 -> #REF! | D32: =('Summary 735'!D32+'Summary 2221'!D32+'Summary 2439'!D32+'Summary 2682'!D32+'Summary 2855'!D32+Summary!D37+#REF!+#REF!+#REF!+#REF!+#REF!+'Summary 2037'!D32+'Summary 2817'!D32)/13 -> #REF! | E32: =('Summary 735'!E32+'Summary 2221'!E32+'Summary 2439'!E32+'Summary 2682'!E32+'Summary 2855'!E32)/5 -> 0 | F32: =('Summary 735'!F32+'Summary 2221'!F32+'Summary 2439'!F32+'Summary 2682'!F32+'Summary 2855'!F32+Summary!F37+#REF!+#REF!+#REF!+#REF!+#REF!+'Summary 2037'!F32+'Summary 2817'!F32)/13 -> #REF! | G32: =('Summary 735'!G32+'Summary 2221'!G32+'Summary 2439'!G32+'Summary 2682'!G32+'Summary 2855'!G32+Summary!G37+#REF!+#REF!+#REF!+#REF!+#REF!+'Summary 2037'!G32+'Summary 2817'!G32)/13 -> #REF!
A33: Markup Food | B33: =('Summary 735'!B33+'Summary 2221'!B33+'Summary 2439'!B33+'Summary 2682'!B33+'Summary 2855'!B33)/5 -> 0 | C33: =('Summary 735'!C33+'Summary 2221'!C33+'Summary 2439'!C33+'Summary 2682'!C33+'Summary 2855'!C33+Summary!C38+#REF!+#REF!+#REF!+#REF!+#REF!+'Summary 2037'!C33+'Summary 2817'!C33)/13 -> #REF! | D33: =('Summary 735'!D33+'Summary 2221'!D33+'Summary 2439'!D33+'Summary 2682'!D33+'Summary 2855'!D33+Summary!D38+#REF!+#REF!+#REF!+#REF!+#REF!+'Summary 2037'!D33+'Summary 2817'!D33)/13 -> #REF! | E33: =('Summary 735'!E33+'Summary 2221'!E33+'Summary 2439'!E33+'Summary 2682'!E33+'Summary 2855'!E33)/5 -> 0 | F33: =('Summary 735'!F33+'Summary 2221'!F33+'Summary 2439'!F33+'Summary 2682'!F33+'Summary 2855'!F33+Summary!F38+#REF!+#REF!+#REF!+#REF!+#REF!+'Summary 2037'!F33+'Summary 2817'!F33)/13 -> #REF! | G33: =('Summary 735'!G33+'Summary 2221'!G33+'Summary 2439'!G33+'Summary 2682'!G33+'Summary 2855'!G33+Summary!G38+#REF!+#REF!+#REF!+#REF!+#REF!+'Summary 2037'!G33+'Summary 2817'!G33)/13 -> #REF!
A34: Markup Labor | B34: =('Summary 735'!B34+'Summary 2221'!B34+'Summary 2439'!B34+'Summary 2682'!B34+'Summary 2855'!B34)/5 -> 0 | C34: =('Summary 735'!C34+'Summary 2221'!C34+'Summary 2439'!C34+'Summary 2682'!C34+'Summary 2855'!C34+Summary!C39+#REF!+#REF!+#REF!+#REF!+#REF!+'Summary 2037'!C34+'Summary 2817'!C34)/13 -> #REF! | D34: =('Summary 735'!D34+'Summary 2221'!D34+'Summary 2439'!D34+'Summary 2682'!D34+'Summary 2855'!D34+Summary!D39+#REF!+#REF!+#REF!+#REF!+#REF!+'Summary 2037'!D34+'Summary 2817'!D34)/13 -> #REF! | E34: =('Summary 735'!E34+'Summary 2221'!E34+'Summary 2439'!E34+'Summary 2682'!E34+'Summary 2855'!E34)/5 -> 0 | F34: =('Summary 735'!F34+'Summary 2221'!F34+'Summary 2439'!F34+'Summary 2682'!F34+'Summary 2855'!F34+Summary!F39+#REF!+#REF!+#REF!+#REF!+#REF!+'Summary 2037'!F34+'Summary 2817'!F34)/13 -> #REF! | G34: =('Summary 735'!G34+'Summary 2221'!G34+'Summary 2439'!G34+'Summary 2682'!G34+'Summary 2855'!G34+Summary!G39+#REF!+#REF!+#REF!+#REF!+#REF!+'Summary 2037'!G34+'Summary 2817'!G34)/13 -> #REF!
A36: Per Pax Avg
A37: OVERHEAD | B37: ='P&L'!$J$30 -> 0 | C37: ='P&L'!$K$30 -> 4 | D37: ='P&L'!$L$30 -> 3 | E37: ='P&L'!$M$30 -> 2.5 | F37: ='P&L'!$N$30 -> 3 | G37: ='P&L'!$O$30 -> 3
A38: Food Cost (DM) | B38: =IFERROR(B31/B7," ") | C38: =IFERROR(C31/C7," ") | D38: =IFERROR(D31/D7," ") | E38: =IFERROR(E31/E7," ") -> 0 | F38: =IFERROR(F31/F7," ") | G38: =IFERROR(G31/G7," ")
A39: Wage Cost (DL) | B39: =IFERROR(B32/B7," ") | C39: =IFERROR(C32/C7," ") | D39: =IFERROR(D32/D7," ") | E39: =IFERROR(E32/E7," ") -> 0 | F39: =IFERROR(F32/F7," ") | G39: =IFERROR(G32/G7," ")
A40: Markup Food | B40: =IFERROR(B33/B8," ") | C40: =IFERROR(C33/C7," ") | D40: =IFERROR(D33/D7," ") | E40: =IFERROR(E33/E7," ") -> 0 | F40: =IFERROR(F33/F7," ") | G40: =IFERROR(G33/G7," ")
A41: Markup Labor | B41: =IFERROR(B34/B7," ") | C41: =IFERROR(C34/C7," ") | D41: =IFERROR(D34/D7," ") | E41: =IFERROR(E34/E7," ") -> 0 | F41: =IFERROR(F34/F7," ") | G41: =IFERROR(G34/G7," ")
A108: 388
A109: 787

Sheet Summary Long Haul
A2: Customer | G2: Flights Per week | H2: =Summary!H2+#REF!+#REF!+#REF!+#REF!+#REF!+'Summary 2037'!H2+'Summary 2817'!H2 -> #REF! | L2: AC type | M2: Cycle
E3: AC Type | F3: 737 | G3: Flights Per Month | H3: =H4/12 -> #REF! | J3: Total Revenues | L3: 737 | M3: 1
E4: Load | F4: ='P&L'!P4 -> 0.8 | G4: Annual Flights | H4: =H2*52 -> #REF! | J4: =H17*H4 -> #REF!
A5: Summary
A6: BNA | B6: FC | C6: BC | D6: PY | E6: EY | F6: TC | G6: CY | H6: Total | I6: Hnd
A7: FLIGHT CONFIG | B7: =+FlightConfig!B17 -> 0 | C7: =+FlightConfig!C17 -> 32 | D7: =+FlightConfig!D17 -> 56 | E7: =+FlightConfig!E17 -> 174 | F7: =+FlightConfig!F17 -> 2 | G7: =+FlightConfig!G17 -> 8 | H7: =SUM(B7:G7) -> 272
A8: Load Factor | B8: =ROUNDUP(B7*$F$4,0) -> 0 | C8: =ROUNDUP(C7*$F$4,0) -> 26 | D8: =ROUNDUP(D7*$F$4,0) -> 45 | E8: =ROUNDUP(E7*$F$4,0) -> 140 | F8: =ROUNDUP(F7*$F$4,0) -> 2 | G8: =ROUNDUP(G7*$F$4,0) -> 7 | H8: =SUM(B8:G8) -> 220
B9: FIRST CLASS | C9: BUSINESS CLASS | D9: PREMIUM ECONOMY CLASS | E9: ECONOMY CLASS | F9: TECH CREW CLASS | G9: cABIN CREW CLASS | H9: Per Flight | J9: Annual
A10: OVERHEAD | B10: =(Summary!B10+#REF!+#REF!+#REF!+#REF!+#REF!)/6 -> #REF! | C10: =(Summary!C10+#REF!+#REF!+#REF!+#REF!+#REF!)/6 -> #REF! | D10: =(Summary!D10+#REF!+#REF!+#REF!+#REF!+#REF!)/6 -> #REF! | E10: =(Summary!E10+#REF!+#REF!+#REF!+#REF!+#REF!)/6 -> #REF! | F10: =(Summary!F10+#REF!+#REF!+#REF!+#REF!+#REF!)/6 -> #REF! | G10: =(Summary!G10+#REF!+#REF!+#REF!+#REF!+#REF!)/6 -> #REF! | H10: =(Summary!H10+#REF!+#REF!+#REF!+#REF!+#REF!)/6 -> #REF! | J10: =H10*$H$4 -> #REF!
A11: Food Cost (DM) | B11: =(Summary!B11+#REF!+#REF!+#REF!+#REF!+#REF!)/6 -> #REF! | C11: =(Summary!C11+#REF!+#REF!+#REF!+#REF!+#REF!)/6 -> #REF! | D11: =(Summary!D11+#REF!+#REF!+#REF!+#REF!+#REF!)/6 -> #REF! | E11: =(Summary!E11+#REF!+#REF!+#REF!+#REF!+#REF!)/6 -> #REF! | F11: =(Summary!F11+#REF!+#REF!+#REF!+#REF!+#REF!)/6 -> #REF! | G11: =(Summary!G11+#REF!+#REF!+#REF!+#REF!+#REF!)/6 -> #REF! | H11: =(Summary!H11+#REF!+#REF!+#REF!+#REF!+#REF!)/6 -> #REF! | I11: =I12*45% -> #REF! | J11: =H11*$H$4 -> #REF!
A12: Wage Cost (DL) | B12: =(Summary!B12+#REF!+#REF!+#REF!+#REF!+#REF!)/6 -> #REF! | C12: =(Summary!C12+#REF!+#REF!+#REF!+#REF!+#REF!)/6 -> #REF! | D12: =(Summary!D12+#REF!+#REF!+#REF!+#REF!+#REF!)/6 -> #REF! | E12: =(Summary!E12+#REF!+#REF!+#REF!+#REF!+#REF!)/6 -> #REF! | F12: =(Summary!F12+#REF!+#REF!+#REF!+#REF!+#REF!)/6 -> #REF! | G12: =(Summary!G12+#REF!+#REF!+#REF!+#REF!+#REF!)/6 -> #REF! | H12: =(Summary!H12+#REF!+#REF!+#REF!+#REF!+#REF!)/6 -> #REF! | I12: =H11+H12 -> #REF! | J12: =H12*$H$4 -> #REF!
A13: Food Mark up | B13: =(Summary!B13+#REF!+#REF!+#REF!+#REF!+#REF!)/6 -> #VALUE! | C13: =(Summary!C13+#REF!+#REF!+#REF!+#REF!+#REF!)/6 -> #REF! | D13: =(Summary!D13+#REF!+#REF!+#REF!+#REF!+#REF!)/6 -> #REF! | E13: =(Summary!E13+#REF!+#REF!+#REF!+#REF!+#REF!)/6 -> #REF! | F13: =(Summary!F13+#REF!+#REF!+#REF!+#REF!+#REF!)/6 -> #REF! | G13: =(Summary!G13+#REF!+#REF!+#REF!+#REF!+#REF!)/6 -> #REF! | H13: =(Summary!H13+#REF!+#REF!+#REF!+#REF!+#REF!)/6 -> #REF! | J13: =H13*$H$4 -> #REF!
A14: Labor Mark up | B14: =(Summary!B14+#REF!+#REF!+#REF!+#REF!+#REF!)/6 -> #VALUE! | C14: =(Summary!C14+#REF!+#REF!+#REF!+#REF!+#REF!)/6 -> #REF! | D14: =(Summary!D14+#REF!+#REF!+#REF!+#REF!+#REF!)/6 -> #REF! | E14: =(Summary!E14+#REF!+#REF!+#REF!+#REF!+#REF!)/6 -> #REF! | F14: =(Summary!F14+#REF!+#REF!+#REF!+#REF!+#REF!)/6 -> #REF! | G14: =(Summary!G14+#REF!+#REF!+#REF!+#REF!+#REF!)/6 -> #REF! | H14: =(Summary!H14+#REF!+#REF!+#REF!+#REF!+#REF!)/6 -> #REF! | J14: =H14*$H$4 -> #REF! | L14: Direct Labour
A15: Handling Cost | B15: =(Summary!B15+#REF!+#REF!+#REF!+#REF!+#REF!)/6 -> #REF! | C15: =(Summary!C15+#REF!+#REF!+#REF!+#REF!+#REF!)/6 -> #REF! | D15: =(Summary!D15+#REF!+#REF!+#REF!+#REF!+#REF!)/6 -> #REF! | E15: =(Summary!E15+#REF!+#REF!+#REF!+#REF!+#REF!)/6 -> #REF! | F15: =(Summary!F15+#REF!+#REF!+#REF!+#REF!+#REF!)/6 -> #REF! | G15: =(Summary!G15+#REF!+#REF!+#REF!+#REF!+#REF!)/6 -> #REF! | H15: =(Summary!H15+#REF!+#REF!+#REF!+#REF!+#REF!)/6 -> #REF! | J15: =H15*$H$4 -> #REF! | L15: =J12+J15 -> #REF! | M15: 1
A16: Handling Mark up | B16: =(Summary!B16+#REF!+#REF!+#REF!+#REF!+#REF!)/6 -> #REF! | C16: =(Summary!C16+#REF!+#REF!+#REF!+#REF!+#REF!)/6 -> #REF! | D16: =(Summary!D16+#REF!+#REF!+#REF!+#REF!+#REF!)/6 -> #REF! | E16: =(Summary!E16+#REF!+#REF!+#REF!+#REF!+#REF!)/6 -> #REF! | F16: =(Summary!F16+#REF!+#REF!+#REF!+#REF!+#REF!)/6 -> #REF! | G16: =(Summary!G16+#REF!+#REF!+#REF!+#REF!+#REF!)/6 -> #REF! | H16: =(Summary!H16+#REF!+#REF!+#REF!+#REF!+#REF!)/6 -> #REF! | J16: =H16*$H$4 -> #REF! | L16: =L15*M16 -> #REF! | M16: 0.8
A17: Total Per Flight | B17: =SUM(B11:B16) -> #REF! | C17: =SUM(C11:C16) -> #REF! | D17: =SUM(D10:D16) -> #REF! | E17: =SUM(E10:E16) -> #REF! | F17: =SUM(F10:F16) -> #REF! | G17: =SUM(G10:G16) -> #REF! | H17: =SUM(H10:H16) -> #REF! | J17: =H17*$H$4 -> #REF! | L17: =L15*M17 -> #REF! | M17: 0.2
B18: =B17 -> #REF! | C18: =C17 -> #REF! | D18: =D17 -> #REF! | E18: =E17-E15-E16 -> #REF! | F18: =F17 -> #REF! | G18: =G17 -> #REF! | I18: =E15+E16 -> #REF!
A19: Handling | B19: Cost | C19: Mark Up | D19: Price | I19: =E16 -> #REF!
A20: 737 Handling | B20: =(Summary!B21+#REF!+#REF!+#REF!+#REF!+#REF!+'Summary 2037'!B20+'Summary 2817'!B20)/8 -> #REF! | C20: =B20*'P&L'!$P$10 -> #REF! | D20: =SUM(B20:C20) -> #REF!
A21: B777 Handling | B21: =Handling!#REF! -> #REF! | C21: =Handling!#REF! -> #REF! | D21: =Handling!#REF! -> #REF!
A22: A380 Handling | B22: =Handling!#REF! -> #REF! | C22: =Handling!#REF! -> #REF! | D22: =Handling!#REF! -> #REF!
A24: Avg Price Per Pax | B24: =IFERROR(((B11+B12+B13+B14)/B8),0) -> 0 | C24: =IFERROR(((C11+C12+C13+C14)/C8),0) -> 0 | D24: =IFERROR(((D10+D11+D12+D13+D14)/D8),0) -> 0 | E24: =IFERROR(((E10+E11+E12+E13+E14)/E8),0) -> 0 | F24: =IFERROR(((F10+F11+F12+F13+F14)/F8),0) -> 0 | G24: =IFERROR(((G10+G11+G12+G13+G14)/G8),0) -> 0
A25: Avg Mark up Per Pax | B25: =IFERROR(((B13+B14)/B8),0) -> 0 | C25: =IFERROR(((C13+C14)/C8),0) -> 0 | D25: =IFERROR(((D13+D14)/D8),0) -> 0 | E25: =IFERROR(((E13+E14)/E8),0) -> 0 | F25: =IFERROR(((F13+F14)/F8),0) -> 0 | G25: =IFERROR(((G13+G14)/G8),0) -> 0
A26: Over head Per Pax | B26: =IFERROR((B10/B8),0) -> 0 | C26: =IFERROR((C10/C8),0) -> 0 | D26: =IFERROR((D10/D8),0) -> 0 | E26: =IFERROR((E10/E8),0) -> 0 | F26: =IFERROR((F10/F8),0) -> 0 | G26: =IFERROR((G10/G8),0) -> 0
B28: CYCLE | C28: FLT
A29: Config | B29: ='P&L'!P5 -> 3
A30: OVERHEAD | B30: =(Summary!B35+#REF!+#REF!+#REF!+#REF!+#REF!)/6 -> #REF! | C30: =(Summary!C35+#REF!+#REF!+#REF!+#REF!+#REF!)/6 -> #REF! | D30: =(Summary!D35+#REF!+#REF!+#REF!+#REF!+#REF!)/6 -> #REF! | E30: =(Summary!E35+#REF!+#REF!+#REF!+#REF!+#REF!)/6 -> #REF! | F30: =(Summary!F35+#REF!+#REF!+#REF!+#REF!+#REF!)/6 -> #REF! | G30: =(Summary!G35+#REF!+#REF!+#REF!+#REF!+#REF!)/6 -> #REF!
A31: Food Cost (DM) | B31: =(Summary!B36+#REF!+#REF!+#REF!+#REF!+#REF!)/6 -> #REF! | C31: =(Summary!C36+#REF!+#REF!+#REF!+#REF!+#REF!)/6 -> #REF! | D31: =(Summary!D36+#REF!+#REF!+#REF!+#REF!+#REF!)/6 -> #REF! | E31: =(Summary!E36+#REF!+#REF!+#REF!+#REF!+#REF!)/6 -> #REF! | F31: =(Summary!F36+#REF!+#REF!+#REF!+#REF!+#REF!)/6 -> #REF! | G31: =(Summary!G36+#REF!+#REF!+#REF!+#REF!+#REF!)/6 -> #REF!
A32: Wage Cost (DL) | B32: =(Summary!B37+#REF!+#REF!+#REF!+#REF!+#REF!)/6 -> #REF! | C32: =(Summary!C37+#REF!+#REF!+#REF!+#REF!+#REF!)/6 -> #REF! | D32: =(Summary!D37+#REF!+#REF!+#REF!+#REF!+#REF!)/6 -> #REF! | E32: =(Summary!E37+#REF!+#REF!+#REF!+#REF!+#REF!)/6 -> #REF! | F32: =(Summary!F37+#REF!+#REF!+#REF!+#REF!+#REF!)/6 -> #REF! | G32: =(Summary!G37+#REF!+#REF!+#REF!+#REF!+#REF!)/6 -> #REF!
A33: Markup Food | B33: =(Summary!B38+#REF!+#REF!+#REF!+#REF!+#REF!)/6 -> #REF! | C33: =(Summary!C38+#REF!+#REF!+#REF!+#REF!+#REF!)/6 -> #REF! | D33: =(Summary!D38+#REF!+#REF!+#REF!+#REF!+#REF!)/6 -> #REF! | E33: =(Summary!E38+#REF!+#REF!+#REF!+#REF!+#REF!)/6 -> #REF! | F33: =(Summary!F38+#REF!+#REF!+#REF!+#REF!+#REF!)/6 -> #REF! | G33: =(Summary!G38+#REF!+#REF!+#REF!+#REF!+#REF!)/6 -> #REF!
A34: Markup Labor | B34: =(Summary!B39+#REF!+#REF!+#REF!+#REF!+#REF!)/6 -> #REF! | C34: =(Summary!C39+#REF!+#REF!+#REF!+#REF!+#REF!)/6 -> #REF! | D34: =(Summary!D39+#REF!+#REF!+#REF!+#REF!+#REF!)/6 -> #REF! | E34: =(Summary!E39+#REF!+#REF!+#REF!+#REF!+#REF!)/6 -> #REF! | F34: =(Summary!F39+#REF!+#REF!+#REF!+#REF!+#REF!)/6 -> #REF! | G34: =(Summary!G39+#REF!+#REF!+#REF!+#REF!+#REF!)/6 -> #REF!
A36: Per Pax Avg
A37: OVERHEAD | B37: ='P&L'!$J$30 -> 0 | C37: ='P&L'!$K$30 -> 4 | D37: ='P&L'!$L$30 -> 3 | E37: ='P&L'!$M$30 -> 2.5 | F37: ='P&L'!$N$30 -> 3 | G37: ='P&L'!$O$30 -> 3
A38: Food Cost (DM) | B38: =IFERROR(B31/B7," ") | C38: =IFERROR(C31/C7," ") | D38: =IFERROR(D31/D7," ") | E38: =IFERROR(E31/E7," ") | F38: =IFERROR(F31/F7," ") | G38: =IFERROR(G31/G7," ")
A39: Wage Cost (DL) | B39: =IFERROR(B32/B7," ") | C39: =IFERROR(C32/C7," ") | D39: =IFERROR(D32/D7," ") | E39: =IFERROR(E32/E7," ") | F39: =IFERROR(F32/F7," ") | G39: =IFERROR(G32/G7," ")
A40: Markup Food | B40: =IFERROR(B33/B8," ") | C40: =IFERROR(C33/C7," ") | D40: =IFERROR(D33/D7," ") | E40: =IFERROR(E33/E7," ") | F40: =IFERROR(F33/F7," ") | G40: =IFERROR(G33/G7," ")
A41: Markup Labor | B41: =IFERROR(B34/B7," ") | C41: =IFERROR(C34/C7," ") | D41: =IFERROR(D34/D7," ") | E41: =IFERROR(E34/E7," ") | F41: =IFERROR(F34/F7," ") | G41: =IFERROR(G34/G7," ")
A108: 388
A109: 787

Sheet Summary  735
A2: Customer | G2: Flights Per week | H2: 0 | L2: AC type | M2: Cycle
E3: AC Type | F3: 738 | G3: Flights Per Month | H3: =H4/12 -> 0 | J3: Total Revenues | L3: 737 | M3: 1
E4: Load | F4: ='P&L'!P4 -> 0.8 | G4: Annual Flights | H4: =H2*52 -> 0 | J4: =H17*H4 -> 0
A5: Summary
A6: BNA | B6: FC | C6: BC | D6: PY | E6: EY | F6: TC | G6: CY | H6: Total | I6: Hnd
A7: FLIGHT CONFIG | B7: =+FlightConfig!B17 -> 0 | C7: =+FlightConfig!C17 -> 32 | D7: =+FlightConfig!D17 -> 56 | E7: =+FlightConfig!E17 -> 174 | F7: =+FlightConfig!F17 -> 2 | G7: =+FlightConfig!G17 -> 8 | H7: =SUM(B7:G7) -> 272
A8: Load Factor | B8: =ROUNDUP(B7*$F$4,0) -> 0 | C8: =ROUNDUP(C7*$F$4,0) -> 26 | D8: =ROUNDUP(D7*$F$4,0) -> 45 | E8: =ROUNDUP(E7*$F$4,0) -> 140 | F8: =ROUNDUP(F7*$F$4,0) -> 2 | G8: =ROUNDUP(G7*$F$4,0) -> 7 | H8: =SUM(B8:G8) -> 220
B9: FIRST CLASS | C9: BUSINESS CLASS | D9: PREMIUM ECONOMY CLASS | E9: ECONOMY CLASS | F9: TECH CREW CLASS | G9: cABIN CREW CLASS | H9: Per Flight | J9: Annual
A10: OVERHEAD | B10: =B37*B8 -> 0 | C10: =C37*C8 -> 104 | D10: =D37*D8 -> 135 | E10: =E37*E8 -> 350 | F10: =F37*F8 -> 6 | G10: =G37*G8 -> 21 | H10: =SUM(B10:G10) -> 616 | J10: =H10*$H$4 -> 0
A11: Food Cost (DM) | B11: =IFERROR(B38*B8,0) -> 0 | C11: =IFERROR(C38*$C$8,0) -> 0 | D11: =IFERROR(D38*$D$8,0) -> 0 | E11: =IFERROR(E38*$E$8,0) -> 0 | F11: =IFERROR(F38*$F$8,0) -> 0 | G11: =IFERROR(G38*G8,0) -> 0 | H11: =SUM(B11:G11) -> 0 | I11: =I12*45% -> 0 | J11: =H11*$H$4 -> 0
A12: Wage Cost (DL) | B12: =IFERROR(B39*B8,0) -> 0 | C12: =IFERROR(C39*$C$8,0) -> 0 | D12: =IFERROR(D39*$D$8,0) -> 0 | E12: =IFERROR(E39*$E$8,0) -> 0 | F12: =IFERROR(F39*$F$8,0) -> 0 | G12: =IFERROR(G39*G8,0) -> 0 | H12: =SUM(B12:G12) -> 0 | I12: =H11+H12 -> 0 | J12: =H12*$H$4 -> 0
A13: Food Mark up | B13: =IFERROR(B40*B8," ") | C13: =IFERROR(C40*$C$8,0) -> 0 | D13: =IFERROR(D40*$D$8,0) -> 0 | E13: =IFERROR(E40*$E$8,0) -> 0 | F13: =IFERROR(F40*$F$8,0) -> 0 | G13: 0 | H13: =SUM(B13:G13) -> 0 | J13: =H13*$H$4 -> 0
A14: Labor Mark up | B14: =IFERROR(B41*B8," ") | C14: =IFERROR(C41*$C$8,0) -> 0 | D14: =IFERROR(D41*$D$8,0) -> 0 | E14: =IFERROR(E41*$E$8,0) -> 0 | F14: =IFERROR(F41*$F$8,0) -> 0 | G14: 0 | H14: =SUM(B14:G14) -> 0 | J14: =H14*$H$4 -> 0 | L14: Direct Labour
A15: Handling Cost | B15: 0 | C15: 0 | D15: 0 | E15: =+B20 -> 0 | F15: 0 | G15: 0 | H15: =SUM(B15:G15) -> 0 | J15: =H15*$H$4 -> 0 | L15: =J12+J15 -> 0 | M15: 1
A16: Handling Mark up | B16: 0 | C16: 0 | D16: 0 | E16: =+C20 -> 0 | F16: 0 | G16: 0 | H16: =SUM(B16:G16) -> 0 | J16: =H16*$H$4 -> 0 | L16: =L15*M16 -> 0 | M16: 0.8
A17: Total Per Flight | B17: =SUM(B11:B16) -> 0 | C17: =SUM(C11:C16) -> 0 | D17: =SUM(D10:D16) -> 135 | E17: =SUM(E10:E16) -> 350 | F17: =SUM(F10:F16) -> 6 | G17: =SUM(G10:G16) -> 21 | H17: =SUM(H10:H16) -> 616 | J17: =H17*$H$4 -> 0 | L17: =L15*M17 -> 0 | M17: 0.2
B18: =B17 -> 0 | C18: =C17 -> 0 | D18: =D17 -> 135 | E18: =E17-E15-E16 -> 350 | F18: =F17 -> 6 | G18: =G17 -> 21 | I18: =E15+E16 -> 0
A19: Handling | B19: Cost | C19: Mark Up | D19: Price | I19: =E16 -> 0
A20: 738 Handling | B20: =Handling!C58 -> 0 | C20: =B20*'P&L'!$P$10 -> 0 | D20: =SUM(B20:C20) -> 0
A21: B777 Handling | B21: =Handling!#REF! -> #REF! | C21: =Handling!#REF! -> #REF! | D21: =Handling!#REF! -> #REF!
A22: A380 Handling | B22: =Handling!#REF! -> #REF! | C22: =Handling!#REF! -> #REF! | D22: =Handling!#REF! -> #REF!
A24: Avg Price Per Pax | B24: =IFERROR(((B11+B12+B13+B14)/B8),0) -> 0 | C24: =IFERROR(((C11+C12+C13+C14)/C8),0) -> 0 | D24: =IFERROR(((D10+D11+D12+D13+D14)/D8),0) -> 3 | E24: =IFERROR(((E10+E11+E12+E13+E14)/E8),0) -> 2.5 | F24: =IFERROR(((F10+F11+F12+F13+F14)/F8),0) -> 3 | G24: =IFERROR(((G10+G11+G12+G13+G14)/G8),0) -> 3
A25: Avg Mark up Per Pax | B25: =IFERROR(((B13+B14)/B8),0) -> 0 | C25: =IFERROR(((C13+C14)/C8),0) -> 0 | D25: =IFERROR(((D13+D14)/D8),0) -> 0 | E25: =IFERROR(((E13+E14)/E8),0) -> 0 | F25: =IFERROR(((F13+F14)/F8),0) -> 0 | G25: =IFERROR(((G13+G14)/G8),0) -> 0
A26: Over head Per Pax | B26: =IFERROR((B10/B8),0) -> 0 | C26: =IFERROR((C10/C8),0) -> 4 | D26: =IFERROR((D10/D8),0) -> 3 | E26: =IFERROR((E10/E8),0) -> 2.5 | F26: =IFERROR((F10/F8),0) -> 3 | G26: =IFERROR((G10/G8),0) -> 3
B28: CYCLE | C28: FLT
A29: Config | B29: ='P&L'!P5 -> 3 | C29: 735
A30: OVERHEAD | B30: =B37*B8 -> 0 | C30: =C37*C8 -> 104 | D30: =D37*D8 -> 135 | E30: =E37*E8 -> 350 | F30: =F37*F8 -> 6 | G30: =G37*G8 -> 21
A31: Food Cost (DM) | B31: =IFERROR(IF($B$29=$B$29,SUMIF(Food!$C:$C,B$9&$B$29&$C$29,Food!$V:$V),0),"") -> 0 | C31: =IFERROR(IF($B$29=$B$29,SUMIF(Food!$C:$C,C$9&$B$29&$C$29,Food!$V:$V),0),"") -> 0 | D31: =IFERROR(IF($B$29=$B$29,SUMIF(Food!$C:$C,D$9&$B$29&$C$29,Food!$V:$V),0),"") -> 0 | E31: =IFERROR(IF($B$29=$B$29,SUMIF(Food!$C:$C,E$9&$B$29&$C$29,Food!$V:$V),0),"") -> 0 | F31: =IFERROR(IF($B$29=$B$29,SUMIF(Food!$C:$C,F$9&$B$29&$C$29,Food!$V:$V),0),"") -> 0 | G31: =IFERROR(IF($B$29=$B$29,SUMIF(Food!$C:$C,G$9&$B$29&$C$29,Food!$V:$V),0),"") -> 0
A32: Wage Cost (DL) | B32: =IFERROR(IF($B$29=$B$29,SUMIF(Food!$C:$C,B$9&$B$29&$C$29,Food!$X:$X),0),"") -> 0 | C32: =IFERROR(IF($B$29=$B$29,SUMIF(Food!$C:$C,C$9&$B$29&$C$29,Food!$X:$X),0),"") -> 0 | D32: =IFERROR(IF($B$29=$B$29,SUMIF(Food!$C:$C,D$9&$B$29&$C$29,Food!$X:$X),0),"") -> 0 | E32: =IFERROR(IF($B$29=$B$29,SUMIF(Food!$C:$C,E$9&$B$29&$C$29,Food!$X:$X),0),"") -> 0 | F32: =IFERROR(IF($B$29=$B$29,SUMIF(Food!$C:$C,F$9&$B$29&$C$29,Food!$X:$X),0),"") -> 0 | G32: =IFERROR(IF($B$29=$B$29,SUMIF(Food!$C:$C,G$9&$B$29&$C$29,Food!$X:$X),0),"") -> 0
A33: Markup Food | B33: =IFERROR(IF($B$29=$B$29,SUMIF(Food!$C:$C,B$9&$B$29&$C$29,Food!$Z:$Z),0),"") -> 0 | C33: =IFERROR(IF($B$29=$B$29,SUMIF(Food!$C:$C,C$9&$B$29&$C$29,Food!$Z:$Z),0),"") -> 0 | D33: =IFERROR(IF($B$29=$B$29,SUMIF(Food!$C:$C,D$9&$B$29&$C$29,Food!$Z:$Z),0),"") -> 0 | E33: =IFERROR(IF($B$29=$B$29,SUMIF(Food!$C:$C,E$9&$B$29&$C$29,Food!$Z:$Z),0),"") -> 0 | F33: =IFERROR(IF($B$29=$B$29,SUMIF(Food!$C:$C,F$9&$B$29&$C$29,Food!$Z:$Z),0),"") -> 0 | G33: =IFERROR(IF($B$29=$B$29,SUMIF(Food!$C:$C,G$9&$B$29&$C$29,Food!$O:$O),0),"") -> 0
A34: Markup Labor | B34: =IFERROR(IF($B$29=$B$29,SUMIF(Food!$C:$C,B$9&$B$29&$C$29,Food!$AA:$AA),0),"") -> 0 | C34: =IFERROR(IF($B$29=$B$29,SUMIF(Food!$C:$C,C$9&$B$29&$C$29,Food!$AA:$AA),0),"") -> 0 | D34: =IFERROR(IF($B$29=$B$29,SUMIF(Food!$C:$C,D$9&$B$29&$C$29,Food!$AA:$AA),0),"") -> 0 | E34: =IFERROR(IF($B$29=$B$29,SUMIF(Food!$C:$C,E$9&$B$29&$C$29,Food!$AA:$AA),0),"") -> 0 | F34: =IFERROR(IF($B$29=$B$29,SUMIF(Food!$C:$C,F$9&$B$29&$C$29,Food!$AA:$AA),0),"") -> 0 | G34: =IFERROR(IF($B$29=$B$29,SUMIF(Food!$C:$C,G$9&$B$29&$C$29,Food!$P:$P),0),"") -> 0
A36: Per Pax Avg
A37: OVERHEAD | B37: ='P&L'!$J$30 -> 0 | C37: ='P&L'!$K$30 -> 4 | D37: ='P&L'!$L$30 -> 3 | E37: ='P&L'!$M$30 -> 2.5 | F37: ='P&L'!$N$30 -> 3 | G37: ='P&L'!$O$30 -> 3
A38: Food Cost (DM) | B38: =IFERROR(B31/B7," ") | C38: =IFERROR(C31/C7," ") -> 0 | D38: =IFERROR(D31/D7," ") -> 0 | E38: =IFERROR(E31/E7," ") -> 0 | F38: =IFERROR(F31/F7," ") -> 0 | G38: =IFERROR(G31/G7," ") -> 0
A39: Wage Cost (DL) | B39: =IFERROR(B32/B7," ") | C39: =IFERROR(C32/C7," ") -> 0 | D39: =IFERROR(D32/D7," ") -> 0 | E39: =IFERROR(E32/E7," ") -> 0 | F39: =IFERROR(F32/F7," ") -> 0 | G39: =IFERROR(G32/G7," ") -> 0
A40: Markup Food | B40: =IFERROR(B33/B8," ") | C40: =IFERROR(C33/C7," ") -> 0 | D40: =IFERROR(D33/D7," ") -> 0 | E40: =IFERROR(E33/E7," ") -> 0 | F40: =IFERROR(F33/F7," ") -> 0 | G40: =IFERROR(G33/G7," ") -> 0
A41: Markup Labor | B41: =IFERROR(B34/B7," ") | C41: =IFERROR(C34/C7," ") -> 0 | D41: =IFERROR(D34/D7," ") -> 0 | E41: =IFERROR(E34/E7," ") -> 0 | F41: =IFERROR(F34/F7," ") -> 0 | G41: =IFERROR(G34/G7," ") -> 0
A108: 388
A109: 787

Sheet Summary 2221
A2: Customer | G2: Flights Per week | H2: 0 | L2: AC type | M2: Cycle
E3: AC Type | F3: 738 | G3: Flights Per Month | H3: =H4/12 -> 0 | J3: Total Revenues | L3: 737 | M3: 1
E4: Load | F4: ='P&L'!P4 -> 0.8 | G4: Annual Flights | H4: =H2*52 -> 0 | J4: =H17*H4 -> 0
A5: Summary
A6: BNA | B6: FC | C6: BC | D6: PY | E6: EY | F6: TC | G6: CY | H6: Total | I6: Hnd
A7: FLIGHT CONFIG | B7: =+FlightConfig!B17 -> 0 | C7: =+FlightConfig!C17 -> 32 | D7: =+FlightConfig!D17 -> 56 | E7: =+FlightConfig!E17 -> 174 | F7: =+FlightConfig!F17 -> 2 | G7: =+FlightConfig!G17 -> 8 | H7: =SUM(B7:G7) -> 272
A8: Load Factor | B8: =ROUNDUP(B7*$F$4,0) -> 0 | C8: =ROUNDUP(C7*$F$4,0) -> 26 | D8: =ROUNDUP(D7*$F$4,0) -> 45 | E8: =ROUNDUP(E7*$F$4,0) -> 140 | F8: =ROUNDUP(F7*$F$4,0) -> 2 | G8: =ROUNDUP(G7*$F$4,0) -> 7 | H8: =SUM(B8:G8) -> 220
B9: FIRST CLASS | C9: BUSINESS CLASS | D9: PREMIUM ECONOMY CLASS | E9: ECONOMY CLASS | F9: TECH CREW CLASS | G9: cABIN CREW CLASS | H9: Per Flight | J9: Annual
A10: OVERHEAD | B10: =B37*B8 -> 0 | C10: =C37*C8 -> 104 | D10: =D37*D8 -> 135 | E10: =E37*E8 -> 350 | F10: =F37*F8 -> 6 | G10: =G37*G8 -> 21 | H10: =SUM(B10:G10) -> 616 | J10: =H10*$H$4 -> 0
A11: Food Cost (DM) | B11: =IFERROR(B38*B8,0) -> 0 | C11: =IFERROR(C38*$C$8,0) -> 0 | D11: =IFERROR(D38*$D$8,0) -> 0 | E11: =IFERROR(E38*$E$8,0) -> 0 | F11: =IFERROR(F38*$F$8,0) -> 0 | G11: =IFERROR(G38*G8,0) -> 0 | H11: =SUM(B11:G11) -> 0 | I11: =I12*45% -> 0 | J11: =H11*$H$4 -> 0
A12: Wage Cost (DL) | B12: =IFERROR(B39*B8,0) -> 0 | C12: =IFERROR(C39*$C$8,0) -> 0 | D12: =IFERROR(D39*$D$8,0) -> 0 | E12: =IFERROR(E39*$E$8,0) -> 0 | F12: =IFERROR(F39*$F$8,0) -> 0 | G12: =IFERROR(G39*G8,0) -> 0 | H12: =SUM(B12:G12) -> 0 | I12: =H11+H12 -> 0 | J12: =H12*$H$4 -> 0
A13: Food Mark up | B13: =IFERROR(B40*B8," ") | C13: =IFERROR(C40*$C$8,0) -> 0 | D13: =IFERROR(D40*$D$8,0) -> 0 | E13: =IFERROR(E40*$E$8,0) -> 0 | F13: =IFERROR(F40*$F$8,0) -> 0 | G13: 0 | H13: =SUM(B13:G13) -> 0 | J13: =H13*$H$4 -> 0
A14: Labor Mark up | B14: =IFERROR(B41*B8," ") | C14: =IFERROR(C41*$C$8,0) -> 0 | D14: =IFERROR(D41*$D$8,0) -> 0 | E14: =IFERROR(E41*$E$8,0) -> 0 | F14: =IFERROR(F41*$F$8,0) -> 0 | G14: 0 | H14: =SUM(B14:G14) -> 0 | J14: =H14*$H$4 -> 0 | L14: Direct Labour
A15: Handling Cost | B15: 0 | C15: 0 | D15: 0 | E15: =+B20 -> 0 | F15: 0 | G15: 0 | H15: =SUM(B15:G15) -> 0 | J15: =H15*$H$4 -> 0 | L15: =J12+J15 -> 0 | M15: 1
A16: Handling Mark up | B16: 0 | C16: 0 | D16: 0 | E16: =+C20 -> 0 | F16: 0 | G16: 0 | H16: =SUM(B16:G16) -> 0 | J16: =H16*$H$4 -> 0 | L16: =L15*M16 -> 0 | M16: 0.8
A17: Total Per Flight | B17: =SUM(B11:B16) -> 0 | C17: =SUM(C11:C16) -> 0 | D17: =SUM(D10:D16) -> 135 | E17: =SUM(E10:E16) -> 350 | F17: =SUM(F10:F16) -> 6 | G17: =SUM(G10:G16) -> 21 | H17: =SUM(H10:H16) -> 616 | J17: =H17*$H$4 -> 0 | L17: =L15*M17 -> 0 | M17: 0.2
B18: =B17 -> 0 | C18: =C17 -> 0 | D18: =D17 -> 135 | E18: =E17-E15-E16 -> 350 | F18: =F17 -> 6 | G18: =G17 -> 21 | I18: =E15+E16 -> 0
A19: Handling | B19: Cost | C19: Mark Up | D19: Price | I19: =E16 -> 0
A20: 738 Handling | B20: =Handling!C58 -> 0 | C20: =B20*'P&L'!$P$10 -> 0 | D20: =SUM(B20:C20) -> 0
A21: B777 Handling | B21: =Handling!#REF! -> #REF! | C21: =Handling!#REF! -> #REF! | D21: =Handling!#REF! -> #REF!
A22: A380 Handling | B22: =Handling!#REF! -> #REF! | C22: =Handling!#REF! -> #REF! | D22: =Handling!#REF! -> #REF!
A24: Avg Price Per Pax | B24: =IFERROR(((B11+B12+B13+B14)/B8),0) -> 0 | C24: =IFERROR(((C11+C12+C13+C14)/C8),0) -> 0 | D24: =IFERROR(((D10+D11+D12+D13+D14)/D8),0) -> 3 | E24: =IFERROR(((E10+E11+E12+E13+E14)/E8),0) -> 2.5 | F24: =IFERROR(((F10+F11+F12+F13+F14)/F8),0) -> 3 | G24: =IFERROR(((G10+G11+G12+G13+G14)/G8),0) -> 3
A25: Avg Mark up Per Pax | B25: =IFERROR(((B13+B14)/B8),0) -> 0 | C25: =IFERROR(((C13+C14)/C8),0) -> 0 | D25: =IFERROR(((D13+D14)/D8),0) -> 0 | E25: =IFERROR(((E13+E14)/E8),0) -> 0 | F25: =IFERROR(((F13+F14)/F8),0) -> 0 | G25: =IFERROR(((G13+G14)/G8),0) -> 0
A26: Over head Per Pax | B26: =IFERROR((B10/B8),0) -> 0 | C26: =IFERROR((C10/C8),0) -> 4 | D26: =IFERROR((D10/D8),0) -> 3 | E26: =IFERROR((E10/E8),0) -> 2.5 | F26: =IFERROR((F10/F8),0) -> 3 | G26: =IFERROR((G10/G8),0) -> 3
B28: CYCLE | C28: FLT
A29: Config | B29: ='P&L'!P5 -> 3 | C29: 2221
A30: OVERHEAD | B30: =B37*B8 -> 0 | C30: =C37*C8 -> 104 | D30: =D37*D8 -> 135 | E30: =E37*E8 -> 350 | F30: =F37*F8 -> 6 | G30: =G37*G8 -> 21
A31: Food Cost (DM) | B31: =IFERROR(IF($B$29=$B$29,SUMIF(Food!$C:$C,B$9&$B$29&$C$29,Food!$V:$V),0),"") -> 0 | C31: =IFERROR(IF($B$29=$B$29,SUMIF(Food!$C:$C,C$9&$B$29&$C$29,Food!$V:$V),0),"") -> 0 | D31: =IFERROR(IF($B$29=$B$29,SUMIF(Food!$C:$C,D$9&$B$29&$C$29,Food!$V:$V),0),"") -> 0 | E31: =IFERROR(IF($B$29=$B$29,SUMIF(Food!$C:$C,E$9&$B$29&$C$29,Food!$V:$V),0),"") -> 0 | F31: =IFERROR(IF($B$29=$B$29,SUMIF(Food!$C:$C,F$9&$B$29&$C$29,Food!$V:$V),0),"") -> 0 | G31: =IFERROR(IF($B$29=$B$29,SUMIF(Food!$C:$C,G$9&$B$29&$C$29,Food!$V:$V),0),"") -> 0
A32: Wage Cost (DL) | B32: =IFERROR(IF($B$29=$B$29,SUMIF(Food!$C:$C,B$9&$B$29&$C$29,Food!$X:$X),0),"") -> 0 | C32: =IFERROR(IF($B$29=$B$29,SUMIF(Food!$C:$C,C$9&$B$29&$C$29,Food!$X:$X),0),"") -> 0 | D32: =IFERROR(IF($B$29=$B$29,SUMIF(Food!$C:$C,D$9&$B$29&$C$29,Food!$X:$X),0),"") -> 0 | E32: =IFERROR(IF($B$29=$B$29,SUMIF(Food!$C:$C,E$9&$B$29&$C$29,Food!$X:$X),0),"") -> 0 | F32: =IFERROR(IF($B$29=$B$29,SUMIF(Food!$C:$C,F$9&$B$29&$C$29,Food!$X:$X),0),"") -> 0 | G32: =IFERROR(IF($B$29=$B$29,SUMIF(Food!$C:$C,G$9&$B$29&$C$29,Food!$X:$X),0),"") -> 0
A33: Markup Food | B33: =IFERROR(IF($B$29=$B$29,SUMIF(Food!$C:$C,B$9&$B$29&$C$29,Food!$Z:$Z),0),"") -> 0 | C33: =IFERROR(IF($B$29=$B$29,SUMIF(Food!$C:$C,C$9&$B$29&$C$29,Food!$Z:$Z),0),"") -> 0 | D33: =IFERROR(IF($B$29=$B$29,SUMIF(Food!$C:$C,D$9&$B$29&$C$29,Food!$Z:$Z),0),"") -> 0 | E33: =IFERROR(IF($B$29=$B$29,SUMIF(Food!$C:$C,E$9&$B$29&$C$29,Food!$Z:$Z),0),"") -> 0 | F33: =IFERROR(IF($B$29=$B$29,SUMIF(Food!$C:$C,F$9&$B$29&$C$29,Food!$Z:$Z),0),"") -> 0 | G33: =IFERROR(IF($B$29=$B$29,SUMIF(Food!$C:$C,G$9&$B$29&$C$29,Food!$O:$O),0),"") -> 0
A34: Markup Labor | B34: =IFERROR(IF($B$29=$B$29,SUMIF(Food!$C:$C,B$9&$B$29&$C$29,Food!$AA:$AA),0),"") -> 0 | C34: =IFERROR(IF($B$29=$B$29,SUMIF(Food!$C:$C,C$9&$B$29&$C$29,Food!$AA:$AA),0),"") -> 0 | D34: =IFERROR(IF($B$29=$B$29,SUMIF(Food!$C:$C,D$9&$B$29&$C$29,Food!$AA:$AA),0),"") -> 0 | E34: =IFERROR(IF($B$29=$B$29,SUMIF(Food!$C:$C,E$9&$B$29&$C$29,Food!$AA:$AA),0),"") -> 0 | F34: =IFERROR(IF($B$29=$B$29,SUMIF(Food!$C:$C,F$9&$B$29&$C$29,Food!$AA:$AA),0),"") -> 0 | G34: =IFERROR(IF($B$29=$B$29,SUMIF(Food!$C:$C,G$9&$B$29&$C$29,Food!$P:$P),0),"") -> 0
A36: Per Pax Avg
A37: OVERHEAD | B37: ='P&L'!$J$30 -> 0 | C37: ='P&L'!$K$30 -> 4 | D37: ='P&L'!$L$30 -> 3 | E37: ='P&L'!$M$30 -> 2.5 | F37: ='P&L'!$N$30 -> 3 | G37: ='P&L'!$O$30 -> 3
A38: Food Cost (DM) | B38: =IFERROR(B31/B7," ") | C38: =IFERROR(C31/C7," ") -> 0 | D38: =IFERROR(D31/D7," ") -> 0 | E38: =IFERROR(E31/E7," ") -> 0 | F38: =IFERROR(F31/F7," ") -> 0 | G38: =IFERROR(G31/G7," ") -> 0
A39: Wage Cost (DL) | B39: =IFERROR(B32/B7," ") | C39: =IFERROR(C32/C7," ") -> 0 | D39: =IFERROR(D32/D7," ") -> 0 | E39: =IFERROR(E32/E7," ") -> 0 | F39: =IFERROR(F32/F7," ") -> 0 | G39: =IFERROR(G32/G7," ") -> 0
A40: Markup Food | B40: =IFERROR(B33/B8," ") | C40: =IFERROR(C33/C7," ") -> 0 | D40: =IFERROR(D33/D7," ") -> 0 | E40: =IFERROR(E33/E7," ") -> 0 | F40: =IFERROR(F33/F7," ") -> 0 | G40: =IFERROR(G33/G7," ") -> 0
A41: Markup Labor | B41: =IFERROR(B34/B7," ") | C41: =IFERROR(C34/C7," ") -> 0 | D41: =IFERROR(D34/D7," ") -> 0 | E41: =IFERROR(E34/E7," ") -> 0 | F41: =IFERROR(F34/F7," ") -> 0 | G41: =IFERROR(G34/G7," ") -> 0
A108: 388
A109: 787

Sheet Summary 2439
A2: Customer | G2: Flights Per week | H2: 0 | L2: AC type | M2: Cycle
E3: AC Type | F3: 738 | G3: Flights Per Month | H3: =H4/12 -> 0 | J3: Total Revenues | L3: 737 | M3: 1
E4: Load | F4: ='P&L'!P4 -> 0.8 | G4: Annual Flights | H4: =H2*52 -> 0 | J4: =H17*H4 -> 0
A5: Summary
A6: BNA | B6: FC | C6: BC | D6: PY | E6: EY | F6: TC | G6: CY | H6: Total | I6: Hnd
A7: FLIGHT CONFIG | B7: =+FlightConfig!B17 -> 0 | C7: =+FlightConfig!C17 -> 32 | D7: =+FlightConfig!D17 -> 56 | E7: =+FlightConfig!E17 -> 174 | F7: =+FlightConfig!F17 -> 2 | G7: =+FlightConfig!G17 -> 8 | H7: =SUM(B7:G7) -> 272
A8: Load Factor | B8: =ROUNDUP(B7*$F$4,0) -> 0 | C8: =ROUNDUP(C7*$F$4,0) -> 26 | D8: =ROUNDUP(D7*$F$4,0) -> 45 | E8: =ROUNDUP(E7*$F$4,0) -> 140 | F8: =ROUNDUP(F7*$F$4,0) -> 2 | G8: =ROUNDUP(G7*$F$4,0) -> 7 | H8: =SUM(B8:G8) -> 220
B9: FIRST CLASS | C9: BUSINESS CLASS | D9: PREMIUM ECONOMY CLASS | E9: ECONOMY CLASS | F9: TECH CREW CLASS | G9: cABIN CREW CLASS | H9: Per Flight | J9: Annual
A10: OVERHEAD | B10: =B37*B8 -> 0 | C10: =C37*C8 -> 104 | D10: =D37*D8 -> 135 | E10: =E37*E8 -> 350 | F10: =F37*F8 -> 6 | G10: =G37*G8 -> 21 | H10: =SUM(B10:G10) -> 616 | J10: =H10*$H$4 -> 0
A11: Food Cost (DM) | B11: =IFERROR(B38*B8,0) -> 0 | C11: =IFERROR(C38*$C$8,0) -> 0 | D11: =IFERROR(D38*$D$8,0) -> 0 | E11: =IFERROR(E38*$E$8,0) -> 0 | F11: =IFERROR(F38*$F$8,0) -> 0 | G11: =IFERROR(G38*G8,0) -> 0 | H11: =SUM(B11:G11) -> 0 | I11: =I12*45% -> 0 | J11: =H11*$H$4 -> 0
A12: Wage Cost (DL) | B12: =IFERROR(B39*B8,0) -> 0 | C12: =IFERROR(C39*$C$8,0) -> 0 | D12: =IFERROR(D39*$D$8,0) -> 0 | E12: =IFERROR(E39*$E$8,0) -> 0 | F12: =IFERROR(F39*$F$8,0) -> 0 | G12: =IFERROR(G39*G8,0) -> 0 | H12: =SUM(B12:G12) -> 0 | I12: =H11+H12 -> 0 | J12: =H12*$H$4 -> 0
A13: Food Mark up | B13: =IFERROR(B40*B8," ") | C13: =IFERROR(C40*$C$8,0) -> 0 | D13: =IFERROR(D40*$D$8,0) -> 0 | E13: =IFERROR(E40*$E$8,0) -> 0 | F13: =IFERROR(F40*$F$8,0) -> 0 | G13: 0 | H13: =SUM(B13:G13) -> 0 | J13: =H13*$H$4 -> 0
A14: Labor Mark up | B14: =IFERROR(B41*B8," ") | C14: =IFERROR(C41*$C$8,0) -> 0 | D14: =IFERROR(D41*$D$8,0) -> 0 | E14: =IFERROR(E41*$E$8,0) -> 0 | F14: =IFERROR(F41*$F$8,0) -> 0 | G14: 0 | H14: =SUM(B14:G14) -> 0 | J14: =H14*$H$4 -> 0 | L14: Direct Labour
A15: Handling Cost | B15: 0 | C15: 0 | D15: 0 | E15: =+B20 -> 0 | F15: 0 | G15: 0 | H15: =SUM(B15:G15) -> 0 | J15: =H15*$H$4 -> 0 | L15: =J12+J15 -> 0 | M15: 1
A16: Handling Mark up | B16: 0 | C16: 0 | D16: 0 | E16: =+C20 -> 0 | F16: 0 | G16: 0 | H16: =SUM(B16:G16) -> 0 | J16: =H16*$H$4 -> 0 | L16: =L15*M16 -> 0 | M16: 0.8
A17: Total Per Flight | B17: =SUM(B11:B16) -> 0 | C17: =SUM(C11:C16) -> 0 | D17: =SUM(D10:D16) -> 135 | E17: =SUM(E10:E16) -> 350 | F17: =SUM(F10:F16) -> 6 | G17: =SUM(G10:G16) -> 21 | H17: =SUM(H10:H16) -> 616 | J17: =H17*$H$4 -> 0 | L17: =L15*M17 -> 0 | M17: 0.2
B18: =B17 -> 0 | C18: =C17 -> 0 | D18: =D17 -> 135 | E18: =E17-E15-E16 -> 350 | F18: =F17 -> 6 | G18: =G17 -> 21 | I18: =E15+E16 -> 0
A19: Handling | B19: Cost | C19: Mark Up | D19: Price | I19: =E16 -> 0
A20: 738 Handling | B20: =Handling!C58 -> 0 | C20: =B20*'P&L'!$P$10 -> 0 | D20: =SUM(B20:C20) -> 0
A21: B777 Handling | B21: =Handling!#REF! -> #REF! | C21: =Handling!#REF! -> #REF! | D21: =Handling!#REF! -> #REF!
A22: A380 Handling | B22: =Handling!#REF! -> #REF! | C22: =Handling!#REF! -> #REF! | D22: =Handling!#REF! -> #REF!
A24: Avg Price Per Pax | B24: =IFERROR(((B11+B12+B13+B14)/B8),0) -> 0 | C24: =IFERROR(((C11+C12+C13+C14)/C8),0) -> 0 | D24: =IFERROR(((D10+D11+D12+D13+D14)/D8),0) -> 3 | E24: =IFERROR(((E10+E11+E12+E13+E14)/E8),0) -> 2.5 | F24: =IFERROR(((F10+F11+F12+F13+F14)/F8),0) -> 3 | G24: =IFERROR(((G10+G11+G12+G13+G14)/G8),0) -> 3
A25: Avg Mark up Per Pax | B25: =IFERROR(((B13+B14)/B8),0) -> 0 | C25: =IFERROR(((C13+C14)/C8),0) -> 0 | D25: =IFERROR(((D13+D14)/D8),0) -> 0 | E25: =IFERROR(((E13+E14)/E8),0) -> 0 | F25: =IFERROR(((F13+F14)/F8),0) -> 0 | G25: =IFERROR(((G13+G14)/G8),0) -> 0
A26: Over head Per Pax | B26: =IFERROR((B10/B8),0) -> 0 | C26: =IFERROR((C10/C8),0) -> 4 | D26: =IFERROR((D10/D8),0) -> 3 | E26: =IFERROR((E10/E8),0) -> 2.5 | F26: =IFERROR((F10/F8),0) -> 3 | G26: =IFERROR((G10/G8),0) -> 3
B28: CYCLE | C28: FLT
A29: Config | B29: ='P&L'!P5 -> 3 | C29: 2439
A30: OVERHEAD | B30: =B37*B8 -> 0 | C30: =C37*C8 -> 104 | D30: =D37*D8 -> 135 | E30: =E37*E8 -> 350 | F30: =F37*F8 -> 6 | G30: =G37*G8 -> 21
A31: Food Cost (DM) | B31: =IFERROR(IF($B$29=$B$29,SUMIF(Food!$C:$C,B$9&$B$29&$C$29,Food!$V:$V),0),"") -> 0 | C31: =IFERROR(IF($B$29=$B$29,SUMIF(Food!$C:$C,C$9&$B$29&$C$29,Food!$V:$V),0),"") -> 0 | D31: =IFERROR(IF($B$29=$B$29,SUMIF(Food!$C:$C,D$9&$B$29&$C$29,Food!$V:$V),0),"") -> 0 | E31: =IFERROR(IF($B$29=$B$29,SUMIF(Food!$C:$C,E$9&$B$29&$C$29,Food!$V:$V),0),"") -> 0 | F31: =IFERROR(IF($B$29=$B$29,SUMIF(Food!$C:$C,F$9&$B$29&$C$29,Food!$V:$V),0),"") -> 0 | G31: =IFERROR(IF($B$29=$B$29,SUMIF(Food!$C:$C,G$9&$B$29&$C$29,Food!$V:$V),0),"") -> 0
A32: Wage Cost (DL) | B32: =IFERROR(IF($B$29=$B$29,SUMIF(Food!$C:$C,B$9&$B$29&$C$29,Food!$X:$X),0),"") -> 0 | C32: =IFERROR(IF($B$29=$B$29,SUMIF(Food!$C:$C,C$9&$B$29&$C$29,Food!$X:$X),0),"") -> 0 | D32: =IFERROR(IF($B$29=$B$29,SUMIF(Food!$C:$C,D$9&$B$29&$C$29,Food!$X:$X),0),"") -> 0 | E32: =IFERROR(IF($B$29=$B$29,SUMIF(Food!$C:$C,E$9&$B$29&$C$29,Food!$X:$X),0),"") -> 0 | F32: =IFERROR(IF($B$29=$B$29,SUMIF(Food!$C:$C,F$9&$B$29&$C$29,Food!$X:$X),0),"") -> 0 | G32: =IFERROR(IF($B$29=$B$29,SUMIF(Food!$C:$C,G$9&$B$29&$C$29,Food!$X:$X),0),"") -> 0
A33: Markup Food | B33: =IFERROR(IF($B$29=$B$29,SUMIF(Food!$C:$C,B$9&$B$29&$C$29,Food!$Z:$Z),0),"") -> 0 | C33: =IFERROR(IF($B$29=$B$29,SUMIF(Food!$C:$C,C$9&$B$29&$C$29,Food!$Z:$Z),0),"") -> 0 | D33: =IFERROR(IF($B$29=$B$29,SUMIF(Food!$C:$C,D$9&$B$29&$C$29,Food!$Z:$Z),0),"") -> 0 | E33: =IFERROR(IF($B$29=$B$29,SUMIF(Food!$C:$C,E$9&$B$29&$C$29,Food!$Z:$Z),0),"") -> 0 | F33: =IFERROR(IF($B$29=$B$29,SUMIF(Food!$C:$C,F$9&$B$29&$C$29,Food!$Z:$Z),0),"") -> 0 | G33: =IFERROR(IF($B$29=$B$29,SUMIF(Food!$C:$C,G$9&$B$29&$C$29,Food!$O:$O),0),"") -> 0
A34: Markup Labor | B34: =IFERROR(IF($B$29=$B$29,SUMIF(Food!$C:$C,B$9&$B$29&$C$29,Food!$AA:$AA),0),"") -> 0 | C34: =IFERROR(IF($B$29=$B$29,SUMIF(Food!$C:$C,C$9&$B$29&$C$29,Food!$AA:$AA),0),"") -> 0 | D34: =IFERROR(IF($B$29=$B$29,SUMIF(Food!$C:$C,D$9&$B$29&$C$29,Food!$AA:$AA),0),"") -> 0 | E34: =IFERROR(IF($B$29=$B$29,SUMIF(Food!$C:$C,E$9&$B$29&$C$29,Food!$AA:$AA),0),"") -> 0 | F34: =IFERROR(IF($B$29=$B$29,SUMIF(Food!$C:$C,F$9&$B$29&$C$29,Food!$AA:$AA),0),"") -> 0 | G34: =IFERROR(IF($B$29=$B$29,SUMIF(Food!$C:$C,G$9&$B$29&$C$29,Food!$P:$P),0),"") -> 0
A36: Per Pax Avg
A37: OVERHEAD | B37: ='P&L'!$J$30 -> 0 | C37: ='P&L'!$K$30 -> 4 | D37: ='P&L'!$L$30 -> 3 | E37: ='P&L'!$M$30 -> 2.5 | F37: ='P&L'!$N$30 -> 3 | G37: ='P&L'!$O$30 -> 3
A38: Food Cost (DM) | B38: =IFERROR(B31/B7," ") | C38: =IFERROR(C31/C7," ") -> 0 | D38: =IFERROR(D31/D7," ") -> 0 | E38: =IFERROR(E31/E7," ") -> 0 | F38: =IFERROR(F31/F7," ") -> 0 | G38: =IFERROR(G31/G7," ") -> 0
A39: Wage Cost (DL) | B39: =IFERROR(B32/B7," ") | C39: =IFERROR(C32/C7," ") -> 0 | D39: =IFERROR(D32/D7," ") -> 0 | E39: =IFERROR(E32/E7," ") -> 0 | F39: =IFERROR(F32/F7," ") -> 0 | G39: =IFERROR(G32/G7," ") -> 0
A40: Markup Food | B40: =IFERROR(B33/B8," ") | C40: =IFERROR(C33/C7," ") -> 0 | D40: =IFERROR(D33/D7," ") -> 0 | E40: =IFERROR(E33/E7," ") -> 0 | F40: =IFERROR(F33/F7," ") -> 0 | G40: =IFERROR(G33/G7," ") -> 0
A41: Markup Labor | B41: =IFERROR(B34/B7," ") | C41: =IFERROR(C34/C7," ") -> 0 | D41: =IFERROR(D34/D7," ") -> 0 | E41: =IFERROR(E34/E7," ") -> 0 | F41: =IFERROR(F34/F7," ") -> 0 | G41: =IFERROR(G34/G7," ") -> 0
A108: 388
A109: 787

Sheet Summary 2682
A2: Customer | G2: Flights Per week | H2: 0 | L2: AC type | M2: Cycle
E3: AC Type | F3: 738 | G3: Flights Per Month | H3: =H4/12 -> 0 | J3: Total Revenues | L3: 737 | M3: 1
E4: Load | F4: ='P&L'!P4 -> 0.8 | G4: Annual Flights | H4: =H2*52 -> 0 | J4: =H17*H4 -> 0
A5: Summary
A6: BNA | B6: FC | C6: BC | D6: PY | E6: EY | F6: TC | G6: CY | H6: Total | I6: Hnd
A7: FLIGHT CONFIG | B7: =+FlightConfig!B17 -> 0 | C7: =+FlightConfig!C17 -> 32 | D7: =+FlightConfig!D17 -> 56 | E7: =+FlightConfig!E17 -> 174 | F7: =+FlightConfig!F17 -> 2 | G7: =+FlightConfig!G17 -> 8 | H7: =SUM(B7:G7) -> 272
A8: Load Factor | B8: =ROUNDUP(B7*$F$4,0) -> 0 | C8: =ROUNDUP(C7*$F$4,0) -> 26 | D8: =ROUNDUP(D7*$F$4,0) -> 45 | E8: =ROUNDUP(E7*$F$4,0) -> 140 | F8: =ROUNDUP(F7*$F$4,0) -> 2 | G8: =ROUNDUP(G7*$F$4,0) -> 7 | H8: =SUM(B8:G8) -> 220
B9: FIRST CLASS | C9: BUSINESS CLASS | D9: PREMIUM ECONOMY CLASS | E9: ECONOMY CLASS | F9: TECH CREW CLASS | G9: cABIN CREW CLASS | H9: Per Flight | J9: Annual
A10: OVERHEAD | B10: =B37*B8 -> 0 | C10: =C37*C8 -> 104 | D10: =D37*D8 -> 135 | E10: =E37*E8 -> 350 | F10: =F37*F8 -> 6 | G10: =G37*G8 -> 21 | H10: =SUM(B10:G10) -> 616 | J10: =H10*$H$4 -> 0
A11: Food Cost (DM) | B11: =IFERROR(B38*B8,0) -> 0 | C11: =IFERROR(C38*$C$8,0) -> 0 | D11: =IFERROR(D38*$D$8,0) -> 0 | E11: =IFERROR(E38*$E$8,0) -> 0 | F11: =IFERROR(F38*$F$8,0) -> 0 | G11: =IFERROR(G38*G8,0) -> 0 | H11: =SUM(B11:G11) -> 0 | I11: =I12*45% -> 0 | J11: =H11*$H$4 -> 0
A12: Wage Cost (DL) | B12: =IFERROR(B39*B8,0) -> 0 | C12: =IFERROR(C39*$C$8,0) -> 0 | D12: =IFERROR(D39*$D$8,0) -> 0 | E12: =IFERROR(E39*$E$8,0) -> 0 | F12: =IFERROR(F39*$F$8,0) -> 0 | G12: =IFERROR(G39*G8,0) -> 0 | H12: =SUM(B12:G12) -> 0 | I12: =H11+H12 -> 0 | J12: =H12*$H$4 -> 0
A13: Food Mark up | B13: =IFERROR(B40*B8," ") | C13: =IFERROR(C40*$C$8,0) -> 0 | D13: =IFERROR(D40*$D$8,0) -> 0 | E13: =IFERROR(E40*$E$8,0) -> 0 | F13: =IFERROR(F40*$F$8,0) -> 0 | G13: 0 | H13: =SUM(B13:G13) -> 0 | J13: =H13*$H$4 -> 0
A14: Labor Mark up | B14: =IFERROR(B41*B8," ") | C14: =IFERROR(C41*$C$8,0) -> 0 | D14: =IFERROR(D41*$D$8,0) -> 0 | E14: =IFERROR(E41*$E$8,0) -> 0 | F14: =IFERROR(F41*$F$8,0) -> 0 | G14: 0 | H14: =SUM(B14:G14) -> 0 | J14: =H14*$H$4 -> 0 | L14: Direct Labour
A15: Handling Cost | B15: 0 | C15: 0 | D15: 0 | E15: =+B20 -> 0 | F15: 0 | G15: 0 | H15: =SUM(B15:G15) -> 0 | J15: =H15*$H$4 -> 0 | L15: =J12+J15 -> 0 | M15: 1
A16: Handling Mark up | B16: 0 | C16: 0 | D16: 0 | E16: =+C20 -> 0 | F16: 0 | G16: 0 | H16: =SUM(B16:G16) -> 0 | J16: =H16*$H$4 -> 0 | L16: =L15*M16 -> 0 | M16: 0.8
A17: Total Per Flight | B17: =SUM(B11:B16) -> 0 | C17: =SUM(C11:C16) -> 0 | D17: =SUM(D10:D16) -> 135 | E17: =SUM(E10:E16) -> 350 | F17: =SUM(F10:F16) -> 6 | G17: =SUM(G10:G16) -> 21 | H17: =SUM(H10:H16) -> 616 | J17: =H17*$H$4 -> 0 | L17: =L15*M17 -> 0 | M17: 0.2
B18: =B17 -> 0 | C18: =C17 -> 0 | D18: =D17 -> 135 | E18: =E17-E15-E16 -> 350 | F18: =F17 -> 6 | G18: =G17 -> 21 | I18: =E15+E16 -> 0
A19: Handling | B19: Cost | C19: Mark Up | D19: Price | I19: =E16 -> 0
A20: 738 Handling | B20: =Handling!C58 -> 0 | C20: =B20*'P&L'!$P$10 -> 0 | D20: =SUM(B20:C20) -> 0
A21: B777 Handling | B21: =Handling!#REF! -> #REF! | C21: =Handling!#REF! -> #REF! | D21: =Handling!#REF! -> #REF!
A22: A380 Handling | B22: =Handling!#REF! -> #REF! | C22: =Handling!#REF! -> #REF! | D22: =Handling!#REF! -> #REF!
A24: Avg Price Per Pax | B24: =IFERROR(((B11+B12+B13+B14)/B8),0) -> 0 | C24: =IFERROR(((C11+C12+C13+C14)/C8),0) -> 0 | D24: =IFERROR(((D10+D11+D12+D13+D14)/D8),0) -> 3 | E24: =IFERROR(((E10+E11+E12+E13+E14)/E8),0) -> 2.5 | F24: =IFERROR(((F10+F11+F12+F13+F14)/F8),0) -> 3 | G24: =IFERROR(((G10+G11+G12+G13+G14)/G8),0) -> 3
A25: Avg Mark up Per Pax | B25: =IFERROR(((B13+B14)/B8),0) -> 0 | C25: =IFERROR(((C13+C14)/C8),0) -> 0 | D25: =IFERROR(((D13+D14)/D8),0) -> 0 | E25: =IFERROR(((E13+E14)/E8),0) -> 0 | F25: =IFERROR(((F13+F14)/F8),0) -> 0 | G25: =IFERROR(((G13+G14)/G8),0) -> 0
A26: Over head Per Pax | B26: =IFERROR((B10/B8),0) -> 0 | C26: =IFERROR((C10/C8),0) -> 4 | D26: =IFERROR((D10/D8),0) -> 3 | E26: =IFERROR((E10/E8),0) -> 2.5 | F26: =IFERROR((F10/F8),0) -> 3 | G26: =IFERROR((G10/G8),0) -> 3
B28: CYCLE | C28: FLT
A29: Config | B29: ='P&L'!P5 -> 3 | C29: 2682
A30: OVERHEAD | B30: =B37*B8 -> 0 | C30: =C37*C8 -> 104 | D30: =D37*D8 -> 135 | E30: =E37*E8 -> 350 | F30: =F37*F8 -> 6 | G30: =G37*G8 -> 21
A31: Food Cost (DM) | B31: =IFERROR(IF($B$29=$B$29,SUMIF(Food!$C:$C,B$9&$B$29&$C$29,Food!$V:$V),0),"") -> 0 | C31: =IFERROR(IF($B$29=$B$29,SUMIF(Food!$C:$C,C$9&$B$29&$C$29,Food!$V:$V),0),"") -> 0 | D31: =IFERROR(IF($B$29=$B$29,SUMIF(Food!$C:$C,D$9&$B$29&$C$29,Food!$V:$V),0),"") -> 0 | E31: =IFERROR(IF($B$29=$B$29,SUMIF(Food!$C:$C,E$9&$B$29&$C$29,Food!$V:$V),0),"") -> 0 | F31: =IFERROR(IF($B$29=$B$29,SUMIF(Food!$C:$C,F$9&$B$29&$C$29,Food!$V:$V),0),"") -> 0 | G31: =IFERROR(IF($B$29=$B$29,SUMIF(Food!$C:$C,G$9&$B$29&$C$29,Food!$V:$V),0),"") -> 0
A32: Wage Cost (DL) | B32: =IFERROR(IF($B$29=$B$29,SUMIF(Food!$C:$C,B$9&$B$29&$C$29,Food!$X:$X),0),"") -> 0 | C32: =IFERROR(IF($B$29=$B$29,SUMIF(Food!$C:$C,C$9&$B$29&$C$29,Food!$X:$X),0),"") -> 0 | D32: =IFERROR(IF($B$29=$B$29,SUMIF(Food!$C:$C,D$9&$B$29&$C$29,Food!$X:$X),0),"") -> 0 | E32: =IFERROR(IF($B$29=$B$29,SUMIF(Food!$C:$C,E$9&$B$29&$C$29,Food!$X:$X),0),"") -> 0 | F32: =IFERROR(IF($B$29=$B$29,SUMIF(Food!$C:$C,F$9&$B$29&$C$29,Food!$X:$X),0),"") -> 0 | G32: =IFERROR(IF($B$29=$B$29,SUMIF(Food!$C:$C,G$9&$B$29&$C$29,Food!$X:$X),0),"") -> 0
A33: Markup Food | B33: =IFERROR(IF($B$29=$B$29,SUMIF(Food!$C:$C,B$9&$B$29&$C$29,Food!$Z:$Z),0),"") -> 0 | C33: =IFERROR(IF($B$29=$B$29,SUMIF(Food!$C:$C,C$9&$B$29&$C$29,Food!$Z:$Z),0),"") -> 0 | D33: =IFERROR(IF($B$29=$B$29,SUMIF(Food!$C:$C,D$9&$B$29&$C$29,Food!$Z:$Z),0),"") -> 0 | E33: =IFERROR(IF($B$29=$B$29,SUMIF(Food!$C:$C,E$9&$B$29&$C$29,Food!$Z:$Z),0),"") -> 0 | F33: =IFERROR(IF($B$29=$B$29,SUMIF(Food!$C:$C,F$9&$B$29&$C$29,Food!$Z:$Z),0),"") -> 0 | G33: =IFERROR(IF($B$29=$B$29,SUMIF(Food!$C:$C,G$9&$B$29&$C$29,Food!$O:$O),0),"") -> 0
A34: Markup Labor | B34: =IFERROR(IF($B$29=$B$29,SUMIF(Food!$C:$C,B$9&$B$29&$C$29,Food!$AA:$AA),0),"") -> 0 | C34: =IFERROR(IF($B$29=$B$29,SUMIF(Food!$C:$C,C$9&$B$29&$C$29,Food!$AA:$AA),0),"") -> 0 | D34: =IFERROR(IF($B$29=$B$29,SUMIF(Food!$C:$C,D$9&$B$29&$C$29,Food!$AA:$AA),0),"") -> 0 | E34: =IFERROR(IF($B$29=$B$29,SUMIF(Food!$C:$C,E$9&$B$29&$C$29,Food!$AA:$AA),0),"") -> 0 | F34: =IFERROR(IF($B$29=$B$29,SUMIF(Food!$C:$C,F$9&$B$29&$C$29,Food!$AA:$AA),0),"") -> 0 | G34: =IFERROR(IF($B$29=$B$29,SUMIF(Food!$C:$C,G$9&$B$29&$C$29,Food!$P:$P),0),"") -> 0
A36: Per Pax Avg
A37: OVERHEAD | B37: ='P&L'!$J$30 -> 0 | C37: ='P&L'!$K$30 -> 4 | D37: ='P&L'!$L$30 -> 3 | E37: ='P&L'!$M$30 -> 2.5 | F37: ='P&L'!$N$30 -> 3 | G37: ='P&L'!$O$30 -> 3
A38: Food Cost (DM) | B38: =IFERROR(B31/B7," ") | C38: =IFERROR(C31/C7," ") -> 0 | D38: =IFERROR(D31/D7," ") -> 0 | E38: =IFERROR(E31/E7," ") -> 0 | F38: =IFERROR(F31/F7," ") -> 0 | G38: =IFERROR(G31/G7," ") -> 0
A39: Wage Cost (DL) | B39: =IFERROR(B32/B7," ") | C39: =IFERROR(C32/C7," ") -> 0 | D39: =IFERROR(D32/D7," ") -> 0 | E39: =IFERROR(E32/E7," ") -> 0 | F39: =IFERROR(F32/F7," ") -> 0 | G39: =IFERROR(G32/G7," ") -> 0
A40: Markup Food | B40: =IFERROR(B33/B8," ") | C40: =IFERROR(C33/C7," ") -> 0 | D40: =IFERROR(D33/D7," ") -> 0 | E40: =IFERROR(E33/E7," ") -> 0 | F40: =IFERROR(F33/F7," ") -> 0 | G40: =IFERROR(G33/G7," ") -> 0
A41: Markup Labor | B41: =IFERROR(B34/B7," ") | C41: =IFERROR(C34/C7," ") -> 0 | D41: =IFERROR(D34/D7," ") -> 0 | E41: =IFERROR(E34/E7," ") -> 0 | F41: =IFERROR(F34/F7," ") -> 0 | G41: =IFERROR(G34/G7," ") -> 0
A108: 388
A109: 787

Sheet Summary 2855
A2: Customer | G2: Flights Per week | H2: 0 | L2: AC type | M2: Cycle
E3: AC Type | F3: 738 | G3: Flights Per Month | H3: =H4/12 -> 0 | J3: Total Revenues | L3: 737 | M3: 1
E4: Load | F4: ='P&L'!P4 -> 0.8 | G4: Annual Flights | H4: =H2*52 -> 0 | J4: =H17*H4 -> 0
A5: Summary
A6: BNA | B6: FC | C6: BC | D6: PY | E6: EY | F6: TC | G6: CY | H6: Total | I6: Hnd
A7: FLIGHT CONFIG | B7: =+FlightConfig!B17 -> 0 | C7: =+FlightConfig!C17 -> 32 | D7: =+FlightConfig!D17 -> 56 | E7: =+FlightConfig!E17 -> 174 | F7: =+FlightConfig!F17 -> 2 | G7: =+FlightConfig!G17 -> 8 | H7: =SUM(B7:G7) -> 272
A8: Load Factor | B8: =ROUNDUP(B7*$F$4,0) -> 0 | C8: =ROUNDUP(C7*$F$4,0) -> 26 | D8: =ROUNDUP(D7*$F$4,0) -> 45 | E8: =ROUNDUP(E7*$F$4,0) -> 140 | F8: =ROUNDUP(F7*$F$4,0) -> 2 | G8: =ROUNDUP(G7*$F$4,0) -> 7 | H8: =SUM(B8:G8) -> 220
B9: FIRST CLASS | C9: BUSINESS CLASS | D9: PREMIUM ECONOMY CLASS | E9: ECONOMY CLASS | F9: TECH CREW CLASS | G9: cABIN CREW CLASS | H9: Per Flight | J9: Annual
A10: OVERHEAD | B10: =B37*B8 -> 0 | C10: =C37*C8 -> 104 | D10: =D37*D8 -> 135 | E10: =E37*E8 -> 350 | F10: =F37*F8 -> 6 | G10: =G37*G8 -> 21 | H10: =SUM(B10:G10) -> 616 | J10: =H10*$H$4 -> 0
A11: Food Cost (DM) | B11: =IFERROR(B38*B8,0) -> 0 | C11: =IFERROR(C38*$C$8,0) -> 0 | D11: =IFERROR(D38*$D$8,0) -> 0 | E11: =IFERROR(E38*$E$8,0) -> 0 | F11: =IFERROR(F38*$F$8,0) -> 0 | G11: =IFERROR(G38*G8,0) -> 0 | H11: =SUM(B11:G11) -> 0 | I11: =I12*45% -> 0 | J11: =H11*$H$4 -> 0
A12: Wage Cost (DL) | B12: =IFERROR(B39*B8,0) -> 0 | C12: =IFERROR(C39*$C$8,0) -> 0 | D12: =IFERROR(D39*$D$8,0) -> 0 | E12: =IFERROR(E39*$E$8,0) -> 0 | F12: =IFERROR(F39*$F$8,0) -> 0 | G12: =IFERROR(G39*G8,0) -> 0 | H12: =SUM(B12:G12) -> 0 | I12: =H11+H12 -> 0 | J12: =H12*$H$4 -> 0
A13: Food Mark up | B13: =IFERROR(B40*B8," ") | C13: =IFERROR(C40*$C$8,0) -> 0 | D13: =IFERROR(D40*$D$8,0) -> 0 | E13: =IFERROR(E40*$E$8,0) -> 0 | F13: =IFERROR(F40*$F$8,0) -> 0 | G13: 0 | H13: =SUM(B13:G13) -> 0 | J13: =H13*$H$4 -> 0
A14: Labor Mark up | B14: =IFERROR(B41*B8," ") | C14: =IFERROR(C41*$C$8,0) -> 0 | D14: =IFERROR(D41*$D$8,0) -> 0 | E14: =IFERROR(E41*$E$8,0) -> 0 | F14: =IFERROR(F41*$F$8,0) -> 0 | G14: 0 | H14: =SUM(B14:G14) -> 0 | J14: =H14*$H$4 -> 0 | L14: Direct Labour
A15: Handling Cost | B15: 0 | C15: 0 | D15: 0 | E15: =+B20 -> 0 | F15: 0 | G15: 0 | H15: =SUM(B15:G15) -> 0 | J15: =H15*$H$4 -> 0 | L15: =J12+J15 -> 0 | M15: 1
A16: Handling Mark up | B16: 0 | C16: 0 | D16: 0 | E16: =+C20 -> 0 | F16: 0 | G16: 0 | H16: =SUM(B16:G16) -> 0 | J16: =H16*$H$4 -> 0 | L16: =L15*M16 -> 0 | M16: 0.8
A17: Total Per Flight | B17: =SUM(B11:B16) -> 0 | C17: =SUM(C11:C16) -> 0 | D17: =SUM(D10:D16) -> 135 | E17: =SUM(E10:E16) -> 350 | F17: =SUM(F10:F16) -> 6 | G17: =SUM(G10:G16) -> 21 | H17: =SUM(H10:H16) -> 616 | J17: =H17*$H$4 -> 0 | L17: =L15*M17 -> 0 | M17: 0.2
B18: =B17 -> 0 | C18: =C17 -> 0 | D18: =D17 -> 135 | E18: =E17-E15-E16 -> 350 | F18: =F17 -> 6 | G18: =G17 -> 21 | I18: =E15+E16 -> 0
A19: Handling | B19: Cost | C19: Mark Up | D19: Price | I19: =E16 -> 0
A20: 738 Handling | B20: =Handling!C58 -> 0 | C20: =B20*'P&L'!$P$10 -> 0 | D20: =SUM(B20:C20) -> 0
A21: B777 Handling | B21: =Handling!#REF! -> #REF! | C21: =Handling!#REF! -> #REF! | D21: =Handling!#REF! -> #REF!
A22: A380 Handling | B22: =Handling!#REF! -> #REF! | C22: =Handling!#REF! -> #REF! | D22: =Handling!#REF! -> #REF!
A24: Avg Price Per Pax | B24: =IFERROR(((B11+B12+B13+B14)/B8),0) -> 0 | C24: =IFERROR(((C11+C12+C13+C14)/C8),0) -> 0 | D24: =IFERROR(((D10+D11+D12+D13+D14)/D8),0) -> 3 | E24: =IFERROR(((E10+E11+E12+E13+E14)/E8),0) -> 2.5 | F24: =IFERROR(((F10+F11+F12+F13+F14)/F8),0) -> 3 | G24: =IFERROR(((G10+G11+G12+G13+G14)/G8),0) -> 3
A25: Avg Mark up Per Pax | B25: =IFERROR(((B13+B14)/B8),0) -> 0 | C25: =IFERROR(((C13+C14)/C8),0) -> 0 | D25: =IFERROR(((D13+D14)/D8),0) -> 0 | E25: =IFERROR(((E13+E14)/E8),0) -> 0 | F25: =IFERROR(((F13+F14)/F8),0) -> 0 | G25: =IFERROR(((G13+G14)/G8),0) -> 0
A26: Over head Per Pax | B26: =IFERROR((B10/B8),0) -> 0 | C26: =IFERROR((C10/C8),0) -> 4 | D26: =IFERROR((D10/D8),0) -> 3 | E26: =IFERROR((E10/E8),0) -> 2.5 | F26: =IFERROR((F10/F8),0) -> 3 | G26: =IFERROR((G10/G8),0) -> 3
B28: CYCLE | C28: FLT
A29: Config | B29: ='P&L'!P5 -> 3 | C29: 2855
A30: OVERHEAD | B30: =B37*B8 -> 0 | C30: =C37*C8 -> 104 | D30: =D37*D8 -> 135 | E30: =E37*E8 -> 350 | F30: =F37*F8 -> 6 | G30: =G37*G8 -> 21
A31: Food Cost (DM) | B31: =IFERROR(IF($B$29=$B$29,SUMIF(Food!$C:$C,B$9&$B$29&$C$29,Food!$V:$V),0),"") -> 0 | C31: =IFERROR(IF($B$29=$B$29,SUMIF(Food!$C:$C,C$9&$B$29&$C$29,Food!$V:$V),0),"") -> 0 | D31: =IFERROR(IF($B$29=$B$29,SUMIF(Food!$C:$C,D$9&$B$29&$C$29,Food!$V:$V),0),"") -> 0 | E31: =IFERROR(IF($B$29=$B$29,SUMIF(Food!$C:$C,E$9&$B$29&$C$29,Food!$V:$V),0),"") -> 0 | F31: =IFERROR(IF($B$29=$B$29,SUMIF(Food!$C:$C,F$9&$B$29&$C$29,Food!$V:$V),0),"") -> 0 | G31: =IFERROR(IF($B$29=$B$29,SUMIF(Food!$C:$C,G$9&$B$29&$C$29,Food!$V:$V),0),"") -> 0
A32: Wage Cost (DL) | B32: =IFERROR(IF($B$29=$B$29,SUMIF(Food!$C:$C,B$9&$B$29&$C$29,Food!$X:$X),0),"") -> 0 | C32: =IFERROR(IF($B$29=$B$29,SUMIF(Food!$C:$C,C$9&$B$29&$C$29,Food!$X:$X),0),"") -> 0 | D32: =IFERROR(IF($B$29=$B$29,SUMIF(Food!$C:$C,D$9&$B$29&$C$29,Food!$X:$X),0),"") -> 0 | E32: =IFERROR(IF($B$29=$B$29,SUMIF(Food!$C:$C,E$9&$B$29&$C$29,Food!$X:$X),0),"") -> 0 | F32: =IFERROR(IF($B$29=$B$29,SUMIF(Food!$C:$C,F$9&$B$29&$C$29,Food!$X:$X),0),"") -> 0 | G32: =IFERROR(IF($B$29=$B$29,SUMIF(Food!$C:$C,G$9&$B$29&$C$29,Food!$X:$X),0),"") -> 0
A33: Markup Food | B33: =IFERROR(IF($B$29=$B$29,SUMIF(Food!$C:$C,B$9&$B$29&$C$29,Food!$Z:$Z),0),"") -> 0 | C33: =IFERROR(IF($B$29=$B$29,SUMIF(Food!$C:$C,C$9&$B$29&$C$29,Food!$Z:$Z),0),"") -> 0 | D33: =IFERROR(IF($B$29=$B$29,SUMIF(Food!$C:$C,D$9&$B$29&$C$29,Food!$Z:$Z),0),"") -> 0 | E33: =IFERROR(IF($B$29=$B$29,SUMIF(Food!$C:$C,E$9&$B$29&$C$29,Food!$Z:$Z),0),"") -> 0 | F33: =IFERROR(IF($B$29=$B$29,SUMIF(Food!$C:$C,F$9&$B$29&$C$29,Food!$Z:$Z),0),"") -> 0 | G33: =IFERROR(IF($B$29=$B$29,SUMIF(Food!$C:$C,G$9&$B$29&$C$29,Food!$O:$O),0),"") -> 0
A34: Markup Labor | B34: =IFERROR(IF($B$29=$B$29,SUMIF(Food!$C:$C,B$9&$B$29&$C$29,Food!$AA:$AA),0),"") -> 0 | C34: =IFERROR(IF($B$29=$B$29,SUMIF(Food!$C:$C,C$9&$B$29&$C$29,Food!$AA:$AA),0),"") -> 0 | D34: =IFERROR(IF($B$29=$B$29,SUMIF(Food!$C:$C,D$9&$B$29&$C$29,Food!$AA:$AA),0),"") -> 0 | E34: =IFERROR(IF($B$29=$B$29,SUMIF(Food!$C:$C,E$9&$B$29&$C$29,Food!$AA:$AA),0),"") -> 0 | F34: =IFERROR(IF($B$29=$B$29,SUMIF(Food!$C:$C,F$9&$B$29&$C$29,Food!$AA:$AA),0),"") -> 0 | G34: =IFERROR(IF($B$29=$B$29,SUMIF(Food!$C:$C,G$9&$B$29&$C$29,Food!$P:$P),0),"") -> 0
A36: Per Pax Avg
A37: OVERHEAD | B37: ='P&L'!$J$30 -> 0 | C37: ='P&L'!$K$30 -> 4 | D37: ='P&L'!$L$30 -> 3 | E37: ='P&L'!$M$30 -> 2.5 | F37: ='P&L'!$N$30 -> 3 | G37: ='P&L'!$O$30 -> 3
A38: Food Cost (DM) | B38: =IFERROR(B31/B7," ") | C38: =IFERROR(C31/C7," ") -> 0 | D38: =IFERROR(D31/D7," ") -> 0 | E38: =IFERROR(E31/E7," ") -> 0 | F38: =IFERROR(F31/F7," ") -> 0 | G38: =IFERROR(G31/G7," ") -> 0
A39: Wage Cost (DL) | B39: =IFERROR(B32/B7," ") | C39: =IFERROR(C32/C7," ") -> 0 | D39: =IFERROR(D32/D7," ") -> 0 | E39: =IFERROR(E32/E7," ") -> 0 | F39: =IFERROR(F32/F7," ") -> 0 | G39: =IFERROR(G32/G7," ") -> 0
A40: Markup Food | B40: =IFERROR(B33/B8," ") | C40: =IFERROR(C33/C7," ") -> 0 | D40: =IFERROR(D33/D7," ") -> 0 | E40: =IFERROR(E33/E7," ") -> 0 | F40: =IFERROR(F33/F7," ") -> 0 | G40: =IFERROR(G33/G7," ") -> 0
A41: Markup Labor | B41: =IFERROR(B34/B7," ") | C41: =IFERROR(C34/C7," ") -> 0 | D41: =IFERROR(D34/D7," ") -> 0 | E41: =IFERROR(E34/E7," ") -> 0 | F41: =IFERROR(F34/F7," ") -> 0 | G41: =IFERROR(G34/G7," ") -> 0
A108: 388
A109: 787

Sheet Summary
A2: Customer | G2: Flights Per week | H2: ='Summary '!H2 -> 7 | L2: AC type | M2: Cycle
E3: AC Type | F3: 738 | G3: Flights Per Month | H3: =H4/2 -> 182 | J3: Total Revenues | L3: 737 | M3: 1
E4: Load | F4: ='P&L'!P4 -> 0.8 | G4: Annual Flights | H4: =H2*52 -> 364 | J4: =H18*H4 -> 1786695.1
A5: Summary
A6: BNA | B6: FC | C6: BC | D6: PY | E6: EY | F6: TC | G6: CY | H6: Total | I6: Hnd
A7: FLIGHT CONFIG | B7: =+FlightConfig!B17 -> 0 | C7: =+FlightConfig!C17 -> 32 | D7: =+FlightConfig!D17 -> 56 | E7: =+FlightConfig!E17 -> 174 | F7: =+FlightConfig!F17 -> 2 | G7: =+FlightConfig!G17 -> 8 | H7: =SUM(B7:G7) -> 272
A8: Load Factor | B8: =ROUNDUP(B7*$F$4,0) -> 0 | C8: =ROUNDUP(C7*$F$4,0) -> 26 | D8: =ROUNDUP(D7*$F$4,0) -> 45 | E8: =ROUNDUP(E7*$F$4,0) -> 140 | F8: =ROUNDUP(F7*$F$4,0) -> 2 | G8: =ROUNDUP(G7*$F$4,0) -> 7 | H8: =SUM(B8:G8) -> 220
B9: FIRST CLASS | C9: BUSINESS CLASS | D9: PREMIUM ECONOMY CLASS | E9: ECONOMY CLASS | F9: TECH CREW CLASS | G9: cABIN CREW CLASS | H9: Per Flight | J9: Annual
A10: OVERHEAD | B10: =B43*B8 -> 0 | C10: =C43*C8 -> 104 | D10: =D43*D8 -> 135 | E10: =E43*E8 -> 350 | F10: =F43*F8 -> 6 | G10: =G43*G8 -> 21 | H10: =SUM(B10:G10) -> 616 | J10: =H10*$H$4 -> 224224
A11: Food Cost (DM) | B11: =IFERROR(B44*B8,0) -> 0 | C11: =IFERROR(C44*$C$8,0) -> 479.5082 | D11: =IFERROR(D44*$D$8,0) -> 549.19246 | E11: =IFERROR(E44*$E$8,0) -> 708.7566 | F11: =IFERROR(F44*$F$8,0) -> 21.93841 | G11: =IFERROR(G44*G8,0) -> 87.89665 | H11: =SUM(B11:G11) -> 1847.2923 | I11: =I12*45% -> 1404.6052 | J11: =H11*$H$4 -> 672414.41
A12: Wage Cost (DL) | B12: =IFERROR(B45*B8,0) -> 0 | C12: =IFERROR(C45*$C$8,0) -> 274.2675 | D12: =IFERROR(D45*$D$8,0) -> 325.83214 | E12: =IFERROR(E45*$E$8,0) -> 619.93287 | F12: =IFERROR(F45*$F$8,0) -> 9.64 | G12: =IFERROR(G45*G8,0) -> 44.38 | H12: =SUM(B12:G12) -> 1274.0525 | I12: =H11+H12 -> 3121.3448 | J12: =H12*$H$4 -> 463755.12
A13: Food Mark up | B13: =IFERROR(B46*B8," ") | C13: =IFERROR(C46*$C$8,0) -> 68.792523 | D13: =IFERROR(D46*$D$8,0) -> 59.877061 | E13: =IFERROR(E46*$E$8,0) -> 107.64987 | F13: =IFERROR(F46*$F$8,0) -> 2.8519933 | G13: 0 | H13: =SUM(B13:G13) -> 239.17145 | J13: =H13*$H$4 -> 87058.406
A14: Labor Mark up | B14: =IFERROR(B47*B8," ") | C14: =IFERROR(C47*$C$8,0) -> 35.654775 | D14: =IFERROR(D47*$D$8,0) -> 42.358179 | E14: =IFERROR(E47*$E$8,0) -> 92.827917 | F14: =IFERROR(F47*$F$8,0) -> 1.2532 | G14: 0 | H14: =SUM(B14:G14) -> 172.09407 | J14: =H14*$H$4 -> 62642.242 | L14: Direct Labour
A15: Handling Cost | B15: 0 | C15: 0 | D15: 0 | E15: =+B21+B26 -> 715.08058 | F15: 0 | G15: 0 | H15: =SUM(B15:G15) -> 715.08058 | J15: =H15*$H$4 -> 260289.33 | L15: =J12+J15 -> 724044.45 | M15: 1
A16: Handling Mark up | B16: 0 | C16: 0 | D16: 0 | E16: =+C21+C26 -> 44.812011 | F16: 0 | G16: 0 | H16: =SUM(B16:G16) -> 44.812011 | J16: =H16*$H$4 -> 16311.572 | L16: =L15*M16 -> 579235.56 | M16: 0.8
A17: Extra Revenue/Loss | B17: =IFERROR(B48*$E$8,0) -> 0 | C17: =IFERROR(C48*$B$8,0) -> 0 | D17: =IFERROR(D48*F$8,0) -> 0 | E17: =IFERROR(E48*E$8,0) -> 0 | F17: =IFERROR(F48*F$8,0) -> 0 | G17: =IFERROR(G48*G$8,0) -> 0 | H17: =SUM(B17:G17) -> 0 | J17: =H17*$H$4 -> 0 | L17: =L16*M17 -> 115847.11 | M17: 0.2
A18: Total Per Flight | B18: =SUM(B11:B16) -> 0 | C18: =SUM(C11:C16) -> 858.223 | D18: =SUM(D10:D16) -> 1112.2598 | E18: =SUM(E10:E16) -> 2639.0599 | F18: =SUM(F10:F16) -> 41.683603 | G18: =SUM(G10:G16) -> 153.27665 | H18: =SUM(H10:H17) -> 4908.503 | J18: =H18*$H$4 -> 1786695.1
B19: =B18 -> 0 | C19: =C18 -> 858.223 | D19: =D18 -> 1112.2598 | E19: =E18-E15-E16 -> 1879.1673 | F19: =F18 -> 41.683603 | G19: =G18 -> 153.27665 | I19: =E15+E16 -> 759.89259
A20: Handling | B20: Cost | C20: Mark Up | D20: Price | I20: =E16 -> 44.812011
A21: 330 | B21: =Handling!C22 -> 515.08058 | C21: =B21*'P&L'!$P$10 -> 44.812011 | D21: =SUM(B21:C21) -> 559.89259
A22: B777 Handling | B22: =Handling!#REF! -> #REF! | C22: =Handling!#REF! -> #REF! | D22: =Handling!#REF! -> #REF!
A23: A380 Handling | B23: =Handling!#REF! -> #REF! | C23: =Handling!#REF! -> #REF! | D23: =Handling!#REF! -> #REF!
A25: TRASH REMOVACL | B25: Cost | C25: Mark Up | D25: Price | I25: =E21 -> 0
A26: 330 | B26: =Handling!C26 -> 200 | C26: =B26*'P&L'!$P$11 -> 0 | D26: =SUM(B26:C26) -> 200
A28: Avg Price Per Pax | B28: =IFERROR(((B11+B12+B13+B14)/B8),0) -> 0 | C28: =IFERROR(((C11+C12+C13+C14)/C8),0) -> 33.008577 | D28: =IFERROR(((D10+D11+D12+D13+D14)/D8),0) -> 24.716885 | E28: =IFERROR(((E10+E11+E12+E13+E14)/E8),0) -> 13.422623 | F28: =IFERROR(((F10+F11+F12+F13+F14)/F8),0) -> 20.841802 | G28: =IFERROR(((G10+G11+G12+G13+G14)/G8),0) -> 21.896664
A29: Avg Mark up Per Pax | B29: =IFERROR(((B13+B14)/B8),0) -> 0 | C29: =IFERROR(((C13+C14)/C8),0) -> 4.0172038 | D29: =IFERROR(((D13+D14)/D8),0) -> 2.2718942 | E29: =IFERROR(((E13+E14)/E8),0) -> 1.4319842 | F29: =IFERROR(((F13+F14)/F8),0) -> 2.0525966 | G29: =IFERROR(((G13+G14)/G8),0) -> 0
A30: Over head Per Pax | B30: =IFERROR((B10/B8),0) -> 0 | C30: =IFERROR((C10/C8),0) -> 4 | D30: =IFERROR((D10/D8),0) -> 3 | E30: =IFERROR((E10/E8),0) -> 2.5 | F30: =IFERROR((F10/F8),0) -> 3 | G30: =IFERROR((G10/G8),0) -> 3
A31: Extra Revenue/Loss Per Pax | B31: =IFERROR((B17/B8),0) -> 0 | C31: =IFERROR((C17/C8),0) -> 0 | D31: =IFERROR((D17/D8),0) -> 0 | E31: =IFERROR((E17/E8),0) -> 0 | F31: =IFERROR((F17/F8),0) -> 0 | G31: =IFERROR((G17/G8),0) -> 0
B33: CYCLE | C33: FLT
A34: Config | B34: ='P&L'!P5 -> 3
A35: OVERHEAD | B35: =B43*B8 -> 0 | C35: =C43*C8 -> 104 | D35: =D43*D8 -> 135 | E35: =E43*E8 -> 350 | F35: =F43*F8 -> 6 | G35: =G43*G8 -> 21
A36: Food Cost (DM) | B36: =IFERROR(IF($B$34=$B$34,SUMIF(Food!$C:$C,B$9&$B$34&$C$34,Food!$V:$V),0),"") -> 0 | C36: =IFERROR(IF($B$34=$B$34,SUMIF(Food!$C:$C,C$9&$B$34&$C$34,Food!$V:$V),0),"") -> 590.16394 | D36: =IFERROR(IF($B$34=$B$34,SUMIF(Food!$C:$C,D$9&$B$34&$C$34,Food!$V:$V),0),"") -> 683.43951 | E36: =IFERROR(IF($B$34=$B$34,SUMIF(Food!$C:$C,E$9&$B$34&$C$34,Food!$V:$V),0),"") -> 880.88321 | F36: =IFERROR(IF($B$34=$B$34,SUMIF(Food!$C:$C,F$9&$B$34&$C$34,Food!$V:$V),0),"") -> 21.93841 | G36: =IFERROR(IF($B$34=$B$34,SUMIF(Food!$C:$C,G$9&$B$34&$C$34,Food!$V:$V),0),"") -> 100.45331
A37: Wage Cost (DL) | B37: =IFERROR(IF($B$34=$B$34,SUMIF(Food!$C:$C,B$9&$B$34&$C$34,Food!$X:$X),0),"") -> 0 | C37: =IFERROR(IF($B$34=$B$34,SUMIF(Food!$C:$C,C$9&$B$34&$C$34,Food!$X:$X),0),"") -> 337.56 | D37: =IFERROR(IF($B$34=$B$34,SUMIF(Food!$C:$C,D$9&$B$34&$C$34,Food!$X:$X),0),"") -> 405.48 | E37: =IFERROR(IF($B$34=$B$34,SUMIF(Food!$C:$C,E$9&$B$34&$C$34,Food!$X:$X),0),"") -> 770.488 | F37: =IFERROR(IF($B$34=$B$34,SUMIF(Food!$C:$C,F$9&$B$34&$C$34,Food!$X:$X),0),"") -> 9.64 | G37: =IFERROR(IF($B$34=$B$34,SUMIF(Food!$C:$C,G$9&$B$34&$C$34,Food!$X:$X),0),"") -> 50.72
A38: Markup Food | B38: =IFERROR(IF($B$34=$B$34,SUMIF(Food!$C:$C,B$9&$B$34&$C$34,Food!$Z:$Z),0),"") -> 0 | C38: =IFERROR(IF($B$34=$B$34,SUMIF(Food!$C:$C,C$9&$B$34&$C$34,Food!$Z:$Z),0),"") -> 84.66772 | D38: =IFERROR(IF($B$34=$B$34,SUMIF(Food!$C:$C,D$9&$B$34&$C$34,Food!$Z:$Z),0),"") -> 74.513676 | E38: =IFERROR(IF($B$34=$B$34,SUMIF(Food!$C:$C,E$9&$B$34&$C$34,Food!$Z:$Z),0),"") -> 133.79341 | F38: =IFERROR(IF($B$34=$B$34,SUMIF(Food!$C:$C,F$9&$B$34&$C$34,Food!$Z:$Z),0),"") -> 2.8519933 | G38: =IFERROR(IF($B$34=$B$34,SUMIF(Food!$C:$C,G$9&$B$34&$C$34,Food!$O:$O),0),"") -> 2.3732394
A39: Markup Labor | B39: =IFERROR(IF($B$34=$B$34,SUMIF(Food!$C:$C,B$9&$B$34&$C$34,Food!$AA:$AA),0),"") -> 0 | C39: =IFERROR(IF($B$34=$B$34,SUMIF(Food!$C:$C,C$9&$B$34&$C$34,Food!$AA:$AA),0),"") -> 43.8828 | D39: =IFERROR(IF($B$34=$B$34,SUMIF(Food!$C:$C,D$9&$B$34&$C$34,Food!$AA:$AA),0),"") -> 52.7124 | E39: =IFERROR(IF($B$34=$B$34,SUMIF(Food!$C:$C,E$9&$B$34&$C$34,Food!$AA:$AA),0),"") -> 115.37184 | F39: =IFERROR(IF($B$34=$B$34,SUMIF(Food!$C:$C,F$9&$B$34&$C$34,Food!$AA:$AA),0),"") -> 1.2532 | G39: =IFERROR(IF($B$34=$B$34,SUMIF(Food!$C:$C,G$9&$B$34&$C$34,Food!$P:$P),0),"") -> 1.3312
A40: Extra Revenue/Loss | B40: =IFERROR(IF($B$34=$B$34,SUMIF(Food!$C:$C,B$9&$B$34&$C$34,Food!$AA:$AA),0),"") -> 0 | C40: =IFERROR(IF($B$34=$B$34,SUMIF(Food!$C:$C,C$9&$B$34&$C$34,Food!#REF!),0),"") | D40: =IFERROR(IF($B$34=$B$34,SUMIF(Food!$C:$C,D$9&$B$34&$C$34,Food!#REF!),0),"") | E40: =IFERROR(IF($B$34=$B$34,SUMIF(Food!$C:$C,E$9&$B$34&$C$34,Food!#REF!),0),"") | F40: =IFERROR(IF($B$34=$B$34,SUMIF(Food!$C:$C,F$9&$B$34&$C$34,Food!#REF!),0),"") | G40: =IFERROR(IF($B$34=$B$34,SUMIF(Food!$C:$C,G$9&$B$34&$C$34,Food!#REF!),0),"")
A42: Per Pax Avg
A43: OVERHEAD | B43: ='P&L'!$J$30 -> 0 | C43: ='P&L'!$K$30 -> 4 | D43: ='P&L'!$L$30 -> 3 | E43: ='P&L'!$M$30 -> 2.5 | F43: ='P&L'!$N$30 -> 3 | G43: ='P&L'!$O$30 -> 3
A44: Food Cost (DM) | B44: =IFERROR(B36/B7," ") | C44: =IFERROR(C36/C7," ") -> 18.442623 | D44: =IFERROR(D36/D7," ") -> 12.204277 | E44: =IFERROR(E36/E7," ") -> 5.0625472 | F44: =IFERROR(F36/F7," ") -> 10.969205 | G44: =IFERROR(G36/G7," ") -> 12.556664
A45: Wage Cost (DL) | B45: =IFERROR(B37/B7," ") | C45: =IFERROR(C37/C7," ") -> 10.54875 | D45: =IFERROR(D37/D7," ") -> 7.2407143 | E45: =IFERROR(E37/E7," ") -> 4.428092 | F45: =IFERROR(F37/F7," ") -> 4.82 | G45: =IFERROR(G37/G7," ") -> 6.34
A46: Markup Food | B46: =IFERROR(B38/B8," ") | C46: =IFERROR(C38/C7," ") -> 2.6458663 | D46: =IFERROR(D38/D7," ") -> 1.3306014 | E46: =IFERROR(E38/E7," ") -> 0.76892763 | F46: =IFERROR(F38/F7," ") -> 1.4259966 | G46: =IFERROR(G38/G7," ") -> 0.29665492
A47: Markup Labor | B47: =IFERROR(B39/B7," ") | C47: =IFERROR(C39/C7," ") -> 1.3713375 | D47: =IFERROR(D39/D7," ") -> 0.94129286 | E47: =IFERROR(E39/E7," ") -> 0.66305655 | F47: =IFERROR(F39/F7," ") -> 0.6266 | G47: =IFERROR(G39/G7," ") -> 0.1664
A48: Extra Revenue/Loss | B48: =IFERROR(B40/B8," ") | C48: =IFERROR(C40/C8," ") | D48: =IFERROR(D40/D8," ") | E48: =IFERROR(E40/E8," ") | F48: =IFERROR(F40/F8," ") | G48: =IFERROR(G40/G8," ")
A114: 388
A115: 787

Sheet Summary 2037
A2: Customer | G2: Flights Per week | H2: 0 | L2: AC type | M2: Cycle
E3: AC Type | F3: 738 | G3: Flights Per Month | H3: =H4/12 -> 0 | J3: Total Revenues | L3: 737 | M3: 1
E4: Load | F4: ='P&L'!P4 -> 0.8 | G4: Annual Flights | H4: =H2*52 -> 0 | J4: =H17*H4 -> 0
A5: Summary
A6: BNA | B6: FC | C6: BC | D6: PY | E6: EY | F6: TC | G6: CY | H6: Total | I6: Hnd
A7: FLIGHT CONFIG | B7: =+FlightConfig!B17 -> 0 | C7: =+FlightConfig!C17 -> 32 | D7: =+FlightConfig!D17 -> 56 | E7: =+FlightConfig!E17 -> 174 | F7: =+FlightConfig!F17 -> 2 | G7: =+FlightConfig!G17 -> 8 | H7: =SUM(B7:G7) -> 272
A8: Load Factor | B8: =ROUNDUP(B7*$F$4,0) -> 0 | C8: =ROUNDUP(C7*$F$4,0) -> 26 | D8: =ROUNDUP(D7*$F$4,0) -> 45 | E8: =ROUNDUP(E7*$F$4,0) -> 140 | F8: =ROUNDUP(F7*$F$4,0) -> 2 | G8: =ROUNDUP(G7*$F$4,0) -> 7 | H8: =SUM(B8:G8) -> 220
B9: FIRST CLASS | C9: BUSINESS CLASS | D9: PREMIUM ECONOMY CLASS | E9: ECONOMY CLASS | F9: TECH CREW CLASS | G9: cABIN CREW CLASS | H9: Per Flight | J9: Annual
A10: OVERHEAD | B10: =B37*B8 -> 0 | C10: =C37*C8 -> 104 | D10: =D37*D8 -> 135 | E10: =E37*E8 -> 350 | F10: =F37*F8 -> 6 | G10: =G37*G8 -> 21 | H10: =SUM(B10:G10) -> 616 | J10: =H10*$H$4 -> 0
A11: Food Cost (DM) | B11: =IFERROR(B38*B8,0) -> 0 | C11: =IFERROR(C38*$C$8,0) -> 0 | D11: =IFERROR(D38*$D$8,0) -> 0 | E11: =IFERROR(E38*$E$8,0) -> 0 | F11: =IFERROR(F38*$F$8,0) -> 0 | G11: =IFERROR(G38*G8,0) -> 0 | H11: =SUM(B11:G11) -> 0 | I11: =I12*45% -> 0 | J11: =H11*$H$4 -> 0
A12: Wage Cost (DL) | B12: =IFERROR(B39*B8,0) -> 0 | C12: =IFERROR(C39*$C$8,0) -> 0 | D12: =IFERROR(D39*$D$8,0) -> 0 | E12: =IFERROR(E39*$E$8,0) -> 0 | F12: =IFERROR(F39*$F$8,0) -> 0 | G12: =IFERROR(G39*G8,0) -> 0 | H12: =SUM(B12:G12) -> 0 | I12: =H11+H12 -> 0 | J12: =H12*$H$4 -> 0
A13: Food Mark up | B13: =IFERROR(B40*B8," ") | C13: =IFERROR(C40*$C$8,0) -> 0 | D13: =IFERROR(D40*$D$8,0) -> 0 | E13: =IFERROR(E40*$E$8,0) -> 0 | F13: =IFERROR(F40*$F$8,0) -> 0 | G13: 0 | H13: =SUM(B13:G13) -> 0 | J13: =H13*$H$4 -> 0
A14: Labor Mark up | B14: =IFERROR(B41*B8," ") | C14: =IFERROR(C41*$C$8,0) -> 0 | D14: =IFERROR(D41*$D$8,0) -> 0 | E14: =IFERROR(E41*$E$8,0) -> 0 | F14: =IFERROR(F41*$F$8,0) -> 0 | G14: 0 | H14: =SUM(B14:G14) -> 0 | J14: =H14*$H$4 -> 0 | L14: Direct Labour
A15: Handling Cost | B15: 0 | C15: 0 | D15: 0 | E15: =+B20 -> 515.08058 | F15: 0 | G15: 0 | H15: =SUM(B15:G15) -> 515.08058 | J15: =H15*$H$4 -> 0 | L15: =J12+J15 -> 0 | M15: 1
A16: Handling Mark up | B16: 0 | C16: 0 | D16: 0 | E16: =+C20 -> 44.812011 | F16: 0 | G16: 0 | H16: =SUM(B16:G16) -> 44.812011 | J16: =H16*$H$4 -> 0 | L16: =L15*M16 -> 0 | M16: 0.8
A17: Total Per Flight | B17: =SUM(B11:B16) -> 0 | C17: =SUM(C11:C16) -> 0 | D17: =SUM(D10:D16) -> 135 | E17: =SUM(E10:E16) -> 909.89259 | F17: =SUM(F10:F16) -> 6 | G17: =SUM(G10:G16) -> 21 | H17: =SUM(H10:H16) -> 1175.8926 | J17: =H17*$H$4 -> 0 | L17: =L15*M17 -> 0 | M17: 0.2
B18: =B17 -> 0 | C18: =C17 -> 0 | D18: =D17 -> 135 | E18: =E17-E15-E16 -> 350 | F18: =F17 -> 6 | G18: =G17 -> 21 | I18: =E15+E16 -> 559.89259
A19: Handling | B19: Cost | C19: Mark Up | D19: Price | I19: =E16 -> 44.812011
A20: 738 Handling | B20: =Handling!C22 -> 515.08058 | C20: =B20*'P&L'!$P$10 -> 44.812011 | D20: =SUM(B20:C20) -> 559.89259
A21: B777 Handling | B21: =Handling!#REF! -> #REF! | C21: =Handling!#REF! -> #REF! | D21: =Handling!#REF! -> #REF!
A22: A380 Handling | B22: =Handling!#REF! -> #REF! | C22: =Handling!#REF! -> #REF! | D22: =Handling!#REF! -> #REF!
A24: Avg Price Per Pax | B24: =IFERROR(((B11+B12+B13+B14)/B8),0) -> 0 | C24: =IFERROR(((C11+C12+C13+C14)/C8),0) -> 0 | D24: =IFERROR(((D10+D11+D12+D13+D14)/D8),0) -> 3 | E24: =IFERROR(((E10+E11+E12+E13+E14)/E8),0) -> 2.5 | F24: =IFERROR(((F10+F11+F12+F13+F14)/F8),0) -> 3 | G24: =IFERROR(((G10+G11+G12+G13+G14)/G8),0) -> 3
A25: Avg Mark up Per Pax | B25: =IFERROR(((B13+B14)/B8),0) -> 0 | C25: =IFERROR(((C13+C14)/C8),0) -> 0 | D25: =IFERROR(((D13+D14)/D8),0) -> 0 | E25: =IFERROR(((E13+E14)/E8),0) -> 0 | F25: =IFERROR(((F13+F14)/F8),0) -> 0 | G25: =IFERROR(((G13+G14)/G8),0) -> 0
A26: Over head Per Pax | B26: =IFERROR((B10/B8),0) -> 0 | C26: =IFERROR((C10/C8),0) -> 4 | D26: =IFERROR((D10/D8),0) -> 3 | E26: =IFERROR((E10/E8),0) -> 2.5 | F26: =IFERROR((F10/F8),0) -> 3 | G26: =IFERROR((G10/G8),0) -> 3
B28: CYCLE | C28: FLT
A29: Config | B29: ='P&L'!P5 -> 3 | C29: 2037
A30: OVERHEAD | B30: =B37*B8 -> 0 | C30: =C37*C8 -> 104 | D30: =D37*D8 -> 135 | E30: =E37*E8 -> 350 | F30: =F37*F8 -> 6 | G30: =G37*G8 -> 21
A31: Food Cost (DM) | B31: =IFERROR(IF($B$29=$B$29,SUMIF(Food!$C:$C,B$9&$B$29&$C$29,Food!$V:$V),0),"") -> 0 | C31: =IFERROR(IF($B$29=$B$29,SUMIF(Food!$C:$C,C$9&$B$29&$C$29,Food!$V:$V),0),"") -> 0 | D31: =IFERROR(IF($B$29=$B$29,SUMIF(Food!$C:$C,D$9&$B$29&$C$29,Food!$V:$V),0),"") -> 0 | E31: =IFERROR(IF($B$29=$B$29,SUMIF(Food!$C:$C,E$9&$B$29&$C$29,Food!$V:$V),0),"") -> 0 | F31: =IFERROR(IF($B$29=$B$29,SUMIF(Food!$C:$C,F$9&$B$29&$C$29,Food!$V:$V),0),"") -> 0 | G31: =IFERROR(IF($B$29=$B$29,SUMIF(Food!$C:$C,G$9&$B$29&$C$29,Food!$V:$V),0),"") -> 0
A32: Wage Cost (DL) | B32: =IFERROR(IF($B$29=$B$29,SUMIF(Food!$C:$C,B$9&$B$29&$C$29,Food!$X:$X),0),"") -> 0 | C32: =IFERROR(IF($B$29=$B$29,SUMIF(Food!$C:$C,C$9&$B$29&$C$29,Food!$X:$X),0),"") -> 0 | D32: =IFERROR(IF($B$29=$B$29,SUMIF(Food!$C:$C,D$9&$B$29&$C$29,Food!$X:$X),0),"") -> 0 | E32: =IFERROR(IF($B$29=$B$29,SUMIF(Food!$C:$C,E$9&$B$29&$C$29,Food!$X:$X),0),"") -> 0 | F32: =IFERROR(IF($B$29=$B$29,SUMIF(Food!$C:$C,F$9&$B$29&$C$29,Food!$X:$X),0),"") -> 0 | G32: =IFERROR(IF($B$29=$B$29,SUMIF(Food!$C:$C,G$9&$B$29&$C$29,Food!$X:$X),0),"") -> 0
A33: Markup Food | B33: =IFERROR(IF($B$29=$B$29,SUMIF(Food!$C:$C,B$9&$B$29&$C$29,Food!$Z:$Z),0),"") -> 0 | C33: =IFERROR(IF($B$29=$B$29,SUMIF(Food!$C:$C,C$9&$B$29&$C$29,Food!$Z:$Z),0),"") -> 0 | D33: =IFERROR(IF($B$29=$B$29,SUMIF(Food!$C:$C,D$9&$B$29&$C$29,Food!$Z:$Z),0),"") -> 0 | E33: =IFERROR(IF($B$29=$B$29,SUMIF(Food!$C:$C,E$9&$B$29&$C$29,Food!$Z:$Z),0),"") -> 0 | F33: =IFERROR(IF($B$29=$B$29,SUMIF(Food!$C:$C,F$9&$B$29&$C$29,Food!$Z:$Z),0),"") -> 0 | G33: =IFERROR(IF($B$29=$B$29,SUMIF(Food!$C:$C,G$9&$B$29&$C$29,Food!$O:$O),0),"") -> 0
A34: Markup Labor | B34: =IFERROR(IF($B$29=$B$29,SUMIF(Food!$C:$C,B$9&$B$29&$C$29,Food!$AA:$AA),0),"") -> 0 | C34: =IFERROR(IF($B$29=$B$29,SUMIF(Food!$C:$C,C$9&$B$29&$C$29,Food!$AA:$AA),0),"") -> 0 | D34: =IFERROR(IF($B$29=$B$29,SUMIF(Food!$C:$C,D$9&$B$29&$C$29,Food!$AA:$AA),0),"") -> 0 | E34: =IFERROR(IF($B$29=$B$29,SUMIF(Food!$C:$C,E$9&$B$29&$C$29,Food!$AA:$AA),0),"") -> 0 | F34: =IFERROR(IF($B$29=$B$29,SUMIF(Food!$C:$C,F$9&$B$29&$C$29,Food!$AA:$AA),0),"") -> 0 | G34: =IFERROR(IF($B$29=$B$29,SUMIF(Food!$C:$C,G$9&$B$29&$C$29,Food!$P:$P),0),"") -> 0
A36: Per Pax Avg
A37: OVERHEAD | B37: ='P&L'!$J$30 -> 0 | C37: ='P&L'!$K$30 -> 4 | D37: ='P&L'!$L$30 -> 3 | E37: ='P&L'!$M$30 -> 2.5 | F37: ='P&L'!$N$30 -> 3 | G37: ='P&L'!$O$30 -> 3
A38: Food Cost (DM) | B38: =IFERROR(B31/B7," ") | C38: =IFERROR(C31/C7," ") -> 0 | D38: =IFERROR(D31/D7," ") -> 0 | E38: =IFERROR(E31/E7," ") -> 0 | F38: =IFERROR(F31/F7," ") -> 0 | G38: =IFERROR(G31/G7," ") -> 0
A39: Wage Cost (DL) | B39: =IFERROR(B32/B7," ") | C39: =IFERROR(C32/C7," ") -> 0 | D39: =IFERROR(D32/D7," ") -> 0 | E39: =IFERROR(E32/E7," ") -> 0 | F39: =IFERROR(F32/F7," ") -> 0 | G39: =IFERROR(G32/G7," ") -> 0
A40: Markup Food | B40: =IFERROR(B33/B8," ") | C40: =IFERROR(C33/C7," ") -> 0 | D40: =IFERROR(D33/D7," ") -> 0 | E40: =IFERROR(E33/E7," ") -> 0 | F40: =IFERROR(F33/F7," ") -> 0 | G40: =IFERROR(G33/G7," ") -> 0
A41: Markup Labor | B41: =IFERROR(B34/B7," ") | C41: =IFERROR(C34/C7," ") -> 0 | D41: =IFERROR(D34/D7," ") -> 0 | E41: =IFERROR(E34/E7," ") -> 0 | F41: =IFERROR(F34/F7," ") -> 0 | G41: =IFERROR(G34/G7," ") -> 0
A108: 388
A109: 787

Sheet Summary 2817
A2: Customer | G2: Flights Per week | H2: 0 | L2: AC type | M2: Cycle
E3: AC Type | F3: 738 | G3: Flights Per Month | H3: =H4/12 -> 0 | J3: Total Revenues | L3: 737 | M3: 1
E4: Load | F4: ='P&L'!P4 -> 0.8 | G4: Annual Flights | H4: =H2*52 -> 0 | J4: =H17*H4 -> 0
A5: Summary
A6: BNA | B6: FC | C6: BC | D6: PY | E6: EY | F6: TC | G6: CY | H6: Total | I6: Hnd
A7: FLIGHT CONFIG | B7: =+FlightConfig!B17 -> 0 | C7: =+FlightConfig!C17 -> 32 | D7: =+FlightConfig!D17 -> 56 | E7: =+FlightConfig!E17 -> 174 | F7: =+FlightConfig!F17 -> 2 | G7: =+FlightConfig!G17 -> 8 | H7: =SUM(B7:G7) -> 272
A8: Load Factor | B8: =ROUNDUP(B7*$F$4,0) -> 0 | C8: =ROUNDUP(C7*$F$4,0) -> 26 | D8: =ROUNDUP(D7*$F$4,0) -> 45 | E8: =ROUNDUP(E7*$F$4,0) -> 140 | F8: =ROUNDUP(F7*$F$4,0) -> 2 | G8: =ROUNDUP(G7*$F$4,0) -> 7 | H8: =SUM(B8:G8) -> 220
B9: FIRST CLASS | C9: BUSINESS CLASS | D9: PREMIUM ECONOMY CLASS | E9: ECONOMY CLASS | F9: TECH CREW CLASS | G9: cABIN CREW CLASS | H9: Per Flight | J9: Annual
A10: OVERHEAD | B10: =B37*B8 -> 0 | C10: =C37*C8 -> 104 | D10: =D37*D8 -> 135 | E10: =E37*E8 -> 350 | F10: =F37*F8 -> 6 | G10: =G37*G8 -> 21 | H10: =SUM(B10:G10) -> 616 | J10: =H10*$H$4 -> 0
A11: Food Cost (DM) | B11: =IFERROR(B38*B8,0) -> 0 | C11: =IFERROR(C38*$C$8,0) -> 0 | D11: =IFERROR(D38*$D$8,0) -> 0 | E11: =IFERROR(E38*$E$8,0) -> 0 | F11: =IFERROR(F38*$F$8,0) -> 0 | G11: =IFERROR(G38*G8,0) -> 0 | H11: =SUM(B11:G11) -> 0 | I11: =I12*45% -> 0 | J11: =H11*$H$4 -> 0
A12: Wage Cost (DL) | B12: =IFERROR(B39*B8,0) -> 0 | C12: =IFERROR(C39*$C$8,0) -> 0 | D12: =IFERROR(D39*$D$8,0) -> 0 | E12: =IFERROR(E39*$E$8,0) -> 0 | F12: =IFERROR(F39*$F$8,0) -> 0 | G12: =IFERROR(G39*G8,0) -> 0 | H12: =SUM(B12:G12) -> 0 | I12: =H11+H12 -> 0 | J12: =H12*$H$4 -> 0
A13: Food Mark up | B13: =IFERROR(B40*B8," ") | C13: =IFERROR(C40*$C$8,0) -> 0 | D13: =IFERROR(D40*$D$8,0) -> 0 | E13: =IFERROR(E40*$E$8,0) -> 0 | F13: =IFERROR(F40*$F$8,0) -> 0 | G13: 0 | H13: =SUM(B13:G13) -> 0 | J13: =H13*$H$4 -> 0
A14: Labor Mark up | B14: =IFERROR(B41*B8," ") | C14: =IFERROR(C41*$C$8,0) -> 0 | D14: =IFERROR(D41*$D$8,0) -> 0 | E14: =IFERROR(E41*$E$8,0) -> 0 | F14: =IFERROR(F41*$F$8,0) -> 0 | G14: 0 | H14: =SUM(B14:G14) -> 0 | J14: =H14*$H$4 -> 0 | L14: Direct Labour
A15: Handling Cost | B15: 0 | C15: 0 | D15: 0 | E15: =+B20 -> 515.08058 | F15: 0 | G15: 0 | H15: =SUM(B15:G15) -> 515.08058 | J15: =H15*$H$4 -> 0 | L15: =J12+J15 -> 0 | M15: 1
A16: Handling Mark up | B16: 0 | C16: 0 | D16: 0 | E16: =+C20 -> 44.812011 | F16: 0 | G16: 0 | H16: =SUM(B16:G16) -> 44.812011 | J16: =H16*$H$4 -> 0 | L16: =L15*M16 -> 0 | M16: 0.8
A17: Total Per Flight | B17: =SUM(B11:B16) -> 0 | C17: =SUM(C11:C16) -> 0 | D17: =SUM(D10:D16) -> 135 | E17: =SUM(E10:E16) -> 909.89259 | F17: =SUM(F10:F16) -> 6 | G17: =SUM(G10:G16) -> 21 | H17: =SUM(H10:H16) -> 1175.8926 | J17: =H17*$H$4 -> 0 | L17: =L15*M17 -> 0 | M17: 0.2
B18: =B17 -> 0 | C18: =C17 -> 0 | D18: =D17 -> 135 | E18: =E17-E15-E16 -> 350 | F18: =F17 -> 6 | G18: =G17 -> 21 | I18: =E15+E16 -> 559.89259
A19: Handling | B19: Cost | C19: Mark Up | D19: Price | I19: =E16 -> 44.812011
A20: 738 Handling | B20: =Handling!C22 -> 515.08058 | C20: =B20*'P&L'!$P$10 -> 44.812011 | D20: =SUM(B20:C20) -> 559.89259
A21: B777 Handling | B21: =Handling!#REF! -> #REF! | C21: =Handling!#REF! -> #REF! | D21: =Handling!#REF! -> #REF!
A22: A380 Handling | B22: =Handling!#REF! -> #REF! | C22: =Handling!#REF! -> #REF! | D22: =Handling!#REF! -> #REF!
A24: Avg Price Per Pax | B24: =IFERROR(((B11+B12+B13+B14)/B8),0) -> 0 | C24: =IFERROR(((C11+C12+C13+C14)/C8),0) -> 0 | D24: =IFERROR(((D10+D11+D12+D13+D14)/D8),0) -> 3 | E24: =IFERROR(((E10+E11+E12+E13+E14)/E8),0) -> 2.5 | F24: =IFERROR(((F10+F11+F12+F13+F14)/F8),0) -> 3 | G24: =IFERROR(((G10+G11+G12+G13+G14)/G8),0) -> 3
A25: Avg Mark up Per Pax | B25: =IFERROR(((B13+B14)/B8),0) -> 0 | C25: =IFERROR(((C13+C14)/C8),0) -> 0 | D25: =IFERROR(((D13+D14)/D8),0) -> 0 | E25: =IFERROR(((E13+E14)/E8),0) -> 0 | F25: =IFERROR(((F13+F14)/F8),0) -> 0 | G25: =IFERROR(((G13+G14)/G8),0) -> 0
A26: Over head Per Pax | B26: =IFERROR((B10/B8),0) -> 0 | C26: =IFERROR((C10/C8),0) -> 4 | D26: =IFERROR((D10/D8),0) -> 3 | E26: =IFERROR((E10/E8),0) -> 2.5 | F26: =IFERROR((F10/F8),0) -> 3 | G26: =IFERROR((G10/G8),0) -> 3
B28: CYCLE | C28: FLT
A29: Config | B29: ='P&L'!P5 -> 3 | C29: 2817
A30: OVERHEAD | B30: =B37*B8 -> 0 | C30: =C37*C8 -> 104 | D30: =D37*D8 -> 135 | E30: =E37*E8 -> 350 | F30: =F37*F8 -> 6 | G30: =G37*G8 -> 21
A31: Food Cost (DM) | B31: =IFERROR(IF($B$29=$B$29,SUMIF(Food!$C:$C,B$9&$B$29&$C$29,Food!$V:$V),0),"") -> 0 | C31: =IFERROR(IF($B$29=$B$29,SUMIF(Food!$C:$C,C$9&$B$29&$C$29,Food!$V:$V),0),"") -> 0 | D31: =IFERROR(IF($B$29=$B$29,SUMIF(Food!$C:$C,D$9&$B$29&$C$29,Food!$V:$V),0),"") -> 0 | E31: =IFERROR(IF($B$29=$B$29,SUMIF(Food!$C:$C,E$9&$B$29&$C$29,Food!$V:$V),0),"") -> 0 | F31: =IFERROR(IF($B$29=$B$29,SUMIF(Food!$C:$C,F$9&$B$29&$C$29,Food!$V:$V),0),"") -> 0 | G31: =IFERROR(IF($B$29=$B$29,SUMIF(Food!$C:$C,G$9&$B$29&$C$29,Food!$V:$V),0),"") -> 0
A32: Wage Cost (DL) | B32: =IFERROR(IF($B$29=$B$29,SUMIF(Food!$C:$C,B$9&$B$29&$C$29,Food!$X:$X),0),"") -> 0 | C32: =IFERROR(IF($B$29=$B$29,SUMIF(Food!$C:$C,C$9&$B$29&$C$29,Food!$X:$X),0),"") -> 0 | D32: =IFERROR(IF($B$29=$B$29,SUMIF(Food!$C:$C,D$9&$B$29&$C$29,Food!$X:$X),0),"") -> 0 | E32: =IFERROR(IF($B$29=$B$29,SUMIF(Food!$C:$C,E$9&$B$29&$C$29,Food!$X:$X),0),"") -> 0 | F32: =IFERROR(IF($B$29=$B$29,SUMIF(Food!$C:$C,F$9&$B$29&$C$29,Food!$X:$X),0),"") -> 0 | G32: =IFERROR(IF($B$29=$B$29,SUMIF(Food!$C:$C,G$9&$B$29&$C$29,Food!$X:$X),0),"") -> 0
A33: Markup Food | B33: =IFERROR(IF($B$29=$B$29,SUMIF(Food!$C:$C,B$9&$B$29&$C$29,Food!$Z:$Z),0),"") -> 0 | C33: =IFERROR(IF($B$29=$B$29,SUMIF(Food!$C:$C,C$9&$B$29&$C$29,Food!$Z:$Z),0),"") -> 0 | D33: =IFERROR(IF($B$29=$B$29,SUMIF(Food!$C:$C,D$9&$B$29&$C$29,Food!$Z:$Z),0),"") -> 0 | E33: =IFERROR(IF($B$29=$B$29,SUMIF(Food!$C:$C,E$9&$B$29&$C$29,Food!$Z:$Z),0),"") -> 0 | F33: =IFERROR(IF($B$29=$B$29,SUMIF(Food!$C:$C,F$9&$B$29&$C$29,Food!$Z:$Z),0),"") -> 0 | G33: =IFERROR(IF($B$29=$B$29,SUMIF(Food!$C:$C,G$9&$B$29&$C$29,Food!$O:$O),0),"") -> 0
A34: Markup Labor | B34: =IFERROR(IF($B$29=$B$29,SUMIF(Food!$C:$C,B$9&$B$29&$C$29,Food!$AA:$AA),0),"") -> 0 | C34: =IFERROR(IF($B$29=$B$29,SUMIF(Food!$C:$C,C$9&$B$29&$C$29,Food!$AA:$AA),0),"") -> 0 | D34: =IFERROR(IF($B$29=$B$29,SUMIF(Food!$C:$C,D$9&$B$29&$C$29,Food!$AA:$AA),0),"") -> 0 | E34: =IFERROR(IF($B$29=$B$29,SUMIF(Food!$C:$C,E$9&$B$29&$C$29,Food!$AA:$AA),0),"") -> 0 | F34: =IFERROR(IF($B$29=$B$29,SUMIF(Food!$C:$C,F$9&$B$29&$C$29,Food!$AA:$AA),0),"") -> 0 | G34: =IFERROR(IF($B$29=$B$29,SUMIF(Food!$C:$C,G$9&$B$29&$C$29,Food!$P:$P),0),"") -> 0
A36: Per Pax Avg
A37: OVERHEAD | B37: ='P&L'!$J$30 -> 0 | C37: ='P&L'!$K$30 -> 4 | D37: ='P&L'!$L$30 -> 3 | E37: ='P&L'!$M$30 -> 2.5 | F37: ='P&L'!$N$30 -> 3 | G37: ='P&L'!$O$30 -> 3
A38: Food Cost (DM) | B38: =IFERROR(B31/B7," ") | C38: =IFERROR(C31/C7," ") -> 0 | D38: =IFERROR(D31/D7," ") -> 0 | E38: =IFERROR(E31/E7," ") -> 0 | F38: =IFERROR(F31/F7," ") -> 0 | G38: =IFERROR(G31/G7," ") -> 0
A39: Wage Cost (DL) | B39: =IFERROR(B32/B7," ") | C39: =IFERROR(C32/C7," ") -> 0 | D39: =IFERROR(D32/D7," ") -> 0 | E39: =IFERROR(E32/E7," ") -> 0 | F39: =IFERROR(F32/F7," ") -> 0 | G39: =IFERROR(G32/G7," ") -> 0
A40: Markup Food | B40: =IFERROR(B33/B8," ") | C40: =IFERROR(C33/C7," ") -> 0 | D40: =IFERROR(D33/D7," ") -> 0 | E40: =IFERROR(E33/E7," ") -> 0 | F40: =IFERROR(F33/F7," ") -> 0 | G40: =IFERROR(G33/G7," ") -> 0
A41: Markup Labor | B41: =IFERROR(B34/B7," ") | C41: =IFERROR(C34/C7," ") -> 0 | D41: =IFERROR(D34/D7," ") -> 0 | E41: =IFERROR(E34/E7," ") -> 0 | F41: =IFERROR(F34/F7," ") -> 0 | G41: =IFERROR(G34/G7," ") -> 0
A108: 388
A109: 787

Sheet Handling
A1: HANDLING CALCULATOR
B2: ALL AC TYPE
A3: STATION | B3: BNA | D3: Aircraft type | E3: =FlightConfig!B1 -> 330
A4: AC TYPE | B4: =+E3 -> 330 | D4: BNA | E4: FC | F4: BC | G4: EU | H4: EY | I4: CY | J4: Total
A5: # OF DAYS OPERATING | B5: =+FlightConfig!K2 -> 7 | D5: FLIGHT CONFIG | E5: =FlightConfig!B3 -> 0 | F5: =FlightConfig!C3 -> 32 | G5: =FlightConfig!D3 -> 56 | H5: =FlightConfig!E3 -> 174 | I5: =FlightConfig!G3+FlightConfig!F11 -> 9 | J5: =SUM(E5:I5) -> 271
A7: LABOR | H7: 0.2
A8: POSITION | B8: No. of SHIFTS | C8: HOURS | D8: SHIFTS/WK | E8: ANNUAL HOURS | F8: RATE | G8: EMP COST | H8: TOTAL/HR | I8: ANNUAL | J8: PER FLIGHT
A9: EQ PACKER | B9: 2 | C9: 2.5 | D9: =$B$5*B9 -> 14 | E9: =C9*D9*52 -> 1820 | F9: 18 | G9: =F9*$H$7 -> 3.6 | H9: =F9+G9 -> 21.6 | I9: =E9*H9 -> 39312 | J9: =(B9*H9)*C9 -> 108 | L9: EMD
A10: DISHWASHER | B10: 2 | C10: 3 | D10: =$B$5*B10 -> 14 | E10: =C10*D10*52 -> 2184 | F10: 17 | G10: =F10*$H$7 -> 3.4 | H10: =F10+G10 -> 20.4 | I10: =E10*H10 -> 44553.6 | J10: =(B10*H10)*C10 -> 122.4 | L10: Van Charge | O10: ='P&L'!P10 -> 0.087
A11: Ramp Coordinator | B11: 1 | C11: 3 | D11: =$B$5*B11 -> 7 | E11: =C11*D11*52 -> 1092 | F11: 22 | G11: =F11*$H$7 -> 4.4 | H11: =F11+G11 -> 26.4 | I11: =E11*H11 -> 28828.8 | J11: =(B11*H11)*C11 -> 79.2 | L11: Labor | M11: Tuck | N11: total | O11: mark up | P11: Selling price
A12: INVENTORY CLERK | B12: 1 | C12: 0.25 | D12: =$B$5*B12 -> 7 | E12: =C12*D12*52 -> 91 | F12: 19 | G12: =F12*$H$7 -> 3.8 | H12: =F12+G12 -> 22.8 | I12: =E12*H12 -> 2074.8 | J12: =(B12*H12)*C12 -> 5.7 | L12: =H13/2 -> 15 | M12: 12 | N12: =L12+M12 -> 27 | O12: =N12*O10 -> 2.349 | P12: =N12+O12 -> 29.349
A13: DRIVER | B13: 2 | C13: 3 | D13: =$B$5*B13 -> 14 | E13: =C13*D13*52 -> 2184 | F13: 25 | G13: =F13*$H$7 -> 5 | H13: =F13+G13 -> 30 | I13: =E13*H13 -> 65520 | J13: =(B13*H13)*C13 -> 180 | K13: 0.5h consider van charge
A14: Total | I14: =SUM(I9:I13) -> 180289.2 | J14: =SUM(J9:J13) -> 495.3
A17: TRUCK COSTS | B17: No. of TRUCKS | C17: OP HOURS | D17: TTL OP HRS | E17: DEP./DAY | F17: DEP/HR APPLIED | G17: DEP $ | H17: FUEL | I17: MAIN/FEES/DAY | K17: MAIN COST | L17: TOTAL COST | N17: FUEL COST CALCULATOR
A18: A380 TRUCKS | B18: 0 | C18: 0 | D18: =B18*C18 -> 0 | E18: =500000/10/365 -> 136.9863 | F18: =24/3 -> 8 | G18: =(E18/24)*F18*$B18 -> 0 | H18: =O23*B18 -> 0 | I18: =8000/365 -> 21.917808 | K18: =(I18/24)*$G18*$C18 -> 0 | L18: =G18+H18+K18 -> 0 | N18: ROUND TRIP MILES | O18: 10
A19: NARROWBODY TRUCKS | B19: 1 | C19: 3 | D19: =B19*C19 -> 3 | E19: =100000/365 -> 273.9726 | F19: 1 | G19: =E19*F19/'[4]P&L'!$P$2 -> 7.2098053 | H19: =O23 -> 12 | I19: =5000/365 -> 13.69863 | K19: =(I19/24)*$F19*$B19 -> 0.57077626 | L19: =G19+H19+K19 -> 19.780582 | N19: IDLE MILES | O19: 5
N20: TTL MILES | O20: =O18+O19 -> 15
N21: MPG | O21: 5
A22: TOTAL HANDLING COST | C22: =SUM(J14,L18,L19) -> 515.08058 | N22: $/GAL | O22: 4
A23: MARK-UP | B23: =+'P&L'!$P$10 -> 0.087 | C23: =C22*B23 -> 44.812011 | E23: Terminator | F23: Originator | N23: FUEL $ | O23: =(O20/O21)*O22 -> 12
A24: TOTAL HANDLING PRICE | C24: =C22+C23 -> 559.89259 | D24: Turnaround | E24: =C24*1.25*0.6 -> 419.91944 | F24: =C24*1.25-E24 -> 279.9463
A26: INTERNATIONAL GARBAGE | C26: 200
A27: MARK-UP | B27: ='P&L'!P11 -> 0 | C27: =C26*B27 -> 0
A28: TOTAL HANDLING PRICE | C28: =C26+C27 -> 200
A30: ASSUMPTIONS
A31: One coordinator
A32: Two trucks
A33: Two helpers
A39: HANDLING CALCULATOR
B40: ALL AC TYPE
A41: STATION | B41: BNA | D41: Aircraft type | E41: =FlightConfig!#REF! -> #REF!
A42: AC TYPE | B42: 350 | D42: ATL | E42: FC | F42: BC | G42: EU | H42: EY | I42: CY | J42: Total
A43: # OF DAYS OPERATING | B43: 5 | D43: FLIGHT CONFIG | E43: 0 | F43: 40 | G43: 32 | H43: 228 | I43: 2 | J43: 9
A45: LABOR | H45: 0.2
A46: POSITION | B46: No. of SHIFTS | C46: HOURS | D46: SHIFTS/WK | E46: ANNUAL HOURS | F46: RATE | G46: EMP COST | H46: TOTAL/HR | I46: ANNUAL | J46: PER FLIGHT
A47: PACKER/QC | B47: 2 | C47: 3 | D47: =$B$5*B47 -> 14 | E47: =C47*D47*52 -> 2184 | F47: 18 | G47: =F47*$H$7 -> 3.6 | H47: =F47+G47 -> 21.6 | I47: =E47*H47 -> 47174.4 | J47: =(B47*H47)*C47 -> 129.6 | L47: EMD
A48: DISHWASHER | B48: 2 | C48: 3 | D48: =$B$5*B48 -> 14 | E48: =C48*D48*52 -> 2184 | F48: 17 | G48: =F48*$H$7 -> 3.4 | H48: =F48+G48 -> 20.4 | I48: =E48*H48 -> 44553.6 | J48: =(B48*H48)*C48 -> 122.4 | L48: Van Charge | O48: ='P&L'!P45 -> 0
A49: Ramp Coordinator | B49: 1 | C49: 3 | D49: =$B$5*B49 -> 7 | E49: =C49*D49*52 -> 1092 | F49: 22 | G49: =F49*$H$7 -> 4.4 | H49: =F49+G49 -> 26.4 | I49: =E49*H49 -> 28828.8 | J49: =(B49*H49)*C49 -> 79.2 | L49: Labor | M49: Tuck | N49: total | O49: mark up | P49: Selling price
A50: INVENTORY CLERK | B50: 1 | C50: 0.25 | D50: =$B$5*B50 -> 7 | E50: =C50*D50*52 -> 91 | F50: 19 | G50: =F50*$H$7 -> 3.8 | H50: =F50+G50 -> 22.8 | I50: =E50*H50 -> 2074.8 | J50: =(B50*H50)*C50 -> 5.7 | L50: =H51/2 -> 15 | M50: 12 | N50: =L50+M50 -> 27 | O50: =N50*O48 -> 0 | P50: =N50+O50 -> 27
A51: DRIVER | B51: 2 | C51: 3 | D51: =$B$5*B51 -> 14 | E51: =C51*D51*52 -> 2184 | F51: 25 | G51: =F51*$H$7 -> 5 | H51: =F51+G51 -> 30 | I51: =E51*H51 -> 65520 | J51: =(B51*H51)*C51 -> 180
A52: Total | I52: =SUM(I47:I51) -> 188151.6 | J52: =SUM(J47:J51) -> 516.9
A55: TRUCK COSTS | B55: No. of TRUCKS | C55: OP HOURS | D55: TTL OP HRS | E55: DEP./DAY | F55: DEP/HR APPLIED | G55: DEP $ | H55: FUEL | I55: MAIN/FEES/DAY | K55: MAIN COST | L55: TOTAL COST | N55: FUEL COST CALCULATOR
A56: A380 TRUCKS | B56: 0 | C56: 0 | D56: =B56*C56 -> 0 | E56: =500000/10/365 -> 136.9863 | F56: =24/3 -> 8 | G56: =(E56/24)*F56*$B56 -> 0 | H56: =O61*B56 -> 0 | I56: =8000/365 -> 21.917808 | K56: =(I56/24)*$G56*$C56 -> 0 | L56: =G56+H56+K56 -> 0 | N56: ROUND TRIP MILES | O56: 10
A57: NARROWBODY TRUCKS | B57: 1 | C57: 3 | D57: =B57*C57 -> 3 | E57: =100000/365 -> 273.9726 | F57: 1 | G57: =E57*F57/'[4]P&L'!$P$2 -> 7.2098053 | H57: =O61 -> 12 | I57: =5000/365 -> 13.69863 | K57: =(I57/24)*$F57*$B57 -> 0.57077626 | L57: =G57+H57+K57 -> 19.780582 | N57: IDLE MILES | O57: 5
N58: TTL MILES | O58: =O56+O57 -> 15
N59: MPG | O59: 5
A60: TOTAL HANDLING COST | C60: =SUM(J52,L56,L57) -> 536.68058 | N60: $/GAL | O60: 4
A61: MARK-UP | B61: ='P&L'!P10 -> 0.087 | C61: =C60*B61 -> 46.691211 | E61: long hual | F61: short hual | N61: FUEL $ | O61: =(O58/O59)*O60 -> 12
A62: TOTAL HANDLING PRICE | C62: =C60+C61 -> 583.37179 | D62: Turnaround | E62: 544.68493 | F62: 399.93493

Sheet FlightConfig
A1: Aircraft type | B1: 330 | J1: WEEKS | K1: =IF($B$1=388,K15,K9) -> 52
A2: DFW | B2: FC | C2: BC | D2: EU | E2: EY | F2: TC | G2: CY | H2: Total | J2: FLIGHTS/WEEK | K2: =IF($B$1=330,K16,K16) -> 7
A3: FLIGHT CONFIG | B3: 0 | C3: 32 | D3: 56 | E3: 174 | F3: 2 | G3: 8 | H3: =IF($B$1=737,H17,IF($B$1=737,H23,IF($B$1=380,H23))) -> FALSE | J3: FLTS PER YEAR | K3: =IF($B$1=330,K17,K11) -> 364
A4: LOAD FACTORS | B4: =+'P&L'!$P$4 -> 0.8 | C4: =+'P&L'!$P$4 -> 0.8 | D4: =+'P&L'!$P$4 -> 0.8 | E4: =+'P&L'!$P$4 -> 0.8 | F4: =+'P&L'!$P$4 -> 0.8 | G4: =+'P&L'!$P$4 -> 0.8 | J4: # OF CYCLES | K4: =IF($B$1=737,K18,K12) -> 1
A5: PAX COUNT | B5: =ROUNDUP(B3*B4,0) -> 0 | C5: =ROUNDUP(C3*C4,0) -> 26 | D5: =ROUNDUP(D3*D4,0) -> 45 | E5: =ROUNDUP(E3*E4,0) -> 140 | F5: =ROUNDUP(F3*F4,0) -> 2 | G5: =ROUNDUP(G3*G4,0) -> 7 | H5: =SUM(B5:G5) -> 220 | J5: FLTS PER CYCLE | K5: =K19 -> 365
A9: Aircraft type | B9: 787 | J9: WEEKS | K9: 52
A10: DFW | B10: FC | C10: BC | D10: EU | E10: EY | F10: TC | G10: CY | H10: Total | J10: FLIGHTS/WEEK | K10: 5
A11: FLIGHT CONFIG | B11: 0 | C11: 0 | D11: 36 | E11: 323 | F11: 1 | G11: 10 | H11: =SUM(B11:G11) -> 370 | J11: FLTS PER YEAR | K11: =K9*K10 -> 260
A12: LOAD FACTORS | B12: 1 | C12: 1 | D12: 1 | E12: 1 | F12: 1 | G12: 1 | J12: # OF CYCLES | K12: 1
A13: PAX COUNT | B13: =ROUNDUP(B11*B12,0) -> 0 | C13: =ROUNDUP(C11*C12,0) -> 0 | D13: =ROUNDUP(D11*D12,0) -> 36 | E13: =ROUNDUP(E11*E12,0) -> 323 | F13: =ROUNDUP(F11*F12,0) -> 1 | G13: =ROUNDUP(G11*G12,0) -> 10 | H13: =SUM(B13:G13) -> 370 | J13: FLTS PER CYCLE | K13: =K11/K12 -> 260
A15: Aircraft type | B15: 330 | J15: WEEKS | K15: 52
A16: DFW | B16: FC | C16: BC | D16: EU | E16: EY | F16: TC | G16: CY | H16: Total | J16: FLIGHTS/WEEK | K16: ='P&L'!P2 -> 7
A17: FLIGHT CONFIG | B17: 0 | C17: 32 | D17: 56 | E17: 174 | F17: 2 | G17: 8 | H17: =SUM(B17:G17) -> 272 | J17: FLTS PER YEAR | K17: =K15*K16 -> 364
A18: LOAD FACTORS | B18: =+'P&L'!$P$4 -> 0.8 | C18: =+'P&L'!$P$4 -> 0.8 | D18: =+'P&L'!$P$4 -> 0.8 | E18: =+'P&L'!$P$4 -> 0.8 | F18: =+'P&L'!$P$4 -> 0.8 | G18: =+'P&L'!$P$4 -> 0.8 | J18: # OF CYCLES | K18: 1
A19: PAX COUNT | B19: =ROUNDUP(B17*B18,0) -> 0 | C19: =ROUNDUP(C17*C18,0) -> 26 | D19: =ROUNDUP(D17*D18,0) -> 45 | E19: =ROUNDUP(E17*E18,0) -> 140 | F19: =ROUNDUP(F17*F18,0) -> 2 | G19: =ROUNDUP(G17*G18,0) -> 7 | H19: =SUM(B19:G19) -> 220 | J19: FLTS PER CYCLE | K19: 365
B28: FIRST CLASS | C28: BUSINESS CLASS | D28: PREMIUM ECONOMY CLASS | E28: ECONOMY CLASS | F28: TECH CREW CLASS | G28: CABIN CREW CLASS
C29: 32 | D29: 56 | E29: 174 | F29: 2 | G29: 8
B33: ACTUALLY CONFIGRATION IS 16/36/108

Sheet Food
V1: Per Flight | AE1: Annual
M2: =20/60*1.2 -> 0.4 | O2: ='P&L'!P8 -> 0.13 | P2: ='P&L'!P9 -> 0.13
A3: CLASS | B3: CYCLE | D3: SERVICE | E3: Item # | G3: Description | H3: QTY | I3: RATIOS | J3: Volume Per Flight | K3: DM | L3: IE MM | M3: DL | N3: TOTAL COST | O3: Food Markup | P3: Labor Markup | Q3: Price | R3: extra material cost | T3: MM Operation | V3: DM per flt | W3: MM per flt | X3: DL per flt | Y3: Cost per flt | Z3: Food Markup per flt | AA3: Labor Markup Per flt | AB3: Revenue per flt | AD3: Annual NM cost | AE3: Annual DM | AF3: Annual MM | AG3: Annual DL | AH3: Annual Cost | AI3: Annual Revenue
A5: BUSINESS CLASS | B5: 2 | C5: =CONCATENATE(A5&B5&F5) -> BUSINESS CLASS2 | E5: 10001 | G5: =VLOOKUP(E5,'[5]FG MASTER'!$A$10:$AB$203,2,0) -> BC TSU | H5: 40 | I5: STD | J5: =IFERROR(IF(I5="std",H5,HLOOKUP(A5,FlightConfig!$B$28:$G$29,2,0)*I5),"") -> 40 | K5: =VLOOKUP(Food!E5,'[5]FG MASTER'!$A$1:$AC$521,16,0) -> 0 | L5: =VLOOKUP(Food!E5,'FG MASTER'!A:AJ,17,0) -> 2 | M5: =IFERROR(L5*$M$2,"") -> 0.8 | N5: =IFERROR((K5)+M5,"") -> 0.8 | O5: =IFERROR($K5*(1+$O$2)-$K5+R5,0) -> 0 | P5: =IFERROR($M5*(1+$P$2)-$M5,0) -> 0.104 | Q5: =SUM(N5:P5) -> 0.904 | T5: =L5*J5 -> 80 | V5: =IFERROR(K5*J5-R5*J5,"") -> 0 | W5: =IFERROR(+L5*J5,"") -> 80 | X5: =IFERROR(+M5*J5,"") -> 32 | Y5: =IFERROR(+N5*J5,"") -> 32 | Z5: =IFERROR(O5*$J5,"") -> 0 | AA5: =IFERROR(P5*$J5,"") -> 4.16 | AB5: =IFERROR(+(Q5+R5)*J5,"") -> 36.16 | AD5: =IFERROR(#REF!*FlightConfig!$K$3,"") | AE5: =IFERROR(V5*FlightConfig!$K$3,"") -> 0 | AF5: =IFERROR(W5*FlightConfig!$K$3,"") -> 29120 | AG5: =IFERROR(X5*FlightConfig!$K$3,"") -> 11648 | AH5: =IFERROR(Y5*FlightConfig!$K$3,"") -> 11648 | AI5: =IFERROR(AB5*FlightConfig!$K$3,"") -> 13162.24
A6: BUSINESS CLASS | B6: 2 | C6: =CONCATENATE(A6&B6&F6) -> BUSINESS CLASS2 | E6: 10002 | G6: =VLOOKUP(E6,'[5]FG MASTER'!$A$10:$AB$203,2,0) -> BC C2 SALAD MESCLUN MIX GREEN250g | H6: 1 | I6: 0.1 | J6: =IFERROR(IF(I6="std",H6,ROUND(HLOOKUP(A6,FlightConfig!$B$28:$G$29,2,0)*I6,0)),"") -> 3 | K6: =VLOOKUP(Food!E6,'[5]FG MASTER'!$A$1:$AC$521,16,0) -> 1.6204507 | L6: =VLOOKUP(Food!E6,'FG MASTER'!A:AJ,17,0) -> 2.5 | M6: =IFERROR(L6*$M$2,"") -> 1 | N6: =IFERROR((K6)+M6,"") -> 2.6204507 | O6: =IFERROR($K6*(1+$O$2)-$K6+R6,0) -> 0.2106586 | P6: =IFERROR($M6*(1+$P$2)-$M6,0) -> 0.13 | Q6: =SUM(N6:P6) -> 2.9611093 | T6: =L6*J6 -> 7.5 | V6: =IFERROR(K6*J6-R6*J6,"") -> 4.8613522 | W6: =IFERROR(+L6*J6,"") -> 7.5 | X6: =IFERROR(+M6*J6,"") -> 3 | Y6: =IFERROR(+N6*J6+R6*J6,"") -> 7.8613522 | Z6: =IFERROR(O6*$J6,"") -> 0.63197579 | AA6: =IFERROR(P6*$J6,"") -> 0.39 | AB6: =IFERROR(+(Q6+R6)*J6,"") -> 8.883328 | AD6: =IFERROR(#REF!*FlightConfig!$K$3,"") | AE6: =IFERROR(V6*FlightConfig!$K$3,"") -> 1769.5322 | AF6: =IFERROR(W6*FlightConfig!$K$3,"") -> 2730 | AG6: =IFERROR(X6*FlightConfig!$K$3,"") -> 1092 | AH6: =IFERROR(Y6*FlightConfig!$K$3,"") -> 2861.5322 | AI6: =IFERROR(AB6*FlightConfig!$K$3,"") -> 3233.5314
A7: BUSINESS CLASS | B7: 2 | C7: =CONCATENATE(A7&B7&F7) -> BUSINESS CLASS2 | E7: 10004 | G7: =VLOOKUP(E7,'[5]FG MASTER'!$A$10:$AB$203,2,0) -> BC C2 GARNISH SUNFLOWER SEED | H7: 1 | I7: 0.1 | J7: =IFERROR(IF(I7="std",H7,ROUND(HLOOKUP(A7,FlightConfig!$B$28:$G$29,2,0)*I7,0)),"") -> 3 | K7: =VLOOKUP(Food!E7,'[5]FG MASTER'!$A$1:$AC$521,16,0) -> 0.2656962 | L7: =VLOOKUP(Food!E7,'FG MASTER'!A:AJ,17,0) -> 1.5 | M7: =IFERROR(L7*$M$2,"") -> 0.6 | N7: =IFERROR((K7)+M7,"") -> 0.8656962 | O7: =IFERROR($K7*(1+$O$2)-$K7+R7,0) -> 0.034540506 | P7: =IFERROR($M7*(1+$P$2)-$M7,0) -> 0.078 | Q7: =SUM(N7:P7) -> 0.97823671 | T7: =L7*J7 -> 4.5 | V7: =IFERROR(K7*J7-R7*J7,"") -> 0.7970886 | W7: =IFERROR(+L7*J7,"") -> 4.5 | X7: =IFERROR(+M7*J7,"") -> 1.8 | Y7: =IFERROR(+N7*J7+R7*J7,"") -> 2.5970886 | Z7: =IFERROR(O7*$J7,"") -> 0.10362152 | AA7: =IFERROR(P7*$J7,"") -> 0.234 | AB7: =IFERROR(+(Q7+R7)*J7,"") -> 2.9347101 | AD7: =IFERROR(#REF!*FlightConfig!$K$3,"") | AE7: =IFERROR(V7*FlightConfig!$K$3,"") -> 290.14025 | AF7: =IFERROR(W7*FlightConfig!$K$3,"") -> 1638 | AG7: =IFERROR(X7*FlightConfig!$K$3,"") -> 655.2 | AH7: =IFERROR(Y7*FlightConfig!$K$3,"") -> 945.34025 | AI7: =IFERROR(AB7*FlightConfig!$K$3,"") -> 1068.2345
A8: BUSINESS CLASS | B8: 2 | C8: =CONCATENATE(A8&B8&F8) -> BUSINESS CLASS2 | E8: 10006 | G8: =VLOOKUP(E8,'[5]FG MASTER'!$A$10:$AB$203,2,0) -> BC BUTTER | H8: 1 | I8: 1 | J8: =IFERROR(IF(I8="std",H8,ROUND(HLOOKUP(A8,FlightConfig!$B$28:$G$29,2,0)*I8,0)),"") -> 32 | K8: =VLOOKUP(Food!E8,'[5]FG MASTER'!$A$1:$AC$521,16,0) -> 0.0852 | L8: =VLOOKUP(Food!E8,'FG MASTER'!A:AJ,17,0) -> 0.75 | M8: =IFERROR(L8*$M$2,"") -> 0.3 | N8: =IFERROR((K8)+M8,"") -> 0.3852 | O8: =IFERROR($K8*(1+$O$2)-$K8+R8,0) -> 0.011076 | P8: =IFERROR($M8*(1+$P$2)-$M8,0) -> 0.039 | Q8: =SUM(N8:P8) -> 0.435276 | T8: =L8*J8 -> 24 | V8: =IFERROR(K8*J8-R8*J8,"") -> 2.7264 | W8: =IFERROR(+L8*J8,"") -> 24 | X8: =IFERROR(+M8*J8,"") -> 9.6 | Y8: =IFERROR(+N8*J8+R8*J8,"") -> 12.3264 | Z8: =IFERROR(O8*$J8,"") -> 0.354432 | AA8: =IFERROR(P8*$J8,"") -> 1.248 | AB8: =IFERROR(+(Q8+R8)*J8,"") -> 13.928832 | AD8: =IFERROR(#REF!*FlightConfig!$K$3,"") | AE8: =IFERROR(V8*FlightConfig!$K$3,"") -> 992.4096 | AF8: =IFERROR(W8*FlightConfig!$K$3,"") -> 8736 | AG8: =IFERROR(X8*FlightConfig!$K$3,"") -> 3494.4 | AH8: =IFERROR(Y8*FlightConfig!$K$3,"") -> 4486.8096 | AI8: =IFERROR(AB8*FlightConfig!$K$3,"") -> 5070.0948
A9: BUSINESS CLASS | B9: 2 | C9: =CONCATENATE(A9&B9&F9) -> BUSINESS CLASS2 | E9: 10007 | G9: =VLOOKUP(E9,'[5]FG MASTER'!$A$10:$AB$203,2,0) -> BC C2 STARTER A MEAT BEEF PASTRAMI, DUCK RILLET, SOOORESSATA, FIG JAM AND MESCULIN LETTUCE OKRA BLACK MISSION FIG | H9: 1 | I9: 0.6 | J9: =IFERROR(IF(I9="std",H9,ROUND(HLOOKUP(A9,FlightConfig!$B$28:$G$29,2,0)*I9,0)),"") -> 19 | K9: =VLOOKUP(Food!E9,'[5]FG MASTER'!$A$1:$AC$521,16,0) -> 1.56555 | L9: =VLOOKUP(Food!E9,'FG MASTER'!A:AJ,17,0) -> 3 | M9: =IFERROR(L9*$M$2,"") -> 1.2 | N9: =IFERROR((K9)+M9,"") -> 2.76555 | O9: =IFERROR($K9*(1+$O$2)-$K9+R9,0) -> -0.24433342 | P9: =IFERROR($M9*(1+$P$2)-$M9,0) -> 0.156 | Q9: =SUM(N9:P9) -> 2.6772166 | R9: -0.44785492 | S9: =R9*J9 -> -8.5092435 | T9: =L9*J9 -> 57 | V9: =IFERROR(K9*J9-R9*J9,"") -> 38.254693 | W9: =L9*J9 -> 57 | X9: =+M9*J9 -> 22.8 | Y9: =IFERROR(+N9*J9+R9*J9,"") -> 44.036207 | Z9: =IFERROR(O9*$J9,"") -> -4.642335 | AA9: =IFERROR(P9*$J9,"") -> 2.964 | AB9: =IFERROR(+(Q9+R9)*J9,"") -> 42.357872 | AD9: =IFERROR(#REF!*FlightConfig!$K$3,"") | AE9: =IFERROR(V9*FlightConfig!$K$3,"") -> 13924.708 | AF9: =IFERROR(W9*FlightConfig!$K$3,"") -> 20748 | AG9: =IFERROR(X9*FlightConfig!$K$3,"") -> 8299.2 | AH9: =IFERROR(Y9*FlightConfig!$K$3,"") -> 16029.179 | AI9: =IFERROR(AB9*FlightConfig!$K$3,"") -> 15418.265
A10: BUSINESS CLASS | B10: 2 | C10: =CONCATENATE(A10&B10&F10) -> BUSINESS CLASS2 | E10: 10009 | G10: =VLOOKUP(E10,'[5]FG MASTER'!$A$10:$AB$203,2,0) -> BC C2 STARTER B FISH SMOKED TROUT, PICKLED RED ONION, CUCUMBER APPLE SALAD AND MESCLUN MIX | H10: 1 | I10: 0.6 | J10: =IFERROR(IF(I10="std",H10,ROUND(HLOOKUP(A10,FlightConfig!$B$28:$G$29,2,0)*I10,0)),"") -> 19 | K10: =VLOOKUP(Food!E10,'[5]FG MASTER'!$A$1:$AC$521,16,0) -> 1.805388 | L10: =VLOOKUP(Food!E10,'FG MASTER'!A:AJ,17,0) -> 3.5 | M10: =IFERROR(L10*$M$2,"") -> 1.4 | N10: =IFERROR((K10)+M10,"") -> 3.205388 | O10: =IFERROR($K10*(1+$O$2)-$K10+R10,0) -> 0.21413628 | P10: =IFERROR($M10*(1+$P$2)-$M10,0) -> 0.182 | Q10: =SUM(N10:P10) -> 3.6015243 | R10: -0.020564157 | S10: =R10*J10 -> -0.39071898 | T10: =L10*J10 -> 66.5 | V10: =IFERROR(K10*J10-R10*J10,"") -> 34.693091 | W10: =IFERROR(+L10*J10,"") -> 66.5 | X10: =IFERROR(+M10*J10,"") -> 26.6 | Y10: =IFERROR(+N10*J10+R10*J10,"") -> 60.511653 | Z10: =IFERROR(O10*$J10,"") -> 4.0685894 | AA10: =IFERROR(P10*$J10,"") -> 3.458 | AB10: =IFERROR(+(Q10+R10)*J10,"") -> 68.038242 | AD10: =IFERROR(#REF!*FlightConfig!$K$3,"") | AE10: =IFERROR(V10*FlightConfig!$K$3,"") -> 12628.285 | AF10: =IFERROR(W10*FlightConfig!$K$3,"") -> 24206 | AG10: =IFERROR(X10*FlightConfig!$K$3,"") -> 9682.4 | AH10: =IFERROR(Y10*FlightConfig!$K$3,"") -> 22026.242 | AI10: =IFERROR(AB10*FlightConfig!$K$3,"") -> 24765.92
A11: BUSINESS CLASS | B11: 2 | C11: =CONCATENATE(A11&B11&F11) -> BUSINESS CLASS2 | E11: 10011 | G11: =VLOOKUP(E11,'[5]FG MASTER'!$A$10:$AB$203,2,0) -> BC C2 STARTER GARNISH SHAVED RADISH 100G | H11: 2 | I11: 0.1 | J11: =IFERROR(IF(I11="std",H11,ROUND(HLOOKUP(A11,FlightConfig!$B$28:$G$29,2,0)*I11,0)),"") -> 3 | K11: =VLOOKUP(Food!E11,'[5]FG MASTER'!$A$1:$AC$521,16,0) -> 0.69029572 | L11: =VLOOKUP(Food!E11,'FG MASTER'!A:AJ,17,0) -> 2.5 | M11: =IFERROR(L11*$M$2,"") -> 1 | N11: =IFERROR((K11)+M11,"") -> 1.6902957 | O11: =IFERROR($K11*(1+$O$2)-$K11+R11,0) -> 0.089738444 | P11: =IFERROR($M11*(1+$P$2)-$M11,0) -> 0.13 | Q11: =SUM(N11:P11) -> 1.9100342 | T11: =L11*J11 -> 7.5 | V11: =IFERROR(K11*J11-R11*J11,"") -> 2.0708872 | W11: =IFERROR(+L11*J11,"") -> 7.5 | X11: =IFERROR(+M11*J11,"") -> 3 | Y11: =IFERROR(+N11*J11+R11*J11,"") -> 5.0708872 | Z11: =IFERROR(O11*$J11,"") -> 0.26921533 | AA11: =IFERROR(P11*$J11,"") -> 0.39 | AB11: =IFERROR(+(Q11+R11)*J11,"") -> 5.7301025 | AD11: =IFERROR(#REF!*FlightConfig!$K$3,"") | AE11: =IFERROR(V11*FlightConfig!$K$3,"") -> 753.80293 | AF11: =IFERROR(W11*FlightConfig!$K$3,"") -> 2730 | AG11: =IFERROR(X11*FlightConfig!$K$3,"") -> 1092 | AH11: =IFERROR(Y11*FlightConfig!$K$3,"") -> 1845.8029 | AI11: =IFERROR(AB11*FlightConfig!$K$3,"") -> 2085.7573
A12: BUSINESS CLASS | B12: 2 | C12: =CONCATENATE(A12&B12&F12) -> BUSINESS CLASS2 | E12: 10013 | G12: =VLOOKUP(E12,'[5]FG MASTER'!$A$10:$AB$203,2,0) -> BC C2 HM A MEAT GRILLED BEEF TENDERLOIN, SMOKED TOMATO JAM, FINGERLING POTATOES, ASPARAGUS | H12: 1 | I12: 0.4 | J12: =IFERROR(IF(I12="std",H12,ROUND(HLOOKUP(A12,FlightConfig!$B$28:$G$29,2,0)*I12,0)),"") -> 13 | K12: =VLOOKUP(Food!E12,'[5]FG MASTER'!$A$1:$AC$521,16,0) -> 8.7456735 | L12: =VLOOKUP(Food!E12,'FG MASTER'!A:AJ,17,0) -> 8 | M12: =IFERROR(L12*$M$2,"") -> 3.2 | N12: =IFERROR((K12)+M12,"") -> 11.945673 | O12: =IFERROR($K12*(1+$O$2)-$K12+R12,0) -> 2.9910664 | P12: =IFERROR($M12*(1+$P$2)-$M12,0) -> 0.416 | Q12: =SUM(N12:P12) -> 15.35274 | R12: 1.8541289 | S12: =R12*J12 -> 24.103675 | T12: =(L12/2)*J12 -> 52 | V12: =IFERROR(K12*J12-R12*J12,"") -> 89.59008 | W12: =IFERROR(+L12*J12,"") -> 104 | X12: =IFERROR(+M12*J12,"") -> 41.6 | Y12: =IFERROR(+N12*J12+R12*J12,"") -> 179.39743 | Z12: =IFERROR(O12*$J12,"") -> 38.883864 | AA12: =IFERROR(P12*$J12,"") -> 5.408 | AB12: =IFERROR(+(Q12+R12)*J12,"") -> 223.68929 | AD12: =IFERROR(#REF!*FlightConfig!$K$3,"") | AE12: =IFERROR(V12*FlightConfig!$K$3,"") -> 32610.789 | AF12: =IFERROR(W12*FlightConfig!$K$3,"") -> 37856 | AG12: =IFERROR(X12*FlightConfig!$K$3,"") -> 15142.4 | AH12: =IFERROR(Y12*FlightConfig!$K$3,"") -> 65300.665 | AI12: =IFERROR(AB12*FlightConfig!$K$3,"") -> 81422.903
A13: BUSINESS CLASS | B13: 2 | C13: =CONCATENATE(A13&B13&F13) -> BUSINESS CLASS2 | E13: 10015 | G13: =VLOOKUP(E13,'[5]FG MASTER'!$A$10:$AB$203,2,0) -> BC C2 HM C POULTRY LEMON CHICKEN LEG CONFIT, WILD MUSHROOM CONSERVA, MASH POTATOES, BABY CARROT | H13: 1 | I13: 0.4 | J13: =IFERROR(IF(I13="std",H13,ROUND(HLOOKUP(A13,FlightConfig!$B$28:$G$29,2,0)*I13,0)),"") -> 13 | K13: =VLOOKUP(Food!E13,'[5]FG MASTER'!$A$1:$AC$521,16,0) -> 4.3527434 | L13: =VLOOKUP(Food!E13,'FG MASTER'!A:AJ,17,0) -> 6.5 | M13: =IFERROR(L13*$M$2,"") -> 2.6 | N13: =IFERROR((K13)+M13,"") -> 6.9527434 | O13: =IFERROR($K13*(1+$O$2)-$K13+R13,0) -> 0.56585664 | P13: =IFERROR($M13*(1+$P$2)-$M13,0) -> 0.338 | Q13: =SUM(N13:P13) -> 7.8566 | T13: =(L13/2)*J13 -> 42.25 | V13: =IFERROR(K13*J13-R13*J13,"") -> 56.585664 | W13: =IFERROR(+L13*J13,"") -> 84.5 | X13: =IFERROR(+M13*J13,"") -> 33.8 | Y13: =IFERROR(+N13*J13+R13*J13,"") -> 90.385664 | Z13: =IFERROR(O13*$J13,"") -> 7.3561363 | AA13: =IFERROR(P13*$J13,"") -> 4.394 | AB13: =IFERROR(+(Q13+R13)*J13,"") -> 102.1358 | AD13: =IFERROR(#REF!*FlightConfig!$K$3,"") | AE13: =IFERROR(V13*FlightConfig!$K$3,"") -> 20597.182 | AF13: =IFERROR(W13*FlightConfig!$K$3,"") -> 30758 | AG13: =IFERROR(X13*FlightConfig!$K$3,"") -> 12303.2 | AH13: =IFERROR(Y13*FlightConfig!$K$3,"") -> 32900.382 | AI13: =IFERROR(AB13*FlightConfig!$K$3,"") -> 37177.431
A14: BUSINESS CLASS | B14: 2 | C14: =CONCATENATE(A14&B14&F14) -> BUSINESS CLASS2 | E14: 10017 | G14: =VLOOKUP(E14,'[5]FG MASTER'!$A$10:$AB$203,2,0) -> BC C2 HM D VEG PASTA MAMI SMOKED MOZZERELLA RAVIOLI 25GX4, POMODRINI SAUCE, BUFFALA MOZZARELLA, BROCCOLINI | H14: 1 | I14: 0.4 | J14: =IFERROR(IF(I14="std",H14,ROUND(HLOOKUP(A14,FlightConfig!$B$28:$G$29,2,0)*I14,0)),"") -> 13 | K14: =VLOOKUP(Food!E14,'[5]FG MASTER'!$A$1:$AC$521,16,0) -> 4.2014889 | L14: =VLOOKUP(Food!E14,'FG MASTER'!A:AJ,17,0) -> 4 | M14: =IFERROR(L14*$M$2,"") -> 1.6 | N14: =IFERROR((K14)+M14,"") -> 5.8014889 | O14: =IFERROR($K14*(1+$O$2)-$K14+R14,0) -> 0.54619356 | P14: =IFERROR($M14*(1+$P$2)-$M14,0) -> 0.208 | Q14: =SUM(N14:P14) -> 6.5556825 | T14: =(L14/2)*J14 -> 26 | V14: =IFERROR(K14*J14-R14*J14,"") -> 54.619356 | W14: =IFERROR(+L14*J14,"") -> 52 | X14: =IFERROR(+M14*J14,"") -> 20.8 | Y14: =IFERROR(+N14*J14+R14*J14,"") -> 75.419356 | Z14: =IFERROR(O14*$J14,"") -> 7.1005162 | AA14: =IFERROR(P14*$J14,"") -> 2.704 | AB14: =IFERROR(+(Q14+R14)*J14,"") -> 85.223872 | AD14: =IFERROR(#REF!*FlightConfig!$K$3,"") | AE14: =IFERROR(V14*FlightConfig!$K$3,"") -> 19881.445 | AF14: =IFERROR(W14*FlightConfig!$K$3,"") -> 18928 | AG14: =IFERROR(X14*FlightConfig!$K$3,"") -> 7571.2 | AH14: =IFERROR(Y14*FlightConfig!$K$3,"") -> 27452.645 | AI14: =IFERROR(AB14*FlightConfig!$K$3,"") -> 31021.489
A15: BUSINESS CLASS | B15: 2 | C15: =CONCATENATE(A15&B15&F15) -> BUSINESS CLASS2 | E15: 10019 | G15: =VLOOKUP(E15,'[5]FG MASTER'!$A$10:$AB$203,2,0) -> BC HM GARNISH MICRO GREEN 90G | H15: 2 | I15: 0.1 | J15: =IFERROR(IF(I15="std",H15,ROUND(HLOOKUP(A15,FlightConfig!$B$28:$G$29,2,0)*I15,0)),"") -> 3 | K15: =VLOOKUP(Food!E15,'[5]FG MASTER'!$A$1:$AC$521,16,0) -> 8.6754953 | L15: =VLOOKUP(Food!E15,'FG MASTER'!A:AJ,17,0) -> 2 | M15: =IFERROR(L15*$M$2,"") -> 0.8 | N15: =IFERROR((K15)+M15,"") -> 9.4754953 | O15: =IFERROR($K15*(1+$O$2)-$K15+R15,0) -> 1.1278144 | P15: =IFERROR($M15*(1+$P$2)-$M15,0) -> 0.104 | Q15: =SUM(N15:P15) -> 10.70731 | T15: =L15*J15 -> 6 | V15: =IFERROR(K15*J15-R15*J15,"") -> 26.026486 | W15: =IFERROR(+L15*J15,"") -> 6 | X15: =IFERROR(+M15*J15,"") -> 2.4 | Y15: =IFERROR(+N15*J15+R15*J15,"") -> 28.426486 | Z15: =IFERROR(O15*$J15,"") -> 3.3834432 | AA15: =IFERROR(P15*$J15,"") -> 0.312 | AB15: =IFERROR(+(Q15+R15)*J15,"") -> 32.121929 | AD15: =IFERROR(#REF!*FlightConfig!$K$3,"") | AE15: =IFERROR(V15*FlightConfig!$K$3,"") -> 9473.6409 | AF15: =IFERROR(W15*FlightConfig!$K$3,"") -> 2184 | AG15: =IFERROR(X15*FlightConfig!$K$3,"") -> 873.6 | AH15: =IFERROR(Y15*FlightConfig!$K$3,"") -> 10347.241 | AI15: =IFERROR(AB15*FlightConfig!$K$3,"") -> 11692.382
A16: BUSINESS CLASS | B16: 2 | C16: =CONCATENATE(A16&B16&F16) -> BUSINESS CLASS2 | E16: 10020 | G16: =VLOOKUP(E16,'[5]FG MASTER'!$A$10:$AB$203,2,0) -> BC C2 DE CHEESE THOMASVILLE TOMME AND BRIE | H16: 1 | I16: 0.1 | J16: =IFERROR(IF(I16="std",H16,ROUND(HLOOKUP(A16,FlightConfig!$B$28:$G$29,2,0)*I16,0)),"") -> 3 | K16: =VLOOKUP(Food!E16,'[5]FG MASTER'!$A$1:$AC$521,16,0) -> 2.5484917 | L16: =VLOOKUP(Food!E16,'FG MASTER'!A:AJ,17,0) -> 2 | M16: =IFERROR(L16*$M$2,"") -> 0.8 | N16: =IFERROR((K16)+M16,"") -> 3.3484917 | O16: =IFERROR($K16*(1+$O$2)-$K16+R16,0) -> 0.33130393 | P16: =IFERROR($M16*(1+$P$2)-$M16,0) -> 0.104 | Q16: =SUM(N16:P16) -> 3.7837957 | T16: =L16*J16 -> 6 | V16: =IFERROR(K16*J16-R16*J16,"") -> 7.6454752 | W16: =IFERROR(+L16*J16,"") -> 6 | X16: =IFERROR(+M16*J16,"") -> 2.4 | Y16: =IFERROR(+N16*J16+R16*J16,"") -> 10.045475 | Z16: =IFERROR(O16*$J16,"") -> 0.99391178 | AA16: =IFERROR(P16*$J16,"") -> 0.312 | AB16: =IFERROR(+(Q16+R16)*J16,"") -> 11.351387 | AD16: =IFERROR(#REF!*FlightConfig!$K$3,"") | AE16: =IFERROR(V16*FlightConfig!$K$3,"") -> 2782.953 | AF16: =IFERROR(W16*FlightConfig!$K$3,"") -> 2184 | AG16: =IFERROR(X16*FlightConfig!$K$3,"") -> 873.6 | AH16: =IFERROR(Y16*FlightConfig!$K$3,"") -> 3656.553 | AI16: =IFERROR(AB16*FlightConfig!$K$3,"") -> 4131.9049
A17: BUSINESS CLASS | B17: 2 | C17: =CONCATENATE(A17&B17&F17) -> BUSINESS CLASS2 | E17: 10022 | G17: =VLOOKUP(E17,'[5]FG MASTER'!$A$10:$AB$203,2,0) -> BC C2 DE CAKE BANANA PUDDING CHEESECAKE WITH STRUSEL CRUMBLE AND BLUEBERRIES | H17: 16 | I17: STD | J17: =IFERROR(IF(I17="std",H17,ROUND(HLOOKUP(A17,FlightConfig!$B$28:$G$29,2,0)*I17,0)),"") -> 16 | K17: =VLOOKUP(Food!E17,'[5]FG MASTER'!$A$1:$AC$521,16,0) -> 0.80838292 | L17: =VLOOKUP(Food!E17,'FG MASTER'!A:AJ,17,0) -> 2.5 | M17: =IFERROR(L17*$M$2,"") -> 1 | N17: =IFERROR((K17)+M17,"") -> 1.8083829 | O17: =IFERROR($K17*(1+$O$2)-$K17+R17,0) -> 0.10508978 | P17: =IFERROR($M17*(1+$P$2)-$M17,0) -> 0.13 | Q17: =SUM(N17:P17) -> 2.0434727 | T17: =(L17/2)*J17 -> 20 | V17: =IFERROR(K17*J17-R17*J17,"") -> 12.934127 | W17: =IFERROR(+L17*J17,"") -> 40 | X17: =IFERROR(+M17*J17,"") -> 16 | Y17: =IFERROR(+N17*J17+R17*J17,"") -> 28.934127 | Z17: =IFERROR(O17*$J17,"") -> 1.6814365 | AA17: =IFERROR(P17*$J17,"") -> 2.08 | AB17: =IFERROR(+(Q17+R17)*J17,"") -> 32.695563 | AD17: =IFERROR(#REF!*FlightConfig!$K$3,"") | AE17: =IFERROR(V17*FlightConfig!$K$3,"") -> 4708.0222 | AF17: =IFERROR(W17*FlightConfig!$K$3,"") -> 14560 | AG17: =IFERROR(X17*FlightConfig!$K$3,"") -> 5824 | AH17: =IFERROR(Y17*FlightConfig!$K$3,"") -> 10532.022 | AI17: =IFERROR(AB17*FlightConfig!$K$3,"") -> 11901.185
A18: BUSINESS CLASS | B18: 2 | C18: =CONCATENATE(A18&B18&F18) -> BUSINESS CLASS2 | E18: 10024 | G18: =VLOOKUP(E18,'[5]FG MASTER'!$A$10:$AB$203,2,0) -> BC C2 DE CAKE GARNISH RHUN CARAMEL 200G | H18: 1 | I18: 0.1 | J18: =IFERROR(IF(I18="std",H18,ROUND(HLOOKUP(A18,FlightConfig!$B$28:$G$29,2,0)*I18,0)),"") -> 3 | K18: =VLOOKUP(Food!E18,'[5]FG MASTER'!$A$1:$AC$521,16,0) -> 4.9617871 | L18: =VLOOKUP(Food!E18,'FG MASTER'!A:AJ,17,0) -> 2 | M18: =IFERROR(L18*$M$2,"") -> 0.8 | N18: =IFERROR((K18)+M18,"") -> 5.7617871 | O18: =IFERROR($K18*(1+$O$2)-$K18+R18,0) -> 0.64503232 | P18: =IFERROR($M18*(1+$P$2)-$M18,0) -> 0.104 | Q18: =SUM(N18:P18) -> 6.5108194 | T18: =L18*J18 -> 6 | V18: =IFERROR(K18*J18-R18*J18,"") -> 14.885361 | W18: =IFERROR(+L18*J18,"") -> 6 | X18: =IFERROR(+M18*J18,"") -> 2.4 | Y18: =IFERROR(+N18*J18+R18*J18,"") -> 17.285361 | Z18: =IFERROR(O18*$J18,"") -> 1.935097 | AA18: =IFERROR(P18*$J18,"") -> 0.312 | AB18: =IFERROR(+(Q18+R18)*J18,"") -> 19.532458 | AD18: =IFERROR(#REF!*FlightConfig!$K$3,"") | AE18: =IFERROR(V18*FlightConfig!$K$3,"") -> 5418.2715 | AF18: =IFERROR(W18*FlightConfig!$K$3,"") -> 2184 | AG18: =IFERROR(X18*FlightConfig!$K$3,"") -> 873.6 | AH18: =IFERROR(Y18*FlightConfig!$K$3,"") -> 6291.8715 | AI18: =IFERROR(AB18*FlightConfig!$K$3,"") -> 7109.8148
A19: BUSINESS CLASS | B19: 2 | C19: =CONCATENATE(A19&B19&F19) -> BUSINESS CLASS2 | E19: 10026 | G19: =VLOOKUP(E19,'[5]FG MASTER'!$A$10:$AB$203,2,0) -> BC C2 DE FRUIT GRAPE, HONEYDEW, CANTALOUPE, WATERMELON | H19: 1 | I19: 0.1 | J19: =IFERROR(IF(I19="std",H19,ROUND(HLOOKUP(A19,FlightConfig!$B$28:$G$29,2,0)*I19,0)),"") -> 3 | K19: =VLOOKUP(Food!E19,'[5]FG MASTER'!$A$1:$AC$521,16,0) -> 2.5654785 | L19: =VLOOKUP(Food!E19,'FG MASTER'!A:AJ,17,0) -> 3.5 | M19: =IFERROR(L19*$M$2,"") -> 1.4 | N19: =IFERROR((K19)+M19,"") -> 3.9654785 | O19: =IFERROR($K19*(1+$O$2)-$K19+R19,0) -> 0.3335122 | P19: =IFERROR($M19*(1+$P$2)-$M19,0) -> 0.182 | Q19: =SUM(N19:P19) -> 4.4809907 | T19: =L19*J19 -> 10.5 | V19: =IFERROR(K19*J19-R19*J19,"") -> 7.6964355 | W19: =IFERROR(+L19*J19,"") -> 10.5 | X19: =IFERROR(+M19*J19,"") -> 4.2 | Y19: =IFERROR(+N19*J19+R19*J19,"") -> 11.896435 | Z19: =IFERROR(O19*$J19,"") -> 1.0005366 | AA19: =IFERROR(P19*$J19,"") -> 0.546 | AB19: =IFERROR(+(Q19+R19)*J19,"") -> 13.442972 | AD19: =IFERROR(#REF!*FlightConfig!$K$3,"") | AE19: =IFERROR(V19*FlightConfig!$K$3,"") -> 2801.5025 | AF19: =IFERROR(W19*FlightConfig!$K$3,"") -> 3822 | AG19: =IFERROR(X19*FlightConfig!$K$3,"") -> 1528.8 | AH19: =IFERROR(Y19*FlightConfig!$K$3,"") -> 4330.3025 | AI19: =IFERROR(AB19*FlightConfig!$K$3,"") -> 4893.2418
A20: BUSINESS CLASS | B20: 2 | C20: =CONCATENATE(A20&B20&F20) -> BUSINESS CLASS2 | E20: 10028 | G20: =VLOOKUP(E20,'[5]FG MASTER'!$A$10:$AB$203,2,0) -> BC BRD TYPE 1 HERB SOURDOUGH 30G AND MULTIGRAIN CHEESE ROLL 40G | H20: 1 | I20: 0.6 | J20: =IFERROR(IF(I20="std",H20,ROUND(HLOOKUP(A20,FlightConfig!$B$28:$G$29,2,0)*I20,0)),"") -> 19 | K20: =VLOOKUP(Food!E20,'[5]FG MASTER'!$A$1:$AC$521,16,0) -> 1.11825 | L20: =VLOOKUP(Food!E20,'FG MASTER'!A:AJ,17,0) -> 1 | M20: =IFERROR(L20*$M$2,"") -> 0.4 | N20: =IFERROR((K20)+M20,"") -> 1.51825 | O20: =IFERROR($K20*(1+$O$2)-$K20+R20,0) -> 0.1453725 | P20: =IFERROR($M20*(1+$P$2)-$M20,0) -> 0.052 | Q20: =SUM(N20:P20) -> 1.7156225 | T20: =0.32*J20 -> 6.08 | V20: =IFERROR(K20*J20-R20*J20,"") -> 21.24675 | W20: =IFERROR(+L20*J20,"") -> 19 | X20: =IFERROR(+M20*J20,"") -> 7.6 | Y20: =IFERROR(+N20*J20+R20*J20,"") -> 28.84675 | Z20: =IFERROR(O20*$J20,"") -> 2.7620775 | AA20: =IFERROR(P20*$J20,"") -> 0.988 | AB20: =IFERROR(+(Q20+R20)*J20,"") -> 32.596827 | AD20: =IFERROR(#REF!*FlightConfig!$K$3,"") | AE20: =IFERROR(V20*FlightConfig!$K$3,"") -> 7733.817 | AF20: =IFERROR(W20*FlightConfig!$K$3,"") -> 6916 | AG20: =IFERROR(X20*FlightConfig!$K$3,"") -> 2766.4 | AH20: =IFERROR(Y20*FlightConfig!$K$3,"") -> 10500.217 | AI20: =IFERROR(AB20*FlightConfig!$K$3,"") -> 11865.245
A21: BUSINESS CLASS | B21: 2 | C21: =CONCATENATE(A21&B21&F21) -> BUSINESS CLASS2 | E21: 10030 | G21: =VLOOKUP(E21,'[5]FG MASTER'!$A$10:$AB$203,2,0) -> BC BRD TYPE 3 ARTISAN BAGUETTE | H21: 2 | I21: 0.1 | J21: =IFERROR(IF(I21="std",H21,ROUND(HLOOKUP(A21,FlightConfig!$B$28:$G$29,2,0)*I21,0)),"") -> 3 | K21: =VLOOKUP(Food!E21,'[5]FG MASTER'!$A$1:$AC$521,16,0) -> 2.41755 | L21: =VLOOKUP(Food!E21,'FG MASTER'!A:AJ,17,0) -> 0.2 | M21: =IFERROR(L21*$M$2,"") -> 0.08 | N21: =IFERROR((K21)+M21,"") -> 2.49755 | O21: =IFERROR($K21*(1+$O$2)-$K21+R21,0) -> 0.3142815 | P21: =IFERROR($M21*(1+$P$2)-$M21,0) -> 0.0104 | Q21: =SUM(N21:P21) -> 2.8222315 | T21: =L21*J21 -> 0.6 | V21: =IFERROR(K21*J21-R21*J21,"") -> 7.25265 | W21: =IFERROR(+L21*J21,"") -> 0.6 | X21: =IFERROR(+M21*J21,"") -> 0.24 | Y21: =IFERROR(+N21*J21+R21*J21,"") -> 7.49265 | Z21: =IFERROR(O21*$J21,"") -> 0.9428445 | AA21: =IFERROR(P21*$J21,"") -> 0.0312 | AB21: =IFERROR(+(Q21+R21)*J21,"") -> 8.4666945 | AD21: =IFERROR(#REF!*FlightConfig!$K$3,"") | AE21: =IFERROR(V21*FlightConfig!$K$3,"") -> 2639.9646 | AF21: =IFERROR(W21*FlightConfig!$K$3,"") -> 218.4 | AG21: =IFERROR(X21*FlightConfig!$K$3,"") -> 87.36 | AH21: =IFERROR(Y21*FlightConfig!$K$3,"") -> 2727.3246 | AI21: =IFERROR(AB21*FlightConfig!$K$3,"") -> 3081.8768
A22: BUSINESS CLASS | B22: 2 | C22: =CONCATENATE(A22&B22&F22) -> BUSINESS CLASS2 | E22: 10031 | G22: =VLOOKUP(E22,'[5]FG MASTER'!$A$10:$AB$203,2,0) -> BC BRD C2 CROISSANT MINI | H22: 1 | I22: 0.4 | J22: =IFERROR(IF(I22="std",H22,ROUND(HLOOKUP(A22,FlightConfig!$B$28:$G$29,2,0)*I22,0)),"") -> 13 | K22: =VLOOKUP(Food!E22,'[5]FG MASTER'!$A$1:$AC$521,16,0) -> 0.62835 | L22: =VLOOKUP(Food!E22,'FG MASTER'!A:AJ,17,0) -> 0.6 | M22: =IFERROR(L22*$M$2,"") -> 0.24 | N22: =IFERROR((K22)+M22,"") -> 0.86835 | O22: =IFERROR($K22*(1+$O$2)-$K22+R22,0) -> 0.0816855 | P22: =IFERROR($M22*(1+$P$2)-$M22,0) -> 0.0312 | Q22: =SUM(N22:P22) -> 0.9812355 | T22: =L22*J22 -> 7.8 | V22: =IFERROR(K22*J22-R22*J22,"") -> 8.16855 | W22: =IFERROR(+L22*J22,"") -> 7.8 | X22: =IFERROR(+M22*J22,"") -> 3.12 | Y22: =IFERROR(+N22*J22+R22*J22,"") -> 11.28855 | Z22: =IFERROR(O22*$J22,"") -> 1.0619115 | AA22: =IFERROR(P22*$J22,"") -> 0.4056 | AB22: =IFERROR(+(Q22+R22)*J22,"") -> 12.756061 | AD22: =IFERROR(#REF!*FlightConfig!$K$3,"") | AE22: =IFERROR(V22*FlightConfig!$K$3,"") -> 2973.3522 | AF22: =IFERROR(W22*FlightConfig!$K$3,"") -> 2839.2 | AG22: =IFERROR(X22*FlightConfig!$K$3,"") -> 1135.68 | AH22: =IFERROR(Y22*FlightConfig!$K$3,"") -> 4109.0322 | AI22: =IFERROR(AB22*FlightConfig!$K$3,"") -> 4643.2064
A23: BUSINESS CLASS | B23: 2 | C23: =CONCATENATE(A23&B23&F23) -> BUSINESS CLASS2 | E23: 10001 | G23: =VLOOKUP(E23,'[5]FG MASTER'!$A$10:$AB$203,2,0) -> BC TSU | H23: 1 | I23: 1 | J23: =IFERROR(IF(I23="std",H23,ROUND(HLOOKUP(A23,FlightConfig!$B$28:$G$29,2,0)*I23,0)),"") -> 32 | K23: =VLOOKUP(Food!E23,'[5]FG MASTER'!$A$1:$AC$521,16,0) -> 0 | L23: =VLOOKUP(Food!E23,'FG MASTER'!A:AJ,17,0) -> 2 | M23: =IFERROR(L23*$M$2,"") -> 0.8 | N23: =IFERROR((K23)+M23,"") -> 0.8 | O23: =IFERROR($K23*(1+$O$2)-$K23+R23,0) -> 0 | P23: =IFERROR($M23*(1+$P$2)-$M23,0) -> 0.104 | Q23: =SUM(N23:P23) -> 0.904 | T23: =L23*J23 -> 64 | V23: =IFERROR(K23*J23-R23*J23,"") -> 0 | W23: =IFERROR(+L23*J23,"") -> 64 | X23: =IFERROR(+M23*J23,"") -> 25.6 | Y23: =IFERROR(+N23*J23+R23*J23,"") -> 25.6 | Z23: =IFERROR(O23*$J23,"") -> 0 | AA23: =IFERROR(P23*$J23,"") -> 3.328 | AB23: =IFERROR(+(Q23+R23)*J23,"") -> 28.928 | AD23: =IFERROR(#REF!*FlightConfig!$K$3,"") | AE23: =IFERROR(V23*FlightConfig!$K$3,"") -> 0 | AF23: =IFERROR(W23*FlightConfig!$K$3,"") -> 23296 | AG23: =IFERROR(X23*FlightConfig!$K$3,"") -> 9318.4 | AH23: =IFERROR(Y23*FlightConfig!$K$3,"") -> 9318.4 | AI23: =IFERROR(AB23*FlightConfig!$K$3,"") -> 10529.792
A24: BUSINESS CLASS | B24: 2 | C24: =CONCATENATE(A24&B24&F24) -> BUSINESS CLASS2 | E24: 10033 | G24: =VLOOKUP(E24,'[5]FG MASTER'!$A$10:$AB$203,2,0) -> BC C2 COLD CUT CHIVE CREAM CHEESE, GEORGIA GOUDA, HAM, PROSUITTO, GREEN LEAF LETTUCE, CUCUMBER, BABY PEPPER | H24: 1 | I24: 1 | J24: =IFERROR(IF(I24="std",H24,ROUND(HLOOKUP(A24,FlightConfig!$B$28:$G$29,2,0)*I24,0)),"") -> 32 | K24: =VLOOKUP(Food!E24,'[5]FG MASTER'!$A$1:$AC$521,16,0) -> 3.8311288 | L24: =VLOOKUP(Food!E24,'FG MASTER'!A:AJ,17,0) -> 3 | M24: =IFERROR(L24*$M$2,"") -> 1.2 | N24: =IFERROR((K24)+M24,"") -> 5.0311288 | O24: =IFERROR($K24*(1+$O$2)-$K24+R24,0) -> 0.49804674 | P24: =IFERROR($M24*(1+$P$2)-$M24,0) -> 0.156 | Q24: =SUM(N24:P24) -> 5.6851755 | T24: =L24*J24 -> 96 | V24: =IFERROR(K24*J24-R24*J24,"") -> 122.59612 | W24: =IFERROR(+L24*J24,"") -> 96 | X24: =IFERROR(+M24*J24,"") -> 38.4 | Y24: =IFERROR(+N24*J24+R24*J24,"") -> 160.99612 | Z24: =IFERROR(O24*$J24,"") -> 15.937496 | AA24: =IFERROR(P24*$J24,"") -> 4.992 | AB24: =IFERROR(+(Q24+R24)*J24,"") -> 181.92562 | AD24: =IFERROR(#REF!*FlightConfig!$K$3,"") | AE24: =IFERROR(V24*FlightConfig!$K$3,"") -> 44624.988 | AF24: =IFERROR(W24*FlightConfig!$K$3,"") -> 34944 | AG24: =IFERROR(X24*FlightConfig!$K$3,"") -> 13977.6 | AH24: =IFERROR(Y24*FlightConfig!$K$3,"") -> 58602.588 | AI24: =IFERROR(AB24*FlightConfig!$K$3,"") -> 66220.924
A25: BUSINESS CLASS | B25: 2 | C25: =CONCATENATE(A25&B25&F25) -> BUSINESS CLASS2 | E25: 10035 | G25: =VLOOKUP(E25,'[5]FG MASTER'!$A$10:$AB$203,2,0) -> BC C2 BRK FRUIT COCONUT CHIA OVERNIGHT OAT, MANGO, BLUEBERRIES | H25: 1 | I25: 1 | J25: =IFERROR(IF(I25="std",H25,ROUND(HLOOKUP(A25,FlightConfig!$B$28:$G$29,2,0)*I25,0)),"") -> 32 | K25: =VLOOKUP(Food!E25,'[5]FG MASTER'!$A$1:$AC$521,16,0) -> 0.91484033 | L25: =VLOOKUP(Food!E25,'FG MASTER'!A:AJ,17,0) -> 2.25 | M25: =IFERROR(L25*$M$2,"") -> 0.9 | N25: =IFERROR((K25)+M25,"") -> 1.8148403 | O25: =IFERROR($K25*(1+$O$2)-$K25+R25,0) -> 0.11892924 | P25: =IFERROR($M25*(1+$P$2)-$M25,0) -> 0.117 | Q25: =SUM(N25:P25) -> 2.0507696 | T25: =L25*J25 -> 72 | V25: =IFERROR(K25*J25-R25*J25,"") -> 29.27489 | W25: =IFERROR(+L25*J25,"") -> 72 | X25: =IFERROR(+M25*J25,"") -> 28.8 | Y25: =IFERROR(+N25*J25+R25*J25,"") -> 58.07489 | Z25: =IFERROR(O25*$J25,"") -> 3.8057358 | AA25: =IFERROR(P25*$J25,"") -> 3.744 | AB25: =IFERROR(+(Q25+R25)*J25,"") -> 65.624626 | AD25: =IFERROR(#REF!*FlightConfig!$K$3,"") | AE25: =IFERROR(V25*FlightConfig!$K$3,"") -> 10656.06 | AF25: =IFERROR(W25*FlightConfig!$K$3,"") -> 26208 | AG25: =IFERROR(X25*FlightConfig!$K$3,"") -> 10483.2 | AH25: =IFERROR(Y25*FlightConfig!$K$3,"") -> 21139.26 | AI25: =IFERROR(AB25*FlightConfig!$K$3,"") -> 23887.364
A26: BUSINESS CLASS | B26: 2 | C26: =CONCATENATE(A26&B26&F26) -> BUSINESS CLASS2 | E26: 10037 | G26: =VLOOKUP(E26,'[5]FG MASTER'!$A$10:$AB$203,2,0) -> BC C2 YOGURT VANILLA GREEK YOGURT CHOBANI 4OZ | H26: 1 | I26: 1 | J26: =IFERROR(IF(I26="std",H26,ROUND(HLOOKUP(A26,FlightConfig!$B$28:$G$29,2,0)*I26,0)),"") -> 32 | K26: =VLOOKUP(Food!E26,'[5]FG MASTER'!$A$1:$AC$521,16,0) -> 0.88395 | L26: =VLOOKUP(Food!E26,'FG MASTER'!A:AJ,17,0) -> 0.25 | M26: =IFERROR(L26*$M$2,"") -> 0.1 | N26: =IFERROR((K26)+M26,"") -> 0.98395 | O26: =IFERROR($K26*(1+$O$2)-$K26+R26,0) -> 0.1149135 | P26: =IFERROR($M26*(1+$P$2)-$M26,0) -> 0.013 | Q26: =SUM(N26:P26) -> 1.1118635 | T26: =L26*J26 -> 8 | V26: =IFERROR(K26*J26-R26*J26,"") -> 28.2864 | W26: =IFERROR(+L26*J26,"") -> 8 | X26: =IFERROR(+M26*J26,"") -> 3.2 | Y26: =IFERROR(+N26*J26+R26*J26,"") -> 31.4864 | Z26: =IFERROR(O26*$J26,"") -> 3.677232 | AA26: =IFERROR(P26*$J26,"") -> 0.416 | AB26: =IFERROR(+(Q26+R26)*J26,"") -> 35.579632 | AD26: =IFERROR(#REF!*FlightConfig!$K$3,"") | AE26: =IFERROR(V26*FlightConfig!$K$3,"") -> 10296.25 | AF26: =IFERROR(W26*FlightConfig!$K$3,"") -> 2912 | AG26: =IFERROR(X26*FlightConfig!$K$3,"") -> 1164.8 | AH26: =IFERROR(Y26*FlightConfig!$K$3,"") -> 11461.05 | AI26: =IFERROR(AB26*FlightConfig!$K$3,"") -> 12950.986
A27: PREMIUM ECONOMY CLASS | B27: 2 | C27: =CONCATENATE(A27&B27&F27) -> PREMIUM ECONOMY CLASS2 | E27: 10041 | G27: =VLOOKUP(E27,'[5]FG MASTER'!$A$10:$AB$203,2,0) -> PY TSU | H27: 1 | I27: 1 | J27: =IFERROR(IF(I27="std",H27,ROUND(HLOOKUP(A27,FlightConfig!$B$28:$G$29,2,0)*I27,0)),"") -> 56 | K27: =VLOOKUP(Food!E27,'[5]FG MASTER'!$A$1:$AC$521,16,0) -> 0 | L27: =VLOOKUP(Food!E27,'FG MASTER'!A:AJ,17,0) -> 2 | M27: =IFERROR(L27*$M$2,"") -> 0.8 | N27: =IFERROR((K27)+M27,"") -> 0.8 | O27: =IFERROR($K27*(1+$O$2)-$K27+R27,0) -> 0 | P27: =IFERROR($M27*(1+$P$2)-$M27,0) -> 0.104 | Q27: =SUM(N27:P27) -> 0.904 | T27: =L27*J27 -> 112 | V27: =IFERROR(K27*J27-R27*J27,"") -> 0 | W27: =IFERROR(+L27*J27,"") -> 112 | X27: =IFERROR(+M27*J27,"") -> 44.8 | Y27: =IFERROR(+N27*J27+R27*J27,"") -> 44.8 | Z27: =IFERROR(O27*$J27,"") -> 0 | AA27: =IFERROR(P27*$J27,"") -> 5.824 | AB27: =IFERROR(+(Q27+R27)*J27,"") -> 50.624 | AD27: =IFERROR(#REF!*FlightConfig!$K$3,"") | AE27: =IFERROR(V27*FlightConfig!$K$3,"") -> 0 | AF27: =IFERROR(W27*FlightConfig!$K$3,"") -> 40768 | AG27: =IFERROR(X27*FlightConfig!$K$3,"") -> 16307.2 | AH27: =IFERROR(Y27*FlightConfig!$K$3,"") -> 16307.2 | AI27: =IFERROR(AB27*FlightConfig!$K$3,"") -> 18427.136
A28: PREMIUM ECONOMY CLASS | B28: 2 | C28: =CONCATENATE(A28&B28&F28) -> PREMIUM ECONOMY CLASS2 | E28: 10070 | G28: =VLOOKUP(E28,'[5]FG MASTER'!$A$10:$AB$203,2,0) -> PY/YC BUTTER | H28: 1 | I28: 1 | J28: =IFERROR(IF(I28="std",H28,ROUND(HLOOKUP(A28,FlightConfig!$B$28:$G$29,2,0)*I28,0)),"") -> 56 | K28: =VLOOKUP(Food!E28,'[5]FG MASTER'!$A$1:$AC$521,16,0) -> 0.11715 | L28: =VLOOKUP(Food!E28,'FG MASTER'!A:AJ,17,0) -> 0.2 | M28: =IFERROR(L28*$M$2,"") -> 0.08 | N28: =IFERROR((K28)+M28,"") -> 0.19715 | O28: =IFERROR($K28*(1+$O$2)-$K28+R28,0) -> 0.0152295 | P28: =IFERROR($M28*(1+$P$2)-$M28,0) -> 0.0104 | Q28: =SUM(N28:P28) -> 0.2227795 | T28: =L28*J28 -> 11.2 | V28: =IFERROR(K28*J28-R28*J28,"") -> 6.5604 | W28: =IFERROR(+L28*J28,"") -> 11.2 | X28: =IFERROR(+M28*J28,"") -> 4.48 | Y28: =IFERROR(+N28*J28+R28*J28,"") -> 11.0404 | Z28: =IFERROR(O28*$J28,"") -> 0.852852 | AA28: =IFERROR(P28*$J28,"") -> 0.5824 | AB28: =IFERROR(+(Q28+R28)*J28,"") -> 12.475652 | AD28: =IFERROR(#REF!*FlightConfig!$K$3,"") | AE28: =IFERROR(V28*FlightConfig!$K$3,"") -> 2387.9856 | AF28: =IFERROR(W28*FlightConfig!$K$3,"") -> 4076.8 | AG28: =IFERROR(X28*FlightConfig!$K$3,"") -> 1630.72 | AH28: =IFERROR(Y28*FlightConfig!$K$3,"") -> 4018.7056 | AI28: =IFERROR(AB28*FlightConfig!$K$3,"") -> 4541.1373
A29: PREMIUM ECONOMY CLASS | B29: 2 | C29: =CONCATENATE(A29&B29&F29) -> PREMIUM ECONOMY CLASS2 | E29: 10091 | G29: =VLOOKUP(E29,'[5]FG MASTER'!$A$10:$AB$203,2,0) -> PY TSU CHEESE - MINI BRIE WEDGE INVD WRAP, ILE DE GRANCE CHEESE | H29: 1 | I29: 1 | J29: =IFERROR(IF(I29="std",H29,ROUND(HLOOKUP(A29,FlightConfig!$B$28:$G$29,2,0)*I29,0)),"") -> 56 | K29: =VLOOKUP(Food!E29,'[5]FG MASTER'!$A$1:$AC$521,16,0) -> 0.921225 | L29: =VLOOKUP(Food!E29,'FG MASTER'!A:AJ,17,0) -> 0.2 | M29: =IFERROR(L29*$M$2,"") -> 0.08 | N29: =IFERROR((K29)+M29,"") -> 1.001225 | O29: =IFERROR($K29*(1+$O$2)-$K29+R29,0) -> 0.11975925 | P29: =IFERROR($M29*(1+$P$2)-$M29,0) -> 0.0104 | Q29: =SUM(N29:P29) -> 1.1313842 | T29: =L29*J29 -> 11.2 | V29: =IFERROR(K29*J29-R29*J29,"") -> 51.5886 | W29: =L29*J29 -> 11.2 | X29: =+M29*J29 -> 4.48 | Y29: =IFERROR(+N29*J29+R29*J29,"") -> 56.0686 | Z29: =IFERROR(O29*$J29,"") -> 6.706518 | AA29: =IFERROR(P29*$J29,"") -> 0.5824 | AB29: =IFERROR(+(Q29+R29)*J29,"") -> 63.357518 | AD29: =IFERROR(#REF!*FlightConfig!$K$3,"") | AE29: =IFERROR(V29*FlightConfig!$K$3,"") -> 18778.25 | AF29: =IFERROR(W29*FlightConfig!$K$3,"") -> 4076.8 | AG29: =IFERROR(X29*FlightConfig!$K$3,"") -> 1630.72 | AH29: =IFERROR(Y29*FlightConfig!$K$3,"") -> 20408.97 | AI29: =IFERROR(AB29*FlightConfig!$K$3,"") -> 23062.137
A30: PREMIUM ECONOMY CLASS | B30: 2 | C30: =CONCATENATE(A30&B30&F30) -> PREMIUM ECONOMY CLASS2 | E30: 10086 | G30: =VLOOKUP(E30,'[5]FG MASTER'!$A$10:$AB$203,2,0) -> PY CRACKER | H30: 1 | I30: 1 | J30: =IFERROR(IF(I30="std",H30,ROUND(HLOOKUP(A30,FlightConfig!$B$28:$G$29,2,0)*I30,0)),"") -> 56 | K30: =VLOOKUP(Food!E30,'[5]FG MASTER'!$A$1:$AC$521,16,0) -> 0.05325 | L30: =VLOOKUP(Food!E30,'FG MASTER'!A:AJ,17,0) -> 0.2 | M30: =IFERROR(L30*$M$2,"") -> 0.08 | N30: =IFERROR((K30)+M30,"") -> 0.13325 | O30: =IFERROR($K30*(1+$O$2)-$K30+R30,0) -> 0.0069225 | P30: =IFERROR($M30*(1+$P$2)-$M30,0) -> 0.0104 | Q30: =SUM(N30:P30) -> 0.1505725 | T30: =(L30/2)*J30 -> 5.6 | V30: =IFERROR(K30*J30-R30*J30,"") -> 2.982 | W30: =IFERROR(+L30*J30,"") -> 11.2 | X30: =IFERROR(+M30*J30,"") -> 4.48 | Y30: =IFERROR(+N30*J30+R30*J30,"") -> 7.462 | Z30: =IFERROR(O30*$J30,"") -> 0.38766 | AA30: =IFERROR(P30*$J30,"") -> 0.5824 | AB30: =IFERROR(+(Q30+R30)*J30,"") -> 8.43206 | AD30: =IFERROR(#REF!*FlightConfig!$K$3,"") | AE30: =IFERROR(V30*FlightConfig!$K$3,"") -> 1085.448 | AF30: =IFERROR(W30*FlightConfig!$K$3,"") -> 4076.8 | AG30: =IFERROR(X30*FlightConfig!$K$3,"") -> 1630.72 | AH30: =IFERROR(Y30*FlightConfig!$K$3,"") -> 2716.168 | AI30: =IFERROR(AB30*FlightConfig!$K$3,"") -> 3069.2698
A31: PREMIUM ECONOMY CLASS | B31: 2 | C31: =CONCATENATE(A31&B31&F31) -> PREMIUM ECONOMY CLASS2 | E31: 10044 | G31: =VLOOKUP(E31,'[5]FG MASTER'!$A$10:$AB$203,2,0) -> PY C2 HM A FISH COD ALMONDINE, TARRAGON CREAM SAUCE, WILD RICE PILAF, ROASTED CAULIFLOWER, CHERRY TOAMTO | H31: 1 | I31: 0.6 | J31: =IFERROR(IF(I31="std",H31,ROUND(HLOOKUP(A31,FlightConfig!$B$28:$G$29,2,0)*I31,0)),"") -> 34 | K31: =VLOOKUP(Food!E31,'[5]FG MASTER'!$A$1:$AC$521,16,0) -> 3.6294295 | L31: =VLOOKUP(Food!E31,'FG MASTER'!A:AJ,17,0) -> 7 | M31: =IFERROR(L31*$M$2,"") -> 2.8 | N31: =IFERROR((K31)+M31,"") -> 6.4294295 | O31: =IFERROR($K31*(1+$O$2)-$K31+R31,0) -> 0.47182583 | P31: =IFERROR($M31*(1+$P$2)-$M31,0) -> 0.364 | Q31: =SUM(N31:P31) -> 7.2652553 | T31: =(L31/2)*J31 -> 119 | V31: =IFERROR(K31*J31-R31*J31,"") -> 123.4006 | W31: =IFERROR(+L31*J31,"") -> 238 | X31: =IFERROR(+M31*J31,"") -> 95.2 | Y31: =IFERROR(+N31*J31+R31*J31,"") -> 218.6006 | Z31: =IFERROR(O31*$J31,"") -> 16.042078 | AA31: =IFERROR(P31*$J31,"") -> 12.376 | AB31: =IFERROR(+(Q31+R31)*J31,"") -> 247.01868 | AD31: =IFERROR(#REF!*FlightConfig!$K$3,"") | AE31: =IFERROR(V31*FlightConfig!$K$3,"") -> 44917.819 | AF31: =IFERROR(W31*FlightConfig!$K$3,"") -> 86632 | AG31: =IFERROR(X31*FlightConfig!$K$3,"") -> 34652.8 | AH31: =IFERROR(Y31*FlightConfig!$K$3,"") -> 79570.619 | AI31: =IFERROR(AB31*FlightConfig!$K$3,"") -> 89914.8
A32: PREMIUM ECONOMY CLASS | B32: 2 | C32: =CONCATENATE(A32&B32&F32) -> PREMIUM ECONOMY CLASS2 | E32: 10042 | G32: =VLOOKUP(E32,'[5]FG MASTER'!$A$10:$AB$203,2,0) -> PY C2 STARTER PASTRAMI, FARRO SALAD, | H32: 1 | I32: 1 | J32: =IFERROR(IF(I32="std",H32,ROUND(HLOOKUP(A32,FlightConfig!$B$28:$G$29,2,0)*I32,0)),"") -> 56 | K32: =VLOOKUP(Food!E32,'[5]FG MASTER'!$A$1:$AC$521,16,0) -> 0.59434987 | L32: =VLOOKUP(Food!E32,'FG MASTER'!A:AJ,17,0) -> 1.25 | M32: =IFERROR(L32*$M$2,"") -> 0.5 | N32: =IFERROR((K32)+M32,"") -> 1.0943499 | O32: =IFERROR($K32*(1+$O$2)-$K32+R32,0) -> -0.3145939 | P32: =IFERROR($M32*(1+$P$2)-$M32,0) -> 0.065 | Q32: =SUM(N32:P32) -> 0.84475597 | R32: -0.39185939 | S32: =R32*J32 -> -21.944126 | T32: =L32*J32 -> 70 | V32: =IFERROR(K32*J32-R32*J32,"") -> 55.227719 | W32: =L32*J32 -> 70 | X32: =+M32*J32 -> 28 | Y32: =IFERROR(+N32*J32+R32*J32,"") -> 39.339467 | Z32: =IFERROR(O32*$J32,"") -> -17.617259 | AA32: =IFERROR(P32*$J32,"") -> 3.64 | AB32: =IFERROR(+(Q32+R32)*J32,"") -> 25.362209 | AD32: =IFERROR(#REF!*FlightConfig!$K$3,"") | AE32: =IFERROR(V32*FlightConfig!$K$3,"") -> 20102.89 | AF32: =IFERROR(W32*FlightConfig!$K$3,"") -> 25480 | AG32: =IFERROR(X32*FlightConfig!$K$3,"") -> 10192 | AH32: =IFERROR(Y32*FlightConfig!$K$3,"") -> 14319.566 | AI32: =IFERROR(AB32*FlightConfig!$K$3,"") -> 9231.8439
A33: PREMIUM ECONOMY CLASS | B33: 2 | C33: =CONCATENATE(A33&B33&F33) -> PREMIUM ECONOMY CLASS2 | E33: 10046 | G33: =VLOOKUP(E33,'[5]FG MASTER'!$A$10:$AB$203,2,0) -> PY C2 HM B MEAT ROASTED CHICKEN THIGH WITH TRUFFLE CREAM SAUCE, SPINACH WITH GARLIC, MASH POTATOES, AND BABY CARROT | H33: 1 | I33: 0.4 | J33: =IFERROR(IF(I33="std",H33,ROUND(HLOOKUP(A33,FlightConfig!$B$28:$G$29,2,0)*I33,0)),"") -> 22 | K33: =VLOOKUP(Food!E33,'[5]FG MASTER'!$A$1:$AC$521,16,0) -> 2.0468851 | L33: =VLOOKUP(Food!E33,'FG MASTER'!A:AJ,17,0) -> 6.5 | M33: =IFERROR(L33*$M$2,"") -> 2.6 | N33: =IFERROR((K33)+M33,"") -> 4.6468851 | O33: =IFERROR($K33*(1+$O$2)-$K33+R33,0) -> 0.26609506 | P33: =IFERROR($M33*(1+$P$2)-$M33,0) -> 0.338 | Q33: =SUM(N33:P33) -> 5.2509801 | T33: =(L33/2)*J33 -> 71.5 | V33: =IFERROR(K33*J33-R33*J33,"") -> 45.031471 | W33: =IFERROR(+L33*J33,"") -> 143 | X33: =IFERROR(+M33*J33,"") -> 57.2 | Y33: =IFERROR(+N33*J33+R33*J33,"") -> 102.23147 | Z33: =IFERROR(O33*$J33,"") -> 5.8540913 | AA33: =IFERROR(P33*$J33,"") -> 7.436 | AB33: =IFERROR(+(Q33+R33)*J33,"") -> 115.52156 | AD33: =IFERROR(#REF!*FlightConfig!$K$3,"") | AE33: =IFERROR(V33*FlightConfig!$K$3,"") -> 16391.456 | AF33: =IFERROR(W33*FlightConfig!$K$3,"") -> 52052 | AG33: =IFERROR(X33*FlightConfig!$K$3,"") -> 20820.8 | AH33: =IFERROR(Y33*FlightConfig!$K$3,"") -> 37212.256 | AI33: =IFERROR(AB33*FlightConfig!$K$3,"") -> 42049.849
A34: PREMIUM ECONOMY CLASS | B34: 2 | C34: =CONCATENATE(A34&B34&F34) -> PREMIUM ECONOMY CLASS2 | E34: 10048 | G34: =VLOOKUP(E34,'[5]FG MASTER'!$A$10:$AB$203,2,0) -> PY C2 DE PEACH COBBLER TART, BLACKBERRY PASTRY CREAM | H34: 1 | I34: 1 | J34: =IFERROR(IF(I34="std",H34,ROUND(HLOOKUP(A34,FlightConfig!$B$28:$G$29,2,0)*I34,0)),"") -> 56 | K34: =VLOOKUP(Food!E34,'[5]FG MASTER'!$A$1:$AC$521,16,0) -> 0.75437145 | L34: =VLOOKUP(Food!E34,'FG MASTER'!A:AJ,17,0) -> 2.25 | M34: =IFERROR(L34*$M$2,"") -> 0.9 | N34: =IFERROR((K34)+M34,"") -> 1.6543714 | O34: =IFERROR($K34*(1+$O$2)-$K34+R34,0) -> 0.098068288 | P34: =IFERROR($M34*(1+$P$2)-$M34,0) -> 0.117 | Q34: =SUM(N34:P34) -> 1.8694397 | T34: =(L34/2)*J34 -> 63 | V34: =IFERROR(K34*J34-R34*J34,"") -> 42.244801 | W34: =IFERROR(+L34*J34,"") -> 126 | X34: =IFERROR(+M34*J34,"") -> 50.4 | Y34: =IFERROR(+N34*J34+R34*J34,"") -> 92.644801 | Z34: =IFERROR(O34*$J34,"") -> 5.4918242 | AA34: =IFERROR(P34*$J34,"") -> 6.552 | AB34: =IFERROR(+(Q34+R34)*J34,"") -> 104.68863 | AD34: =IFERROR(#REF!*FlightConfig!$K$3,"") | AE34: =IFERROR(V34*FlightConfig!$K$3,"") -> 15377.108 | AF34: =IFERROR(W34*FlightConfig!$K$3,"") -> 45864 | AG34: =IFERROR(X34*FlightConfig!$K$3,"") -> 18345.6 | AH34: =IFERROR(Y34*FlightConfig!$K$3,"") -> 33722.708 | AI34: =IFERROR(AB34*FlightConfig!$K$3,"") -> 38106.66
A35: PREMIUM ECONOMY CLASS | B35: 2 | C35: =CONCATENATE(A35&B35&F35) -> PREMIUM ECONOMY CLASS2 | E35: 10050 | G35: =VLOOKUP(E35,'[5]FG MASTER'!$A$10:$AB$203,2,0) -> PY BRD TYPE 1 SIX GRAIN ROLL | H35: 1 | I35: 1.2 | J35: =IFERROR(IF(I35="std",H35,ROUND(HLOOKUP(A35,FlightConfig!$B$28:$G$29,2,0)*I35,0)),"") -> 67 | K35: =VLOOKUP(Food!E35,'[5]FG MASTER'!$A$1:$AC$521,16,0) -> 0.5032125 | L35: =VLOOKUP(Food!E35,'FG MASTER'!A:AJ,17,0) -> 0.5 | M35: =IFERROR(L35*$M$2,"") -> 0.2 | N35: =IFERROR((K35)+M35,"") -> 0.7032125 | O35: =IFERROR($K35*(1+$O$2)-$K35+R35,0) -> 0.065417625 | P35: =IFERROR($M35*(1+$P$2)-$M35,0) -> 0.026 | Q35: =SUM(N35:P35) -> 0.79463012 | T35: =L35*J35 -> 33.5 | V35: =IFERROR(K35*J35-R35*J35,"") -> 33.715237 | W35: =IFERROR(+L35*J35,"") -> 33.5 | X35: =IFERROR(+M35*J35,"") -> 13.4 | Y35: =IFERROR(+N35*J35+R35*J35,"") -> 47.115237 | Z35: =IFERROR(O35*$J35,"") -> 4.3829809 | AA35: =IFERROR(P35*$J35,"") -> 1.742 | AB35: =IFERROR(+(Q35+R35)*J35,"") -> 53.240218 | AD35: =IFERROR(#REF!*FlightConfig!$K$3,"") | AE35: =IFERROR(V35*FlightConfig!$K$3,"") -> 12272.346 | AF35: =IFERROR(W35*FlightConfig!$K$3,"") -> 12194 | AG35: =IFERROR(X35*FlightConfig!$K$3,"") -> 4877.6 | AH35: =IFERROR(Y35*FlightConfig!$K$3,"") -> 17149.946 | AI35: =IFERROR(AB35*FlightConfig!$K$3,"") -> 19379.439
A36: PREMIUM ECONOMY CLASS | B36: 2 | C36: =CONCATENATE(A36&B36&F36) -> PREMIUM ECONOMY CLASS2 | E36: 10041 | G36: =VLOOKUP(E36,'[5]FG MASTER'!$A$10:$AB$203,2,0) -> PY TSU | H36: 1 | I36: 1 | J36: =IFERROR(IF(I36="std",H36,ROUND(HLOOKUP(A36,FlightConfig!$B$28:$G$29,2,0)*I36,0)),"") -> 56 | K36: =VLOOKUP(Food!E36,'[5]FG MASTER'!$A$1:$AC$521,16,0) -> 0 | L36: =VLOOKUP(Food!E36,'FG MASTER'!A:AJ,17,0) -> 2 | M36: =IFERROR(L36*$M$2,"") -> 0.8 | N36: =IFERROR((K36)+M36,"") -> 0.8 | O36: =IFERROR($K36*(1+$O$2)-$K36+R36,0) -> 0 | P36: =IFERROR($M36*(1+$P$2)-$M36,0) -> 0.104 | Q36: =SUM(N36:P36) -> 0.904 | T36: =L36*J36 -> 112 | V36: =IFERROR(K36*J36-R36*J36,"") -> 0 | W36: =IFERROR(+L36*J36,"") -> 112 | X36: =IFERROR(+M36*J36,"") -> 44.8 | Y36: =IFERROR(+N36*J36+R36*J36,"") -> 44.8 | Z36: =IFERROR(O36*$J36,"") -> 0 | AA36: =IFERROR(P36*$J36,"") -> 5.824 | AB36: =IFERROR(+(Q36+R36)*J36,"") -> 50.624 | AD36: =IFERROR(#REF!*FlightConfig!$K$3,"") | AE36: =IFERROR(V36*FlightConfig!$K$3,"") -> 0 | AF36: =IFERROR(W36*FlightConfig!$K$3,"") -> 40768 | AG36: =IFERROR(X36*FlightConfig!$K$3,"") -> 16307.2 | AH36: =IFERROR(Y36*FlightConfig!$K$3,"") -> 16307.2 | AI36: =IFERROR(AB36*FlightConfig!$K$3,"") -> 18427.136
A37: PREMIUM ECONOMY CLASS | B37: 2 | C37: =CONCATENATE(A37&B37&F37) -> PREMIUM ECONOMY CLASS2 | E37: 10088 | G37: =VLOOKUP(E37,'[5]FG MASTER'!$A$10:$AB$203,2,0) -> NATURE VALLEY GRANOLA BAR | H37: 1 | I37: 1 | J37: =IFERROR(IF(I37="std",H37,ROUND(HLOOKUP(A37,FlightConfig!$B$28:$G$29,2,0)*I37,0)),"") -> 56 | K37: =VLOOKUP(Food!E37,'[5]FG MASTER'!$A$1:$AC$521,16,0) -> 0.602151 | L37: =VLOOKUP(Food!E37,'FG MASTER'!A:AJ,17,0) -> 0.2 | M37: =IFERROR(L37*$M$2,"") -> 0.08 | N37: =IFERROR((K37)+M37,"") -> 0.682151 | O37: =IFERROR($K37*(1+$O$2)-$K37+R37,0) -> 0.07827963 | P37: =IFERROR($M37*(1+$P$2)-$M37,0) -> 0.0104 | Q37: =SUM(N37:P37) -> 0.77083063 | T37: =L37*J37 -> 11.2 | V37: =IFERROR(K37*J37-R37*J37,"") -> 33.720456 | W37: =IFERROR(+L37*J37,"") -> 11.2 | X37: =IFERROR(+M37*J37,"") -> 4.48 | Y37: =IFERROR(+N37*J37+R37*J37,"") -> 38.200456 | Z37: =IFERROR(O37*$J37,"") -> 4.3836593 | AA37: =IFERROR(P37*$J37,"") -> 0.5824 | AB37: =IFERROR(+(Q37+R37)*J37,"") -> 43.166515 | AD37: =IFERROR(#REF!*FlightConfig!$K$3,"") | AE37: =IFERROR(V37*FlightConfig!$K$3,"") -> 12274.246 | AF37: =IFERROR(W37*FlightConfig!$K$3,"") -> 4076.8 | AG37: =IFERROR(X37*FlightConfig!$K$3,"") -> 1630.72 | AH37: =IFERROR(Y37*FlightConfig!$K$3,"") -> 13904.966 | AI37: =IFERROR(AB37*FlightConfig!$K$3,"") -> 15712.612
A38: PREMIUM ECONOMY CLASS | B38: 2 | C38: =CONCATENATE(A38&B38&F38) -> PREMIUM ECONOMY CLASS2 | E38: 10070 | G38: =VLOOKUP(E38,'[5]FG MASTER'!$A$10:$AB$203,2,0) -> PY/YC BUTTER | H38: 1 | I38: 1 | J38: =IFERROR(IF(I38="std",H38,ROUND(HLOOKUP(A38,FlightConfig!$B$28:$G$29,2,0)*I38,0)),"") -> 56 | K38: =VLOOKUP(Food!E38,'[5]FG MASTER'!$A$1:$AC$521,16,0) -> 0.11715 | L38: =VLOOKUP(Food!E38,'FG MASTER'!A:AJ,17,0) -> 0.2 | M38: =IFERROR(L38*$M$2,"") -> 0.08 | N38: =IFERROR((K38)+M38,"") -> 0.19715 | O38: =IFERROR($K38*(1+$O$2)-$K38+R38,0) -> 0.0152295 | P38: =IFERROR($M38*(1+$P$2)-$M38,0) -> 0.0104 | Q38: =SUM(N38:P38) -> 0.2227795 | T38: =L38*J38 -> 11.2 | V38: =IFERROR(K38*J38-R38*J38,"") -> 6.5604 | W38: =IFERROR(+L38*J38,"") -> 11.2 | X38: =IFERROR(+M38*J38,"") -> 4.48 | Y38: =IFERROR(+N38*J38+R38*J38,"") -> 11.0404 | Z38: =IFERROR(O38*$J38,"") -> 0.852852 | AA38: =IFERROR(P38*$J38,"") -> 0.5824 | AB38: =IFERROR(+(Q38+R38)*J38,"") -> 12.475652 | AD38: =IFERROR(#REF!*FlightConfig!$K$3,"") | AE38: =IFERROR(V38*FlightConfig!$K$3,"") -> 2387.9856 | AF38: =IFERROR(W38*FlightConfig!$K$3,"") -> 4076.8 | AG38: =IFERROR(X38*FlightConfig!$K$3,"") -> 1630.72 | AH38: =IFERROR(Y38*FlightConfig!$K$3,"") -> 4018.7056 | AI38: =IFERROR(AB38*FlightConfig!$K$3,"") -> 4541.1373
A39: PREMIUM ECONOMY CLASS | B39: 2 | C39: =CONCATENATE(A39&B39&F39) -> PREMIUM ECONOMY CLASS2 | E39: 10089 | G39: =VLOOKUP(E39,'[5]FG MASTER'!$A$10:$AB$203,2,0) -> YOGURT UPSTATE | H39: 1 | I39: 1 | J39: =IFERROR(IF(I39="std",H39,ROUND(HLOOKUP(A39,FlightConfig!$B$28:$G$29,2,0)*I39,0)),"") -> 56 | K39: =VLOOKUP(Food!E39,'[5]FG MASTER'!$A$1:$AC$521,16,0) -> 0.58575 | L39: =VLOOKUP(Food!E39,'FG MASTER'!A:AJ,17,0) -> 0.2 | M39: =IFERROR(L39*$M$2,"") -> 0.08 | N39: =IFERROR((K39)+M39,"") -> 0.66575 | O39: =IFERROR($K39*(1+$O$2)-$K39+R39,0) -> 0.0761475 | P39: =IFERROR($M39*(1+$P$2)-$M39,0) -> 0.0104 | Q39: =SUM(N39:P39) -> 0.7522975 | T39: =L39*J39 -> 11.2 | V39: =IFERROR(K39*J39-R39*J39,"") -> 32.802 | W39: =L39*J39 -> 11.2 | X39: =+M39*J39 -> 4.48 | Y39: =IFERROR(+N39*J39+R39*J39,"") -> 37.282 | Z39: =IFERROR(O39*$J39,"") -> 4.26426 | AA39: =IFERROR(P39*$J39,"") -> 0.5824 | AB39: =IFERROR(+(Q39+R39)*J39,"") -> 42.12866 | AD39: =IFERROR(#REF!*FlightConfig!$K$3,"") | AE39: =IFERROR(V39*FlightConfig!$K$3,"") -> 11939.928 | AF39: =IFERROR(W39*FlightConfig!$K$3,"") -> 4076.8 | AG39: =IFERROR(X39*FlightConfig!$K$3,"") -> 1630.72 | AH39: =IFERROR(Y39*FlightConfig!$K$3,"") -> 13570.648 | AI39: =IFERROR(AB39*FlightConfig!$K$3,"") -> 15334.832
A40: PREMIUM ECONOMY CLASS | B40: 2 | C40: =CONCATENATE(A40&B40&F40) -> PREMIUM ECONOMY CLASS2 | E40: 10090 | G40: =VLOOKUP(E40,'[5]FG MASTER'!$A$10:$AB$203,2,0) -> MARMALADE ORANGE JM SMUCKER | H40: 1 | I40: 1 | J40: =IFERROR(IF(I40="std",H40,ROUND(HLOOKUP(A40,FlightConfig!$B$28:$G$29,2,0)*I40,0)),"") -> 56 | K40: =VLOOKUP(Food!E40,'[5]FG MASTER'!$A$1:$AC$521,16,0) -> 0.07455 | L40: =VLOOKUP(Food!E40,'FG MASTER'!A:AJ,17,0) -> 0.2 | M40: =IFERROR(L40*$M$2,"") -> 0.08 | N40: =IFERROR((K40)+M40,"") -> 0.15455 | O40: =IFERROR($K40*(1+$O$2)-$K40+R40,0) -> 0.0096915 | P40: =IFERROR($M40*(1+$P$2)-$M40,0) -> 0.0104 | Q40: =SUM(N40:P40) -> 0.1746415 | T40: =(L40/2)*J40 -> 5.6 | V40: =IFERROR(K40*J40-R40*J40,"") -> 4.1748 | W40: =IFERROR(+L40*J40,"") -> 11.2 | X40: =IFERROR(+M40*J40,"") -> 4.48 | Y40: =IFERROR(+N40*J40+R40*J40,"") -> 8.6548 | Z40: =IFERROR(O40*$J40,"") -> 0.542724 | AA40: =IFERROR(P40*$J40,"") -> 0.5824 | AB40: =IFERROR(+(Q40+R40)*J40,"") -> 9.779924 | AD40: =IFERROR(#REF!*FlightConfig!$K$3,"") | AE40: =IFERROR(V40*FlightConfig!$K$3,"") -> 1519.6272 | AF40: =IFERROR(W40*FlightConfig!$K$3,"") -> 4076.8 | AG40: =IFERROR(X40*FlightConfig!$K$3,"") -> 1630.72 | AH40: =IFERROR(Y40*FlightConfig!$K$3,"") -> 3150.3472 | AI40: =IFERROR(AB40*FlightConfig!$K$3,"") -> 3559.8923
A41: PREMIUM ECONOMY CLASS | B41: 2 | C41: =CONCATENATE(A41&B41&F41) -> PREMIUM ECONOMY CLASS2 | E41: 10052 | G41: =VLOOKUP(E41,'[5]FG MASTER'!$A$10:$AB$203,2,0) -> PY C2 BREAKFAST PLATE HAM, GEORGIA GOUDA, EGG, CHERRY TOMATO, GREEN LEAF LETTUCE, CANTALOUPE AND HONEYDEW | H41: 1 | I41: 1 | J41: =IFERROR(IF(I41="std",H41,ROUND(HLOOKUP(A41,FlightConfig!$B$28:$G$29,2,0)*I41,0)),"") -> 56 | K41: =VLOOKUP(Food!E41,'[5]FG MASTER'!$A$1:$AC$521,16,0) -> 1.4795513 | L41: =VLOOKUP(Food!E41,'FG MASTER'!A:AJ,17,0) -> 2.75 | M41: =IFERROR(L41*$M$2,"") -> 1.1 | N41: =IFERROR((K41)+M41,"") -> 2.5795512 | O41: =IFERROR($K41*(1+$O$2)-$K41+R41,0) -> 0.035284689 | P41: =IFERROR($M41*(1+$P$2)-$M41,0) -> 0.143 | Q41: =SUM(N41:P41) -> 2.7578359 | R41: -0.15705697 | S41: =R41*J41 -> -8.7951905 | T41: =(L41/2)*J41 -> 77 | V41: =IFERROR(K41*J41-R41*J41,"") -> 91.65006 | W41: =IFERROR(+L41*J41,"") -> 154 | X41: =IFERROR(+M41*J41,"") -> 61.6 | Y41: =IFERROR(+N41*J41+R41*J41,"") -> 135.65968 | Z41: =IFERROR(O41*$J41,"") -> 1.9759426 | AA41: =IFERROR(P41*$J41,"") -> 8.008 | AB41: =IFERROR(+(Q41+R41)*J41,"") -> 145.64362 | AD41: =IFERROR(#REF!*FlightConfig!$K$3,"") | AE41: =IFERROR(V41*FlightConfig!$K$3,"") -> 33360.622 | AF41: =IFERROR(W41*FlightConfig!$K$3,"") -> 56056 | AG41: =IFERROR(X41*FlightConfig!$K$3,"") -> 22422.4 | AH41: =IFERROR(Y41*FlightConfig!$K$3,"") -> 49380.123 | AI41: =IFERROR(AB41*FlightConfig!$K$3,"") -> 53014.278
A42: ECONOMY CLASS | B42: 2 | C42: =CONCATENATE(A42&B42&F42) -> ECONOMY CLASS2 | E42: 10054 | G42: =VLOOKUP(E42,'[5]FG MASTER'!$A$10:$AB$203,2,0) -> YC TSU | H42: 1 | I42: 1 | J42: =IFERROR(IF(I42="std",H42,ROUND(HLOOKUP(A42,FlightConfig!$B$28:$G$29,2,0)*I42,0)),"") -> 174 | K42: =VLOOKUP(Food!E42,'[5]FG MASTER'!$A$1:$AC$521,16,0) -> 0 | L42: =VLOOKUP(Food!E42,'FG MASTER'!A:AJ,17,0) -> 0.93 | M42: =IFERROR(L42*$M$2,"") -> 0.372 | N42: =IFERROR((K42)+M42,"") -> 0.372 | O42: =IFERROR($K42*(1+18%)-$K42+R42,0) -> 0 | P42: =IFERROR($M42*(1+18%)-$M42,0) -> 0.06696 | Q42: =SUM(N42:P42) -> 0.43896 | T42: =L42*J42 -> 161.82 | V42: =IFERROR(K42*J42-R42*J42,"") -> 0 | W42: =L42*J42 -> 161.82 | X42: =+M42*J42 -> 64.728 | Y42: =IFERROR(+N42*J42+R42*J42,"") -> 64.728 | Z42: =IFERROR(O42*$J42,"") -> 0 | AA42: =IFERROR(P42*$J42,"") -> 11.65104 | AB42: =IFERROR(+(Q42+R42)*J42,"") -> 76.37904 | AD42: =IFERROR(#REF!*FlightConfig!$K$3,"") | AE42: =IFERROR(V42*FlightConfig!$K$3,"") -> 0 | AF42: =IFERROR(W42*FlightConfig!$K$3,"") -> 58902.48 | AG42: =IFERROR(X42*FlightConfig!$K$3,"") -> 23560.992 | AH42: =IFERROR(Y42*FlightConfig!$K$3,"") -> 23560.992 | AI42: =IFERROR(AB42*FlightConfig!$K$3,"") -> 27801.971
A43: ECONOMY CLASS | B43: 2 | C43: =CONCATENATE(A43&B43&F43) -> ECONOMY CLASS2 | E43: 10070 | G43: =VLOOKUP(E43,'[5]FG MASTER'!$A$10:$AB$203,2,0) -> PY/YC BUTTER | H43: 1 | I43: 1 | J43: =IFERROR(IF(I43="std",H43,ROUND(HLOOKUP(A43,FlightConfig!$B$28:$G$29,2,0)*I43,0)),"") -> 174 | K43: =VLOOKUP(Food!E43,'[5]FG MASTER'!$A$1:$AC$521,16,0) -> 0.11715 | L43: =VLOOKUP(Food!E43,'FG MASTER'!A:AJ,17,0) -> 0.2 | M43: =IFERROR(L43*$M$2,"") -> 0.08 | N43: =IFERROR((K43)+M43,"") -> 0.19715 | O43: =IFERROR($K43*(1+$O$2)-$K43+R43,0) -> 0.0152295 | P43: =IFERROR($M43*(1+$P$2)-$M43,0) -> 0.0104 | Q43: =SUM(N43:P43) -> 0.2227795 | T43: =L43*J43 -> 34.8 | V43: =IFERROR(K43*J43-R43*J43,"") -> 20.3841 | W43: =IFERROR(+L43*J43,"") -> 34.8 | X43: =IFERROR(+M43*J43,"") -> 13.92 | Y43: =IFERROR(+N43*J43+R43*J43,"") -> 34.3041 | Z43: =IFERROR(O43*$J43,"") -> 2.649933 | AA43: =IFERROR(P43*$J43,"") -> 1.8096 | AB43: =IFERROR(+(Q43+R43)*J43,"") -> 38.763633 | AD43: =IFERROR(#REF!*FlightConfig!$K$3,"") | AE43: =IFERROR(V43*FlightConfig!$K$3,"") -> 7419.8124 | AF43: =IFERROR(W43*FlightConfig!$K$3,"") -> 12667.2 | AG43: =IFERROR(X43*FlightConfig!$K$3,"") -> 5066.88 | AH43: =IFERROR(Y43*FlightConfig!$K$3,"") -> 12486.692 | AI43: =IFERROR(AB43*FlightConfig!$K$3,"") -> 14109.962
A44: ECONOMY CLASS | B44: 2 | C44: =CONCATENATE(A44&B44&F44) -> ECONOMY CLASS2 | E44: 10055 | G44: =VLOOKUP(E44,'[5]FG MASTER'!$A$10:$AB$203,2,0) -> YC C2 SALAD MESCLUN GREEN, CUCUMBER SLICE, SHREDDED CARROT, BOCCANCINI MOZZARELLA BALL | H44: 1 | I44: 1 | J44: =IFERROR(IF(I44="std",H44,ROUND(HLOOKUP(A44,FlightConfig!$B$28:$G$29,2,0)*I44,0)),"") -> 174 | K44: =VLOOKUP(Food!E44,'[5]FG MASTER'!$A$1:$AC$521,16,0) -> 0.451134 | L44: =VLOOKUP(Food!E44,'FG MASTER'!A:AJ,17,0) -> 1 | M44: =IFERROR(L44*$M$2,"") -> 0.4 | N44: =IFERROR((K44)+M44,"") -> 0.851134 | O44: =IFERROR($K44*(1+18%)-$K44+R44,0) -> 0.08120412 | P44: =IFERROR($M44*(1+18%)-$M44,0) -> 0.072 | Q44: =SUM(N44:P44) -> 1.0043381 | T44: =L44*J44 -> 174 | V44: =IFERROR(K44*J44-R44*J44,"") -> 78.497316 | W44: =L44*J44 -> 174 | X44: =+M44*J44 -> 69.6 | Y44: =IFERROR(+N44*J44+R44*J44,"") -> 148.09732 | Z44: =IFERROR(O44*$J44,"") -> 14.129517 | AA44: =IFERROR(P44*$J44,"") -> 12.528 | AB44: =IFERROR(+(Q44+R44)*J44,"") -> 174.75483 | AD44: =IFERROR(#REF!*FlightConfig!$K$3,"") | AE44: =IFERROR(V44*FlightConfig!$K$3,"") -> 28573.023 | AF44: =IFERROR(W44*FlightConfig!$K$3,"") -> 63336 | AG44: =IFERROR(X44*FlightConfig!$K$3,"") -> 25334.4 | AH44: =IFERROR(Y44*FlightConfig!$K$3,"") -> 53907.423 | AI44: =IFERROR(AB44*FlightConfig!$K$3,"") -> 63610.759
A45: ECONOMY CLASS | B45: 2 | C45: =CONCATENATE(A45&B45&F45) -> ECONOMY CLASS2 | E45: 10057 | G45: =VLOOKUP(E45,'[5]FG MASTER'!$A$10:$AB$203,2,0) -> YC C2 HM B ROASTED CHICKEN THIGH WITH TRUFFLE CREAM SAUCE, SPINACH WITH GARLIC, MASH POTATOES, AND BABY CARROT | H45: 1 | I45: 1 | J45: =IFERROR(IF(I45="std",H45,ROUND(HLOOKUP(A45,FlightConfig!$B$28:$G$29,2,0)*I45,0)),"") -> 174 | K45: =VLOOKUP(Food!E45,'[5]FG MASTER'!$A$1:$AC$521,16,0) -> 2.0468851 | L45: =VLOOKUP(Food!E45,'FG MASTER'!A:AJ,17,0) -> 6.5 | M45: =IFERROR(L45*$M$2,"") -> 2.6 | N45: =IFERROR((K45)+M45,"") -> 4.6468851 | O45: =IFERROR($K45*(1+18%)-$K45+R45,0) -> 0.36843931 | P45: =IFERROR($M45*(1+18%)-$M45,0) -> 0.468 | Q45: =SUM(N45:P45) -> 5.4833244 | T45: =(L45/2)*J45 -> 565.5 | V45: =IFERROR(K45*J45-R45*J45,"") -> 356.158 | W45: =IFERROR(+L45*J45,"") -> 1131 | X45: =IFERROR(+M45*J45,"") -> 452.4 | Y45: =IFERROR(+N45*J45+R45*J45,"") -> 808.558 | Z45: =IFERROR(O45*$J45,"") -> 64.10844 | AA45: =IFERROR(P45*$J45,"") -> 81.432 | AB45: =IFERROR(+(Q45+R45)*J45,"") -> 954.09844 | AD45: =IFERROR(#REF!*FlightConfig!$K$3,"") | AE45: =IFERROR(V45*FlightConfig!$K$3,"") -> 129641.51 | AF45: =IFERROR(W45*FlightConfig!$K$3,"") -> 411684 | AG45: =IFERROR(X45*FlightConfig!$K$3,"") -> 164673.6 | AH45: =IFERROR(Y45*FlightConfig!$K$3,"") -> 294315.11 | AI45: =IFERROR(AB45*FlightConfig!$K$3,"") -> 347291.83
A46: ECONOMY CLASS | B46: 2 | C46: =CONCATENATE(A46&B46&F46) -> ECONOMY CLASS2 | E46: 10059 | G46: =VLOOKUP(E46,'[5]FG MASTER'!$A$10:$AB$203,2,0) -> YC C2 DE STRAWBERRY MOUSSE, WHITE CHOCOLATE CURLS | H46: 1 | I46: 1 | J46: =IFERROR(IF(I46="std",H46,ROUND(HLOOKUP(A46,FlightConfig!$B$28:$G$29,2,0)*I46,0)),"") -> 174 | K46: =VLOOKUP(Food!E46,'[5]FG MASTER'!$A$1:$AC$521,16,0) -> 0.5892645 | L46: =VLOOKUP(Food!E46,'FG MASTER'!A:AJ,17,0) -> 1 | M46: =IFERROR(L46*$M$2,"") -> 0.4 | N46: =IFERROR((K46)+M46,"") -> 0.9892645 | O46: =IFERROR($K46*(1+18%)-$K46+R46,0) -> 0.10606761 | P46: =IFERROR($M46*(1+18%)-$M46,0) -> 0.072 | Q46: =SUM(N46:P46) -> 1.1673321 | T46: =(L46/2)*J46 -> 87 | V46: =IFERROR(K46*J46-R46*J46,"") -> 102.53202 | W46: =IFERROR(+L46*J46,"") -> 174 | X46: =IFERROR(+M46*J46,"") -> 69.6 | Y46: =IFERROR(+N46*J46+R46*J46,"") -> 172.13202 | Z46: =IFERROR(O46*$J46,"") -> 18.455764 | AA46: =IFERROR(P46*$J46,"") -> 12.528 | AB46: =IFERROR(+(Q46+R46)*J46,"") -> 203.11579 | AD46: =IFERROR(#REF!*FlightConfig!$K$3,"") | AE46: =IFERROR(V46*FlightConfig!$K$3,"") -> 37321.656 | AF46: =IFERROR(W46*FlightConfig!$K$3,"") -> 63336 | AG46: =IFERROR(X46*FlightConfig!$K$3,"") -> 25334.4 | AH46: =IFERROR(Y46*FlightConfig!$K$3,"") -> 62656.056 | AI46: =IFERROR(AB46*FlightConfig!$K$3,"") -> 73934.147
A47: ECONOMY CLASS | B47: 2 | C47: =CONCATENATE(A47&B47&F47) -> ECONOMY CLASS2 | E47: 10061 | G47: =VLOOKUP(E47,'[5]FG MASTER'!$A$10:$AB$203,2,0) -> YC C2 BRD TYPE 1 HONEY WHEAT ROLL | H47: 1 | I47: 1.2 | J47: =IFERROR(IF(I47="std",H47,ROUND(HLOOKUP(A47,FlightConfig!$B$28:$G$29,2,0)*I47,0)),"") -> 209 | K47: =VLOOKUP(Food!E47,'[5]FG MASTER'!$A$1:$AC$521,16,0) -> 0.15975 | L47: =VLOOKUP(Food!E47,'FG MASTER'!A:AJ,17,0) -> 0.2 | M47: =IFERROR(L47*$M$2,"") -> 0.08 | N47: =IFERROR((K47)+M47,"") -> 0.23975 | O47: =IFERROR($K47*(1+18%)-$K47+R47,0) -> 0.028755 | P47: =IFERROR($M47*(1+18%)-$M47,0) -> 0.0144 | Q47: =SUM(N47:P47) -> 0.282905 | T47: =L47*J47 -> 41.8 | V47: =IFERROR(K47*J47-R47*J47,"") -> 33.38775 | W47: =IFERROR(+L47*J47,"") -> 41.8 | X47: =IFERROR(+M47*J47,"") -> 16.72 | Y47: =IFERROR(+N47*J47+R47*J47,"") -> 50.10775 | Z47: =IFERROR(O47*$J47,"") -> 6.009795 | AA47: =IFERROR(P47*$J47,"") -> 3.0096 | AB47: =IFERROR(+(Q47+R47)*J47,"") -> 59.127145 | AD47: =IFERROR(#REF!*FlightConfig!$K$3,"") | AE47: =IFERROR(V47*FlightConfig!$K$3,"") -> 12153.141 | AF47: =IFERROR(W47*FlightConfig!$K$3,"") -> 15215.2 | AG47: =IFERROR(X47*FlightConfig!$K$3,"") -> 6086.08 | AH47: =IFERROR(Y47*FlightConfig!$K$3,"") -> 18239.221 | AI47: =IFERROR(AB47*FlightConfig!$K$3,"") -> 21522.281
A48: ECONOMY CLASS | B48: 2 | C48: =CONCATENATE(A48&B48&F48) -> ECONOMY CLASS2 | E48: 10063 | G48: =VLOOKUP(E48,'[5]FG MASTER'!$A$10:$AB$203,2,0) -> YC C2 JUICE CUP APPLE JUICE | H48: 1 | I48: 1 | J48: =IFERROR(IF(I48="std",H48,ROUND(HLOOKUP(A48,FlightConfig!$B$28:$G$29,2,0)*I48,0)),"") -> 174 | K48: =VLOOKUP(Food!E48,'[5]FG MASTER'!$A$1:$AC$521,16,0) -> 0.426 | L48: =VLOOKUP(Food!E48,'FG MASTER'!A:AJ,17,0) -> 0.2 | M48: =IFERROR(L48*$M$2,"") -> 0.08 | N48: =IFERROR((K48)+M48,"") -> 0.506 | O48: =IFERROR($K48*(1+18%)-$K48+R48,0) -> 0.07668 | P48: =IFERROR($M48*(1+18%)-$M48,0) -> 0.0144 | Q48: =SUM(N48:P48) -> 0.59708 | T48: =L48*J48 -> 34.8 | V48: =IFERROR(K48*J48-R48*J48,"") -> 74.124 | W48: =IFERROR(+L48*J48,"") -> 34.8 | X48: =IFERROR(+M48*J48,"") -> 13.92 | Y48: =IFERROR(+N48*J48+R48*J48,"") -> 88.044 | Z48: =IFERROR(O48*$J48,"") -> 13.34232 | AA48: =IFERROR(P48*$J48,"") -> 2.5056 | AB48: =IFERROR(+(Q48+R48)*J48,"") -> 103.89192 | AD48: =IFERROR(#REF!*FlightConfig!$K$3,"") | AE48: =IFERROR(V48*FlightConfig!$K$3,"") -> 26981.136 | AF48: =IFERROR(W48*FlightConfig!$K$3,"") -> 12667.2 | AG48: =IFERROR(X48*FlightConfig!$K$3,"") -> 5066.88 | AH48: =IFERROR(Y48*FlightConfig!$K$3,"") -> 32048.016 | AI48: =IFERROR(AB48*FlightConfig!$K$3,"") -> 37816.659
A49: ECONOMY CLASS | B49: 2 | C49: =CONCATENATE(A49&B49&F49) -> ECONOMY CLASS2 | E49: 10065 | G49: =VLOOKUP(E49,'[5]FG MASTER'!$A$10:$AB$203,2,0) -> YC C2 SW NOMINATED SANDWICH (COST PASS THROUGH) | H49: 1 | I49: 1 | J49: =IFERROR(IF(I49="std",H49,ROUND(HLOOKUP(A49,FlightConfig!$B$28:$G$29,2,0)*I49,0)),"") -> 174 | K49: =VLOOKUP(Food!E49,'[5]FG MASTER'!$A$1:$AC$521,16,0) -> 0 | L49: =VLOOKUP(Food!E49,'FG MASTER'!A:AJ,17,0) -> 1 | M49: =IFERROR(L49*$M$2,"") -> 0.4 | N49: =IFERROR((K49)+M49,"") -> 0.4 | O49: =IFERROR($K49*(1+18%)-$K49+R49,0) -> 0 | P49: =IFERROR($M49*(1+18%)-$M49,0) -> 0.072 | Q49: =SUM(N49:P49) -> 0.472 | T49: =L49*J49 -> 174 | V49: =IFERROR(K49*J49-R49*J49,"") -> 0 | W49: =IFERROR(+L49*J49,"") -> 174 | X49: =IFERROR(+M49*J49,"") -> 69.6 | Y49: =IFERROR(+N49*J49+R49*J49,"") -> 69.6 | Z49: =IFERROR(O49*$J49,"") -> 0 | AA49: =IFERROR(P49*$J49,"") -> 12.528 | AB49: =IFERROR(+(Q49+R49)*J49,"") -> 82.128 | AD49: =IFERROR(#REF!*FlightConfig!$K$3,"") | AE49: =IFERROR(V49*FlightConfig!$K$3,"") -> 0 | AF49: =IFERROR(W49*FlightConfig!$K$3,"") -> 63336 | AG49: =IFERROR(X49*FlightConfig!$K$3,"") -> 25334.4 | AH49: =IFERROR(Y49*FlightConfig!$K$3,"") -> 25334.4 | AI49: =IFERROR(AB49*FlightConfig!$K$3,"") -> 29894.592
A50: TECH CREW CLASS | B50: 2 | C50: =CONCATENATE(A50&B50&F50) -> TECH CREW CLASS2 | E50: 10073 | G50: =VLOOKUP(E50,'[5]FG MASTER'!$A$10:$AB$203,2,0) -> CREW CUTLERY DISPOSAL | H50: 1 | I50: 1 | J50: =IFERROR(IF(I50="std",H50,ROUND(HLOOKUP(A50,FlightConfig!$B$28:$G$29,2,0)*I50,0)),"") -> 2 | K50: =VLOOKUP(Food!E50,'[5]FG MASTER'!$A$1:$AC$521,16,0) -> 0.1065 | L50: =VLOOKUP(Food!E50,'FG MASTER'!A:AJ,17,0) -> 0.2 | M50: =IFERROR(L50*$M$2,"") -> 0.08 | N50: =IFERROR((K50)+M50,"") -> 0.1865 | O50: =IFERROR($K50*(1+$O$2)-$K50+R50,0) -> 0.013845 | P50: =IFERROR($M50*(1+$P$2)-$M50,0) -> 0.0104 | Q50: =SUM(N50:P50) -> 0.210745 | T50: =L50*J50 -> 0.4 | V50: =IFERROR(K50*J50-R50*J50,"") -> 0.213 | W50: =IFERROR(+L50*J50,"") -> 0.4 | X50: =IFERROR(+M50*J50,"") -> 0.16 | Y50: =IFERROR(+N50*J50+R50*J50,"") -> 0.373 | Z50: =IFERROR(O50*$J50,"") -> 0.02769 | AA50: =IFERROR(P50*$J50,"") -> 0.0208 | AB50: =IFERROR(+(Q50+R50)*J50,"") -> 0.42149 | AD50: =IFERROR(#REF!*FlightConfig!$K$3,"") | AE50: =IFERROR(V50*FlightConfig!$K$3,"") -> 77.532 | AF50: =IFERROR(W50*FlightConfig!$K$3,"") -> 145.6 | AG50: =IFERROR(X50*FlightConfig!$K$3,"") -> 58.24 | AH50: =IFERROR(Y50*FlightConfig!$K$3,"") -> 135.772 | AI50: =IFERROR(AB50*FlightConfig!$K$3,"") -> 153.42236
A51: TECH CREW CLASS | B51: 2 | C51: =CONCATENATE(A51&B51&F51) -> TECH CREW CLASS2 | E51: 10072 | G51: =VLOOKUP(E51,'[5]FG MASTER'!$A$10:$AB$203,2,0) -> CREW BUTTER | H51: 1 | I51: 1 | J51: =IFERROR(IF(I51="std",H51,ROUND(HLOOKUP(A51,FlightConfig!$B$28:$G$29,2,0)*I51,0)),"") -> 2 | K51: =VLOOKUP(Food!E51,'[5]FG MASTER'!$A$1:$AC$521,16,0) -> 0.11715 | L51: =VLOOKUP(Food!E51,'FG MASTER'!A:AJ,17,0) -> 0.2 | M51: =IFERROR(L51*$M$2,"") -> 0.08 | N51: =IFERROR((K51)+M51,"") -> 0.19715 | O51: =IFERROR($K51*(1+$O$2)-$K51+R51,0) -> 0.0152295 | P51: =IFERROR($M51*(1+$P$2)-$M51,0) -> 0.0104 | Q51: =SUM(N51:P51) -> 0.2227795 | T51: =L51*J51 -> 0.4 | V51: =IFERROR(K51*J51-R51*J51,"") -> 0.2343 | W51: =IFERROR(+L51*J51,"") -> 0.4 | X51: =IFERROR(+M51*J51,"") -> 0.16 | Y51: =IFERROR(+N51*J51+R51*J51,"") -> 0.3943 | Z51: =IFERROR(O51*$J51,"") -> 0.030459 | AA51: =IFERROR(P51*$J51,"") -> 0.0208 | AB51: =IFERROR(+(Q51+R51)*J51,"") -> 0.445559 | AD51: =IFERROR(#REF!*FlightConfig!$K$3,"") | AE51: =IFERROR(V51*FlightConfig!$K$3,"") -> 85.2852 | AF51: =IFERROR(W51*FlightConfig!$K$3,"") -> 145.6 | AG51: =IFERROR(X51*FlightConfig!$K$3,"") -> 58.24 | AH51: =IFERROR(Y51*FlightConfig!$K$3,"") -> 143.5252 | AI51: =IFERROR(AB51*FlightConfig!$K$3,"") -> 162.18348
A52: TECH CREW CLASS | B52: 2 | C52: =CONCATENATE(A52&B52&F52) -> TECH CREW CLASS2 | E52: 10074 | G52: =VLOOKUP(E52,'[5]FG MASTER'!$A$10:$AB$203,2,0) -> CREW BREAD MILTIGRAIN | H52: 1 | I52: 1 | J52: =IFERROR(IF(I52="std",H52,ROUND(HLOOKUP(A52,FlightConfig!$B$28:$G$29,2,0)*I52,0)),"") -> 2 | K52: =VLOOKUP(Food!E52,'[5]FG MASTER'!$A$1:$AC$521,16,0) -> 0.26625 | L52: =VLOOKUP(Food!E52,'FG MASTER'!A:AJ,17,0) -> 0.2 | M52: =IFERROR(L52*$M$2,"") -> 0.08 | N52: =IFERROR((K52)+M52,"") -> 0.34625 | O52: =IFERROR($K52*(1+$O$2)-$K52+R52,0) -> 0.0346125 | P52: =IFERROR($M52*(1+$P$2)-$M52,0) -> 0.0104 | Q52: =SUM(N52:P52) -> 0.3912625 | T52: =L52*J52 -> 0.4 | V52: =IFERROR(K52*J52-R52*J52,"") -> 0.5325 | W52: =IFERROR(+L52*J52,"") -> 0.4 | X52: =IFERROR(+M52*J52,"") -> 0.16 | Y52: =IFERROR(+N52*J52+R52*J52,"") -> 0.6925 | Z52: =IFERROR(O52*$J52,"") -> 0.069225 | AA52: =IFERROR(P52*$J52,"") -> 0.0208 | AB52: =IFERROR(+(Q52+R52)*J52,"") -> 0.782525 | AD52: =IFERROR(#REF!*FlightConfig!$K$3,"") | AE52: =IFERROR(V52*FlightConfig!$K$3,"") -> 193.83 | AF52: =IFERROR(W52*FlightConfig!$K$3,"") -> 145.6 | AG52: =IFERROR(X52*FlightConfig!$K$3,"") -> 58.24 | AH52: =IFERROR(Y52*FlightConfig!$K$3,"") -> 252.07 | AI52: =IFERROR(AB52*FlightConfig!$K$3,"") -> 284.8391
A53: TECH CREW CLASS | B53: 2 | C53: =CONCATENATE(A53&B53&F53) -> TECH CREW CLASS2 | E53: 10077 | G53: =VLOOKUP(E53,'[5]FG MASTER'!$A$10:$AB$203,2,0) -> DECK CREW CM SMOKE SALMON, GOUDA CHEESE SLICE, BABY SPINACH, PICKLED RED ONION, RED CHERRY TOMATO, CAPER, POTATO SALAD | H53: 1 | I53: 0.5 | J53: =IFERROR(IF(I53="std",H53,ROUND(HLOOKUP(A53,FlightConfig!$B$28:$G$29,2,0)*I53,0)),"") -> 1 | K53: =VLOOKUP(Food!E53,'[5]FG MASTER'!$A$1:$AC$521,16,0) -> 1.8101166 | L53: =VLOOKUP(Food!E53,'FG MASTER'!A:AJ,17,0) -> 2.75 | M53: =IFERROR(L53*$M$2,"") -> 1.1 | N53: =IFERROR((K53)+M53,"") -> 2.9101166 | O53: =IFERROR($K53*(1+$O$2)-$K53+R53,0) -> 0.218111 | P53: =IFERROR($M53*(1+$P$2)-$M53,0) -> 0.143 | Q53: =SUM(N53:P53) -> 3.2712276 | R53: -0.017204157 | S53: =R53*J53 -> -0.017204157 | T53: =L53*J53 -> 2.75 | V53: =IFERROR(K53*J53-R53*J53,"") -> 1.8273208 | W53: =IFERROR(+L53*J53,"") -> 2.75 | X53: =IFERROR(+M53*J53,"") -> 1.1 | Y53: =IFERROR(+N53*J53+R53*J53,"") -> 2.8929124 | Z53: =IFERROR(O53*$J53,"") -> 0.218111 | AA53: =IFERROR(P53*$J53,"") -> 0.143 | AB53: =IFERROR(+(Q53+R53)*J53,"") -> 3.2540234 | AD53: =IFERROR(#REF!*FlightConfig!$K$3,"") | AE53: =IFERROR(V53*FlightConfig!$K$3,"") -> 665.14476 | AF53: =IFERROR(W53*FlightConfig!$K$3,"") -> 1001 | AG53: =IFERROR(X53*FlightConfig!$K$3,"") -> 400.4 | AH53: =IFERROR(Y53*FlightConfig!$K$3,"") -> 1053.0201 | AI53: =IFERROR(AB53*FlightConfig!$K$3,"") -> 1184.4645
A54: TECH CREW CLASS | B54: 2 | C54: =CONCATENATE(A54&B54&F54) -> TECH CREW CLASS2 | E54: 10078 | G54: =VLOOKUP(E54,'[5]FG MASTER'!$A$10:$AB$203,2,0) -> DECK CREW CM A PASTRAMI, GOUDA CHEESE, MESCLUN MIX, CHERRY TOMATO RED GRAPES, PASTA PESTO SALAD | H54: 1 | I54: 1 | J54: =IFERROR(IF(I54="std",H54,ROUND(HLOOKUP(A54,FlightConfig!$B$28:$G$29,2,0)*I54,0)),"") -> 2 | K54: =VLOOKUP(Food!E54,'[5]FG MASTER'!$A$1:$AC$521,16,0) -> 1.4504874 | L54: =VLOOKUP(Food!E54,'FG MASTER'!A:AJ,17,0) -> 2.75 | M54: =IFERROR(L54*$M$2,"") -> 1.1 | N54: =IFERROR((K54)+M54,"") -> 2.5504874 | O54: =IFERROR($K54*(1+$O$2)-$K54+R54,0) -> -0.59515541 | P54: =IFERROR($M54*(1+$P$2)-$M54,0) -> 0.143 | Q54: =SUM(N54:P54) -> 2.098332 | R54: -0.78371878 | S54: =R54*J54 -> -1.5674376 | T54: =L54*J54 -> 5.5 | V54: =IFERROR(K54*J54-R54*J54,"") -> 4.4684124 | W54: =L54*J54 -> 5.5 | X54: =+M54*J54 -> 2.2 | Y54: =IFERROR(+N54*J54+R54*J54,"") -> 3.5335372 | Z54: =IFERROR(O54*$J54,"") -> -1.1903108 | AA54: =IFERROR(P54*$J54,"") -> 0.286 | AB54: =IFERROR(+(Q54+R54)*J54,"") -> 2.6292264 | AD54: =IFERROR(#REF!*FlightConfig!$K$3,"") | AE54: =IFERROR(V54*FlightConfig!$K$3,"") -> 1626.5021 | AF54: =IFERROR(W54*FlightConfig!$K$3,"") -> 2002 | AG54: =IFERROR(X54*FlightConfig!$K$3,"") -> 800.8 | AH54: =IFERROR(Y54*FlightConfig!$K$3,"") -> 1286.2076 | AI54: =IFERROR(AB54*FlightConfig!$K$3,"") -> 957.03842
A55: TECH CREW CLASS | B55: 2 | C55: =CONCATENATE(A55&B55&F55) -> TECH CREW CLASS2 | E55: 10079 | G55: =VLOOKUP(E55,'[5]FG MASTER'!$A$10:$AB$203,2,0) -> CREW VINAIGRETTE DRESSING | H55: 1 | I55: 1 | J55: =IFERROR(IF(I55="std",H55,ROUND(HLOOKUP(A55,FlightConfig!$B$28:$G$29,2,0)*I55,0)),"") -> 2 | K55: =VLOOKUP(Food!E55,'[5]FG MASTER'!$A$1:$AC$521,16,0) -> 0.1065 | L55: =VLOOKUP(Food!E55,'FG MASTER'!A:AJ,17,0) -> 0.2 | M55: =IFERROR(L55*$M$2,"") -> 0.08 | N55: =IFERROR((K55)+M55,"") -> 0.1865 | O55: =IFERROR($K55*(1+$O$2)-$K55+R55,0) -> 0.013845 | P55: =IFERROR($M55*(1+$P$2)-$M55,0) -> 0.0104 | Q55: =SUM(N55:P55) -> 0.210745 | T55: =L55*J55 -> 0.4 | V55: =IFERROR(K55*J55-R55*J55,"") -> 0.213 | W55: =IFERROR(+L55*J55,"") -> 0.4 | X55: =IFERROR(+M55*J55,"") -> 0.16 | Y55: =IFERROR(+N55*J55+R55*J55,"") -> 0.373 | Z55: =IFERROR(O55*$J55,"") -> 0.02769 | AA55: =IFERROR(P55*$J55,"") -> 0.0208 | AB55: =IFERROR(+(Q55+R55)*J55,"") -> 0.42149 | AD55: =IFERROR(#REF!*FlightConfig!$K$3,"") | AE55: =IFERROR(V55*FlightConfig!$K$3,"") -> 77.532 | AF55: =IFERROR(W55*FlightConfig!$K$3,"") -> 145.6 | AG55: =IFERROR(X55*FlightConfig!$K$3,"") -> 58.24 | AH55: =IFERROR(Y55*FlightConfig!$K$3,"") -> 135.772 | AI55: =IFERROR(AB55*FlightConfig!$K$3,"") -> 153.42236
A56: TECH CREW CLASS | B56: 2 | C56: =CONCATENATE(A56&B56&F56) -> TECH CREW CLASS2 | E56: 10072 | G56: =VLOOKUP(E56,'[5]FG MASTER'!$A$10:$AB$203,2,0) -> CREW BUTTER | H56: 1 | I56: 1 | J56: =IFERROR(IF(I56="std",H56,ROUND(HLOOKUP(A56,FlightConfig!$B$28:$G$29,2,0)*I56,0)),"") -> 2 | K56: =VLOOKUP(Food!E56,'[5]FG MASTER'!$A$1:$AC$521,16,0) -> 0.11715 | L56: =VLOOKUP(Food!E56,'FG MASTER'!A:AJ,17,0) -> 0.2 | M56: =IFERROR(L56*$M$2,"") -> 0.08 | N56: =IFERROR((K56)+M56,"") -> 0.19715 | O56: =IFERROR($K56*(1+$O$2)-$K56+R56,0) -> 0.0152295 | P56: =IFERROR($M56*(1+$P$2)-$M56,0) -> 0.0104 | Q56: =SUM(N56:P56) -> 0.2227795 | T56: =L56*J56 -> 0.4 | V56: =IFERROR(K56*J56-R56*J56,"") -> 0.2343 | W56: =IFERROR(+L56*J56,"") -> 0.4 | X56: =IFERROR(+M56*J56,"") -> 0.16 | Y56: =IFERROR(+N56*J56+R56*J56,"") -> 0.3943 | Z56: =IFERROR(O56*$J56,"") -> 0.030459 | AA56: =IFERROR(P56*$J56,"") -> 0.0208 | AB56: =IFERROR(+(Q56+R56)*J56,"") -> 0.445559 | AD56: =IFERROR(#REF!*FlightConfig!$K$3,"") | AE56: =IFERROR(V56*FlightConfig!$K$3,"") -> 85.2852 | AF56: =IFERROR(W56*FlightConfig!$K$3,"") -> 145.6 | AG56: =IFERROR(X56*FlightConfig!$K$3,"") -> 58.24 | AH56: =IFERROR(Y56*FlightConfig!$K$3,"") -> 143.5252 | AI56: =IFERROR(AB56*FlightConfig!$K$3,"") -> 162.18348
A57: TECH CREW CLASS | B57: 2 | C57: =CONCATENATE(A57&B57&F57) -> TECH CREW CLASS2 | E57: 10073 | G57: =VLOOKUP(E57,'[5]FG MASTER'!$A$10:$AB$203,2,0) -> CREW CUTLERY DISPOSAL | H57: 1 | I57: 1 | J57: =IFERROR(IF(I57="std",H57,ROUND(HLOOKUP(A57,FlightConfig!$B$28:$G$29,2,0)*I57,0)),"") -> 2 | K57: =VLOOKUP(Food!E57,'[5]FG MASTER'!$A$1:$AC$521,16,0) -> 0.1065 | L57: =VLOOKUP(Food!E57,'FG MASTER'!A:AJ,17,0) -> 0.2 | M57: =IFERROR(L57*$M$2,"") -> 0.08 | N57: =IFERROR((K57)+M57,"") -> 0.1865 | O57: =IFERROR($K57*(1+$O$2)-$K57+R57,0) -> 0.013845 | P57: =IFERROR($M57*(1+$P$2)-$M57,0) -> 0.0104 | Q57: =SUM(N57:P57) -> 0.210745 | T57: =L57*J57 -> 0.4 | V57: =IFERROR(K57*J57-R57*J57,"") -> 0.213 | W57: =IFERROR(+L57*J57,"") -> 0.4 | X57: =IFERROR(+M57*J57,"") -> 0.16 | Y57: =IFERROR(+N57*J57+R57*J57,"") -> 0.373 | Z57: =IFERROR(O57*$J57,"") -> 0.02769 | AA57: =IFERROR(P57*$J57,"") -> 0.0208 | AB57: =IFERROR(+(Q57+R57)*J57,"") -> 0.42149 | AD57: =IFERROR(#REF!*FlightConfig!$K$3,"") | AE57: =IFERROR(V57*FlightConfig!$K$3,"") -> 77.532 | AF57: =IFERROR(W57*FlightConfig!$K$3,"") -> 145.6 | AG57: =IFERROR(X57*FlightConfig!$K$3,"") -> 58.24 | AH57: =IFERROR(Y57*FlightConfig!$K$3,"") -> 135.772 | AI57: =IFERROR(AB57*FlightConfig!$K$3,"") -> 153.42236
A58: TECH CREW CLASS | B58: 2 | C58: =CONCATENATE(A58&B58&F58) -> TECH CREW CLASS2 | E58: 10074 | G58: =VLOOKUP(E58,'[5]FG MASTER'!$A$10:$AB$203,2,0) -> CREW BREAD MILTIGRAIN | H58: 1 | I58: 1.2 | J58: =IFERROR(IF(I58="std",H58,ROUND(HLOOKUP(A58,FlightConfig!$B$28:$G$29,2,0)*I58,0)),"") -> 2 | K58: =VLOOKUP(Food!E58,'[5]FG MASTER'!$A$1:$AC$521,16,0) -> 0.26625 | L58: =VLOOKUP(Food!E58,'FG MASTER'!A:AJ,17,0) -> 0.2 | M58: =IFERROR(L58*$M$2,"") -> 0.08 | N58: =IFERROR((K58)+M58,"") -> 0.34625 | O58: =IFERROR($K58*(1+$O$2)-$K58+R58,0) -> 0.0346125 | P58: =IFERROR($M58*(1+$P$2)-$M58,0) -> 0.0104 | Q58: =SUM(N58:P58) -> 0.3912625 | T58: =L58*J58 -> 0.4 | V58: =IFERROR(K58*J58-R58*J58,"") -> 0.5325 | W58: =IFERROR(+L58*J58,"") -> 0.4 | X58: =IFERROR(+M58*J58,"") -> 0.16 | Y58: =IFERROR(+N58*J58+R58*J58,"") -> 0.6925 | Z58: =IFERROR(O58*$J58,"") -> 0.069225 | AA58: =IFERROR(P58*$J58,"") -> 0.0208 | AB58: =IFERROR(+(Q58+R58)*J58,"") -> 0.782525 | AD58: =IFERROR(#REF!*FlightConfig!$K$3,"") | AE58: =IFERROR(V58*FlightConfig!$K$3,"") -> 193.83 | AF58: =IFERROR(W58*FlightConfig!$K$3,"") -> 145.6 | AG58: =IFERROR(X58*FlightConfig!$K$3,"") -> 58.24 | AH58: =IFERROR(Y58*FlightConfig!$K$3,"") -> 252.07 | AI58: =IFERROR(AB58*FlightConfig!$K$3,"") -> 284.8391
A59: TECH CREW CLASS | B59: 2 | C59: =CONCATENATE(A59&B59&F59) -> TECH CREW CLASS2 | E59: 10080 | G59: =VLOOKUP(E59,'[5]FG MASTER'!$A$10:$AB$203,2,0) -> DECK CREW P HM SALAD CHOPPED ROMAIN LETTUCE, CUCUMBER SLICE, CARROT JULIENCE | H59: 1 | I59: 1 | J59: =IFERROR(IF(I59="std",H59,ROUND(HLOOKUP(A59,FlightConfig!$B$28:$G$29,2,0)*I59,0)),"") -> 2 | K59: =VLOOKUP(Food!E59,'[5]FG MASTER'!$A$1:$AC$521,16,0) -> 0.30885 | L59: =VLOOKUP(Food!E59,'FG MASTER'!A:AJ,17,0) -> 1.05 | M59: =IFERROR(L59*$M$2,"") -> 0.42 | N59: =IFERROR((K59)+M59,"") -> 0.72885 | O59: =IFERROR($K59*(1+$O$2)-$K59+R59,0) -> 0.0401505 | P59: =IFERROR($M59*(1+$P$2)-$M59,0) -> 0.0546 | Q59: =SUM(N59:P59) -> 0.8236005 | T59: =L59*J59 -> 2.1 | V59: =IFERROR(K59*J59-R59*J59,"") -> 0.6177 | W59: =IFERROR(+L59*J59,"") -> 2.1 | X59: =IFERROR(+M59*J59,"") -> 0.84 | Y59: =IFERROR(+N59*J59+R59*J59,"") -> 1.4577 | Z59: =IFERROR(O59*$J59,"") -> 0.080301 | AA59: =IFERROR(P59*$J59,"") -> 0.1092 | AB59: =IFERROR(+(Q59+R59)*J59,"") -> 1.647201 | AD59: =IFERROR(#REF!*FlightConfig!$K$3,"") | AE59: =IFERROR(V59*FlightConfig!$K$3,"") -> 224.8428 | AF59: =IFERROR(W59*FlightConfig!$K$3,"") -> 764.4 | AG59: =IFERROR(X59*FlightConfig!$K$3,"") -> 305.76 | AH59: =IFERROR(Y59*FlightConfig!$K$3,"") -> 530.6028 | AI59: =IFERROR(AB59*FlightConfig!$K$3,"") -> 599.58116
A60: TECH CREW CLASS | B60: 2 | C60: =CONCATENATE(A60&B60&F60) -> TECH CREW CLASS2 | E60: 10015 | G60: =VLOOKUP(E60,'[5]FG MASTER'!$A$10:$AB$203,2,0) -> BC C2 HM C POULTRY LEMON CHICKEN LEG CONFIT, WILD MUSHROOM CONSERVA, MASH POTATOES, BABY CARROT | H60: 1 | I60: 0.5 | J60: =IFERROR(IF(I60="std",H60,ROUND(HLOOKUP(A60,FlightConfig!$B$28:$G$29,2,0)*I60,0)),"") -> 1 | K60: =VLOOKUP(Food!E60,'[5]FG MASTER'!$A$1:$AC$521,16,0) -> 4.3527434 | L60: =VLOOKUP(Food!E60,'FG MASTER'!A:AJ,17,0) -> 6.5 | M60: =IFERROR(L60*$M$2,"") -> 2.6 | N60: =IFERROR((K60)+M60,"") -> 6.9527434 | O60: =IFERROR($K60*(1+$O$2)-$K60+R60,0) -> 0.56585664 | P60: =IFERROR($M60*(1+$P$2)-$M60,0) -> 0.338 | Q60: =SUM(N60:P60) -> 7.8566 | T60: =(L60/2)*J60 -> 3.25 | V60: =IFERROR(K60*J60-R60*J60,"") -> 4.3527434 | W60: =L60*J60 -> 6.5 | X60: =+M60*J60 -> 2.6 | Y60: =IFERROR(+N60*J60+R60*J60,"") -> 6.9527434 | Z60: =IFERROR(O60*$J60,"") -> 0.56585664 | AA60: =IFERROR(P60*$J60,"") -> 0.338 | AB60: =IFERROR(+(Q60+R60)*J60,"") -> 7.8566 | AD60: =IFERROR(#REF!*FlightConfig!$K$3,"") | AE60: =IFERROR(V60*FlightConfig!$K$3,"") -> 1584.3986 | AF60: =IFERROR(W60*FlightConfig!$K$3,"") -> 2366 | AG60: =IFERROR(X60*FlightConfig!$K$3,"") -> 946.4 | AH60: =IFERROR(Y60*FlightConfig!$K$3,"") -> 2530.7986 | AI60: =IFERROR(AB60*FlightConfig!$K$3,"") -> 2859.8024
A61: TECH CREW CLASS | B61: 2 | C61: =CONCATENATE(A61&B61&F61) -> TECH CREW CLASS2 | E61: 10013 | G61: =VLOOKUP(E61,'[5]FG MASTER'!$A$10:$AB$203,2,0) -> BC C2 HM A MEAT GRILLED BEEF TENDERLOIN, SMOKED TOMATO JAM, FINGERLING POTATOES, ASPARAGUS | H61: 1 | I61: 1 | J61: =IFERROR(IF(I61="std",H61,ROUND(HLOOKUP(A61,FlightConfig!$B$28:$G$29,2,0)*I61,0)),"") -> 2 | K61: =VLOOKUP(Food!E61,'[5]FG MASTER'!$A$1:$AC$521,16,0) -> 8.7456735 | L61: =VLOOKUP(Food!E61,'FG MASTER'!A:AJ,17,0) -> 8 | M61: =IFERROR(L61*$M$2,"") -> 3.2 | N61: =IFERROR((K61)+M61,"") -> 11.945673 | O61: =IFERROR($K61*(1+$O$2)-$K61+R61,0) -> 1.1369376 | P61: =IFERROR($M61*(1+$P$2)-$M61,0) -> 0.416 | Q61: =SUM(N61:P61) -> 13.498611 | T61: =(L61/2)*J61 -> 8 | V61: =IFERROR(K61*J61-R61*J61,"") -> 17.491347 | W61: =IFERROR(+L61*J61,"") -> 16 | X61: =IFERROR(+M61*J61,"") -> 6.4 | Y61: =IFERROR(+N61*J61+R61*J61,"") -> 23.891347 | Z61: =IFERROR(O61*$J61,"") -> 2.2738751 | AA61: =IFERROR(P61*$J61,"") -> 0.832 | AB61: =IFERROR(+(Q61+R61)*J61,"") -> 26.997222 | AD61: =IFERROR(#REF!*FlightConfig!$K$3,"") | AE61: =IFERROR(V61*FlightConfig!$K$3,"") -> 6366.8503 | AF61: =IFERROR(W61*FlightConfig!$K$3,"") -> 5824 | AG61: =IFERROR(X61*FlightConfig!$K$3,"") -> 2329.6 | AH61: =IFERROR(Y61*FlightConfig!$K$3,"") -> 8696.4503 | AI61: =IFERROR(AB61*FlightConfig!$K$3,"") -> 9826.9888
A62: TECH CREW CLASS | B62: 2 | C62: =CONCATENATE(A62&B62&F62) -> TECH CREW CLASS2 | E62: 10073 | G62: =VLOOKUP(E62,'[5]FG MASTER'!$A$10:$AB$203,2,0) -> CREW CUTLERY DISPOSAL | H62: 1 | I62: 1 | J62: =IFERROR(IF(I62="std",H62,ROUND(HLOOKUP(A62,FlightConfig!$B$28:$G$29,2,0)*I62,0)),"") -> 2 | K62: =VLOOKUP(Food!E62,'[5]FG MASTER'!$A$1:$AC$521,16,0) -> 0.1065 | L62: =VLOOKUP(Food!E62,'FG MASTER'!A:AJ,17,0) -> 0.2 | M62: =IFERROR(L62*$M$2,"") -> 0.08 | N62: =IFERROR((K62)+M62,"") -> 0.1865 | O62: =IFERROR($K62*(1+$O$2)-$K62+R62,0) -> 0.013845 | P62: =IFERROR($M62*(1+$P$2)-$M62,0) -> 0.0104 | Q62: =SUM(N62:P62) -> 0.210745 | T62: =L62*J62 -> 0.4 | V62: =IFERROR(K62*J62-R62*J62,"") -> 0.213 | W62: =IFERROR(+L62*J62,"") -> 0.4 | X62: =IFERROR(+M62*J62,"") -> 0.16 | Y62: =IFERROR(+N62*J62+R62*J62,"") -> 0.373 | Z62: =IFERROR(O62*$J62,"") -> 0.02769 | AA62: =IFERROR(P62*$J62,"") -> 0.0208 | AB62: =IFERROR(+(Q62+R62)*J62,"") -> 0.42149 | AD62: =IFERROR(#REF!*FlightConfig!$K$3,"") | AE62: =IFERROR(V62*FlightConfig!$K$3,"") -> 77.532 | AF62: =IFERROR(W62*FlightConfig!$K$3,"") -> 145.6 | AG62: =IFERROR(X62*FlightConfig!$K$3,"") -> 58.24 | AH62: =IFERROR(Y62*FlightConfig!$K$3,"") -> 135.772 | AI62: =IFERROR(AB62*FlightConfig!$K$3,"") -> 153.42236
A63: TECH CREW CLASS | B63: 2 | C63: =CONCATENATE(A63&B63&F63) -> TECH CREW CLASS2 | E63: 10082 | G63: =VLOOKUP(E63,'[5]FG MASTER'!$A$10:$AB$203,2,0) -> CREW YOGURT | H63: 1 | I63: 1 | J63: =IFERROR(IF(I63="std",H63,ROUND(HLOOKUP(A63,FlightConfig!$B$28:$G$29,2,0)*I63,0)),"") -> 2 | K63: =VLOOKUP(Food!E63,'[5]FG MASTER'!$A$1:$AC$521,16,0) -> 0.47925 | L63: =VLOOKUP(Food!E63,'FG MASTER'!A:AJ,17,0) -> 0.2 | M63: =IFERROR(L63*$M$2,"") -> 0.08 | N63: =IFERROR((K63)+M63,"") -> 0.55925 | O63: =IFERROR($K63*(1+$O$2)-$K63+R63,0) -> 0.0623025 | P63: =IFERROR($M63*(1+$P$2)-$M63,0) -> 0.0104 | Q63: =SUM(N63:P63) -> 0.6319525 | T63: =L63*J63 -> 0.4 | V63: =IFERROR(K63*J63-R63*J63,"") -> 0.9585 | W63: =IFERROR(+L63*J63,"") -> 0.4 | X63: =IFERROR(+M63*J63,"") -> 0.16 | Y63: =IFERROR(+N63*J63+R63*J63,"") -> 1.1185 | Z63: =IFERROR(O63*$J63,"") -> 0.124605 | AA63: =IFERROR(P63*$J63,"") -> 0.0208 | AB63: =IFERROR(+(Q63+R63)*J63,"") -> 1.263905 | AD63: =IFERROR(#REF!*FlightConfig!$K$3,"") | AE63: =IFERROR(V63*FlightConfig!$K$3,"") -> 348.894 | AF63: =IFERROR(W63*FlightConfig!$K$3,"") -> 145.6 | AG63: =IFERROR(X63*FlightConfig!$K$3,"") -> 58.24 | AH63: =IFERROR(Y63*FlightConfig!$K$3,"") -> 407.134 | AI63: =IFERROR(AB63*FlightConfig!$K$3,"") -> 460.06142
A64: TECH CREW CLASS | B64: 2 | C64: =CONCATENATE(A64&B64&F64) -> TECH CREW CLASS2 | E64: 10083 | G64: =VLOOKUP(E64,'[5]FG MASTER'!$A$10:$AB$203,2,0) -> CREW CHEESE | H64: 1 | I64: 1 | J64: =IFERROR(IF(I64="std",H64,ROUND(HLOOKUP(A64,FlightConfig!$B$28:$G$29,2,0)*I64,0)),"") -> 2 | K64: =VLOOKUP(Food!E64,'[5]FG MASTER'!$A$1:$AC$521,16,0) -> 0.3195 | L64: =VLOOKUP(Food!E64,'FG MASTER'!A:AJ,17,0) -> 0.2 | M64: =IFERROR(L64*$M$2,"") -> 0.08 | N64: =IFERROR((K64)+M64,"") -> 0.3995 | O64: =IFERROR($K64*(1+$O$2)-$K64+R64,0) -> 0.041535 | P64: =IFERROR($M64*(1+$P$2)-$M64,0) -> 0.0104 | Q64: =SUM(N64:P64) -> 0.451435 | T64: =L64*J64 -> 0.4 | V64: =IFERROR(K64*J64-R64*J64,"") -> 0.639 | W64: =IFERROR(+L64*J64,"") -> 0.4 | X64: =IFERROR(+M64*J64,"") -> 0.16 | Y64: =IFERROR(+N64*J64+R64*J64,"") -> 0.799 | Z64: =IFERROR(O64*$J64,"") -> 0.08307 | AA64: =IFERROR(P64*$J64,"") -> 0.0208 | AB64: =IFERROR(+(Q64+R64)*J64,"") -> 0.90287 | AD64: =IFERROR(#REF!*FlightConfig!$K$3,"") | AE64: =IFERROR(V64*FlightConfig!$K$3,"") -> 232.596 | AF64: =IFERROR(W64*FlightConfig!$K$3,"") -> 145.6 | AG64: =IFERROR(X64*FlightConfig!$K$3,"") -> 58.24 | AH64: =IFERROR(Y64*FlightConfig!$K$3,"") -> 290.836 | AI64: =IFERROR(AB64*FlightConfig!$K$3,"") -> 328.64468
A65: TECH CREW CLASS | B65: 2 | C65: =CONCATENATE(A65&B65&F65) -> TECH CREW CLASS2 | E65: 10074 | G65: =VLOOKUP(E65,'[5]FG MASTER'!$A$10:$AB$203,2,0) -> CREW BREAD MILTIGRAIN | H65: 1 | I65: 1 | J65: =IFERROR(IF(I65="std",H65,ROUND(HLOOKUP(A65,FlightConfig!$B$28:$G$29,2,0)*I65,0)),"") -> 2 | K65: =VLOOKUP(Food!E65,'[5]FG MASTER'!$A$1:$AC$521,16,0) -> 0.26625 | L65: =VLOOKUP(Food!E65,'FG MASTER'!A:AJ,17,0) -> 0.2 | M65: =IFERROR(L65*$M$2,"") -> 0.08 | N65: =IFERROR((K65)+M65,"") -> 0.34625 | O65: =IFERROR($K65*(1+$O$2)-$K65+R65,0) -> 0.0346125 | P65: =IFERROR($M65*(1+$P$2)-$M65,0) -> 0.0104 | Q65: =SUM(N65:P65) -> 0.3912625 | T65: =L65*J65 -> 0.4 | V65: =IFERROR(K65*J65-R65*J65,"") -> 0.5325 | W65: =IFERROR(+L65*J65,"") -> 0.4 | X65: =IFERROR(+M65*J65,"") -> 0.16 | Y65: =IFERROR(+N65*J65+R65*J65,"") -> 0.6925 | Z65: =IFERROR(O65*$J65,"") -> 0.069225 | AA65: =IFERROR(P65*$J65,"") -> 0.0208 | AB65: =IFERROR(+(Q65+R65)*J65,"") -> 0.782525 | AD65: =IFERROR(#REF!*FlightConfig!$K$3,"") | AE65: =IFERROR(V65*FlightConfig!$K$3,"") -> 193.83 | AF65: =IFERROR(W65*FlightConfig!$K$3,"") -> 145.6 | AG65: =IFERROR(X65*FlightConfig!$K$3,"") -> 58.24 | AH65: =IFERROR(Y65*FlightConfig!$K$3,"") -> 252.07 | AI65: =IFERROR(AB65*FlightConfig!$K$3,"") -> 284.8391
A66: TECH CREW CLASS | B66: 2 | C66: =CONCATENATE(A66&B66&F66) -> TECH CREW CLASS2 | E66: 10072 | G66: =VLOOKUP(E66,'[5]FG MASTER'!$A$10:$AB$203,2,0) -> CREW BUTTER | H66: 1 | I66: 1 | J66: =IFERROR(IF(I66="std",H66,ROUND(HLOOKUP(A66,FlightConfig!$B$28:$G$29,2,0)*I66,0)),"") -> 2 | K66: =VLOOKUP(Food!E66,'[5]FG MASTER'!$A$1:$AC$521,16,0) -> 0.11715 | L66: =VLOOKUP(Food!E66,'FG MASTER'!A:AJ,17,0) -> 0.2 | M66: =IFERROR(L66*$M$2,"") -> 0.08 | N66: =IFERROR((K66)+M66,"") -> 0.19715 | O66: =IFERROR($K66*(1+$O$2)-$K66+R66,0) -> 0.0152295 | P66: =IFERROR($M66*(1+$P$2)-$M66,0) -> 0.0104 | Q66: =SUM(N66:P66) -> 0.2227795 | T66: =L66*J66 -> 0.4 | V66: =IFERROR(K66*J66-R66*J66,"") -> 0.2343 | W66: =IFERROR(+L66*J66,"") -> 0.4 | X66: =IFERROR(+M66*J66,"") -> 0.16 | Y66: =IFERROR(+N66*J66+R66*J66,"") -> 0.3943 | Z66: =IFERROR(O66*$J66,"") -> 0.030459 | AA66: =IFERROR(P66*$J66,"") -> 0.0208 | AB66: =IFERROR(+(Q66+R66)*J66,"") -> 0.445559 | AD66: =IFERROR(#REF!*FlightConfig!$K$3,"") | AE66: =IFERROR(V66*FlightConfig!$K$3,"") -> 85.2852 | AF66: =IFERROR(W66*FlightConfig!$K$3,"") -> 145.6 | AG66: =IFERROR(X66*FlightConfig!$K$3,"") -> 58.24 | AH66: =IFERROR(Y66*FlightConfig!$K$3,"") -> 143.5252 | AI66: =IFERROR(AB66*FlightConfig!$K$3,"") -> 162.18348
A67: TECH CREW CLASS | B67: 2 | C67: =CONCATENATE(A67&B67&F67) -> TECH CREW CLASS2 | E67: 10084 | G67: =VLOOKUP(E67,'[5]FG MASTER'!$A$10:$AB$203,2,0) -> DECK CREW P HB SCRAMBLE EGG, KALE, POTATOES, TURKEY SAUSAGE, HAM | H67: 1 | I67: 1 | J67: =IFERROR(IF(I67="std",H67,ROUND(HLOOKUP(A67,FlightConfig!$B$28:$G$29,2,0)*I67,0)),"") -> 2 | K67: =VLOOKUP(Food!E67,'[5]FG MASTER'!$A$1:$AC$521,16,0) -> 1.5648045 | L67: =VLOOKUP(Food!E67,'FG MASTER'!A:AJ,17,0) -> 4.5 | M67: =IFERROR(L67*$M$2,"") -> 1.8 | N67: =IFERROR((K67)+M67,"") -> 3.3648045 | O67: =IFERROR($K67*(1+$O$2)-$K67+R67,0) -> 0.20342458 | P67: =IFERROR($M67*(1+$P$2)-$M67,0) -> 0.234 | Q67: =SUM(N67:P67) -> 3.8022291 | T67: =(L67/2)*J67 -> 4.5 | V67: =IFERROR(K67*J67-R67*J67,"") -> 3.129609 | W67: =IFERROR(+L67*J67,"") -> 9 | X67: =IFERROR(+M67*J67,"") -> 3.6 | Y67: =IFERROR(+N67*J67+R67*J67,"") -> 6.729609 | Z67: =IFERROR(O67*$J67,"") -> 0.40684917 | AA67: =IFERROR(P67*$J67,"") -> 0.468 | AB67: =IFERROR(+(Q67+R67)*J67,"") -> 7.6044582 | AD67: =IFERROR(#REF!*FlightConfig!$K$3,"") | AE67: =IFERROR(V67*FlightConfig!$K$3,"") -> 1139.1777 | AF67: =IFERROR(W67*FlightConfig!$K$3,"") -> 3276 | AG67: =IFERROR(X67*FlightConfig!$K$3,"") -> 1310.4 | AH67: =IFERROR(Y67*FlightConfig!$K$3,"") -> 2449.5777 | AI67: =IFERROR(AB67*FlightConfig!$K$3,"") -> 2768.0228
A68: CABIN CREW CLASS | B68: 2 | C68: =CONCATENATE(A68&B68&F68) -> CABIN CREW CLASS2 | E68: 10075 | G68: =VLOOKUP(E68,'[5]FG MASTER'!$A$10:$AB$203,2,0) -> CABIN CREW CM A - HAM, MAYO, RED PEPPER STRIP, ROMAIN LETTUCE, CIABATTA BREADCUMBER, MESCLUN MIX, PEMPERNICKEL ROLL POTATO SALAD | H68: 1 | I68: 0.5 | J68: =IFERROR(IF(I68="std",H68,ROUND(HLOOKUP(A68,FlightConfig!$B$28:$G$29,2,0)*I68,0)),"") -> 4 | K68: =VLOOKUP(Food!E68,'[5]FG MASTER'!$A$1:$AC$521,16,0) -> 1.3373098 | L68: =VLOOKUP(Food!E68,'FG MASTER'!A:AJ,17,0) -> 2.75 | M68: =IFERROR(L68*$M$2,"") -> 1.1 | N68: =IFERROR((K68)+M68,"") -> 2.4373098 | O68: =IFERROR($K68*(1+$O$2)-$K68+R68,0) -> -0.38734669 | P68: =IFERROR($M68*(1+$P$2)-$M68,0) -> 0.143 | Q68: =SUM(N68:P68) -> 2.1929632 | R68: -0.56119697 | S68: =R68*J68 -> -2.2447879 | T68: =L68*J68 -> 11 | V68: =IFERROR(K68*J68-R68*J68,"") -> 7.5940273 | W68: =IFERROR(+L68*J68,"") -> 11 | X68: =IFERROR(+M68*J68,"") -> 4.4 | Y68: =IFERROR(+N68*J68+R68*J68,"") -> 7.5044515 | Z68: =IFERROR(O68*$J68,"") -> -1.5493868 | AA68: =IFERROR(P68*$J68,"") -> 0.572 | AB68: =IFERROR(+(Q68+R68)*J68,"") -> 6.5270647 | AD68: =IFERROR(#REF!*FlightConfig!$K$3,"") | AE68: =IFERROR(V68*FlightConfig!$K$3,"") -> 2764.2259 | AF68: =IFERROR(W68*FlightConfig!$K$3,"") -> 4004 | AG68: =IFERROR(X68*FlightConfig!$K$3,"") -> 1601.6 | AH68: =IFERROR(Y68*FlightConfig!$K$3,"") -> 2731.6203 | AI68: =IFERROR(AB68*FlightConfig!$K$3,"") -> 2375.8516
A69: CABIN CREW CLASS | B69: 2 | C69: =CONCATENATE(A69&B69&F69) -> CABIN CREW CLASS2 | E69: 10076 | G69: =VLOOKUP(E69,'[5]FG MASTER'!$A$10:$AB$203,2,0) -> CABIN CREW CM B - FRESH MOZZARELLA, PESTO MAYO, ROASTED TOMATO, BABY SPINACH, WHEAT TOLL, PASTA PESTO SALAD | H69: 1 | I69: 0.5 | J69: =IFERROR(IF(I69="std",H69,ROUND(HLOOKUP(A69,FlightConfig!$B$28:$G$29,2,0)*I69,0)),"") -> 4 | K69: =VLOOKUP(Food!E69,'[5]FG MASTER'!$A$1:$AC$521,16,0) -> 1.8118738 | L69: =VLOOKUP(Food!E69,'FG MASTER'!A:AJ,17,0) -> 2.75 | M69: =IFERROR(L69*$M$2,"") -> 1.1 | N69: =IFERROR((K69)+M69,"") -> 2.9118738 | O69: =IFERROR($K69*(1+$O$2)-$K69+R69,0) -> 0.2355436 | P69: =IFERROR($M69*(1+$P$2)-$M69,0) -> 0.143 | Q69: =SUM(N69:P69) -> 3.2904175 | T69: =L69*J69 -> 11 | V69: =IFERROR(K69*J69-R69*J69,"") -> 7.2474954 | W69: =L69*J69 -> 11 | X69: =+M69*J69 -> 4.4 | Y69: =IFERROR(+N69*J69+R69*J69,"") -> 11.647495 | Z69: =IFERROR(O69*$J69,"") -> 0.9421744 | AA69: =IFERROR(P69*$J69,"") -> 0.572 | AB69: =IFERROR(+(Q69+R69)*J69,"") -> 13.16167 | AD69: =IFERROR(#REF!*FlightConfig!$K$3,"") | AE69: =IFERROR(V69*FlightConfig!$K$3,"") -> 2638.0883 | AF69: =IFERROR(W69*FlightConfig!$K$3,"") -> 4004 | AG69: =IFERROR(X69*FlightConfig!$K$3,"") -> 1601.6 | AH69: =IFERROR(Y69*FlightConfig!$K$3,"") -> 4239.6883 | AI69: =IFERROR(AB69*FlightConfig!$K$3,"") -> 4790.8478
A70: CABIN CREW CLASS | B70: 2 | C70: =CONCATENATE(A70&B70&F70) -> CABIN CREW CLASS2 | E70: 10079 | G70: =VLOOKUP(E70,'[5]FG MASTER'!$A$10:$AB$203,2,0) -> CREW VINAIGRETTE DRESSING | H70: 1 | I70: 1 | J70: =IFERROR(IF(I70="std",H70,ROUND(HLOOKUP(A70,FlightConfig!$B$28:$G$29,2,0)*I70,0)),"") -> 8 | K70: =VLOOKUP(Food!E70,'[5]FG MASTER'!$A$1:$AC$521,16,0) -> 0.1065 | L70: =VLOOKUP(Food!E70,'FG MASTER'!A:AJ,17,0) -> 0.2 | M70: =IFERROR(L70*$M$2,"") -> 0.08 | N70: =IFERROR((K70)+M70,"") -> 0.1865 | O70: =IFERROR($K70*(1+$O$2)-$K70+R70,0) -> 0.013845 | P70: =IFERROR($M70*(1+$P$2)-$M70,0) -> 0.0104 | Q70: =SUM(N70:P70) -> 0.210745 | T70: =L70*J70 -> 1.6 | V70: =IFERROR(K70*J70-R70*J70,"") -> 0.852 | W70: =L70*J70 -> 1.6 | X70: =+M70*J70 -> 0.64 | Y70: =IFERROR(+N70*J70+R70*J70,"") -> 1.492 | Z70: =IFERROR(O70*$J70,"") -> 0.11076 | AA70: =IFERROR(P70*$J70,"") -> 0.0832 | AB70: =IFERROR(+(Q70+R70)*J70,"") -> 1.68596 | AD70: =IFERROR(#REF!*FlightConfig!$K$3,"") | AE70: =IFERROR(V70*FlightConfig!$K$3,"") -> 310.128 | AF70: =IFERROR(W70*FlightConfig!$K$3,"") -> 582.4 | AG70: =IFERROR(X70*FlightConfig!$K$3,"") -> 232.96 | AH70: =IFERROR(Y70*FlightConfig!$K$3,"") -> 543.088 | AI70: =IFERROR(AB70*FlightConfig!$K$3,"") -> 613.68944
A71: CABIN CREW CLASS | B71: 2 | C71: =CONCATENATE(A71&B71&F71) -> CABIN CREW CLASS2 | E71: 10072 | G71: =VLOOKUP(E71,'[5]FG MASTER'!$A$10:$AB$203,2,0) -> CREW BUTTER | H71: 1 | I71: 1 | J71: =IFERROR(IF(I71="std",H71,ROUND(HLOOKUP(A71,FlightConfig!$B$28:$G$29,2,0)*I71,0)),"") -> 8 | K71: =VLOOKUP(Food!E71,'[5]FG MASTER'!$A$1:$AC$521,16,0) -> 0.11715 | L71: =VLOOKUP(Food!E71,'FG MASTER'!A:AJ,17,0) -> 0.2 | M71: =IFERROR(L71*$M$2,"") -> 0.08 | N71: =IFERROR((K71)+M71,"") -> 0.19715 | O71: =IFERROR($K71*(1+$O$2)-$K71+R71,0) -> 0.0152295 | P71: =IFERROR($M71*(1+$P$2)-$M71,0) -> 0.0104 | Q71: =SUM(N71:P71) -> 0.2227795 | T71: =L71*J71 -> 1.6 | V71: =IFERROR(K71*J71-R71*J71,"") -> 0.9372 | W71: =IFERROR(+L71*J71,"") -> 1.6 | X71: =IFERROR(+M71*J71,"") -> 0.64 | Y71: =IFERROR(+N71*J71+R71*J71,"") -> 1.5772 | Z71: =IFERROR(O71*$J71,"") -> 0.121836 | AA71: =IFERROR(P71*$J71,"") -> 0.0832 | AB71: =IFERROR(+(Q71+R71)*J71,"") -> 1.782236 | AD71: =IFERROR(#REF!*FlightConfig!$K$3,"") | AE71: =IFERROR(V71*FlightConfig!$K$3,"") -> 341.1408 | AF71: =IFERROR(W71*FlightConfig!$K$3,"") -> 582.4 | AG71: =IFERROR(X71*FlightConfig!$K$3,"") -> 232.96 | AH71: =IFERROR(Y71*FlightConfig!$K$3,"") -> 574.1008 | AI71: =IFERROR(AB71*FlightConfig!$K$3,"") -> 648.7339
