Workbook
Name COMMERCIAL_ITEMS: #REF!
Name COMMERCIAL_ITEMS: #REF!

Sheet P&L
R2: 21 | S2: Flights Per Week
R3: ='Summary '!H4 -> 1092 | S3: Flights Per Year
R4: 0.85 | S4: Load
B5: Description | C5: Grand Total | E5: Virgin Atlantic | G5: Unit Central Cost | R5: 1 | S5: Cycle
C6: $ | D6: % | E6: $ | F6: % | G6: $ | H6: % | R6: 0 | S6: Discount
B7: Revenue Meals | C7: =SUM(E7,G7) -> 4538568.5 | D7: =C7/$C$12 -> 0.64006484 | E7: =SUM('Summary '!J11:J14) -> 4538568.5 | F7: =E7/$E$12 -> 0.64006484 | G7: 1e-05 | H7: =G7/$G$12 -> 1
B8: Revenue Handling | C8: =SUM(E8,G8) -> 1782366.4 | D8: =C8/$C$12 -> 0.25136341 | E8: =SUM('Summary '!J15:J16) -> 1782366.4 | F8: =E8/$E$12 -> 0.25136341 | H8: =G8/$G$12 -> 0 | R8: 0.15 | S8: Mark up on Food
B9: Revenue Overheads | C9: =SUM(E9,G9) -> 769860 | D9: =C9/$C$12 -> 0.10857175 | E9: =705*R3 -> 769860 | F9: =E9/$E$12 -> 0.10857175 | H9: =G9/$G$12 -> 0 | I9: $705 PER FLIGHT OVERHEAD CHARGE | R9: 0.15 | S9: Mark up on Food Labor
B10: Revenue Other | C10: =SUM(E10,G10) -> 0 | D10: =C10/$C$12 -> 0 | F10: =E10/$E$12 -> 0 | H10: =G10/$G$12 -> 0 | R10: 0.13 | S10: Mark up on Handling
B11: Discount | C11: =SUM(E11,G11) -> 0 | D11: =C11/$C$12 -> 0 | E11: =SUM(E7:E9)*R6 -> 0 | F11: =E11/$E$12 -> 0 | H11: =G11/$G$12 -> 0
B12: Net Revenue | C12: =SUM(C7:C11) -> 7090794.9 | D12: =C12/$C$12 -> 1 | E12: =SUM(E7:E11) -> 7090794.9 | F12: =E12/$E$12 -> 1 | G12: =SUM(G7:G11) -> 1e-05 | H12: =G12/$G$12 -> 1
B13: Food Cost | C13: =SUM(E13,G13) -> 2589705.4 | D13: =C13/$C$12 -> 0.36522074 | E13: ='Summary '!J11 -> 2589705.4 | F13: =E13/$E$12 -> 0.36522074 | H13: =G13/$G$12 -> 0 | R13: VA ATL TOTAL HANDLING
B14: Other product cost | C14: =SUM(E14,G14) -> 0 | D14: =C14/$C$12 -> 0 | E14: 0 | F14: =E14/$E$12 -> 0 | H14: =G14/$G$12 -> 0 | R14: =R20+R25+R30+R35 -> 1575.559 | S14: A330
B15: Total Direct Materials | C15: =SUM(C13:C14) -> 2589705.4 | D15: =C15/$C$12 -> 0.36522074 | E15: =SUM(E13:E14) -> 2589705.4 | F15: =E15/$E$12 -> 0.36522074 | G15: =SUM(G13:G14) -> 0 | H15: =G15/$G$12 -> 0 | R15: =R21+R26+R31+R36 -> 1932.8198 | S15: A350
B16: Direct Labor - Wages | C16: =SUM(E16,G16) -> 2347353.1 | D16: =C16/$C$12 -> 0.3310423 | E16: ='Summary '!L16 -> 2347353.1 | F16: =E16/$E$12 -> 0.3310423 | H16: =G16/$G$12 -> 0 | R16: =R22+R27+R32+R37 -> 1529.342 | S16: 787
B17: Direct Labor - OT Premium | C17: =SUM(E17,G17) -> 0 | D17: =C17/$C$12 -> 0 | E17: 0 | F17: =E17/$E$12 -> 0 | H17: =G17/$G$12 -> 0
B18: Direct Labor - Benefit Cost | C18: =SUM(E18,G18) -> 586838.26 | D18: =C18/$C$12 -> 0.082760575 | E18: ='Summary '!L17 -> 586838.26 | F18: =E18/$E$12 -> 0.082760575 | H18: =G18/$G$12 -> 0
B19: Direct Labor - Other | C19: =SUM(E19,G19) -> 0 | D19: =C19/$C$12 -> 0 | E19: 0 | F19: =E19/$E$12 -> 0 | H19: =G19/$G$12 -> 0 | R19: VA ATL TRANSPORT
B20: Direct Management Labor Cost | C20: =SUM(E20,G20) -> 0 | D20: =C20/$C$12 -> 0 | E20: 0 | F20: =E20/$E$12 -> 0 | H20: =G20/$G$12 -> 0 | R20: =Handling!V53 -> 313.236 | S20: A330 TURNAROUND
B21: Total Direct Labor | C21: =SUM(C16:C20) -> 2934191.3 | D21: =C21/$C$12 -> 0.41380288 | E21: =SUM(E16:E20) -> 2934191.3 | F21: =E21/$E$12 -> 0.41380288 | G21: =SUM(G16:G20) -> 0 | H21: =G21/$G$12 -> 0 | I21: =E21-E8 -> 1151824.9 | R21: =Handling!X53 -> 362.956 | S21: A350 TURNAROUND
B22: Gross Profit Margin (CM1) | C22: =C12-C15-C21 -> 1566898.2 | D22: =C22/$C$12 -> 0.22097638 | E22: =E12-E15-E21 -> 1566898.2 | F22: =E22/$E$12 -> 0.22097638 | G22: =G12-G15-G21 -> 1e-05 | H22: =G22/$G$12 -> 1 | R22: =Handling!Z53 -> 313.236 | S22: 787 TURNAROUND
K23: VA ATL Avg. Revenue Per Flight | O23: ='Summary '!H17+705 -> 6493.4019 | Q23: =4993+705 -> 5698
B24: Indirect Management Labor Cost | C24: =SUM(E24,G24) -> 500000 | D24: =C24/$C$12 -> 0.070513956 | E24: 500000 | F24: =E24/$C$12 -> 0.070513956 | H24: =G24/$G$12 -> 0 | K24: Avg. Price Per Pax | R24: VA ATL INTERNATIONAL GARBAGE
B25: Indirect Hourly Labor Cost | C25: =SUM(E25,G25) -> 0 | D25: =C25/$C$12 -> 0 | E25: 0 | F25: =E25/$C$12 -> 0 | H25: =G25/$G$12 -> 0 | K25: FC | L25: BC | M25: PY | N25: EY | O25: TC | P25: CY | R25: =Handling!AD39 -> 339 | S25: A330
B26: Total Indirect Labor | C26: =SUM(C24:C25) -> 500000 | D26: =C26/$C$12 -> 0.070513956 | E26: =SUM(E24:E25) -> 500000 | F26: =E26/$E$12 -> 0.070513956 | G26: =SUM(G24:G25) -> 0 | H26: =G26/$G$12 -> 0 | K26: ='Summary '!B24 -> 0 | L26: ='Summary '!C24 -> 34.40362 | M26: ='Summary '!D24 -> 23.803061 | N26: ='Summary '!E24 -> 12.417626 | O26: ='Summary '!F24 -> 0 | P26: ='Summary '!G24 -> 36.1169 | R26: =Handling!AD41 -> 395.5 | S26: A350
B27: Operating Expense-Variable | C27: =SUM(E27,G27) -> 84000 | D27: =C27/$C$12 -> 0.011846345 | E27: =7000*12 -> 84000 | F27: =E27/E12 -> 0.011846345 | H27: =G27/$G$12 -> 0 | I27: Utility | R27: =Handling!AD43 -> 339 | S27: 787
B28: Operating Expense-Fixed | C28: =SUM(E28,G28) -> 0 | D28: =C28/$C$12 -> 0 | F28: =E28/E12 -> 0 | H28: =G28/$G$12 -> 0 | I28: ??? Freezer and Cooler | K28: Overhead
B29: Other OPEX Cost | C29: =SUM(C27:C28) -> 84000 | D29: =C29/$C$12 -> 0.011846345 | E29: =SUM(E27:E28) -> 84000 | F29: =E29/E12 -> 0.011846345 | G29: =SUM(G27:G28) -> 0 | H29: =G29/$G$12 -> 0 | K29: FC | L29: BC | M29: PY | N29: YC | O29: TC | P29: CC | R29: VA ATL WASH UP
B30: EBITDA | C30: =C22-C26-C29 -> 982898.2 | D30: =C30/$C$12 -> 0.13861608 | E30: =E22-E26-E29 -> 982898.2 | F30: =E30/$E$12 -> 0.13861608 | G30: =G22-G26-G29 -> 1e-05 | H30: =G30/$G$12 -> 1 | I30: =E30/12 -> 81908.183 | K30: 0 | L30: 0 | M30: 0 | N30: 0 | O30: 0 | P30: 0 | R30: =Handling!C84 -> 704.103 | S30: A330
E31: =E30/(E9+'Summary '!J25) -> 0.15617035 | R31: =Handling!E84 -> 878.3038 | S31: A350
B32: Note - On the P&L we can update the Flights per week, AC type, Load Factor, Cycle & Mark up's | R32: =Handling!G84 -> 653.366 | S32: 787
E34: Overhead =(2/3)*(property tax+utility) | R34: VA ATL PACKING
R35: =Handling!S39+Handling!S45 -> 219.22 | S35: A330
B36: customer service account manager | R36: =Handling!S41+Handling!S47 -> 296.06 | S36: A350
B37: culinary operation duty manager | R37: =Handling!S43+Handling!S50 -> 223.74 | S37: 787
B38: hourly invoice assisant
B39: ramp duty manager
B67: CONTRACTORS | C67: 271755
B68: EXTERIOR SIGNAGE | C68: 2000
B69: MULTITEMP FREEZERS | C69: 164340
B70: DISHWASHER RETAL (YEARLY) | C70: 3840
B71: PERMITTING | C71: 19000
B72: RENT/LEASE (YEARLY) | C72: 261360
B73: TRUCK (2 TRUCKS) | C73: 675000
B74: EQUIPMENT AND UTILITY (5 YEARS) | C74: =116139*5 -> 580695

Sheet Bid Assumption 
A1: Bid Fact Sheet
A2: Airline Name | B2: NEOS
A3: City Code and Unit Number | B3: JFK
A4: Date Bid Preparation Begins
A5: Period used for Annualization
A6: Access Fee %
A7: Trade Discount %
A8: Cash Discount %
A9: Start Up Date
A12: Aircraft Type | B12: 787
A13: Configuration: First Class | B13: =+'FlightConfig '!B3 -> 0
A14: Business Class | B14: =+'FlightConfig '!C3 -> 34
A15: Tourist Class | B15: =SUM('FlightConfig '!D3:E3) -> 246
A16: ETA | B16: 0.26736111
A17: ETD | B17: 0.93402778
A18: Frequency (days of operations) | B18: =+'FlightConfig '!K2 -> 0
A19: Total No. of Flights per Year | B19: =+'FlightConfig '!K3 -> 0
A20: Load Factor %
A21: Source of Load Factor | B21: Flight Config
A22: Account Rep. | B22: Kathy Shi
A23: Reason For Bid | B23: New Unit | E23: Food Markup
A24: Incumbent | E24: Ancillary Markup
A25: New or Old Route | B25: New | E25: Service Markup
A26: Credit Established/Payment Status
A27: Was Account Previously Bid | E27: Overhead Recovery per Pax F/C
A28: Outcome | E28: Overhead Recovery per Pax B/C
A29: Is there a Global Agreement | E29: Overhead Recovery per Pax E/U
A30: Date Building Lease expires | E30: Overhead Recovery per Pax Y/C
E31: Overhead Recovery per Pax C/Y
E32: Overhead Recovery per Pax C/C
A33: Investment | B33: Amount | C33: No. Years | D33: $ per Year | E33: Overhead Recovery per Pax T/C
A34: Building | C34: 0 | D34: =+B34/C34 -> #DIV/0!
A35: Land | C35: N/A | D35: N/A
A36: Building - Leasehold Improvements | C36: 0 | D36: =+B36/C36 -> #DIV/0!
A37: Trucks - Highlifts | C37: 0 | D37: =+B37/C37 -> #DIV/0!
A38: Trucks - Vans/Utility Vehicles | C38: 0 | D38: =+B38/C38 -> #DIV/0!
A39: Equipment | C39: 0 | D39: =+B39/C39 -> #DIV/0!
A40: Rent of Property | C40: 0 | D40: =+B40/C40 -> #DIV/0!
A42: Other Cities that Dnata serves this Customer and Discounts applied:
A43: SFO
A47: Pricing Assumptions:
A48: Methodology: fc+lc+mu=sp
A49: Contract length:
A50: # of Trucks/price - ea:
A51: # of Vans/Utility Vehicles/price - ea:
A52: Equipment descriptions:

Sheet Summary 
A2: Customer | G2: Flights Per week | H2: ='P&L'!R2 -> 21 | L2: AC type | M2: Cycle
E3: AC Type | G3: Flights Per Month | H3: =H4/12 -> 91 | J3: Total Revenues | L3: 737 | M3: 1
E4: Load | F4: ='P&L'!R4 -> 0.85 | G4: Annual Flights | H4: =H2*52 -> 1092 | J4: =H17*H4 -> 6320934.9
A5: Summary
A6: BNA | B6: FC | C6: BC | D6: PY | E6: EY | F6: TC | G6: CY | H6: Total | I6: Hnd
A7: FLIGHT CONFIG | B7: =+'FlightConfig '!B17 -> 0 | C7: =('Summary FLT104'!C7+'Summary FLT110'!C7)/2 -> 32 | D7: =('Summary FLT104'!D7+'Summary FLT110'!D7)/2 -> 46 | E7: =('Summary FLT104'!E7+'Summary FLT110'!E7)/2 -> 191 | F7: =('Summary FLT104'!F7+'Summary FLT110'!F7)/2 -> 0 | G7: =('Summary FLT104'!G7+'Summary FLT110'!G7)/2 -> 6 | H7: =('Summary FLT104'!H7+'Summary FLT110'!H7)/2 -> 275
A8: Load Factor | B8: =ROUNDUP(B7*$F$4,0) -> 0 | C8: =ROUNDUP(C7*$F$4,0) -> 28 | D8: =ROUNDUP(D7*$F$4,0) -> 40 | E8: =ROUNDUP(E7*$F$4,0) -> 163 | F8: =ROUNDUP(F7*$F$4,0) -> 0 | G8: =ROUNDUP(G7*$F$4,0) -> 6 | H8: =SUM(B8:G8) -> 237
B9: FIRST CLASS | C9: BUSINESS CLASS | D9: PREMIUM ECONOMY CLASS | E9: ECONOMY CLASS | F9: TECH CREW CLASS | G9: cABIN CREW CLASS | H9: Per Flight | J9: Annual
A10: OVERHEAD | B10: =('Summary FLT104'!B10+'Summary FLT110'!B10)/2 -> 0 | C10: =('Summary FLT104'!C10+'Summary FLT110'!C10)/2 -> 0 | D10: =('Summary FLT104'!D10+'Summary FLT110'!D10)/2 -> 0 | E10: =('Summary FLT104'!E10+'Summary FLT110'!E10)/2 -> 0 | F10: =('Summary FLT104'!F10+'Summary FLT110'!F10)/2 -> 0 | G10: =('Summary FLT104'!G10+'Summary FLT110'!G10)/2 -> 0 | H10: =('Summary FLT104'!H10+'Summary FLT110'!H10)/2 -> 0 | J10: =H10*$H$4 -> 0
A11: Food Cost (DM) | B11: =('Summary FLT104'!B11+'Summary FLT110'!B11)/2 -> 0 | C11: =('Summary FLT104'!C11+'Summary FLT110'!C11)/2 -> 623.09296 | D11: =('Summary FLT104'!D11+'Summary FLT110'!D11)/2 -> 550.99257 | E11: =('Summary FLT104'!E11+'Summary FLT110'!E11)/2 -> 1065.1635 | F11: =('Summary FLT104'!F11+'Summary FLT110'!F11)/2 -> 0 | G11: =('Summary FLT104'!G11+'Summary FLT110'!G11)/2 -> 132.276 | H11: =('Summary FLT104'!H11+'Summary FLT110'!H11)/2 -> 2371.5251 | I11: =I12*45% -> 1626.3385 | J11: =H11*$H$4 -> 2589705.4
A12: Wage Cost (DL) | B12: =('Summary FLT104'!B12+'Summary FLT110'!B12)/2 -> 0 | C12: =('Summary FLT104'!C12+'Summary FLT110'!C12)/2 -> 214.56038 | D12: =('Summary FLT104'!D12+'Summary FLT110'!D12)/2 -> 276.94 | E12: =('Summary FLT104'!E12+'Summary FLT110'!E12)/2 -> 694.9 | F12: =('Summary FLT104'!F12+'Summary FLT110'!F12)/2 -> 0 | G12: =('Summary FLT104'!G12+'Summary FLT110'!G12)/2 -> 56.16 | H12: =('Summary FLT104'!H12+'Summary FLT110'!H12)/2 -> 1242.5604 | I12: =H11+H12 -> 3614.0855 | J12: =H12*$H$4 -> 1356875.9
A13: Food Mark up | B13: =('Summary FLT104'!B13+'Summary FLT110'!B13)/2 -> 0 | C13: =('Summary FLT104'!C13+'Summary FLT110'!C13)/2 -> 93.463945 | D13: =('Summary FLT104'!D13+'Summary FLT110'!D13)/2 -> 82.648885 | E13: =('Summary FLT104'!E13+'Summary FLT110'!E13)/2 -> 159.77453 | F13: =('Summary FLT104'!F13+'Summary FLT110'!F13)/2 -> 0 | G13: =('Summary FLT104'!G13+'Summary FLT110'!G13)/2 -> 19.8414 | H13: =('Summary FLT104'!H13+'Summary FLT110'!H13)/2 -> 355.72876 | J13: =H13*$H$4 -> 388455.81
A14: Labor Mark up | B14: =('Summary FLT104'!B14+'Summary FLT110'!B14)/2 -> 0 | C14: =('Summary FLT104'!C14+'Summary FLT110'!C14)/2 -> 32.184057 | D14: =('Summary FLT104'!D14+'Summary FLT110'!D14)/2 -> 41.541 | E14: =('Summary FLT104'!E14+'Summary FLT110'!E14)/2 -> 104.235 | F14: =('Summary FLT104'!F14+'Summary FLT110'!F14)/2 -> 0 | G14: =('Summary FLT104'!G14+'Summary FLT110'!G14)/2 -> 8.424 | H14: =('Summary FLT104'!H14+'Summary FLT110'!H14)/2 -> 186.38406 | J14: =H14*$H$4 -> 203531.39 | L14: Direct Labour
A15: Handling Cost | B15: =('Summary FLT104'!B15+'Summary FLT110'!B15)/2 -> 0 | C15: =('Summary FLT104'!C15+'Summary FLT110'!C15)/2 -> 0 | D15: =('Summary FLT104'!D15+'Summary FLT110'!D15)/2 -> 0 | E15: =('Summary FLT104'!E15+'Summary FLT110'!E15)/2 -> 1444.428 | F15: =('Summary FLT104'!F15+'Summary FLT110'!F15)/2 -> 0 | G15: =('Summary FLT104'!G15+'Summary FLT110'!G15)/2 -> 0 | H15: =('Summary FLT104'!H15+'Summary FLT110'!H15)/2 -> 1444.428 | J15: =H15*$H$4 -> 1577315.4 | L15: =J12+J15 -> 2934191.3 | M15: 1
A16: Handling Mark up | B16: =('Summary FLT104'!B16+'Summary FLT110'!B16)/2 -> 0 | C16: =('Summary FLT104'!C16+'Summary FLT110'!C16)/2 -> 0 | D16: =('Summary FLT104'!D16+'Summary FLT110'!D16)/2 -> 0 | E16: =('Summary FLT104'!E16+'Summary FLT110'!E16)/2 -> 187.77564 | F16: =('Summary FLT104'!F16+'Summary FLT110'!F16)/2 -> 0 | G16: =('Summary FLT104'!G16+'Summary FLT110'!G16)/2 -> 0 | H16: =('Summary FLT104'!H16+'Summary FLT110'!H16)/2 -> 187.77564 | J16: =H16*$H$4 -> 205051 | L16: =L15*M16 -> 2347353.1 | M16: 0.8
A17: Total Per Flight | B17: =SUM(B11:B16) -> 0 | C17: =SUM(C11:C16) -> 963.30135 | D17: =SUM(D10:D16) -> 952.12245 | E17: =SUM(E10:E16) -> 3656.2767 | F17: =SUM(F10:F16) -> 0 | G17: =SUM(G10:G16) -> 216.7014 | H17: =SUM(H10:H16) -> 5788.4019 | J17: =H17*$H$4 -> 6320934.9 | L17: =L15*M17 -> 586838.26 | M17: 0.2
B18: =B17 -> 0 | C18: =C17 -> 963.30135 | D18: =D17 -> 952.12245 | E18: =E17-E15-E16 -> 2024.0731 | F18: =F17 -> 0 | G18: =G17 -> 216.7014 | I18: =E15+E16 -> 1632.2036
A19: Handling | B19: Cost | C19: Mark Up | D19: Price | I19: =E16 -> 187.77564 | J19: =H11+H12+H15 -> 5058.5135
A20: 737 Handling | D20: =Handling!C84+Handling!S39+Handling!S45+Handling!V53+Handling!AD39 -> 1575.559 | J20: =H13+H14+H16 -> 729.88846
A21: B777 Handling | B21: =Handling!#REF! -> #REF! | C21: =Handling!#REF! -> #REF! | D21: =Handling!#REF! -> #REF!
A22: A380 Handling | B22: =Handling!#REF! -> #REF! | C22: =Handling!#REF! -> #REF! | D22: =Handling!#REF! -> #REF!
A24: Avg Price Per Pax | B24: =IFERROR(((B11+B12+B13+B14)/B8),0) -> 0 | C24: =IFERROR(((C11+C12+C13+C14)/C8),0) -> 34.40362 | D24: =IFERROR(((D10+D11+D12+D13+D14)/D8),0) -> 23.803061 | E24: =IFERROR(((E10+E11+E12+E13+E14)/E8),0) -> 12.417626 | F24: =IFERROR(((F10+F11+F12+F13+F14)/F8),0) -> 0 | G24: =IFERROR(((G10+G11+G12+G13+G14)/G8),0) -> 36.1169
A25: Avg Mark up Per Pax | B25: =IFERROR(((B13+B14)/B8),0) -> 0 | C25: =IFERROR(((C13+C14)/C8),0) -> 4.4874286 | D25: =IFERROR(((D13+D14)/D8),0) -> 3.1047471 | E25: =IFERROR(((E13+E14)/E8),0) -> 1.6196904 | F25: =IFERROR(((F13+F14)/F8),0) -> 0 | G25: =IFERROR(((G13+G14)/G8),0) -> 4.7109 | J25: =J11+J12+J15 -> 5523896.7
A26: Over head Per Pax | B26: =IFERROR((B10/B8),0) -> 0 | C26: =IFERROR((C10/C8),0) -> 0 | D26: =IFERROR((D10/D8),0) -> 0 | E26: =IFERROR((E10/E8),0) -> 0 | F26: =IFERROR((F10/F8),0) -> 0 | G26: =IFERROR((G10/G8),0) -> 0 | J26: =J13+J14+J16 -> 797038.2
B28: CYCLE | C28: FLT
A29: Config | B29: ='P&L'!R5 -> 1
A30: OVERHEAD | B30: =B37*B8 -> 0 | C30: =C37*C8 -> 0 | D30: =D37*D8 -> 0 | E30: =E37*E8 -> 0 | F30: =F37*F8 -> 0 | G30: =G37*G8 -> 0
A31: Food Cost (DM) | B31: =('Summary FLT104'!B31+'Summary FLT110'!B31)/2 -> 0 | C31: =('Summary FLT104'!C31+'Summary FLT110'!C31)/2 -> 725.94515 | D31: =('Summary FLT104'!D31+'Summary FLT110'!D31)/2 -> 641.86215 | E31: =('Summary FLT104'!E31+'Summary FLT110'!E31)/2 -> 1248.0784 | F31: =('Summary FLT104'!F31+'Summary FLT110'!F31)/2 -> 0 | G31: =('Summary FLT104'!G31+'Summary FLT110'!G31)/2 -> 132.276
A32: Wage Cost (DL) | B32: =('Summary FLT104'!B32+'Summary FLT110'!B32)/2 -> 0 | C32: =('Summary FLT104'!C32+'Summary FLT110'!C32)/2 -> 249.77 | D32: =('Summary FLT104'!D32+'Summary FLT110'!D32)/2 -> 322.72 | E32: =('Summary FLT104'!E32+'Summary FLT110'!E32)/2 -> 814.25 | F32: =('Summary FLT104'!F32+'Summary FLT110'!F32)/2 -> 0 | G32: =('Summary FLT104'!G32+'Summary FLT110'!G32)/2 -> 56.16
A33: Markup Food | B33: =('Summary FLT104'!B33+'Summary FLT110'!B33)/2 -> 0 | C33: =('Summary FLT104'!C33+'Summary FLT110'!C33)/2 -> 108.89177 | D33: =('Summary FLT104'!D33+'Summary FLT110'!D33)/2 -> 96.279322 | E33: =('Summary FLT104'!E33+'Summary FLT110'!E33)/2 -> 187.21177 | F33: =('Summary FLT104'!F33+'Summary FLT110'!F33)/2 -> 0 | G33: =('Summary FLT104'!G33+'Summary FLT110'!G33)/2 -> 19.8414
A34: Markup Labor | B34: =('Summary FLT104'!B34+'Summary FLT110'!B34)/2 -> 0 | C34: =('Summary FLT104'!C34+'Summary FLT110'!C34)/2 -> 37.4655 | D34: =('Summary FLT104'!D34+'Summary FLT110'!D34)/2 -> 48.408 | E34: =('Summary FLT104'!E34+'Summary FLT110'!E34)/2 -> 122.1375 | F34: =('Summary FLT104'!F34+'Summary FLT110'!F34)/2 -> 0 | G34: =('Summary FLT104'!G34+'Summary FLT110'!G34)/2 -> 8.424
A36: Per Pax Avg
A37: OVERHEAD | B37: ='P&L'!$K$30 -> 0 | C37: ='P&L'!$L$30 -> 0 | D37: ='P&L'!$M$30 -> 0 | E37: ='P&L'!$N$30 -> 0 | F37: ='P&L'!$O$30 -> 0 | G37: ='P&L'!$P$30 -> 0
A38: Food Cost (DM) | B38: =IFERROR(B31/B7," ") | C38: =IFERROR(C31/C7," ") -> 22.685786 | D38: =IFERROR(D31/D7," ") -> 13.953525 | E38: =IFERROR(E31/E7," ") -> 6.5344421 | F38: =IFERROR(F31/F7," ") | G38: =IFERROR(G31/G7," ") -> 22.046
A39: Wage Cost (DL) | B39: =IFERROR(B32/B7," ") | C39: =IFERROR(C32/C7," ") -> 7.8053125 | D39: =IFERROR(D32/D7," ") -> 7.0156522 | E39: =IFERROR(E32/E7," ") -> 4.263089 | F39: =IFERROR(F32/F7," ") | G39: =IFERROR(G32/G7," ") -> 9.36
A40: Markup Food | B40: =IFERROR(B33/B8," ") | C40: =IFERROR(C33/C7," ") -> 3.4028679 | D40: =IFERROR(D33/D7," ") -> 2.0930287 | E40: =IFERROR(E33/E7," ") -> 0.98016632 | F40: =IFERROR(F33/F7," ") | G40: =IFERROR(G33/G7," ") -> 3.3069
A41: Markup Labor | B41: =IFERROR(B34/B7," ") | C41: =IFERROR(C34/C7," ") -> 1.1707969 | D41: =IFERROR(D34/D7," ") -> 1.0523478 | E41: =IFERROR(E34/E7," ") -> 0.63946335 | F41: =IFERROR(F34/F7," ") | G41: =IFERROR(G34/G7," ") -> 1.404
A108: 388
A109: 787

Sheet Summary Short Haul
A2: Customer | G2: Flights Per week | H2: ='Summary 735'!H2+'Summary 2221'!H2+'Summary 2439'!H2+'Summary 2682'!H2+'Summary 2855'!H2 -> 0 | L2: AC type | M2: Cycle
E3: AC Type | F3: 737 | G3: Flights Per Month | H3: =H4/12 -> 0 | J3: Total Revenues | L3: 737 | M3: 1
E4: Load | F4: ='P&L'!R4 -> 0.85 | G4: Annual Flights | H4: =H2*52 -> 0 | J4: =H17*H4 -> #REF!
A5: Summary
A6: BNA | B6: FC | C6: BC | D6: PY | E6: EY | F6: TC | G6: CY | H6: Total | I6: Hnd
A7: FLIGHT CONFIG | B7: =+'FlightConfig '!B17 -> 0 | C7: =+'FlightConfig '!C17 -> 34 | D7: =+'FlightConfig '!D17 -> 48 | E7: =+'FlightConfig '!E17 -> 198 | F7: =+'FlightConfig '!F17 -> 0 | G7: =+'FlightConfig '!G17 -> 6 | H7: =SUM(B7:G7) -> 286
A8: Load Factor | B8: =ROUNDUP(B7*$F$4,0) -> 0 | C8: =ROUNDUP(C7*$F$4,0) -> 29 | D8: =ROUNDUP(D7*$F$4,0) -> 41 | E8: =ROUNDUP(E7*$F$4,0) -> 169 | F8: =ROUNDUP(F7*$F$4,0) -> 0 | G8: =ROUNDUP(G7*$F$4,0) -> 6 | H8: =SUM(B8:G8) -> 245
B9: FIRST CLASS | C9: BUSINESS CLASS | D9: PREMIUM ECONOMY CLASS | E9: ECONOMY CLASS | F9: TECH CREW CLASS | G9: cABIN CREW CLASS | H9: Per Flight | J9: Annual
A10: OVERHEAD | B10: =B37*B8 -> 0 | C10: =('Summary 735'!C10+'Summary 2221'!C10+'Summary 2439'!C10+'Summary 2682'!C10+'Summary 2855'!C10+#REF!+'Summary FLT104'!C10+'Summary FLT110'!C10+#REF!+#REF!+#REF!+'Summary 2037'!C10+'Summary 2817'!C10)/13 -> #REF! | D10: =('Summary 735'!D10+'Summary 2221'!D10+'Summary 2439'!D10+'Summary 2682'!D10+'Summary 2855'!D10+#REF!+'Summary FLT104'!D10+'Summary FLT110'!D10+#REF!+#REF!+#REF!+'Summary 2037'!D10+'Summary 2817'!D10)/13 -> #REF! | E10: =('Summary 735'!E10+'Summary 2221'!E10+'Summary 2439'!E10+'Summary 2682'!E10+'Summary 2855'!E10+#REF!+'Summary FLT104'!E10+'Summary FLT110'!E10+#REF!+#REF!+#REF!+'Summary 2037'!E10+'Summary 2817'!E10)/13 -> #REF! | F10: =('Summary 735'!F10+'Summary 2221'!F10+'Summary 2439'!F10+'Summary 2682'!F10+'Summary 2855'!F10+#REF!+'Summary FLT104'!F10+'Summary FLT110'!F10+#REF!+#REF!+#REF!+'Summary 2037'!F10+'Summary 2817'!F10)/13 -> #REF! | G10: =('Summary 735'!G10+'Summary 2221'!G10+'Summary 2439'!G10+'Summary 2682'!G10+'Summary 2855'!G10+#REF!+'Summary FLT104'!G10+'Summary FLT110'!G10+#REF!+#REF!+#REF!+'Summary 2037'!G10+'Summary 2817'!G10)/13 -> #REF! | H10: =SUM(B10:G10) -> #REF! | J10: =H10*$H$4 -> #REF!
A11: Food Cost (DM) | B11: =('Summary 735'!B11+'Summary 2221'!B11+'Summary 2439'!B11+'Summary 2682'!B11+'Summary 2855'!B11)/5 -> 0 | C11: =('Summary 735'!C11+'Summary 2221'!C11+'Summary 2439'!C11+'Summary 2682'!C11+'Summary 2855'!C11)/5 -> 0 | D11: =('Summary 735'!D11+'Summary 2221'!D11+'Summary 2439'!D11+'Summary 2682'!D11+'Summary 2855'!D11)/5 -> 0 | E11: =('Summary 735'!E11+'Summary 2221'!E11+'Summary 2439'!E11+'Summary 2682'!E11+'Summary 2855'!E11)/5 -> 0 | F11: =('Summary 735'!F11+'Summary 2221'!F11+'Summary 2439'!F11+'Summary 2682'!F11+'Summary 2855'!F11)/5 -> 0 | G11: =('Summary 735'!G11+'Summary 2221'!G11+'Summary 2439'!G11+'Summary 2682'!G11+'Summary 2855'!G11)/5 -> 0 | H11: =SUM(B11:G11) -> 0 | I11: =I12*45% -> #REF! | J11: =H11*$H$4 -> 0
A12: Wage Cost (DL) | B12: =('Summary 735'!B12+'Summary 2221'!B12+'Summary 2439'!B12+'Summary 2682'!B12+'Summary 2855'!B12+#REF!+'Summary FLT104'!B12+'Summary FLT110'!B12+#REF!+#REF!+#REF!+'Summary 2037'!B12+'Summary 2817'!B12)/13 -> #REF! | C12: =('Summary 735'!C12+'Summary 2221'!C12+'Summary 2439'!C12+'Summary 2682'!C12+'Summary 2855'!C12)/5 -> 0 | D12: =('Summary 735'!D12+'Summary 2221'!D12+'Summary 2439'!D12+'Summary 2682'!D12+'Summary 2855'!D12)/5 -> 0 | E12: =('Summary 735'!E12+'Summary 2221'!E12+'Summary 2439'!E12+'Summary 2682'!E12+'Summary 2855'!E12)/5 -> 0 | F12: =('Summary 735'!F12+'Summary 2221'!F12+'Summary 2439'!F12+'Summary 2682'!F12+'Summary 2855'!F12)/5 -> 0 | G12: =('Summary 735'!G12+'Summary 2221'!G12+'Summary 2439'!G12+'Summary 2682'!G12+'Summary 2855'!G12)/5 -> 0 | H12: =SUM(B12:G12) -> #REF! | I12: =H11+H12 -> #REF! | J12: =H12*$H$4 -> #REF!
A13: Food Mark up | B13: =('Summary 735'!B13+'Summary 2221'!B13+'Summary 2439'!B13+'Summary 2682'!B13+'Summary 2855'!B13+#REF!+'Summary FLT104'!B13+'Summary FLT110'!B13+#REF!+#REF!+#REF!+'Summary 2037'!B13+'Summary 2817'!B13)/13 -> #VALUE! | C13: =('Summary 735'!C13+'Summary 2221'!C13+'Summary 2439'!C13+'Summary 2682'!C13+'Summary 2855'!C13)/5 -> 0 | D13: =('Summary 735'!D13+'Summary 2221'!D13+'Summary 2439'!D13+'Summary 2682'!D13+'Summary 2855'!D13)/5 -> 0 | E13: =('Summary 735'!E13+'Summary 2221'!E13+'Summary 2439'!E13+'Summary 2682'!E13+'Summary 2855'!E13)/5 -> 0 | F13: =('Summary 735'!F13+'Summary 2221'!F13+'Summary 2439'!F13+'Summary 2682'!F13+'Summary 2855'!F13)/5 -> 0 | G13: =('Summary 735'!G13+'Summary 2221'!G13+'Summary 2439'!G13+'Summary 2682'!G13+'Summary 2855'!G13)/5 -> 0 | H13: =SUM(B13:G13) -> #VALUE! | J13: =H13*$H$4 -> #VALUE!
A14: Labor Mark up | B14: =('Summary 735'!B14+'Summary 2221'!B14+'Summary 2439'!B14+'Summary 2682'!B14+'Summary 2855'!B14+#REF!+'Summary FLT104'!B14+'Summary FLT110'!B14+#REF!+#REF!+#REF!+'Summary 2037'!B14+'Summary 2817'!B14)/13 -> #VALUE! | C14: =('Summary 735'!C14+'Summary 2221'!C14+'Summary 2439'!C14+'Summary 2682'!C14+'Summary 2855'!C14)/5 -> 0 | D14: =('Summary 735'!D14+'Summary 2221'!D14+'Summary 2439'!D14+'Summary 2682'!D14+'Summary 2855'!D14)/5 -> 0 | E14: =('Summary 735'!E14+'Summary 2221'!E14+'Summary 2439'!E14+'Summary 2682'!E14+'Summary 2855'!E14)/5 -> 0 | F14: =('Summary 735'!F14+'Summary 2221'!F14+'Summary 2439'!F14+'Summary 2682'!F14+'Summary 2855'!F14)/5 -> 0 | G14: =('Summary 735'!G14+'Summary 2221'!G14+'Summary 2439'!G14+'Summary 2682'!G14+'Summary 2855'!G14)/5 -> 0 | H14: =SUM(B14:G14) -> #VALUE! | J14: =H14*$H$4 -> #VALUE! | L14: Direct Labour
A15: Handling Cost | B15: =SUM('Summary 735'!B15+'Summary 2221'!B15+'Summary 2221'!B15+'Summary 2439'!B15+'Summary 2682'!B15+'Summary 2855'!B15+#REF!+'Summary FLT104'!B15+'Summary FLT110'!B15+#REF!+#REF!+#REF!+'Summary 2037'!B15+'Summary 2817'!B15)/13 -> #REF! | C15: =('Summary 735'!C15+'Summary 2221'!C15+'Summary 2439'!C15+'Summary 2682'!C15+'Summary 2855'!C15)/5 -> 0 | D15: =('Summary 735'!D15+'Summary 2221'!D15+'Summary 2439'!D15+'Summary 2682'!D15+'Summary 2855'!D15)/5 -> 0 | E15: =('Summary 735'!E15+'Summary 2221'!E15+'Summary 2439'!E15+'Summary 2682'!E15+'Summary 2855'!E15)/5 -> 0 | F15: =('Summary 735'!F15+'Summary 2221'!F15+'Summary 2439'!F15+'Summary 2682'!F15+'Summary 2855'!F15)/5 -> 0 | G15: =('Summary 735'!G15+'Summary 2221'!G15+'Summary 2439'!G15+'Summary 2682'!G15+'Summary 2855'!G15)/5 -> 0 | H15: =SUM(B15:G15) -> #REF! | J15: =H15*$H$4 -> #REF! | L15: =J12+J15 -> #REF! | M15: 1
A16: Handling Mark up | B16: =SUM('Summary 735'!B16+'Summary 2221'!B16+'Summary 2221'!B16+'Summary 2439'!B16+'Summary 2682'!B16+'Summary 2855'!B16+#REF!+'Summary FLT104'!B16+'Summary FLT110'!B16+#REF!+#REF!+#REF!+'Summary 2037'!B16+'Summary 2817'!B16)/13 -> #REF! | C16: =('Summary 735'!C16+'Summary 2221'!C16+'Summary 2439'!C16+'Summary 2682'!C16+'Summary 2855'!C16)/5 -> 0 | D16: =('Summary 735'!D16+'Summary 2221'!D16+'Summary 2439'!D16+'Summary 2682'!D16+'Summary 2855'!D16)/5 -> 0 | E16: =('Summary 735'!E16+'Summary 2221'!E16+'Summary 2439'!E16+'Summary 2682'!E16+'Summary 2855'!E16)/5 -> 0 | F16: =('Summary 735'!F16+'Summary 2221'!F16+'Summary 2439'!F16+'Summary 2682'!F16+'Summary 2855'!F16)/5 -> 0 | G16: =('Summary 735'!G16+'Summary 2221'!G16+'Summary 2439'!G16+'Summary 2682'!G16+'Summary 2855'!G16)/5 -> 0 | H16: =SUM(B16:G16) -> #REF! | J16: =H16*$H$4 -> #REF! | L16: =L15*M16 -> #REF! | M16: 0.8
A17: Total Per Flight | B17: =SUM(B11:B16) -> #REF! | C17: =SUM(C11:C16) -> 0 | D17: =SUM(D10:D16) -> #REF! | E17: =SUM(E10:E16) -> #REF! | F17: =SUM(F10:F16) -> #REF! | G17: =SUM(G10:G16) -> #REF! | H17: =SUM(H10:H16) -> #REF! | J17: =H17*$H$4 -> #REF! | L17: =L15*M17 -> #REF! | M17: 0.2
B18: =B17 -> #REF! | C18: =C17 -> 0 | D18: =D17 -> #REF! | E18: =E17-E15-E16 -> #REF! | F18: =F17 -> #REF! | G18: =G17 -> #REF! | I18: =E15+E16 -> 0
A19: Handling | B19: Cost | C19: Mark Up | D19: Price | I19: =E16 -> 0
A20: 737 Handling | B20: =SUM('Summary 735'!B20+'Summary 2221'!B20+'Summary 2221'!B20+'Summary 2439'!B20+'Summary 2682'!B20+'Summary 2855'!B20+#REF!+'Summary FLT104'!B20+'Summary FLT110'!B20+#REF!+#REF!+#REF!+'Summary 2037'!B20+'Summary 2817'!B20)/13 -> #REF! | C20: =B20*'P&L'!$R$10 -> #REF! | D20: =SUM(B20:C20) -> #REF!
A21: B777 Handling | B21: =Handling!#REF! -> #REF! | C21: =Handling!#REF! -> #REF! | D21: =Handling!#REF! -> #REF!
A22: A380 Handling | B22: =Handling!#REF! -> #REF! | C22: =Handling!#REF! -> #REF! | D22: =Handling!#REF! -> #REF!
A24: Avg Price Per Pax | B24: =IFERROR(((B11+B12+B13+B14)/B8),0) -> 0 | C24: =IFERROR(((C11+C12+C13+C14)/C8),0) -> 0 | D24: =IFERROR(((D10+D11+D12+D13+D14)/D8),0) -> 0 | E24: =IFERROR(((E10+E11+E12+E13+E14)/E8),0) -> 0 | F24: =IFERROR(((F10+F11+F12+F13+F14)/F8),0) -> 0 | G24: =IFERROR(((G10+G11+G12+G13+G14)/G8),0) -> 0
A25: Avg Mark up Per Pax | B25: =IFERROR(((B13+B14)/B8),0) -> 0 | C25: =IFERROR(((C13+C14)/C8),0) -> 0 | D25: =IFERROR(((D13+D14)/D8),0) -> 0 | E25: =IFERROR(((E13+E14)/E8),0) -> 0 | F25: =IFERROR(((F13+F14)/F8),0) -> 0 | G25: =IFERROR(((G13+G14)/G8),0) -> 0
A26: Over head Per Pax | B26: =IFERROR((B10/B8),0) -> 0 | C26: =IFERROR((C10/C8),0) -> 0 | D26: =IFERROR((D10/D8),0) -> 0 | E26: =IFERROR((E10/E8),0) -> 0 | F26: =IFERROR((F10/F8),0) -> 0 | G26: =IFERROR((G10/G8),0) -> 0
B28: CYCLE | C28: FLT
A29: Config | B29: ='P&L'!R5 -> 1
A30: OVERHEAD | B30: =B37*B8 -> 0 | C30: =C37*C8 -> 0 | D30: =D37*D8 -> 0 | E30: =E37*E8 -> 0 | F30: =F37*F8 -> 0 | G30: =G37*G8 -> 0
A31: Food Cost (DM) | B31: =('Summary 735'!B31+'Summary 2221'!B31+'Summary 2439'!B31+'Summary 2682'!B31+'Summary 2855'!B31)/5 -> 0 | C31: =('Summary 735'!C31+'Summary 2221'!C31+'Summary 2439'!C31+'Summary 2682'!C31+'Summary 2855'!C31+#REF!+'Summary FLT104'!C31+'Summary FLT110'!C31+#REF!+#REF!+#REF!+'Summary 2037'!C31+'Summary 2817'!C31)/13 -> #REF! | D31: =('Summary 735'!D31+'Summary 2221'!D31+'Summary 2439'!D31+'Summary 2682'!D31+'Summary 2855'!D31+#REF!+'Summary FLT104'!D31+'Summary FLT110'!D31+#REF!+#REF!+#REF!+'Summary 2037'!D31+'Summary 2817'!D31)/13 -> #REF! | E31: =('Summary 735'!E31+'Summary 2221'!E31+'Summary 2439'!E31+'Summary 2682'!E31+'Summary 2855'!E31)/5 -> 0 | F31: =('Summary 735'!F31+'Summary 2221'!F31+'Summary 2439'!F31+'Summary 2682'!F31+'Summary 2855'!F31+#REF!+'Summary FLT104'!F31+'Summary FLT110'!F31+#REF!+#REF!+#REF!+'Summary 2037'!F31+'Summary 2817'!F31)/13 -> #REF! | G31: =('Summary 735'!G31+'Summary 2221'!G31+'Summary 2439'!G31+'Summary 2682'!G31+'Summary 2855'!G31+#REF!+'Summary FLT104'!G31+'Summary FLT110'!G31+#REF!+#REF!+#REF!+'Summary 2037'!G31+'Summary 2817'!G31)/13 -> #REF!
A32: Wage Cost (DL) | B32: =('Summary 735'!B32+'Summary 2221'!B32+'Summary 2439'!B32+'Summary 2682'!B32+'Summary 2855'!B32)/5 -> 0 | C32: =('Summary 735'!C32+'Summary 2221'!C32+'Summary 2439'!C32+'Summary 2682'!C32+'Summary 2855'!C32+#REF!+'Summary FLT104'!C32+'Summary FLT110'!C32+#REF!+#REF!+#REF!+'Summary 2037'!C32+'Summary 2817'!C32)/13 -> #REF! | D32: =('Summary 735'!D32+'Summary 2221'!D32+'Summary 2439'!D32+'Summary 2682'!D32+'Summary 2855'!D32+#REF!+'Summary FLT104'!D32+'Summary FLT110'!D32+#REF!+#REF!+#REF!+'Summary 2037'!D32+'Summary 2817'!D32)/13 -> #REF! | E32: =('Summary 735'!E32+'Summary 2221'!E32+'Summary 2439'!E32+'Summary 2682'!E32+'Summary 2855'!E32)/5 -> 0 | F32: =('Summary 735'!F32+'Summary 2221'!F32+'Summary 2439'!F32+'Summary 2682'!F32+'Summary 2855'!F32+#REF!+'Summary FLT104'!F32+'Summary FLT110'!F32+#REF!+#REF!+#REF!+'Summary 2037'!F32+'Summary 2817'!F32)/13 -> #REF! | G32: =('Summary 735'!G32+'Summary 2221'!G32+'Summary 2439'!G32+'Summary 2682'!G32+'Summary 2855'!G32+#REF!+'Summary FLT104'!G32+'Summary FLT110'!G32+#REF!+#REF!+#REF!+'Summary 2037'!G32+'Summary 2817'!G32)/13 -> #REF!
A33: Markup Food | B33: =('Summary 735'!B33+'Summary 2221'!B33+'Summary 2439'!B33+'Summary 2682'!B33+'Summary 2855'!B33)/5 -> 0 | C33: =('Summary 735'!C33+'Summary 2221'!C33+'Summary 2439'!C33+'Summary 2682'!C33+'Summary 2855'!C33+#REF!+'Summary FLT104'!C33+'Summary FLT110'!C33+#REF!+#REF!+#REF!+'Summary 2037'!C33+'Summary 2817'!C33)/13 -> #REF! | D33: =('Summary 735'!D33+'Summary 2221'!D33+'Summary 2439'!D33+'Summary 2682'!D33+'Summary 2855'!D33+#REF!+'Summary FLT104'!D33+'Summary FLT110'!D33+#REF!+#REF!+#REF!+'Summary 2037'!D33+'Summary 2817'!D33)/13 -> #REF! | E33: =('Summary 735'!E33+'Summary 2221'!E33+'Summary 2439'!E33+'Summary 2682'!E33+'Summary 2855'!E33)/5 -> 0 | F33: =('Summary 735'!F33+'Summary 2221'!F33+'Summary 2439'!F33+'Summary 2682'!F33+'Summary 2855'!F33+#REF!+'Summary FLT104'!F33+'Summary FLT110'!F33+#REF!+#REF!+#REF!+'Summary 2037'!F33+'Summary 2817'!F33)/13 -> #REF! | G33: =('Summary 735'!G33+'Summary 2221'!G33+'Summary 2439'!G33+'Summary 2682'!G33+'Summary 2855'!G33+#REF!+'Summary FLT104'!G33+'Summary FLT110'!G33+#REF!+#REF!+#REF!+'Summary 2037'!G33+'Summary 2817'!G33)/13 -> #REF!
A34: Markup Labor | B34: =('Summary 735'!B34+'Summary 2221'!B34+'Summary 2439'!B34+'Summary 2682'!B34+'Summary 2855'!B34)/5 -> 0 | C34: =('Summary 735'!C34+'Summary 2221'!C34+'Summary 2439'!C34+'Summary 2682'!C34+'Summary 2855'!C34+#REF!+'Summary FLT104'!C34+'Summary FLT110'!C34+#REF!+#REF!+#REF!+'Summary 2037'!C34+'Summary 2817'!C34)/13 -> #REF! | D34: =('Summary 735'!D34+'Summary 2221'!D34+'Summary 2439'!D34+'Summary 2682'!D34+'Summary 2855'!D34+#REF!+'Summary FLT104'!D34+'Summary FLT110'!D34+#REF!+#REF!+#REF!+'Summary 2037'!D34+'Summary 2817'!D34)/13 -> #REF! | E34: =('Summary 735'!E34+'Summary 2221'!E34+'Summary 2439'!E34+'Summary 2682'!E34+'Summary 2855'!E34)/5 -> 0 | F34: =('Summary 735'!F34+'Summary 2221'!F34+'Summary 2439'!F34+'Summary 2682'!F34+'Summary 2855'!F34+#REF!+'Summary FLT104'!F34+'Summary FLT110'!F34+#REF!+#REF!+#REF!+'Summary 2037'!F34+'Summary 2817'!F34)/13 -> #REF! | G34: =('Summary 735'!G34+'Summary 2221'!G34+'Summary 2439'!G34+'Summary 2682'!G34+'Summary 2855'!G34+#REF!+'Summary FLT104'!G34+'Summary FLT110'!G34+#REF!+#REF!+#REF!+'Summary 2037'!G34+'Summary 2817'!G34)/13 -> #REF!
A36: Per Pax Avg
A37: OVERHEAD | B37: ='P&L'!$K$30 -> 0 | C37: ='P&L'!$L$30 -> 0 | D37: ='P&L'!$M$30 -> 0 | E37: ='P&L'!$N$30 -> 0 | F37: ='P&L'!$O$30 -> 0 | G37: ='P&L'!$P$30 -> 0
A38: Food Cost (DM) | B38: =IFERROR(B31/B7," ") | C38: =IFERROR(C31/C7," ") | D38: =IFERROR(D31/D7," ") | E38: =IFERROR(E31/E7," ") -> 0 | F38: =IFERROR(F31/F7," ") | G38: =IFERROR(G31/G7," ")
A39: Wage Cost (DL) | B39: =IFERROR(B32/B7," ") | C39: =IFERROR(C32/C7," ") | D39: =IFERROR(D32/D7," ") | E39: =IFERROR(E32/E7," ") -> 0 | F39: =IFERROR(F32/F7," ") | G39: =IFERROR(G32/G7," ")
A40: Markup Food | B40: =IFERROR(B33/B8," ") | C40: =IFERROR(C33/C7," ") | D40: =IFERROR(D33/D7," ") | E40: =IFERROR(E33/E7," ") -> 0 | F40: =IFERROR(F33/F7," ") | G40: =IFERROR(G33/G7," ")
A41: Markup Labor | B41: =IFERROR(B34/B7," ") | C41: =IFERROR(C34/C7," ") | D41: =IFERROR(D34/D7," ") | E41: =IFERROR(E34/E7," ") -> 0 | F41: =IFERROR(F34/F7," ") | G41: =IFERROR(G34/G7," ")
A108: 388
A109: 787

Sheet Summary Long Haul
A2: Customer | G2: Flights Per week | H2: =#REF!+'Summary FLT104'!H2+'Summary FLT110'!H2+#REF!+#REF!+#REF!+'Summary 2037'!H2+'Summary 2817'!H2 -> #REF! | L2: AC type | M2: Cycle
E3: AC Type | F3: 737 | G3: Flights Per Month | H3: =H4/12 -> #REF! | J3: Total Revenues | L3: 737 | M3: 1
E4: Load | F4: ='P&L'!R4 -> 0.85 | G4: Annual Flights | H4: =H2*52 -> #REF! | J4: =H17*H4 -> #REF!
A5: Summary
A6: BNA | B6: FC | C6: BC | D6: PY | E6: EY | F6: TC | G6: CY | H6: Total | I6: Hnd
A7: FLIGHT CONFIG | B7: =+'FlightConfig '!B17 -> 0 | C7: =+'FlightConfig '!C17 -> 34 | D7: =+'FlightConfig '!D17 -> 48 | E7: =+'FlightConfig '!E17 -> 198 | F7: =+'FlightConfig '!F17 -> 0 | G7: =+'FlightConfig '!G17 -> 6 | H7: =SUM(B7:G7) -> 286
A8: Load Factor | B8: =ROUNDUP(B7*$F$4,0) -> 0 | C8: =ROUNDUP(C7*$F$4,0) -> 29 | D8: =ROUNDUP(D7*$F$4,0) -> 41 | E8: =ROUNDUP(E7*$F$4,0) -> 169 | F8: =ROUNDUP(F7*$F$4,0) -> 0 | G8: =ROUNDUP(G7*$F$4,0) -> 6 | H8: =SUM(B8:G8) -> 245
B9: FIRST CLASS | C9: BUSINESS CLASS | D9: PREMIUM ECONOMY CLASS | E9: ECONOMY CLASS | F9: TECH CREW CLASS | G9: cABIN CREW CLASS | H9: Per Flight | J9: Annual
A10: OVERHEAD | B10: =(#REF!+'Summary FLT104'!B10+'Summary FLT110'!B10+#REF!+#REF!+#REF!)/6 -> #REF! | C10: =(#REF!+'Summary FLT104'!C10+'Summary FLT110'!C10+#REF!+#REF!+#REF!)/6 -> #REF! | D10: =(#REF!+'Summary FLT104'!D10+'Summary FLT110'!D10+#REF!+#REF!+#REF!)/6 -> #REF! | E10: =(#REF!+'Summary FLT104'!E10+'Summary FLT110'!E10+#REF!+#REF!+#REF!)/6 -> #REF! | F10: =(#REF!+'Summary FLT104'!F10+'Summary FLT110'!F10+#REF!+#REF!+#REF!)/6 -> #REF! | G10: =(#REF!+'Summary FLT104'!G10+'Summary FLT110'!G10+#REF!+#REF!+#REF!)/6 -> #REF! | H10: =(#REF!+'Summary FLT104'!H10+'Summary FLT110'!H10+#REF!+#REF!+#REF!)/6 -> #REF! | J10: =H10*$H$4 -> #REF!
A11: Food Cost (DM) | B11: =(#REF!+'Summary FLT104'!B11+'Summary FLT110'!B11+#REF!+#REF!+#REF!)/6 -> #REF! | C11: =(#REF!+'Summary FLT104'!C11+'Summary FLT110'!C11+#REF!+#REF!+#REF!)/6 -> #REF! | D11: =(#REF!+'Summary FLT104'!D11+'Summary FLT110'!D11+#REF!+#REF!+#REF!)/6 -> #REF! | E11: =(#REF!+'Summary FLT104'!E11+'Summary FLT110'!E11+#REF!+#REF!+#REF!)/6 -> #REF! | F11: =(#REF!+'Summary FLT104'!F11+'Summary FLT110'!F11+#REF!+#REF!+#REF!)/6 -> #REF! | G11: =(#REF!+'Summary FLT104'!G11+'Summary FLT110'!G11+#REF!+#REF!+#REF!)/6 -> #REF! | H11: =(#REF!+'Summary FLT104'!H11+'Summary FLT110'!H11+#REF!+#REF!+#REF!)/6 -> #REF! | I11: =I12*45% -> #REF! | J11: =H11*$H$4 -> #REF!
A12: Wage Cost (DL) | B12: =(#REF!+'Summary FLT104'!B12+'Summary FLT110'!B12+#REF!+#REF!+#REF!)/6 -> #REF! | C12: =(#REF!+'Summary FLT104'!C12+'Summary FLT110'!C12+#REF!+#REF!+#REF!)/6 -> #REF! | D12: =(#REF!+'Summary FLT104'!D12+'Summary FLT110'!D12+#REF!+#REF!+#REF!)/6 -> #REF! | E12: =(#REF!+'Summary FLT104'!E12+'Summary FLT110'!E12+#REF!+#REF!+#REF!)/6 -> #REF! | F12: =(#REF!+'Summary FLT104'!F12+'Summary FLT110'!F12+#REF!+#REF!+#REF!)/6 -> #REF! | G12: =(#REF!+'Summary FLT104'!G12+'Summary FLT110'!G12+#REF!+#REF!+#REF!)/6 -> #REF! | H12: =(#REF!+'Summary FLT104'!H12+'Summary FLT110'!H12+#REF!+#REF!+#REF!)/6 -> #REF! | I12: =H11+H12 -> #REF! | J12: =H12*$H$4 -> #REF!
A13: Food Mark up | B13: =(#REF!+'Summary FLT104'!B13+'Summary FLT110'!B13+#REF!+#REF!+#REF!)/6 -> #REF! | C13: =(#REF!+'Summary FLT104'!C13+'Summary FLT110'!C13+#REF!+#REF!+#REF!)/6 -> #REF! | D13: =(#REF!+'Summary FLT104'!D13+'Summary FLT110'!D13+#REF!+#REF!+#REF!)/6 -> #REF! | E13: =(#REF!+'Summary FLT104'!E13+'Summary FLT110'!E13+#REF!+#REF!+#REF!)/6 -> #REF! | F13: =(#REF!+'Summary FLT104'!F13+'Summary FLT110'!F13+#REF!+#REF!+#REF!)/6 -> #REF! | G13: =(#REF!+'Summary FLT104'!G13+'Summary FLT110'!G13+#REF!+#REF!+#REF!)/6 -> #REF! | H13: =(#REF!+'Summary FLT104'!H13+'Summary FLT110'!H13+#REF!+#REF!+#REF!)/6 -> #REF! | J13: =H13*$H$4 -> #REF!
A14: Labor Mark up | B14: =(#REF!+'Summary FLT104'!B14+'Summary FLT110'!B14+#REF!+#REF!+#REF!)/6 -> #REF! | C14: =(#REF!+'Summary FLT104'!C14+'Summary FLT110'!C14+#REF!+#REF!+#REF!)/6 -> #REF! | D14: =(#REF!+'Summary FLT104'!D14+'Summary FLT110'!D14+#REF!+#REF!+#REF!)/6 -> #REF! | E14: =(#REF!+'Summary FLT104'!E14+'Summary FLT110'!E14+#REF!+#REF!+#REF!)/6 -> #REF! | F14: =(#REF!+'Summary FLT104'!F14+'Summary FLT110'!F14+#REF!+#REF!+#REF!)/6 -> #REF! | G14: =(#REF!+'Summary FLT104'!G14+'Summary FLT110'!G14+#REF!+#REF!+#REF!)/6 -> #REF! | H14: =(#REF!+'Summary FLT104'!H14+'Summary FLT110'!H14+#REF!+#REF!+#REF!)/6 -> #REF! | J14: =H14*$H$4 -> #REF! | L14: Direct Labour
A15: Handling Cost | B15: =(#REF!+'Summary FLT104'!B15+'Summary FLT110'!B15+#REF!+#REF!+#REF!)/6 -> #REF! | C15: =(#REF!+'Summary FLT104'!C15+'Summary FLT110'!C15+#REF!+#REF!+#REF!)/6 -> #REF! | D15: =(#REF!+'Summary FLT104'!D15+'Summary FLT110'!D15+#REF!+#REF!+#REF!)/6 -> #REF! | E15: =(#REF!+'Summary FLT104'!E15+'Summary FLT110'!E15+#REF!+#REF!+#REF!)/6 -> #REF! | F15: =(#REF!+'Summary FLT104'!F15+'Summary FLT110'!F15+#REF!+#REF!+#REF!)/6 -> #REF! | G15: =(#REF!+'Summary FLT104'!G15+'Summary FLT110'!G15+#REF!+#REF!+#REF!)/6 -> #REF! | H15: =(#REF!+'Summary FLT104'!H15+'Summary FLT110'!H15+#REF!+#REF!+#REF!)/6 -> #REF! | J15: =H15*$H$4 -> #REF! | L15: =J12+J15 -> #REF! | M15: 1
A16: Handling Mark up | B16: =(#REF!+'Summary FLT104'!B16+'Summary FLT110'!B16+#REF!+#REF!+#REF!)/6 -> #REF! | C16: =(#REF!+'Summary FLT104'!C16+'Summary FLT110'!C16+#REF!+#REF!+#REF!)/6 -> #REF! | D16: =(#REF!+'Summary FLT104'!D16+'Summary FLT110'!D16+#REF!+#REF!+#REF!)/6 -> #REF! | E16: =(#REF!+'Summary FLT104'!E16+'Summary FLT110'!E16+#REF!+#REF!+#REF!)/6 -> #REF! | F16: =(#REF!+'Summary FLT104'!F16+'Summary FLT110'!F16+#REF!+#REF!+#REF!)/6 -> #REF! | G16: =(#REF!+'Summary FLT104'!G16+'Summary FLT110'!G16+#REF!+#REF!+#REF!)/6 -> #REF! | H16: =(#REF!+'Summary FLT104'!H16+'Summary FLT110'!H16+#REF!+#REF!+#REF!)/6 -> #REF! | J16: =H16*$H$4 -> #REF! | L16: =L15*M16 -> #REF! | M16: 0.8
A17: Total Per Flight | B17: =SUM(B11:B16) -> #REF! | C17: =SUM(C11:C16) -> #REF! | D17: =SUM(D10:D16) -> #REF! | E17: =SUM(E10:E16) -> #REF! | F17: =SUM(F10:F16) -> #REF! | G17: =SUM(G10:G16) -> #REF! | H17: =SUM(H10:H16) -> #REF! | J17: =H17*$H$4 -> #REF! | L17: =L15*M17 -> #REF! | M17: 0.2
B18: =B17 -> #REF! | C18: =C17 -> #REF! | D18: =D17 -> #REF! | E18: =E17-E15-E16 -> #REF! | F18: =F17 -> #REF! | G18: =G17 -> #REF! | I18: =E15+E16 -> #REF!
A19: Handling | B19: Cost | C19: Mark Up | D19: Price | I19: =E16 -> #REF!
A20: 737 Handling | B20: =(#REF!+'Summary FLT104'!B20+'Summary FLT110'!B20+#REF!+#REF!+#REF!+'Summary 2037'!B20+'Summary 2817'!B20)/8 -> #REF! | C20: =B20*'P&L'!$R$10 -> #REF! | D20: =SUM(B20:C20) -> #REF!
A21: B777 Handling | B21: =Handling!#REF! -> #REF! | C21: =Handling!#REF! -> #REF! | D21: =Handling!#REF! -> #REF!
A22: A380 Handling | B22: =Handling!#REF! -> #REF! | C22: =Handling!#REF! -> #REF! | D22: =Handling!#REF! -> #REF!
A24: Avg Price Per Pax | B24: =IFERROR(((B11+B12+B13+B14)/B8),0) -> 0 | C24: =IFERROR(((C11+C12+C13+C14)/C8),0) -> 0 | D24: =IFERROR(((D10+D11+D12+D13+D14)/D8),0) -> 0 | E24: =IFERROR(((E10+E11+E12+E13+E14)/E8),0) -> 0 | F24: =IFERROR(((F10+F11+F12+F13+F14)/F8),0) -> 0 | G24: =IFERROR(((G10+G11+G12+G13+G14)/G8),0) -> 0
A25: Avg Mark up Per Pax | B25: =IFERROR(((B13+B14)/B8),0) -> 0 | C25: =IFERROR(((C13+C14)/C8),0) -> 0 | D25: =IFERROR(((D13+D14)/D8),0) -> 0 | E25: =IFERROR(((E13+E14)/E8),0) -> 0 | F25: =IFERROR(((F13+F14)/F8),0) -> 0 | G25: =IFERROR(((G13+G14)/G8),0) -> 0
A26: Over head Per Pax | B26: =IFERROR((B10/B8),0) -> 0 | C26: =IFERROR((C10/C8),0) -> 0 | D26: =IFERROR((D10/D8),0) -> 0 | E26: =IFERROR((E10/E8),0) -> 0 | F26: =IFERROR((F10/F8),0) -> 0 | G26: =IFERROR((G10/G8),0) -> 0
B28: CYCLE | C28: FLT
A29: Config | B29: ='P&L'!R5 -> 1
A30: OVERHEAD | B30: =(#REF!+'Summary FLT104'!B30+'Summary FLT110'!B30+#REF!+#REF!+#REF!)/6 -> #REF! | C30: =(#REF!+'Summary FLT104'!C30+'Summary FLT110'!C30+#REF!+#REF!+#REF!)/6 -> #REF! | D30: =(#REF!+'Summary FLT104'!D30+'Summary FLT110'!D30+#REF!+#REF!+#REF!)/6 -> #REF! | E30: =(#REF!+'Summary FLT104'!E30+'Summary FLT110'!E30+#REF!+#REF!+#REF!)/6 -> #REF! | F30: =(#REF!+'Summary FLT104'!F30+'Summary FLT110'!F30+#REF!+#REF!+#REF!)/6 -> #REF! | G30: =(#REF!+'Summary FLT104'!G30+'Summary FLT110'!G30+#REF!+#REF!+#REF!)/6 -> #REF!
A31: Food Cost (DM) | B31: =(#REF!+'Summary FLT104'!B31+'Summary FLT110'!B31+#REF!+#REF!+#REF!)/6 -> #REF! | C31: =(#REF!+'Summary FLT104'!C31+'Summary FLT110'!C31+#REF!+#REF!+#REF!)/6 -> #REF! | D31: =(#REF!+'Summary FLT104'!D31+'Summary FLT110'!D31+#REF!+#REF!+#REF!)/6 -> #REF! | E31: =(#REF!+'Summary FLT104'!E31+'Summary FLT110'!E31+#REF!+#REF!+#REF!)/6 -> #REF! | F31: =(#REF!+'Summary FLT104'!F31+'Summary FLT110'!F31+#REF!+#REF!+#REF!)/6 -> #REF! | G31: =(#REF!+'Summary FLT104'!G31+'Summary FLT110'!G31+#REF!+#REF!+#REF!)/6 -> #REF!
A32: Wage Cost (DL) | B32: =(#REF!+'Summary FLT104'!B32+'Summary FLT110'!B32+#REF!+#REF!+#REF!)/6 -> #REF! | C32: =(#REF!+'Summary FLT104'!C32+'Summary FLT110'!C32+#REF!+#REF!+#REF!)/6 -> #REF! | D32: =(#REF!+'Summary FLT104'!D32+'Summary FLT110'!D32+#REF!+#REF!+#REF!)/6 -> #REF! | E32: =(#REF!+'Summary FLT104'!E32+'Summary FLT110'!E32+#REF!+#REF!+#REF!)/6 -> #REF! | F32: =(#REF!+'Summary FLT104'!F32+'Summary FLT110'!F32+#REF!+#REF!+#REF!)/6 -> #REF! | G32: =(#REF!+'Summary FLT104'!G32+'Summary FLT110'!G32+#REF!+#REF!+#REF!)/6 -> #REF!
A33: Markup Food | B33: =(#REF!+'Summary FLT104'!B33+'Summary FLT110'!B33+#REF!+#REF!+#REF!)/6 -> #REF! | C33: =(#REF!+'Summary FLT104'!C33+'Summary FLT110'!C33+#REF!+#REF!+#REF!)/6 -> #REF! | D33: =(#REF!+'Summary FLT104'!D33+'Summary FLT110'!D33+#REF!+#REF!+#REF!)/6 -> #REF! | E33: =(#REF!+'Summary FLT104'!E33+'Summary FLT110'!E33+#REF!+#REF!+#REF!)/6 -> #REF! | F33: =(#REF!+'Summary FLT104'!F33+'Summary FLT110'!F33+#REF!+#REF!+#REF!)/6 -> #REF! | G33: =(#REF!+'Summary FLT104'!G33+'Summary FLT110'!G33+#REF!+#REF!+#REF!)/6 -> #REF!
A34: Markup Labor | B34: =(#REF!+'Summary FLT104'!B34+'Summary FLT110'!B34+#REF!+#REF!+#REF!)/6 -> #REF! | C34: =(#REF!+'Summary FLT104'!C34+'Summary FLT110'!C34+#REF!+#REF!+#REF!)/6 -> #REF! | D34: =(#REF!+'Summary FLT104'!D34+'Summary FLT110'!D34+#REF!+#REF!+#REF!)/6 -> #REF! | E34: =(#REF!+'Summary FLT104'!E34+'Summary FLT110'!E34+#REF!+#REF!+#REF!)/6 -> #REF! | F34: =(#REF!+'Summary FLT104'!F34+'Summary FLT110'!F34+#REF!+#REF!+#REF!)/6 -> #REF! | G34: =(#REF!+'Summary FLT104'!G34+'Summary FLT110'!G34+#REF!+#REF!+#REF!)/6 -> #REF!
A36: Per Pax Avg
A37: OVERHEAD | B37: ='P&L'!$K$30 -> 0 | C37: ='P&L'!$L$30 -> 0 | D37: ='P&L'!$M$30 -> 0 | E37: ='P&L'!$N$30 -> 0 | F37: ='P&L'!$O$30 -> 0 | G37: ='P&L'!$P$30 -> 0
A38: Food Cost (DM) | B38: =IFERROR(B31/B7," ") | C38: =IFERROR(C31/C7," ") | D38: =IFERROR(D31/D7," ") | E38: =IFERROR(E31/E7," ") | F38: =IFERROR(F31/F7," ") | G38: =IFERROR(G31/G7," ")
A39: Wage Cost (DL) | B39: =IFERROR(B32/B7," ") | C39: =IFERROR(C32/C7," ") | D39: =IFERROR(D32/D7," ") | E39: =IFERROR(E32/E7," ") | F39: =IFERROR(F32/F7," ") | G39: =IFERROR(G32/G7," ")
A40: Markup Food | B40: =IFERROR(B33/B8," ") | C40: =IFERROR(C33/C7," ") | D40: =IFERROR(D33/D7," ") | E40: =IFERROR(E33/E7," ") | F40: =IFERROR(F33/F7," ") | G40: =IFERROR(G33/G7," ")
A41: Markup Labor | B41: =IFERROR(B34/B7," ") | C41: =IFERROR(C34/C7," ") | D41: =IFERROR(D34/D7," ") | E41: =IFERROR(E34/E7," ") | F41: =IFERROR(F34/F7," ") | G41: =IFERROR(G34/G7," ")
A108: 388
A109: 787

Sheet Summary  735
A2: Customer | G2: Flights Per week | H2: 0 | L2: AC type | M2: Cycle
E3: AC Type | F3: 738 | G3: Flights Per Month | H3: =H4/12 -> 0 | J3: Total Revenues | L3: 737 | M3: 1
E4: Load | F4: ='P&L'!R4 -> 0.85 | G4: Annual Flights | H4: =H2*52 -> 0 | J4: =H17*H4 -> 0
A5: Summary
A6: BNA | B6: FC | C6: BC | D6: PY | E6: EY | F6: TC | G6: CY | H6: Total | I6: Hnd
A7: FLIGHT CONFIG | B7: =+'FlightConfig '!B17 -> 0 | C7: =+'FlightConfig '!C17 -> 34 | D7: =+'FlightConfig '!D17 -> 48 | E7: =+'FlightConfig '!E17 -> 198 | F7: =+'FlightConfig '!F17 -> 0 | G7: =+'FlightConfig '!G17 -> 6 | H7: =SUM(B7:G7) -> 286
A8: Load Factor | B8: =ROUNDUP(B7*$F$4,0) -> 0 | C8: =ROUNDUP(C7*$F$4,0) -> 29 | D8: =ROUNDUP(D7*$F$4,0) -> 41 | E8: =ROUNDUP(E7*$F$4,0) -> 169 | F8: =ROUNDUP(F7*$F$4,0) -> 0 | G8: =ROUNDUP(G7*$F$4,0) -> 6 | H8: =SUM(B8:G8) -> 245
B9: FIRST CLASS | C9: BUSINESS CLASS | D9: PREMIUM ECONOMY CLASS | E9: ECONOMY CLASS | F9: TECH CREW CLASS | G9: cABIN CREW CLASS | H9: Per Flight | J9: Annual
A10: OVERHEAD | B10: =B37*B8 -> 0 | C10: =C37*C8 -> 0 | D10: =D37*D8 -> 0 | E10: =E37*E8 -> 0 | F10: =F37*F8 -> 0 | G10: =G37*G8 -> 0 | H10: =SUM(B10:G10) -> 0 | J10: =H10*$H$4 -> 0
A11: Food Cost (DM) | B11: =IFERROR(B38*B8,0) -> 0 | C11: =IFERROR(C38*$C$8,0) -> 0 | D11: =IFERROR(D38*$D$8,0) -> 0 | E11: =IFERROR(E38*$E$8,0) -> 0 | F11: =IFERROR(F38*$F$8,0) -> 0 | G11: =IFERROR(G38*G8,0) -> 0 | H11: =SUM(B11:G11) -> 0 | I11: =I12*45% -> 0 | J11: =H11*$H$4 -> 0
A12: Wage Cost (DL) | B12: =IFERROR(B39*B8,0) -> 0 | C12: =IFERROR(C39*$C$8,0) -> 0 | D12: =IFERROR(D39*$D$8,0) -> 0 | E12: =IFERROR(E39*$E$8,0) -> 0 | F12: =IFERROR(F39*$F$8,0) -> 0 | G12: =IFERROR(G39*G8,0) -> 0 | H12: =SUM(B12:G12) -> 0 | I12: =H11+H12 -> 0 | J12: =H12*$H$4 -> 0
A13: Food Mark up | B13: =IFERROR(B40*B8," ") | C13: =IFERROR(C40*$C$8,0) -> 0 | D13: =IFERROR(D40*$D$8,0) -> 0 | E13: =IFERROR(E40*$E$8,0) -> 0 | F13: =IFERROR(F40*$F$8,0) -> 0 | G13: 0 | H13: =SUM(B13:G13) -> 0 | J13: =H13*$H$4 -> 0
A14: Labor Mark up | B14: =IFERROR(B41*B8," ") | C14: =IFERROR(C41*$C$8,0) -> 0 | D14: =IFERROR(D41*$D$8,0) -> 0 | E14: =IFERROR(E41*$E$8,0) -> 0 | F14: =IFERROR(F41*$F$8,0) -> 0 | G14: 0 | H14: =SUM(B14:G14) -> 0 | J14: =H14*$H$4 -> 0 | L14: Direct Labour
A15: Handling Cost | B15: 0 | C15: 0 | D15: 0 | E15: =+B20 -> 0 | F15: 0 | G15: 0 | H15: =SUM(B15:G15) -> 0 | J15: =H15*$H$4 -> 0 | L15: =J12+J15 -> 0 | M15: 1
A16: Handling Mark up | B16: 0 | C16: 0 | D16: 0 | E16: =+C20 -> 0 | F16: 0 | G16: 0 | H16: =SUM(B16:G16) -> 0 | J16: =H16*$H$4 -> 0 | L16: =L15*M16 -> 0 | M16: 0.8
A17: Total Per Flight | B17: =SUM(B11:B16) -> 0 | C17: =SUM(C11:C16) -> 0 | D17: =SUM(D10:D16) -> 0 | E17: =SUM(E10:E16) -> 0 | F17: =SUM(F10:F16) -> 0 | G17: =SUM(G10:G16) -> 0 | H17: =SUM(H10:H16) -> 0 | J17: =H17*$H$4 -> 0 | L17: =L15*M17 -> 0 | M17: 0.2
B18: =B17 -> 0 | C18: =C17 -> 0 | D18: =D17 -> 0 | E18: =E17-E15-E16 -> 0 | F18: =F17 -> 0 | G18: =G17 -> 0 | I18: =E15+E16 -> 0
A19: Handling | B19: Cost | C19: Mark Up | D19: Price | I19: =E16 -> 0
A20: 738 Handling | B20: =Handling!C56 -> 0 | C20: =B20*'P&L'!$R$10 -> 0 | D20: =SUM(B20:C20) -> 0
A21: B777 Handling | B21: =Handling!#REF! -> #REF! | C21: =Handling!#REF! -> #REF! | D21: =Handling!#REF! -> #REF!
A22: A380 Handling | B22: =Handling!#REF! -> #REF! | C22: =Handling!#REF! -> #REF! | D22: =Handling!#REF! -> #REF!
A24: Avg Price Per Pax | B24: =IFERROR(((B11+B12+B13+B14)/B8),0) -> 0 | C24: =IFERROR(((C11+C12+C13+C14)/C8),0) -> 0 | D24: =IFERROR(((D10+D11+D12+D13+D14)/D8),0) -> 0 | E24: =IFERROR(((E10+E11+E12+E13+E14)/E8),0) -> 0 | F24: =IFERROR(((F10+F11+F12+F13+F14)/F8),0) -> 0 | G24: =IFERROR(((G10+G11+G12+G13+G14)/G8),0) -> 0
A25: Avg Mark up Per Pax | B25: =IFERROR(((B13+B14)/B8),0) -> 0 | C25: =IFERROR(((C13+C14)/C8),0) -> 0 | D25: =IFERROR(((D13+D14)/D8),0) -> 0 | E25: =IFERROR(((E13+E14)/E8),0) -> 0 | F25: =IFERROR(((F13+F14)/F8),0) -> 0 | G25: =IFERROR(((G13+G14)/G8),0) -> 0
A26: Over head Per Pax | B26: =IFERROR((B10/B8),0) -> 0 | C26: =IFERROR((C10/C8),0) -> 0 | D26: =IFERROR((D10/D8),0) -> 0 | E26: =IFERROR((E10/E8),0) -> 0 | F26: =IFERROR((F10/F8),0) -> 0 | G26: =IFERROR((G10/G8),0) -> 0
B28: CYCLE | C28: FLT
A29: Config | B29: ='P&L'!R5 -> 1 | C29: 735
A30: OVERHEAD | B30: =B37*B8 -> 0 | C30: =C37*C8 -> 0 | D30: =D37*D8 -> 0 | E30: =E37*E8 -> 0 | F30: =F37*F8 -> 0 | G30: =G37*G8 -> 0
A31: Food Cost (DM) | B31: =IFERROR(IF($B$29=$B$29,SUMIF(Food!$C:$C,B$9&$B$29&$C$29,Food!$X:$X),0),"") -> 0 | C31: =IFERROR(IF($B$29=$B$29,SUMIF(Food!$C:$C,C$9&$B$29&$C$29,Food!$X:$X),0),"") -> 0 | D31: =IFERROR(IF($B$29=$B$29,SUMIF(Food!$C:$C,D$9&$B$29&$C$29,Food!$X:$X),0),"") -> 0 | E31: =IFERROR(IF($B$29=$B$29,SUMIF(Food!$C:$C,E$9&$B$29&$C$29,Food!$X:$X),0),"") -> 0 | F31: =IFERROR(IF($B$29=$B$29,SUMIF(Food!$C:$C,F$9&$B$29&$C$29,Food!$X:$X),0),"") -> 0 | G31: =IFERROR(IF($B$29=$B$29,SUMIF(Food!$C:$C,G$9&$B$29&$C$29,Food!$X:$X),0),"") -> 0
A32: Wage Cost (DL) | B32: =IFERROR(IF($B$29=$B$29,SUMIF(Food!$C:$C,B$9&$B$29&$C$29,Food!$Z:$Z),0),"") -> 0 | C32: =IFERROR(IF($B$29=$B$29,SUMIF(Food!$C:$C,C$9&$B$29&$C$29,Food!$Z:$Z),0),"") -> 0 | D32: =IFERROR(IF($B$29=$B$29,SUMIF(Food!$C:$C,D$9&$B$29&$C$29,Food!$Z:$Z),0),"") -> 0 | E32: =IFERROR(IF($B$29=$B$29,SUMIF(Food!$C:$C,E$9&$B$29&$C$29,Food!$Z:$Z),0),"") -> 0 | F32: =IFERROR(IF($B$29=$B$29,SUMIF(Food!$C:$C,F$9&$B$29&$C$29,Food!$Z:$Z),0),"") -> 0 | G32: =IFERROR(IF($B$29=$B$29,SUMIF(Food!$C:$C,G$9&$B$29&$C$29,Food!$Z:$Z),0),"") -> 0
A33: Markup Food | B33: =IFERROR(IF($B$29=$B$29,SUMIF(Food!$C:$C,B$9&$B$29&$C$29,Food!$AB:$AB),0),"") -> 0 | C33: =IFERROR(IF($B$29=$B$29,SUMIF(Food!$C:$C,C$9&$B$29&$C$29,Food!$AB:$AB),0),"") -> 0 | D33: =IFERROR(IF($B$29=$B$29,SUMIF(Food!$C:$C,D$9&$B$29&$C$29,Food!$AB:$AB),0),"") -> 0 | E33: =IFERROR(IF($B$29=$B$29,SUMIF(Food!$C:$C,E$9&$B$29&$C$29,Food!$AB:$AB),0),"") -> 0 | F33: =IFERROR(IF($B$29=$B$29,SUMIF(Food!$C:$C,F$9&$B$29&$C$29,Food!$AB:$AB),0),"") -> 0 | G33: =IFERROR(IF($B$29=$B$29,SUMIF(Food!$C:$C,G$9&$B$29&$C$29,Food!$O:$O),0),"") -> 0
A34: Markup Labor | B34: =IFERROR(IF($B$29=$B$29,SUMIF(Food!$C:$C,B$9&$B$29&$C$29,Food!$AC:$AC),0),"") -> 0 | C34: =IFERROR(IF($B$29=$B$29,SUMIF(Food!$C:$C,C$9&$B$29&$C$29,Food!$AC:$AC),0),"") -> 0 | D34: =IFERROR(IF($B$29=$B$29,SUMIF(Food!$C:$C,D$9&$B$29&$C$29,Food!$AC:$AC),0),"") -> 0 | E34: =IFERROR(IF($B$29=$B$29,SUMIF(Food!$C:$C,E$9&$B$29&$C$29,Food!$AC:$AC),0),"") -> 0 | F34: =IFERROR(IF($B$29=$B$29,SUMIF(Food!$C:$C,F$9&$B$29&$C$29,Food!$AC:$AC),0),"") -> 0 | G34: =IFERROR(IF($B$29=$B$29,SUMIF(Food!$C:$C,G$9&$B$29&$C$29,Food!$P:$P),0),"") -> 0
A36: Per Pax Avg
A37: OVERHEAD | B37: ='P&L'!$K$30 -> 0 | C37: ='P&L'!$L$30 -> 0 | D37: ='P&L'!$M$30 -> 0 | E37: ='P&L'!$N$30 -> 0 | F37: ='P&L'!$O$30 -> 0 | G37: ='P&L'!$P$30 -> 0
A38: Food Cost (DM) | B38: =IFERROR(B31/B7," ") | C38: =IFERROR(C31/C7," ") -> 0 | D38: =IFERROR(D31/D7," ") -> 0 | E38: =IFERROR(E31/E7," ") -> 0 | F38: =IFERROR(F31/F7," ") | G38: =IFERROR(G31/G7," ") -> 0
A39: Wage Cost (DL) | B39: =IFERROR(B32/B7," ") | C39: =IFERROR(C32/C7," ") -> 0 | D39: =IFERROR(D32/D7," ") -> 0 | E39: =IFERROR(E32/E7," ") -> 0 | F39: =IFERROR(F32/F7," ") | G39: =IFERROR(G32/G7," ") -> 0
A40: Markup Food | B40: =IFERROR(B33/B8," ") | C40: =IFERROR(C33/C7," ") -> 0 | D40: =IFERROR(D33/D7," ") -> 0 | E40: =IFERROR(E33/E7," ") -> 0 | F40: =IFERROR(F33/F7," ") | G40: =IFERROR(G33/G7," ") -> 0
A41: Markup Labor | B41: =IFERROR(B34/B7," ") | C41: =IFERROR(C34/C7," ") -> 0 | D41: =IFERROR(D34/D7," ") -> 0 | E41: =IFERROR(E34/E7," ") -> 0 | F41: =IFERROR(F34/F7," ") | G41: =IFERROR(G34/G7," ") -> 0
A108: 388
A109: 787

Sheet Summary 2221
A2: Customer | G2: Flights Per week | H2: 0 | L2: AC type | M2: Cycle
E3: AC Type | F3: 738 | G3: Flights Per Month | H3: =H4/12 -> 0 | J3: Total Revenues | L3: 737 | M3: 1
E4: Load | F4: ='P&L'!R4 -> 0.85 | G4: Annual Flights | H4: =H2*52 -> 0 | J4: =H17*H4 -> 0
A5: Summary
A6: BNA | B6: FC | C6: BC | D6: PY | E6: EY | F6: TC | G6: CY | H6: Total | I6: Hnd
A7: FLIGHT CONFIG | B7: =+'FlightConfig '!B17 -> 0 | C7: =+'FlightConfig '!C17 -> 34 | D7: =+'FlightConfig '!D17 -> 48 | E7: =+'FlightConfig '!E17 -> 198 | F7: =+'FlightConfig '!F17 -> 0 | G7: =+'FlightConfig '!G17 -> 6 | H7: =SUM(B7:G7) -> 286
A8: Load Factor | B8: =ROUNDUP(B7*$F$4,0) -> 0 | C8: =ROUNDUP(C7*$F$4,0) -> 29 | D8: =ROUNDUP(D7*$F$4,0) -> 41 | E8: =ROUNDUP(E7*$F$4,0) -> 169 | F8: =ROUNDUP(F7*$F$4,0) -> 0 | G8: =ROUNDUP(G7*$F$4,0) -> 6 | H8: =SUM(B8:G8) -> 245
B9: FIRST CLASS | C9: BUSINESS CLASS | D9: PREMIUM ECONOMY CLASS | E9: ECONOMY CLASS | F9: TECH CREW CLASS | G9: cABIN CREW CLASS | H9: Per Flight | J9: Annual
A10: OVERHEAD | B10: =B37*B8 -> 0 | C10: =C37*C8 -> 0 | D10: =D37*D8 -> 0 | E10: =E37*E8 -> 0 | F10: =F37*F8 -> 0 | G10: =G37*G8 -> 0 | H10: =SUM(B10:G10) -> 0 | J10: =H10*$H$4 -> 0
A11: Food Cost (DM) | B11: =IFERROR(B38*B8,0) -> 0 | C11: =IFERROR(C38*$C$8,0) -> 0 | D11: =IFERROR(D38*$D$8,0) -> 0 | E11: =IFERROR(E38*$E$8,0) -> 0 | F11: =IFERROR(F38*$F$8,0) -> 0 | G11: =IFERROR(G38*G8,0) -> 0 | H11: =SUM(B11:G11) -> 0 | I11: =I12*45% -> 0 | J11: =H11*$H$4 -> 0
A12: Wage Cost (DL) | B12: =IFERROR(B39*B8,0) -> 0 | C12: =IFERROR(C39*$C$8,0) -> 0 | D12: =IFERROR(D39*$D$8,0) -> 0 | E12: =IFERROR(E39*$E$8,0) -> 0 | F12: =IFERROR(F39*$F$8,0) -> 0 | G12: =IFERROR(G39*G8,0) -> 0 | H12: =SUM(B12:G12) -> 0 | I12: =H11+H12 -> 0 | J12: =H12*$H$4 -> 0
A13: Food Mark up | B13: =IFERROR(B40*B8," ") | C13: =IFERROR(C40*$C$8,0) -> 0 | D13: =IFERROR(D40*$D$8,0) -> 0 | E13: =IFERROR(E40*$E$8,0) -> 0 | F13: =IFERROR(F40*$F$8,0) -> 0 | G13: 0 | H13: =SUM(B13:G13) -> 0 | J13: =H13*$H$4 -> 0
A14: Labor Mark up | B14: =IFERROR(B41*B8," ") | C14: =IFERROR(C41*$C$8,0) -> 0 | D14: =IFERROR(D41*$D$8,0) -> 0 | E14: =IFERROR(E41*$E$8,0) -> 0 | F14: =IFERROR(F41*$F$8,0) -> 0 | G14: 0 | H14: =SUM(B14:G14) -> 0 | J14: =H14*$H$4 -> 0 | L14: Direct Labour
A15: Handling Cost | B15: 0 | C15: 0 | D15: 0 | E15: =+B20 -> 0 | F15: 0 | G15: 0 | H15: =SUM(B15:G15) -> 0 | J15: =H15*$H$4 -> 0 | L15: =J12+J15 -> 0 | M15: 1
A16: Handling Mark up | B16: 0 | C16: 0 | D16: 0 | E16: =+C20 -> 0 | F16: 0 | G16: 0 | H16: =SUM(B16:G16) -> 0 | J16: =H16*$H$4 -> 0 | L16: =L15*M16 -> 0 | M16: 0.8
A17: Total Per Flight | B17: =SUM(B11:B16) -> 0 | C17: =SUM(C11:C16) -> 0 | D17: =SUM(D10:D16) -> 0 | E17: =SUM(E10:E16) -> 0 | F17: =SUM(F10:F16) -> 0 | G17: =SUM(G10:G16) -> 0 | H17: =SUM(H10:H16) -> 0 | J17: =H17*$H$4 -> 0 | L17: =L15*M17 -> 0 | M17: 0.2
B18: =B17 -> 0 | C18: =C17 -> 0 | D18: =D17 -> 0 | E18: =E17-E15-E16 -> 0 | F18: =F17 -> 0 | G18: =G17 -> 0 | I18: =E15+E16 -> 0
A19: Handling | B19: Cost | C19: Mark Up | D19: Price | I19: =E16 -> 0
A20: 738 Handling | B20: =Handling!C56 -> 0 | C20: =B20*'P&L'!$R$10 -> 0 | D20: =SUM(B20:C20) -> 0
A21: B777 Handling | B21: =Handling!#REF! -> #REF! | C21: =Handling!#REF! -> #REF! | D21: =Handling!#REF! -> #REF!
A22: A380 Handling | B22: =Handling!#REF! -> #REF! | C22: =Handling!#REF! -> #REF! | D22: =Handling!#REF! -> #REF!
A24: Avg Price Per Pax | B24: =IFERROR(((B11+B12+B13+B14)/B8),0) -> 0 | C24: =IFERROR(((C11+C12+C13+C14)/C8),0) -> 0 | D24: =IFERROR(((D10+D11+D12+D13+D14)/D8),0) -> 0 | E24: =IFERROR(((E10+E11+E12+E13+E14)/E8),0) -> 0 | F24: =IFERROR(((F10+F11+F12+F13+F14)/F8),0) -> 0 | G24: =IFERROR(((G10+G11+G12+G13+G14)/G8),0) -> 0
A25: Avg Mark up Per Pax | B25: =IFERROR(((B13+B14)/B8),0) -> 0 | C25: =IFERROR(((C13+C14)/C8),0) -> 0 | D25: =IFERROR(((D13+D14)/D8),0) -> 0 | E25: =IFERROR(((E13+E14)/E8),0) -> 0 | F25: =IFERROR(((F13+F14)/F8),0) -> 0 | G25: =IFERROR(((G13+G14)/G8),0) -> 0
A26: Over head Per Pax | B26: =IFERROR((B10/B8),0) -> 0 | C26: =IFERROR((C10/C8),0) -> 0 | D26: =IFERROR((D10/D8),0) -> 0 | E26: =IFERROR((E10/E8),0) -> 0 | F26: =IFERROR((F10/F8),0) -> 0 | G26: =IFERROR((G10/G8),0) -> 0
B28: CYCLE | C28: FLT
A29: Config | B29: ='P&L'!R5 -> 1 | C29: 2221
A30: OVERHEAD | B30: =B37*B8 -> 0 | C30: =C37*C8 -> 0 | D30: =D37*D8 -> 0 | E30: =E37*E8 -> 0 | F30: =F37*F8 -> 0 | G30: =G37*G8 -> 0
A31: Food Cost (DM) | B31: =IFERROR(IF($B$29=$B$29,SUMIF(Food!$C:$C,B$9&$B$29&$C$29,Food!$X:$X),0),"") -> 0 | C31: =IFERROR(IF($B$29=$B$29,SUMIF(Food!$C:$C,C$9&$B$29&$C$29,Food!$X:$X),0),"") -> 0 | D31: =IFERROR(IF($B$29=$B$29,SUMIF(Food!$C:$C,D$9&$B$29&$C$29,Food!$X:$X),0),"") -> 0 | E31: =IFERROR(IF($B$29=$B$29,SUMIF(Food!$C:$C,E$9&$B$29&$C$29,Food!$X:$X),0),"") -> 0 | F31: =IFERROR(IF($B$29=$B$29,SUMIF(Food!$C:$C,F$9&$B$29&$C$29,Food!$X:$X),0),"") -> 0 | G31: =IFERROR(IF($B$29=$B$29,SUMIF(Food!$C:$C,G$9&$B$29&$C$29,Food!$X:$X),0),"") -> 0
A32: Wage Cost (DL) | B32: =IFERROR(IF($B$29=$B$29,SUMIF(Food!$C:$C,B$9&$B$29&$C$29,Food!$Z:$Z),0),"") -> 0 | C32: =IFERROR(IF($B$29=$B$29,SUMIF(Food!$C:$C,C$9&$B$29&$C$29,Food!$Z:$Z),0),"") -> 0 | D32: =IFERROR(IF($B$29=$B$29,SUMIF(Food!$C:$C,D$9&$B$29&$C$29,Food!$Z:$Z),0),"") -> 0 | E32: =IFERROR(IF($B$29=$B$29,SUMIF(Food!$C:$C,E$9&$B$29&$C$29,Food!$Z:$Z),0),"") -> 0 | F32: =IFERROR(IF($B$29=$B$29,SUMIF(Food!$C:$C,F$9&$B$29&$C$29,Food!$Z:$Z),0),"") -> 0 | G32: =IFERROR(IF($B$29=$B$29,SUMIF(Food!$C:$C,G$9&$B$29&$C$29,Food!$Z:$Z),0),"") -> 0
A33: Markup Food | B33: =IFERROR(IF($B$29=$B$29,SUMIF(Food!$C:$C,B$9&$B$29&$C$29,Food!$AB:$AB),0),"") -> 0 | C33: =IFERROR(IF($B$29=$B$29,SUMIF(Food!$C:$C,C$9&$B$29&$C$29,Food!$AB:$AB),0),"") -> 0 | D33: =IFERROR(IF($B$29=$B$29,SUMIF(Food!$C:$C,D$9&$B$29&$C$29,Food!$AB:$AB),0),"") -> 0 | E33: =IFERROR(IF($B$29=$B$29,SUMIF(Food!$C:$C,E$9&$B$29&$C$29,Food!$AB:$AB),0),"") -> 0 | F33: =IFERROR(IF($B$29=$B$29,SUMIF(Food!$C:$C,F$9&$B$29&$C$29,Food!$AB:$AB),0),"") -> 0 | G33: =IFERROR(IF($B$29=$B$29,SUMIF(Food!$C:$C,G$9&$B$29&$C$29,Food!$O:$O),0),"") -> 0
A34: Markup Labor | B34: =IFERROR(IF($B$29=$B$29,SUMIF(Food!$C:$C,B$9&$B$29&$C$29,Food!$AC:$AC),0),"") -> 0 | C34: =IFERROR(IF($B$29=$B$29,SUMIF(Food!$C:$C,C$9&$B$29&$C$29,Food!$AC:$AC),0),"") -> 0 | D34: =IFERROR(IF($B$29=$B$29,SUMIF(Food!$C:$C,D$9&$B$29&$C$29,Food!$AC:$AC),0),"") -> 0 | E34: =IFERROR(IF($B$29=$B$29,SUMIF(Food!$C:$C,E$9&$B$29&$C$29,Food!$AC:$AC),0),"") -> 0 | F34: =IFERROR(IF($B$29=$B$29,SUMIF(Food!$C:$C,F$9&$B$29&$C$29,Food!$AC:$AC),0),"") -> 0 | G34: =IFERROR(IF($B$29=$B$29,SUMIF(Food!$C:$C,G$9&$B$29&$C$29,Food!$P:$P),0),"") -> 0
A36: Per Pax Avg
A37: OVERHEAD | B37: ='P&L'!$K$30 -> 0 | C37: ='P&L'!$L$30 -> 0 | D37: ='P&L'!$M$30 -> 0 | E37: ='P&L'!$N$30 -> 0 | F37: ='P&L'!$O$30 -> 0 | G37: ='P&L'!$P$30 -> 0
A38: Food Cost (DM) | B38: =IFERROR(B31/B7," ") | C38: =IFERROR(C31/C7," ") -> 0 | D38: =IFERROR(D31/D7," ") -> 0 | E38: =IFERROR(E31/E7," ") -> 0 | F38: =IFERROR(F31/F7," ") | G38: =IFERROR(G31/G7," ") -> 0
A39: Wage Cost (DL) | B39: =IFERROR(B32/B7," ") | C39: =IFERROR(C32/C7," ") -> 0 | D39: =IFERROR(D32/D7," ") -> 0 | E39: =IFERROR(E32/E7," ") -> 0 | F39: =IFERROR(F32/F7," ") | G39: =IFERROR(G32/G7," ") -> 0
A40: Markup Food | B40: =IFERROR(B33/B8," ") | C40: =IFERROR(C33/C7," ") -> 0 | D40: =IFERROR(D33/D7," ") -> 0 | E40: =IFERROR(E33/E7," ") -> 0 | F40: =IFERROR(F33/F7," ") | G40: =IFERROR(G33/G7," ") -> 0
A41: Markup Labor | B41: =IFERROR(B34/B7," ") | C41: =IFERROR(C34/C7," ") -> 0 | D41: =IFERROR(D34/D7," ") -> 0 | E41: =IFERROR(E34/E7," ") -> 0 | F41: =IFERROR(F34/F7," ") | G41: =IFERROR(G34/G7," ") -> 0
A108: 388
A109: 787

Sheet Summary 2439
A2: Customer | G2: Flights Per week | H2: 0 | L2: AC type | M2: Cycle
E3: AC Type | F3: 738 | G3: Flights Per Month | H3: =H4/12 -> 0 | J3: Total Revenues | L3: 737 | M3: 1
E4: Load | F4: ='P&L'!R4 -> 0.85 | G4: Annual Flights | H4: =H2*52 -> 0 | J4: =H17*H4 -> 0
A5: Summary
A6: BNA | B6: FC | C6: BC | D6: PY | E6: EY | F6: TC | G6: CY | H6: Total | I6: Hnd
A7: FLIGHT CONFIG | B7: =+'FlightConfig '!B17 -> 0 | C7: =+'FlightConfig '!C17 -> 34 | D7: =+'FlightConfig '!D17 -> 48 | E7: =+'FlightConfig '!E17 -> 198 | F7: =+'FlightConfig '!F17 -> 0 | G7: =+'FlightConfig '!G17 -> 6 | H7: =SUM(B7:G7) -> 286
A8: Load Factor | B8: =ROUNDUP(B7*$F$4,0) -> 0 | C8: =ROUNDUP(C7*$F$4,0) -> 29 | D8: =ROUNDUP(D7*$F$4,0) -> 41 | E8: =ROUNDUP(E7*$F$4,0) -> 169 | F8: =ROUNDUP(F7*$F$4,0) -> 0 | G8: =ROUNDUP(G7*$F$4,0) -> 6 | H8: =SUM(B8:G8) -> 245
B9: FIRST CLASS | C9: BUSINESS CLASS | D9: PREMIUM ECONOMY CLASS | E9: ECONOMY CLASS | F9: TECH CREW CLASS | G9: cABIN CREW CLASS | H9: Per Flight | J9: Annual
A10: OVERHEAD | B10: =B37*B8 -> 0 | C10: =C37*C8 -> 0 | D10: =D37*D8 -> 0 | E10: =E37*E8 -> 0 | F10: =F37*F8 -> 0 | G10: =G37*G8 -> 0 | H10: =SUM(B10:G10) -> 0 | J10: =H10*$H$4 -> 0
A11: Food Cost (DM) | B11: =IFERROR(B38*B8,0) -> 0 | C11: =IFERROR(C38*$C$8,0) -> 0 | D11: =IFERROR(D38*$D$8,0) -> 0 | E11: =IFERROR(E38*$E$8,0) -> 0 | F11: =IFERROR(F38*$F$8,0) -> 0 | G11: =IFERROR(G38*G8,0) -> 0 | H11: =SUM(B11:G11) -> 0 | I11: =I12*45% -> 0 | J11: =H11*$H$4 -> 0
A12: Wage Cost (DL) | B12: =IFERROR(B39*B8,0) -> 0 | C12: =IFERROR(C39*$C$8,0) -> 0 | D12: =IFERROR(D39*$D$8,0) -> 0 | E12: =IFERROR(E39*$E$8,0) -> 0 | F12: =IFERROR(F39*$F$8,0) -> 0 | G12: =IFERROR(G39*G8,0) -> 0 | H12: =SUM(B12:G12) -> 0 | I12: =H11+H12 -> 0 | J12: =H12*$H$4 -> 0
A13: Food Mark up | B13: =IFERROR(B40*B8," ") | C13: =IFERROR(C40*$C$8,0) -> 0 | D13: =IFERROR(D40*$D$8,0) -> 0 | E13: =IFERROR(E40*$E$8,0) -> 0 | F13: =IFERROR(F40*$F$8,0) -> 0 | G13: 0 | H13: =SUM(B13:G13) -> 0 | J13: =H13*$H$4 -> 0
A14: Labor Mark up | B14: =IFERROR(B41*B8," ") | C14: =IFERROR(C41*$C$8,0) -> 0 | D14: =IFERROR(D41*$D$8,0) -> 0 | E14: =IFERROR(E41*$E$8,0) -> 0 | F14: =IFERROR(F41*$F$8,0) -> 0 | G14: 0 | H14: =SUM(B14:G14) -> 0 | J14: =H14*$H$4 -> 0 | L14: Direct Labour
A15: Handling Cost | B15: 0 | C15: 0 | D15: 0 | E15: =+B20 -> 0 | F15: 0 | G15: 0 | H15: =SUM(B15:G15) -> 0 | J15: =H15*$H$4 -> 0 | L15: =J12+J15 -> 0 | M15: 1
A16: Handling Mark up | B16: 0 | C16: 0 | D16: 0 | E16: =+C20 -> 0 | F16: 0 | G16: 0 | H16: =SUM(B16:G16) -> 0 | J16: =H16*$H$4 -> 0 | L16: =L15*M16 -> 0 | M16: 0.8
A17: Total Per Flight | B17: =SUM(B11:B16) -> 0 | C17: =SUM(C11:C16) -> 0 | D17: =SUM(D10:D16) -> 0 | E17: =SUM(E10:E16) -> 0 | F17: =SUM(F10:F16) -> 0 | G17: =SUM(G10:G16) -> 0 | H17: =SUM(H10:H16) -> 0 | J17: =H17*$H$4 -> 0 | L17: =L15*M17 -> 0 | M17: 0.2
B18: =B17 -> 0 | C18: =C17 -> 0 | D18: =D17 -> 0 | E18: =E17-E15-E16 -> 0 | F18: =F17 -> 0 | G18: =G17 -> 0 | I18: =E15+E16 -> 0
A19: Handling | B19: Cost | C19: Mark Up | D19: Price | I19: =E16 -> 0
A20: 738 Handling | B20: =Handling!C56 -> 0 | C20: =B20*'P&L'!$R$10 -> 0 | D20: =SUM(B20:C20) -> 0
A21: B777 Handling | B21: =Handling!#REF! -> #REF! | C21: =Handling!#REF! -> #REF! | D21: =Handling!#REF! -> #REF!
A22: A380 Handling | B22: =Handling!#REF! -> #REF! | C22: =Handling!#REF! -> #REF! | D22: =Handling!#REF! -> #REF!
A24: Avg Price Per Pax | B24: =IFERROR(((B11+B12+B13+B14)/B8),0) -> 0 | C24: =IFERROR(((C11+C12+C13+C14)/C8),0) -> 0 | D24: =IFERROR(((D10+D11+D12+D13+D14)/D8),0) -> 0 | E24: =IFERROR(((E10+E11+E12+E13+E14)/E8),0) -> 0 | F24: =IFERROR(((F10+F11+F12+F13+F14)/F8),0) -> 0 | G24: =IFERROR(((G10+G11+G12+G13+G14)/G8),0) -> 0
A25: Avg Mark up Per Pax | B25: =IFERROR(((B13+B14)/B8),0) -> 0 | C25: =IFERROR(((C13+C14)/C8),0) -> 0 | D25: =IFERROR(((D13+D14)/D8),0) -> 0 | E25: =IFERROR(((E13+E14)/E8),0) -> 0 | F25: =IFERROR(((F13+F14)/F8),0) -> 0 | G25: =IFERROR(((G13+G14)/G8),0) -> 0
A26: Over head Per Pax | B26: =IFERROR((B10/B8),0) -> 0 | C26: =IFERROR((C10/C8),0) -> 0 | D26: =IFERROR((D10/D8),0) -> 0 | E26: =IFERROR((E10/E8),0) -> 0 | F26: =IFERROR((F10/F8),0) -> 0 | G26: =IFERROR((G10/G8),0) -> 0
B28: CYCLE | C28: FLT
A29: Config | B29: ='P&L'!R5 -> 1 | C29: 2439
A30: OVERHEAD | B30: =B37*B8 -> 0 | C30: =C37*C8 -> 0 | D30: =D37*D8 -> 0 | E30: =E37*E8 -> 0 | F30: =F37*F8 -> 0 | G30: =G37*G8 -> 0
A31: Food Cost (DM) | B31: =IFERROR(IF($B$29=$B$29,SUMIF(Food!$C:$C,B$9&$B$29&$C$29,Food!$X:$X),0),"") -> 0 | C31: =IFERROR(IF($B$29=$B$29,SUMIF(Food!$C:$C,C$9&$B$29&$C$29,Food!$X:$X),0),"") -> 0 | D31: =IFERROR(IF($B$29=$B$29,SUMIF(Food!$C:$C,D$9&$B$29&$C$29,Food!$X:$X),0),"") -> 0 | E31: =IFERROR(IF($B$29=$B$29,SUMIF(Food!$C:$C,E$9&$B$29&$C$29,Food!$X:$X),0),"") -> 0 | F31: =IFERROR(IF($B$29=$B$29,SUMIF(Food!$C:$C,F$9&$B$29&$C$29,Food!$X:$X),0),"") -> 0 | G31: =IFERROR(IF($B$29=$B$29,SUMIF(Food!$C:$C,G$9&$B$29&$C$29,Food!$X:$X),0),"") -> 0
A32: Wage Cost (DL) | B32: =IFERROR(IF($B$29=$B$29,SUMIF(Food!$C:$C,B$9&$B$29&$C$29,Food!$Z:$Z),0),"") -> 0 | C32: =IFERROR(IF($B$29=$B$29,SUMIF(Food!$C:$C,C$9&$B$29&$C$29,Food!$Z:$Z),0),"") -> 0 | D32: =IFERROR(IF($B$29=$B$29,SUMIF(Food!$C:$C,D$9&$B$29&$C$29,Food!$Z:$Z),0),"") -> 0 | E32: =IFERROR(IF($B$29=$B$29,SUMIF(Food!$C:$C,E$9&$B$29&$C$29,Food!$Z:$Z),0),"") -> 0 | F32: =IFERROR(IF($B$29=$B$29,SUMIF(Food!$C:$C,F$9&$B$29&$C$29,Food!$Z:$Z),0),"") -> 0 | G32: =IFERROR(IF($B$29=$B$29,SUMIF(Food!$C:$C,G$9&$B$29&$C$29,Food!$Z:$Z),0),"") -> 0
A33: Markup Food | B33: =IFERROR(IF($B$29=$B$29,SUMIF(Food!$C:$C,B$9&$B$29&$C$29,Food!$AB:$AB),0),"") -> 0 | C33: =IFERROR(IF($B$29=$B$29,SUMIF(Food!$C:$C,C$9&$B$29&$C$29,Food!$AB:$AB),0),"") -> 0 | D33: =IFERROR(IF($B$29=$B$29,SUMIF(Food!$C:$C,D$9&$B$29&$C$29,Food!$AB:$AB),0),"") -> 0 | E33: =IFERROR(IF($B$29=$B$29,SUMIF(Food!$C:$C,E$9&$B$29&$C$29,Food!$AB:$AB),0),"") -> 0 | F33: =IFERROR(IF($B$29=$B$29,SUMIF(Food!$C:$C,F$9&$B$29&$C$29,Food!$AB:$AB),0),"") -> 0 | G33: =IFERROR(IF($B$29=$B$29,SUMIF(Food!$C:$C,G$9&$B$29&$C$29,Food!$O:$O),0),"") -> 0
A34: Markup Labor | B34: =IFERROR(IF($B$29=$B$29,SUMIF(Food!$C:$C,B$9&$B$29&$C$29,Food!$AC:$AC),0),"") -> 0 | C34: =IFERROR(IF($B$29=$B$29,SUMIF(Food!$C:$C,C$9&$B$29&$C$29,Food!$AC:$AC),0),"") -> 0 | D34: =IFERROR(IF($B$29=$B$29,SUMIF(Food!$C:$C,D$9&$B$29&$C$29,Food!$AC:$AC),0),"") -> 0 | E34: =IFERROR(IF($B$29=$B$29,SUMIF(Food!$C:$C,E$9&$B$29&$C$29,Food!$AC:$AC),0),"") -> 0 | F34: =IFERROR(IF($B$29=$B$29,SUMIF(Food!$C:$C,F$9&$B$29&$C$29,Food!$AC:$AC),0),"") -> 0 | G34: =IFERROR(IF($B$29=$B$29,SUMIF(Food!$C:$C,G$9&$B$29&$C$29,Food!$P:$P),0),"") -> 0
A36: Per Pax Avg
A37: OVERHEAD | B37: ='P&L'!$K$30 -> 0 | C37: ='P&L'!$L$30 -> 0 | D37: ='P&L'!$M$30 -> 0 | E37: ='P&L'!$N$30 -> 0 | F37: ='P&L'!$O$30 -> 0 | G37: ='P&L'!$P$30 -> 0
A38: Food Cost (DM) | B38: =IFERROR(B31/B7," ") | C38: =IFERROR(C31/C7," ") -> 0 | D38: =IFERROR(D31/D7," ") -> 0 | E38: =IFERROR(E31/E7," ") -> 0 | F38: =IFERROR(F31/F7," ") | G38: =IFERROR(G31/G7," ") -> 0
A39: Wage Cost (DL) | B39: =IFERROR(B32/B7," ") | C39: =IFERROR(C32/C7," ") -> 0 | D39: =IFERROR(D32/D7," ") -> 0 | E39: =IFERROR(E32/E7," ") -> 0 | F39: =IFERROR(F32/F7," ") | G39: =IFERROR(G32/G7," ") -> 0
A40: Markup Food | B40: =IFERROR(B33/B8," ") | C40: =IFERROR(C33/C7," ") -> 0 | D40: =IFERROR(D33/D7," ") -> 0 | E40: =IFERROR(E33/E7," ") -> 0 | F40: =IFERROR(F33/F7," ") | G40: =IFERROR(G33/G7," ") -> 0
A41: Markup Labor | B41: =IFERROR(B34/B7," ") | C41: =IFERROR(C34/C7," ") -> 0 | D41: =IFERROR(D34/D7," ") -> 0 | E41: =IFERROR(E34/E7," ") -> 0 | F41: =IFERROR(F34/F7," ") | G41: =IFERROR(G34/G7," ") -> 0
A108: 388
A109: 787

Sheet Summary 2682
A2: Customer | G2: Flights Per week | H2: 0 | L2: AC type | M2: Cycle
E3: AC Type | F3: 738 | G3: Flights Per Month | H3: =H4/12 -> 0 | J3: Total Revenues | L3: 737 | M3: 1
E4: Load | F4: ='P&L'!R4 -> 0.85 | G4: Annual Flights | H4: =H2*52 -> 0 | J4: =H17*H4 -> 0
A5: Summary
A6: BNA | B6: FC | C6: BC | D6: PY | E6: EY | F6: TC | G6: CY | H6: Total | I6: Hnd
A7: FLIGHT CONFIG | B7: =+'FlightConfig '!B17 -> 0 | C7: =+'FlightConfig '!C17 -> 34 | D7: =+'FlightConfig '!D17 -> 48 | E7: =+'FlightConfig '!E17 -> 198 | F7: =+'FlightConfig '!F17 -> 0 | G7: =+'FlightConfig '!G17 -> 6 | H7: =SUM(B7:G7) -> 286
A8: Load Factor | B8: =ROUNDUP(B7*$F$4,0) -> 0 | C8: =ROUNDUP(C7*$F$4,0) -> 29 | D8: =ROUNDUP(D7*$F$4,0) -> 41 | E8: =ROUNDUP(E7*$F$4,0) -> 169 | F8: =ROUNDUP(F7*$F$4,0) -> 0 | G8: =ROUNDUP(G7*$F$4,0) -> 6 | H8: =SUM(B8:G8) -> 245
B9: FIRST CLASS | C9: BUSINESS CLASS | D9: PREMIUM ECONOMY CLASS | E9: ECONOMY CLASS | F9: TECH CREW CLASS | G9: cABIN CREW CLASS | H9: Per Flight | J9: Annual
A10: OVERHEAD | B10: =B37*B8 -> 0 | C10: =C37*C8 -> 0 | D10: =D37*D8 -> 0 | E10: =E37*E8 -> 0 | F10: =F37*F8 -> 0 | G10: =G37*G8 -> 0 | H10: =SUM(B10:G10) -> 0 | J10: =H10*$H$4 -> 0
A11: Food Cost (DM) | B11: =IFERROR(B38*B8,0) -> 0 | C11: =IFERROR(C38*$C$8,0) -> 0 | D11: =IFERROR(D38*$D$8,0) -> 0 | E11: =IFERROR(E38*$E$8,0) -> 0 | F11: =IFERROR(F38*$F$8,0) -> 0 | G11: =IFERROR(G38*G8,0) -> 0 | H11: =SUM(B11:G11) -> 0 | I11: =I12*45% -> 0 | J11: =H11*$H$4 -> 0
A12: Wage Cost (DL) | B12: =IFERROR(B39*B8,0) -> 0 | C12: =IFERROR(C39*$C$8,0) -> 0 | D12: =IFERROR(D39*$D$8,0) -> 0 | E12: =IFERROR(E39*$E$8,0) -> 0 | F12: =IFERROR(F39*$F$8,0) -> 0 | G12: =IFERROR(G39*G8,0) -> 0 | H12: =SUM(B12:G12) -> 0 | I12: =H11+H12 -> 0 | J12: =H12*$H$4 -> 0
A13: Food Mark up | B13: =IFERROR(B40*B8," ") | C13: =IFERROR(C40*$C$8,0) -> 0 | D13: =IFERROR(D40*$D$8,0) -> 0 | E13: =IFERROR(E40*$E$8,0) -> 0 | F13: =IFERROR(F40*$F$8,0) -> 0 | G13: 0 | H13: =SUM(B13:G13) -> 0 | J13: =H13*$H$4 -> 0
A14: Labor Mark up | B14: =IFERROR(B41*B8," ") | C14: =IFERROR(C41*$C$8,0) -> 0 | D14: =IFERROR(D41*$D$8,0) -> 0 | E14: =IFERROR(E41*$E$8,0) -> 0 | F14: =IFERROR(F41*$F$8,0) -> 0 | G14: 0 | H14: =SUM(B14:G14) -> 0 | J14: =H14*$H$4 -> 0 | L14: Direct Labour
A15: Handling Cost | B15: 0 | C15: 0 | D15: 0 | E15: =+B20 -> 0 | F15: 0 | G15: 0 | H15: =SUM(B15:G15) -> 0 | J15: =H15*$H$4 -> 0 | L15: =J12+J15 -> 0 | M15: 1
A16: Handling Mark up | B16: 0 | C16: 0 | D16: 0 | E16: =+C20 -> 0 | F16: 0 | G16: 0 | H16: =SUM(B16:G16) -> 0 | J16: =H16*$H$4 -> 0 | L16: =L15*M16 -> 0 | M16: 0.8
A17: Total Per Flight | B17: =SUM(B11:B16) -> 0 | C17: =SUM(C11:C16) -> 0 | D17: =SUM(D10:D16) -> 0 | E17: =SUM(E10:E16) -> 0 | F17: =SUM(F10:F16) -> 0 | G17: =SUM(G10:G16) -> 0 | H17: =SUM(H10:H16) -> 0 | J17: =H17*$H$4 -> 0 | L17: =L15*M17 -> 0 | M17: 0.2
B18: =B17 -> 0 | C18: =C17 -> 0 | D18: =D17 -> 0 | E18: =E17-E15-E16 -> 0 | F18: =F17 -> 0 | G18: =G17 -> 0 | I18: =E15+E16 -> 0
A19: Handling | B19: Cost | C19: Mark Up | D19: Price | I19: =E16 -> 0
A20: 738 Handling | B20: =Handling!C56 -> 0 | C20: =B20*'P&L'!$R$10 -> 0 | D20: =SUM(B20:C20) -> 0
A21: B777 Handling | B21: =Handling!#REF! -> #REF! | C21: =Handling!#REF! -> #REF! | D21: =Handling!#REF! -> #REF!
A22: A380 Handling | B22: =Handling!#REF! -> #REF! | C22: =Handling!#REF! -> #REF! | D22: =Handling!#REF! -> #REF!
A24: Avg Price Per Pax | B24: =IFERROR(((B11+B12+B13+B14)/B8),0) -> 0 | C24: =IFERROR(((C11+C12+C13+C14)/C8),0) -> 0 | D24: =IFERROR(((D10+D11+D12+D13+D14)/D8),0) -> 0 | E24: =IFERROR(((E10+E11+E12+E13+E14)/E8),0) -> 0 | F24: =IFERROR(((F10+F11+F12+F13+F14)/F8),0) -> 0 | G24: =IFERROR(((G10+G11+G12+G13+G14)/G8),0) -> 0
A25: Avg Mark up Per Pax | B25: =IFERROR(((B13+B14)/B8),0) -> 0 | C25: =IFERROR(((C13+C14)/C8),0) -> 0 | D25: =IFERROR(((D13+D14)/D8),0) -> 0 | E25: =IFERROR(((E13+E14)/E8),0) -> 0 | F25: =IFERROR(((F13+F14)/F8),0) -> 0 | G25: =IFERROR(((G13+G14)/G8),0) -> 0
A26: Over head Per Pax | B26: =IFERROR((B10/B8),0) -> 0 | C26: =IFERROR((C10/C8),0) -> 0 | D26: =IFERROR((D10/D8),0) -> 0 | E26: =IFERROR((E10/E8),0) -> 0 | F26: =IFERROR((F10/F8),0) -> 0 | G26: =IFERROR((G10/G8),0) -> 0
B28: CYCLE | C28: FLT
A29: Config | B29: ='P&L'!R5 -> 1 | C29: 2682
A30: OVERHEAD | B30: =B37*B8 -> 0 | C30: =C37*C8 -> 0 | D30: =D37*D8 -> 0 | E30: =E37*E8 -> 0 | F30: =F37*F8 -> 0 | G30: =G37*G8 -> 0
A31: Food Cost (DM) | B31: =IFERROR(IF($B$29=$B$29,SUMIF(Food!$C:$C,B$9&$B$29&$C$29,Food!$X:$X),0),"") -> 0 | C31: =IFERROR(IF($B$29=$B$29,SUMIF(Food!$C:$C,C$9&$B$29&$C$29,Food!$X:$X),0),"") -> 0 | D31: =IFERROR(IF($B$29=$B$29,SUMIF(Food!$C:$C,D$9&$B$29&$C$29,Food!$X:$X),0),"") -> 0 | E31: =IFERROR(IF($B$29=$B$29,SUMIF(Food!$C:$C,E$9&$B$29&$C$29,Food!$X:$X),0),"") -> 0 | F31: =IFERROR(IF($B$29=$B$29,SUMIF(Food!$C:$C,F$9&$B$29&$C$29,Food!$X:$X),0),"") -> 0 | G31: =IFERROR(IF($B$29=$B$29,SUMIF(Food!$C:$C,G$9&$B$29&$C$29,Food!$X:$X),0),"") -> 0
A32: Wage Cost (DL) | B32: =IFERROR(IF($B$29=$B$29,SUMIF(Food!$C:$C,B$9&$B$29&$C$29,Food!$Z:$Z),0),"") -> 0 | C32: =IFERROR(IF($B$29=$B$29,SUMIF(Food!$C:$C,C$9&$B$29&$C$29,Food!$Z:$Z),0),"") -> 0 | D32: =IFERROR(IF($B$29=$B$29,SUMIF(Food!$C:$C,D$9&$B$29&$C$29,Food!$Z:$Z),0),"") -> 0 | E32: =IFERROR(IF($B$29=$B$29,SUMIF(Food!$C:$C,E$9&$B$29&$C$29,Food!$Z:$Z),0),"") -> 0 | F32: =IFERROR(IF($B$29=$B$29,SUMIF(Food!$C:$C,F$9&$B$29&$C$29,Food!$Z:$Z),0),"") -> 0 | G32: =IFERROR(IF($B$29=$B$29,SUMIF(Food!$C:$C,G$9&$B$29&$C$29,Food!$Z:$Z),0),"") -> 0
A33: Markup Food | B33: =IFERROR(IF($B$29=$B$29,SUMIF(Food!$C:$C,B$9&$B$29&$C$29,Food!$AB:$AB),0),"") -> 0 | C33: =IFERROR(IF($B$29=$B$29,SUMIF(Food!$C:$C,C$9&$B$29&$C$29,Food!$AB:$AB),0),"") -> 0 | D33: =IFERROR(IF($B$29=$B$29,SUMIF(Food!$C:$C,D$9&$B$29&$C$29,Food!$AB:$AB),0),"") -> 0 | E33: =IFERROR(IF($B$29=$B$29,SUMIF(Food!$C:$C,E$9&$B$29&$C$29,Food!$AB:$AB),0),"") -> 0 | F33: =IFERROR(IF($B$29=$B$29,SUMIF(Food!$C:$C,F$9&$B$29&$C$29,Food!$AB:$AB),0),"") -> 0 | G33: =IFERROR(IF($B$29=$B$29,SUMIF(Food!$C:$C,G$9&$B$29&$C$29,Food!$O:$O),0),"") -> 0
A34: Markup Labor | B34: =IFERROR(IF($B$29=$B$29,SUMIF(Food!$C:$C,B$9&$B$29&$C$29,Food!$AC:$AC),0),"") -> 0 | C34: =IFERROR(IF($B$29=$B$29,SUMIF(Food!$C:$C,C$9&$B$29&$C$29,Food!$AC:$AC),0),"") -> 0 | D34: =IFERROR(IF($B$29=$B$29,SUMIF(Food!$C:$C,D$9&$B$29&$C$29,Food!$AC:$AC),0),"") -> 0 | E34: =IFERROR(IF($B$29=$B$29,SUMIF(Food!$C:$C,E$9&$B$29&$C$29,Food!$AC:$AC),0),"") -> 0 | F34: =IFERROR(IF($B$29=$B$29,SUMIF(Food!$C:$C,F$9&$B$29&$C$29,Food!$AC:$AC),0),"") -> 0 | G34: =IFERROR(IF($B$29=$B$29,SUMIF(Food!$C:$C,G$9&$B$29&$C$29,Food!$P:$P),0),"") -> 0
A36: Per Pax Avg
A37: OVERHEAD | B37: ='P&L'!$K$30 -> 0 | C37: ='P&L'!$L$30 -> 0 | D37: ='P&L'!$M$30 -> 0 | E37: ='P&L'!$N$30 -> 0 | F37: ='P&L'!$O$30 -> 0 | G37: ='P&L'!$P$30 -> 0
A38: Food Cost (DM) | B38: =IFERROR(B31/B7," ") | C38: =IFERROR(C31/C7," ") -> 0 | D38: =IFERROR(D31/D7," ") -> 0 | E38: =IFERROR(E31/E7," ") -> 0 | F38: =IFERROR(F31/F7," ") | G38: =IFERROR(G31/G7," ") -> 0
A39: Wage Cost (DL) | B39: =IFERROR(B32/B7," ") | C39: =IFERROR(C32/C7," ") -> 0 | D39: =IFERROR(D32/D7," ") -> 0 | E39: =IFERROR(E32/E7," ") -> 0 | F39: =IFERROR(F32/F7," ") | G39: =IFERROR(G32/G7," ") -> 0
A40: Markup Food | B40: =IFERROR(B33/B8," ") | C40: =IFERROR(C33/C7," ") -> 0 | D40: =IFERROR(D33/D7," ") -> 0 | E40: =IFERROR(E33/E7," ") -> 0 | F40: =IFERROR(F33/F7," ") | G40: =IFERROR(G33/G7," ") -> 0
A41: Markup Labor | B41: =IFERROR(B34/B7," ") | C41: =IFERROR(C34/C7," ") -> 0 | D41: =IFERROR(D34/D7," ") -> 0 | E41: =IFERROR(E34/E7," ") -> 0 | F41: =IFERROR(F34/F7," ") | G41: =IFERROR(G34/G7," ") -> 0
A108: 388
A109: 787

Sheet Summary 2855
A2: Customer | G2: Flights Per week | H2: 0 | L2: AC type | M2: Cycle
E3: AC Type | F3: 738 | G3: Flights Per Month | H3: =H4/12 -> 0 | J3: Total Revenues | L3: 737 | M3: 1
E4: Load | F4: ='P&L'!R4 -> 0.85 | G4: Annual Flights | H4: =H2*52 -> 0 | J4: =H17*H4 -> 0
A5: Summary
A6: BNA | B6: FC | C6: BC | D6: PY | E6: EY | F6: TC | G6: CY | H6: Total | I6: Hnd
A7: FLIGHT CONFIG | B7: =+'FlightConfig '!B17 -> 0 | C7: =+'FlightConfig '!C17 -> 34 | D7: =+'FlightConfig '!D17 -> 48 | E7: =+'FlightConfig '!E17 -> 198 | F7: =+'FlightConfig '!F17 -> 0 | G7: =+'FlightConfig '!G17 -> 6 | H7: =SUM(B7:G7) -> 286
A8: Load Factor | B8: =ROUNDUP(B7*$F$4,0) -> 0 | C8: =ROUNDUP(C7*$F$4,0) -> 29 | D8: =ROUNDUP(D7*$F$4,0) -> 41 | E8: =ROUNDUP(E7*$F$4,0) -> 169 | F8: =ROUNDUP(F7*$F$4,0) -> 0 | G8: =ROUNDUP(G7*$F$4,0) -> 6 | H8: =SUM(B8:G8) -> 245
B9: FIRST CLASS | C9: BUSINESS CLASS | D9: PREMIUM ECONOMY CLASS | E9: ECONOMY CLASS | F9: TECH CREW CLASS | G9: cABIN CREW CLASS | H9: Per Flight | J9: Annual
A10: OVERHEAD | B10: =B37*B8 -> 0 | C10: =C37*C8 -> 0 | D10: =D37*D8 -> 0 | E10: =E37*E8 -> 0 | F10: =F37*F8 -> 0 | G10: =G37*G8 -> 0 | H10: =SUM(B10:G10) -> 0 | J10: =H10*$H$4 -> 0
A11: Food Cost (DM) | B11: =IFERROR(B38*B8,0) -> 0 | C11: =IFERROR(C38*$C$8,0) -> 0 | D11: =IFERROR(D38*$D$8,0) -> 0 | E11: =IFERROR(E38*$E$8,0) -> 0 | F11: =IFERROR(F38*$F$8,0) -> 0 | G11: =IFERROR(G38*G8,0) -> 0 | H11: =SUM(B11:G11) -> 0 | I11: =I12*45% -> 0 | J11: =H11*$H$4 -> 0
A12: Wage Cost (DL) | B12: =IFERROR(B39*B8,0) -> 0 | C12: =IFERROR(C39*$C$8,0) -> 0 | D12: =IFERROR(D39*$D$8,0) -> 0 | E12: =IFERROR(E39*$E$8,0) -> 0 | F12: =IFERROR(F39*$F$8,0) -> 0 | G12: =IFERROR(G39*G8,0) -> 0 | H12: =SUM(B12:G12) -> 0 | I12: =H11+H12 -> 0 | J12: =H12*$H$4 -> 0
A13: Food Mark up | B13: =IFERROR(B40*B8," ") | C13: =IFERROR(C40*$C$8,0) -> 0 | D13: =IFERROR(D40*$D$8,0) -> 0 | E13: =IFERROR(E40*$E$8,0) -> 0 | F13: =IFERROR(F40*$F$8,0) -> 0 | G13: 0 | H13: =SUM(B13:G13) -> 0 | J13: =H13*$H$4 -> 0
A14: Labor Mark up | B14: =IFERROR(B41*B8," ") | C14: =IFERROR(C41*$C$8,0) -> 0 | D14: =IFERROR(D41*$D$8,0) -> 0 | E14: =IFERROR(E41*$E$8,0) -> 0 | F14: =IFERROR(F41*$F$8,0) -> 0 | G14: 0 | H14: =SUM(B14:G14) -> 0 | J14: =H14*$H$4 -> 0 | L14: Direct Labour
A15: Handling Cost | B15: 0 | C15: 0 | D15: 0 | E15: =+B20 -> 0 | F15: 0 | G15: 0 | H15: =SUM(B15:G15) -> 0 | J15: =H15*$H$4 -> 0 | L15: =J12+J15 -> 0 | M15: 1
A16: Handling Mark up | B16: 0 | C16: 0 | D16: 0 | E16: =+C20 -> 0 | F16: 0 | G16: 0 | H16: =SUM(B16:G16) -> 0 | J16: =H16*$H$4 -> 0 | L16: =L15*M16 -> 0 | M16: 0.8
A17: Total Per Flight | B17: =SUM(B11:B16) -> 0 | C17: =SUM(C11:C16) -> 0 | D17: =SUM(D10:D16) -> 0 | E17: =SUM(E10:E16) -> 0 | F17: =SUM(F10:F16) -> 0 | G17: =SUM(G10:G16) -> 0 | H17: =SUM(H10:H16) -> 0 | J17: =H17*$H$4 -> 0 | L17: =L15*M17 -> 0 | M17: 0.2
B18: =B17 -> 0 | C18: =C17 -> 0 | D18: =D17 -> 0 | E18: =E17-E15-E16 -> 0 | F18: =F17 -> 0 | G18: =G17 -> 0 | I18: =E15+E16 -> 0
A19: Handling | B19: Cost | C19: Mark Up | D19: Price | I19: =E16 -> 0
A20: 738 Handling | B20: =Handling!C56 -> 0 | C20: =B20*'P&L'!$R$10 -> 0 | D20: =SUM(B20:C20) -> 0
A21: B777 Handling | B21: =Handling!#REF! -> #REF! | C21: =Handling!#REF! -> #REF! | D21: =Handling!#REF! -> #REF!
A22: A380 Handling | B22: =Handling!#REF! -> #REF! | C22: =Handling!#REF! -> #REF! | D22: =Handling!#REF! -> #REF!
A24: Avg Price Per Pax | B24: =IFERROR(((B11+B12+B13+B14)/B8),0) -> 0 | C24: =IFERROR(((C11+C12+C13+C14)/C8),0) -> 0 | D24: =IFERROR(((D10+D11+D12+D13+D14)/D8),0) -> 0 | E24: =IFERROR(((E10+E11+E12+E13+E14)/E8),0) -> 0 | F24: =IFERROR(((F10+F11+F12+F13+F14)/F8),0) -> 0 | G24: =IFERROR(((G10+G11+G12+G13+G14)/G8),0) -> 0
A25: Avg Mark up Per Pax | B25: =IFERROR(((B13+B14)/B8),0) -> 0 | C25: =IFERROR(((C13+C14)/C8),0) -> 0 | D25: =IFERROR(((D13+D14)/D8),0) -> 0 | E25: =IFERROR(((E13+E14)/E8),0) -> 0 | F25: =IFERROR(((F13+F14)/F8),0) -> 0 | G25: =IFERROR(((G13+G14)/G8),0) -> 0
A26: Over head Per Pax | B26: =IFERROR((B10/B8),0) -> 0 | C26: =IFERROR((C10/C8),0) -> 0 | D26: =IFERROR((D10/D8),0) -> 0 | E26: =IFERROR((E10/E8),0) -> 0 | F26: =IFERROR((F10/F8),0) -> 0 | G26: =IFERROR((G10/G8),0) -> 0
B28: CYCLE | C28: FLT
A29: Config | B29: ='P&L'!R5 -> 1 | C29: 2855
A30: OVERHEAD | B30: =B37*B8 -> 0 | C30: =C37*C8 -> 0 | D30: =D37*D8 -> 0 | E30: =E37*E8 -> 0 | F30: =F37*F8 -> 0 | G30: =G37*G8 -> 0
A31: Food Cost (DM) | B31: =IFERROR(IF($B$29=$B$29,SUMIF(Food!$C:$C,B$9&$B$29&$C$29,Food!$X:$X),0),"") -> 0 | C31: =IFERROR(IF($B$29=$B$29,SUMIF(Food!$C:$C,C$9&$B$29&$C$29,Food!$X:$X),0),"") -> 0 | D31: =IFERROR(IF($B$29=$B$29,SUMIF(Food!$C:$C,D$9&$B$29&$C$29,Food!$X:$X),0),"") -> 0 | E31: =IFERROR(IF($B$29=$B$29,SUMIF(Food!$C:$C,E$9&$B$29&$C$29,Food!$X:$X),0),"") -> 0 | F31: =IFERROR(IF($B$29=$B$29,SUMIF(Food!$C:$C,F$9&$B$29&$C$29,Food!$X:$X),0),"") -> 0 | G31: =IFERROR(IF($B$29=$B$29,SUMIF(Food!$C:$C,G$9&$B$29&$C$29,Food!$X:$X),0),"") -> 0
A32: Wage Cost (DL) | B32: =IFERROR(IF($B$29=$B$29,SUMIF(Food!$C:$C,B$9&$B$29&$C$29,Food!$Z:$Z),0),"") -> 0 | C32: =IFERROR(IF($B$29=$B$29,SUMIF(Food!$C:$C,C$9&$B$29&$C$29,Food!$Z:$Z),0),"") -> 0 | D32: =IFERROR(IF($B$29=$B$29,SUMIF(Food!$C:$C,D$9&$B$29&$C$29,Food!$Z:$Z),0),"") -> 0 | E32: =IFERROR(IF($B$29=$B$29,SUMIF(Food!$C:$C,E$9&$B$29&$C$29,Food!$Z:$Z),0),"") -> 0 | F32: =IFERROR(IF($B$29=$B$29,SUMIF(Food!$C:$C,F$9&$B$29&$C$29,Food!$Z:$Z),0),"") -> 0 | G32: =IFERROR(IF($B$29=$B$29,SUMIF(Food!$C:$C,G$9&$B$29&$C$29,Food!$Z:$Z),0),"") -> 0
A33: Markup Food | B33: =IFERROR(IF($B$29=$B$29,SUMIF(Food!$C:$C,B$9&$B$29&$C$29,Food!$AB:$AB),0),"") -> 0 | C33: =IFERROR(IF($B$29=$B$29,SUMIF(Food!$C:$C,C$9&$B$29&$C$29,Food!$AB:$AB),0),"") -> 0 | D33: =IFERROR(IF($B$29=$B$29,SUMIF(Food!$C:$C,D$9&$B$29&$C$29,Food!$AB:$AB),0),"") -> 0 | E33: =IFERROR(IF($B$29=$B$29,SUMIF(Food!$C:$C,E$9&$B$29&$C$29,Food!$AB:$AB),0),"") -> 0 | F33: =IFERROR(IF($B$29=$B$29,SUMIF(Food!$C:$C,F$9&$B$29&$C$29,Food!$AB:$AB),0),"") -> 0 | G33: =IFERROR(IF($B$29=$B$29,SUMIF(Food!$C:$C,G$9&$B$29&$C$29,Food!$O:$O),0),"") -> 0
A34: Markup Labor | B34: =IFERROR(IF($B$29=$B$29,SUMIF(Food!$C:$C,B$9&$B$29&$C$29,Food!$AC:$AC),0),"") -> 0 | C34: =IFERROR(IF($B$29=$B$29,SUMIF(Food!$C:$C,C$9&$B$29&$C$29,Food!$AC:$AC),0),"") -> 0 | D34: =IFERROR(IF($B$29=$B$29,SUMIF(Food!$C:$C,D$9&$B$29&$C$29,Food!$AC:$AC),0),"") -> 0 | E34: =IFERROR(IF($B$29=$B$29,SUMIF(Food!$C:$C,E$9&$B$29&$C$29,Food!$AC:$AC),0),"") -> 0 | F34: =IFERROR(IF($B$29=$B$29,SUMIF(Food!$C:$C,F$9&$B$29&$C$29,Food!$AC:$AC),0),"") -> 0 | G34: =IFERROR(IF($B$29=$B$29,SUMIF(Food!$C:$C,G$9&$B$29&$C$29,Food!$P:$P),0),"") -> 0
A36: Per Pax Avg
A37: OVERHEAD | B37: ='P&L'!$K$30 -> 0 | C37: ='P&L'!$L$30 -> 0 | D37: ='P&L'!$M$30 -> 0 | E37: ='P&L'!$N$30 -> 0 | F37: ='P&L'!$O$30 -> 0 | G37: ='P&L'!$P$30 -> 0
A38: Food Cost (DM) | B38: =IFERROR(B31/B7," ") | C38: =IFERROR(C31/C7," ") -> 0 | D38: =IFERROR(D31/D7," ") -> 0 | E38: =IFERROR(E31/E7," ") -> 0 | F38: =IFERROR(F31/F7," ") | G38: =IFERROR(G31/G7," ") -> 0
A39: Wage Cost (DL) | B39: =IFERROR(B32/B7," ") | C39: =IFERROR(C32/C7," ") -> 0 | D39: =IFERROR(D32/D7," ") -> 0 | E39: =IFERROR(E32/E7," ") -> 0 | F39: =IFERROR(F32/F7," ") | G39: =IFERROR(G32/G7," ") -> 0
A40: Markup Food | B40: =IFERROR(B33/B8," ") | C40: =IFERROR(C33/C7," ") -> 0 | D40: =IFERROR(D33/D7," ") -> 0 | E40: =IFERROR(E33/E7," ") -> 0 | F40: =IFERROR(F33/F7," ") | G40: =IFERROR(G33/G7," ") -> 0
A41: Markup Labor | B41: =IFERROR(B34/B7," ") | C41: =IFERROR(C34/C7," ") -> 0 | D41: =IFERROR(D34/D7," ") -> 0 | E41: =IFERROR(E34/E7," ") -> 0 | F41: =IFERROR(F34/F7," ") | G41: =IFERROR(G34/G7," ") -> 0
A108: 388
A109: 787

Sheet Summary FLT104
A2: Customer | G2: Flights Per week | H2: 7 | L2: AC type | M2: Cycle
E3: AC Type | F3: 738 | G3: Flights Per Month | H3: =H4/12 -> 30.333333 | J3: Total Revenues | L3: 737 | M3: 1
E4: Load | F4: ='P&L'!R4 -> 0.85 | G4: Annual Flights | H4: =H2*52 -> 364 | J4: =H17*H4 -> 2396534.2
A5: Summary
A6: BNA | B6: FC | C6: BC | D6: PY | E6: EY | F6: TC | G6: CY | H6: Total | I6: Hnd
A7: FLIGHT CONFIG | B7: =+'FlightConfig '!B17 -> 0 | C7: =+'FlightConfig '!C17 -> 34 | D7: =+'FlightConfig '!D17 -> 48 | E7: =+'FlightConfig '!E17 -> 198 | F7: =+'FlightConfig '!F17 -> 0 | G7: =+'FlightConfig '!G17 -> 6 | H7: =SUM(B7:G7) -> 286
A8: Load Factor | B8: =ROUNDUP(B7*$F$4,0) -> 0 | C8: =ROUNDUP(C7*$F$4,0) -> 29 | D8: =ROUNDUP(D7*$F$4,0) -> 41 | E8: =ROUNDUP(E7*$F$4,0) -> 169 | F8: =ROUNDUP(F7*$F$4,0) -> 0 | G8: =ROUNDUP(G7*$F$4,0) -> 6 | H8: =SUM(B8:G8) -> 245
B9: FIRST CLASS | C9: BUSINESS CLASS | D9: PREMIUM ECONOMY CLASS | E9: ECONOMY CLASS | F9: TECH CREW CLASS | G9: CABIN CREW CLASS | H9: Per Flight | J9: Annual
A10: OVERHEAD | B10: =B37*B8 -> 0 | C10: =C37*C8 -> 0 | D10: =D37*D8 -> 0 | E10: =E37*E8 -> 0 | F10: =F37*F8 -> 0 | G10: =G37*G8 -> 0 | H10: =SUM(B10:G10) -> 0 | J10: =H10*$H$4 -> 0
A11: Food Cost (DM) | B11: =IFERROR(B38*B8,0) -> 0 | C11: =IFERROR(C38*$C$8,0) -> 753.10893 | D11: =IFERROR(D38*$D$8,0) -> 603.06413 | E11: =IFERROR(E38*$E$8,0) -> 1412.0521 | F11: =IFERROR(F38*$F$8,0) -> 0 | G11: =IFERROR(G38*G8,0) -> 78.972 | H11: =SUM(B11:G11) -> 2847.1972 | I11: =I12*45% -> 1915.4493 | J11: =H11*$H$4 -> 1036379.8
A12: Wage Cost (DL) | B12: =IFERROR(B39*B8,0) -> 0 | C12: =IFERROR(C39*$C$8,0) -> 237.00676 | D12: =IFERROR(D39*$D$8,0) -> 319.8 | E12: =IFERROR(E39*$E$8,0) -> 823.03 | F12: =IFERROR(F39*$F$8,0) -> 0 | G12: =IFERROR(G39*G8,0) -> 29.52 | H12: =SUM(B12:G12) -> 1409.3568 | I12: =H11+H12 -> 4256.5539 | J12: =H12*$H$4 -> 513005.86
A13: Food Mark up | B13: =IFERROR(B40*B9,0) -> 0 | C13: =IFERROR(C40*$C$8,0) -> 112.96634 | D13: =IFERROR(D40*$D$8,0) -> 90.45962 | E13: =IFERROR(E40*$E$8,0) -> 211.80781 | F13: =IFERROR(F40*$F$8,0) -> 0 | G13: =IFERROR(G40*$G$8,0) -> 11.8458 | H13: =SUM(B13:G13) -> 427.07957 | J13: =H13*$H$4 -> 155456.96
A14: Labor Mark up | B14: =IFERROR(B41*B10,0) -> 0 | C14: =IFERROR(C41*$C$8,0) -> 35.551015 | D14: =IFERROR(D41*$D$8,0) -> 47.97 | E14: =IFERROR(E41*$E$8,0) -> 123.4545 | F14: =IFERROR(F41*$F$8,0) -> 0 | G14: =IFERROR(G41*$G$8,0) -> 4.428 | H14: =SUM(B14:G14) -> 211.40351 | J14: =H14*$H$4 -> 76950.879 | L14: Direct Labour
A15: Handling Cost | B15: 0 | C15: 0 | D15: 0 | E15: =+B20 -> 1494.556 | F15: 0 | G15: =IFERROR(G42*$G$8,0) -> 0 | H15: =SUM(B15:G15) -> 1494.556 | J15: =H15*$H$4 -> 544018.38 | L15: =J12+J15 -> 1057024.2 | M15: 1
A16: Handling Mark up | B16: 0 | C16: 0 | D16: 0 | E16: =+C20 -> 194.29228 | F16: 0 | G16: =IFERROR(G43*$G$8,0) -> 0 | H16: =SUM(B16:G16) -> 194.29228 | J16: =H16*$H$4 -> 70722.39 | L16: =L15*M16 -> 845619.4 | M16: 0.8
A17: Total Per Flight | B17: =SUM(B11:B16) -> 0 | C17: =SUM(C11:C16) -> 1138.633 | D17: =SUM(D10:D16) -> 1061.2938 | E17: =SUM(E10:E16) -> 4259.1927 | F17: =SUM(F10:F16) -> 0 | G17: =SUM(G10:G16) -> 124.7658 | H17: =SUM(H10:H16) -> 6583.8853 | J17: =H17*$H$4 -> 2396534.2 | L17: =L15*M17 -> 211404.85 | M17: 0.2
B18: =B17 -> 0 | C18: =C17 -> 1138.633 | D18: =D17 -> 1061.2938 | E18: =E17-E15-E16 -> 2570.3444 | F18: =F17 -> 0 | G18: =G17 -> 124.7658 | I18: =E15+E16 -> 1688.8483
A19: Handling | B19: Cost | C19: Mark Up | D19: Price | I19: =E16 -> 194.29228 | J19: =H11+H12+H15 -> 5751.1099
A20: 738 Handling | B20: =Handling!C83+Handling!S39+Handling!S45+Handling!V53+Handling!AD39 -> 1494.556 | C20: =B20*'P&L'!$R$10 -> 194.29228 | D20: =SUM(B20:C20) -> 1688.8483 | J20: =H13+H14+H16 -> 832.77537
A21: B777 Handling | B21: =Handling!#REF! -> #REF! | C21: =Handling!#REF! -> #REF! | D21: =Handling!#REF! -> #REF!
A22: A380 Handling | B22: =Handling!#REF! -> #REF! | C22: =Handling!#REF! -> #REF! | D22: =Handling!#REF! -> #REF!
A24: Avg Price Per Pax | B24: =IFERROR(((B11+B12+B13+B14)/B8),0) -> 0 | C24: =IFERROR(((C11+C12+C13+C14)/C8),0) -> 39.263208 | D24: =IFERROR(((D10+D11+D12+D13+D14)/D8),0) -> 25.885213 | E24: =IFERROR(((E10+E11+E12+E13+E14)/E8),0) -> 15.209139 | F24: =IFERROR(((F10+F11+F12+F13+F14)/F8),0) -> 0 | G24: =IFERROR(((G10+G11+G12+G13+G14)/G8),0) -> 20.7943
A25: Avg Mark up Per Pax | B25: =IFERROR(((B13+B14)/B8),0) -> 0 | C25: =IFERROR(((C13+C14)/C8),0) -> 5.1212881 | D25: =IFERROR(((D13+D14)/D8),0) -> 3.3763322 | E25: =IFERROR(((E13+E14)/E8),0) -> 1.9838007 | F25: =IFERROR(((F13+F14)/F8),0) -> 0 | G25: =IFERROR(((G13+G14)/G8),0) -> 2.7123
A26: Over head Per Pax | B26: =IFERROR((B10/B8),0) -> 0 | C26: =IFERROR((C10/C8),0) -> 0 | D26: =IFERROR((D10/D8),0) -> 0 | E26: =IFERROR((E10/E8),0) -> 0 | F26: =IFERROR((F10/F8),0) -> 0 | G26: =IFERROR((G10/G8),0) -> 0
B28: CYCLE | C28: FLT
A29: Config | B29: ='P&L'!R5 -> 1 | C29: 104
A30: OVERHEAD | B30: =B37*B8 -> 0 | C30: =C37*C8 -> 0 | D30: =D37*D8 -> 0 | E30: =E37*E8 -> 0 | F30: =F37*F8 -> 0 | G30: =G37*G8 -> 0
A31: Food Cost (DM) | B31: =IFERROR(IF($B$29=$B$29,SUMIF(Food!$C:$C,B$9&$B$29&$C$29,Food!$X:$X),0),"")+IFERROR(IF($B$29=$B$29,SUMIF(Food!$C:$C,B$9&$B$29&$C$29,Food!$W:$W),0),"") -> 0 | C31: =IFERROR(IF($B$29=$B$29,SUMIF(Food!$C:$C,C$9&$B$29&$C$29,Food!$X:$X),0),"") -> 882.95529 | D31: =IFERROR(IF($B$29=$B$29,SUMIF(Food!$C:$C,D$9&$B$29&$C$29,Food!$X:$X),0),"") -> 706.0263 | E31: =IFERROR(IF($B$29=$B$29,SUMIF(Food!$C:$C,E$9&$B$29&$C$29,Food!$X:$X),0),"") -> 1654.3569 | F31: =IFERROR(IF($B$29=$B$29,SUMIF(Food!$C:$C,F$9&$B$29&$C$29,Food!$X:$X),0),"") -> 0 | G31: =IFERROR(IF($B$29=$B$29,SUMIF(Food!$C:$C,G$9&$B$29&$C$29,Food!$X:$X),0),"") -> 78.972
A32: Wage Cost (DL) | B32: =IFERROR(IF($B$29=$B$29,SUMIF(Food!$C:$C,B$9&$B$29&$C$29,Food!$Z:$Z),0),"") -> 0 | C32: =IFERROR(IF($B$29=$B$29,SUMIF(Food!$C:$C,C$9&$B$29&$C$29,Food!$Z:$Z),0),"") -> 277.87 | D32: =IFERROR(IF($B$29=$B$29,SUMIF(Food!$C:$C,D$9&$B$29&$C$29,Food!$Z:$Z),0),"") -> 374.4 | E32: =IFERROR(IF($B$29=$B$29,SUMIF(Food!$C:$C,E$9&$B$29&$C$29,Food!$Z:$Z),0),"") -> 964.26 | F32: =IFERROR(IF($B$29=$B$29,SUMIF(Food!$C:$C,F$9&$B$29&$C$29,Food!$Z:$Z),0),"") -> 0 | G32: =IFERROR(IF($B$29=$B$29,SUMIF(Food!$C:$C,G$9&$B$29&$C$29,Food!$Z:$Z),0),"") -> 29.52
A33: Markup Food | B33: =IFERROR(IF($B$29=$B$29,SUMIF(Food!$C:$C,B$9&$B$29&$C$29,Food!$AB:$AB),0),"") -> 0 | C33: =IFERROR(IF($B$29=$B$29,SUMIF(Food!$C:$C,C$9&$B$29&$C$29,Food!$AB:$AB),0),"") -> 132.44329 | D33: =IFERROR(IF($B$29=$B$29,SUMIF(Food!$C:$C,D$9&$B$29&$C$29,Food!$AB:$AB),0),"") -> 105.90394 | E33: =IFERROR(IF($B$29=$B$29,SUMIF(Food!$C:$C,E$9&$B$29&$C$29,Food!$AB:$AB),0),"") -> 248.15353 | F33: =IFERROR(IF($B$29=$B$29,SUMIF(Food!$C:$C,F$9&$B$29&$C$29,Food!$AB:$AB),0),"") -> 0 | G33: =IFERROR(IF($B$29=$B$29,SUMIF(Food!$C:$C,G$9&$B$29&$C$29,Food!$AB:$AB),0),"") -> 11.8458
A34: Markup Labor | B34: =IFERROR(IF($B$29=$B$29,SUMIF(Food!$C:$C,B$9&$B$29&$C$29,Food!$AC:$AC),0),"") -> 0 | C34: =IFERROR(IF($B$29=$B$29,SUMIF(Food!$C:$C,C$9&$B$29&$C$29,Food!$AC:$AC),0),"") -> 41.6805 | D34: =IFERROR(IF($B$29=$B$29,SUMIF(Food!$C:$C,D$9&$B$29&$C$29,Food!$AC:$AC),0),"") -> 56.16 | E34: =IFERROR(IF($B$29=$B$29,SUMIF(Food!$C:$C,E$9&$B$29&$C$29,Food!$AC:$AC),0),"") -> 144.639 | F34: =IFERROR(IF($B$29=$B$29,SUMIF(Food!$C:$C,F$9&$B$29&$C$29,Food!$AC:$AC),0),"") -> 0 | G34: =IFERROR(IF($B$29=$B$29,SUMIF(Food!$C:$C,G$9&$B$29&$C$29,Food!$AC:$AC),0),"") -> 4.428
A36: Per Pax Avg
A37: OVERHEAD | B37: ='P&L'!$K$30 -> 0 | C37: ='P&L'!$L$30 -> 0 | D37: ='P&L'!$M$30 -> 0 | E37: ='P&L'!$N$30 -> 0 | F37: ='P&L'!$O$30 -> 0 | G37: ='P&L'!$P$30 -> 0
A38: Food Cost (DM) | B38: =IFERROR(B31/B7," ") | C38: =IFERROR(C31/C7," ") -> 25.969273 | D38: =IFERROR(D31/D7," ") -> 14.708881 | E38: =IFERROR(E31/E7," ") -> 8.3553378 | F38: =IFERROR(F31/F7," ") | G38: =IFERROR(G31/G7," ") -> 13.162
A39: Wage Cost (DL) | B39: =IFERROR(B32/B7," ") | C39: =IFERROR(C32/C7," ") -> 8.1726471 | D39: =IFERROR(D32/D7," ") -> 7.8 | E39: =IFERROR(E32/E7," ") -> 4.87 | F39: =IFERROR(F32/F7," ") | G39: =IFERROR(G32/G7," ") -> 4.92
A40: Markup Food | B40: =IFERROR(B33/B8," ") | C40: =IFERROR(C33/C7," ") -> 3.895391 | D40: =IFERROR(D33/D7," ") -> 2.2063322 | E40: =IFERROR(E33/E7," ") -> 1.2533007 | F40: =IFERROR(F33/F7," ") | G40: =IFERROR(G33/G7," ") -> 1.9743
A41: Markup Labor | B41: =IFERROR(B34/B7," ") | C41: =IFERROR(C34/C7," ") -> 1.2258971 | D41: =IFERROR(D34/D7," ") -> 1.17 | E41: =IFERROR(E34/E7," ") -> 0.7305 | F41: =IFERROR(F34/F7," ") | G41: =IFERROR(G34/G7," ") -> 0.738
A108: 388
A109: 787

Sheet Summary FLT110
A2: Customer | G2: Flights Per week | H2: 7 | L2: AC type | M2: Cycle
E3: AC Type | F3: 738 | G3: Flights Per Month | H3: =H4/12 -> 30.333333 | J3: Total Revenues | L3: 330 | M3: 1
E4: Load | F4: ='P&L'!R4 -> 0.85 | G4: Annual Flights | H4: =H2*52 -> 364 | J4: =H17*H4 -> 1817422.4
A5: Summary
A6: BNA | B6: FC | C6: BC | D6: PY | E6: EY | F6: TC | G6: CY | H6: Total | I6: Hnd
A7: FLIGHT CONFIG | B7: =+'FlightConfig '!B17 -> 0 | C7: =+'FlightConfig '!C23 -> 30 | D7: =+'FlightConfig '!D23 -> 44 | E7: =+'FlightConfig '!E23 -> 184 | F7: =+'FlightConfig '!F23 -> 0 | G7: =+'FlightConfig '!G23 -> 6 | H7: =+'FlightConfig '!H23 -> 264
A8: Load Factor | B8: =ROUNDUP(B7*$F$4,0) -> 0 | C8: =ROUNDUP(C7*$F$4,0) -> 26 | D8: =ROUNDUP(D7*$F$4,0) -> 38 | E8: =ROUNDUP(E7*$F$4,0) -> 157 | F8: =ROUNDUP(F7*$F$4,0) -> 0 | G8: =ROUNDUP(G7*$F$4,0) -> 6 | H8: =SUM(B8:G8) -> 227
B9: FIRST CLASS | C9: BUSINESS CLASS | D9: PREMIUM ECONOMY CLASS | E9: ECONOMY CLASS | F9: TECH CREW CLASS | G9: cABIN CREW CLASS | H9: Per Flight | J9: Annual
A10: OVERHEAD | B10: =B37*B8 -> 0 | C10: =C37*C8 -> 0 | D10: =D37*D8 -> 0 | E10: =E37*E8 -> 0 | F10: =F37*F8 -> 0 | G10: =G37*G8 -> 0 | H10: =SUM(B10:G10) -> 0 | J10: =H10*$H$4 -> 0
A11: Food Cost (DM) | B11: =IFERROR(B38*B8,0) -> 0 | C11: =IFERROR(C38*$C$8,0) -> 493.077 | D11: =IFERROR(D38*$D$8,0) -> 498.921 | E11: =IFERROR(E38*$E$8,0) -> 718.275 | F11: =IFERROR(F38*$F$8,0) -> 0 | G11: =IFERROR(G38*$G$8,0) -> 185.58 | H11: =SUM(B11:G11) -> 1895.853 | J11: =H11*$H$4 -> 690090.49
A12: Wage Cost (DL) | B12: =IFERROR(B39*B8,0) -> 0 | C12: =IFERROR(C39*$C$8,0) -> 192.114 | D12: =IFERROR(D39*$D$8,0) -> 234.08 | E12: =IFERROR(E39*$E$8,0) -> 566.77 | F12: =IFERROR(F39*$F$8,0) -> 0 | G12: =IFERROR(G39*$G$8,0) -> 82.8 | H12: =SUM(B12:G12) -> 1075.764 | J12: =H12*$H$4 -> 391578.1
A13: Food Mark up | B13: =IFERROR(B40*B9,0) -> 0 | C13: =IFERROR(C40*$C$8,0) -> 73.96155 | D13: =IFERROR(D40*$D$8,0) -> 74.83815 | E13: =IFERROR(E40*$E$8,0) -> 107.74125 | F13: =IFERROR(F40*$F$8,0) -> 0 | G13: =IFERROR(G40*$G$8,0) -> 27.837 | H13: =SUM(B13:G13) -> 284.37795 | J13: =H13*$H$4 -> 103513.57
A14: Labor Mark up | B14: =IFERROR(B41*B10,0) -> 0 | C14: =IFERROR(C41*$C$8,0) -> 28.8171 | D14: =IFERROR(D41*$D$8,0) -> 35.112 | E14: =IFERROR(E41*$E$8,0) -> 85.0155 | F14: =IFERROR(F41*$F$8,0) -> 0 | G14: =IFERROR(G41*$G$8,0) -> 12.42 | H14: =SUM(B14:G14) -> 161.3646 | J14: =H14*$H$4 -> 58736.714 | L14: Direct Labour
A15: Handling Cost | B15: 0 | C15: 0 | D15: 0 | E15: =+B20 -> 1394.3 | F15: 0 | G15: 0 | H15: =SUM(B15:G15) -> 1394.3 | J15: =H15*$H$4 -> 507525.2 | L15: =J12+J15 -> 899103.3 | M15: 1
A16: Handling Mark up | B16: 0 | C16: 0 | D16: 0 | E16: =+C20 -> 181.259 | F16: 0 | G16: 0 | H16: =SUM(B16:G16) -> 181.259 | J16: =H16*$H$4 -> 65978.276 | L16: =L15*M16 -> 719282.64 | M16: 0.8
A17: Total Per Flight | B17: =SUM(B11:B16) -> 0 | C17: =SUM(C11:C16) -> 787.96965 | D17: =SUM(D10:D16) -> 842.95115 | E17: =SUM(E10:E16) -> 3053.3608 | F17: =SUM(F10:F16) -> 0 | G17: =SUM(G10:G16) -> 308.637 | H17: =SUM(H10:H16) -> 4992.9186 | J17: =H17*$H$4 -> 1817422.4 | L17: =L15*M17 -> 179820.66 | M17: 0.2
B18: =B17 -> 0 | C18: =C17 -> 787.96965 | D18: =D17 -> 842.95115 | E18: =E17-E15-E16 -> 1477.8018 | F18: =F17 -> 0 | G18: =G17 -> 308.637 | I18: =E15+E16 -> 1575.559
A19: Handling | B19: Cost | C19: Mark Up | D19: Price | I19: =E16 -> 181.259 | J19: =H11+H12+H15 -> 4365.917
A20: 738 Handling | B20: =Handling!C83+Handling!R39+Handling!R45+Handling!V52+Handling!AC39 -> 1394.3 | C20: =B20*'P&L'!$R$10 -> 181.259 | D20: =SUM(B20:C20) -> 1575.559 | J20: =H13+H14+H16 -> 627.00155
A21: B777 Handling | B21: =Handling!#REF! -> #REF! | C21: =Handling!#REF! -> #REF! | D21: =Handling!#REF! -> #REF!
A22: A380 Handling | B22: =Handling!#REF! -> #REF! | C22: =Handling!#REF! -> #REF! | D22: =Handling!#REF! -> #REF!
A24: Avg Price Per Pax | B24: =IFERROR(((B11+B12+B13+B14)/B8),0) -> 0 | C24: =IFERROR(((C11+C12+C13+C14)/C8),0) -> 30.306525 | D24: =IFERROR(((D10+D11+D12+D13+D14)/D8),0) -> 22.182925 | E24: =IFERROR(((E10+E11+E12+E13+E14)/E8),0) -> 9.41275 | F24: =IFERROR(((F10+F11+F12+F13+F14)/F8),0) -> 0 | G24: =IFERROR(((G10+G11+G12+G13+G14)/G8),0) -> 51.4395
A25: Avg Mark up Per Pax | B25: =IFERROR(((B13+B14)/B8),0) -> 0 | C25: =IFERROR(((C13+C14)/C8),0) -> 3.953025 | D25: =IFERROR(((D13+D14)/D8),0) -> 2.893425 | E25: =IFERROR(((E13+E14)/E8),0) -> 1.22775 | F25: =IFERROR(((F13+F14)/F8),0) -> 0 | G25: =IFERROR(((G13+G14)/G8),0) -> 6.7095
A26: Over head Per Pax | B26: =IFERROR((B10/B8),0) -> 0 | C26: =IFERROR((C10/C8),0) -> 0 | D26: =IFERROR((D10/D8),0) -> 0 | E26: =IFERROR((E10/E8),0) -> 0 | F26: =IFERROR((F10/F8),0) -> 0 | G26: =IFERROR((G10/G8),0) -> 0
B28: CYCLE | C28: FLT
A29: Config | B29: ='P&L'!R5 -> 1 | C29: 110
A30: OVERHEAD | B30: =B37*B8 -> 0 | C30: =C37*C8 -> 0 | D30: =D37*D8 -> 0 | E30: =E37*E8 -> 0 | F30: =F37*F8 -> 0 | G30: =G37*G8 -> 0
A31: Food Cost (DM) | B31: =IFERROR(IF($B$29=$B$29,SUMIF(Food!$C:$C,B$9&$B$29&$C$29,Food!$X:$X),0),"")+IFERROR(IF($B$29=$B$29,SUMIF(Food!$C:$C,B$9&$B$29&$C$29,Food!$W:$W),0),"") -> 0 | C31: =IFERROR(IF($B$29=$B$29,SUMIF(Food!$C:$C,C$9&$B$29&$C$29,Food!$X:$X),0),"") -> 568.935 | D31: =IFERROR(IF($B$29=$B$29,SUMIF(Food!$C:$C,D$9&$B$29&$C$29,Food!$X:$X),0),"") -> 577.698 | E31: =IFERROR(IF($B$29=$B$29,SUMIF(Food!$C:$C,E$9&$B$29&$C$29,Food!$X:$X),0),"") -> 841.8 | F31: =IFERROR(IF($B$29=$B$29,SUMIF(Food!$C:$C,F$9&$B$29&$C$29,Food!$X:$X),0),"") -> 0 | G31: =IFERROR(IF($B$29=$B$29,SUMIF(Food!$C:$C,G$9&$B$29&$C$29,Food!$X:$X),0),"") -> 185.58 | H31: NM cost added
A32: Wage Cost (DL) | B32: =IFERROR(IF($B$29=$B$29,SUMIF(Food!$C:$C,B$9&$B$29&$C$29,Food!$Z:$Z),0),"") -> 0 | C32: =IFERROR(IF($B$29=$B$29,SUMIF(Food!$C:$C,C$9&$B$29&$C$29,Food!$Z:$Z),0),"") -> 221.67 | D32: =IFERROR(IF($B$29=$B$29,SUMIF(Food!$C:$C,D$9&$B$29&$C$29,Food!$Z:$Z),0),"") -> 271.04 | E32: =IFERROR(IF($B$29=$B$29,SUMIF(Food!$C:$C,E$9&$B$29&$C$29,Food!$Z:$Z),0),"") -> 664.24 | F32: =IFERROR(IF($B$29=$B$29,SUMIF(Food!$C:$C,F$9&$B$29&$C$29,Food!$Z:$Z),0),"") -> 0 | G32: =IFERROR(IF($B$29=$B$29,SUMIF(Food!$C:$C,G$9&$B$29&$C$29,Food!$Z:$Z),0),"") -> 82.8
A33: Markup Food | B33: =IFERROR(IF($B$29=$B$29,SUMIF(Food!$C:$C,B$9&$B$29&$C$29,Food!$AB:$AB),0),"") -> 0 | C33: =IFERROR(IF($B$29=$B$29,SUMIF(Food!$C:$C,C$9&$B$29&$C$29,Food!$AB:$AB),0),"") -> 85.34025 | D33: =IFERROR(IF($B$29=$B$29,SUMIF(Food!$C:$C,D$9&$B$29&$C$29,Food!$AB:$AB),0),"") -> 86.6547 | E33: =IFERROR(IF($B$29=$B$29,SUMIF(Food!$C:$C,E$9&$B$29&$C$29,Food!$AB:$AB),0),"") -> 126.27 | F33: =IFERROR(IF($B$29=$B$29,SUMIF(Food!$C:$C,F$9&$B$29&$C$29,Food!$AB:$AB),0),"") -> 0 | G33: =IFERROR(IF($B$29=$B$29,SUMIF(Food!$C:$C,G$9&$B$29&$C$29,Food!$AB:$AB),0),"") -> 27.837
A34: Markup Labor | B34: =IFERROR(IF($B$29=$B$29,SUMIF(Food!$C:$C,B$9&$B$29&$C$29,Food!$AC:$AC),0),"") -> 0 | C34: =IFERROR(IF($B$29=$B$29,SUMIF(Food!$C:$C,C$9&$B$29&$C$29,Food!$AC:$AC),0),"") -> 33.2505 | D34: =IFERROR(IF($B$29=$B$29,SUMIF(Food!$C:$C,D$9&$B$29&$C$29,Food!$AC:$AC),0),"") -> 40.656 | E34: =IFERROR(IF($B$29=$B$29,SUMIF(Food!$C:$C,E$9&$B$29&$C$29,Food!$AC:$AC),0),"") -> 99.636 | F34: =IFERROR(IF($B$29=$B$29,SUMIF(Food!$C:$C,F$9&$B$29&$C$29,Food!$AC:$AC),0),"") -> 0 | G34: =IFERROR(IF($B$29=$B$29,SUMIF(Food!$C:$C,G$9&$B$29&$C$29,Food!$AC:$AC),0),"") -> 12.42
A36: Per Pax Avg
A37: OVERHEAD | B37: ='P&L'!$K$30 -> 0 | C37: ='P&L'!$L$30 -> 0 | D37: ='P&L'!$M$30 -> 0 | E37: ='P&L'!$N$30 -> 0 | F37: ='P&L'!$O$30 -> 0 | G37: ='P&L'!$P$30 -> 0
A38: Food Cost (DM) | B38: =IFERROR(B31/B7," ") | C38: =IFERROR(C31/C7," ") -> 18.9645 | D38: =IFERROR(D31/D7," ") -> 13.1295 | E38: =IFERROR(E31/E7," ") -> 4.575 | F38: =IFERROR(F31/F7," ") | G38: =IFERROR(G31/G7," ") -> 30.93
A39: Wage Cost (DL) | B39: =IFERROR(B32/B7," ") | C39: =IFERROR(C32/C7," ") -> 7.389 | D39: =IFERROR(D32/D7," ") -> 6.16 | E39: =IFERROR(E32/E7," ") -> 3.61 | F39: =IFERROR(F32/F7," ") | G39: =IFERROR(G32/G7," ") -> 13.8
A40: Markup Food | B40: =IFERROR(B33/B8," ") | C40: =IFERROR(C33/C7," ") -> 2.844675 | D40: =IFERROR(D33/D7," ") -> 1.969425 | E40: =IFERROR(E33/E7," ") -> 0.68625 | F40: =IFERROR(F33/F7," ") | G40: =IFERROR(G33/G7," ") -> 4.6395
A41: Markup Labor | B41: =IFERROR(B34/B7," ") | C41: =IFERROR(C34/C7," ") -> 1.10835 | D41: =IFERROR(D34/D7," ") -> 0.924 | E41: =IFERROR(E34/E7," ") -> 0.5415 | F41: =IFERROR(F34/F7," ") | G41: =IFERROR(G34/G7," ") -> 2.07
A108: 388
A109: 787

Sheet Summary 2037
A2: Customer | G2: Flights Per week | H2: 0 | L2: AC type | M2: Cycle
E3: AC Type | F3: 738 | G3: Flights Per Month | H3: =H4/12 -> 0 | J3: Total Revenues | L3: 737 | M3: 1
E4: Load | F4: ='P&L'!R4 -> 0.85 | G4: Annual Flights | H4: =H2*52 -> 0 | J4: =H17*H4 -> #REF!
A5: Summary
A6: BNA | B6: FC | C6: BC | D6: PY | E6: EY | F6: TC | G6: CY | H6: Total | I6: Hnd
A7: FLIGHT CONFIG | B7: =+'FlightConfig '!B17 -> 0 | C7: =+'FlightConfig '!C17 -> 34 | D7: =+'FlightConfig '!D17 -> 48 | E7: =+'FlightConfig '!E17 -> 198 | F7: =+'FlightConfig '!F17 -> 0 | G7: =+'FlightConfig '!G17 -> 6 | H7: =SUM(B7:G7) -> 286
A8: Load Factor | B8: =ROUNDUP(B7*$F$4,0) -> 0 | C8: =ROUNDUP(C7*$F$4,0) -> 29 | D8: =ROUNDUP(D7*$F$4,0) -> 41 | E8: =ROUNDUP(E7*$F$4,0) -> 169 | F8: =ROUNDUP(F7*$F$4,0) -> 0 | G8: =ROUNDUP(G7*$F$4,0) -> 6 | H8: =SUM(B8:G8) -> 245
B9: FIRST CLASS | C9: BUSINESS CLASS | D9: PREMIUM ECONOMY CLASS | E9: ECONOMY CLASS | F9: TECH CREW CLASS | G9: cABIN CREW CLASS | H9: Per Flight | J9: Annual
A10: OVERHEAD | B10: =B37*B8 -> 0 | C10: =C37*C8 -> 0 | D10: =D37*D8 -> 0 | E10: =E37*E8 -> 0 | F10: =F37*F8 -> 0 | G10: =G37*G8 -> 0 | H10: =SUM(B10:G10) -> 0 | J10: =H10*$H$4 -> 0
A11: Food Cost (DM) | B11: =IFERROR(B38*B8,0) -> 0 | C11: =IFERROR(C38*$C$8,0) -> 0 | D11: =IFERROR(D38*$D$8,0) -> 0 | E11: =IFERROR(E38*$E$8,0) -> 0 | F11: =IFERROR(F38*$F$8,0) -> 0 | G11: =IFERROR(G38*G8,0) -> 0 | H11: =SUM(B11:G11) -> 0 | I11: =I12*45% -> 0 | J11: =H11*$H$4 -> 0
A12: Wage Cost (DL) | B12: =IFERROR(B39*B8,0) -> 0 | C12: =IFERROR(C39*$C$8,0) -> 0 | D12: =IFERROR(D39*$D$8,0) -> 0 | E12: =IFERROR(E39*$E$8,0) -> 0 | F12: =IFERROR(F39*$F$8,0) -> 0 | G12: =IFERROR(G39*G8,0) -> 0 | H12: =SUM(B12:G12) -> 0 | I12: =H11+H12 -> 0 | J12: =H12*$H$4 -> 0
A13: Food Mark up | B13: =IFERROR(B40*B8," ") | C13: =IFERROR(C40*$C$8,0) -> 0 | D13: =IFERROR(D40*$D$8,0) -> 0 | E13: =IFERROR(E40*$E$8,0) -> 0 | F13: =IFERROR(F40*$F$8,0) -> 0 | G13: 0 | H13: =SUM(B13:G13) -> 0 | J13: =H13*$H$4 -> 0
A14: Labor Mark up | B14: =IFERROR(B41*B8," ") | C14: =IFERROR(C41*$C$8,0) -> 0 | D14: =IFERROR(D41*$D$8,0) -> 0 | E14: =IFERROR(E41*$E$8,0) -> 0 | F14: =IFERROR(F41*$F$8,0) -> 0 | G14: 0 | H14: =SUM(B14:G14) -> 0 | J14: =H14*$H$4 -> 0 | L14: Direct Labour
A15: Handling Cost | B15: 0 | C15: 0 | D15: 0 | E15: =+B20 -> #REF! | F15: 0 | G15: 0 | H15: =SUM(B15:G15) -> #REF! | J15: =H15*$H$4 -> #REF! | L15: =J12+J15 -> #REF! | M15: 1
A16: Handling Mark up | B16: 0 | C16: 0 | D16: 0 | E16: =+C20 -> #REF! | F16: 0 | G16: 0 | H16: =SUM(B16:G16) -> #REF! | J16: =H16*$H$4 -> #REF! | L16: =L15*M16 -> #REF! | M16: 0.8
A17: Total Per Flight | B17: =SUM(B11:B16) -> 0 | C17: =SUM(C11:C16) -> 0 | D17: =SUM(D10:D16) -> 0 | E17: =SUM(E10:E16) -> #REF! | F17: =SUM(F10:F16) -> 0 | G17: =SUM(G10:G16) -> 0 | H17: =SUM(H10:H16) -> #REF! | J17: =H17*$H$4 -> #REF! | L17: =L15*M17 -> #REF! | M17: 0.2
B18: =B17 -> 0 | C18: =C17 -> 0 | D18: =D17 -> 0 | E18: =E17-E15-E16 -> #REF! | F18: =F17 -> 0 | G18: =G17 -> 0 | I18: =E15+E16 -> #REF!
A19: Handling | B19: Cost | C19: Mark Up | D19: Price | I19: =E16 -> #REF!
A20: 738 Handling | B20: =Handling!C22 -> #REF! | C20: =B20*'P&L'!$R$10 -> #REF! | D20: =SUM(B20:C20) -> #REF!
A21: B777 Handling | B21: =Handling!#REF! -> #REF! | C21: =Handling!#REF! -> #REF! | D21: =Handling!#REF! -> #REF!
A22: A380 Handling | B22: =Handling!#REF! -> #REF! | C22: =Handling!#REF! -> #REF! | D22: =Handling!#REF! -> #REF!
A24: Avg Price Per Pax | B24: =IFERROR(((B11+B12+B13+B14)/B8),0) -> 0 | C24: =IFERROR(((C11+C12+C13+C14)/C8),0) -> 0 | D24: =IFERROR(((D10+D11+D12+D13+D14)/D8),0) -> 0 | E24: =IFERROR(((E10+E11+E12+E13+E14)/E8),0) -> 0 | F24: =IFERROR(((F10+F11+F12+F13+F14)/F8),0) -> 0 | G24: =IFERROR(((G10+G11+G12+G13+G14)/G8),0) -> 0
A25: Avg Mark up Per Pax | B25: =IFERROR(((B13+B14)/B8),0) -> 0 | C25: =IFERROR(((C13+C14)/C8),0) -> 0 | D25: =IFERROR(((D13+D14)/D8),0) -> 0 | E25: =IFERROR(((E13+E14)/E8),0) -> 0 | F25: =IFERROR(((F13+F14)/F8),0) -> 0 | G25: =IFERROR(((G13+G14)/G8),0) -> 0
A26: Over head Per Pax | B26: =IFERROR((B10/B8),0) -> 0 | C26: =IFERROR((C10/C8),0) -> 0 | D26: =IFERROR((D10/D8),0) -> 0 | E26: =IFERROR((E10/E8),0) -> 0 | F26: =IFERROR((F10/F8),0) -> 0 | G26: =IFERROR((G10/G8),0) -> 0
B28: CYCLE | C28: FLT
A29: Config | B29: ='P&L'!R5 -> 1 | C29: 2037
A30: OVERHEAD | B30: =B37*B8 -> 0 | C30: =C37*C8 -> 0 | D30: =D37*D8 -> 0 | E30: =E37*E8 -> 0 | F30: =F37*F8 -> 0 | G30: =G37*G8 -> 0
A31: Food Cost (DM) | B31: =IFERROR(IF($B$29=$B$29,SUMIF(Food!$C:$C,B$9&$B$29&$C$29,Food!$X:$X),0),"") -> 0 | C31: =IFERROR(IF($B$29=$B$29,SUMIF(Food!$C:$C,C$9&$B$29&$C$29,Food!$X:$X),0),"") -> 0 | D31: =IFERROR(IF($B$29=$B$29,SUMIF(Food!$C:$C,D$9&$B$29&$C$29,Food!$X:$X),0),"") -> 0 | E31: =IFERROR(IF($B$29=$B$29,SUMIF(Food!$C:$C,E$9&$B$29&$C$29,Food!$X:$X),0),"") -> 0 | F31: =IFERROR(IF($B$29=$B$29,SUMIF(Food!$C:$C,F$9&$B$29&$C$29,Food!$X:$X),0),"") -> 0 | G31: =IFERROR(IF($B$29=$B$29,SUMIF(Food!$C:$C,G$9&$B$29&$C$29,Food!$X:$X),0),"") -> 0
A32: Wage Cost (DL) | B32: =IFERROR(IF($B$29=$B$29,SUMIF(Food!$C:$C,B$9&$B$29&$C$29,Food!$Z:$Z),0),"") -> 0 | C32: =IFERROR(IF($B$29=$B$29,SUMIF(Food!$C:$C,C$9&$B$29&$C$29,Food!$Z:$Z),0),"") -> 0 | D32: =IFERROR(IF($B$29=$B$29,SUMIF(Food!$C:$C,D$9&$B$29&$C$29,Food!$Z:$Z),0),"") -> 0 | E32: =IFERROR(IF($B$29=$B$29,SUMIF(Food!$C:$C,E$9&$B$29&$C$29,Food!$Z:$Z),0),"") -> 0 | F32: =IFERROR(IF($B$29=$B$29,SUMIF(Food!$C:$C,F$9&$B$29&$C$29,Food!$Z:$Z),0),"") -> 0 | G32: =IFERROR(IF($B$29=$B$29,SUMIF(Food!$C:$C,G$9&$B$29&$C$29,Food!$Z:$Z),0),"") -> 0
A33: Markup Food | B33: =IFERROR(IF($B$29=$B$29,SUMIF(Food!$C:$C,B$9&$B$29&$C$29,Food!$AB:$AB),0),"") -> 0 | C33: =IFERROR(IF($B$29=$B$29,SUMIF(Food!$C:$C,C$9&$B$29&$C$29,Food!$AB:$AB),0),"") -> 0 | D33: =IFERROR(IF($B$29=$B$29,SUMIF(Food!$C:$C,D$9&$B$29&$C$29,Food!$AB:$AB),0),"") -> 0 | E33: =IFERROR(IF($B$29=$B$29,SUMIF(Food!$C:$C,E$9&$B$29&$C$29,Food!$AB:$AB),0),"") -> 0 | F33: =IFERROR(IF($B$29=$B$29,SUMIF(Food!$C:$C,F$9&$B$29&$C$29,Food!$AB:$AB),0),"") -> 0 | G33: =IFERROR(IF($B$29=$B$29,SUMIF(Food!$C:$C,G$9&$B$29&$C$29,Food!$O:$O),0),"") -> 0
A34: Markup Labor | B34: =IFERROR(IF($B$29=$B$29,SUMIF(Food!$C:$C,B$9&$B$29&$C$29,Food!$AC:$AC),0),"") -> 0 | C34: =IFERROR(IF($B$29=$B$29,SUMIF(Food!$C:$C,C$9&$B$29&$C$29,Food!$AC:$AC),0),"") -> 0 | D34: =IFERROR(IF($B$29=$B$29,SUMIF(Food!$C:$C,D$9&$B$29&$C$29,Food!$AC:$AC),0),"") -> 0 | E34: =IFERROR(IF($B$29=$B$29,SUMIF(Food!$C:$C,E$9&$B$29&$C$29,Food!$AC:$AC),0),"") -> 0 | F34: =IFERROR(IF($B$29=$B$29,SUMIF(Food!$C:$C,F$9&$B$29&$C$29,Food!$AC:$AC),0),"") -> 0 | G34: =IFERROR(IF($B$29=$B$29,SUMIF(Food!$C:$C,G$9&$B$29&$C$29,Food!$P:$P),0),"") -> 0
A36: Per Pax Avg
A37: OVERHEAD | B37: ='P&L'!$K$30 -> 0 | C37: ='P&L'!$L$30 -> 0 | D37: ='P&L'!$M$30 -> 0 | E37: ='P&L'!$N$30 -> 0 | F37: ='P&L'!$O$30 -> 0 | G37: ='P&L'!$P$30 -> 0
A38: Food Cost (DM) | B38: =IFERROR(B31/B7," ") | C38: =IFERROR(C31/C7," ") -> 0 | D38: =IFERROR(D31/D7," ") -> 0 | E38: =IFERROR(E31/E7," ") -> 0 | F38: =IFERROR(F31/F7," ") | G38: =IFERROR(G31/G7," ") -> 0
A39: Wage Cost (DL) | B39: =IFERROR(B32/B7," ") | C39: =IFERROR(C32/C7," ") -> 0 | D39: =IFERROR(D32/D7," ") -> 0 | E39: =IFERROR(E32/E7," ") -> 0 | F39: =IFERROR(F32/F7," ") | G39: =IFERROR(G32/G7," ") -> 0
A40: Markup Food | B40: =IFERROR(B33/B8," ") | C40: =IFERROR(C33/C7," ") -> 0 | D40: =IFERROR(D33/D7," ") -> 0 | E40: =IFERROR(E33/E7," ") -> 0 | F40: =IFERROR(F33/F7," ") | G40: =IFERROR(G33/G7," ") -> 0
A41: Markup Labor | B41: =IFERROR(B34/B7," ") | C41: =IFERROR(C34/C7," ") -> 0 | D41: =IFERROR(D34/D7," ") -> 0 | E41: =IFERROR(E34/E7," ") -> 0 | F41: =IFERROR(F34/F7," ") | G41: =IFERROR(G34/G7," ") -> 0
A108: 388
A109: 787

Sheet Summary 2817
A2: Customer | G2: Flights Per week | H2: 0 | L2: AC type | M2: Cycle
E3: AC Type | F3: 738 | G3: Flights Per Month | H3: =H4/12 -> 0 | J3: Total Revenues | L3: 737 | M3: 1
E4: Load | F4: ='P&L'!R4 -> 0.85 | G4: Annual Flights | H4: =H2*52 -> 0 | J4: =H17*H4 -> #REF!
A5: Summary
A6: BNA | B6: FC | C6: BC | D6: PY | E6: EY | F6: TC | G6: CY | H6: Total | I6: Hnd
A7: FLIGHT CONFIG | B7: =+'FlightConfig '!B17 -> 0 | C7: =+'FlightConfig '!C17 -> 34 | D7: =+'FlightConfig '!D17 -> 48 | E7: =+'FlightConfig '!E17 -> 198 | F7: =+'FlightConfig '!F17 -> 0 | G7: =+'FlightConfig '!G17 -> 6 | H7: =SUM(B7:G7) -> 286
A8: Load Factor | B8: =ROUNDUP(B7*$F$4,0) -> 0 | C8: =ROUNDUP(C7*$F$4,0) -> 29 | D8: =ROUNDUP(D7*$F$4,0) -> 41 | E8: =ROUNDUP(E7*$F$4,0) -> 169 | F8: =ROUNDUP(F7*$F$4,0) -> 0 | G8: =ROUNDUP(G7*$F$4,0) -> 6 | H8: =SUM(B8:G8) -> 245
B9: FIRST CLASS | C9: BUSINESS CLASS | D9: PREMIUM ECONOMY CLASS | E9: ECONOMY CLASS | F9: TECH CREW CLASS | G9: cABIN CREW CLASS | H9: Per Flight | J9: Annual
A10: OVERHEAD | B10: =B37*B8 -> 0 | C10: =C37*C8 -> 0 | D10: =D37*D8 -> 0 | E10: =E37*E8 -> 0 | F10: =F37*F8 -> 0 | G10: =G37*G8 -> 0 | H10: =SUM(B10:G10) -> 0 | J10: =H10*$H$4 -> 0
A11: Food Cost (DM) | B11: =IFERROR(B38*B8,0) -> 0 | C11: =IFERROR(C38*$C$8,0) -> 0 | D11: =IFERROR(D38*$D$8,0) -> 0 | E11: =IFERROR(E38*$E$8,0) -> 0 | F11: =IFERROR(F38*$F$8,0) -> 0 | G11: =IFERROR(G38*G8,0) -> 0 | H11: =SUM(B11:G11) -> 0 | I11: =I12*45% -> 0 | J11: =H11*$H$4 -> 0
A12: Wage Cost (DL) | B12: =IFERROR(B39*B8,0) -> 0 | C12: =IFERROR(C39*$C$8,0) -> 0 | D12: =IFERROR(D39*$D$8,0) -> 0 | E12: =IFERROR(E39*$E$8,0) -> 0 | F12: =IFERROR(F39*$F$8,0) -> 0 | G12: =IFERROR(G39*G8,0) -> 0 | H12: =SUM(B12:G12) -> 0 | I12: =H11+H12 -> 0 | J12: =H12*$H$4 -> 0
A13: Food Mark up | B13: =IFERROR(B40*B8," ") | C13: =IFERROR(C40*$C$8,0) -> 0 | D13: =IFERROR(D40*$D$8,0) -> 0 | E13: =IFERROR(E40*$E$8,0) -> 0 | F13: =IFERROR(F40*$F$8,0) -> 0 | G13: 0 | H13: =SUM(B13:G13) -> 0 | J13: =H13*$H$4 -> 0
A14: Labor Mark up | B14: =IFERROR(B41*B8," ") | C14: =IFERROR(C41*$C$8,0) -> 0 | D14: =IFERROR(D41*$D$8,0) -> 0 | E14: =IFERROR(E41*$E$8,0) -> 0 | F14: =IFERROR(F41*$F$8,0) -> 0 | G14: 0 | H14: =SUM(B14:G14) -> 0 | J14: =H14*$H$4 -> 0 | L14: Direct Labour
A15: Handling Cost | B15: 0 | C15: 0 | D15: 0 | E15: =+B20 -> #REF! | F15: 0 | G15: 0 | H15: =SUM(B15:G15) -> #REF! | J15: =H15*$H$4 -> #REF! | L15: =J12+J15 -> #REF! | M15: 1
A16: Handling Mark up | B16: 0 | C16: 0 | D16: 0 | E16: =+C20 -> #REF! | F16: 0 | G16: 0 | H16: =SUM(B16:G16) -> #REF! | J16: =H16*$H$4 -> #REF! | L16: =L15*M16 -> #REF! | M16: 0.8
A17: Total Per Flight | B17: =SUM(B11:B16) -> 0 | C17: =SUM(C11:C16) -> 0 | D17: =SUM(D10:D16) -> 0 | E17: =SUM(E10:E16) -> #REF! | F17: =SUM(F10:F16) -> 0 | G17: =SUM(G10:G16) -> 0 | H17: =SUM(H10:H16) -> #REF! | J17: =H17*$H$4 -> #REF! | L17: =L15*M17 -> #REF! | M17: 0.2
B18: =B17 -> 0 | C18: =C17 -> 0 | D18: =D17 -> 0 | E18: =E17-E15-E16 -> #REF! | F18: =F17 -> 0 | G18: =G17 -> 0 | I18: =E15+E16 -> #REF!
A19: Handling | B19: Cost | C19: Mark Up | D19: Price | I19: =E16 -> #REF!
A20: 738 Handling | B20: =Handling!C22 -> #REF! | C20: =B20*'P&L'!$R$10 -> #REF! | D20: =SUM(B20:C20) -> #REF!
A21: B777 Handling | B21: =Handling!#REF! -> #REF! | C21: =Handling!#REF! -> #REF! | D21: =Handling!#REF! -> #REF!
A22: A380 Handling | B22: =Handling!#REF! -> #REF! | C22: =Handling!#REF! -> #REF! | D22: =Handling!#REF! -> #REF!
A24: Avg Price Per Pax | B24: =IFERROR(((B11+B12+B13+B14)/B8),0) -> 0 | C24: =IFERROR(((C11+C12+C13+C14)/C8),0) -> 0 | D24: =IFERROR(((D10+D11+D12+D13+D14)/D8),0) -> 0 | E24: =IFERROR(((E10+E11+E12+E13+E14)/E8),0) -> 0 | F24: =IFERROR(((F10+F11+F12+F13+F14)/F8),0) -> 0 | G24: =IFERROR(((G10+G11+G12+G13+G14)/G8),0) -> 0
A25: Avg Mark up Per Pax | B25: =IFERROR(((B13+B14)/B8),0) -> 0 | C25: =IFERROR(((C13+C14)/C8),0) -> 0 | D25: =IFERROR(((D13+D14)/D8),0) -> 0 | E25: =IFERROR(((E13+E14)/E8),0) -> 0 | F25: =IFERROR(((F13+F14)/F8),0) -> 0 | G25: =IFERROR(((G13+G14)/G8),0) -> 0
A26: Over head Per Pax | B26: =IFERROR((B10/B8),0) -> 0 | C26: =IFERROR((C10/C8),0) -> 0 | D26: =IFERROR((D10/D8),0) -> 0 | E26: =IFERROR((E10/E8),0) -> 0 | F26: =IFERROR((F10/F8),0) -> 0 | G26: =IFERROR((G10/G8),0) -> 0
B28: CYCLE | C28: FLT
A29: Config | B29: ='P&L'!R5 -> 1 | C29: 2817
A30: OVERHEAD | B30: =B37*B8 -> 0 | C30: =C37*C8 -> 0 | D30: =D37*D8 -> 0 | E30: =E37*E8 -> 0 | F30: =F37*F8 -> 0 | G30: =G37*G8 -> 0
A31: Food Cost (DM) | B31: =IFERROR(IF($B$29=$B$29,SUMIF(Food!$C:$C,B$9&$B$29&$C$29,Food!$X:$X),0),"") -> 0 | C31: =IFERROR(IF($B$29=$B$29,SUMIF(Food!$C:$C,C$9&$B$29&$C$29,Food!$X:$X),0),"") -> 0 | D31: =IFERROR(IF($B$29=$B$29,SUMIF(Food!$C:$C,D$9&$B$29&$C$29,Food!$X:$X),0),"") -> 0 | E31: =IFERROR(IF($B$29=$B$29,SUMIF(Food!$C:$C,E$9&$B$29&$C$29,Food!$X:$X),0),"") -> 0 | F31: =IFERROR(IF($B$29=$B$29,SUMIF(Food!$C:$C,F$9&$B$29&$C$29,Food!$X:$X),0),"") -> 0 | G31: =IFERROR(IF($B$29=$B$29,SUMIF(Food!$C:$C,G$9&$B$29&$C$29,Food!$X:$X),0),"") -> 0
A32: Wage Cost (DL) | B32: =IFERROR(IF($B$29=$B$29,SUMIF(Food!$C:$C,B$9&$B$29&$C$29,Food!$Z:$Z),0),"") -> 0 | C32: =IFERROR(IF($B$29=$B$29,SUMIF(Food!$C:$C,C$9&$B$29&$C$29,Food!$Z:$Z),0),"") -> 0 | D32: =IFERROR(IF($B$29=$B$29,SUMIF(Food!$C:$C,D$9&$B$29&$C$29,Food!$Z:$Z),0),"") -> 0 | E32: =IFERROR(IF($B$29=$B$29,SUMIF(Food!$C:$C,E$9&$B$29&$C$29,Food!$Z:$Z),0),"") -> 0 | F32: =IFERROR(IF($B$29=$B$29,SUMIF(Food!$C:$C,F$9&$B$29&$C$29,Food!$Z:$Z),0),"") -> 0 | G32: =IFERROR(IF($B$29=$B$29,SUMIF(Food!$C:$C,G$9&$B$29&$C$29,Food!$Z:$Z),0),"") -> 0
A33: Markup Food | B33: =IFERROR(IF($B$29=$B$29,SUMIF(Food!$C:$C,B$9&$B$29&$C$29,Food!$AB:$AB),0),"") -> 0 | C33: =IFERROR(IF($B$29=$B$29,SUMIF(Food!$C:$C,C$9&$B$29&$C$29,Food!$AB:$AB),0),"") -> 0 | D33: =IFERROR(IF($B$29=$B$29,SUMIF(Food!$C:$C,D$9&$B$29&$C$29,Food!$AB:$AB),0),"") -> 0 | E33: =IFERROR(IF($B$29=$B$29,SUMIF(Food!$C:$C,E$9&$B$29&$C$29,Food!$AB:$AB),0),"") -> 0 | F33: =IFERROR(IF($B$29=$B$29,SUMIF(Food!$C:$C,F$9&$B$29&$C$29,Food!$AB:$AB),0),"") -> 0 | G33: =IFERROR(IF($B$29=$B$29,SUMIF(Food!$C:$C,G$9&$B$29&$C$29,Food!$O:$O),0),"") -> 0
A34: Markup Labor | B34: =IFERROR(IF($B$29=$B$29,SUMIF(Food!$C:$C,B$9&$B$29&$C$29,Food!$AC:$AC),0),"") -> 0 | C34: =IFERROR(IF($B$29=$B$29,SUMIF(Food!$C:$C,C$9&$B$29&$C$29,Food!$AC:$AC),0),"") -> 0 | D34: =IFERROR(IF($B$29=$B$29,SUMIF(Food!$C:$C,D$9&$B$29&$C$29,Food!$AC:$AC),0),"") -> 0 | E34: =IFERROR(IF($B$29=$B$29,SUMIF(Food!$C:$C,E$9&$B$29&$C$29,Food!$AC:$AC),0),"") -> 0 | F34: =IFERROR(IF($B$29=$B$29,SUMIF(Food!$C:$C,F$9&$B$29&$C$29,Food!$AC:$AC),0),"") -> 0 | G34: =IFERROR(IF($B$29=$B$29,SUMIF(Food!$C:$C,G$9&$B$29&$C$29,Food!$P:$P),0),"") -> 0
A36: Per Pax Avg
A37: OVERHEAD | B37: ='P&L'!$K$30 -> 0 | C37: ='P&L'!$L$30 -> 0 | D37: ='P&L'!$M$30 -> 0 | E37: ='P&L'!$N$30 -> 0 | F37: ='P&L'!$O$30 -> 0 | G37: ='P&L'!$P$30 -> 0
A38: Food Cost (DM) | B38: =IFERROR(B31/B7," ") | C38: =IFERROR(C31/C7," ") -> 0 | D38: =IFERROR(D31/D7," ") -> 0 | E38: =IFERROR(E31/E7," ") -> 0 | F38: =IFERROR(F31/F7," ") | G38: =IFERROR(G31/G7," ") -> 0
A39: Wage Cost (DL) | B39: =IFERROR(B32/B7," ") | C39: =IFERROR(C32/C7," ") -> 0 | D39: =IFERROR(D32/D7," ") -> 0 | E39: =IFERROR(E32/E7," ") -> 0 | F39: =IFERROR(F32/F7," ") | G39: =IFERROR(G32/G7," ") -> 0
A40: Markup Food | B40: =IFERROR(B33/B8," ") | C40: =IFERROR(C33/C7," ") -> 0 | D40: =IFERROR(D33/D7," ") -> 0 | E40: =IFERROR(E33/E7," ") -> 0 | F40: =IFERROR(F33/F7," ") | G40: =IFERROR(G33/G7," ") -> 0
A41: Markup Labor | B41: =IFERROR(B34/B7," ") | C41: =IFERROR(C34/C7," ") -> 0 | D41: =IFERROR(D34/D7," ") -> 0 | E41: =IFERROR(E34/E7," ") -> 0 | F41: =IFERROR(F34/F7," ") | G41: =IFERROR(G34/G7," ") -> 0
A108: 388
A109: 787

Sheet Handling
A1: HANDLING CALCULATOR
B2: ALL AC TYPE
A3: STATION | B3: BNA | D3: Aircraft type | E3: ='FlightConfig '!B1 -> 350
A4: AC TYPE | B4: =+E3 -> 350 | C4: Long Hual with Food | D4: BNA | E4: FC | F4: BC | G4: EU | N4: CY | O4: Total
A5: # OF DAYS OPERATING | B5: =+'FlightConfig '!K2 -> 0 | D5: FLIGHT CONFIG | E5: ='FlightConfig '!B3 -> 0 | F5: ='FlightConfig '!C3 -> 34 | G5: ='FlightConfig '!D3 -> 48 | N5: ='FlightConfig '!G3+'FlightConfig '!F11 -> 7 | O5: =SUM(E5:N5) -> 89
A7: LABOR
A8: POSITION | B8: No. of SHIFTS | C8: HOURS | D8: SHIFTS/WK | E8: ANNUAL HOURS | F8: RATE | G8: EMP COST | N8: ANNUAL | O8: PER FLIGHT
A9: PACKER/QC | B9: 1 | C9: 1 | D9: =$B$5*B9 -> 0 | E9: =C9*D9*52 -> 0 | F9: 18 | G9: =F9*#REF! -> #REF! | N9: =E9*#REF! -> #REF! | O9: =(B9*#REF!)*C9 -> #REF! | Q9: EMD
A10: DISHWASHER | B10: 2 | C10: 2 | D10: =$B$5*B10 -> 0 | E10: =C10*D10*52 -> 0 | F10: 17 | G10: =F10*#REF! -> #REF! | N10: =E10*#REF! -> #REF! | O10: =(B10*#REF!)*C10 -> #REF! | Q10: Van Charge
A11: Ramp Coordinator | B11: 1 | C11: 2 | D11: =$B$5*B11 -> 0 | E11: =C11*D11*52 -> 0 | F11: 18 | G11: =F11*#REF! -> #REF! | N11: =E11*#REF! -> #REF! | O11: =(B11*#REF!)*C11 -> #REF! | Q11: Labor | R11: Tuck | T11: total | U11: Selling price
A12: INVENTORY CLERK | B12: 1 | C12: 0.5 | D12: =$B$5*B12 -> 0 | E12: =C12*D12*52 -> 0 | F12: 19 | G12: =F12*#REF! -> #REF! | N12: =E12*#REF! -> #REF! | O12: =(B12*#REF!)*C12 -> #REF! | Q12: =#REF!/2 -> #REF! | R12: 12 | T12: =Q12+R12 -> #REF! | U12: =T12+#REF! -> #REF!
A13: DRIVER | B13: 1 | C13: 2 | D13: =$B$5*B13 -> 0 | E13: =C13*D13*52 -> 0 | F13: 22 | G13: =F13*#REF! -> #REF! | N13: =E13*#REF! -> #REF! | O13: =(B13*#REF!)*C13 -> #REF!
A14: Total | N14: =SUM(N9:N13) -> #REF! | O14: =SUM(O9:O13) -> #REF!
A17: TRUCK COSTS | B17: No. of TRUCKS | C17: OP HOURS | D17: TTL OP HRS | E17: DEP./DAY | F17: DEP/HR APPLIED | G17: DEP $ | N17: MAIN/FEES/DAY | P17: MAIN COST | Q17: TOTAL COST | T17: FUEL COST CALCULATOR
A18: A380 TRUCKS | B18: 0 | C18: 0 | D18: =B18*C18 -> 0 | E18: =500000/10/365 -> 136.9863 | F18: =24/3 -> 8 | G18: =(E18/24)*F18*$B18 -> 0 | N18: =8000/365 -> 21.917808 | P18: =(N18/24)*$G18*$C18 -> 0 | Q18: =G18+#REF!+P18 -> #REF! | T18: ROUND TRIP MILES
A19: NARROWBODY TRUCKS | B19: 1 | C19: 2 | D19: =B19*C19 -> 2 | E19: =100000/365 -> 273.9726 | F19: 1 | G19: =E19*F19/'[1]P&L'!$P$2 -> 7.2098053 | N19: =5000/365 -> 13.69863 | P19: =(N19/24)*$F19*$B19 -> 0.57077626 | Q19: =G19+#REF!+P19 -> #REF! | T19: IDLE MILES
T20: TTL MILES
T21: MPG
A22: TOTAL HANDLING COST | C22: =SUM(O14,Q18,Q19) -> #REF! | T22: $/GAL
A23: MARK-UP | B23: =+'P&L'!$R$10 -> 0.13 | C23: =C22*B23 -> #REF! | E23: long hual | F23: short hual | T23: FUEL $
A24: TOTAL HANDLING PRICE | C24: =C22+C23 -> #REF! | D24: Turnaround | E24: 544.68493 | F24: 399.93493
A28: ASSUMPTIONS
A29: One coordinator
A30: Two trucks
A31: Two helpers
A36: WASHUP | O36: EQUIPMENT PACKING | U36: TRANSPORT & HANDLING | AB36: INTERNATIONAL TRASH
A37: Category | C37: Aircraft | O37: Packing Category | P37: Total Man Minutes per Aircraft | Q37: Price per MM | R37: ATL Price | U37: ATL | AB37: ATL
C38: A330-300 | D38: A330-900 | E38: A350-1000 | F38: A350-1000B | G38: B787-900 | O38: China / Glassware (inc cutlery) | S38: ='P&L'!$R$10 -> 0.13 | U38: Activity | V38: A330-300 | W38: A330-900 | X38: A350-1000 | Y38: A350-1000B | Z38: B787-900 | AB38: Aircraft type | AC38: Total Cost ($) | AD38: ='P&L'!$R$10 -> 0.13
O39: A330-300 | P39: 335 | Q39: 0.4 | R39: 134 | S39: =R39*(1+$S$38) -> 151.42 | U39: Turnaround (Strip and Load) | AB39: A330-300 | AC39: 300 | AD39: =AC39*(1+$S$38) -> 339
A40: Total factors - All flights | O40: A330-900 | P40: 335 | Q40: 0.4 | R40: 134 | S40: =R40*(1+$S$38) -> 151.42 | U40: Driver Man Minutes | V40: 480 | W40: 480 | X40: 560 | Y40: 560 | Z40: 480 | AB40: A330-900 | AC40: 300 | AD40: =AC40*(1+$S$38) -> 339
A41: J-Class Equipment | C41: Quantities | I41: MM | J41: MM | K41: MM | L41: MM | M41: MM | O41: A350-1000 | P41: 455 | Q41: 0.4 | R41: 182 | S41: =R41*(1+$S$38) -> 205.66 | U41: Price per Man Minutes | V41: 0.55 | W41: 0.55 | X41: 0.55 | Y41: 0.55 | Z41: 0.55 | AB41: A350-1000 | AC41: 350 | AD41: =AC41*(1+$S$38) -> 395.5
A42: Crockery | C42: 496 | D42: 480 | E42: 648 | F42: 340 | G42: 485 | H42: 0.3 | I42: =C42*$H$42 -> 148.8 | J42: =D42*$H$42 -> 144 | K42: =E42*$H$42 -> 194.4 | L42: =F42*$H$42 -> 102 | M42: =G42*$H$42 -> 145.5 | O42: A350-1000B | P42: 395 | Q42: 0.4 | R42: 158 | S42: =R42*(1+$S$38) -> 178.54 | U42: Driver Cost | V42: =V40*V41 -> 264 | W42: =W40*W41 -> 264 | X42: =X40*X41 -> 308 | Y42: =Y40*Y41 -> 308 | Z42: =Z40*Z41 -> 264 | AB42: A350-1000B | AC42: 350 | AD42: =AC42*(1+$S$38) -> 395.5
A43: Glassware | C43: 276 | D43: 284 | E43: 380 | F43: 326 | G43: 302 | H43: 1 | I43: =C43*$H$43 -> 276 | J43: =D43*$H$43 -> 284 | K43: =E43*$H$43 -> 380 | L43: =F43*$H$43 -> 326 | M43: =G43*$H$43 -> 302 | O43: B787-900 | P43: 345 | Q43: 0.4 | R43: 138 | S43: =R43*(1+$S$38) -> 155.94 | U43: Flt Co-ord Man Minutes | V43: 0 | W43: 0 | X43: 0 | Y43: 0 | Z43: 0 | AB43: B787-900 | AC43: 300 | AD43: =AC43*(1+$S$38) -> 339
A44: Cutlery* | C44: 414 | D44: 420 | E44: 492 | F44: 258 | G44: 414 | H44: 0.75 | I44: =C44*$H$44 -> 310.5 | J44: =D44*$H$44 -> 315 | K44: =E44*$H$44 -> 369 | L44: =F44*$H$44 -> 193.5 | M44: =G44*$H$44 -> 310.5 | O44: WY Bar alcohol packing | S44: ='P&L'!$R$10 -> 0.13 | U44: Price per Man Minutes | V44: 0 | W44: 0 | X44: 0 | Y44: 0 | Z44: 0
A45: Tray 1/1 | C45: 60 | D45: 60 | E45: 82 | F45: 34 | G45: 59 | H45: 0.3 | I45: =C45*$H$45 -> 18 | J45: =D45*$H$45 -> 18 | K45: =E45*$H$45 -> 24.6 | L45: =F45*$H$45 -> 10.2 | M45: =G45*$H$45 -> 17.7 | O45: A330-300 | P45: 150 | Q45: 0.4 | R45: 60 | S45: =R45*(1+$S$38) -> 67.8 | U45: Flt Co-ord Cost | V45: 0 | W45: 0 | X45: 0 | Y45: 0 | Z45: 0
A46: Sundries Items | C46: 0 | D46: 0 | E46: 0 | F46: 0 | G46: 0 | I46: =C46*$H$46 -> 0 | J46: =D46*$H$46 -> 0 | K46: =E46*$H$46 -> 0 | L46: =F46*$H$46 -> 0 | M46: =G46*$H$46 -> 0 | O46: A330-900 | P46: 150 | Q46: 0.4 | R46: 60 | S46: =R46*(1+$S$38) -> 67.8 | U46: Dispatch Man Minutes | V46: 30 | W46: 30 | X46: 30 | Y46: 30 | Z46: 30
A47: Total Volume of Washing per Aircraft | C47: 1246 | D47: 1244 | E47: 1602 | F47: 958 | G47: 1260 | I47: =SUM(I42:I46) -> 753.3 | J47: =SUM(J42:J46) -> 761 | K47: =SUM(K42:K46) -> 968 | L47: =SUM(L42:L46) -> 631.7 | M47: =SUM(M42:M46) -> 775.7 | O47: A350-1000 | P47: 200 | Q47: 0.4 | R47: 80 | S47: =R47*(1+$S$38) -> 90.4 | U47: Price per Man Minutes | V47: 0.44 | W47: 0.44 | X47: 0.44 | Y47: 0.44 | Z47: 0.44
A48: Total Man Minutes per Aircraft | C48: =I47 -> 753.3 | D48: =J47 -> 761 | E48: =K47 -> 968 | F48: =L47 -> 631.7 | G48: =M47 -> 775.7 | O48: A350-1000B | P48: 250 | Q48: 0.4 | R48: 100 | S48: =R48*(1+$S$38) -> 113 | U48: Dispatch Cost | V48: =V46*V47 -> 13.2 | W48: =W46*W47 -> 13.2 | X48: =X46*X47 -> 13.2 | Y48: =Y46*Y47 -> 13.2 | Z48: =Z46*Z47 -> 13.2
A49: Price per Man Minute | C49: 0.4 | D49: 0.4 | E49: 0.4 | F49: 0.4 | G49: 0.4 | O49: B787-900 | P49: 150 | Q49: 0.4 | R49: 60 | S49: =R49*(1+$S$38) -> 67.8 | U49: [Add resource as appropriate] | V49: 0 | W49: 0 | X49: 0 | Y49: 0 | Z49: 0
A50: Cost per Flight | C50: =C48*C49 -> 301.32 | D50: =D48*D49 -> 304.4 | E50: =E48*E49 -> 387.2 | F50: =F48*F49 -> 252.68 | G50: =G48*G49 -> 310.28 | O50: WY Bar packing | P50: 150 | Q50: 0.4 | R50: 60 | S50: =R50*(1+$S$38) -> 67.8 | U50: [Add resource labour rate as appropriate] | V50: 0 | W50: 0 | X50: 0 | Y50: 0 | Z50: 0
A51: W-Class Equipment | C51: Quantities | I51: MM | J51: MM | K51: MM | L51: MM | M51: MM | U51: Cost | V51: 0 | W51: 0 | X51: 0 | Y51: 0 | Z51: 0
A52: Crockery | C52: 374 | D52: 363 | E52: 444 | F52: 416 | G52: 283 | H52: 0.3 | I52: =$H$52*C52 -> 112.2 | J52: =$H$52*D52 -> 108.9 | K52: =$H$52*E52 -> 133.2 | L52: =$H$52*F52 -> 124.8 | M52: =$H$52*G52 -> 84.9 | U52: Total Cost Per Flight | V52: =V42+V45+V48+V51 -> 277.2 | W52: =W42+W45+W48+W51 -> 277.2 | X52: =X42+X45+X48+X51 -> 321.2 | Y52: =Y42+Y45+Y48+Y51 -> 321.2 | Z52: =Z42+Z45+Z48+Z51 -> 277.2
A53: Glassware | C53: 192 | D53: 184 | E53: 224 | F53: 224 | G53: 140 | H53: 1 | I53: =$H$53*C53 -> 192 | J53: =$H$53*D53 -> 184 | K53: =$H$53*E53 -> 224 | L53: =$H$53*F53 -> 224 | M53: =$H$53*G53 -> 140 | U53: ='P&L'!$R$10 -> 0.13 | V53: =V52*(1+$U$53) -> 313.236 | W53: =W52*(1+$U$53) -> 313.236 | X53: =X52*(1+$U$53) -> 362.956 | Y53: =Y52*(1+$U$53) -> 362.956 | Z53: =Z52*(1+$U$53) -> 313.236
A54: Cutlery* | C54: 288 | D54: 276 | E54: 336 | F54: 336 | G54: 210 | H54: 0.75 | I54: =$H$54*C54 -> 216 | J54: =$H$54*D54 -> 207 | K54: =$H$54*E54 -> 252 | L54: =$H$54*F54 -> 252 | M54: =$H$54*G54 -> 157.5 | U54: Strip Only
A55: Tray (1/1 & 1/2) | C55: 96 | D55: 92 | E55: 112 | F55: 112 | G55: 70 | H55: 0.3 | I55: =$H$55*C55 -> 28.8 | J55: =$H$55*D55 -> 27.6 | K55: =$H$55*E55 -> 33.6 | L55: =$H$55*F55 -> 33.6 | M55: =$H$55*G55 -> 21 | U55: Driver Man Minutes | V55: 360 | W55: 360 | X55: 420 | Y55: 420 | Z55: 360
A56: Sundries Items | C56: 0 | D56: 0 | E56: 0 | F56: 0 | G56: 0 | I56: =H56*C56 -> 0 | J56: =I56*D56 -> 0 | K56: =J56*E56 -> 0 | L56: =K56*F56 -> 0 | M56: =L56*G56 -> 0 | U56: Price per Man Minutes | V56: 0.55 | W56: 0.55 | X56: 0.55 | Y56: 0.55 | Z56: 0.55
A57: Total Volume of Washing per Aircraft | C57: 950 | D57: 915 | E57: 1116 | F57: 1088 | G57: 703 | I57: =SUM(I52:I56) -> 549 | J57: =SUM(J52:J56) -> 527.5 | K57: =SUM(K52:K56) -> 642.8 | L57: =SUM(L52:L56) -> 634.4 | M57: =SUM(M52:M56) -> 403.4 | U57: Driver Cost | V57: =V55*V56 -> 198 | W57: =W55*W56 -> 198 | X57: =X55*X56 -> 231 | Y57: =Y55*Y56 -> 231 | Z57: =Z55*Z56 -> 198
A58: Total Man Minutes per Aircraft | C58: =I57 -> 549 | D58: =J57 -> 527.5 | E58: =K57 -> 642.8 | F58: =L57 -> 634.4 | G58: =M57 -> 403.4 | U58: Flt Co-ord Man Minutes | V58: 0 | W58: 0 | X58: 0 | Y58: 0 | Z58: 0
A59: Price per Man Minute | C59: 0.4 | D59: 0.4 | E59: 0.4 | F59: 0.4 | G59: 0.4 | U59: Price per Man Minutes | V59: 0 | W59: 0 | X59: 0 | Y59: 0 | Z59: 0
A60: Cost per Flight | C60: =C58*C59 -> 219.6 | D60: =D58*D59 -> 211 | E60: =E58*E59 -> 257.12 | F60: =F58*F59 -> 253.76 | G60: =G58*G59 -> 161.36 | U60: Flt Co-ord Cost | V60: =V58*V59 -> 0 | W60: =W58*W59 -> 0 | X60: =X58*X59 -> 0 | Y60: =Y58*Y59 -> 0 | Z60: =Z58*Z59 -> 0
A61: Y-Class Equipment | C61: Quantities | I61: MM | J61: MM | K61: MM | L61: MM | M61: MM | U61: Dispatch Man Minutes | V61: 30 | W61: 30 | X61: 30 | Y61: 30 | Z61: 30
A62: Tray 1/2 | C62: 185 | D62: 184 | E62: 235 | F62: 325 | G62: 192 | H62: 0.25 | I62: =$H$62*C62 -> 46.25 | J62: =$H$62*D62 -> 46 | K62: =$H$62*E62 -> 58.75 | L62: =$H$62*F62 -> 81.25 | M62: =$H$62*G62 -> 48 | U62: Price per Man Minutes | V62: 0.44 | W62: 0.44 | X62: 0.44 | Y62: 0.44 | Z62: 0.44
A63: Plastics | C63: 185 | D63: 184 | E63: 235 | F63: 325 | G63: 192 | H63: 0.4 | I63: =$H$63*C63 -> 74 | J63: =$H$63*D63 -> 73.6 | K63: =$H$63*E63 -> 94 | L63: =$H$63*F63 -> 130 | M63: =$H$63*G63 -> 76.8 | U63: Dispatch Cost | V63: =V61*V62 -> 13.2 | W63: =W61*W62 -> 13.2 | X63: =X61*X62 -> 13.2 | Y63: =Y61*Y62 -> 13.2 | Z63: =Z61*Z62 -> 13.2
A64: Sundries Items | C64: 0 | D64: 0 | E64: 0 | F64: 0 | G64: 0 | H64: 0.25 | I64: =$H$64*C64 -> 0 | J64: =$H$64*D64 -> 0 | K64: =$H$64*E64 -> 0 | L64: =$H$64*F64 -> 0 | M64: =$H$64*G64 -> 0 | U64: [Add resource as appropriate] | V64: 0 | W64: 0 | X64: 0 | Y64: 0 | Z64: 0
A65: Total Volume of Washing per Aircraft | C65: 370 | D65: 368 | E65: 470 | F65: 650 | G65: 384 | I65: =$H$65*C65 -> 0 | J65: =$H$65*D65 -> 0 | K65: =$H$65*E65 -> 0 | L65: =$H$65*F65 -> 0 | M65: =$H$65*G65 -> 0 | U65: [Add resource labour rate as appropriate] | V65: 0 | W65: 0 | X65: 0 | Y65: 0 | Z65: 0
A66: Total Man Minutes per Aircraft | C66: =I66 -> 120.25 | D66: =J66 -> 119.6 | E66: =K66 -> 152.75 | F66: =L66 -> 211.25 | G66: =M66 -> 124.8 | I66: =SUM(I62:I65) -> 120.25 | J66: =SUM(J62:J65) -> 119.6 | K66: =SUM(K62:K65) -> 152.75 | L66: =SUM(L62:L65) -> 211.25 | M66: =SUM(M62:M65) -> 124.8 | U66: Cost | V66: =V64*V65 -> 0 | W66: =W64*W65 -> 0 | X66: =X64*X65 -> 0 | Y66: =Y64*Y65 -> 0 | Z66: =Z64*Z65 -> 0
A67: Price per Man Minute | C67: 0.4 | D67: 0.4 | E67: 0.4 | F67: 0.4 | G67: 0.4 | U67: Total Cost Per Flight | V67: =V57+V60+V63+V66 -> 211.2 | W67: =W57+W60+W63+W66 -> 211.2 | X67: =X57+X60+X63+X66 -> 244.2 | Y67: =Y57+Y60+Y63+Y66 -> 244.2 | Z67: =Z57+Z60+Z63+Z66 -> 211.2
A68: Cost per Flight | C68: =C66*C67 -> 48.1 | D68: =D66*D67 -> 47.84 | E68: =E66*E67 -> 61.1 | F68: =F66*F67 -> 84.5 | G68: =G66*G67 -> 49.92 | U68: ='P&L'!$R$10 -> 0.13 | V68: =V67*(1+$U$53) -> 238.656 | W68: =W67*(1+$U$53) -> 238.656 | X68: =X67*(1+$U$53) -> 275.946 | Y68: =Y67*(1+$U$53) -> 275.946 | Z68: =Z67*(1+$U$53) -> 238.656
A69: Carts, Ovens & Boxes | I69: MM | J69: MM | K69: MM | L69: MM | M69: MM | U69: Load Only
A70: Full Cart | C70: 23 | D70: 21 | E70: 29 | F70: 31 | G70: 27 | H70: 2.5 | I70: =C70*$H$70 -> 57.5 | J70: =D70*$H$70 -> 52.5 | K70: =E70*$H$70 -> 72.5 | L70: =F70*$H$70 -> 77.5 | M70: =G70*$H$70 -> 67.5 | U70: Driver Man Minutes | V70: 300 | W70: 300 | X70: 360 | Y70: 360 | Z70: 300
A71: Half Cart | C71: 5 | D71: 9 | E71: 15 | F71: 19 | G71: 6 | H71: 1.5 | I71: =C71*$H$71 -> 7.5 | J71: =D71*$H$71 -> 13.5 | K71: =E71*$H$71 -> 22.5 | L71: =F71*$H$71 -> 28.5 | M71: =G71*$H$71 -> 9 | U71: Price per Man Minutes | V71: 0.55 | W71: 0.55 | X71: 0.55 | Y71: 0.55 | Z71: 0.55
A72: Box | C72: 20 | D72: 23 | E72: 15 | F72: 10 | G72: 7 | H72: 0.3 | I72: =C72*$H$72 -> 6 | J72: =D72*$H$72 -> 6.9 | K72: =E72*$H$72 -> 4.5 | L72: =F72*$H$72 -> 3 | M72: =G72*$H$72 -> 2.1 | U72: Driver Cost | V72: =V70*V71 -> 165 | W72: =W70*W71 -> 165 | X72: =X70*X71 -> 198 | Y72: =Y70*Y71 -> 198 | Z72: =Z70*Z71 -> 165
A73: Oven | C73: 12 | D73: 12 | E73: 15 | F73: 18 | G73: 12 | H73: 0.3 | I73: =C73*$H$73 -> 3.6 | J73: =D73*$H$73 -> 3.6 | K73: =E73*$H$73 -> 4.5 | L73: =F73*$H$73 -> 5.4 | M73: =G73*$H$73 -> 3.6 | U73: Flt Co-ord Man Minutes | V73: 0 | W73: 0 | X73: 0 | Y73: 0 | Z73: 0
A74: Waste Cart | C74: 0 | D74: 0 | E74: 0 | F74: 0 | G74: 0 | H74: 1.5 | I74: =C74*$H$74 -> 0 | J74: =D74*$H$74 -> 0 | K74: =E74*$H$74 -> 0 | L74: =F74*$H$74 -> 0 | M74: =G74*$H$74 -> 0 | U74: Price per Man Minutes | V74: 0 | W74: 0 | X74: 0 | Y74: 0 | Z74: 0
A75: Drawer M11 | C75: 136 | D75: 150 | E75: 176 | F75: 184 | G75: 138 | H75: 0.3 | I75: =C75*$H$75 -> 40.8 | J75: =D75*$H$75 -> 45 | K75: =E75*$H$75 -> 52.8 | L75: =F75*$H$75 -> 55.2 | M75: =G75*$H$75 -> 41.4 | U75: Flt Co-ord Cost | V75: =V73*V74 -> 0 | W75: =W73*W74 -> 0 | X75: =X73*X74 -> 0 | Y75: =Y73*Y74 -> 0 | Z75: =Z73*Z74 -> 0
A76: Drawer M8 | C76: 44 | D76: 42 | E76: 45 | F76: 68 | G76: 38 | H76: 0.3 | I76: =C76*$H$76 -> 13.2 | J76: =D76*$H$76 -> 12.6 | K76: =E76*$H$76 -> 13.5 | L76: =F76*$H$76 -> 20.4 | M76: =G76*$H$76 -> 11.4 | U76: Dispatch Man Minutes | V76: 30 | W76: 30 | X76: 30 | Y76: 30 | Z76: 30
A77: Glass Racks | C77: 22 | D77: 22 | E77: 31 | F77: 22 | G77: 22 | H77: 0.3 | I77: =C77*$H$77 -> 6.6 | J77: =D77*$H$77 -> 6.6 | K77: =E77*$H$77 -> 9.3 | L77: =F77*$H$77 -> 6.6 | M77: =G77*$H$77 -> 6.6 | U77: Price per Man Minutes | V77: 0.44 | W77: 0.44 | X77: 0.44 | Y77: 0.44 | Z77: 0.44
A78: Total Volume of Washing per Aircraft | C78: 262 | D78: 279 | E78: 326 | F78: 352 | G78: 250 | I78: =SUM(I70:I77) -> 135.2 | J78: =SUM(J70:J77) -> 140.7 | K78: =SUM(K70:K77) -> 179.6 | L78: =SUM(L70:L77) -> 196.6 | M78: =SUM(M70:M77) -> 141.6 | U78: Dispatch Cost | V78: =V76*V77 -> 13.2 | W78: =W76*W77 -> 13.2 | X78: =X76*X77 -> 13.2 | Y78: =Y76*Y77 -> 13.2 | Z78: =Z76*Z77 -> 13.2
A79: Total Man Minutes per Aircraft | C79: =I78 -> 135.2 | D79: =J78 -> 140.7 | E79: =K78 -> 179.6 | F79: =L78 -> 196.6 | G79: =M78 -> 141.6 | U79: [Add resource as appropriate] | V79: 0 | W79: 0 | X79: 0 | Y79: 0 | Z79: 0
A80: Price per Man Minute | C80: 0.4 | D80: 0.4 | E80: 0.4 | F80: 0.4 | G80: 0.4 | U80: [Add resource labour rate as appropriate] | V80: 0 | W80: 0 | X80: 0 | Y80: 0 | Z80: 0
A81: Cost per Flight | C81: =C79*C80 -> 54.08 | D81: =D79*D80 -> 56.28 | E81: =E79*E80 -> 71.84 | F81: =F79*F80 -> 78.64 | G81: =G79*G80 -> 56.64 | U81: Cost | V81: =V79*V80 -> 0 | W81: =W79*W80 -> 0 | X81: =X79*X80 -> 0 | Y81: =Y79*Y80 -> 0 | Z81: =Z79*Z80 -> 0
U82: Total Cost Per Flight | V82: =V72+V75+V78+V81 -> 178.2 | W82: =W72+W75+W78+W81 -> 178.2 | X82: =X72+X75+X78+X81 -> 211.2 | Y82: =Y72+Y75+Y78+Y81 -> 211.2 | Z82: =Z72+Z75+Z78+Z81 -> 178.2
A83: Total Cost Per Flight ($) | B83: ATL | C83: =C50+C60+C68+C81 -> 623.1 | D83: =D50+D60+D68+D81 -> 619.52 | E83: =E50+E60+E68+E81 -> 777.26 | F83: =F50+F60+F68+F81 -> 669.58 | G83: =G50+G60+G68+G81 -> 578.2 | U83: ='P&L'!$R$10 -> 0.13 | V83: =V82*(1+$U$53) -> 201.366 | W83: =W82*(1+$U$53) -> 201.366 | X83: =X82*(1+$U$53) -> 238.656 | Y83: =Y82*(1+$U$53) -> 238.656 | Z83: =Z82*(1+$U$53) -> 201.366
B84: ='P&L'!$R$10 -> 0.13 | C84: =C83*(1+$U$53) -> 704.103 | D84: =D83*(1+$U$53) -> 700.0576 | E84: =E83*(1+$U$53) -> 878.3038 | F84: =F83*(1+$U$53) -> 756.6254 | G84: =G83*(1+$U$53) -> 653.366 | U84: Additional Activity
U85: Extra Truck Trip (one off fee if applicable) | V85: 215 | W85: 215 | X85: 215 | Y85: 215 | Z85: 215
U86: Aircraft Change Airside | V86: 215 | W86: 215 | X86: 215 | Y86: 215 | Z86: 215
U87: Extra Van Trip (one off fee if applicable) | V87: 50 | W87: 50 | X87: 50 | Y87: 50 | Z87: 50
U88: Garbage Removal (one off fee if applicable) | V88: 350 | W88: 350 | X88: 350 | Y88: 350 | Z88: 350
U90: Assumptions

Sheet FlightConfig 
A1: Aircraft type | B1: 350 | J1: WEEKS
A2: DFW | B2: FC | C2: BC | D2: EU | E2: EY | F2: TC | G2: CY | H2: Total | J2: FLIGHTS/WEEK
A3: FLIGHT CONFIG | B3: =IF($B$1=350,B17,IF($B$1=737,B23,IF($B$1=380,B23))) -> 0 | C3: =IF($B$1=350,C17,IF($B$1=737,C23,IF($B$1=380,C23))) -> 34 | D3: =IF($B$1=350,D17,IF($B$1=737,D23,IF($B$1=380,D23))) -> 48 | E3: =IF($B$1=350,E17,IF($B$1=737,E23,IF($B$1=380,E23))) -> 198 | F3: =IF($B$1=350,F17,IF($B$1=737,F23,IF($B$1=380,F23))) -> 0 | G3: =IF($B$1=350,G17,IF($B$1=737,G23,IF($B$1=380,G23))) -> 6 | H3: =IF($B$1=350,H17,IF($B$1=737,H23,IF($B$1=380,H23))) -> 286 | J3: FLTS PER YEAR
A4: LOAD FACTORS | B4: =+'P&L'!$R$4 -> 0.85 | C4: =+'P&L'!$R$4 -> 0.85 | D4: =+'P&L'!$R$4 -> 0.85 | E4: =+'P&L'!$R$4 -> 0.85 | F4: =+'P&L'!$R$4 -> 0.85 | G4: =+'P&L'!$R$4 -> 0.85 | J4: # OF CYCLES
A5: PAX COUNT | B5: =ROUNDUP(B3*B4,0) -> 0 | C5: =ROUNDUP(C3*C4,0) -> 29 | D5: =ROUNDUP(D3*D4,0) -> 41 | E5: =ROUNDUP(E3*E4,0) -> 169 | F5: =ROUNDUP(F3*F4,0) -> 0 | G5: =ROUNDUP(G3*G4,0) -> 6 | H5: =SUM(B5:G5) -> 245 | J5: FLTS PER CYCLE
A9: Aircraft type | B9: 787 | J9: WEEKS | K9: 52
A10: DFW | B10: FC | C10: BC | D10: EU | E10: EY | F10: TC | G10: CY | H10: Total | J10: FLIGHTS/WEEK | K10: 5
A11: FLIGHT CONFIG | B11: 0 | C11: 0 | D11: 36 | E11: 323 | F11: 1 | G11: 10 | H11: =SUM(B11:G11) -> 370 | J11: FLTS PER YEAR | K11: =K9*K10 -> 260
A12: LOAD FACTORS | B12: 1 | C12: 1 | D12: 1 | E12: 1 | F12: 1 | G12: 1 | J12: # OF CYCLES | K12: 1
A13: PAX COUNT | B13: =ROUNDUP(B11*B12,0) -> 0 | C13: =ROUNDUP(C11*C12,0) -> 0 | D13: =ROUNDUP(D11*D12,0) -> 36 | E13: =ROUNDUP(E11*E12,0) -> 323 | F13: =ROUNDUP(F11*F12,0) -> 1 | G13: =ROUNDUP(G11*G12,0) -> 10 | H13: =SUM(B13:G13) -> 370 | J13: FLTS PER CYCLE | K13: =K11/K12 -> 260
A14: 0
A15: Aircraft type | B15: 350 | J15: WEEKS | K15: 52
A16: DFW | B16: FC | C16: BC | D16: EU | E16: EY | F16: TC | G16: CY | H16: Total | J16: FLIGHTS/WEEK | K16: 7
A17: FLIGHT CONFIG | B17: =B29 -> 0 | C17: =C29 -> 34 | D17: =D29 -> 48 | E17: =E29 -> 198 | F17: =F29 -> 0 | G17: =G29 -> 6 | H17: =SUM(B17:G17) -> 286 | J17: FLTS PER YEAR | K17: =K15*K16 -> 364
A18: LOAD FACTORS | B18: =+'P&L'!$R$4 -> 0.85 | C18: =+'P&L'!$R$4 -> 0.85 | D18: =+'P&L'!$R$4 -> 0.85 | E18: =+'P&L'!$R$4 -> 0.85 | F18: =+'P&L'!$R$4 -> 0.85 | G18: =+'P&L'!$R$4 -> 0.85 | J18: # OF CYCLES | K18: 1
A19: PAX COUNT | B19: =ROUNDUP(B17*B18,0) -> 0 | C19: =ROUNDUP(C17*C18,0) -> 29 | D19: =ROUNDUP(D17*D18,0) -> 41 | E19: =ROUNDUP(E17*E18,0) -> 169 | F19: =ROUNDUP(F17*F18,0) -> 0 | G19: =ROUNDUP(G17*G18,0) -> 6 | H19: =SUM(B19:G19) -> 245 | J19: FLTS PER CYCLE | K19: 365
B21: 330 | J21: WEEKS | K21: 52
A22: DFW | B22: FC | C22: BC | D22: EU | E22: EY | F22: TC | G22: CY | H22: Total | J22: FLIGHTS/WEEK | K22: 7
A23: FLIGHT CONFIG | B23: =B35 -> 0 | C23: =C35 -> 30 | D23: =D35 -> 44 | E23: =E35 -> 184 | F23: =F35 -> 0 | G23: =G35 -> 6 | H23: =SUM(B23:G23) -> 264 | J23: FLTS PER YEAR | K23: =K21*K22 -> 364
A24: LOAD FACTORS | B24: =+'P&L'!$R$4 -> 0.85 | C24: =+'P&L'!$R$4 -> 0.85 | D24: =+'P&L'!$R$4 -> 0.85 | E24: =+'P&L'!$R$4 -> 0.85 | F24: =+'P&L'!$R$4 -> 0.85 | G24: =+'P&L'!$R$4 -> 0.85 | J24: # OF CYCLES | K24: 1
A25: PAX COUNT | B25: =ROUNDUP(B23*B24,0) -> 0 | C25: =ROUNDUP(C23*C24,0) -> 26 | D25: =ROUNDUP(D23*D24,0) -> 38 | E25: =ROUNDUP(E23*E24,0) -> 157 | F25: =ROUNDUP(F23*F24,0) -> 0 | G25: =ROUNDUP(G23*G24,0) -> 6 | H25: =SUM(B25:G25) -> 227 | J25: FLTS PER CYCLE | K25: 365
A28: AC350 | B28: FIRST CLASS | C28: BUSINESS CLASS | D28: PREMIUM ECONOMY CLASS | E28: ECONOMY CLASS | F28: TECH CREW CLASS | G28: CABIN CREW CLASS
B29: 0 | C29: 34 | D29: 48 | E29: 198 | G29: 6
A34: AC330 | B34: FIRST CLASS | C34: BUSINESS CLASS | D34: PREMIUM ECONOMY CLASS | E34: ECONOMY CLASS | F34: TECH CREW CLASS | G34: CABIN CREW CLASS
B35: 0 | C35: 30 | D35: 44 | E35: 184 | G35: 6

Sheet Food
X1: Per Flight | AG1: Annual
M2: 0.4 | O2: ='P&L'!R8 -> 0.15 | P2: ='P&L'!R9 -> 0.15
A3: CLASS | B3: CYCLE | D3: SERVICE | E3: Item # | G3: Description | H3: QTY | I3: RATIOS | J3: Volume Per Flight | K3: DM | L3: IE MM | M3: DL | N3: TOTAL COST | O3: Food Markup | P3: Labor Markup | Q3: Price | R3: Food+MU | S3: Labor +MU | T3: Total | W3: NM per flt | X3: DM per flt | Y3: MM per flt | Z3: DL per flt | AA3: Cost per flt | AB3: Food Markup per flt | AC3: Labor Markup Per flt | AD3: Revenue per flt | AF3: Annual NM cost | AG3: Annual DM | AH3: Annual MM | AI3: Annual DL | AJ3: Annual Cost | AK3: Annual Revenue
A5: BUSINESS CLASS | B5: 1 | C5: =CONCATENATE(A5&B5&F5) -> BUSINESS CLASS1 | E5: 1001 | G5: =VLOOKUP(E5,'FG MASTER'!$A$10:$AB$218,2,0) -> BC C1 DINNER GEORGIA PEACH CHILI WHIPPED BUTTER | H5: 1 | I5: 1 | J5: =IFERROR(IF(I5="std",H5,HLOOKUP(A5,'FlightConfig '!$B$28:$G$29,2,0)*I5),"") -> 34 | K5: =VLOOKUP(Food!E5,'FG MASTER'!$A$1:$AC$536,16,0) -> 0.47 | L5: =VLOOKUP(Food!E5,'FG MASTER'!$A$10:$AC$536,17,0) -> 0.5 | M5: =IFERROR(L5*$M$2,"") -> 0.2 | N5: =IFERROR((K5)+M5,"") -> 0.67 | O5: =IFERROR($K5*(1+$O$2)-$K5,0) -> 0.0705 | P5: =IFERROR($M5*(1+$P$2)-$M5,0) -> 0.03 | Q5: =SUM(N5:P5) -> 0.7705 | R5: =K5*(1+$O$2) -> 0.5405 | S5: =M5*(1+$P$2) -> 0.23 | T5: =R5+S5 -> 0.7705 | W5: =IFERROR(#REF!*J5,"") | X5: =IFERROR(K5*J5,"") -> 15.98 | Y5: =IFERROR(+L5*J5,"") -> 17 | Z5: =IFERROR(+M5*J5,"") -> 6.8 | AA5: =IFERROR(+N5*J5,"") -> 22.78 | AB5: =IFERROR(O5*$J5,"") -> 2.397 | AC5: =IFERROR(P5*$J5,"") -> 1.02 | AD5: =IFERROR(+Q5*J5,"") -> 26.197 | AF5: =IFERROR(W5*'FlightConfig '!$K$3,"") | AG5: =IFERROR(X5*'FlightConfig '!$K$17,"") -> 5816.72 | AH5: =IFERROR(Y5*'FlightConfig '!$K$17,"") -> 6188 | AI5: =IFERROR(Z5*'FlightConfig '!$K$17,"") -> 2475.2 | AJ5: =IFERROR(AA5*'FlightConfig '!$K$17,"") -> 8291.92 | AK5: =IFERROR(AB5*'FlightConfig '!$K$17,"") -> 872.508
A6: BUSINESS CLASS | B6: 1 | C6: =CONCATENATE(A6&B6&F6) -> BUSINESS CLASS1 | E6: 1002 | G6: =VLOOKUP(E6,'FG MASTER'!$A$10:$AB$218,2,0) -> BC C1 DINNER SWEETWATER BEET AND CHEESE ROLL | H6: 1 | I6: 0.5 | J6: =IFERROR(IF(I6="std",H6,HLOOKUP(A6,'FlightConfig '!$B$28:$G$29,2,0)*I6),"") -> 17 | K6: =VLOOKUP(Food!E6,'FG MASTER'!$A$1:$AC$536,16,0) -> 0.3 | L6: =VLOOKUP(Food!E6,'FG MASTER'!$A$10:$AC$536,17,0) -> 0.25 | M6: =IFERROR(L6*$M$2,"") -> 0.1 | N6: =IFERROR((K6)+M6,"") -> 0.4 | O6: =IFERROR($K6*(1+$O$2)-$K6,0) -> 0.045 | P6: =IFERROR($M6*(1+$P$2)-$M6,0) -> 0.015 | Q6: =SUM(N6:P6) -> 0.46 | R6: =K6*(1+$O$2) -> 0.345 | S6: =M6*(1+$P$2) -> 0.115 | T6: =R6+S6 -> 0.46 | W6: =IFERROR(#REF!*J6,"") | X6: =IFERROR(K6*J6,"") -> 5.1 | Y6: =IFERROR(+L6*J6,"") -> 4.25 | Z6: =IFERROR(+M6*J6,"") -> 1.7 | AA6: =IFERROR(+N6*J6,"") -> 6.8 | AB6: =IFERROR(O6*$J6,"") -> 0.765 | AC6: =IFERROR(P6*$J6,"") -> 0.255 | AD6: =IFERROR(+Q6*J6,"") -> 7.82 | AF6: =IFERROR(W6*'FlightConfig '!$K$3,"") | AG6: =IFERROR(X6*'FlightConfig '!$K$17,"") -> 1856.4 | AH6: =IFERROR(Y6*'FlightConfig '!$K$17,"") -> 1547 | AI6: =IFERROR(Z6*'FlightConfig '!$K$17,"") -> 618.8 | AJ6: =IFERROR(AA6*'FlightConfig '!$K$17,"") -> 2475.2 | AK6: =IFERROR(AB6*'FlightConfig '!$K$17,"") -> 278.46
A7: BUSINESS CLASS | B7: 1 | C7: =CONCATENATE(A7&B7&F7) -> BUSINESS CLASS1 | E7: 1003 | G7: =VLOOKUP(E7,'FG MASTER'!$A$10:$AB$218,2,0) -> BC C1 DINNER HERB FOCACCIA ROLL | H7: 1 | I7: 0.5 | J7: =IFERROR(IF(I7="std",H7,HLOOKUP(A7,'FlightConfig '!$B$28:$G$29,2,0)*I7),"") -> 17 | K7: =VLOOKUP(Food!E7,'FG MASTER'!$A$1:$AC$536,16,0) -> 0.14 | L7: =VLOOKUP(Food!E7,'FG MASTER'!$A$10:$AC$536,17,0) -> 0.25 | M7: =IFERROR(L7*$M$2,"") -> 0.1 | N7: =IFERROR((K7)+M7,"") -> 0.24 | O7: =IFERROR($K7*(1+$O$2)-$K7,0) -> 0.021 | P7: =IFERROR($M7*(1+$P$2)-$M7,0) -> 0.015 | Q7: =SUM(N7:P7) -> 0.276 | R7: =K7*(1+$O$2) -> 0.161 | S7: =M7*(1+$P$2) -> 0.115 | T7: =R7+S7 -> 0.276 | W7: =IFERROR(#REF!*J7,"") | X7: =IFERROR(K7*J7,"") -> 2.38 | Y7: =IFERROR(+L7*J7,"") -> 4.25 | Z7: =IFERROR(+M7*J7,"") -> 1.7 | AA7: =IFERROR(+N7*J7,"") -> 4.08 | AB7: =IFERROR(O7*$J7,"") -> 0.357 | AC7: =IFERROR(P7*$J7,"") -> 0.255 | AD7: =IFERROR(+Q7*J7,"") -> 4.692 | AF7: =IFERROR(W7*'FlightConfig '!$K$3,"") | AG7: =IFERROR(X7*'FlightConfig '!$K$17,"") -> 866.32 | AH7: =IFERROR(Y7*'FlightConfig '!$K$17,"") -> 1547 | AI7: =IFERROR(Z7*'FlightConfig '!$K$17,"") -> 618.8 | AJ7: =IFERROR(AA7*'FlightConfig '!$K$17,"") -> 1485.12 | AK7: =IFERROR(AB7*'FlightConfig '!$K$17,"") -> 129.948
A8: BUSINESS CLASS | B8: 1 | C8: =CONCATENATE(A8&B8&F8) -> BUSINESS CLASS1 | E8: 1004 | G8: =VLOOKUP(E8,'FG MASTER'!$A$10:$AB$218,2,0) -> BC C1 DINNER HHAWAIIAN ROLL | H8: 1 | I8: 0.5 | J8: =IFERROR(IF(I8="std",H8,HLOOKUP(A8,'FlightConfig '!$B$28:$G$29,2,0)*I8),"") -> 17 | K8: =VLOOKUP(Food!E8,'FG MASTER'!$A$1:$AC$536,16,0) -> 0.25 | L8: =VLOOKUP(Food!E8,'FG MASTER'!$A$10:$AC$536,17,0) -> 0.25 | M8: =IFERROR(L8*$M$2,"") -> 0.1 | N8: =IFERROR((K8)+M8,"") -> 0.35 | O8: =IFERROR($K8*(1+$O$2)-$K8,0) -> 0.0375 | P8: =IFERROR($M8*(1+$P$2)-$M8,0) -> 0.015 | Q8: =SUM(N8:P8) -> 0.4025 | R8: =K8*(1+$O$2) -> 0.2875 | S8: =M8*(1+$P$2) -> 0.115 | T8: =R8+S8 -> 0.4025 | W8: =IFERROR(#REF!*J8,"") | X8: =IFERROR(K8*J8,"") -> 4.25 | Y8: =IFERROR(+L8*J8,"") -> 4.25 | Z8: =IFERROR(+M8*J8,"") -> 1.7 | AA8: =IFERROR(+N8*J8,"") -> 5.95 | AB8: =IFERROR(O8*$J8,"") -> 0.6375 | AC8: =IFERROR(P8*$J8,"") -> 0.255 | AD8: =IFERROR(+Q8*J8,"") -> 6.8425 | AF8: =IFERROR(W8*'FlightConfig '!$K$3,"") | AG8: =IFERROR(X8*'FlightConfig '!$K$17,"") -> 1547 | AH8: =IFERROR(Y8*'FlightConfig '!$K$17,"") -> 1547 | AI8: =IFERROR(Z8*'FlightConfig '!$K$17,"") -> 618.8 | AJ8: =IFERROR(AA8*'FlightConfig '!$K$17,"") -> 2165.8 | AK8: =IFERROR(AB8*'FlightConfig '!$K$17,"") -> 232.05
A9: BUSINESS CLASS | B9: 1 | C9: =CONCATENATE(A9&B9&F9) -> BUSINESS CLASS1 | E9: 1005 | G9: =VLOOKUP(E9,'FG MASTER'!$A$10:$AB$218,2,0) -> BC C1 DINNER STARTER 1 NON VEG ROTATION 1 GRILLED PRAWN U10, MANGO CURRY AIOLI, LEMON HERB SLAW, MICRO CILANTRO, MANGO RELISH | H9: 1 | I9: 0.55 | J9: =IFERROR(IF(I9="std",H9,HLOOKUP(A9,'FlightConfig '!$B$28:$G$29,2,0)*I9),"") -> 18.7 | K9: =VLOOKUP(Food!E9,'FG MASTER'!$A$1:$AC$536,16,0) -> 2.87 | L9: =VLOOKUP(Food!E9,'FG MASTER'!$A$10:$AC$536,17,0) -> 4.25 | M9: =IFERROR(L9*$M$2,"") -> 1.7 | N9: =IFERROR((K9)+M9,"") -> 4.57 | O9: =IFERROR($K9*(1+$O$2)-$K9,0) -> 0.4305 | P9: =IFERROR($M9*(1+$P$2)-$M9,0) -> 0.255 | Q9: =SUM(N9:P9) -> 5.2555 | R9: =K9*(1+$O$2) -> 3.3005 | S9: =M9*(1+$P$2) -> 1.955 | T9: =R9+S9 -> 5.2555 | W9: =IFERROR(#REF!*J9,"") | X9: =IFERROR(K9*J9,"") -> 53.669 | Y9: =IFERROR(+L9*J9,"") -> 79.475 | Z9: =IFERROR(+M9*J9,"") -> 31.79 | AA9: =IFERROR(+N9*J9,"") -> 85.459 | AB9: =IFERROR(O9*$J9,"") -> 8.05035 | AC9: =IFERROR(P9*$J9,"") -> 4.7685 | AD9: =IFERROR(+Q9*J9,"") -> 98.27785 | AF9: =IFERROR(W9*'FlightConfig '!$K$3,"") | AG9: =IFERROR(X9*'FlightConfig '!$K$17,"") -> 19535.516 | AH9: =IFERROR(Y9*'FlightConfig '!$K$17,"") -> 28928.9 | AI9: =IFERROR(Z9*'FlightConfig '!$K$17,"") -> 11571.56 | AJ9: =IFERROR(AA9*'FlightConfig '!$K$17,"") -> 31107.076 | AK9: =IFERROR(AB9*'FlightConfig '!$K$17,"") -> 2930.3274
A10: BUSINESS CLASS | B10: 1 | C10: =CONCATENATE(A10&B10&F10) -> BUSINESS CLASS1 | E10: 1006 | G10: =VLOOKUP(E10,'FG MASTER'!$A$10:$AB$218,2,0) -> BC C1 DINNER STARTER 2 VEG ROTATION 1 BURRATA CHEESE, MARINATED TOMATO, BASIL OIL, MICRO BASIL. BALSAMIC REDUCTION | H10: 1 | I10: 0.55 | J10: =IFERROR(IF(I10="std",H10,HLOOKUP(A10,'FlightConfig '!$B$28:$G$29,2,0)*I10),"") -> 18.7 | K10: =VLOOKUP(Food!E10,'FG MASTER'!$A$1:$AC$536,16,0) -> 5.06 | L10: =VLOOKUP(Food!E10,'FG MASTER'!$A$10:$AC$536,17,0) -> 2.7 | M10: =IFERROR(L10*$M$2,"") -> 1.08 | N10: =IFERROR((K10)+M10,"") -> 6.14 | O10: =IFERROR($K10*(1+$O$2)-$K10,0) -> 0.759 | P10: =IFERROR($M10*(1+$P$2)-$M10,0) -> 0.162 | Q10: =SUM(N10:P10) -> 7.061 | R10: =K10*(1+$O$2) -> 5.819 | S10: =M10*(1+$P$2) -> 1.242 | T10: =R10+S10 -> 7.061 | W10: =IFERROR(#REF!*J10,"") | X10: =IFERROR(K10*J10,"") -> 94.622 | Y10: =IFERROR(+L10*J10,"") -> 50.49 | Z10: =IFERROR(+M10*J10,"") -> 20.196 | AA10: =IFERROR(+N10*J10,"") -> 114.818 | AB10: =IFERROR(O10*$J10,"") -> 14.1933 | AC10: =IFERROR(P10*$J10,"") -> 3.0294 | AD10: =IFERROR(+Q10*J10,"") -> 132.0407 | AF10: =IFERROR(W10*'FlightConfig '!$K$3,"") | AG10: =IFERROR(X10*'FlightConfig '!$K$17,"") -> 34442.408 | AH10: =IFERROR(Y10*'FlightConfig '!$K$17,"") -> 18378.36 | AI10: =IFERROR(Z10*'FlightConfig '!$K$17,"") -> 7351.344 | AJ10: =IFERROR(AA10*'FlightConfig '!$K$17,"") -> 41793.752 | AK10: =IFERROR(AB10*'FlightConfig '!$K$17,"") -> 5166.3612
A11: BUSINESS CLASS | B11: 1 | C11: =CONCATENATE(A11&B11&F11) -> BUSINESS CLASS1 | E11: 1007 | G11: =VLOOKUP(E11,'FG MASTER'!$A$10:$AB$218,2,0) -> BC C1 DINNER STARTER 1 NON VEG ROTATION 2 PROSCUTTIO WRAPPED PEACHES, FRISEE LETTUCE, WATERMELON, FETA CHEESE MINT LIME VINAIGRETTE | H11: 1 | I11: 0 | J11: =IFERROR(IF(I11="std",H11,HLOOKUP(A11,'FlightConfig '!$B$28:$G$29,2,0)*I11),"") -> 0 | K11: =VLOOKUP(Food!E11,'FG MASTER'!$A$1:$AC$536,16,0) -> 2.95 | L11: =VLOOKUP(Food!E11,'FG MASTER'!$A$10:$AC$536,17,0) -> 3.75 | M11: =IFERROR(L11*$M$2,"") -> 1.5 | N11: =IFERROR((K11)+M11,"") -> 4.45 | O11: =IFERROR($K11*(1+$O$2)-$K11,0) -> 0.4425 | P11: =IFERROR($M11*(1+$P$2)-$M11,0) -> 0.225 | Q11: =SUM(N11:P11) -> 5.1175 | R11: =K11*(1+$O$2) -> 3.3925 | S11: =M11*(1+$P$2) -> 1.725 | T11: =R11+S11 -> 5.1175 | W11: =IFERROR(#REF!*J11,"") | X11: =IFERROR(K11*J11,"") -> 0 | Y11: =IFERROR(+L11*J11,"") -> 0 | Z11: =IFERROR(+M11*J11,"") -> 0 | AA11: =IFERROR(+N11*J11,"") -> 0 | AB11: =IFERROR(O11*$J11,"") -> 0 | AC11: =IFERROR(P11*$J11,"") -> 0 | AD11: =IFERROR(+Q11*J11,"") -> 0 | AF11: =IFERROR(W11*'FlightConfig '!$K$3,"") | AG11: =IFERROR(X11*'FlightConfig '!$K$17,"") -> 0 | AH11: =IFERROR(Y11*'FlightConfig '!$K$17,"") -> 0 | AI11: =IFERROR(Z11*'FlightConfig '!$K$17,"") -> 0 | AJ11: =IFERROR(AA11*'FlightConfig '!$K$17,"") -> 0 | AK11: =IFERROR(AB11*'FlightConfig '!$K$17,"") -> 0
A12: BUSINESS CLASS | B12: 1 | C12: =CONCATENATE(A12&B12&F12) -> BUSINESS CLASS1 | E12: 1008 | G12: =VLOOKUP(E12,'FG MASTER'!$A$10:$AB$218,2,0) -> BC C1 DINNER STARTER 2 VEG ROTATION 2 POMENTO CHEESE STUFFED PEPPADEW PEPPER, ARUGULA, OLIVE OIL | H12: 1 | I12: 0 | J12: =IFERROR(IF(I12="std",H12,HLOOKUP(A12,'FlightConfig '!$B$28:$G$29,2,0)*I12),"") -> 0 | K12: =VLOOKUP(Food!E12,'FG MASTER'!$A$1:$AC$536,16,0) -> 1.59 | L12: =VLOOKUP(Food!E12,'FG MASTER'!$A$10:$AC$536,17,0) -> 4 | M12: =IFERROR(L12*$M$2,"") -> 1.6 | N12: =IFERROR((K12)+M12,"") -> 3.19 | O12: =IFERROR($K12*(1+$O$2)-$K12,0) -> 0.2385 | P12: =IFERROR($M12*(1+$P$2)-$M12,0) -> 0.24 | Q12: =SUM(N12:P12) -> 3.6685 | R12: =K12*(1+$O$2) -> 1.8285 | S12: =M12*(1+$P$2) -> 1.84 | T12: =R12+S12 -> 3.6685 | W12: =IFERROR(#REF!*J12,"") | X12: =IFERROR(K12*J12,"") -> 0 | Y12: =IFERROR(+L12*J12,"") -> 0 | Z12: =IFERROR(+M12*J12,"") -> 0 | AA12: =IFERROR(+N12*J12,"") -> 0 | AB12: =IFERROR(O12*$J12,"") -> 0 | AC12: =IFERROR(P12*$J12,"") -> 0 | AD12: =IFERROR(+Q12*J12,"") -> 0 | AF12: =IFERROR(W12*'FlightConfig '!$K$3,"") | AG12: =IFERROR(X12*'FlightConfig '!$K$17,"") -> 0 | AH12: =IFERROR(Y12*'FlightConfig '!$K$17,"") -> 0 | AI12: =IFERROR(Z12*'FlightConfig '!$K$17,"") -> 0 | AJ12: =IFERROR(AA12*'FlightConfig '!$K$17,"") -> 0 | AK12: =IFERROR(AB12*'FlightConfig '!$K$17,"") -> 0
A13: BUSINESS CLASS | B13: 1 | C13: =CONCATENATE(A13&B13&F13) -> BUSINESS CLASS1 | E13: 1009 | G13: =VLOOKUP(E13,'FG MASTER'!$A$10:$AB$218,2,0) -> BC C1 DINNER ENTRÉE 1 LEMON CONFIT CHICKEN LEG, LEMON CHICKIEN JUS, MASHED POTATOES, HARICOT VERT, LEMON AGRUMATO | H13: 1 | I13: 0.6 | J13: =IFERROR(IF(I13="std",H13,HLOOKUP(A13,'FlightConfig '!$B$28:$G$29,2,0)*I13),"") -> 20.4 | K13: =VLOOKUP(Food!E13,'FG MASTER'!$A$1:$AC$536,16,0) -> 4.28 | L13: =VLOOKUP(Food!E13,'FG MASTER'!$A$10:$AC$536,17,0) -> 4.25 | M13: =IFERROR(L13*$M$2,"") -> 1.7 | N13: =IFERROR((K13)+M13,"") -> 5.98 | O13: =IFERROR($K13*(1+$O$2)-$K13,0) -> 0.642 | P13: =IFERROR($M13*(1+$P$2)-$M13,0) -> 0.255 | Q13: =SUM(N13:P13) -> 6.877 | R13: =K13*(1+$O$2) -> 4.922 | S13: =M13*(1+$P$2) -> 1.955 | T13: =R13+S13 -> 6.877 | W13: =IFERROR(#REF!*J13,"") | X13: =IFERROR(K13*J13,"") -> 87.312 | Y13: =IFERROR(+L13*J13,"") -> 86.7 | Z13: =IFERROR(+M13*J13,"") -> 34.68 | AA13: =IFERROR(+N13*J13,"") -> 121.992 | AB13: =IFERROR(O13*$J13,"") -> 13.0968 | AC13: =IFERROR(P13*$J13,"") -> 5.202 | AD13: =IFERROR(+Q13*J13,"") -> 140.2908 | AF13: =IFERROR(W13*'FlightConfig '!$K$3,"") | AG13: =IFERROR(X13*'FlightConfig '!$K$17,"") -> 31781.568 | AH13: =IFERROR(Y13*'FlightConfig '!$K$17,"") -> 31558.8 | AI13: =IFERROR(Z13*'FlightConfig '!$K$17,"") -> 12623.52 | AJ13: =IFERROR(AA13*'FlightConfig '!$K$17,"") -> 44405.088 | AK13: =IFERROR(AB13*'FlightConfig '!$K$17,"") -> 4767.2352
A14: BUSINESS CLASS | B14: 1 | C14: =CONCATENATE(A14&B14&F14) -> BUSINESS CLASS1 | E14: 1010 | G14: =VLOOKUP(E14,'FG MASTER'!$A$10:$AB$218,2,0) -> BC C1 DINNER ENTRÉE 2 FOX BROCHTERS SMOKED PRESSED LAMB SHOULDER, BABY CARROT , PEARL ONION, PEA PUREE, MASHED POTATOES, THYME DEMI GLACE | H14: 1 | I14: 0.4 | J14: =IFERROR(IF(I14="std",H14,HLOOKUP(A14,'FlightConfig '!$B$28:$G$29,2,0)*I14),"") -> 13.6 | K14: =VLOOKUP(Food!E14,'FG MASTER'!$A$1:$AC$536,16,0) -> 9.3 | L14: =VLOOKUP(Food!E14,'FG MASTER'!$A$10:$AC$536,17,0) -> 7.5 | M14: =IFERROR(L14*$M$2,"") -> 3 | N14: =IFERROR((K14)+M14,"") -> 12.3 | O14: =IFERROR($K14*(1+$O$2)-$K14,0) -> 1.395 | P14: =IFERROR($M14*(1+$P$2)-$M14,0) -> 0.45 | Q14: =SUM(N14:P14) -> 14.145 | R14: =K14*(1+$O$2) -> 10.695 | S14: =M14*(1+$P$2) -> 3.45 | T14: =R14+S14 -> 14.145 | W14: =IFERROR(#REF!*J14,"") | X14: =IFERROR(K14*J14,"") -> 126.48 | Y14: =IFERROR(+L14*J14,"") -> 102 | Z14: =IFERROR(+M14*J14,"") -> 40.8 | AA14: =IFERROR(+N14*J14,"") -> 167.28 | AB14: =IFERROR(O14*$J14,"") -> 18.972 | AC14: =IFERROR(P14*$J14,"") -> 6.12 | AD14: =IFERROR(+Q14*J14,"") -> 192.372 | AF14: =IFERROR(W14*'FlightConfig '!$K$3,"") | AG14: =IFERROR(X14*'FlightConfig '!$K$17,"") -> 46038.72 | AH14: =IFERROR(Y14*'FlightConfig '!$K$17,"") -> 37128 | AI14: =IFERROR(Z14*'FlightConfig '!$K$17,"") -> 14851.2 | AJ14: =IFERROR(AA14*'FlightConfig '!$K$17,"") -> 60889.92 | AK14: =IFERROR(AB14*'FlightConfig '!$K$17,"") -> 6905.808
A15: BUSINESS CLASS | B15: 1 | C15: =CONCATENATE(A15&B15&F15) -> BUSINESS CLASS1 | E15: 1011 | G15: =VLOOKUP(E15,'FG MASTER'!$A$10:$AB$218,2,0) -> BC C1 DINNER ENTRÉE 3 TRUFFLE PARMESAN RISOTTO, BABY ZUCCHINI, WILD MUSHROOM CONSERVA, ASPARAGUS, RAITA SAUCE | H15: 1 | I15: 0.2 | J15: =IFERROR(IF(I15="std",H15,HLOOKUP(A15,'FlightConfig '!$B$28:$G$29,2,0)*I15),"") -> 6.8 | K15: =VLOOKUP(Food!E15,'FG MASTER'!$A$1:$AC$536,16,0) -> 3.41 | L15: =VLOOKUP(Food!E15,'FG MASTER'!$A$10:$AC$536,17,0) -> 4.25 | M15: =IFERROR(L15*$M$2,"") -> 1.7 | N15: =IFERROR((K15)+M15,"") -> 5.11 | O15: =IFERROR($K15*(1+$O$2)-$K15,0) -> 0.5115 | P15: =IFERROR($M15*(1+$P$2)-$M15,0) -> 0.255 | Q15: =SUM(N15:P15) -> 5.8765 | R15: =K15*(1+$O$2) -> 3.9215 | S15: =M15*(1+$P$2) -> 1.955 | T15: =R15+S15 -> 5.8765 | W15: =IFERROR(#REF!*J15,"") | X15: =IFERROR(K15*J15,"") -> 23.188 | Y15: =IFERROR(+L15*J15,"") -> 28.9 | Z15: =IFERROR(+M15*J15,"") -> 11.56 | AA15: =IFERROR(+N15*J15,"") -> 34.748 | AB15: =IFERROR(O15*$J15,"") -> 3.4782 | AC15: =IFERROR(P15*$J15,"") -> 1.734 | AD15: =IFERROR(+Q15*J15,"") -> 39.9602 | AF15: =IFERROR(W15*'FlightConfig '!$K$3,"") | AG15: =IFERROR(X15*'FlightConfig '!$K$17,"") -> 8440.432 | AH15: =IFERROR(Y15*'FlightConfig '!$K$17,"") -> 10519.6 | AI15: =IFERROR(Z15*'FlightConfig '!$K$17,"") -> 4207.84 | AJ15: =IFERROR(AA15*'FlightConfig '!$K$17,"") -> 12648.272 | AK15: =IFERROR(AB15*'FlightConfig '!$K$17,"") -> 1266.0648
A16: BUSINESS CLASS | B16: 1 | C16: =CONCATENATE(A16&B16&F16) -> BUSINESS CLASS1 | E16: 1012 | G16: =VLOOKUP(E16,'FG MASTER'!$A$10:$AB$218,2,0) -> BC C1 DINNER DESSERT COLD ROTATION 1 BANANA PUDDING CHEESECAKE, STREUSEL CRUMBLES, BLUEBERRIES | H16: 1 | I16: 0.5 | J16: =IFERROR(IF(I16="std",H16,HLOOKUP(A16,'FlightConfig '!$B$28:$G$29,2,0)*I16),"") -> 17 | K16: =VLOOKUP(Food!E16,'FG MASTER'!$A$1:$AC$536,16,0) -> 0.98 | L16: =VLOOKUP(Food!E16,'FG MASTER'!$A$10:$AC$536,17,0) -> 2 | M16: =IFERROR(L16*$M$2,"") -> 0.8 | N16: =IFERROR((K16)+M16,"") -> 1.78 | O16: =IFERROR($K16*(1+$O$2)-$K16,0) -> 0.147 | P16: =IFERROR($M16*(1+$P$2)-$M16,0) -> 0.12 | Q16: =SUM(N16:P16) -> 2.047 | R16: =K16*(1+$O$2) -> 1.127 | S16: =M16*(1+$P$2) -> 0.92 | T16: =R16+S16 -> 2.047 | W16: =IFERROR(#REF!*J16,"") | X16: =IFERROR(K16*J16,"") -> 16.66 | Y16: =IFERROR(+L16*J16,"") -> 34 | Z16: =IFERROR(+M16*J16,"") -> 13.6 | AA16: =IFERROR(+N16*J16,"") -> 30.26 | AB16: =IFERROR(O16*$J16,"") -> 2.499 | AC16: =IFERROR(P16*$J16,"") -> 2.04 | AD16: =IFERROR(+Q16*J16,"") -> 34.799 | AF16: =IFERROR(W16*'FlightConfig '!$K$3,"") | AG16: =IFERROR(X16*'FlightConfig '!$K$17,"") -> 6064.24 | AH16: =IFERROR(Y16*'FlightConfig '!$K$17,"") -> 12376 | AI16: =IFERROR(Z16*'FlightConfig '!$K$17,"") -> 4950.4 | AJ16: =IFERROR(AA16*'FlightConfig '!$K$17,"") -> 11014.64 | AK16: =IFERROR(AB16*'FlightConfig '!$K$17,"") -> 909.636
... A19: BUSINESS CLASS | B19: 1 | C19: =CONCATENATE(A19&B19&F19) -> BUSINESS CLASS1 | E19: 1015 | G19: =VLOOKUP(E19,'FG MASTER'!$A$10:$AB$218,2,0) -> BC C1 DINNER DESSERT HOT ROTATION 2 STICKY TOFFEE PUDDING, CHANTILLY CREAM, CROQUANT, TOFEE SAUCE | H19: 1 | I19: 0.5 | J19: =IFERROR(IF(I19="std",H19,HLOOKUP(A19,'FlightConfig '!$B$28:$G$29,2,0)*I19),"") -> 17 | K19: =VLOOKUP(Food!E19,'FG MASTER'!$A$1:$AC$536,16,0) -> 2.56 | L19: =VLOOKUP(Food!E19,'FG MASTER'!$A$10:$AC$536,17,0) -> 1.25 | M19: =IFERROR(L19*$M$2,"") -> 0.5 | N19: =IFERROR((K19)+M19,"") -> 3.06 | O19: =IFERROR($K19*(1+$O$2)-$K19,0) -> 0.384 | P19: =IFERROR($M19*(1+$P$2)-$M19,0) -> 0.075 | Q19: =SUM(N19:P19) -> 3.519 | R19: =K19*(1+$O$2) -> 2.944 | S19: =M19*(1+$P$2) -> 0.575 | T19: =R19+S19 -> 3.519 | W19: =IFERROR(#REF!*J19,"") | X19: =IFERROR(K19*J19,"") -> 43.52 | Y19: =IFERROR(+L19*J19,"") -> 21.25 | Z19: =IFERROR(+M19*J19,"") -> 8.5 | AA19: =IFERROR(+N19*J19,"") -> 52.02 | AB19: =IFERROR(O19*$J19,"") -> 6.528 | AC19: =IFERROR(P19*$J19,"") -> 1.275 | AD19: =IFERROR(+Q19*J19,"") -> 59.823 | AF19: =IFERROR(W19*'FlightConfig '!$K$3,"") | AG19: =IFERROR(X19*'FlightConfig '!$K$17,"") -> 15841.28 | AH19: =IFERROR(Y19*'FlightConfig '!$K$17,"") -> 7735 | AI19: =IFERROR(Z19*'FlightConfig '!$K$17,"") -> 3094 | AJ19: =IFERROR(AA19*'FlightConfig '!$K$17,"") -> 18935.28 | AK19: =IFERROR(AB19*'FlightConfig '!$K$17,"") -> 2376.192
A20: BUSINESS CLASS | B20: 1 | C20: =CONCATENATE(A20&B20&F20) -> BUSINESS CLASS1 | E20: 1016 | G20: =VLOOKUP(E20,'FG MASTER'!$A$10:$AB$218,2,0) -> BC C1 DINNER CHEESE PLATE DAIRY GRIFFIN, ASHER BLUE, GREEN HILL BRIE, ANGRY CUKES, MUSCADINE JELLY | H20: 1 | I20: 0.6 | J20: =IFERROR(IF(I20="std",H20,HLOOKUP(A20,'FlightConfig '!$B$28:$G$29,2,0)*I20),"") -> 20.4 | K20: 0 | L20: 0 | M20: =IFERROR(L20*$M$2,"") -> 0 | N20: =IFERROR((K20)+M20,"") -> 0 | O20: =IFERROR($K20*(1+$O$2)-$K20,0) -> 0 | P20: =IFERROR($M20*(1+$P$2)-$M20,0) -> 0 | Q20: =SUM(N20:P20) -> 0 | R20: =K20*(1+$O$2) -> 0 | S20: =M20*(1+$P$2) -> 0 | T20: =R20+S20 -> 0 | W20: =IFERROR(#REF!*J20,"") | X20: =IFERROR(K20*J20,"") -> 0 | Y20: =IFERROR(+L20*J20,"") -> 0 | Z20: =IFERROR(+M20*J20,"") -> 0 | AA20: =IFERROR(+N20*J20,"") -> 0 | AB20: =IFERROR(O20*$J20,"") -> 0 | AC20: =IFERROR(P20*$J20,"") -> 0 | AD20: =IFERROR(+Q20*J20,"") -> 0 | AF20: =IFERROR(W20*'FlightConfig '!$K$3,"") | AG20: =IFERROR(X20*'FlightConfig '!$K$17,"") -> 0 | AH20: =IFERROR(Y20*'FlightConfig '!$K$17,"") -> 0 | AI20: =IFERROR(Z20*'FlightConfig '!$K$17,"") -> 0 | AJ20: =IFERROR(AA20*'FlightConfig '!$K$17,"") -> 0 | AK20: =IFERROR(AB20*'FlightConfig '!$K$17,"") -> 0
A21: BUSINESS CLASS | B21: 1 | C21: =CONCATENATE(A21&B21&F21) -> BUSINESS CLASS1 | E21: 1017 | G21: =VLOOKUP(E21,'FG MASTER'!$A$10:$AB$218,2,0) -> BC C1 BREAKFAST ENTRÉE 1 SAVORY PECAN BELGIAN WAFFLE, FRIED CHICKEN, MAPLE SAUSAGE GRAVY, SCRAMBLE EGG | H21: 1 | I21: 0.5 | J21: =IFERROR(IF(I21="std",H21,HLOOKUP(A21,'FlightConfig '!$B$28:$G$29,2,0)*I21),"") -> 17 | K21: =VLOOKUP(Food!E21,'FG MASTER'!$A$1:$AC$536,16,0) -> 4.71 | L21: =VLOOKUP(Food!E21,'FG MASTER'!$A$10:$AC$536,17,0) -> 4.25 | M21: =IFERROR(L21*$M$2,"") -> 1.7 | N21: =IFERROR((K21)+M21,"") -> 6.41 | O21: =IFERROR($K21*(1+$O$2)-$K21,0) -> 0.7065 | P21: =IFERROR($M21*(1+$P$2)-$M21,0) -> 0.255 | Q21: =SUM(N21:P21) -> 7.3715 | R21: =K21*(1+$O$2) -> 5.4165 | S21: =M21*(1+$P$2) -> 1.955 | T21: =R21+S21 -> 7.3715 | W21: =IFERROR(#REF!*J21,"") | X21: =IFERROR(K21*J21,"") -> 80.07 | Y21: =IFERROR(+L21*J21,"") -> 72.25 | Z21: =IFERROR(+M21*J21,"") -> 28.9 | AA21: =IFERROR(+N21*J21,"") -> 108.97 | AB21: =IFERROR(O21*$J21,"") -> 12.0105 | AC21: =IFERROR(P21*$J21,"") -> 4.335 | AD21: =IFERROR(+Q21*J21,"") -> 125.3155 | AF21: =IFERROR(W21*'FlightConfig '!$K$3,"") | AG21: =IFERROR(X21*'FlightConfig '!$K$17,"") -> 29145.48 | AH21: =IFERROR(Y21*'FlightConfig '!$K$17,"") -> 26299 | AI21: =IFERROR(Z21*'FlightConfig '!$K$17,"") -> 10519.6 | AJ21: =IFERROR(AA21*'FlightConfig '!$K$17,"") -> 39665.08 | AK21: =IFERROR(AB21*'FlightConfig '!$K$17,"") -> 4371.822
A22: BUSINESS CLASS | B22: 1 | C22: =CONCATENATE(A22&B22&F22) -> BUSINESS CLASS1 | E22: 1018 | G22: =VLOOKUP(E22,'FG MASTER'!$A$10:$AB$218,2,0) -> BC C1 BREAKFAST ENTRÉE 2 SAVORY FRITTATA, MARINATED TOMATO, HASHBROWN, GREEN ONION MORNAY | H22: 1 | I22: 0.2 | J22: =IFERROR(IF(I22="std",H22,HLOOKUP(A22,'FlightConfig '!$B$28:$G$29,2,0)*I22),"") -> 6.8 | K22: =VLOOKUP(Food!E22,'FG MASTER'!$A$1:$AC$536,16,0) -> 2.29 | L22: =VLOOKUP(Food!E22,'FG MASTER'!$A$10:$AC$536,17,0) -> 4.5 | M22: =IFERROR(L22*$M$2,"") -> 1.8 | N22: =IFERROR((K22)+M22,"") -> 4.09 | O22: =IFERROR($K22*(1+$O$2)-$K22,0) -> 0.3435 | P22: =IFERROR($M22*(1+$P$2)-$M22,0) -> 0.27 | Q22: =SUM(N22:P22) -> 4.7035 | R22: =K22*(1+$O$2) -> 2.6335 | S22: =M22*(1+$P$2) -> 2.07 | T22: =R22+S22 -> 4.7035 | W22: =IFERROR(#REF!*J22,"") | X22: =IFERROR(K22*J22,"") -> 15.572 | Y22: =IFERROR(+L22*J22,"") -> 30.6 | Z22: =IFERROR(+M22*J22,"") -> 12.24 | AA22: =IFERROR(+N22*J22,"") -> 27.812 | AB22: =IFERROR(O22*$J22,"") -> 2.3358 | AC22: =IFERROR(P22*$J22,"") -> 1.836 | AD22: =IFERROR(+Q22*J22,"") -> 31.9838 | AF22: =IFERROR(W22*'FlightConfig '!$K$3,"") | AG22: =IFERROR(X22*'FlightConfig '!$K$17,"") -> 5668.208 | AH22: =IFERROR(Y22*'FlightConfig '!$K$17,"") -> 11138.4 | AI22: =IFERROR(Z22*'FlightConfig '!$K$17,"") -> 4455.36 | AJ22: =IFERROR(AA22*'FlightConfig '!$K$17,"") -> 10123.568 | AK22: =IFERROR(AB22*'FlightConfig '!$K$17,"") -> 850.2312
A23: BUSINESS CLASS | B23: 1 | C23: =CONCATENATE(A23&B23&F23) -> BUSINESS CLASS1 | E23: 1019 | G23: =VLOOKUP(E23,'FG MASTER'!$A$10:$AB$218,2,0) -> BC C1 BREAKFAST ENTRÉE 3 SWEET GREEK YOGURT PARFAIT, MANGO PINEAPPLE CHUTNEY, BLUSBERRY, COCONUT AND OAT GRANOLA | H23: 1 | I23: 0.3 | J23: =IFERROR(IF(I23="std",H23,HLOOKUP(A23,'FlightConfig '!$B$28:$G$29,2,0)*I23),"") -> 10.2 | K23: =VLOOKUP(Food!E23,'FG MASTER'!$A$1:$AC$536,16,0) -> 2.15 | L23: =VLOOKUP(Food!E23,'FG MASTER'!$A$10:$AC$536,17,0) -> 3.25 | M23: =IFERROR(L23*$M$2,"") -> 1.3 | N23: =IFERROR((K23)+M23,"") -> 3.45 | O23: =IFERROR($K23*(1+$O$2)-$K23,0) -> 0.3225 | P23: =IFERROR($M23*(1+$P$2)-$M23,0) -> 0.195 | Q23: =SUM(N23:P23) -> 3.9675 | R23: =K23*(1+$O$2) -> 2.4725 | S23: =M23*(1+$P$2) -> 1.495 | T23: =R23+S23 -> 3.9675 | W23: =IFERROR(#REF!*J23,"") | X23: =IFERROR(K23*J23,"") -> 21.93 | Y23: =IFERROR(+L23*J23,"") -> 33.15 | Z23: =IFERROR(+M23*J23,"") -> 13.26 | AA23: =IFERROR(+N23*J23,"") -> 35.19 | AB23: =IFERROR(O23*$J23,"") -> 3.2895 | AC23: =IFERROR(P23*$J23,"") -> 1.989 | AD23: =IFERROR(+Q23*J23,"") -> 40.4685 | AF23: =IFERROR(W23*'FlightConfig '!$K$3,"") | AG23: =IFERROR(X23*'FlightConfig '!$K$17,"") -> 7982.52 | AH23: =IFERROR(Y23*'FlightConfig '!$K$17,"") -> 12066.6 | AI23: =IFERROR(Z23*'FlightConfig '!$K$17,"") -> 4826.64 | AJ23: =IFERROR(AA23*'FlightConfig '!$K$17,"") -> 12809.16 | AK23: =IFERROR(AB23*'FlightConfig '!$K$17,"") -> 1197.378
A24: BUSINESS CLASS | B24: 1 | C24: =CONCATENATE(A24&B24&F24) -> BUSINESS CLASS1 | E24: 1020 | G24: =VLOOKUP(E24,'FG MASTER'!$A$10:$AB$218,2,0) -> BC C1 BREAKFAST SIDE 1 FRUIT SEASONAL 4 TYPES 130G | H24: 1 | I24: 0.5 | J24: =IFERROR(IF(I24="std",H24,HLOOKUP(A24,'FlightConfig '!$B$28:$G$29,2,0)*I24),"") -> 17 | K24: =VLOOKUP(Food!E24,'FG MASTER'!$A$1:$AC$536,16,0) -> 2 | L24: =VLOOKUP(Food!E24,'FG MASTER'!$A$10:$AC$536,17,0) -> 1.5 | M24: =IFERROR(L24*$M$2,"") -> 0.6 | N24: =IFERROR((K24)+M24,"") -> 2.6 | O24: =IFERROR($K24*(1+$O$2)-$K24,0) -> 0.3 | P24: =IFERROR($M24*(1+$P$2)-$M24,0) -> 0.09 | Q24: =SUM(N24:P24) -> 2.99 | R24: =K24*(1+$O$2) -> 2.3 | S24: =M24*(1+$P$2) -> 0.69 | T24: =R24+S24 -> 2.99 | W24: =IFERROR(#REF!*J24,"") | X24: =IFERROR(K24*J24,"") -> 34 | Y24: =IFERROR(+L24*J24,"") -> 25.5 | Z24: =IFERROR(+M24*J24,"") -> 10.2 | AA24: =IFERROR(+N24*J24,"") -> 44.2 | AB24: =IFERROR(O24*$J24,"") -> 5.1 | AC24: =IFERROR(P24*$J24,"") -> 1.53 | AD24: =IFERROR(+Q24*J24,"") -> 50.83 | AF24: =IFERROR(W24*'FlightConfig '!$K$3,"") | AG24: =IFERROR(X24*'FlightConfig '!$K$17,"") -> 12376 | AH24: =IFERROR(Y24*'FlightConfig '!$K$17,"") -> 9282 | AI24: =IFERROR(Z24*'FlightConfig '!$K$17,"") -> 3712.8 | AJ24: =IFERROR(AA24*'FlightConfig '!$K$17,"") -> 16088.8 | AK24: =IFERROR(AB24*'FlightConfig '!$K$17,"") -> 1856.4
A25: BUSINESS CLASS | B25: 1 | C25: =CONCATENATE(A25&B25&F25) -> BUSINESS CLASS1 | E25: 1021 | G25: =VLOOKUP(E25,'FG MASTER'!$A$10:$AB$218,2,0) -> BC C1 BREAKFAST SIDE 2 PEACH AND PECAN SCONE | H25: 1 | I25: 0.5 | J25: =IFERROR(IF(I25="std",H25,HLOOKUP(A25,'FlightConfig '!$B$28:$G$29,2,0)*I25),"") -> 17 | K25: =VLOOKUP(Food!E25,'FG MASTER'!$A$1:$AC$536,16,0) -> 1.18 | L25: =VLOOKUP(Food!E25,'FG MASTER'!$A$10:$AC$536,17,0) -> 2 | M25: =IFERROR(L25*$M$2,"") -> 0.8 | N25: =IFERROR((K25)+M25,"") -> 1.98 | O25: =IFERROR($K25*(1+$O$2)-$K25,0) -> 0.177 | P25: =IFERROR($M25*(1+$P$2)-$M25,0) -> 0.12 | Q25: =SUM(N25:P25) -> 2.277 | R25: =K25*(1+$O$2) -> 1.357 | S25: =M25*(1+$P$2) -> 0.92 | T25: =R25+S25 -> 2.277 | W25: =IFERROR(#REF!*J25,"") | X25: =IFERROR(K25*J25,"") -> 20.06 | Y25: =IFERROR(+L25*J25,"") -> 34 | Z25: =IFERROR(+M25*J25,"") -> 13.6 | AA25: =IFERROR(+N25*J25,"") -> 33.66 | AB25: =IFERROR(O25*$J25,"") -> 3.009 | AC25: =IFERROR(P25*$J25,"") -> 2.04 | AD25: =IFERROR(+Q25*J25,"") -> 38.709 | AF25: =IFERROR(W25*'FlightConfig '!$K$3,"") | AG25: =IFERROR(X25*'FlightConfig '!$K$17,"") -> 7301.84 | AH25: =IFERROR(Y25*'FlightConfig '!$K$17,"") -> 12376 | AI25: =IFERROR(Z25*'FlightConfig '!$K$17,"") -> 4950.4 | AJ25: =IFERROR(AA25*'FlightConfig '!$K$17,"") -> 12252.24 | AK25: =IFERROR(AB25*'FlightConfig '!$K$17,"") -> 1095.276
A26: BUSINESS CLASS | B26: 1 | C26: =CONCATENATE(A26&B26&F26) -> BUSINESS CLASS1 | E26: 1022 | G26: =VLOOKUP(E26,'FG MASTER'!$A$10:$AB$218,2,0) -> BC C1 BREAKFAST SIDE 3 YOGURT | H26: 1 | I26: 0 | J26: =IFERROR(IF(I26="std",H26,HLOOKUP(A26,'FlightConfig '!$B$28:$G$29,2,0)*I26),"") -> 0 | K26: =VLOOKUP(Food!E26,'FG MASTER'!$A$1:$AC$536,16,0) -> 0.44 | L26: =VLOOKUP(Food!E26,'FG MASTER'!$A$10:$AC$536,17,0) -> 0.5 | M26: =IFERROR(L26*$M$2,"") -> 0.2 | N26: =IFERROR((K26)+M26,"") -> 0.64 | O26: =IFERROR($K26*(1+$O$2)-$K26,0) -> 0.066 | P26: =IFERROR($M26*(1+$P$2)-$M26,0) -> 0.03 | Q26: =SUM(N26:P26) -> 0.736 | R26: =K26*(1+$O$2) -> 0.506 | S26: =M26*(1+$P$2) -> 0.23 | T26: =R26+S26 -> 0.736 | W26: =IFERROR(#REF!*J26,"") | X26: =IFERROR(K26*J26,"") -> 0 | Y26: =IFERROR(+L26*J26,"") -> 0 | Z26: =IFERROR(+M26*J26,"") -> 0 | AA26: =IFERROR(+N26*J26,"") -> 0 | AB26: =IFERROR(O26*$J26,"") -> 0 | AC26: =IFERROR(P26*$J26,"") -> 0 | AD26: =IFERROR(+Q26*J26,"") -> 0 | AF26: =IFERROR(W26*'FlightConfig '!$K$3,"") | AG26: =IFERROR(X26*'FlightConfig '!$K$17,"") -> 0 | AH26: =IFERROR(Y26*'FlightConfig '!$K$17,"") -> 0 | AI26: =IFERROR(Z26*'FlightConfig '!$K$17,"") -> 0 | AJ26: =IFERROR(AA26*'FlightConfig '!$K$17,"") -> 0 | AK26: =IFERROR(AB26*'FlightConfig '!$K$17,"") -> 0
A27: BUSINESS CLASS | B27: 1 | C27: =CONCATENATE(A27&B27&F27) -> BUSINESS CLASS1 | E27: 1023 | G27: =VLOOKUP(E27,'FG MASTER'!$A$10:$AB$218,2,0) -> BC C1 BREAKFAST SIDE 4 HOMEMADE GRANOLA | H27: 1 | I27: 0 | J27: =IFERROR(IF(I27="std",H27,HLOOKUP(A27,'FlightConfig '!$B$28:$G$29,2,0)*I27),"") -> 0 | K27: =VLOOKUP(Food!E27,'FG MASTER'!$A$1:$AC$536,16,0) -> 0.78 | L27: =VLOOKUP(Food!E27,'FG MASTER'!$A$10:$AC$536,17,0) -> 0.75 | M27: =IFERROR(L27*$M$2,"") -> 0.3 | N27: =IFERROR((K27)+M27,"") -> 1.08 | O27: =IFERROR($K27*(1+$O$2)-$K27,0) -> 0.117 | P27: =IFERROR($M27*(1+$P$2)-$M27,0) -> 0.045 | Q27: =SUM(N27:P27) -> 1.242 | R27: =K27*(1+$O$2) -> 0.897 | S27: =M27*(1+$P$2) -> 0.345 | T27: =R27+S27 -> 1.242 | W27: =IFERROR(#REF!*J27,"") | X27: =IFERROR(K27*J27,"") -> 0 | Y27: =IFERROR(+L27*J27,"") -> 0 | Z27: =IFERROR(+M27*J27,"") -> 0 | AA27: =IFERROR(+N27*J27,"") -> 0 | AB27: =IFERROR(O27*$J27,"") -> 0 | AC27: =IFERROR(P27*$J27,"") -> 0 | AD27: =IFERROR(+Q27*J27,"") -> 0 | AF27: =IFERROR(W27*'FlightConfig '!$K$3,"") | AG27: =IFERROR(X27*'FlightConfig '!$K$17,"") -> 0 | AH27: =IFERROR(Y27*'FlightConfig '!$K$17,"") -> 0 | AI27: =IFERROR(Z27*'FlightConfig '!$K$17,"") -> 0 | AJ27: =IFERROR(AA27*'FlightConfig '!$K$17,"") -> 0 | AK27: =IFERROR(AB27*'FlightConfig '!$K$17,"") -> 0
A28: BUSINESS CLASS | B28: 1 | C28: =CONCATENATE(A28&B28&F28) -> BUSINESS CLASS1 | E28: 1024 | G28: =VLOOKUP(E28,'FG MASTER'!$A$10:$AB$218,2,0) -> BC C1 BREAKFAST SIDE 5 MAPLE CINNAMON BIRCHER MUESLI | H28: 1 | I28: 0 | J28: =IFERROR(IF(I28="std",H28,HLOOKUP(A28,'FlightConfig '!$B$28:$G$29,2,0)*I28),"") -> 0 | K28: =VLOOKUP(Food!E28,'FG MASTER'!$A$1:$AC$536,16,0) -> 0.85 | L28: =VLOOKUP(Food!E28,'FG MASTER'!$A$10:$AC$536,17,0) -> 1 | M28: =IFERROR(L28*$M$2,"") -> 0.4 | N28: =IFERROR((K28)+M28,"") -> 1.25 | O28: =IFERROR($K28*(1+$O$2)-$K28,0) -> 0.1275 | P28: =IFERROR($M28*(1+$P$2)-$M28,0) -> 0.06 | Q28: =SUM(N28:P28) -> 1.4375 | R28: =K28*(1+$O$2) -> 0.9775 | S28: =M28*(1+$P$2) -> 0.46 | T28: =R28+S28 -> 1.4375 | W28: =IFERROR(#REF!*J28,"") | X28: =IFERROR(K28*J28,"") -> 0 | Y28: =IFERROR(+L28*J28,"") -> 0 | Z28: =IFERROR(+M28*J28,"") -> 0 | AA28: =IFERROR(+N28*J28,"") -> 0 | AB28: =IFERROR(O28*$J28,"") -> 0 | AC28: =IFERROR(P28*$J28,"") -> 0 | AD28: =IFERROR(+Q28*J28,"") -> 0 | AF28: =IFERROR(W28*'FlightConfig '!$K$3,"") | AG28: =IFERROR(X28*'FlightConfig '!$K$17,"") -> 0 | AH28: =IFERROR(Y28*'FlightConfig '!$K$17,"") -> 0 | AI28: =IFERROR(Z28*'FlightConfig '!$K$17,"") -> 0 | AJ28: =IFERROR(AA28*'FlightConfig '!$K$17,"") -> 0 | AK28: =IFERROR(AB28*'FlightConfig '!$K$17,"") -> 0
A29: BUSINESS CLASS | B29: 1 | C29: =CONCATENATE(A29&B29&F29) -> BUSINESS CLASS1 | E29: 1025 | G29: =VLOOKUP(E29,'FG MASTER'!$A$10:$AB$218,2,0) -> BC C1 BREAKFAST SIDE 6 CORN FLAKES | H29: 1 | I29: 0 | J29: =IFERROR(IF(I29="std",H29,HLOOKUP(A29,'FlightConfig '!$B$28:$G$29,2,0)*I29),"") -> 0 | K29: =VLOOKUP(Food!E29,'FG MASTER'!$A$1:$AC$536,16,0) -> 0.69 | L29: =VLOOKUP(Food!E29,'FG MASTER'!$A$10:$AC$536,17,0) -> 0.25 | M29: =IFERROR(L29*$M$2,"") -> 0.1 | N29: =IFERROR((K29)+M29,"") -> 0.79 | O29: =IFERROR($K29*(1+$O$2)-$K29,0) -> 0.1035 | P29: =IFERROR($M29*(1+$P$2)-$M29,0) -> 0.015 | Q29: =SUM(N29:P29) -> 0.9085 | R29: =K29*(1+$O$2) -> 0.7935 | S29: =M29*(1+$P$2) -> 0.115 | T29: =R29+S29 -> 0.9085 | W29: =IFERROR(#REF!*J29,"") | X29: =IFERROR(K29*J29,"") -> 0 | Y29: =IFERROR(+L29*J29,"") -> 0 | Z29: =IFERROR(+M29*J29,"") -> 0 | AA29: =IFERROR(+N29*J29,"") -> 0 | AB29: =IFERROR(O29*$J29,"") -> 0 | AC29: =IFERROR(P29*$J29,"") -> 0 | AD29: =IFERROR(+Q29*J29,"") -> 0 | AF29: =IFERROR(W29*'FlightConfig '!$K$3,"") | AG29: =IFERROR(X29*'FlightConfig '!$K$17,"") -> 0 | AH29: =IFERROR(Y29*'FlightConfig '!$K$17,"") -> 0 | AI29: =IFERROR(Z29*'FlightConfig '!$K$17,"") -> 0 | AJ29: =IFERROR(AA29*'FlightConfig '!$K$17,"") -> 0 | AK29: =IFERROR(AB29*'FlightConfig '!$K$17,"") -> 0
A30: BUSINESS CLASS | B30: 1 | C30: =CONCATENATE(A30&B30&F30) -> BUSINESS CLASS1 | E30: 1026 | G30: =VLOOKUP(E30,'FG MASTER'!$A$10:$AB$218,2,0) -> BC C1 BREAKFAST SIDE OPTION 1 FIRED CHICKEN BISCUIT WITH TOMATO JAM | H30: 1 | I30: 0 | J30: =IFERROR(IF(I30="std",H30,HLOOKUP(A30,'FlightConfig '!$B$28:$G$29,2,0)*I30),"") -> 0 | K30: =VLOOKUP(Food!E30,'FG MASTER'!$A$1:$AC$536,16,0) -> 1.14 | L30: =VLOOKUP(Food!E30,'FG MASTER'!$A$10:$AC$536,17,0) -> 2 | M30: =IFERROR(L30*$M$2,"") -> 0.8 | N30: =IFERROR((K30)+M30,"") -> 1.94 | O30: =IFERROR($K30*(1+$O$2)-$K30,0) -> 0.171 | P30: =IFERROR($M30*(1+$P$2)-$M30,0) -> 0.12 | Q30: =SUM(N30:P30) -> 2.231 | R30: =K30*(1+$O$2) -> 1.311 | S30: =M30*(1+$P$2) -> 0.92 | T30: =R30+S30 -> 2.231 | W30: =IFERROR(#REF!*J30,"") | X30: =IFERROR(K30*J30,"") -> 0 | Y30: =IFERROR(+L30*J30,"") -> 0 | Z30: =IFERROR(+M30*J30,"") -> 0 | AA30: =IFERROR(+N30*J30,"") -> 0 | AB30: =IFERROR(O30*$J30,"") -> 0 | AC30: =IFERROR(P30*$J30,"") -> 0 | AD30: =IFERROR(+Q30*J30,"") -> 0 | AF30: =IFERROR(W30*'FlightConfig '!$K$3,"") | AG30: =IFERROR(X30*'FlightConfig '!$K$17,"") -> 0 | AH30: =IFERROR(Y30*'FlightConfig '!$K$17,"") -> 0 | AI30: =IFERROR(Z30*'FlightConfig '!$K$17,"") -> 0 | AJ30: =IFERROR(AA30*'FlightConfig '!$K$17,"") -> 0 | AK30: =IFERROR(AB30*'FlightConfig '!$K$17,"") -> 0
A31: BUSINESS CLASS | B31: 1 | C31: =CONCATENATE(A31&B31&F31) -> BUSINESS CLASS1 | E31: 1027 | G31: =VLOOKUP(E31,'FG MASTER'!$A$10:$AB$218,2,0) -> BC C1 BREAKFAST SIDE OPTION 2 CHOCOLATE CROISSANT | H31: 1 | I31: 0 | J31: =IFERROR(IF(I31="std",H31,HLOOKUP(A31,'FlightConfig '!$B$28:$G$29,2,0)*I31),"") -> 0 | K31: =VLOOKUP(Food!E31,'FG MASTER'!$A$1:$AC$536,16,0) -> 1.16 | L31: =VLOOKUP(Food!E31,'FG MASTER'!$A$10:$AC$536,17,0) -> 0.5 | M31: =IFERROR(L31*$M$2,"") -> 0.2 | N31: =IFERROR((K31)+M31,"") -> 1.36 | O31: =IFERROR($K31*(1+$O$2)-$K31,0) -> 0.174 | P31: =IFERROR($M31*(1+$P$2)-$M31,0) -> 0.03 | Q31: =SUM(N31:P31) -> 1.564 | R31: =K31*(1+$O$2) -> 1.334 | S31: =M31*(1+$P$2) -> 0.23 | T31: =R31+S31 -> 1.564 | W31: =IFERROR(#REF!*J31,"") | X31: =IFERROR(K31*J31,"") -> 0 | Y31: =IFERROR(+L31*J31,"") -> 0 | Z31: =IFERROR(+M31*J31,"") -> 0 | AA31: =IFERROR(+N31*J31,"") -> 0 | AB31: =IFERROR(O31*$J31,"") -> 0 | AC31: =IFERROR(P31*$J31,"") -> 0 | AD31: =IFERROR(+Q31*J31,"") -> 0 | AF31: =IFERROR(W31*'FlightConfig '!$K$3,"") | AG31: =IFERROR(X31*'FlightConfig '!$K$17,"") -> 0 | AH31: =IFERROR(Y31*'FlightConfig '!$K$17,"") -> 0 | AI31: =IFERROR(Z31*'FlightConfig '!$K$17,"") -> 0 | AJ31: =IFERROR(AA31*'FlightConfig '!$K$17,"") -> 0 | AK31: =IFERROR(AB31*'FlightConfig '!$K$17,"") -> 0
A32: PREMIUM ECONOMY CLASS | B32: 1 | C32: =CONCATENATE(A32&B32&F32) -> PREMIUM ECONOMY CLASS1 | E32: 1028 | G32: =VLOOKUP(E32,'FG MASTER'!$A$10:$AB$218,2,0) -> PY C1 DINNER GEORGIA PEACH CHILI WHIPPED BUTTER | H32: 1 | I32: 1 | J32: =IFERROR(IF(I32="std",H32,HLOOKUP(A32,'FlightConfig '!$B$28:$G$29,2,0)*I32),"") -> 48 | K32: =VLOOKUP(Food!E32,'FG MASTER'!$A$1:$AC$536,16,0) -> 0.47 | L32: =VLOOKUP(Food!E32,'FG MASTER'!$A$10:$AC$536,17,0) -> 0.5 | M32: =IFERROR(L32*$M$2,"") -> 0.2 | N32: =IFERROR((K32)+M32,"") -> 0.67 | O32: =IFERROR($K32*(1+$O$2)-$K32,0) -> 0.0705 | P32: =IFERROR($M32*(1+$P$2)-$M32,0) -> 0.03 | Q32: =SUM(N32:P32) -> 0.7705 | R32: =K32*(1+$O$2) -> 0.5405 | S32: =M32*(1+$P$2) -> 0.23 | T32: =R32+S32 -> 0.7705 | W32: =IFERROR(#REF!*J32,"") | X32: =IFERROR(K32*J32,"") -> 22.56 | Y32: =IFERROR(+L32*J32,"") -> 24 | Z32: =IFERROR(+M32*J32,"") -> 9.6 | AA32: =IFERROR(+N32*J32,"") -> 32.16 | AB32: =IFERROR(O32*$J32,"") -> 3.384 | AC32: =IFERROR(P32*$J32,"") -> 1.44 | AD32: =IFERROR(+Q32*J32,"") -> 36.984 | AF32: =IFERROR(W32*'FlightConfig '!$K$3,"") | AG32: =IFERROR(X32*'FlightConfig '!$K$17,"") -> 8211.84 | AH32: =IFERROR(Y32*'FlightConfig '!$K$17,"") -> 8736 | AI32: =IFERROR(Z32*'FlightConfig '!$K$17,"") -> 3494.4 | AJ32: =IFERROR(AA32*'FlightConfig '!$K$17,"") -> 11706.24 | AK32: =IFERROR(AB32*'FlightConfig '!$K$17,"") -> 1231.776
... A74: CABIN CREW CLASS | B74: 1 | C74: =CONCATENATE(A74&B74&F74) -> CABIN CREW CLASS1 | E74: 1070 | G74: =VLOOKUP(E74,'FG MASTER'!$A$10:$AB$218,2,0) -> CREW C1 BREAKFAST HOT SANDWICH 3 FRIED CHICKEN BISCUIT | H74: 1 | I74: 1 | J74: =IFERROR(IF(I74="std",H74,HLOOKUP(A74,'FlightConfig '!$B$28:$G$29,2,0)*I74),"") -> 6 | K74: =VLOOKUP(Food!E74,'FG MASTER'!$A$1:$AC$536,16,0) -> 1.14 | L74: =VLOOKUP(Food!E74,'FG MASTER'!$A$10:$AC$536,17,0) -> 2 | M74: =IFERROR(L74*$M$2,"") -> 0.8 | N74: =IFERROR((K74)+M74,"") -> 1.94 | O74: =IFERROR($K74*(1+$O$2)-$K74,0) -> 0.171 | P74: =IFERROR($M74*(1+$P$2)-$M74,0) -> 0.12 | Q74: =SUM(N74:P74) -> 2.231 | R74: =K74*(1+$O$2) -> 1.311 | S74: =M74*(1+$P$2) -> 0.92 | T74: =R74+S74 -> 2.231 | W74: =IFERROR(#REF!*J74,"") | X74: =IFERROR(K74*J74,"") -> 6.84 | Y74: =IFERROR(+L74*J74,"") -> 12 | Z74: =IFERROR(+M74*J74,"") -> 4.8 | AA74: =IFERROR(+N74*J74,"") -> 11.64 | AB74: =IFERROR(O74*$J74,"") -> 1.026 | AC74: =IFERROR(P74*$J74,"") -> 0.72 | AD74: =IFERROR(+Q74*J74,"") -> 13.386 | AF74: =IFERROR(W74*'FlightConfig '!$K$3,"") | AG74: =IFERROR(X74*'FlightConfig '!$K$17,"") -> 2489.76 | AH74: =IFERROR(Y74*'FlightConfig '!$K$17,"") -> 4368 | AI74: =IFERROR(Z74*'FlightConfig '!$K$17,"") -> 1747.2 | AJ74: =IFERROR(AA74*'FlightConfig '!$K$17,"") -> 4236.96 | AK74: =IFERROR(AB74*'FlightConfig '!$K$17,"") -> 373.464
A75: BUSINESS CLASS | B75: 1 | C75: =CONCATENATE(A75&B75&F75) -> BUSINESS CLASS1110 | E75: 1001 | F75: 110 | G75: =VLOOKUP(E75,'FG MASTER'!$A$10:$AB$218,2,0) -> BC C1 DINNER GEORGIA PEACH CHILI WHIPPED BUTTER | H75: 1 | I75: 1 | J75: =IFERROR(IF(I75="std",H75,HLOOKUP(A75,'FlightConfig '!$B$34:$G$35,2,0)*I75),"") -> 30 | K75: =VLOOKUP(Food!E75,'FG MASTER'!$A$1:$AC$536,16,0) -> 0.47 | L75: =VLOOKUP(Food!E75,'FG MASTER'!$A$10:$AC$536,17,0) -> 0.5 | M75: =IFERROR(L75*$M$2,"") -> 0.2 | N75: =IFERROR((K75)+M75,"") -> 0.67 | O75: =IFERROR($K75*(1+$O$2)-$K75,0) -> 0.0705 | P75: =IFERROR($M75*(1+$P$2)-$M75,0) -> 0.03 | Q75: =SUM(N75:P75) -> 0.7705 | R75: =K75*(1+$O$2) -> 0.5405 | S75: =M75*(1+$P$2) -> 0.23 | T75: =R75+S75 -> 0.7705 | W75: =IFERROR(#REF!*J75,"") | X75: =IFERROR(K75*J75,"") -> 14.1 | Y75: =IFERROR(+L75*J75,"") -> 15 | Z75: =IFERROR(+M75*J75,"") -> 6 | AA75: =IFERROR(+N75*J75,"") -> 20.1 | AB75: =IFERROR(O75*$J75,"") -> 2.115 | AC75: =IFERROR(P75*$J75,"") -> 0.9 | AD75: =IFERROR(+Q75*J75,"") -> 23.115 | AF75: =IFERROR(W75*'FlightConfig '!$K$3,"") | AG75: =IFERROR(X75*'FlightConfig '!$K$23,"") -> 5132.4 | AH75: =IFERROR(Y75*'FlightConfig '!$K$23,"") -> 5460 | AI75: =IFERROR(Z75*'FlightConfig '!$K$23,"") -> 2184 | AJ75: =IFERROR(AA75*'FlightConfig '!$K$23,"") -> 7316.4 | AK75: =IFERROR(AB75*'FlightConfig '!$K$23,"") -> 769.86
A76: BUSINESS CLASS | B76: 1 | C76: =CONCATENATE(A76&B76&F76) -> BUSINESS CLASS1110 | E76: 1002 | F76: 110 | G76: =VLOOKUP(E76,'FG MASTER'!$A$10:$AB$218,2,0) -> BC C1 DINNER SWEETWATER BEET AND CHEESE ROLL | H76: 1 | I76: 0.5 | J76: =IFERROR(IF(I76="std",H76,HLOOKUP(A76,'FlightConfig '!$B$34:$G$35,2,0)*I76),"") -> 15 | K76: =VLOOKUP(Food!E76,'FG MASTER'!$A$1:$AC$536,16,0) -> 0.3 | L76: =VLOOKUP(Food!E76,'FG MASTER'!$A$10:$AC$536,17,0) -> 0.25 | M76: =IFERROR(L76*$M$2,"") -> 0.1 | N76: =IFERROR((K76)+M76,"") -> 0.4 | O76: =IFERROR($K76*(1+$O$2)-$K76,0) -> 0.045 | P76: =IFERROR($M76*(1+$P$2)-$M76,0) -> 0.015 | Q76: =SUM(N76:P76) -> 0.46 | R76: =K76*(1+$O$2) -> 0.345 | S76: =M76*(1+$P$2) -> 0.115 | T76: =R76+S76 -> 0.46 | W76: =IFERROR(#REF!*J76,"") | X76: =IFERROR(K76*J76,"") -> 4.5 | Y76: =IFERROR(+L76*J76,"") -> 3.75 | Z76: =IFERROR(+M76*J76,"") -> 1.5 | AA76: =IFERROR(+N76*J76,"") -> 6 | AB76: =IFERROR(O76*$J76,"") -> 0.675 | AC76: =IFERROR(P76*$J76,"") -> 0.225 | AD76: =IFERROR(+Q76*J76,"") -> 6.9 | AF76: =IFERROR(W76*'FlightConfig '!$K$3,"") | AG76: =IFERROR(X76*'FlightConfig '!$K$23,"") -> 1638 | AH76: =IFERROR(Y76*'FlightConfig '!$K$23,"") -> 1365 | AI76: =IFERROR(Z76*'FlightConfig '!$K$23,"") -> 546 | AJ76: =IFERROR(AA76*'FlightConfig '!$K$23,"") -> 2184 | AK76: =IFERROR(AB76*'FlightConfig '!$K$23,"") -> 245.7
A77: BUSINESS CLASS | B77: 1 | C77: =CONCATENATE(A77&B77&F77) -> BUSINESS CLASS1110 | E77: 1003 | F77: 110 | G77: =VLOOKUP(E77,'FG MASTER'!$A$10:$AB$218,2,0) -> BC C1 DINNER HERB FOCACCIA ROLL | H77: 1 | I77: 0.5 | J77: =IFERROR(IF(I77="std",H77,HLOOKUP(A77,'FlightConfig '!$B$34:$G$35,2,0)*I77),"") -> 15 | K77: =VLOOKUP(Food!E77,'FG MASTER'!$A$1:$AC$536,16,0) -> 0.14 | L77: =VLOOKUP(Food!E77,'FG MASTER'!$A$10:$AC$536,17,0) -> 0.25 | M77: =IFERROR(L77*$M$2,"") -> 0.1 | N77: =IFERROR((K77)+M77,"") -> 0.24 | O77: =IFERROR($K77*(1+$O$2)-$K77,0) -> 0.021 | P77: =IFERROR($M77*(1+$P$2)-$M77,0) -> 0.015 | Q77: =SUM(N77:P77) -> 0.276 | R77: =K77*(1+$O$2) -> 0.161 | S77: =M77*(1+$P$2) -> 0.115 | T77: =R77+S77 -> 0.276 | W77: =IFERROR(#REF!*J77,"") | X77: =IFERROR(K77*J77,"") -> 2.1 | Y77: =IFERROR(+L77*J77,"") -> 3.75 | Z77: =IFERROR(+M77*J77,"") -> 1.5 | AA77: =IFERROR(+N77*J77,"") -> 3.6 | AB77: =IFERROR(O77*$J77,"") -> 0.315 | AC77: =IFERROR(P77*$J77,"") -> 0.225 | AD77: =IFERROR(+Q77*J77,"") -> 4.14 | AF77: =IFERROR(W77*'FlightConfig '!$K$3,"") | AG77: =IFERROR(X77*'FlightConfig '!$K$23,"") -> 764.4 | AH77: =IFERROR(Y77*'FlightConfig '!$K$23,"") -> 1365 | AI77: =IFERROR(Z77*'FlightConfig '!$K$23,"") -> 546 | AJ77: =IFERROR(AA77*'FlightConfig '!$K$23,"") -> 1310.4 | AK77: =IFERROR(AB77*'FlightConfig '!$K$23,"") -> 114.66
A78: BUSINESS CLASS | B78: 1 | C78: =CONCATENATE(A78&B78&F78) -> BUSINESS CLASS1110 | E78: 1004 | F78: 110 | G78: =VLOOKUP(E78,'FG MASTER'!$A$10:$AB$218,2,0) -> BC C1 DINNER HHAWAIIAN ROLL | H78: 1 | I78: 0.5 | J78: =IFERROR(IF(I78="std",H78,HLOOKUP(A78,'FlightConfig '!$B$34:$G$35,2,0)*I78),"") -> 15 | K78: =VLOOKUP(Food!E78,'FG MASTER'!$A$1:$AC$536,16,0) -> 0.25 | L78: =VLOOKUP(Food!E78,'FG MASTER'!$A$10:$AC$536,17,0) -> 0.25 | M78: =IFERROR(L78*$M$2,"") -> 0.1 | N78: =IFERROR((K78)+M78,"") -> 0.35 | O78: =IFERROR($K78*(1+$O$2)-$K78,0) -> 0.0375 | P78: =IFERROR($M78*(1+$P$2)-$M78,0) -> 0.015 | Q78: =SUM(N78:P78) -> 0.4025 | R78: =K78*(1+$O$2) -> 0.2875 | S78: =M78*(1+$P$2) -> 0.115 | T78: =R78+S78 -> 0.4025 | W78: =IFERROR(#REF!*J78,"") | X78: =IFERROR(K78*J78,"") -> 3.75 | Y78: =IFERROR(+L78*J78,"") -> 3.75 | Z78: =IFERROR(+M78*J78,"") -> 1.5 | AA78: =IFERROR(+N78*J78,"") -> 5.25 | AB78: =IFERROR(O78*$J78,"") -> 0.5625 | AC78: =IFERROR(P78*$J78,"") -> 0.225 | AD78: =IFERROR(+Q78*J78,"") -> 6.0375 | AF78: =IFERROR(W78*'FlightConfig '!$K$3,"") | AG78: =IFERROR(X78*'FlightConfig '!$K$23,"") -> 1365 | AH78: =IFERROR(Y78*'FlightConfig '!$K$23,"") -> 1365 | AI78: =IFERROR(Z78*'FlightConfig '!$K$23,"") -> 546 | AJ78: =IFERROR(AA78*'FlightConfig '!$K$23,"") -> 1911 | AK78: =IFERROR(AB78*'FlightConfig '!$K$23,"") -> 204.75
A79: BUSINESS CLASS | B79: 1 | C79: =CONCATENATE(A79&B79&F79) -> BUSINESS CLASS1110 | E79: 1005 | F79: 110 | G79: =VLOOKUP(E79,'FG MASTER'!$A$10:$AB$218,2,0) -> BC C1 DINNER STARTER 1 NON VEG ROTATION 1 GRILLED PRAWN U10, MANGO CURRY AIOLI, LEMON HERB SLAW, MICRO CILANTRO, MANGO RELISH | H79: 1 | I79: 0.55 | J79: =IFERROR(IF(I79="std",H79,HLOOKUP(A79,'FlightConfig '!$B$34:$G$35,2,0)*I79),"") -> 16.5 | K79: =VLOOKUP(Food!E79,'FG MASTER'!$A$1:$AC$536,16,0) -> 2.87 | L79: =VLOOKUP(Food!E79,'FG MASTER'!$A$10:$AC$536,17,0) -> 4.25 | M79: =IFERROR(L79*$M$2,"") -> 1.7 | N79: =IFERROR((K79)+M79,"") -> 4.57 | O79: =IFERROR($K79*(1+$O$2)-$K79,0) -> 0.4305 | P79: =IFERROR($M79*(1+$P$2)-$M79,0) -> 0.255 | Q79: =SUM(N79:P79) -> 5.2555 | R79: =K79*(1+$O$2) -> 3.3005 | S79: =M79*(1+$P$2) -> 1.955 | T79: =R79+S79 -> 5.2555 | W79: =IFERROR(#REF!*J79,"") | X79: =IFERROR(K79*J79,"") -> 47.355 | Y79: =IFERROR(+L79*J79,"") -> 70.125 | Z79: =IFERROR(+M79*J79,"") -> 28.05 | AA79: =IFERROR(+N79*J79,"") -> 75.405 | AB79: =IFERROR(O79*$J79,"") -> 7.10325 | AC79: =IFERROR(P79*$J79,"") -> 4.2075 | AD79: =IFERROR(+Q79*J79,"") -> 86.71575 | AF79: =IFERROR(W79*'FlightConfig '!$K$3,"") | AG79: =IFERROR(X79*'FlightConfig '!$K$23,"") -> 17237.22 | AH79: =IFERROR(Y79*'FlightConfig '!$K$23,"") -> 25525.5 | AI79: =IFERROR(Z79*'FlightConfig '!$K$23,"") -> 10210.2 | AJ79: =IFERROR(AA79*'FlightConfig '!$K$23,"") -> 27447.42 | AK79: =IFERROR(AB79*'FlightConfig '!$K$23,"") -> 2585.583
A80: BUSINESS CLASS | B80: 1 | C80: =CONCATENATE(A80&B80&F80) -> BUSINESS CLASS1110 | E80: 1006 | F80: 110 | G80: =VLOOKUP(E80,'FG MASTER'!$A$10:$AB$218,2,0) -> BC C1 DINNER STARTER 2 VEG ROTATION 1 BURRATA CHEESE, MARINATED TOMATO, BASIL OIL, MICRO BASIL. BALSAMIC REDUCTION | H80: 1 | I80: 0.55 | J80: =IFERROR(IF(I80="std",H80,HLOOKUP(A80,'FlightConfig '!$B$34:$G$35,2,0)*I80),"") -> 16.5 | K80: =VLOOKUP(Food!E80,'FG MASTER'!$A$1:$AC$536,16,0) -> 5.06 | L80: =VLOOKUP(Food!E80,'FG MASTER'!$A$10:$AC$536,17,0) -> 2.7 | M80: =IFERROR(L80*$M$2,"") -> 1.08 | N80: =IFERROR((K80)+M80,"") -> 6.14 | O80: =IFERROR($K80*(1+$O$2)-$K80,0) -> 0.759 | P80: =IFERROR($M80*(1+$P$2)-$M80,0) -> 0.162 | Q80: =SUM(N80:P80) -> 7.061 | R80: =K80*(1+$O$2) -> 5.819 | S80: =M80*(1+$P$2) -> 1.242 | T80: =R80+S80 -> 7.061 | W80: =IFERROR(#REF!*J80,"") | X80: =IFERROR(K80*J80,"") -> 83.49 | Y80: =IFERROR(+L80*J80,"") -> 44.55 | Z80: =IFERROR(+M80*J80,"") -> 17.82 | AA80: =IFERROR(+N80*J80,"") -> 101.31 | AB80: =IFERROR(O80*$J80,"") -> 12.5235 | AC80: =IFERROR(P80*$J80,"") -> 2.673 | AD80: =IFERROR(+Q80*J80,"") -> 116.5065 | AF80: =IFERROR(W80*'FlightConfig '!$K$3,"") | AG80: =IFERROR(X80*'FlightConfig '!$K$23,"") -> 30390.36 | AH80: =IFERROR(Y80*'FlightConfig '!$K$23,"") -> 16216.2 | AI80: =IFERROR(Z80*'FlightConfig '!$K$23,"") -> 6486.48 | AJ80: =IFERROR(AA80*'FlightConfig '!$K$23,"") -> 36876.84 | AK80: =IFERROR(AB80*'FlightConfig '!$K$23,"") -> 4558.554
A81: BUSINESS CLASS | B81: 1 | C81: =CONCATENATE(A81&B81&F81) -> BUSINESS CLASS1110 | E81: 1007 | F81: 110 | G81: =VLOOKUP(E81,'FG MASTER'!$A$10:$AB$218,2,0) -> BC C1 DINNER STARTER 1 NON VEG ROTATION 2 PROSCUTTIO WRAPPED PEACHES, FRISEE LETTUCE, WATERMELON, FETA CHEESE MINT LIME VINAIGRETTE | H81: 1 | I81: 0 | J81: =IFERROR(IF(I81="std",H81,HLOOKUP(A81,'FlightConfig '!$B$34:$G$35,2,0)*I81),"") -> 0 | K81: =VLOOKUP(Food!E81,'FG MASTER'!$A$1:$AC$536,16,0) -> 2.95 | L81: =VLOOKUP(Food!E81,'FG MASTER'!$A$10:$AC$536,17,0) -> 3.75 | M81: =IFERROR(L81*$M$2,"") -> 1.5 | N81: =IFERROR((K81)+M81,"") -> 4.45 | O81: =IFERROR($K81*(1+$O$2)-$K81,0) -> 0.4425 | P81: =IFERROR($M81*(1+$P$2)-$M81,0) -> 0.225 | Q81: =SUM(N81:P81) -> 5.1175 | R81: =K81*(1+$O$2) -> 3.3925 | S81: =M81*(1+$P$2) -> 1.725 | T81: =R81+S81 -> 5.1175 | W81: =IFERROR(#REF!*J81,"") | X81: =IFERROR(K81*J81,"") -> 0 | Y81: =IFERROR(+L81*J81,"") -> 0 | Z81: =IFERROR(+M81*J81,"") -> 0 | AA81: =IFERROR(+N81*J81,"") -> 0 | AB81: =IFERROR(O81*$J81,"") -> 0 | AC81: =IFERROR(P81*$J81,"") -> 0 | AD81: =IFERROR(+Q81*J81,"") -> 0 | AF81: =IFERROR(W81*'FlightConfig '!$K$3,"") | AG81: =IFERROR(X81*'FlightConfig '!$K$23,"") -> 0 | AH81: =IFERROR(Y81*'FlightConfig '!$K$23,"") -> 0 | AI81: =IFERROR(Z81*'FlightConfig '!$K$23,"") -> 0 | AJ81: =IFERROR(AA81*'FlightConfig '!$K$23,"") -> 0 | AK81: =IFERROR(AB81*'FlightConfig '!$K$23,"") -> 0
A82: BUSINESS CLASS | B82: 1 | C82: =CONCATENATE(A82&B82&F82) -> BUSINESS CLASS1110 | E82: 1008 | F82: 110 | G82: =VLOOKUP(E82,'FG MASTER'!$A$10:$AB$218,2,0) -> BC C1 DINNER STARTER 2 VEG ROTATION 2 POMENTO CHEESE STUFFED PEPPADEW PEPPER, ARUGULA, OLIVE OIL | H82: 1 | I82: 0 | J82: =IFERROR(IF(I82="std",H82,HLOOKUP(A82,'FlightConfig '!$B$34:$G$35,2,0)*I82),"") -> 0 | K82: =VLOOKUP(Food!E82,'FG MASTER'!$A$1:$AC$536,16,0) -> 1.59 | L82: =VLOOKUP(Food!E82,'FG MASTER'!$A$10:$AC$536,17,0) -> 4 | M82: =IFERROR(L82*$M$2,"") -> 1.6 | N82: =IFERROR((K82)+M82,"") -> 3.19 | O82: =IFERROR($K82*(1+$O$2)-$K82,0) -> 0.2385 | P82: =IFERROR($M82*(1+$P$2)-$M82,0) -> 0.24 | Q82: =SUM(N82:P82) -> 3.6685 | R82: =K82*(1+$O$2) -> 1.8285 | S82: =M82*(1+$P$2) -> 1.84 | T82: =R82+S82 -> 3.6685 | W82: =IFERROR(#REF!*J82,"") | X82: =IFERROR(K82*J82,"") -> 0 | Y82: =IFERROR(+L82*J82,"") -> 0 | Z82: =IFERROR(+M82*J82,"") -> 0 | AA82: =IFERROR(+N82*J82,"") -> 0 | AB82: =IFERROR(O82*$J82,"") -> 0 | AC82: =IFERROR(P82*$J82,"") -> 0 | AD82: =IFERROR(+Q82*J82,"") -> 0 | AF82: =IFERROR(W82*'FlightConfig '!$K$3,"") | AG82: =IFERROR(X82*'FlightConfig '!$K$23,"") -> 0 | AH82: =IFERROR(Y82*'FlightConfig '!$K$23,"") -> 0 | AI82: =IFERROR(Z82*'FlightConfig '!$K$23,"") -> 0 | AJ82: =IFERROR(AA82*'FlightConfig '!$K$23,"") -> 0 | AK82: =IFERROR(AB82*'FlightConfig '!$K$23,"") -> 0
A83: BUSINESS CLASS | B83: 1 | C83: =CONCATENATE(A83&B83&F83) -> BUSINESS CLASS1110 | E83: 1009 | F83: 110 | G83: =VLOOKUP(E83,'FG MASTER'!$A$10:$AB$218,2,0) -> BC C1 DINNER ENTRÉE 1 LEMON CONFIT CHICKEN LEG, LEMON CHICKIEN JUS, MASHED POTATOES, HARICOT VERT, LEMON AGRUMATO | H83: 1 | I83: 0.6 | J83: =IFERROR(IF(I83="std",H83,HLOOKUP(A83,'FlightConfig '!$B$34:$G$35,2,0)*I83),"") -> 18 | K83: =VLOOKUP(Food!E83,'FG MASTER'!$A$1:$AC$536,16,0) -> 4.28 | L83: =VLOOKUP(Food!E83,'FG MASTER'!$A$10:$AC$536,17,0) -> 4.25 | M83: =IFERROR(L83*$M$2,"") -> 1.7 | N83: =IFERROR((K83)+M83,"") -> 5.98 | O83: =IFERROR($K83*(1+$O$2)-$K83,0) -> 0.642 | P83: =IFERROR($M83*(1+$P$2)-$M83,0) -> 0.255 | Q83: =SUM(N83:P83) -> 6.877 | R83: =K83*(1+$O$2) -> 4.922 | S83: =M83*(1+$P$2) -> 1.955 | T83: =R83+S83 -> 6.877 | W83: =IFERROR(#REF!*J83,"") | X83: =IFERROR(K83*J83,"") -> 77.04 | Y83: =IFERROR(+L83*J83,"") -> 76.5 | Z83: =IFERROR(+M83*J83,"") -> 30.6 | AA83: =IFERROR(+N83*J83,"") -> 107.64 | AB83: =IFERROR(O83*$J83,"") -> 11.556 | AC83: =IFERROR(P83*$J83,"") -> 4.59 | AD83: =IFERROR(+Q83*J83,"") -> 123.786 | AF83: =IFERROR(W83*'FlightConfig '!$K$3,"") | AG83: =IFERROR(X83*'FlightConfig '!$K$23,"") -> 28042.56 | AH83: =IFERROR(Y83*'FlightConfig '!$K$23,"") -> 27846 | AI83: =IFERROR(Z83*'FlightConfig '!$K$23,"") -> 11138.4 | AJ83: =IFERROR(AA83*'FlightConfig '!$K$23,"") -> 39180.96 | AK83: =IFERROR(AB83*'FlightConfig '!$K$23,"") -> 4206.384
A84: BUSINESS CLASS | B84: 1 | C84: =CONCATENATE(A84&B84&F84) -> BUSINESS CLASS1110 | E84: 1010 | F84: 110 | G84: =VLOOKUP(E84,'FG MASTER'!$A$10:$AB$218,2,0) -> BC C1 DINNER ENTRÉE 2 FOX BROCHTERS SMOKED PRESSED LAMB SHOULDER, BABY CARROT , PEARL ONION, PEA PUREE, MASHED POTATOES, THYME DEMI GLACE | H84: 1 | I84: 0.4 | J84: =IFERROR(IF(I84="std",H84,HLOOKUP(A84,'FlightConfig '!$B$34:$G$35,2,0)*I84),"") -> 12 | K84: =VLOOKUP(Food!E84,'FG MASTER'!$A$1:$AC$536,16,0) -> 9.3 | L84: =VLOOKUP(Food!E84,'FG MASTER'!$A$10:$AC$536,17,0) -> 7.5 | M84: =IFERROR(L84*$M$2,"") -> 3 | N84: =IFERROR((K84)+M84,"") -> 12.3 | O84: =IFERROR($K84*(1+$O$2)-$K84,0) -> 1.395 | P84: =IFERROR($M84*(1+$P$2)-$M84,0) -> 0.45 | Q84: =SUM(N84:P84) -> 14.145 | R84: =K84*(1+$O$2) -> 10.695 | S84: =M84*(1+$P$2) -> 3.45 | T84: =R84+S84 -> 14.145 | W84: =IFERROR(#REF!*J84,"") | X84: =IFERROR(K84*J84,"") -> 111.6 | Y84: =IFERROR(+L84*J84,"") -> 90 | Z84: =IFERROR(+M84*J84,"") -> 36 | AA84: =IFERROR(+N84*J84,"") -> 147.6 | AB84: =IFERROR(O84*$J84,"") -> 16.74 | AC84: =IFERROR(P84*$J84,"") -> 5.4 | AD84: =IFERROR(+Q84*J84,"") -> 169.74 | AF84: =IFERROR(W84*'FlightConfig '!$K$3,"") | AG84: =IFERROR(X84*'FlightConfig '!$K$23,"") -> 40622.4 | AH84: =IFERROR(Y84*'FlightConfig '!$K$23,"") -> 32760 | AI84: =IFERROR(Z84*'FlightConfig '!$K$23,"") -> 13104 | AJ84: =IFERROR(AA84*'FlightConfig '!$K$23,"") -> 53726.4 | AK84: =IFERROR(AB84*'FlightConfig '!$K$23,"") -> 6093.36
A85: BUSINESS CLASS | B85: 1 | C85: =CONCATENATE(A85&B85&F85) -> BUSINESS CLASS1110 | E85: 1011 | F85: 110 | G85: =VLOOKUP(E85,'FG MASTER'!$A$10:$AB$218,2,0) -> BC C1 DINNER ENTRÉE 3 TRUFFLE PARMESAN RISOTTO, BABY ZUCCHINI, WILD MUSHROOM CONSERVA, ASPARAGUS, RAITA SAUCE | H85: 1 | I85: 0.2 | J85: =IFERROR(IF(I85="std",H85,HLOOKUP(A85,'FlightConfig '!$B$34:$G$35,2,0)*I85),"") -> 6 | K85: =VLOOKUP(Food!E85,'FG MASTER'!$A$1:$AC$536,16,0) -> 3.41 | L85: =VLOOKUP(Food!E85,'FG MASTER'!$A$10:$AC$536,17,0) -> 4.25 | M85: =IFERROR(L85*$M$2,"") -> 1.7 | N85: =IFERROR((K85)+M85,"") -> 5.11 | O85: =IFERROR($K85*(1+$O$2)-$K85,0) -> 0.5115 | P85: =IFERROR($M85*(1+$P$2)-$M85,0) -> 0.255 | Q85: =SUM(N85:P85) -> 5.8765 | R85: =K85*(1+$O$2) -> 3.9215 | S85: =M85*(1+$P$2) -> 1.955 | T85: =R85+S85 -> 5.8765 | W85: =IFERROR(#REF!*J85,"") | X85: =IFERROR(K85*J85,"") -> 20.46 | Y85: =IFERROR(+L85*J85,"") -> 25.5 | Z85: =IFERROR(+M85*J85,"") -> 10.2 | AA85: =IFERROR(+N85*J85,"") -> 30.66 | AB85: =IFERROR(O85*$J85,"") -> 3.069 | AC85: =IFERROR(P85*$J85,"") -> 1.53 | AD85: =IFERROR(+Q85*J85,"") -> 35.259 | AF85: =IFERROR(W85*'FlightConfig '!$K$3,"") | AG85: =IFERROR(X85*'FlightConfig '!$K$23,"") -> 7447.44 | AH85: =IFERROR(Y85*'FlightConfig '!$K$23,"") -> 9282 | AI85: =IFERROR(Z85*'FlightConfig '!$K$23,"") -> 3712.8 | AJ85: =IFERROR(AA85*'FlightConfig '!$K$23,"") -> 11160.24 | AK85: =IFERROR(AB85*'FlightConfig '!$K$23,"") -> 1117.116
A86: BUSINESS CLASS | B86: 1 | C86: =CONCATENATE(A86&B86&F86) -> BUSINESS CLASS1110 | E86: 1012 | F86: 110 | G86: =VLOOKUP(E86,'FG MASTER'!$A$10:$AB$218,2,0) -> BC C1 DINNER DESSERT COLD ROTATION 1 BANANA PUDDING CHEESECAKE, STREUSEL CRUMBLES, BLUEBERRIES | H86: 1 | I86: 0.5 | J86: =IFERROR(IF(I86="std",H86,HLOOKUP(A86,'FlightConfig '!$B$34:$G$35,2,0)*I86),"") -> 15 | K86: =VLOOKUP(Food!E86,'FG MASTER'!$A$1:$AC$536,16,0) -> 0.98 | L86: =VLOOKUP(Food!E86,'FG MASTER'!$A$10:$AC$536,17,0) -> 2 | M86: =IFERROR(L86*$M$2,"") -> 0.8 | N86: =IFERROR((K86)+M86,"") -> 1.78 | O86: =IFERROR($K86*(1+$O$2)-$K86,0) -> 0.147 | P86: =IFERROR($M86*(1+$P$2)-$M86,0) -> 0.12 | Q86: =SUM(N86:P86) -> 2.047 | R86: =K86*(1+$O$2) -> 1.127 | S86: =M86*(1+$P$2) -> 0.92 | T86: =R86+S86 -> 2.047 | W86: =IFERROR(#REF!*J86,"") | X86: =IFERROR(K86*J86,"") -> 14.7 | Y86: =IFERROR(+L86*J86,"") -> 30 | Z86: =IFERROR(+M86*J86,"") -> 12 | AA86: =IFERROR(+N86*J86,"") -> 26.7 | AB86: =IFERROR(O86*$J86,"") -> 2.205 | AC86: =IFERROR(P86*$J86,"") -> 1.8 | AD86: =IFERROR(+Q86*J86,"") -> 30.705 | AF86: =IFERROR(W86*'FlightConfig '!$K$3,"") | AG86: =IFERROR(X86*'FlightConfig '!$K$23,"") -> 5350.8 | AH86: =IFERROR(Y86*'FlightConfig '!$K$23,"") -> 10920 | AI86: =IFERROR(Z86*'FlightConfig '!$K$23,"") -> 4368 | AJ86: =IFERROR(AA86*'FlightConfig '!$K$23,"") -> 9718.8 | AK86: =IFERROR(AB86*'FlightConfig '!$K$23,"") -> 802.62
... A89: BUSINESS CLASS | B89: 1 | C89: =CONCATENATE(A89&B89&F89) -> BUSINESS CLASS1110 | E89: 1015 | F89: 110 | G89: =VLOOKUP(E89,'FG MASTER'!$A$10:$AB$218,2,0) -> BC C1 DINNER DESSERT HOT ROTATION 2 STICKY TOFFEE PUDDING, CHANTILLY CREAM, CROQUANT, TOFEE SAUCE | H89: 1 | I89: 0.5 | J89: =IFERROR(IF(I89="std",H89,HLOOKUP(A89,'FlightConfig '!$B$34:$G$35,2,0)*I89),"") -> 15 | K89: =VLOOKUP(Food!E89,'FG MASTER'!$A$1:$AC$536,16,0) -> 2.56 | L89: =VLOOKUP(Food!E89,'FG MASTER'!$A$10:$AC$536,17,0) -> 1.25 | M89: =IFERROR(L89*$M$2,"") -> 0.5 | N89: =IFERROR((K89)+M89,"") -> 3.06 | O89: =IFERROR($K89*(1+$O$2)-$K89,0) -> 0.384 | P89: =IFERROR($M89*(1+$P$2)-$M89,0) -> 0.075 | Q89: =SUM(N89:P89) -> 3.519 | R89: =K89*(1+$O$2) -> 2.944 | S89: =M89*(1+$P$2) -> 0.575 | T89: =R89+S89 -> 3.519 | W89: =IFERROR(#REF!*J89,"") | X89: =IFERROR(K89*J89,"") -> 38.4 | Y89: =IFERROR(+L89*J89,"") -> 18.75 | Z89: =IFERROR(+M89*J89,"") -> 7.5 | AA89: =IFERROR(+N89*J89,"") -> 45.9 | AB89: =IFERROR(O89*$J89,"") -> 5.76 | AC89: =IFERROR(P89*$J89,"") -> 1.125 | AD89: =IFERROR(+Q89*J89,"") -> 52.785 | AF89: =IFERROR(W89*'FlightConfig '!$K$3,"") | AG89: =IFERROR(X89*'FlightConfig '!$K$23,"") -> 13977.6 | AH89: =IFERROR(Y89*'FlightConfig '!$K$23,"") -> 6825 | AI89: =IFERROR(Z89*'FlightConfig '!$K$23,"") -> 2730 | AJ89: =IFERROR(AA89*'FlightConfig '!$K$23,"") -> 16707.6 | AK89: =IFERROR(AB89*'FlightConfig '!$K$23,"") -> 2096.64
A90: BUSINESS CLASS | B90: 1 | C90: =CONCATENATE(A90&B90&F90) -> BUSINESS CLASS1110 | E90: 1016 | F90: 110 | G90: =VLOOKUP(E90,'FG MASTER'!$A$10:$AB$218,2,0) -> BC C1 DINNER CHEESE PLATE DAIRY GRIFFIN, ASHER BLUE, GREEN HILL BRIE, ANGRY CUKES, MUSCADINE JELLY | H90: 1 | I90: 0.6 | J90: =IFERROR(IF(I90="std",H90,HLOOKUP(A90,'FlightConfig '!$B$34:$G$35,2,0)*I90),"") -> 18 | K90: 0 | L90: 0 | M90: =IFERROR(L90*$M$2,"") -> 0 | N90: =IFERROR((K90)+M90,"") -> 0 | O90: =IFERROR($K90*(1+$O$2)-$K90,0) -> 0 | P90: =IFERROR($M90*(1+$P$2)-$M90,0) -> 0 | Q90: =SUM(N90:P90) -> 0 | R90: =K90*(1+$O$2) -> 0 | S90: =M90*(1+$P$2) -> 0 | T90: =R90+S90 -> 0 | W90: =IFERROR(#REF!*J90,"") | X90: =IFERROR(K90*J90,"") -> 0 | Y90: =IFERROR(+L90*J90,"") -> 0 | Z90: =IFERROR(+M90*J90,"") -> 0 | AA90: =IFERROR(+N90*J90,"") -> 0 | AB90: =IFERROR(O90*$J90,"") -> 0 | AC90: =IFERROR(P90*$J90,"") -> 0 | AD90: =IFERROR(+Q90*J90,"") -> 0 | AF90: =IFERROR(W90*'FlightConfig '!$K$3,"") | AG90: =IFERROR(X90*'FlightConfig '!$K$23,"") -> 0 | AH90: =IFERROR(Y90*'FlightConfig '!$K$23,"") -> 0 | AI90: =IFERROR(Z90*'FlightConfig '!$K$23,"") -> 0 | AJ90: =IFERROR(AA90*'FlightConfig '!$K$23,"") -> 0 | AK90: =IFERROR(AB90*'FlightConfig '!$K$23,"") -> 0
A91: BUSINESS CLASS | B91: 1 | C91: =CONCATENATE(A91&B91&F91) -> BUSINESS CLASS1110 | E91: 1017 | F91: 110 | G91: =VLOOKUP(E91,'FG MASTER'!$A$10:$AB$218,2,0) -> BC C1 BREAKFAST ENTRÉE 1 SAVORY PECAN BELGIAN WAFFLE, FRIED CHICKEN, MAPLE SAUSAGE GRAVY, SCRAMBLE EGG | H91: 1 | I91: 0.5 | J91: =IFERROR(IF(I91="std",H91,HLOOKUP(A91,'FlightConfig '!$B$34:$G$35,2,0)*I91),"") -> 15 | K91: =VLOOKUP(Food!E91,'FG MASTER'!$A$1:$AC$536,16,0) -> 4.71 | L91: =VLOOKUP(Food!E91,'FG MASTER'!$A$10:$AC$536,17,0) -> 4.25 | M91: =IFERROR(L91*$M$2,"") -> 1.7 | N91: =IFERROR((K91)+M91,"") -> 6.41 | O91: =IFERROR($K91*(1+$O$2)-$K91,0) -> 0.7065 | P91: =IFERROR($M91*(1+$P$2)-$M91,0) -> 0.255 | Q91: =SUM(N91:P91) -> 7.3715 | R91: =K91*(1+$O$2) -> 5.4165 | S91: =M91*(1+$P$2) -> 1.955 | T91: =R91+S91 -> 7.3715 | W91: =IFERROR(#REF!*J91,"") | X91: =IFERROR(K91*J91,"") -> 70.65 | Y91: =IFERROR(+L91*J91,"") -> 63.75 | Z91: =IFERROR(+M91*J91,"") -> 25.5 | AA91: =IFERROR(+N91*J91,"") -> 96.15 | AB91: =IFERROR(O91*$J91,"") -> 10.5975 | AC91: =IFERROR(P91*$J91,"") -> 3.825 | AD91: =IFERROR(+Q91*J91,"") -> 110.5725 | AF91: =IFERROR(W91*'FlightConfig '!$K$3,"") | AG91: =IFERROR(X91*'FlightConfig '!$K$23,"") -> 25716.6 | AH91: =IFERROR(Y91*'FlightConfig '!$K$23,"") -> 23205 | AI91: =IFERROR(Z91*'FlightConfig '!$K$23,"") -> 9282 | AJ91: =IFERROR(AA91*'FlightConfig '!$K$23,"") -> 34998.6 | AK91: =IFERROR(AB91*'FlightConfig '!$K$23,"") -> 3857.49
A92: BUSINESS CLASS | B92: 1 | C92: =CONCATENATE(A92&B92&F92) -> BUSINESS CLASS1110 | E92: 1018 | F92: 110 | G92: =VLOOKUP(E92,'FG MASTER'!$A$10:$AB$218,2,0) -> BC C1 BREAKFAST ENTRÉE 2 SAVORY FRITTATA, MARINATED TOMATO, HASHBROWN, GREEN ONION MORNAY | H92: 1 | I92: 0.2 | J92: =IFERROR(IF(I92="std",H92,HLOOKUP(A92,'FlightConfig '!$B$34:$G$35,2,0)*I92),"") -> 6 | K92: =VLOOKUP(Food!E92,'FG MASTER'!$A$1:$AC$536,16,0) -> 2.29 | L92: =VLOOKUP(Food!E92,'FG MASTER'!$A$10:$AC$536,17,0) -> 4.5 | M92: =IFERROR(L92*$M$2,"") -> 1.8 | N92: =IFERROR((K92)+M92,"") -> 4.09 | O92: =IFERROR($K92*(1+$O$2)-$K92,0) -> 0.3435 | P92: =IFERROR($M92*(1+$P$2)-$M92,0) -> 0.27 | Q92: =SUM(N92:P92) -> 4.7035 | R92: =K92*(1+$O$2) -> 2.6335 | S92: =M92*(1+$P$2) -> 2.07 | T92: =R92+S92 -> 4.7035 | W92: =IFERROR(#REF!*J92,"") | X92: =IFERROR(K92*J92,"") -> 13.74 | Y92: =IFERROR(+L92*J92,"") -> 27 | Z92: =IFERROR(+M92*J92,"") -> 10.8 | AA92: =IFERROR(+N92*J92,"") -> 24.54 | AB92: =IFERROR(O92*$J92,"") -> 2.061 | AC92: =IFERROR(P92*$J92,"") -> 1.62 | AD92: =IFERROR(+Q92*J92,"") -> 28.221 | AF92: =IFERROR(W92*'FlightConfig '!$K$3,"") | AG92: =IFERROR(X92*'FlightConfig '!$K$23,"") -> 5001.36 | AH92: =IFERROR(Y92*'FlightConfig '!$K$23,"") -> 9828 | AI92: =IFERROR(Z92*'FlightConfig '!$K$23,"") -> 3931.2 | AJ92: =IFERROR(AA92*'FlightConfig '!$K$23,"") -> 8932.56 | AK92: =IFERROR(AB92*'FlightConfig '!$K$23,"") -> 750.204
A93: BUSINESS CLASS | B93: 1 | C93: =CONCATENATE(A93&B93&F93) -> BUSINESS CLASS1110 | E93: 1019 | F93: 110 | G93: =VLOOKUP(E93,'FG MASTER'!$A$10:$AB$218,2,0) -> BC C1 BREAKFAST ENTRÉE 3 SWEET GREEK YOGURT PARFAIT, MANGO PINEAPPLE CHUTNEY, BLUSBERRY, COCONUT AND OAT GRANOLA | H93: 1 | I93: 0.3 | J93: =IFERROR(IF(I93="std",H93,HLOOKUP(A93,'FlightConfig '!$B$34:$G$35,2,0)*I93),"") -> 9 | K93: =VLOOKUP(Food!E93,'FG MASTER'!$A$1:$AC$536,16,0) -> 2.15 | L93: =VLOOKUP(Food!E93,'FG MASTER'!$A$10:$AC$536,17,0) -> 3.25 | M93: =IFERROR(L93*$M$2,"") -> 1.3 | N93: =IFERROR((K93)+M93,"") -> 3.45 | O93: =IFERROR($K93*(1+$O$2)-$K93,0) -> 0.3225 | P93: =IFERROR($M93*(1+$P$2)-$M93,0) -> 0.195 | Q93: =SUM(N93:P93) -> 3.9675 | R93: =K93*(1+$O$2) -> 2.4725 | S93: =M93*(1+$P$2) -> 1.495 | T93: =R93+S93 -> 3.9675 | W93: =IFERROR(#REF!*J93,"") | X93: =IFERROR(K93*J93,"") -> 19.35 | Y93: =IFERROR(+L93*J93,"") -> 29.25 | Z93: =IFERROR(+M93*J93,"") -> 11.7 | AA93: =IFERROR(+N93*J93,"") -> 31.05 | AB93: =IFERROR(O93*$J93,"") -> 2.9025 | AC93: =IFERROR(P93*$J93,"") -> 1.755 | AD93: =IFERROR(+Q93*J93,"") -> 35.7075 | AF93: =IFERROR(W93*'FlightConfig '!$K$3,"") | AG93: =IFERROR(X93*'FlightConfig '!$K$23,"") -> 7043.4 | AH93: =IFERROR(Y93*'FlightConfig '!$K$23,"") -> 10647 | AI93: =IFERROR(Z93*'FlightConfig '!$K$23,"") -> 4258.8 | AJ93: =IFERROR(AA93*'FlightConfig '!$K$23,"") -> 11302.2 | AK93: =IFERROR(AB93*'FlightConfig '!$K$23,"") -> 1056.51
A94: BUSINESS CLASS | B94: 1 | C94: =CONCATENATE(A94&B94&F94) -> BUSINESS CLASS1110 | E94: 1020 | F94: 110 | G94: =VLOOKUP(E94,'FG MASTER'!$A$10:$AB$218,2,0) -> BC C1 BREAKFAST SIDE 1 FRUIT SEASONAL 4 TYPES 130G | H94: 1 | I94: 0.5 | J94: =IFERROR(IF(I94="std",H94,HLOOKUP(A94,'FlightConfig '!$B$34:$G$35,2,0)*I94),"") -> 15 | K94: =VLOOKUP(Food!E94,'FG MASTER'!$A$1:$AC$536,16,0) -> 2 | L94: =VLOOKUP(Food!E94,'FG MASTER'!$A$10:$AC$536,17,0) -> 1.5 | M94: =IFERROR(L94*$M$2,"") -> 0.6 | N94: =IFERROR((K94)+M94,"") -> 2.6 | O94: =IFERROR($K94*(1+$O$2)-$K94,0) -> 0.3 | P94: =IFERROR($M94*(1+$P$2)-$M94,0) -> 0.09 | Q94: =SUM(N94:P94) -> 2.99 | R94: =K94*(1+$O$2) -> 2.3 | S94: =M94*(1+$P$2) -> 0.69 | T94: =R94+S94 -> 2.99 | W94: =IFERROR(#REF!*J94,"") | X94: =IFERROR(K94*J94,"") -> 30 | Y94: =IFERROR(+L94*J94,"") -> 22.5 | Z94: =IFERROR(+M94*J94,"") -> 9 | AA94: =IFERROR(+N94*J94,"") -> 39 | AB94: =IFERROR(O94*$J94,"") -> 4.5 | AC94: =IFERROR(P94*$J94,"") -> 1.35 | AD94: =IFERROR(+Q94*J94,"") -> 44.85 | AF94: =IFERROR(W94*'FlightConfig '!$K$3,"") | AG94: =IFERROR(X94*'FlightConfig '!$K$23,"") -> 10920 | AH94: =IFERROR(Y94*'FlightConfig '!$K$23,"") -> 8190 | AI94: =IFERROR(Z94*'FlightConfig '!$K$23,"") -> 3276 | AJ94: =IFERROR(AA94*'FlightConfig '!$K$23,"") -> 14196 | AK94: =IFERROR(AB94*'FlightConfig '!$K$23,"") -> 1638
A95: BUSINESS CLASS | B95: 1 | C95: =CONCATENATE(A95&B95&F95) -> BUSINESS CLASS1110 | E95: 1021 | F95: 110 | G95: =VLOOKUP(E95,'FG MASTER'!$A$10:$AB$218,2,0) -> BC C1 BREAKFAST SIDE 2 PEACH AND PECAN SCONE | H95: 1 | I95: 0.5 | J95: =IFERROR(IF(I95="std",H95,HLOOKUP(A95,'FlightConfig '!$B$34:$G$35,2,0)*I95),"") -> 15 | K95: =VLOOKUP(Food!E95,'FG MASTER'!$A$1:$AC$536,16,0) -> 1.18 | L95: =VLOOKUP(Food!E95,'FG MASTER'!$A$10:$AC$536,17,0) -> 2 | M95: =IFERROR(L95*$M$2,"") -> 0.8 | N95: =IFERROR((K95)+M95,"") -> 1.98 | O95: =IFERROR($K95*(1+$O$2)-$K95,0) -> 0.177 | P95: =IFERROR($M95*(1+$P$2)-$M95,0) -> 0.12 | Q95: =SUM(N95:P95) -> 2.277 | R95: =K95*(1+$O$2) -> 1.357 | S95: =M95*(1+$P$2) -> 0.92 | T95: =R95+S95 -> 2.277 | W95: =IFERROR(#REF!*J95,"") | X95: =IFERROR(K95*J95,"") -> 17.7 | Y95: =IFERROR(+L95*J95,"") -> 30 | Z95: =IFERROR(+M95*J95,"") -> 12 | AA95: =IFERROR(+N95*J95,"") -> 29.7 | AB95: =IFERROR(O95*$J95,"") -> 2.655 | AC95: =IFERROR(P95*$J95,"") -> 1.8 | AD95: =IFERROR(+Q95*J95,"") -> 34.155 | AF95: =IFERROR(W95*'FlightConfig '!$K$3,"") | AG95: =IFERROR(X95*'FlightConfig '!$K$23,"") -> 6442.8 | AH95: =IFERROR(Y95*'FlightConfig '!$K$23,"") -> 10920 | AI95: =IFERROR(Z95*'FlightConfig '!$K$23,"") -> 4368 | AJ95: =IFERROR(AA95*'FlightConfig '!$K$23,"") -> 10810.8 | AK95: =IFERROR(AB95*'FlightConfig '!$K$23,"") -> 966.42
