Workbook
Name COMMERCIAL_ITEMS: #REF!
Name COMMERCIAL_ITEMS: #REF!

Sheet P&L
R2: 13 | S2: Flights Per Week
R3: ='Summary '!H4 -> 676 | S3: Flights Per Year
R4: 0.8 | S4: Load
B5: Description | C5: Grand Total | E5: Virgin Atlantic | G5: Unit Central Cost | R5: 1 | S5: Cycle
C6: $ | D6: % | E6: $ | F6: % | G6: $ | H6: % | R6: 0 | S6: Discount
B7: Revenue Meals | C7: =SUM(E7,G7) -> 2114664.7 | D7: =C7/$C$12 -> 0.57236412 | E7: =SUM('Summary '!J11:J14) -> 2114664.7 | F7: =E7/$E$12 -> 0.57236412 | G7: 1e-05 | H7: =G7/$G$12 -> 1
B8: Revenue Handling | C8: =SUM(E8,G8) -> 1103369.7 | D8: =C8/$C$12 -> 0.29864271 | E8: =SUM('Summary '!J15:J16) -> 1103369.7 | F8: =E8/$E$12 -> 0.29864271 | H8: =G8/$G$12 -> 0 | R8: 0.22 | S8: Mark up on Food
B9: Revenue Overheads | C9: =SUM(E9,G9) -> 476580 | D9: =C9/$C$12 -> 0.12899316 | E9: =705*R3 -> 476580 | F9: =E9/$E$12 -> 0.12899316 | H9: =G9/$G$12 -> 0 | I9: $705 PER FLIGHT OVERHEAD CHARGE | R9: 0.2 | S9: Mark up on Food Labor
B10: Revenue Other | C10: =SUM(E10,G10) -> 0 | D10: =C10/$C$12 -> 0 | F10: =E10/$E$12 -> 0 | H10: =G10/$G$12 -> 0 | R10: 0.13 | S10: Mark up on Handling
B11: Discount | C11: =SUM(E11,G11) -> 0 | D11: =C11/$C$12 -> 0 | E11: =SUM(E7:E9)*R6 -> 0 | F11: =E11/$E$12 -> 0 | H11: =G11/$G$12 -> 0
B12: Net Revenue | C12: =SUM(C7:C11) -> 3694614.4 | D12: =C12/$C$12 -> 1 | E12: =SUM(E7:E11) -> 3694614.4 | F12: =E12/$E$12 -> 1 | G12: =SUM(G7:G11) -> 1e-05 | H12: =G12/$G$12 -> 1 | I12: =E12/12 -> 307884.53
B13: Food Cost | C13: =SUM(E13,G13) -> 1153884.7 | D13: =C13/$C$12 -> 0.31231532 | E13: ='Summary '!J11 -> 1153884.7 | F13: =E13/$E$12 -> 0.31231532 | H13: =G13/$G$12 -> 0 | R13: VA ATL TOTAL HANDLING
B14: Other product cost | C14: =SUM(E14,G14) -> 0 | D14: =C14/$C$12 -> 0 | E14: 0 | F14: =E14/$E$12 -> 0 | H14: =G14/$G$12 -> 0 | R14: =R20+R25+R30+R35 -> 1575.559 | S14: A330
B15: Total Direct Materials | C15: =SUM(C13:C14) -> 1153884.7 | D15: =C15/$C$12 -> 0.31231532 | E15: =SUM(E13:E14) -> 1153884.7 | F15: =E15/$E$12 -> 0.31231532 | G15: =SUM(G13:G14) -> 0 | H15: =G15/$G$12 -> 0 | R15: =R21+R26+R31+R36 -> 1932.8198 | S15: A350
B16: Direct Labor - Wages | C16: =SUM(E16,G16) -> 1299396.4 | D16: =C16/$C$12 -> 0.35170014 | E16: ='Summary '!L16 -> 1299396.4 | F16: =E16/$E$12 -> 0.35170014 | H16: =G16/$G$12 -> 0 | R16: =R22+R27+R32+R37 -> 1529.342 | S16: 787
B17: Direct Labor - OT Premium | C17: =SUM(E17,G17) -> 0 | D17: =C17/$C$12 -> 0 | E17: 0 | F17: =E17/$E$12 -> 0 | H17: =G17/$G$12 -> 0
B18: Direct Labor - Benefit Cost | C18: =SUM(E18,G18) -> 266141.43 | D18: =C18/$C$12 -> 0.072034969 | E18: ='Summary '!L17 -> 266141.43 | F18: =E18/$E$12 -> 0.072034969 | H18: =G18/$G$12 -> 0 | I18: =E18/E16 -> 0.20481928
B19: Direct Labor - Other | C19: =SUM(E19,G19) -> 0 | D19: =C19/$C$12 -> 0 | E19: 0 | F19: =E19/$E$12 -> 0 | H19: =G19/$G$12 -> 0 | R19: VA ATL TRANSPORT
B20: Direct Management Labor Cost | C20: =SUM(E20,G20) -> 0 | D20: =C20/$C$12 -> 0 | E20: 0 | F20: =E20/$E$12 -> 0 | H20: =G20/$G$12 -> 0 | R20: =Handling!V53 -> 313.236 | S20: A330 TURNAROUND
B21: Total Direct Labor | C21: =SUM(C16:C20) -> 1565537.8 | D21: =C21/$C$12 -> 0.42373511 | E21: =SUM(E16:E20) -> 1565537.8 | F21: =E21/$E$12 -> 0.42373511 | G21: =SUM(G16:G20) -> 0 | H21: =G21/$G$12 -> 0 | I21: =E21-E8 -> 462168.18 | R21: =Handling!X53 -> 362.956 | S21: A350 TURNAROUND
B22: Gross Profit Margin (CM1) | C22: =C12-C15-C21 -> 975191.86 | D22: =C22/$C$12 -> 0.26394957 | E22: =E12-E15-E21 -> 975191.86 | F22: =E22/$E$12 -> 0.26394957 | G22: =G12-G15-G21 -> 1e-05 | H22: =G22/$G$12 -> 1 | R22: =Handling!Z53 -> 313.236 | S22: 787 TURNAROUND
K23: VA ATL Avg. Revenue Per Flight | O23: ='Summary '!H17+705 -> 5465.4059 | Q23: =4993+705 -> 5698
B24: Indirect Management Labor Cost | C24: =SUM(E24,G24) -> 80500 | D24: =C24/$C$12 -> 0.021788471 | E24: =70000*1.15 -> 80500 | F24: =E24/$C$12 -> 0.021788471 | H24: =G24/$G$12 -> 0 | I24: extra management? | K24: Avg. Price Per Pax | R24: VA ATL INTERNATIONAL GARBAGE
B25: Indirect Hourly Labor Cost | C25: =SUM(E25,G25) -> 0 | D25: =C25/$C$12 -> 0 | E25: 0 | F25: =E25/$C$12 -> 0 | H25: =G25/$G$12 -> 0 | K25: FC | L25: BC | M25: PY | N25: EY | O25: TC | P25: CY | R25: =Handling!AD39 -> 339 | S25: A330
B26: Total Indirect Labor | C26: =SUM(C24:C25) -> 80500 | D26: =C26/$C$12 -> 0.021788471 | E26: =SUM(E24:E25) -> 80500 | F26: =E26/$E$12 -> 0.021788471 | G26: =SUM(G24:G25) -> 0 | H26: =G26/$G$12 -> 0 | K26: ='Summary '!B24 -> 0 | L26: ='Summary '!C24 -> 30.177713 | M26: ='Summary '!D24 -> 17.59077 | N26: ='Summary '!E24 -> 10.400983 | O26: ='Summary '!F24 -> 0 | P26: ='Summary '!G24 -> 20.274574 | R26: =Handling!AD41 -> 395.5 | S26: A350
B27: Operating Expense-Variable | C27: =SUM(E27,G27) -> 84000 | D27: =C27/$C$12 -> 0.022735796 | E27: =7000*12 -> 84000 | F27: =E27/E12 -> 0.022735796 | H27: =G27/$G$12 -> 0 | I27: Utility | L27: 34.4 | M27: 23.8 | N27: 12.42 | O27: $- | P27: 36.12 | R27: =Handling!AD43 -> 339 | S27: 787
B28: Operating Expense-Fixed | C28: =SUM(E28,G28) -> 66666.667 | D28: =C28/$C$12 -> 0.018044283 | E28: =200000/3 -> 66666.667 | F28: =E28/E12 -> 0.018044283 | H28: =G28/$G$12 -> 0 | I28: ??? Freezer and Cooler | K28: Overhead
B29: Other OPEX Cost | C29: =SUM(C27:C28) -> 150666.67 | D29: =C29/$C$12 -> 0.040780079 | E29: =SUM(E27:E28) -> 150666.67 | F29: =E29/E12 -> 0.040780079 | G29: =SUM(G27:G28) -> 0 | H29: =G29/$G$12 -> 0 | K29: FC | L29: BC | M29: PY | N29: YC | O29: TC | P29: CC | R29: VA ATL WASH UP
B30: EBITDA | C30: =C22-C26-C29 -> 744025.2 | D30: =C30/$C$12 -> 0.20138102 | E30: =E22-E26-E29 -> 744025.2 | F30: =E30/$E$12 -> 0.20138102 | G30: =G22-G26-G29 -> 1e-05 | H30: =G30/$G$12 -> 1 | I30: =E30/12 -> 62002.1 | K30: 0 | L30: 0 | M30: 0 | N30: 0 | O30: 0 | P30: 0 | R30: =Handling!C84 -> 704.103 | S30: A330
E31: =E30/12 -> 62002.1 | I31: =11000*30 -> 330000 | K31: =I31*12 -> 3960000 | R31: =Handling!E84 -> 878.3038 | S31: A350
B32: Note - On the P&L we can update the Flights per week, AC type, Load Factor, Cycle & Mark up's | R32: =Handling!G84 -> 653.366 | S32: 787
E34: Overhead =(2/3)*(property tax+utility) | R34: VA ATL PACKING
R35: =Handling!S39+Handling!S45 -> 219.22 | S35: A330
B36: customer service account manager | R36: =Handling!S41+Handling!S47 -> 296.06 | S36: A350
B37: culinary operation duty manager | R37: =Handling!S43+Handling!S50 -> 223.74 | S37: 787
B38: hourly invoice assisant
B39: ramp duty manager
B67: CONTRACTORS | C67: 271755
B68: EXTERIOR SIGNAGE | C68: 2000
B69: MULTITEMP FREEZERS | C69: 164340
B70: DISHWASHER RETAL (YEARLY) | C70: 3840
B71: PERMITTING | C71: 19000
B72: RENT/LEASE (YEARLY) | C72: 261360
B73: TRUCK (2 TRUCKS) | C73: 675000
B74: EQUIPMENT AND UTILITY (5 YEARS) | C74: =116139*5 -> 580695

Sheet Bid Assumption 
A1: Bid Fact Sheet
A2: Airline Name | B2: NEOS
A3: City Code and Unit Number | B3: JFK
A4: Date Bid Preparation Begins
A5: Period used for Annualization
A6: Access Fee %
A7: Trade Discount %
A8: Cash Discount %
A9: Start Up Date
A12: Aircraft Type | B12: 787
A13: Configuration: First Class | B13: =+'FlightConfig '!B3 -> 0
A14: Business Class | B14: =+'FlightConfig '!C3 -> 34
A15: Tourist Class | B15: =SUM('FlightConfig '!D3:E3) -> 246
A16: ETA | B16: 0.26736111
A17: ETD | B17: 0.93402778
A18: Frequency (days of operations) | B18: =+'FlightConfig '!K2 -> 0
A19: Total No. of Flights per Year | B19: =+'FlightConfig '!K3 -> 0
A20: Load Factor %
A21: Source of Load Factor | B21: Flight Config
A22: Account Rep. | B22: Kathy Shi
A23: Reason For Bid | B23: New Unit | E23: Food Markup
A24: Incumbent | E24: Ancillary Markup
A25: New or Old Route | B25: New | E25: Service Markup
A26: Credit Established/Payment Status
A27: Was Account Previously Bid | E27: Overhead Recovery per Pax F/C
A28: Outcome | E28: Overhead Recovery per Pax B/C
A29: Is there a Global Agreement | E29: Overhead Recovery per Pax E/U
A30: Date Building Lease expires | E30: Overhead Recovery per Pax Y/C
E31: Overhead Recovery per Pax C/Y
E32: Overhead Recovery per Pax C/C
A33: Investment | B33: Amount | C33: No. Years | D33: $ per Year | E33: Overhead Recovery per Pax T/C
A34: Building | C34: 0 | D34: =+B34/C34 -> #DIV/0!
A35: Land | C35: N/A | D35: N/A
A36: Building - Leasehold Improvements | C36: 0 | D36: =+B36/C36 -> #DIV/0!
A37: Trucks - Highlifts | C37: 0 | D37: =+B37/C37 -> #DIV/0!
A38: Trucks - Vans/Utility Vehicles | C38: 0 | D38: =+B38/C38 -> #DIV/0!
A39: Equipment | C39: 0 | D39: =+B39/C39 -> #DIV/0!
A40: Rent of Property | C40: 0 | D40: =+B40/C40 -> #DIV/0!
A42: Other Cities that Dnata serves this Customer and Discounts applied:
A43: SFO
A47: Pricing Assumptions:
A48: Methodology: fc+lc+mu=sp
A49: Contract length:
A50: # of Trucks/price - ea:
A51: # of Vans/Utility Vehicles/price - ea:
A52: Equipment descriptions:

Sheet Summary 
A2: Customer | G2: Flights Per week | H2: ='P&L'!R2 -> 13 | L2: AC type | M2: Cycle
E3: AC Type | G3: Flights Per Month | H3: =H4/12 -> 56.333333 | J3: Total Revenues | L3: 737 | M3: 1
E4: Load | F4: ='P&L'!R4 -> 0.8 | G4: Annual Flights | H4: =H2*52 -> 676 | J4: =H17*H4 -> 3218034.4 | M4: 2
A5: Summary
A6: BNA | B6: FC | C6: BC | D6: PY | E6: EY | F6: TC | G6: CY | H6: Total | I6: Hnd
A7: FLIGHT CONFIG | B7: =+'FlightConfig '!B17 -> 0 | C7: =('Summary FLT104'!C7+'Summary FLT110'!C7)/2 -> 32 | D7: =('Summary FLT104'!D7+'Summary FLT110'!D7)/2 -> 46 | E7: =('Summary FLT104'!E7+'Summary FLT110'!E7)/2 -> 191 | F7: =('Summary FLT104'!F7+'Summary FLT110'!F7)/2 -> 0 | G7: =('Summary FLT104'!G7+'Summary FLT110'!G7)/2 -> 6 | H7: =('Summary FLT104'!H7+'Summary FLT110'!H7)/2 -> 275
A8: Load Factor | B8: =ROUNDUP(B7*$F$4,0) -> 0 | C8: =ROUNDUP(C7*$F$4,0) -> 26 | D8: =ROUNDUP(D7*$F$4,0) -> 37 | E8: =ROUNDUP(E7*$F$4,0) -> 153 | F8: =ROUNDUP(F7*$F$4,0) -> 0 | G8: =ROUNDUP(G7*$F$4,0) -> 5 | H8: =SUM(B8:G8) -> 221
B9: FIRST CLASS | C9: BUSINESS CLASS | D9: PREMIUM ECONOMY CLASS | E9: ECONOMY CLASS | F9: TECH CREW CLASS | G9: cABIN CREW CLASS | H9: Per Flight | J9: Annual
A10: OVERHEAD | B10: =('Summary FLT104'!B10+'Summary FLT110'!B10)/2 -> 0 | C10: =('Summary FLT104'!C10+'Summary FLT110'!C10)/2 -> 0 | D10: =('Summary FLT104'!D10+'Summary FLT110'!D10)/2 -> 0 | E10: =('Summary FLT104'!E10+'Summary FLT110'!E10)/2 -> 0 | F10: =('Summary FLT104'!F10+'Summary FLT110'!F10)/2 -> 0 | G10: =('Summary FLT104'!G10+'Summary FLT110'!G10)/2 -> 0 | H10: =('Summary FLT104'!H10+'Summary FLT110'!H10)/2 -> 0 | J10: =H10*$H$4 -> 0
A11: Food Cost (DM) | B11: =('Summary FLT104'!B11+'Summary FLT110'!B11)/2 -> 0 | C11: =('Summary FLT104'!C11+'Summary FLT110'!C11)/2 -> 456.44114 | D11: =('Summary FLT104'!D11+'Summary FLT110'!D11)/2 -> 318.22703 | E11: =('Summary FLT104'!E11+'Summary FLT110'!E11)/2 -> 870.20432 | F11: =('Summary FLT104'!F11+'Summary FLT110'!F11)/2 -> 0 | G11: =('Summary FLT104'!G11+'Summary FLT110'!G11)/2 -> 62.0575 | H11: =('Summary FLT104'!H11+'Summary FLT110'!H11)/2 -> 1706.93 | I11: =I12*45% -> 1160.2739 | J11: =H11*$H$4 -> 1153884.7
A12: Wage Cost (DL) | B12: =('Summary FLT104'!B12+'Summary FLT110'!B12)/2 -> 0 | C12: =('Summary FLT104'!C12+'Summary FLT110'!C12)/2 -> 189.80195 | D12: =('Summary FLT104'!D12+'Summary FLT110'!D12)/2 -> 218.85125 | E12: =('Summary FLT104'!E12+'Summary FLT110'!E12)/2 -> 441.41758 | F12: =('Summary FLT104'!F12+'Summary FLT110'!F12)/2 -> 0 | G12: =('Summary FLT104'!G12+'Summary FLT110'!G12)/2 -> 21.3856 | H12: =('Summary FLT104'!H12+'Summary FLT110'!H12)/2 -> 871.45638 | I12: =H11+H12 -> 2578.3864 | J12: =H12*$H$4 -> 589104.51
A13: Food Mark up | B13: =('Summary FLT104'!B13+'Summary FLT110'!B13)/2 -> 0 | C13: =('Summary FLT104'!C13+'Summary FLT110'!C13)/2 -> 100.41705 | D13: =('Summary FLT104'!D13+'Summary FLT110'!D13)/2 -> 70.009947 | E13: =('Summary FLT104'!E13+'Summary FLT110'!E13)/2 -> 191.44495 | F13: =('Summary FLT104'!F13+'Summary FLT110'!F13)/2 -> 0 | G13: =('Summary FLT104'!G13+'Summary FLT110'!G13)/2 -> 13.65265 | H13: =('Summary FLT104'!H13+'Summary FLT110'!H13)/2 -> 375.5246 | J13: =H13*$H$4 -> 253854.63
A14: Labor Mark up | B14: =('Summary FLT104'!B14+'Summary FLT110'!B14)/2 -> 0 | C14: =('Summary FLT104'!C14+'Summary FLT110'!C14)/2 -> 37.960391 | D14: =('Summary FLT104'!D14+'Summary FLT110'!D14)/2 -> 43.77025 | E14: =('Summary FLT104'!E14+'Summary FLT110'!E14)/2 -> 88.283515 | F14: =('Summary FLT104'!F14+'Summary FLT110'!F14)/2 -> 0 | G14: =('Summary FLT104'!G14+'Summary FLT110'!G14)/2 -> 4.27712 | H14: =('Summary FLT104'!H14+'Summary FLT110'!H14)/2 -> 174.29128 | J14: =H14*$H$4 -> 117820.9 | L14: Direct Labour
A15: Handling Cost | B15: =('Summary FLT104'!B15+'Summary FLT110'!B15)/2 -> 0 | C15: =('Summary FLT104'!C15+'Summary FLT110'!C15)/2 -> 0 | D15: =('Summary FLT104'!D15+'Summary FLT110'!D15)/2 -> 0 | E15: =('Summary FLT104'!E15+'Summary FLT110'!E15)/2 -> 1444.428 | F15: =('Summary FLT104'!F15+'Summary FLT110'!F15)/2 -> 0 | G15: =('Summary FLT104'!G15+'Summary FLT110'!G15)/2 -> 0 | H15: =('Summary FLT104'!H15+'Summary FLT110'!H15)/2 -> 1444.428 | J15: =H15*$H$4 -> 976433.33 | L15: =J12+J15 -> 1565537.8 | M15: 1
A16: Handling Mark up | B16: =('Summary FLT104'!B16+'Summary FLT110'!B16)/2 -> 0 | C16: =('Summary FLT104'!C16+'Summary FLT110'!C16)/2 -> 0 | D16: =('Summary FLT104'!D16+'Summary FLT110'!D16)/2 -> 0 | E16: =('Summary FLT104'!E16+'Summary FLT110'!E16)/2 -> 187.77564 | F16: =('Summary FLT104'!F16+'Summary FLT110'!F16)/2 -> 0 | G16: =('Summary FLT104'!G16+'Summary FLT110'!G16)/2 -> 0 | H16: =('Summary FLT104'!H16+'Summary FLT110'!H16)/2 -> 187.77564 | J16: =H16*$H$4 -> 126936.33 | L16: =L15*M16 -> 1299396.4 | M16: 0.83
A17: Total Per Flight | B17: =SUM(B11:B16) -> 0 | C17: =SUM(C11:C16) -> 784.62054 | D17: =SUM(D10:D16) -> 650.85848 | E17: =SUM(E10:E16) -> 3223.554 | F17: =SUM(F10:F16) -> 0 | G17: =SUM(G10:G16) -> 101.37287 | H17: =SUM(H10:H16) -> 4760.4059 | J17: =H17*$H$4 -> 3218034.4 | L17: =L15*M17 -> 266141.43 | M17: 0.17
B18: =B17 -> 0 | C18: =C17 -> 784.62054 | D18: =D17 -> 650.85848 | E18: =E17-E15-E16 -> 1591.3504 | F18: =F17 -> 0 | G18: =G17 -> 101.37287 | I18: =E15+E16 -> 1632.2036
A19: Handling | B19: Cost | C19: Mark Up | D19: Price | I19: =E16 -> 187.77564 | J19: =H11+H12+H15 -> 4022.8144
A20: 737 Handling | D20: =Handling!C84+Handling!S39+Handling!S45+Handling!V53+Handling!AD39 -> 1575.559 | J20: =H13+H14+H16 -> 737.59152
A21: B777 Handling | B21: =Handling!#REF! -> #REF! | C21: =Handling!#REF! -> #REF! | D21: =Handling!#REF! -> #REF!
A22: A380 Handling | B22: =Handling!#REF! -> #REF! | C22: =Handling!#REF! -> #REF! | D22: =Handling!#REF! -> #REF!
A24: Avg Price Per Pax | B24: =IFERROR(((B11+B12+B13+B14)/B8),0) -> 0 | C24: =IFERROR(((C11+C12+C13+C14)/C8),0) -> 30.177713 | D24: =IFERROR(((D10+D11+D12+D13+D14)/D8),0) -> 17.59077 | E24: =IFERROR(((E10+E11+E12+E13+E14)/E8),0) -> 10.400983 | F24: =IFERROR(((F10+F11+F12+F13+F14)/F8),0) -> 0 | G24: =IFERROR(((G10+G11+G12+G13+G14)/G8),0) -> 20.274574
A25: Avg Mark up Per Pax | B25: =IFERROR(((B13+B14)/B8),0) -> 0 | C25: =IFERROR(((C13+C14)/C8),0) -> 5.3222093 | D25: =IFERROR(((D13+D14)/D8),0) -> 3.0751405 | E25: =IFERROR(((E13+E14)/E8),0) -> 1.8282906 | F25: =IFERROR(((F13+F14)/F8),0) -> 0 | G25: =IFERROR(((G13+G14)/G8),0) -> 3.585954 | J25: =J11+J12+J15 -> 2719422.5
A26: Over head Per Pax | B26: =IFERROR((B10/B8),0) -> 0 | C26: =IFERROR((C10/C8),0) -> 0 | D26: =IFERROR((D10/D8),0) -> 0 | E26: =IFERROR((E10/E8),0) -> 0 | F26: =IFERROR((F10/F8),0) -> 0 | G26: =IFERROR((G10/G8),0) -> 0 | J26: =J13+J14+J16 -> 498611.86
B28: CYCLE | C28: FLT
A29: Config | B29: ='P&L'!R5 -> 1
A30: OVERHEAD | B30: =B37*B8 -> 0 | C30: =C37*C8 -> 0 | D30: =D37*D8 -> 0 | E30: =E37*E8 -> 0 | F30: =F37*F8 -> 0 | G30: =G37*G8 -> 0
A31: Food Cost (DM) | B31: =('Summary FLT104'!B31+'Summary FLT110'!B31)/2 -> 0 | C31: =('Summary FLT104'!C31+'Summary FLT110'!C31)/2 -> 562.13739 | D31: =('Summary FLT104'!D31+'Summary FLT110'!D31)/2 -> 390.24187 | E31: =('Summary FLT104'!E31+'Summary FLT110'!E31)/2 -> 1082.7725 | F31: =('Summary FLT104'!F31+'Summary FLT110'!F31)/2 -> 0 | G31: =('Summary FLT104'!G31+'Summary FLT110'!G31)/2 -> 74.469
A32: Wage Cost (DL) | B32: =('Summary FLT104'!B32+'Summary FLT110'!B32)/2 -> 0 | C32: =('Summary FLT104'!C32+'Summary FLT110'!C32)/2 -> 233.664 | D32: =('Summary FLT104'!D32+'Summary FLT110'!D32)/2 -> 268.4 | E32: =('Summary FLT104'!E32+'Summary FLT110'!E32)/2 -> 549.24 | F32: =('Summary FLT104'!F32+'Summary FLT110'!F32)/2 -> 0 | G32: =('Summary FLT104'!G32+'Summary FLT110'!G32)/2 -> 25.66272
A33: Markup Food | B33: =('Summary FLT104'!B33+'Summary FLT110'!B33)/2 -> 0 | C33: =('Summary FLT104'!C33+'Summary FLT110'!C33)/2 -> 123.67023 | D33: =('Summary FLT104'!D33+'Summary FLT110'!D33)/2 -> 85.853211 | E33: =('Summary FLT104'!E33+'Summary FLT110'!E33)/2 -> 238.20996 | F33: =('Summary FLT104'!F33+'Summary FLT110'!F33)/2 -> 0 | G33: =('Summary FLT104'!G33+'Summary FLT110'!G33)/2 -> 16.38318
A34: Markup Labor | B34: =('Summary FLT104'!B34+'Summary FLT110'!B34)/2 -> 0 | C34: =('Summary FLT104'!C34+'Summary FLT110'!C34)/2 -> 46.7328 | D34: =('Summary FLT104'!D34+'Summary FLT110'!D34)/2 -> 53.68 | E34: =('Summary FLT104'!E34+'Summary FLT110'!E34)/2 -> 109.848 | F34: =('Summary FLT104'!F34+'Summary FLT110'!F34)/2 -> 0 | G34: =('Summary FLT104'!G34+'Summary FLT110'!G34)/2 -> 5.132544
A36: Per Pax Avg
A37: OVERHEAD | B37: ='P&L'!$K$30 -> 0 | C37: ='P&L'!$L$30 -> 0 | D37: ='P&L'!$M$30 -> 0 | E37: ='P&L'!$N$30 -> 0 | F37: ='P&L'!$O$30 -> 0 | G37: ='P&L'!$P$30 -> 0
A38: Food Cost (DM) | B38: =IFERROR(B31/B7," ") | C38: =IFERROR(C31/C7," ") -> 17.566793 | D38: =IFERROR(D31/D7," ") -> 8.4835188 | E38: =IFERROR(E31/E7," ") -> 5.6689661 | F38: =IFERROR(F31/F7," ") | G38: =IFERROR(G31/G7," ") -> 12.4115
A39: Wage Cost (DL) | B39: =IFERROR(B32/B7," ") | C39: =IFERROR(C32/C7," ") -> 7.302 | D39: =IFERROR(D32/D7," ") -> 5.8347826 | E39: =IFERROR(E32/E7," ") -> 2.8756021 | F39: =IFERROR(F32/F7," ") | G39: =IFERROR(G32/G7," ") -> 4.27712
A40: Markup Food | B40: =IFERROR(B33/B8," ") | C40: =IFERROR(C33/C7," ") -> 3.8646945 | D40: =IFERROR(D33/D7," ") -> 1.8663741 | E40: =IFERROR(E33/E7," ") -> 1.2471726 | F40: =IFERROR(F33/F7," ") | G40: =IFERROR(G33/G7," ") -> 2.73053
A41: Markup Labor | B41: =IFERROR(B34/B7," ") | C41: =IFERROR(C34/C7," ") -> 1.4604 | D41: =IFERROR(D34/D7," ") -> 1.1669565 | E41: =IFERROR(E34/E7," ") -> 0.57512042 | F41: =IFERROR(F34/F7," ") | G41: =IFERROR(G34/G7," ") -> 0.855424
A108: 388
A109: 787

Sheet Summary Short Haul
A2: Customer | G2: Flights Per week | H2: ='Summary 735'!H2+'Summary 2221'!H2+'Summary 2439'!H2+'Summary 2682'!H2+'Summary 2855'!H2 -> 0 | L2: AC type | M2: Cycle
E3: AC Type | F3: 737 | G3: Flights Per Month | H3: =H4/12 -> 0 | J3: Total Revenues | L3: 737 | M3: 1
E4: Load | F4: ='P&L'!R4 -> 0.8 | G4: Annual Flights | H4: =H2*52 -> 0 | J4: =H17*H4 -> #REF!
A5: Summary
A6: BNA | B6: FC | C6: BC | D6: PY | E6: EY | F6: TC | G6: CY | H6: Total | I6: Hnd
A7: FLIGHT CONFIG | B7: =+'FlightConfig '!B17 -> 0 | C7: =+'FlightConfig '!C17 -> 34 | D7: =+'FlightConfig '!D17 -> 48 | E7: =+'FlightConfig '!E17 -> 198 | F7: =+'FlightConfig '!F17 -> 0 | G7: =+'FlightConfig '!G17 -> 6 | H7: =SUM(B7:G7) -> 286
A8: Load Factor | B8: =ROUNDUP(B7*$F$4,0) -> 0 | C8: =ROUNDUP(C7*$F$4,0) -> 28 | D8: =ROUNDUP(D7*$F$4,0) -> 39 | E8: =ROUNDUP(E7*$F$4,0) -> 159 | F8: =ROUNDUP(F7*$F$4,0) -> 0 | G8: =ROUNDUP(G7*$F$4,0) -> 5 | H8: =SUM(B8:G8) -> 231
B9: FIRST CLASS | C9: BUSINESS CLASS | D9: PREMIUM ECONOMY CLASS | E9: ECONOMY CLASS | F9: TECH CREW CLASS | G9: cABIN CREW CLASS | H9: Per Flight | J9: Annual
A10: OVERHEAD | B10: =B37*B8 -> 0 | C10: =('Summary 735'!C10+'Summary 2221'!C10+'Summary 2439'!C10+'Summary 2682'!C10+'Summary 2855'!C10+#REF!+'Summary FLT104'!C10+'Summary FLT110'!C10+#REF!+#REF!+#REF!+'Summary 2037'!C10+'Summary 2817'!C10)/13 -> #REF! | D10: =('Summary 735'!D10+'Summary 2221'!D10+'Summary 2439'!D10+'Summary 2682'!D10+'Summary 2855'!D10+#REF!+'Summary FLT104'!D10+'Summary FLT110'!D10+#REF!+#REF!+#REF!+'Summary 2037'!D10+'Summary 2817'!D10)/13 -> #REF! | E10: =('Summary 735'!E10+'Summary 2221'!E10+'Summary 2439'!E10+'Summary 2682'!E10+'Summary 2855'!E10+#REF!+'Summary FLT104'!E10+'Summary FLT110'!E10+#REF!+#REF!+#REF!+'Summary 2037'!E10+'Summary 2817'!E10)/13 -> #REF! | F10: =('Summary 735'!F10+'Summary 2221'!F10+'Summary 2439'!F10+'Summary 2682'!F10+'Summary 2855'!F10+#REF!+'Summary FLT104'!F10+'Summary FLT110'!F10+#REF!+#REF!+#REF!+'Summary 2037'!F10+'Summary 2817'!F10)/13 -> #REF! | G10: =('Summary 735'!G10+'Summary 2221'!G10+'Summary 2439'!G10+'Summary 2682'!G10+'Summary 2855'!G10+#REF!+'Summary FLT104'!G10+'Summary FLT110'!G10+#REF!+#REF!+#REF!+'Summary 2037'!G10+'Summary 2817'!G10)/13 -> #REF! | H10: =SUM(B10:G10) -> #REF! | J10: =H10*$H$4 -> #REF!
A11: Food Cost (DM) | B11: =('Summary 735'!B11+'Summary 2221'!B11+'Summary 2439'!B11+'Summary 2682'!B11+'Summary 2855'!B11)/5 -> 0 | C11: =('Summary 735'!C11+'Summary 2221'!C11+'Summary 2439'!C11+'Summary 2682'!C11+'Summary 2855'!C11)/5 -> 0 | D11: =('Summary 735'!D11+'Summary 2221'!D11+'Summary 2439'!D11+'Summary 2682'!D11+'Summary 2855'!D11)/5 -> 0 | E11: =('Summary 735'!E11+'Summary 2221'!E11+'Summary 2439'!E11+'Summary 2682'!E11+'Summary 2855'!E11)/5 -> 0 | F11: =('Summary 735'!F11+'Summary 2221'!F11+'Summary 2439'!F11+'Summary 2682'!F11+'Summary 2855'!F11)/5 -> 0 | G11: =('Summary 735'!G11+'Summary 2221'!G11+'Summary 2439'!G11+'Summary 2682'!G11+'Summary 2855'!G11)/5 -> 0 | H11: =SUM(B11:G11) -> 0 | I11: =I12*45% -> #REF! | J11: =H11*$H$4 -> 0
A12: Wage Cost (DL) | B12: =('Summary 735'!B12+'Summary 2221'!B12+'Summary 2439'!B12+'Summary 2682'!B12+'Summary 2855'!B12+#REF!+'Summary FLT104'!B12+'Summary FLT110'!B12+#REF!+#REF!+#REF!+'Summary 2037'!B12+'Summary 2817'!B12)/13 -> #REF! | C12: =('Summary 735'!C12+'Summary 2221'!C12+'Summary 2439'!C12+'Summary 2682'!C12+'Summary 2855'!C12)/5 -> 0 | D12: =('Summary 735'!D12+'Summary 2221'!D12+'Summary 2439'!D12+'Summary 2682'!D12+'Summary 2855'!D12)/5 -> 0 | E12: =('Summary 735'!E12+'Summary 2221'!E12+'Summary 2439'!E12+'Summary 2682'!E12+'Summary 2855'!E12)/5 -> 0 | F12: =('Summary 735'!F12+'Summary 2221'!F12+'Summary 2439'!F12+'Summary 2682'!F12+'Summary 2855'!F12)/5 -> 0 | G12: =('Summary 735'!G12+'Summary 2221'!G12+'Summary 2439'!G12+'Summary 2682'!G12+'Summary 2855'!G12)/5 -> 0 | H12: =SUM(B12:G12) -> #REF! | I12: =H11+H12 -> #REF! | J12: =H12*$H$4 -> #REF!
A13: Food Mark up | B13: =('Summary 735'!B13+'Summary 2221'!B13+'Summary 2439'!B13+'Summary 2682'!B13+'Summary 2855'!B13+#REF!+'Summary FLT104'!B13+'Summary FLT110'!B13+#REF!+#REF!+#REF!+'Summary 2037'!B13+'Summary 2817'!B13)/13 -> #VALUE! | C13: =('Summary 735'!C13+'Summary 2221'!C13+'Summary 2439'!C13+'Summary 2682'!C13+'Summary 2855'!C13)/5 -> 0 | D13: =('Summary 735'!D13+'Summary 2221'!D13+'Summary 2439'!D13+'Summary 2682'!D13+'Summary 2855'!D13)/5 -> 0 | E13: =('Summary 735'!E13+'Summary 2221'!E13+'Summary 2439'!E13+'Summary 2682'!E13+'Summary 2855'!E13)/5 -> 0 | F13: =('Summary 735'!F13+'Summary 2221'!F13+'Summary 2439'!F13+'Summary 2682'!F13+'Summary 2855'!F13)/5 -> 0 | G13: =('Summary 735'!G13+'Summary 2221'!G13+'Summary 2439'!G13+'Summary 2682'!G13+'Summary 2855'!G13)/5 -> 0 | H13: =SUM(B13:G13) -> #VALUE! | J13: =H13*$H$4 -> #VALUE!
A14: Labor Mark up | B14: =('Summary 735'!B14+'Summary 2221'!B14+'Summary 2439'!B14+'Summary 2682'!B14+'Summary 2855'!B14+#REF!+'Summary FLT104'!B14+'Summary FLT110'!B14+#REF!+#REF!+#REF!+'Summary 2037'!B14+'Summary 2817'!B14)/13 -> #VALUE! | C14: =('Summary 735'!C14+'Summary 2221'!C14+'Summary 2439'!C14+'Summary 2682'!C14+'Summary 2855'!C14)/5 -> 0 | D14: =('Summary 735'!D14+'Summary 2221'!D14+'Summary 2439'!D14+'Summary 2682'!D14+'Summary 2855'!D14)/5 -> 0 | E14: =('Summary 735'!E14+'Summary 2221'!E14+'Summary 2439'!E14+'Summary 2682'!E14+'Summary 2855'!E14)/5 -> 0 | F14: =('Summary 735'!F14+'Summary 2221'!F14+'Summary 2439'!F14+'Summary 2682'!F14+'Summary 2855'!F14)/5 -> 0 | G14: =('Summary 735'!G14+'Summary 2221'!G14+'Summary 2439'!G14+'Summary 2682'!G14+'Summary 2855'!G14)/5 -> 0 | H14: =SUM(B14:G14) -> #VALUE! | J14: =H14*$H$4 -> #VALUE! | L14: Direct Labour
A15: Handling Cost | B15: =SUM('Summary 735'!B15+'Summary 2221'!B15+'Summary 2221'!B15+'Summary 2439'!B15+'Summary 2682'!B15+'Summary 2855'!B15+#REF!+'Summary FLT104'!B15+'Summary FLT110'!B15+#REF!+#REF!+#REF!+'Summary 2037'!B15+'Summary 2817'!B15)/13 -> #REF! | C15: =('Summary 735'!C15+'Summary 2221'!C15+'Summary 2439'!C15+'Summary 2682'!C15+'Summary 2855'!C15)/5 -> 0 | D15: =('Summary 735'!D15+'Summary 2221'!D15+'Summary 2439'!D15+'Summary 2682'!D15+'Summary 2855'!D15)/5 -> 0 | E15: =('Summary 735'!E15+'Summary 2221'!E15+'Summary 2439'!E15+'Summary 2682'!E15+'Summary 2855'!E15)/5 -> 0 | F15: =('Summary 735'!F15+'Summary 2221'!F15+'Summary 2439'!F15+'Summary 2682'!F15+'Summary 2855'!F15)/5 -> 0 | G15: =('Summary 735'!G15+'Summary 2221'!G15+'Summary 2439'!G15+'Summary 2682'!G15+'Summary 2855'!G15)/5 -> 0 | H15: =SUM(B15:G15) -> #REF! | J15: =H15*$H$4 -> #REF! | L15: =J12+J15 -> #REF! | M15: 1
A16: Handling Mark up | B16: =SUM('Summary 735'!B16+'Summary 2221'!B16+'Summary 2221'!B16+'Summary 2439'!B16+'Summary 2682'!B16+'Summary 2855'!B16+#REF!+'Summary FLT104'!B16+'Summary FLT110'!B16+#REF!+#REF!+#REF!+'Summary 2037'!B16+'Summary 2817'!B16)/13 -> #REF! | C16: =('Summary 735'!C16+'Summary 2221'!C16+'Summary 2439'!C16+'Summary 2682'!C16+'Summary 2855'!C16)/5 -> 0 | D16: =('Summary 735'!D16+'Summary 2221'!D16+'Summary 2439'!D16+'Summary 2682'!D16+'Summary 2855'!D16)/5 -> 0 | E16: =('Summary 735'!E16+'Summary 2221'!E16+'Summary 2439'!E16+'Summary 2682'!E16+'Summary 2855'!E16)/5 -> 0 | F16: =('Summary 735'!F16+'Summary 2221'!F16+'Summary 2439'!F16+'Summary 2682'!F16+'Summary 2855'!F16)/5 -> 0 | G16: =('Summary 735'!G16+'Summary 2221'!G16+'Summary 2439'!G16+'Summary 2682'!G16+'Summary 2855'!G16)/5 -> 0 | H16: =SUM(B16:G16) -> #REF! | J16: =H16*$H$4 -> #REF! | L16: =L15*M16 -> #REF! | M16: 0.8
A17: Total Per Flight | B17: =SUM(B11:B16) -> #REF! | C17: =SUM(C11:C16) -> 0 | D17: =SUM(D10:D16) -> #REF! | E17: =SUM(E10:E16) -> #REF! | F17: =SUM(F10:F16) -> #REF! | G17: =SUM(G10:G16) -> #REF! | H17: =SUM(H10:H16) -> #REF! | J17: =H17*$H$4 -> #REF! | L17: =L15*M17 -> #REF! | M17: 0.2
B18: =B17 -> #REF! | C18: =C17 -> 0 | D18: =D17 -> #REF! | E18: =E17-E15-E16 -> #REF! | F18: =F17 -> #REF! | G18: =G17 -> #REF! | I18: =E15+E16 -> 0
A19: Handling | B19: Cost | C19: Mark Up | D19: Price | I19: =E16 -> 0
A20: 737 Handling | B20: =SUM('Summary 735'!B20+'Summary 2221'!B20+'Summary 2221'!B20+'Summary 2439'!B20+'Summary 2682'!B20+'Summary 2855'!B20+#REF!+'Summary FLT104'!B20+'Summary FLT110'!B20+#REF!+#REF!+#REF!+'Summary 2037'!B20+'Summary 2817'!B20)/13 -> #REF! | C20: =B20*'P&L'!$R$10 -> #REF! | D20: =SUM(B20:C20) -> #REF!
A21: B777 Handling | B21: =Handling!#REF! -> #REF! | C21: =Handling!#REF! -> #REF! | D21: =Handling!#REF! -> #REF!
A22: A380 Handling | B22: =Handling!#REF! -> #REF! | C22: =Handling!#REF! -> #REF! | D22: =Handling!#REF! -> #REF!
A24: Avg Price Per Pax | B24: =IFERROR(((B11+B12+B13+B14)/B8),0) -> 0 | C24: =IFERROR(((C11+C12+C13+C14)/C8),0) -> 0 | D24: =IFERROR(((D10+D11+D12+D13+D14)/D8),0) -> 0 | E24: =IFERROR(((E10+E11+E12+E13+E14)/E8),0) -> 0 | F24: =IFERROR(((F10+F11+F12+F13+F14)/F8),0) -> 0 | G24: =IFERROR(((G10+G11+G12+G13+G14)/G8),0) -> 0
A25: Avg Mark up Per Pax | B25: =IFERROR(((B13+B14)/B8),0) -> 0 | C25: =IFERROR(((C13+C14)/C8),0) -> 0 | D25: =IFERROR(((D13+D14)/D8),0) -> 0 | E25: =IFERROR(((E13+E14)/E8),0) -> 0 | F25: =IFERROR(((F13+F14)/F8),0) -> 0 | G25: =IFERROR(((G13+G14)/G8),0) -> 0
A26: Over head Per Pax | B26: =IFERROR((B10/B8),0) -> 0 | C26: =IFERROR((C10/C8),0) -> 0 | D26: =IFERROR((D10/D8),0) -> 0 | E26: =IFERROR((E10/E8),0) -> 0 | F26: =IFERROR((F10/F8),0) -> 0 | G26: =IFERROR((G10/G8),0) -> 0
B28: CYCLE | C28: FLT
A29: Config | B29: ='P&L'!R5 -> 1
A30: OVERHEAD | B30: =B37*B8 -> 0 | C30: =C37*C8 -> 0 | D30: =D37*D8 -> 0 | E30: =E37*E8 -> 0 | F30: =F37*F8 -> 0 | G30: =G37*G8 -> 0
A31: Food Cost (DM) | B31: =('Summary 735'!B31+'Summary 2221'!B31+'Summary 2439'!B31+'Summary 2682'!B31+'Summary 2855'!B31)/5 -> 0 | C31: =('Summary 735'!C31+'Summary 2221'!C31+'Summary 2439'!C31+'Summary 2682'!C31+'Summary 2855'!C31+#REF!+'Summary FLT104'!C31+'Summary FLT110'!C31+#REF!+#REF!+#REF!+'Summary 2037'!C31+'Summary 2817'!C31)/13 -> #REF! | D31: =('Summary 735'!D31+'Summary 2221'!D31+'Summary 2439'!D31+'Summary 2682'!D31+'Summary 2855'!D31+#REF!+'Summary FLT104'!D31+'Summary FLT110'!D31+#REF!+#REF!+#REF!+'Summary 2037'!D31+'Summary 2817'!D31)/13 -> #REF! | E31: =('Summary 735'!E31+'Summary 2221'!E31+'Summary 2439'!E31+'Summary 2682'!E31+'Summary 2855'!E31)/5 -> 0 | F31: =('Summary 735'!F31+'Summary 2221'!F31+'Summary 2439'!F31+'Summary 2682'!F31+'Summary 2855'!F31+#REF!+'Summary FLT104'!F31+'Summary FLT110'!F31+#REF!+#REF!+#REF!+'Summary 2037'!F31+'Summary 2817'!F31)/13 -> #REF! | G31: =('Summary 735'!G31+'Summary 2221'!G31+'Summary 2439'!G31+'Summary 2682'!G31+'Summary 2855'!G31+#REF!+'Summary FLT104'!G31+'Summary FLT110'!G31+#REF!+#REF!+#REF!+'Summary 2037'!G31+'Summary 2817'!G31)/13 -> #REF!
A32: Wage Cost (DL) | B32: =('Summary 735'!B32+'Summary 2221'!B32+'Summary 2439'!B32+'Summary 2682'!B32+'Summary 2855'!B32)/5 -> 0 | C32: =('Summary 735'!C32+'Summary 2221'!C32+'Summary 2439'!C32+'Summary 2682'!C32+'Summary 2855'!C32+#REF!+'Summary FLT104'!C32+'Summary FLT110'!C32+#REF!+#REF!+#REF!+'Summary 2037'!C32+'Summary 2817'!C32)/13 -> #REF! | D32: =('Summary 735'!D32+'Summary 2221'!D32+'Summary 2439'!D32+'Summary 2682'!D32+'Summary 2855'!D32+#REF!+'Summary FLT104'!D32+'Summary FLT110'!D32+#REF!+#REF!+#REF!+'Summary 2037'!D32+'Summary 2817'!D32)/13 -> #REF! | E32: =('Summary 735'!E32+'Summary 2221'!E32+'Summary 2439'!E32+'Summary 2682'!E32+'Summary 2855'!E32)/5 -> 0 | F32: =('Summary 735'!F32+'Summary 2221'!F32+'Summary 2439'!F32+'Summary 2682'!F32+'Summary 2855'!F32+#REF!+'Summary FLT104'!F32+'Summary FLT110'!F32+#REF!+#REF!+#REF!+'Summary 2037'!F32+'Summary 2817'!F32)/13 -> #REF! | G32: =('Summary 735'!G32+'Summary 2221'!G32+'Summary 2439'!G32+'Summary 2682'!G32+'Summary 2855'!G32+#REF!+'Summary FLT104'!G32+'Summary FLT110'!G32+#REF!+#REF!+#REF!+'Summary 2037'!G32+'Summary 2817'!G32)/13 -> #REF!
A33: Markup Food | B33: =('Summary 735'!B33+'Summary 2221'!B33+'Summary 2439'!B33+'Summary 2682'!B33+'Summary 2855'!B33)/5 -> 0 | C33: =('Summary 735'!C33+'Summary 2221'!C33+'Summary 2439'!C33+'Summary 2682'!C33+'Summary 2855'!C33+#REF!+'Summary FLT104'!C33+'Summary FLT110'!C33+#REF!+#REF!+#REF!+'Summary 2037'!C33+'Summary 2817'!C33)/13 -> #REF! | D33: =('Summary 735'!D33+'Summary 2221'!D33+'Summary 2439'!D33+'Summary 2682'!D33+'Summary 2855'!D33+#REF!+'Summary FLT104'!D33+'Summary FLT110'!D33+#REF!+#REF!+#REF!+'Summary 2037'!D33+'Summary 2817'!D33)/13 -> #REF! | E33: =('Summary 735'!E33+'Summary 2221'!E33+'Summary 2439'!E33+'Summary 2682'!E33+'Summary 2855'!E33)/5 -> 0 | F33: =('Summary 735'!F33+'Summary 2221'!F33+'Summary 2439'!F33+'Summary 2682'!F33+'Summary 2855'!F33+#REF!+'Summary FLT104'!F33+'Summary FLT110'!F33+#REF!+#REF!+#REF!+'Summary 2037'!F33+'Summary 2817'!F33)/13 -> #REF! | G33: =('Summary 735'!G33+'Summary 2221'!G33+'Summary 2439'!G33+'Summary 2682'!G33+'Summary 2855'!G33+#REF!+'Summary FLT104'!G33+'Summary FLT110'!G33+#REF!+#REF!+#REF!+'Summary 2037'!G33+'Summary 2817'!G33)/13 -> #REF!
A34: Markup Labor | B34: =('Summary 735'!B34+'Summary 2221'!B34+'Summary 2439'!B34+'Summary 2682'!B34+'Summary 2855'!B34)/5 -> 0 | C34: =('Summary 735'!C34+'Summary 2221'!C34+'Summary 2439'!C34+'Summary 2682'!C34+'Summary 2855'!C34+#REF!+'Summary FLT104'!C34+'Summary FLT110'!C34+#REF!+#REF!+#REF!+'Summary 2037'!C34+'Summary 2817'!C34)/13 -> #REF! | D34: =('Summary 735'!D34+'Summary 2221'!D34+'Summary 2439'!D34+'Summary 2682'!D34+'Summary 2855'!D34+#REF!+'Summary FLT104'!D34+'Summary FLT110'!D34+#REF!+#REF!+#REF!+'Summary 2037'!D34+'Summary 2817'!D34)/13 -> #REF! | E34: =('Summary 735'!E34+'Summary 2221'!E34+'Summary 2439'!E34+'Summary 2682'!E34+'Summary 2855'!E34)/5 -> 0 | F34: =('Summary 735'!F34+'Summary 2221'!F34+'Summary 2439'!F34+'Summary 2682'!F34+'Summary 2855'!F34+#REF!+'Summary FLT104'!F34+'Summary FLT110'!F34+#REF!+#REF!+#REF!+'Summary 2037'!F34+'Summary 2817'!F34)/13 -> #REF! | G34: =('Summary 735'!G34+'Summary 2221'!G34+'Summary 2439'!G34+'Summary 2682'!G34+'Summary 2855'!G34+#REF!+'Summary FLT104'!G34+'Summary FLT110'!G34+#REF!+#REF!+#REF!+'Summary 2037'!G34+'Summary 2817'!G34)/13 -> #REF!
A36: Per Pax Avg
A37: OVERHEAD | B37: ='P&L'!$K$30 -> 0 | C37: ='P&L'!$L$30 -> 0 | D37: ='P&L'!$M$30 -> 0 | E37: ='P&L'!$N$30 -> 0 | F37: ='P&L'!$O$30 -> 0 | G37: ='P&L'!$P$30 -> 0
A38: Food Cost (DM) | B38: =IFERROR(B31/B7," ") | C38: =IFERROR(C31/C7," ") | D38: =IFERROR(D31/D7," ") | E38: =IFERROR(E31/E7," ") -> 0 | F38: =IFERROR(F31/F7," ") | G38: =IFERROR(G31/G7," ")
A39: Wage Cost (DL) | B39: =IFERROR(B32/B7," ") | C39: =IFERROR(C32/C7," ") | D39: =IFERROR(D32/D7," ") | E39: =IFERROR(E32/E7," ") -> 0 | F39: =IFERROR(F32/F7," ") | G39: =IFERROR(G32/G7," ")
A40: Markup Food | B40: =IFERROR(B33/B8," ") | C40: =IFERROR(C33/C7," ") | D40: =IFERROR(D33/D7," ") | E40: =IFERROR(E33/E7," ") -> 0 | F40: =IFERROR(F33/F7," ") | G40: =IFERROR(G33/G7," ")
A41: Markup Labor | B41: =IFERROR(B34/B7," ") | C41: =IFERROR(C34/C7," ") | D41: =IFERROR(D34/D7," ") | E41: =IFERROR(E34/E7," ") -> 0 | F41: =IFERROR(F34/F7," ") | G41: =IFERROR(G34/G7," ")
A108: 388
A109: 787

Sheet Summary Long Haul
A2: Customer | G2: Flights Per week | H2: =#REF!+'Summary FLT104'!H2+'Summary FLT110'!H2+#REF!+#REF!+#REF!+'Summary 2037'!H2+'Summary 2817'!H2 -> #REF! | L2: AC type | M2: Cycle
E3: AC Type | F3: 737 | G3: Flights Per Month | H3: =H4/12 -> #REF! | J3: Total Revenues | L3: 737 | M3: 1
E4: Load | F4: ='P&L'!R4 -> 0.8 | G4: Annual Flights | H4: =H2*52 -> #REF! | J4: =H17*H4 -> #REF!
A5: Summary
A6: BNA | B6: FC | C6: BC | D6: PY | E6: EY | F6: TC | G6: CY | H6: Total | I6: Hnd
A7: FLIGHT CONFIG | B7: =+'FlightConfig '!B17 -> 0 | C7: =+'FlightConfig '!C17 -> 34 | D7: =+'FlightConfig '!D17 -> 48 | E7: =+'FlightConfig '!E17 -> 198 | F7: =+'FlightConfig '!F17 -> 0 | G7: =+'FlightConfig '!G17 -> 6 | H7: =SUM(B7:G7) -> 286
A8: Load Factor | B8: =ROUNDUP(B7*$F$4,0) -> 0 | C8: =ROUNDUP(C7*$F$4,0) -> 28 | D8: =ROUNDUP(D7*$F$4,0) -> 39 | E8: =ROUNDUP(E7*$F$4,0) -> 159 | F8: =ROUNDUP(F7*$F$4,0) -> 0 | G8: =ROUNDUP(G7*$F$4,0) -> 5 | H8: =SUM(B8:G8) -> 231
B9: FIRST CLASS | C9: BUSINESS CLASS | D9: PREMIUM ECONOMY CLASS | E9: ECONOMY CLASS | F9: TECH CREW CLASS | G9: cABIN CREW CLASS | H9: Per Flight | J9: Annual
A10: OVERHEAD | B10: =(#REF!+'Summary FLT104'!B10+'Summary FLT110'!B10+#REF!+#REF!+#REF!)/6 -> #REF! | C10: =(#REF!+'Summary FLT104'!C10+'Summary FLT110'!C10+#REF!+#REF!+#REF!)/6 -> #REF! | D10: =(#REF!+'Summary FLT104'!D10+'Summary FLT110'!D10+#REF!+#REF!+#REF!)/6 -> #REF! | E10: =(#REF!+'Summary FLT104'!E10+'Summary FLT110'!E10+#REF!+#REF!+#REF!)/6 -> #REF! | F10: =(#REF!+'Summary FLT104'!F10+'Summary FLT110'!F10+#REF!+#REF!+#REF!)/6 -> #REF! | G10: =(#REF!+'Summary FLT104'!G10+'Summary FLT110'!G10+#REF!+#REF!+#REF!)/6 -> #REF! | H10: =(#REF!+'Summary FLT104'!H10+'Summary FLT110'!H10+#REF!+#REF!+#REF!)/6 -> #REF! | J10: =H10*$H$4 -> #REF!
A11: Food Cost (DM) | B11: =(#REF!+'Summary FLT104'!B11+'Summary FLT110'!B11+#REF!+#REF!+#REF!)/6 -> #REF! | C11: =(#REF!+'Summary FLT104'!C11+'Summary FLT110'!C11+#REF!+#REF!+#REF!)/6 -> #REF! | D11: =(#REF!+'Summary FLT104'!D11+'Summary FLT110'!D11+#REF!+#REF!+#REF!)/6 -> #REF! | E11: =(#REF!+'Summary FLT104'!E11+'Summary FLT110'!E11+#REF!+#REF!+#REF!)/6 -> #REF! | F11: =(#REF!+'Summary FLT104'!F11+'Summary FLT110'!F11+#REF!+#REF!+#REF!)/6 -> #REF! | G11: =(#REF!+'Summary FLT104'!G11+'Summary FLT110'!G11+#REF!+#REF!+#REF!)/6 -> #REF! | H11: =(#REF!+'Summary FLT104'!H11+'Summary FLT110'!H11+#REF!+#REF!+#REF!)/6 -> #REF! | I11: =I12*45% -> #REF! | J11: =H11*$H$4 -> #REF!
A12: Wage Cost (DL) | B12: =(#REF!+'Summary FLT104'!B12+'Summary FLT110'!B12+#REF!+#REF!+#REF!)/6 -> #REF! | C12: =(#REF!+'Summary FLT104'!C12+'Summary FLT110'!C12+#REF!+#REF!+#REF!)/6 -> #REF! | D12: =(#REF!+'Summary FLT104'!D12+'Summary FLT110'!D12+#REF!+#REF!+#REF!)/6 -> #REF! | E12: =(#REF!+'Summary FLT104'!E12+'Summary FLT110'!E12+#REF!+#REF!+#REF!)/6 -> #REF! | F12: =(#REF!+'Summary FLT104'!F12+'Summary FLT110'!F12+#REF!+#REF!+#REF!)/6 -> #REF! | G12: =(#REF!+'Summary FLT104'!G12+'Summary FLT110'!G12+#REF!+#REF!+#REF!)/6 -> #REF! | H12: =(#REF!+'Summary FLT104'!H12+'Summary FLT110'!H12+#REF!+#REF!+#REF!)/6 -> #REF! | I12: =H11+H12 -> #REF! | J12: =H12*$H$4 -> #REF!
A13: Food Mark up | B13: =(#REF!+'Summary FLT104'!B13+'Summary FLT110'!B13+#REF!+#REF!+#REF!)/6 -> #REF! | C13: =(#REF!+'Summary FLT104'!C13+'Summary FLT110'!C13+#REF!+#REF!+#REF!)/6 -> #REF! | D13: =(#REF!+'Summary FLT104'!D13+'Summary FLT110'!D13+#REF!+#REF!+#REF!)/6 -> #REF! | E13: =(#REF!+'Summary FLT104'!E13+'Summary FLT110'!E13+#REF!+#REF!+#REF!)/6 -> #REF! | F13: =(#REF!+'Summary FLT104'!F13+'Summary FLT110'!F13+#REF!+#REF!+#REF!)/6 -> #REF! | G13: =(#REF!+'Summary FLT104'!G13+'Summary FLT110'!G13+#REF!+#REF!+#REF!)/6 -> #REF! | H13: =(#REF!+'Summary FLT104'!H13+'Summary FLT110'!H13+#REF!+#REF!+#REF!)/6 -> #REF! | J13: =H13*$H$4 -> #REF!
A14: Labor Mark up | B14: =(#REF!+'Summary FLT104'!B14+'Summary FLT110'!B14+#REF!+#REF!+#REF!)/6 -> #REF! | C14: =(#REF!+'Summary FLT104'!C14+'Summary FLT110'!C14+#REF!+#REF!+#REF!)/6 -> #REF! | D14: =(#REF!+'Summary FLT104'!D14+'Summary FLT110'!D14+#REF!+#REF!+#REF!)/6 -> #REF! | E14: =(#REF!+'Summary FLT104'!E14+'Summary FLT110'!E14+#REF!+#REF!+#REF!)/6 -> #REF! | F14: =(#REF!+'Summary FLT104'!F14+'Summary FLT110'!F14+#REF!+#REF!+#REF!)/6 -> #REF! | G14: =(#REF!+'Summary FLT104'!G14+'Summary FLT110'!G14+#REF!+#REF!+#REF!)/6 -> #REF! | H14: =(#REF!+'Summary FLT104'!H14+'Summary FLT110'!H14+#REF!+#REF!+#REF!)/6 -> #REF! | J14: =H14*$H$4 -> #REF! | L14: Direct Labour
A15: Handling Cost | B15: =(#REF!+'Summary FLT104'!B15+'Summary FLT110'!B15+#REF!+#REF!+#REF!)/6 -> #REF! | C15: =(#REF!+'Summary FLT104'!C15+'Summary FLT110'!C15+#REF!+#REF!+#REF!)/6 -> #REF! | D15: =(#REF!+'Summary FLT104'!D15+'Summary FLT110'!D15+#REF!+#REF!+#REF!)/6 -> #REF! | E15: =(#REF!+'Summary FLT104'!E15+'Summary FLT110'!E15+#REF!+#REF!+#REF!)/6 -> #REF! | F15: =(#REF!+'Summary FLT104'!F15+'Summary FLT110'!F15+#REF!+#REF!+#REF!)/6 -> #REF! | G15: =(#REF!+'Summary FLT104'!G15+'Summary FLT110'!G15+#REF!+#REF!+#REF!)/6 -> #REF! | H15: =(#REF!+'Summary FLT104'!H15+'Summary FLT110'!H15+#REF!+#REF!+#REF!)/6 -> #REF! | J15: =H15*$H$4 -> #REF! | L15: =J12+J15 -> #REF! | M15: 1
A16: Handling Mark up | B16: =(#REF!+'Summary FLT104'!B16+'Summary FLT110'!B16+#REF!+#REF!+#REF!)/6 -> #REF! | C16: =(#REF!+'Summary FLT104'!C16+'Summary FLT110'!C16+#REF!+#REF!+#REF!)/6 -> #REF! | D16: =(#REF!+'Summary FLT104'!D16+'Summary FLT110'!D16+#REF!+#REF!+#REF!)/6 -> #REF! | E16: =(#REF!+'Summary FLT104'!E16+'Summary FLT110'!E16+#REF!+#REF!+#REF!)/6 -> #REF! | F16: =(#REF!+'Summary FLT104'!F16+'Summary FLT110'!F16+#REF!+#REF!+#REF!)/6 -> #REF! | G16: =(#REF!+'Summary FLT104'!G16+'Summary FLT110'!G16+#REF!+#REF!+#REF!)/6 -> #REF! | H16: =(#REF!+'Summary FLT104'!H16+'Summary FLT110'!H16+#REF!+#REF!+#REF!)/6 -> #REF! | J16: =H16*$H$4 -> #REF! | L16: =L15*M16 -> #REF! | M16: 0.8
A17: Total Per Flight | B17: =SUM(B11:B16) -> #REF! | C17: =SUM(C11:C16) -> #REF! | D17: =SUM(D10:D16) -> #REF! | E17: =SUM(E10:E16) -> #REF! | F17: =SUM(F10:F16) -> #REF! | G17: =SUM(G10:G16) -> #REF! | H17: =SUM(H10:H16) -> #REF! | J17: =H17*$H$4 -> #REF! | L17: =L15*M17 -> #REF! | M17: 0.2
B18: =B17 -> #REF! | C18: =C17 -> #REF! | D18: =D17 -> #REF! | E18: =E17-E15-E16 -> #REF! | F18: =F17 -> #REF! | G18: =G17 -> #REF! | I18: =E15+E16 -> #REF!
A19: Handling | B19: Cost | C19: Mark Up | D19: Price | I19: =E16 -> #REF!
A20: 737 Handling | B20: =(#REF!+'Summary FLT104'!B20+'Summary FLT110'!B20+#REF!+#REF!+#REF!+'Summary 2037'!B20+'Summary 2817'!B20)/8 -> #REF! | C20: =B20*'P&L'!$R$10 -> #REF! | D20: =SUM(B20:C20) -> #REF!
A21: B777 Handling | B21: =Handling!#REF! -> #REF! | C21: =Handling!#REF! -> #REF! | D21: =Handling!#REF! -> #REF!
A22: A380 Handling | B22: =Handling!#REF! -> #REF! | C22: =Handling!#REF! -> #REF! | D22: =Handling!#REF! -> #REF!
A24: Avg Price Per Pax | B24: =IFERROR(((B11+B12+B13+B14)/B8),0) -> 0 | C24: =IFERROR(((C11+C12+C13+C14)/C8),0) -> 0 | D24: =IFERROR(((D10+D11+D12+D13+D14)/D8),0) -> 0 | E24: =IFERROR(((E10+E11+E12+E13+E14)/E8),0) -> 0 | F24: =IFERROR(((F10+F11+F12+F13+F14)/F8),0) -> 0 | G24: =IFERROR(((G10+G11+G12+G13+G14)/G8),0) -> 0
A25: Avg Mark up Per Pax | B25: =IFERROR(((B13+B14)/B8),0) -> 0 | C25: =IFERROR(((C13+C14)/C8),0) -> 0 | D25: =IFERROR(((D13+D14)/D8),0) -> 0 | E25: =IFERROR(((E13+E14)/E8),0) -> 0 | F25: =IFERROR(((F13+F14)/F8),0) -> 0 | G25: =IFERROR(((G13+G14)/G8),0) -> 0
A26: Over head Per Pax | B26: =IFERROR((B10/B8),0) -> 0 | C26: =IFERROR((C10/C8),0) -> 0 | D26: =IFERROR((D10/D8),0) -> 0 | E26: =IFERROR((E10/E8),0) -> 0 | F26: =IFERROR((F10/F8),0) -> 0 | G26: =IFERROR((G10/G8),0) -> 0
B28: CYCLE | C28: FLT
A29: Config | B29: ='P&L'!R5 -> 1
A30: OVERHEAD | B30: =(#REF!+'Summary FLT104'!B30+'Summary FLT110'!B30+#REF!+#REF!+#REF!)/6 -> #REF! | C30: =(#REF!+'Summary FLT104'!C30+'Summary FLT110'!C30+#REF!+#REF!+#REF!)/6 -> #REF! | D30: =(#REF!+'Summary FLT104'!D30+'Summary FLT110'!D30+#REF!+#REF!+#REF!)/6 -> #REF! | E30: =(#REF!+'Summary FLT104'!E30+'Summary FLT110'!E30+#REF!+#REF!+#REF!)/6 -> #REF! | F30: =(#REF!+'Summary FLT104'!F30+'Summary FLT110'!F30+#REF!+#REF!+#REF!)/6 -> #REF! | G30: =(#REF!+'Summary FLT104'!G30+'Summary FLT110'!G30+#REF!+#REF!+#REF!)/6 -> #REF!
A31: Food Cost (DM) | B31: =(#REF!+'Summary FLT104'!B31+'Summary FLT110'!B31+#REF!+#REF!+#REF!)/6 -> #REF! | C31: =(#REF!+'Summary FLT104'!C31+'Summary FLT110'!C31+#REF!+#REF!+#REF!)/6 -> #REF! | D31: =(#REF!+'Summary FLT104'!D31+'Summary FLT110'!D31+#REF!+#REF!+#REF!)/6 -> #REF! | E31: =(#REF!+'Summary FLT104'!E31+'Summary FLT110'!E31+#REF!+#REF!+#REF!)/6 -> #REF! | F31: =(#REF!+'Summary FLT104'!F31+'Summary FLT110'!F31+#REF!+#REF!+#REF!)/6 -> #REF! | G31: =(#REF!+'Summary FLT104'!G31+'Summary FLT110'!G31+#REF!+#REF!+#REF!)/6 -> #REF!
A32: Wage Cost (DL) | B32: =(#REF!+'Summary FLT104'!B32+'Summary FLT110'!B32+#REF!+#REF!+#REF!)/6 -> #REF! | C32: =(#REF!+'Summary FLT104'!C32+'Summary FLT110'!C32+#REF!+#REF!+#REF!)/6 -> #REF! | D32: =(#REF!+'Summary FLT104'!D32+'Summary FLT110'!D32+#REF!+#REF!+#REF!)/6 -> #REF! | E32: =(#REF!+'Summary FLT104'!E32+'Summary FLT110'!E32+#REF!+#REF!+#REF!)/6 -> #REF! | F32: =(#REF!+'Summary FLT104'!F32+'Summary FLT110'!F32+#REF!+#REF!+#REF!)/6 -> #REF! | G32: =(#REF!+'Summary FLT104'!G32+'Summary FLT110'!G32+#REF!+#REF!+#REF!)/6 -> #REF!
A33: Markup Food | B33: =(#REF!+'Summary FLT104'!B33+'Summary FLT110'!B33+#REF!+#REF!+#REF!)/6 -> #REF! | C33: =(#REF!+'Summary FLT104'!C33+'Summary FLT110'!C33+#REF!+#REF!+#REF!)/6 -> #REF! | D33: =(#REF!+'Summary FLT104'!D33+'Summary FLT110'!D33+#REF!+#REF!+#REF!)/6 -> #REF! | E33: =(#REF!+'Summary FLT104'!E33+'Summary FLT110'!E33+#REF!+#REF!+#REF!)/6 -> #REF! | F33: =(#REF!+'Summary FLT104'!F33+'Summary FLT110'!F33+#REF!+#REF!+#REF!)/6 -> #REF! | G33: =(#REF!+'Summary FLT104'!G33+'Summary FLT110'!G33+#REF!+#REF!+#REF!)/6 -> #REF!
A34: Markup Labor | B34: =(#REF!+'Summary FLT104'!B34+'Summary FLT110'!B34+#REF!+#REF!+#REF!)/6 -> #REF! | C34: =(#REF!+'Summary FLT104'!C34+'Summary FLT110'!C34+#REF!+#REF!+#REF!)/6 -> #REF! | D34: =(#REF!+'Summary FLT104'!D34+'Summary FLT110'!D34+#REF!+#REF!+#REF!)/6 -> #REF! | E34: =(#REF!+'Summary FLT104'!E34+'Summary FLT110'!E34+#REF!+#REF!+#REF!)/6 -> #REF! | F34: =(#REF!+'Summary FLT104'!F34+'Summary FLT110'!F34+#REF!+#REF!+#REF!)/6 -> #REF! | G34: =(#REF!+'Summary FLT104'!G34+'Summary FLT110'!G34+#REF!+#REF!+#REF!)/6 -> #REF!
A36: Per Pax Avg
A37: OVERHEAD | B37: ='P&L'!$K$30 -> 0 | C37: ='P&L'!$L$30 -> 0 | D37: ='P&L'!$M$30 -> 0 | E37: ='P&L'!$N$30 -> 0 | F37: ='P&L'!$O$30 -> 0 | G37: ='P&L'!$P$30 -> 0
A38: Food Cost (DM) | B38: =IFERROR(B31/B7," ") | C38: =IFERROR(C31/C7," ") | D38: =IFERROR(D31/D7," ") | E38: =IFERROR(E31/E7," ") | F38: =IFERROR(F31/F7," ") | G38: =IFERROR(G31/G7," ")
A39: Wage Cost (DL) | B39: =IFERROR(B32/B7," ") | C39: =IFERROR(C32/C7," ") | D39: =IFERROR(D32/D7," ") | E39: =IFERROR(E32/E7," ") | F39: =IFERROR(F32/F7," ") | G39: =IFERROR(G32/G7," ")
A40: Markup Food | B40: =IFERROR(B33/B8," ") | C40: =IFERROR(C33/C7," ") | D40: =IFERROR(D33/D7," ") | E40: =IFERROR(E33/E7," ") | F40: =IFERROR(F33/F7," ") | G40: =IFERROR(G33/G7," ")
A41: Markup Labor | B41: =IFERROR(B34/B7," ") | C41: =IFERROR(C34/C7," ") | D41: =IFERROR(D34/D7," ") | E41: =IFERROR(E34/E7," ") | F41: =IFERROR(F34/F7," ") | G41: =IFERROR(G34/G7," ")
A108: 388
A109: 787

Sheet Summary  735
A2: Customer | G2: Flights Per week | H2: 0 | L2: AC type | M2: Cycle
E3: AC Type | F3: 738 | G3: Flights Per Month | H3: =H4/12 -> 0 | J3: Total Revenues | L3: 737 | M3: 1
E4: Load | F4: ='P&L'!R4 -> 0.8 | G4: Annual Flights | H4: =H2*52 -> 0 | J4: =H17*H4 -> 0
A5: Summary
A6: BNA | B6: FC | C6: BC | D6: PY | E6: EY | F6: TC | G6: CY | H6: Total | I6: Hnd
A7: FLIGHT CONFIG | B7: =+'FlightConfig '!B17 -> 0 | C7: =+'FlightConfig '!C17 -> 34 | D7: =+'FlightConfig '!D17 -> 48 | E7: =+'FlightConfig '!E17 -> 198 | F7: =+'FlightConfig '!F17 -> 0 | G7: =+'FlightConfig '!G17 -> 6 | H7: =SUM(B7:G7) -> 286
A8: Load Factor | B8: =ROUNDUP(B7*$F$4,0) -> 0 | C8: =ROUNDUP(C7*$F$4,0) -> 28 | D8: =ROUNDUP(D7*$F$4,0) -> 39 | E8: =ROUNDUP(E7*$F$4,0) -> 159 | F8: =ROUNDUP(F7*$F$4,0) -> 0 | G8: =ROUNDUP(G7*$F$4,0) -> 5 | H8: =SUM(B8:G8) -> 231
B9: FIRST CLASS | C9: BUSINESS CLASS | D9: PREMIUM ECONOMY CLASS | E9: ECONOMY CLASS | F9: TECH CREW CLASS | G9: cABIN CREW CLASS | H9: Per Flight | J9: Annual
A10: OVERHEAD | B10: =B37*B8 -> 0 | C10: =C37*C8 -> 0 | D10: =D37*D8 -> 0 | E10: =E37*E8 -> 0 | F10: =F37*F8 -> 0 | G10: =G37*G8 -> 0 | H10: =SUM(B10:G10) -> 0 | J10: =H10*$H$4 -> 0
A11: Food Cost (DM) | B11: =IFERROR(B38*B8,0) -> 0 | C11: =IFERROR(C38*$C$8,0) -> 0 | D11: =IFERROR(D38*$D$8,0) -> 0 | E11: =IFERROR(E38*$E$8,0) -> 0 | F11: =IFERROR(F38*$F$8,0) -> 0 | G11: =IFERROR(G38*G8,0) -> 0 | H11: =SUM(B11:G11) -> 0 | I11: =I12*45% -> 0 | J11: =H11*$H$4 -> 0
A12: Wage Cost (DL) | B12: =IFERROR(B39*B8,0) -> 0 | C12: =IFERROR(C39*$C$8,0) -> 0 | D12: =IFERROR(D39*$D$8,0) -> 0 | E12: =IFERROR(E39*$E$8,0) -> 0 | F12: =IFERROR(F39*$F$8,0) -> 0 | G12: =IFERROR(G39*G8,0) -> 0 | H12: =SUM(B12:G12) -> 0 | I12: =H11+H12 -> 0 | J12: =H12*$H$4 -> 0
A13: Food Mark up | B13: =IFERROR(B40*B8," ") | C13: =IFERROR(C40*$C$8,0) -> 0 | D13: =IFERROR(D40*$D$8,0) -> 0 | E13: =IFERROR(E40*$E$8,0) -> 0 | F13: =IFERROR(F40*$F$8,0) -> 0 | G13: 0 | H13: =SUM(B13:G13) -> 0 | J13: =H13*$H$4 -> 0
A14: Labor Mark up | B14: =IFERROR(B41*B8," ") | C14: =IFERROR(C41*$C$8,0) -> 0 | D14: =IFERROR(D41*$D$8,0) -> 0 | E14: =IFERROR(E41*$E$8,0) -> 0 | F14: =IFERROR(F41*$F$8,0) -> 0 | G14: 0 | H14: =SUM(B14:G14) -> 0 | J14: =H14*$H$4 -> 0 | L14: Direct Labour
A15: Handling Cost | B15: 0 | C15: 0 | D15: 0 | E15: =+B20 -> 0 | F15: 0 | G15: 0 | H15: =SUM(B15:G15) -> 0 | J15: =H15*$H$4 -> 0 | L15: =J12+J15 -> 0 | M15: 1
A16: Handling Mark up | B16: 0 | C16: 0 | D16: 0 | E16: =+C20 -> 0 | F16: 0 | G16: 0 | H16: =SUM(B16:G16) -> 0 | J16: =H16*$H$4 -> 0 | L16: =L15*M16 -> 0 | M16: 0.8
A17: Total Per Flight | B17: =SUM(B11:B16) -> 0 | C17: =SUM(C11:C16) -> 0 | D17: =SUM(D10:D16) -> 0 | E17: =SUM(E10:E16) -> 0 | F17: =SUM(F10:F16) -> 0 | G17: =SUM(G10:G16) -> 0 | H17: =SUM(H10:H16) -> 0 | J17: =H17*$H$4 -> 0 | L17: =L15*M17 -> 0 | M17: 0.2
B18: =B17 -> 0 | C18: =C17 -> 0 | D18: =D17 -> 0 | E18: =E17-E15-E16 -> 0 | F18: =F17 -> 0 | G18: =G17 -> 0 | I18: =E15+E16 -> 0
A19: Handling | B19: Cost | C19: Mark Up | D19: Price | I19: =E16 -> 0
A20: 738 Handling | B20: =Handling!C56 -> 0 | C20: =B20*'P&L'!$R$10 -> 0 | D20: =SUM(B20:C20) -> 0
A21: B777 Handling | B21: =Handling!#REF! -> #REF! | C21: =Handling!#REF! -> #REF! | D21: =Handling!#REF! -> #REF!
A22: A380 Handling | B22: =Handling!#REF! -> #REF! | C22: =Handling!#REF! -> #REF! | D22: =Handling!#REF! -> #REF!
A24: Avg Price Per Pax | B24: =IFERROR(((B11+B12+B13+B14)/B8),0) -> 0 | C24: =IFERROR(((C11+C12+C13+C14)/C8),0) -> 0 | D24: =IFERROR(((D10+D11+D12+D13+D14)/D8),0) -> 0 | E24: =IFERROR(((E10+E11+E12+E13+E14)/E8),0) -> 0 | F24: =IFERROR(((F10+F11+F12+F13+F14)/F8),0) -> 0 | G24: =IFERROR(((G10+G11+G12+G13+G14)/G8),0) -> 0
A25: Avg Mark up Per Pax | B25: =IFERROR(((B13+B14)/B8),0) -> 0 | C25: =IFERROR(((C13+C14)/C8),0) -> 0 | D25: =IFERROR(((D13+D14)/D8),0) -> 0 | E25: =IFERROR(((E13+E14)/E8),0) -> 0 | F25: =IFERROR(((F13+F14)/F8),0) -> 0 | G25: =IFERROR(((G13+G14)/G8),0) -> 0
A26: Over head Per Pax | B26: =IFERROR((B10/B8),0) -> 0 | C26: =IFERROR((C10/C8),0) -> 0 | D26: =IFERROR((D10/D8),0) -> 0 | E26: =IFERROR((E10/E8),0) -> 0 | F26: =IFERROR((F10/F8),0) -> 0 | G26: =IFERROR((G10/G8),0) -> 0
B28: CYCLE | C28: FLT
A29: Config | B29: ='P&L'!R5 -> 1 | C29: 735
A30: OVERHEAD | B30: =B37*B8 -> 0 | C30: =C37*C8 -> 0 | D30: =D37*D8 -> 0 | E30: =E37*E8 -> 0 | F30: =F37*F8 -> 0 | G30: =G37*G8 -> 0
A31: Food Cost (DM) | B31: =IFERROR(IF($B$29=$B$29,SUMIF(Food!$C:$C,B$9&$B$29&$C$29,Food!$X:$X),0),"") -> 0 | C31: =IFERROR(IF($B$29=$B$29,SUMIF(Food!$C:$C,C$9&$B$29&$C$29,Food!$X:$X),0),"") -> 0 | D31: =IFERROR(IF($B$29=$B$29,SUMIF(Food!$C:$C,D$9&$B$29&$C$29,Food!$X:$X),0),"") -> 0 | E31: =IFERROR(IF($B$29=$B$29,SUMIF(Food!$C:$C,E$9&$B$29&$C$29,Food!$X:$X),0),"") -> 0 | F31: =IFERROR(IF($B$29=$B$29,SUMIF(Food!$C:$C,F$9&$B$29&$C$29,Food!$X:$X),0),"") -> 0 | G31: =IFERROR(IF($B$29=$B$29,SUMIF(Food!$C:$C,G$9&$B$29&$C$29,Food!$X:$X),0),"") -> 0
A32: Wage Cost (DL) | B32: =IFERROR(IF($B$29=$B$29,SUMIF(Food!$C:$C,B$9&$B$29&$C$29,Food!$Z:$Z),0),"") -> 0 | C32: =IFERROR(IF($B$29=$B$29,SUMIF(Food!$C:$C,C$9&$B$29&$C$29,Food!$Z:$Z),0),"") -> 0 | D32: =IFERROR(IF($B$29=$B$29,SUMIF(Food!$C:$C,D$9&$B$29&$C$29,Food!$Z:$Z),0),"") -> 0 | E32: =IFERROR(IF($B$29=$B$29,SUMIF(Food!$C:$C,E$9&$B$29&$C$29,Food!$Z:$Z),0),"") -> 0 | F32: =IFERROR(IF($B$29=$B$29,SUMIF(Food!$C:$C,F$9&$B$29&$C$29,Food!$Z:$Z),0),"") -> 0 | G32: =IFERROR(IF($B$29=$B$29,SUMIF(Food!$C:$C,G$9&$B$29&$C$29,Food!$Z:$Z),0),"") -> 0
A33: Markup Food | B33: =IFERROR(IF($B$29=$B$29,SUMIF(Food!$C:$C,B$9&$B$29&$C$29,Food!$AB:$AB),0),"") -> 0 | C33: =IFERROR(IF($B$29=$B$29,SUMIF(Food!$C:$C,C$9&$B$29&$C$29,Food!$AB:$AB),0),"") -> 0 | D33: =IFERROR(IF($B$29=$B$29,SUMIF(Food!$C:$C,D$9&$B$29&$C$29,Food!$AB:$AB),0),"") -> 0 | E33: =IFERROR(IF($B$29=$B$29,SUMIF(Food!$C:$C,E$9&$B$29&$C$29,Food!$AB:$AB),0),"") -> 0 | F33: =IFERROR(IF($B$29=$B$29,SUMIF(Food!$C:$C,F$9&$B$29&$C$29,Food!$AB:$AB),0),"") -> 0 | G33: =IFERROR(IF($B$29=$B$29,SUMIF(Food!$C:$C,G$9&$B$29&$C$29,Food!$O:$O),0),"") -> 0
A34: Markup Labor | B34: =IFERROR(IF($B$29=$B$29,SUMIF(Food!$C:$C,B$9&$B$29&$C$29,Food!$AC:$AC),0),"") -> 0 | C34: =IFERROR(IF($B$29=$B$29,SUMIF(Food!$C:$C,C$9&$B$29&$C$29,Food!$AC:$AC),0),"") -> 0 | D34: =IFERROR(IF($B$29=$B$29,SUMIF(Food!$C:$C,D$9&$B$29&$C$29,Food!$AC:$AC),0),"") -> 0 | E34: =IFERROR(IF($B$29=$B$29,SUMIF(Food!$C:$C,E$9&$B$29&$C$29,Food!$AC:$AC),0),"") -> 0 | F34: =IFERROR(IF($B$29=$B$29,SUMIF(Food!$C:$C,F$9&$B$29&$C$29,Food!$AC:$AC),0),"") -> 0 | G34: =IFERROR(IF($B$29=$B$29,SUMIF(Food!$C:$C,G$9&$B$29&$C$29,Food!$P:$P),0),"") -> 0
A36: Per Pax Avg
A37: OVERHEAD | B37: ='P&L'!$K$30 -> 0 | C37: ='P&L'!$L$30 -> 0 | D37: ='P&L'!$M$30 -> 0 | E37: ='P&L'!$N$30 -> 0 | F37: ='P&L'!$O$30 -> 0 | G37: ='P&L'!$P$30 -> 0
A38: Food Cost (DM) | B38: =IFERROR(B31/B7," ") | C38: =IFERROR(C31/C7," ") -> 0 | D38: =IFERROR(D31/D7," ") -> 0 | E38: =IFERROR(E31/E7," ") -> 0 | F38: =IFERROR(F31/F7," ") | G38: =IFERROR(G31/G7," ") -> 0
A39: Wage Cost (DL) | B39: =IFERROR(B32/B7," ") | C39: =IFERROR(C32/C7," ") -> 0 | D39: =IFERROR(D32/D7," ") -> 0 | E39: =IFERROR(E32/E7," ") -> 0 | F39: =IFERROR(F32/F7," ") | G39: =IFERROR(G32/G7," ") -> 0
A40: Markup Food | B40: =IFERROR(B33/B8," ") | C40: =IFERROR(C33/C7," ") -> 0 | D40: =IFERROR(D33/D7," ") -> 0 | E40: =IFERROR(E33/E7," ") -> 0 | F40: =IFERROR(F33/F7," ") | G40: =IFERROR(G33/G7," ") -> 0
A41: Markup Labor | B41: =IFERROR(B34/B7," ") | C41: =IFERROR(C34/C7," ") -> 0 | D41: =IFERROR(D34/D7," ") -> 0 | E41: =IFERROR(E34/E7," ") -> 0 | F41: =IFERROR(F34/F7," ") | G41: =IFERROR(G34/G7," ") -> 0
A108: 388
A109: 787

Sheet Summary 2221
A2: Customer | G2: Flights Per week | H2: 0 | L2: AC type | M2: Cycle
E3: AC Type | F3: 738 | G3: Flights Per Month | H3: =H4/12 -> 0 | J3: Total Revenues | L3: 737 | M3: 1
E4: Load | F4: ='P&L'!R4 -> 0.8 | G4: Annual Flights | H4: =H2*52 -> 0 | J4: =H17*H4 -> 0
A5: Summary
A6: BNA | B6: FC | C6: BC | D6: PY | E6: EY | F6: TC | G6: CY | H6: Total | I6: Hnd
A7: FLIGHT CONFIG | B7: =+'FlightConfig '!B17 -> 0 | C7: =+'FlightConfig '!C17 -> 34 | D7: =+'FlightConfig '!D17 -> 48 | E7: =+'FlightConfig '!E17 -> 198 | F7: =+'FlightConfig '!F17 -> 0 | G7: =+'FlightConfig '!G17 -> 6 | H7: =SUM(B7:G7) -> 286
A8: Load Factor | B8: =ROUNDUP(B7*$F$4,0) -> 0 | C8: =ROUNDUP(C7*$F$4,0) -> 28 | D8: =ROUNDUP(D7*$F$4,0) -> 39 | E8: =ROUNDUP(E7*$F$4,0) -> 159 | F8: =ROUNDUP(F7*$F$4,0) -> 0 | G8: =ROUNDUP(G7*$F$4,0) -> 5 | H8: =SUM(B8:G8) -> 231
B9: FIRST CLASS | C9: BUSINESS CLASS | D9: PREMIUM ECONOMY CLASS | E9: ECONOMY CLASS | F9: TECH CREW CLASS | G9: cABIN CREW CLASS | H9: Per Flight | J9: Annual
A10: OVERHEAD | B10: =B37*B8 -> 0 | C10: =C37*C8 -> 0 | D10: =D37*D8 -> 0 | E10: =E37*E8 -> 0 | F10: =F37*F8 -> 0 | G10: =G37*G8 -> 0 | H10: =SUM(B10:G10) -> 0 | J10: =H10*$H$4 -> 0
A11: Food Cost (DM) | B11: =IFERROR(B38*B8,0) -> 0 | C11: =IFERROR(C38*$C$8,0) -> 0 | D11: =IFERROR(D38*$D$8,0) -> 0 | E11: =IFERROR(E38*$E$8,0) -> 0 | F11: =IFERROR(F38*$F$8,0) -> 0 | G11: =IFERROR(G38*G8,0) -> 0 | H11: =SUM(B11:G11) -> 0 | I11: =I12*45% -> 0 | J11: =H11*$H$4 -> 0
A12: Wage Cost (DL) | B12: =IFERROR(B39*B8,0) -> 0 | C12: =IFERROR(C39*$C$8,0) -> 0 | D12: =IFERROR(D39*$D$8,0) -> 0 | E12: =IFERROR(E39*$E$8,0) -> 0 | F12: =IFERROR(F39*$F$8,0) -> 0 | G12: =IFERROR(G39*G8,0) -> 0 | H12: =SUM(B12:G12) -> 0 | I12: =H11+H12 -> 0 | J12: =H12*$H$4 -> 0
A13: Food Mark up | B13: =IFERROR(B40*B8," ") | C13: =IFERROR(C40*$C$8,0) -> 0 | D13: =IFERROR(D40*$D$8,0) -> 0 | E13: =IFERROR(E40*$E$8,0) -> 0 | F13: =IFERROR(F40*$F$8,0) -> 0 | G13: 0 | H13: =SUM(B13:G13) -> 0 | J13: =H13*$H$4 -> 0
A14: Labor Mark up | B14: =IFERROR(B41*B8," ") | C14: =IFERROR(C41*$C$8,0) -> 0 | D14: =IFERROR(D41*$D$8,0) -> 0 | E14: =IFERROR(E41*$E$8,0) -> 0 | F14: =IFERROR(F41*$F$8,0) -> 0 | G14: 0 | H14: =SUM(B14:G14) -> 0 | J14: =H14*$H$4 -> 0 | L14: Direct Labour
A15: Handling Cost | B15: 0 | C15: 0 | D15: 0 | E15: =+B20 -> 0 | F15: 0 | G15: 0 | H15: =SUM(B15:G15) -> 0 | J15: =H15*$H$4 -> 0 | L15: =J12+J15 -> 0 | M15: 1
A16: Handling Mark up | B16: 0 | C16: 0 | D16: 0 | E16: =+C20 -> 0 | F16: 0 | G16: 0 | H16: =SUM(B16:G16) -> 0 | J16: =H16*$H$4 -> 0 | L16: =L15*M16 -> 0 | M16: 0.8
A17: Total Per Flight | B17: =SUM(B11:B16) -> 0 | C17: =SUM(C11:C16) -> 0 | D17: =SUM(D10:D16) -> 0 | E17: =SUM(E10:E16) -> 0 | F17: =SUM(F10:F16) -> 0 | G17: =SUM(G10:G16) -> 0 | H17: =SUM(H10:H16) -> 0 | J17: =H17*$H$4 -> 0 | L17: =L15*M17 -> 0 | M17: 0.2
B18: =B17 -> 0 | C18: =C17 -> 0 | D18: =D17 -> 0 | E18: =E17-E15-E16 -> 0 | F18: =F17 -> 0 | G18: =G17 -> 0 | I18: =E15+E16 -> 0
A19: Handling | B19: Cost | C19: Mark Up | D19: Price | I19: =E16 -> 0
A20: 738 Handling | B20: =Handling!C56 -> 0 | C20: =B20*'P&L'!$R$10 -> 0 | D20: =SUM(B20:C20) -> 0
A21: B777 Handling | B21: =Handling!#REF! -> #REF! | C21: =Handling!#REF! -> #REF! | D21: =Handling!#REF! -> #REF!
A22: A380 Handling | B22: =Handling!#REF! -> #REF! | C22: =Handling!#REF! -> #REF! | D22: =Handling!#REF! -> #REF!
A24: Avg Price Per Pax | B24: =IFERROR(((B11+B12+B13+B14)/B8),0) -> 0 | C24: =IFERROR(((C11+C12+C13+C14)/C8),0) -> 0 | D24: =IFERROR(((D10+D11+D12+D13+D14)/D8),0) -> 0 | E24: =IFERROR(((E10+E11+E12+E13+E14)/E8),0) -> 0 | F24: =IFERROR(((F10+F11+F12+F13+F14)/F8),0) -> 0 | G24: =IFERROR(((G10+G11+G12+G13+G14)/G8),0) -> 0
A25: Avg Mark up Per Pax | B25: =IFERROR(((B13+B14)/B8),0) -> 0 | C25: =IFERROR(((C13+C14)/C8),0) -> 0 | D25: =IFERROR(((D13+D14)/D8),0) -> 0 | E25: =IFERROR(((E13+E14)/E8),0) -> 0 | F25: =IFERROR(((F13+F14)/F8),0) -> 0 | G25: =IFERROR(((G13+G14)/G8),0) -> 0
A26: Over head Per Pax | B26: =IFERROR((B10/B8),0) -> 0 | C26: =IFERROR((C10/C8),0) -> 0 | D26: =IFERROR((D10/D8),0) -> 0 | E26: =IFERROR((E10/E8),0) -> 0 | F26: =IFERROR((F10/F8),0) -> 0 | G26: =IFERROR((G10/G8),0) -> 0
B28: CYCLE | C28: FLT
A29: Config | B29: ='P&L'!R5 -> 1 | C29: 2221
A30: OVERHEAD | B30: =B37*B8 -> 0 | C30: =C37*C8 -> 0 | D30: =D37*D8 -> 0 | E30: =E37*E8 -> 0 | F30: =F37*F8 -> 0 | G30: =G37*G8 -> 0
A31: Food Cost (DM) | B31: =IFERROR(IF($B$29=$B$29,SUMIF(Food!$C:$C,B$9&$B$29&$C$29,Food!$X:$X),0),"") -> 0 | C31: =IFERROR(IF($B$29=$B$29,SUMIF(Food!$C:$C,C$9&$B$29&$C$29,Food!$X:$X),0),"") -> 0 | D31: =IFERROR(IF($B$29=$B$29,SUMIF(Food!$C:$C,D$9&$B$29&$C$29,Food!$X:$X),0),"") -> 0 | E31: =IFERROR(IF($B$29=$B$29,SUMIF(Food!$C:$C,E$9&$B$29&$C$29,Food!$X:$X),0),"") -> 0 | F31: =IFERROR(IF($B$29=$B$29,SUMIF(Food!$C:$C,F$9&$B$29&$C$29,Food!$X:$X),0),"") -> 0 | G31: =IFERROR(IF($B$29=$B$29,SUMIF(Food!$C:$C,G$9&$B$29&$C$29,Food!$X:$X),0),"") -> 0
A32: Wage Cost (DL) | B32: =IFERROR(IF($B$29=$B$29,SUMIF(Food!$C:$C,B$9&$B$29&$C$29,Food!$Z:$Z),0),"") -> 0 | C32: =IFERROR(IF($B$29=$B$29,SUMIF(Food!$C:$C,C$9&$B$29&$C$29,Food!$Z:$Z),0),"") -> 0 | D32: =IFERROR(IF($B$29=$B$29,SUMIF(Food!$C:$C,D$9&$B$29&$C$29,Food!$Z:$Z),0),"") -> 0 | E32: =IFERROR(IF($B$29=$B$29,SUMIF(Food!$C:$C,E$9&$B$29&$C$29,Food!$Z:$Z),0),"") -> 0 | F32: =IFERROR(IF($B$29=$B$29,SUMIF(Food!$C:$C,F$9&$B$29&$C$29,Food!$Z:$Z),0),"") -> 0 | G32: =IFERROR(IF($B$29=$B$29,SUMIF(Food!$C:$C,G$9&$B$29&$C$29,Food!$Z:$Z),0),"") -> 0
A33: Markup Food | B33: =IFERROR(IF($B$29=$B$29,SUMIF(Food!$C:$C,B$9&$B$29&$C$29,Food!$AB:$AB),0),"") -> 0 | C33: =IFERROR(IF($B$29=$B$29,SUMIF(Food!$C:$C,C$9&$B$29&$C$29,Food!$AB:$AB),0),"") -> 0 | D33: =IFERROR(IF($B$29=$B$29,SUMIF(Food!$C:$C,D$9&$B$29&$C$29,Food!$AB:$AB),0),"") -> 0 | E33: =IFERROR(IF($B$29=$B$29,SUMIF(Food!$C:$C,E$9&$B$29&$C$29,Food!$AB:$AB),0),"") -> 0 | F33: =IFERROR(IF($B$29=$B$29,SUMIF(Food!$C:$C,F$9&$B$29&$C$29,Food!$AB:$AB),0),"") -> 0 | G33: =IFERROR(IF($B$29=$B$29,SUMIF(Food!$C:$C,G$9&$B$29&$C$29,Food!$O:$O),0),"") -> 0
A34: Markup Labor | B34: =IFERROR(IF($B$29=$B$29,SUMIF(Food!$C:$C,B$9&$B$29&$C$29,Food!$AC:$AC),0),"") -> 0 | C34: =IFERROR(IF($B$29=$B$29,SUMIF(Food!$C:$C,C$9&$B$29&$C$29,Food!$AC:$AC),0),"") -> 0 | D34: =IFERROR(IF($B$29=$B$29,SUMIF(Food!$C:$C,D$9&$B$29&$C$29,Food!$AC:$AC),0),"") -> 0 | E34: =IFERROR(IF($B$29=$B$29,SUMIF(Food!$C:$C,E$9&$B$29&$C$29,Food!$AC:$AC),0),"") -> 0 | F34: =IFERROR(IF($B$29=$B$29,SUMIF(Food!$C:$C,F$9&$B$29&$C$29,Food!$AC:$AC),0),"") -> 0 | G34: =IFERROR(IF($B$29=$B$29,SUMIF(Food!$C:$C,G$9&$B$29&$C$29,Food!$P:$P),0),"") -> 0
A36: Per Pax Avg
A37: OVERHEAD | B37: ='P&L'!$K$30 -> 0 | C37: ='P&L'!$L$30 -> 0 | D37: ='P&L'!$M$30 -> 0 | E37: ='P&L'!$N$30 -> 0 | F37: ='P&L'!$O$30 -> 0 | G37: ='P&L'!$P$30 -> 0
A38: Food Cost (DM) | B38: =IFERROR(B31/B7," ") | C38: =IFERROR(C31/C7," ") -> 0 | D38: =IFERROR(D31/D7," ") -> 0 | E38: =IFERROR(E31/E7," ") -> 0 | F38: =IFERROR(F31/F7," ") | G38: =IFERROR(G31/G7," ") -> 0
A39: Wage Cost (DL) | B39: =IFERROR(B32/B7," ") | C39: =IFERROR(C32/C7," ") -> 0 | D39: =IFERROR(D32/D7," ") -> 0 | E39: =IFERROR(E32/E7," ") -> 0 | F39: =IFERROR(F32/F7," ") | G39: =IFERROR(G32/G7," ") -> 0
A40: Markup Food | B40: =IFERROR(B33/B8," ") | C40: =IFERROR(C33/C7," ") -> 0 | D40: =IFERROR(D33/D7," ") -> 0 | E40: =IFERROR(E33/E7," ") -> 0 | F40: =IFERROR(F33/F7," ") | G40: =IFERROR(G33/G7," ") -> 0
A41: Markup Labor | B41: =IFERROR(B34/B7," ") | C41: =IFERROR(C34/C7," ") -> 0 | D41: =IFERROR(D34/D7," ") -> 0 | E41: =IFERROR(E34/E7," ") -> 0 | F41: =IFERROR(F34/F7," ") | G41: =IFERROR(G34/G7," ") -> 0
A108: 388
A109: 787

Sheet Summary 2439
A2: Customer | G2: Flights Per week | H2: 0 | L2: AC type | M2: Cycle
E3: AC Type | F3: 738 | G3: Flights Per Month | H3: =H4/12 -> 0 | J3: Total Revenues | L3: 737 | M3: 1
E4: Load | F4: ='P&L'!R4 -> 0.8 | G4: Annual Flights | H4: =H2*52 -> 0 | J4: =H17*H4 -> 0
A5: Summary
A6: BNA | B6: FC | C6: BC | D6: PY | E6: EY | F6: TC | G6: CY | H6: Total | I6: Hnd
A7: FLIGHT CONFIG | B7: =+'FlightConfig '!B17 -> 0 | C7: =+'FlightConfig '!C17 -> 34 | D7: =+'FlightConfig '!D17 -> 48 | E7: =+'FlightConfig '!E17 -> 198 | F7: =+'FlightConfig '!F17 -> 0 | G7: =+'FlightConfig '!G17 -> 6 | H7: =SUM(B7:G7) -> 286
A8: Load Factor | B8: =ROUNDUP(B7*$F$4,0) -> 0 | C8: =ROUNDUP(C7*$F$4,0) -> 28 | D8: =ROUNDUP(D7*$F$4,0) -> 39 | E8: =ROUNDUP(E7*$F$4,0) -> 159 | F8: =ROUNDUP(F7*$F$4,0) -> 0 | G8: =ROUNDUP(G7*$F$4,0) -> 5 | H8: =SUM(B8:G8) -> 231
B9: FIRST CLASS | C9: BUSINESS CLASS | D9: PREMIUM ECONOMY CLASS | E9: ECONOMY CLASS | F9: TECH CREW CLASS | G9: cABIN CREW CLASS | H9: Per Flight | J9: Annual
A10: OVERHEAD | B10: =B37*B8 -> 0 | C10: =C37*C8 -> 0 | D10: =D37*D8 -> 0 | E10: =E37*E8 -> 0 | F10: =F37*F8 -> 0 | G10: =G37*G8 -> 0 | H10: =SUM(B10:G10) -> 0 | J10: =H10*$H$4 -> 0
A11: Food Cost (DM) | B11: =IFERROR(B38*B8,0) -> 0 | C11: =IFERROR(C38*$C$8,0) -> 0 | D11: =IFERROR(D38*$D$8,0) -> 0 | E11: =IFERROR(E38*$E$8,0) -> 0 | F11: =IFERROR(F38*$F$8,0) -> 0 | G11: =IFERROR(G38*G8,0) -> 0 | H11: =SUM(B11:G11) -> 0 | I11: =I12*45% -> 0 | J11: =H11*$H$4 -> 0
A12: Wage Cost (DL) | B12: =IFERROR(B39*B8,0) -> 0 | C12: =IFERROR(C39*$C$8,0) -> 0 | D12: =IFERROR(D39*$D$8,0) -> 0 | E12: =IFERROR(E39*$E$8,0) -> 0 | F12: =IFERROR(F39*$F$8,0) -> 0 | G12: =IFERROR(G39*G8,0) -> 0 | H12: =SUM(B12:G12) -> 0 | I12: =H11+H12 -> 0 | J12: =H12*$H$4 -> 0
A13: Food Mark up | B13: =IFERROR(B40*B8," ") | C13: =IFERROR(C40*$C$8,0) -> 0 | D13: =IFERROR(D40*$D$8,0) -> 0 | E13: =IFERROR(E40*$E$8,0) -> 0 | F13: =IFERROR(F40*$F$8,0) -> 0 | G13: 0 | H13: =SUM(B13:G13) -> 0 | J13: =H13*$H$4 -> 0
A14: Labor Mark up | B14: =IFERROR(B41*B8," ") | C14: =IFERROR(C41*$C$8,0) -> 0 | D14: =IFERROR(D41*$D$8,0) -> 0 | E14: =IFERROR(E41*$E$8,0) -> 0 | F14: =IFERROR(F41*$F$8,0) -> 0 | G14: 0 | H14: =SUM(B14:G14) -> 0 | J14: =H14*$H$4 -> 0 | L14: Direct Labour
A15: Handling Cost | B15: 0 | C15: 0 | D15: 0 | E15: =+B20 -> 0 | F15: 0 | G15: 0 | H15: =SUM(B15:G15) -> 0 | J15: =H15*$H$4 -> 0 | L15: =J12+J15 -> 0 | M15: 1
A16: Handling Mark up | B16: 0 | C16: 0 | D16: 0 | E16: =+C20 -> 0 | F16: 0 | G16: 0 | H16: =SUM(B16:G16) -> 0 | J16: =H16*$H$4 -> 0 | L16: =L15*M16 -> 0 | M16: 0.8
A17: Total Per Flight | B17: =SUM(B11:B16) -> 0 | C17: =SUM(C11:C16) -> 0 | D17: =SUM(D10:D16) -> 0 | E17: =SUM(E10:E16) -> 0 | F17: =SUM(F10:F16) -> 0 | G17: =SUM(G10:G16) -> 0 | H17: =SUM(H10:H16) -> 0 | J17: =H17*$H$4 -> 0 | L17: =L15*M17 -> 0 | M17: 0.2
B18: =B17 -> 0 | C18: =C17 -> 0 | D18: =D17 -> 0 | E18: =E17-E15-E16 -> 0 | F18: =F17 -> 0 | G18: =G17 -> 0 | I18: =E15+E16 -> 0
A19: Handling | B19: Cost | C19: Mark Up | D19: Price | I19: =E16 -> 0
A20: 738 Handling | B20: =Handling!C56 -> 0 | C20: =B20*'P&L'!$R$10 -> 0 | D20: =SUM(B20:C20) -> 0
A21: B777 Handling | B21: =Handling!#REF! -> #REF! | C21: =Handling!#REF! -> #REF! | D21: =Handling!#REF! -> #REF!
A22: A380 Handling | B22: =Handling!#REF! -> #REF! | C22: =Handling!#REF! -> #REF! | D22: =Handling!#REF! -> #REF!
A24: Avg Price Per Pax | B24: =IFERROR(((B11+B12+B13+B14)/B8),0) -> 0 | C24: =IFERROR(((C11+C12+C13+C14)/C8),0) -> 0 | D24: =IFERROR(((D10+D11+D12+D13+D14)/D8),0) -> 0 | E24: =IFERROR(((E10+E11+E12+E13+E14)/E8),0) -> 0 | F24: =IFERROR(((F10+F11+F12+F13+F14)/F8),0) -> 0 | G24: =IFERROR(((G10+G11+G12+G13+G14)/G8),0) -> 0
A25: Avg Mark up Per Pax | B25: =IFERROR(((B13+B14)/B8),0) -> 0 | C25: =IFERROR(((C13+C14)/C8),0) -> 0 | D25: =IFERROR(((D13+D14)/D8),0) -> 0 | E25: =IFERROR(((E13+E14)/E8),0) -> 0 | F25: =IFERROR(((F13+F14)/F8),0) -> 0 | G25: =IFERROR(((G13+G14)/G8),0) -> 0
A26: Over head Per Pax | B26: =IFERROR((B10/B8),0) -> 0 | C26: =IFERROR((C10/C8),0) -> 0 | D26: =IFERROR((D10/D8),0) -> 0 | E26: =IFERROR((E10/E8),0) -> 0 | F26: =IFERROR((F10/F8),0) -> 0 | G26: =IFERROR((G10/G8),0) -> 0
B28: CYCLE | C28: FLT
A29: Config | B29: ='P&L'!R5 -> 1 | C29: 2439
A30: OVERHEAD | B30: =B37*B8 -> 0 | C30: =C37*C8 -> 0 | D30: =D37*D8 -> 0 | E30: =E37*E8 -> 0 | F30: =F37*F8 -> 0 | G30: =G37*G8 -> 0
A31: Food Cost (DM) | B31: =IFERROR(IF($B$29=$B$29,SUMIF(Food!$C:$C,B$9&$B$29&$C$29,Food!$X:$X),0),"") -> 0 | C31: =IFERROR(IF($B$29=$B$29,SUMIF(Food!$C:$C,C$9&$B$29&$C$29,Food!$X:$X),0),"") -> 0 | D31: =IFERROR(IF($B$29=$B$29,SUMIF(Food!$C:$C,D$9&$B$29&$C$29,Food!$X:$X),0),"") -> 0 | E31: =IFERROR(IF($B$29=$B$29,SUMIF(Food!$C:$C,E$9&$B$29&$C$29,Food!$X:$X),0),"") -> 0 | F31: =IFERROR(IF($B$29=$B$29,SUMIF(Food!$C:$C,F$9&$B$29&$C$29,Food!$X:$X),0),"") -> 0 | G31: =IFERROR(IF($B$29=$B$29,SUMIF(Food!$C:$C,G$9&$B$29&$C$29,Food!$X:$X),0),"") -> 0
A32: Wage Cost (DL) | B32: =IFERROR(IF($B$29=$B$29,SUMIF(Food!$C:$C,B$9&$B$29&$C$29,Food!$Z:$Z),0),"") -> 0 | C32: =IFERROR(IF($B$29=$B$29,SUMIF(Food!$C:$C,C$9&$B$29&$C$29,Food!$Z:$Z),0),"") -> 0 | D32: =IFERROR(IF($B$29=$B$29,SUMIF(Food!$C:$C,D$9&$B$29&$C$29,Food!$Z:$Z),0),"") -> 0 | E32: =IFERROR(IF($B$29=$B$29,SUMIF(Food!$C:$C,E$9&$B$29&$C$29,Food!$Z:$Z),0),"") -> 0 | F32: =IFERROR(IF($B$29=$B$29,SUMIF(Food!$C:$C,F$9&$B$29&$C$29,Food!$Z:$Z),0),"") -> 0 | G32: =IFERROR(IF($B$29=$B$29,SUMIF(Food!$C:$C,G$9&$B$29&$C$29,Food!$Z:$Z),0),"") -> 0
A33: Markup Food | B33: =IFERROR(IF($B$29=$B$29,SUMIF(Food!$C:$C,B$9&$B$29&$C$29,Food!$AB:$AB),0),"") -> 0 | C33: =IFERROR(IF($B$29=$B$29,SUMIF(Food!$C:$C,C$9&$B$29&$C$29,Food!$AB:$AB),0),"") -> 0 | D33: =IFERROR(IF($B$29=$B$29,SUMIF(Food!$C:$C,D$9&$B$29&$C$29,Food!$AB:$AB),0),"") -> 0 | E33: =IFERROR(IF($B$29=$B$29,SUMIF(Food!$C:$C,E$9&$B$29&$C$29,Food!$AB:$AB),0),"") -> 0 | F33: =IFERROR(IF($B$29=$B$29,SUMIF(Food!$C:$C,F$9&$B$29&$C$29,Food!$AB:$AB),0),"") -> 0 | G33: =IFERROR(IF($B$29=$B$29,SUMIF(Food!$C:$C,G$9&$B$29&$C$29,Food!$O:$O),0),"") -> 0
A34: Markup Labor | B34: =IFERROR(IF($B$29=$B$29,SUMIF(Food!$C:$C,B$9&$B$29&$C$29,Food!$AC:$AC),0),"") -> 0 | C34: =IFERROR(IF($B$29=$B$29,SUMIF(Food!$C:$C,C$9&$B$29&$C$29,Food!$AC:$AC),0),"") -> 0 | D34: =IFERROR(IF($B$29=$B$29,SUMIF(Food!$C:$C,D$9&$B$29&$C$29,Food!$AC:$AC),0),"") -> 0 | E34: =IFERROR(IF($B$29=$B$29,SUMIF(Food!$C:$C,E$9&$B$29&$C$29,Food!$AC:$AC),0),"") -> 0 | F34: =IFERROR(IF($B$29=$B$29,SUMIF(Food!$C:$C,F$9&$B$29&$C$29,Food!$AC:$AC),0),"") -> 0 | G34: =IFERROR(IF($B$29=$B$29,SUMIF(Food!$C:$C,G$9&$B$29&$C$29,Food!$P:$P),0),"") -> 0
A36: Per Pax Avg
A37: OVERHEAD | B37: ='P&L'!$K$30 -> 0 | C37: ='P&L'!$L$30 -> 0 | D37: ='P&L'!$M$30 -> 0 | E37: ='P&L'!$N$30 -> 0 | F37: ='P&L'!$O$30 -> 0 | G37: ='P&L'!$P$30 -> 0
A38: Food Cost (DM) | B38: =IFERROR(B31/B7," ") | C38: =IFERROR(C31/C7," ") -> 0 | D38: =IFERROR(D31/D7," ") -> 0 | E38: =IFERROR(E31/E7," ") -> 0 | F38: =IFERROR(F31/F7," ") | G38: =IFERROR(G31/G7," ") -> 0
A39: Wage Cost (DL) | B39: =IFERROR(B32/B7," ") | C39: =IFERROR(C32/C7," ") -> 0 | D39: =IFERROR(D32/D7," ") -> 0 | E39: =IFERROR(E32/E7," ") -> 0 | F39: =IFERROR(F32/F7," ") | G39: =IFERROR(G32/G7," ") -> 0
A40: Markup Food | B40: =IFERROR(B33/B8," ") | C40: =IFERROR(C33/C7," ") -> 0 | D40: =IFERROR(D33/D7," ") -> 0 | E40: =IFERROR(E33/E7," ") -> 0 | F40: =IFERROR(F33/F7," ") | G40: =IFERROR(G33/G7," ") -> 0
A41: Markup Labor | B41: =IFERROR(B34/B7," ") | C41: =IFERROR(C34/C7," ") -> 0 | D41: =IFERROR(D34/D7," ") -> 0 | E41: =IFERROR(E34/E7," ") -> 0 | F41: =IFERROR(F34/F7," ") | G41: =IFERROR(G34/G7," ") -> 0
A108: 388
A109: 787

Sheet Summary 2682
A2: Customer | G2: Flights Per week | H2: 0 | L2: AC type | M2: Cycle
E3: AC Type | F3: 738 | G3: Flights Per Month | H3: =H4/12 -> 0 | J3: Total Revenues | L3: 737 | M3: 1
E4: Load | F4: ='P&L'!R4 -> 0.8 | G4: Annual Flights | H4: =H2*52 -> 0 | J4: =H17*H4 -> 0
A5: Summary
A6: BNA | B6: FC | C6: BC | D6: PY | E6: EY | F6: TC | G6: CY | H6: Total | I6: Hnd
A7: FLIGHT CONFIG | B7: =+'FlightConfig '!B17 -> 0 | C7: =+'FlightConfig '!C17 -> 34 | D7: =+'FlightConfig '!D17 -> 48 | E7: =+'FlightConfig '!E17 -> 198 | F7: =+'FlightConfig '!F17 -> 0 | G7: =+'FlightConfig '!G17 -> 6 | H7: =SUM(B7:G7) -> 286
A8: Load Factor | B8: =ROUNDUP(B7*$F$4,0) -> 0 | C8: =ROUNDUP(C7*$F$4,0) -> 28 | D8: =ROUNDUP(D7*$F$4,0) -> 39 | E8: =ROUNDUP(E7*$F$4,0) -> 159 | F8: =ROUNDUP(F7*$F$4,0) -> 0 | G8: =ROUNDUP(G7*$F$4,0) -> 5 | H8: =SUM(B8:G8) -> 231
B9: FIRST CLASS | C9: BUSINESS CLASS | D9: PREMIUM ECONOMY CLASS | E9: ECONOMY CLASS | F9: TECH CREW CLASS | G9: cABIN CREW CLASS | H9: Per Flight | J9: Annual
A10: OVERHEAD | B10: =B37*B8 -> 0 | C10: =C37*C8 -> 0 | D10: =D37*D8 -> 0 | E10: =E37*E8 -> 0 | F10: =F37*F8 -> 0 | G10: =G37*G8 -> 0 | H10: =SUM(B10:G10) -> 0 | J10: =H10*$H$4 -> 0
A11: Food Cost (DM) | B11: =IFERROR(B38*B8,0) -> 0 | C11: =IFERROR(C38*$C$8,0) -> 0 | D11: =IFERROR(D38*$D$8,0) -> 0 | E11: =IFERROR(E38*$E$8,0) -> 0 | F11: =IFERROR(F38*$F$8,0) -> 0 | G11: =IFERROR(G38*G8,0) -> 0 | H11: =SUM(B11:G11) -> 0 | I11: =I12*45% -> 0 | J11: =H11*$H$4 -> 0
A12: Wage Cost (DL) | B12: =IFERROR(B39*B8,0) -> 0 | C12: =IFERROR(C39*$C$8,0) -> 0 | D12: =IFERROR(D39*$D$8,0) -> 0 | E12: =IFERROR(E39*$E$8,0) -> 0 | F12: =IFERROR(F39*$F$8,0) -> 0 | G12: =IFERROR(G39*G8,0) -> 0 | H12: =SUM(B12:G12) -> 0 | I12: =H11+H12 -> 0 | J12: =H12*$H$4 -> 0
A13: Food Mark up | B13: =IFERROR(B40*B8," ") | C13: =IFERROR(C40*$C$8,0) -> 0 | D13: =IFERROR(D40*$D$8,0) -> 0 | E13: =IFERROR(E40*$E$8,0) -> 0 | F13: =IFERROR(F40*$F$8,0) -> 0 | G13: 0 | H13: =SUM(B13:G13) -> 0 | J13: =H13*$H$4 -> 0
A14: Labor Mark up | B14: =IFERROR(B41*B8," ") | C14: =IFERROR(C41*$C$8,0) -> 0 | D14: =IFERROR(D41*$D$8,0) -> 0 | E14: =IFERROR(E41*$E$8,0) -> 0 | F14: =IFERROR(F41*$F$8,0) -> 0 | G14: 0 | H14: =SUM(B14:G14) -> 0 | J14: =H14*$H$4 -> 0 | L14: Direct Labour
A15: Handling Cost | B15: 0 | C15: 0 | D15: 0 | E15: =+B20 -> 0 | F15: 0 | G15: 0 | H15: =SUM(B15:G15) -> 0 | J15: =H15*$H$4 -> 0 | L15: =J12+J15 -> 0 | M15: 1
A16: Handling Mark up | B16: 0 | C16: 0 | D16: 0 | E16: =+C20 -> 0 | F16: 0 | G16: 0 | H16: =SUM(B16:G16) -> 0 | J16: =H16*$H$4 -> 0 | L16: =L15*M16 -> 0 | M16: 0.8
A17: Total Per Flight | B17: =SUM(B11:B16) -> 0 | C17: =SUM(C11:C16) -> 0 | D17: =SUM(D10:D16) -> 0 | E17: =SUM(E10:E16) -> 0 | F17: =SUM(F10:F16) -> 0 | G17: =SUM(G10:G16) -> 0 | H17: =SUM(H10:H16) -> 0 | J17: =H17*$H$4 -> 0 | L17: =L15*M17 -> 0 | M17: 0.2
B18: =B17 -> 0 | C18: =C17 -> 0 | D18: =D17 -> 0 | E18: =E17-E15-E16 -> 0 | F18: =F17 -> 0 | G18: =G17 -> 0 | I18: =E15+E16 -> 0
A19: Handling | B19: Cost | C19: Mark Up | D19: Price | I19: =E16 -> 0
A20: 738 Handling | B20: =Handling!C56 -> 0 | C20: =B20*'P&L'!$R$10 -> 0 | D20: =SUM(B20:C20) -> 0
A21: B777 Handling | B21: =Handling!#REF! -> #REF! | C21: =Handling!#REF! -> #REF! | D21: =Handling!#REF! -> #REF!
A22: A380 Handling | B22: =Handling!#REF! -> #REF! | C22: =Handling!#REF! -> #REF! | D22: =Handling!#REF! -> #REF!
A24: Avg Price Per Pax | B24: =IFERROR(((B11+B12+B13+B14)/B8),0) -> 0 | C24: =IFERROR(((C11+C12+C13+C14)/C8),0) -> 0 | D24: =IFERROR(((D10+D11+D12+D13+D14)/D8),0) -> 0 | E24: =IFERROR(((E10+E11+E12+E13+E14)/E8),0) -> 0 | F24: =IFERROR(((F10+F11+F12+F13+F14)/F8),0) -> 0 | G24: =IFERROR(((G10+G11+G12+G13+G14)/G8),0) -> 0
A25: Avg Mark up Per Pax | B25: =IFERROR(((B13+B14)/B8),0) -> 0 | C25: =IFERROR(((C13+C14)/C8),0) -> 0 | D25: =IFERROR(((D13+D14)/D8),0) -> 0 | E25: =IFERROR(((E13+E14)/E8),0) -> 0 | F25: =IFERROR(((F13+F14)/F8),0) -> 0 | G25: =IFERROR(((G13+G14)/G8),0) -> 0
A26: Over head Per Pax | B26: =IFERROR((B10/B8),0) -> 0 | C26: =IFERROR((C10/C8),0) -> 0 | D26: =IFERROR((D10/D8),0) -> 0 | E26: =IFERROR((E10/E8),0) -> 0 | F26: =IFERROR((F10/F8),0) -> 0 | G26: =IFERROR((G10/G8),0) -> 0
B28: CYCLE | C28: FLT
A29: Config | B29: ='P&L'!R5 -> 1 | C29: 2682
A30: OVERHEAD | B30: =B37*B8 -> 0 | C30: =C37*C8 -> 0 | D30: =D37*D8 -> 0 | E30: =E37*E8 -> 0 | F30: =F37*F8 -> 0 | G30: =G37*G8 -> 0
A31: Food Cost (DM) | B31: =IFERROR(IF($B$29=$B$29,SUMIF(Food!$C:$C,B$9&$B$29&$C$29,Food!$X:$X),0),"") -> 0 | C31: =IFERROR(IF($B$29=$B$29,SUMIF(Food!$C:$C,C$9&$B$29&$C$29,Food!$X:$X),0),"") -> 0 | D31: =IFERROR(IF($B$29=$B$29,SUMIF(Food!$C:$C,D$9&$B$29&$C$29,Food!$X:$X),0),"") -> 0 | E31: =IFERROR(IF($B$29=$B$29,SUMIF(Food!$C:$C,E$9&$B$29&$C$29,Food!$X:$X),0),"") -> 0 | F31: =IFERROR(IF($B$29=$B$29,SUMIF(Food!$C:$C,F$9&$B$29&$C$29,Food!$X:$X),0),"") -> 0 | G31: =IFERROR(IF($B$29=$B$29,SUMIF(Food!$C:$C,G$9&$B$29&$C$29,Food!$X:$X),0),"") -> 0
A32: Wage Cost (DL) | B32: =IFERROR(IF($B$29=$B$29,SUMIF(Food!$C:$C,B$9&$B$29&$C$29,Food!$Z:$Z),0),"") -> 0 | C32: =IFERROR(IF($B$29=$B$29,SUMIF(Food!$C:$C,C$9&$B$29&$C$29,Food!$Z:$Z),0),"") -> 0 | D32: =IFERROR(IF($B$29=$B$29,SUMIF(Food!$C:$C,D$9&$B$29&$C$29,Food!$Z:$Z),0),"") -> 0 | E32: =IFERROR(IF($B$29=$B$29,SUMIF(Food!$C:$C,E$9&$B$29&$C$29,Food!$Z:$Z),0),"") -> 0 | F32: =IFERROR(IF($B$29=$B$29,SUMIF(Food!$C:$C,F$9&$B$29&$C$29,Food!$Z:$Z),0),"") -> 0 | G32: =IFERROR(IF($B$29=$B$29,SUMIF(Food!$C:$C,G$9&$B$29&$C$29,Food!$Z:$Z),0),"") -> 0
A33: Markup Food | B33: =IFERROR(IF($B$29=$B$29,SUMIF(Food!$C:$C,B$9&$B$29&$C$29,Food!$AB:$AB),0),"") -> 0 | C33: =IFERROR(IF($B$29=$B$29,SUMIF(Food!$C:$C,C$9&$B$29&$C$29,Food!$AB:$AB),0),"") -> 0 | D33: =IFERROR(IF($B$29=$B$29,SUMIF(Food!$C:$C,D$9&$B$29&$C$29,Food!$AB:$AB),0),"") -> 0 | E33: =IFERROR(IF($B$29=$B$29,SUMIF(Food!$C:$C,E$9&$B$29&$C$29,Food!$AB:$AB),0),"") -> 0 | F33: =IFERROR(IF($B$29=$B$29,SUMIF(Food!$C:$C,F$9&$B$29&$C$29,Food!$AB:$AB),0),"") -> 0 | G33: =IFERROR(IF($B$29=$B$29,SUMIF(Food!$C:$C,G$9&$B$29&$C$29,Food!$O:$O),0),"") -> 0
A34: Markup Labor | B34: =IFERROR(IF($B$29=$B$29,SUMIF(Food!$C:$C,B$9&$B$29&$C$29,Food!$AC:$AC),0),"") -> 0 | C34: =IFERROR(IF($B$29=$B$29,SUMIF(Food!$C:$C,C$9&$B$29&$C$29,Food!$AC:$AC),0),"") -> 0 | D34: =IFERROR(IF($B$29=$B$29,SUMIF(Food!$C:$C,D$9&$B$29&$C$29,Food!$AC:$AC),0),"") -> 0 | E34: =IFERROR(IF($B$29=$B$29,SUMIF(Food!$C:$C,E$9&$B$29&$C$29,Food!$AC:$AC),0),"") -> 0 | F34: =IFERROR(IF($B$29=$B$29,SUMIF(Food!$C:$C,F$9&$B$29&$C$29,Food!$AC:$AC),0),"") -> 0 | G34: =IFERROR(IF($B$29=$B$29,SUMIF(Food!$C:$C,G$9&$B$29&$C$29,Food!$P:$P),0),"") -> 0
A36: Per Pax Avg
A37: OVERHEAD | B37: ='P&L'!$K$30 -> 0 | C37: ='P&L'!$L$30 -> 0 | D37: ='P&L'!$M$30 -> 0 | E37: ='P&L'!$N$30 -> 0 | F37: ='P&L'!$O$30 -> 0 | G37: ='P&L'!$P$30 -> 0
A38: Food Cost (DM) | B38: =IFERROR(B31/B7," ") | C38: =IFERROR(C31/C7," ") -> 0 | D38: =IFERROR(D31/D7," ") -> 0 | E38: =IFERROR(E31/E7," ") -> 0 | F38: =IFERROR(F31/F7," ") | G38: =IFERROR(G31/G7," ") -> 0
A39: Wage Cost (DL) | B39: =IFERROR(B32/B7," ") | C39: =IFERROR(C32/C7," ") -> 0 | D39: =IFERROR(D32/D7," ") -> 0 | E39: =IFERROR(E32/E7," ") -> 0 | F39: =IFERROR(F32/F7," ") | G39: =IFERROR(G32/G7," ") -> 0
A40: Markup Food | B40: =IFERROR(B33/B8," ") | C40: =IFERROR(C33/C7," ") -> 0 | D40: =IFERROR(D33/D7," ") -> 0 | E40: =IFERROR(E33/E7," ") -> 0 | F40: =IFERROR(F33/F7," ") | G40: =IFERROR(G33/G7," ") -> 0
A41: Markup Labor | B41: =IFERROR(B34/B7," ") | C41: =IFERROR(C34/C7," ") -> 0 | D41: =IFERROR(D34/D7," ") -> 0 | E41: =IFERROR(E34/E7," ") -> 0 | F41: =IFERROR(F34/F7," ") | G41: =IFERROR(G34/G7," ") -> 0
A108: 388
A109: 787

Sheet Summary 2855
A2: Customer | G2: Flights Per week | H2: 0 | L2: AC type | M2: Cycle
E3: AC Type | F3: 738 | G3: Flights Per Month | H3: =H4/12 -> 0 | J3: Total Revenues | L3: 737 | M3: 1
E4: Load | F4: ='P&L'!R4 -> 0.8 | G4: Annual Flights | H4: =H2*52 -> 0 | J4: =H17*H4 -> 0
A5: Summary
A6: BNA | B6: FC | C6: BC | D6: PY | E6: EY | F6: TC | G6: CY | H6: Total | I6: Hnd
A7: FLIGHT CONFIG | B7: =+'FlightConfig '!B17 -> 0 | C7: =+'FlightConfig '!C17 -> 34 | D7: =+'FlightConfig '!D17 -> 48 | E7: =+'FlightConfig '!E17 -> 198 | F7: =+'FlightConfig '!F17 -> 0 | G7: =+'FlightConfig '!G17 -> 6 | H7: =SUM(B7:G7) -> 286
A8: Load Factor | B8: =ROUNDUP(B7*$F$4,0) -> 0 | C8: =ROUNDUP(C7*$F$4,0) -> 28 | D8: =ROUNDUP(D7*$F$4,0) -> 39 | E8: =ROUNDUP(E7*$F$4,0) -> 159 | F8: =ROUNDUP(F7*$F$4,0) -> 0 | G8: =ROUNDUP(G7*$F$4,0) -> 5 | H8: =SUM(B8:G8) -> 231
B9: FIRST CLASS | C9: BUSINESS CLASS | D9: PREMIUM ECONOMY CLASS | E9: ECONOMY CLASS | F9: TECH CREW CLASS | G9: cABIN CREW CLASS | H9: Per Flight | J9: Annual
A10: OVERHEAD | B10: =B37*B8 -> 0 | C10: =C37*C8 -> 0 | D10: =D37*D8 -> 0 | E10: =E37*E8 -> 0 | F10: =F37*F8 -> 0 | G10: =G37*G8 -> 0 | H10: =SUM(B10:G10) -> 0 | J10: =H10*$H$4 -> 0
A11: Food Cost (DM) | B11: =IFERROR(B38*B8,0) -> 0 | C11: =IFERROR(C38*$C$8,0) -> 0 | D11: =IFERROR(D38*$D$8,0) -> 0 | E11: =IFERROR(E38*$E$8,0) -> 0 | F11: =IFERROR(F38*$F$8,0) -> 0 | G11: =IFERROR(G38*G8,0) -> 0 | H11: =SUM(B11:G11) -> 0 | I11: =I12*45% -> 0 | J11: =H11*$H$4 -> 0
A12: Wage Cost (DL) | B12: =IFERROR(B39*B8,0) -> 0 | C12: =IFERROR(C39*$C$8,0) -> 0 | D12: =IFERROR(D39*$D$8,0) -> 0 | E12: =IFERROR(E39*$E$8,0) -> 0 | F12: =IFERROR(F39*$F$8,0) -> 0 | G12: =IFERROR(G39*G8,0) -> 0 | H12: =SUM(B12:G12) -> 0 | I12: =H11+H12 -> 0 | J12: =H12*$H$4 -> 0
A13: Food Mark up | B13: =IFERROR(B40*B8," ") | C13: =IFERROR(C40*$C$8,0) -> 0 | D13: =IFERROR(D40*$D$8,0) -> 0 | E13: =IFERROR(E40*$E$8,0) -> 0 | F13: =IFERROR(F40*$F$8,0) -> 0 | G13: 0 | H13: =SUM(B13:G13) -> 0 | J13: =H13*$H$4 -> 0
A14: Labor Mark up | B14: =IFERROR(B41*B8," ") | C14: =IFERROR(C41*$C$8,0) -> 0 | D14: =IFERROR(D41*$D$8,0) -> 0 | E14: =IFERROR(E41*$E$8,0) -> 0 | F14: =IFERROR(F41*$F$8,0) -> 0 | G14: 0 | H14: =SUM(B14:G14) -> 0 | J14: =H14*$H$4 -> 0 | L14: Direct Labour
A15: Handling Cost | B15: 0 | C15: 0 | D15: 0 | E15: =+B20 -> 0 | F15: 0 | G15: 0 | H15: =SUM(B15:G15) -> 0 | J15: =H15*$H$4 -> 0 | L15: =J12+J15 -> 0 | M15: 1
A16: Handling Mark up | B16: 0 | C16: 0 | D16: 0 | E16: =+C20 -> 0 | F16: 0 | G16: 0 | H16: =SUM(B16:G16) -> 0 | J16: =H16*$H$4 -> 0 | L16: =L15*M16 -> 0 | M16: 0.8
A17: Total Per Flight | B17: =SUM(B11:B16) -> 0 | C17: =SUM(C11:C16) -> 0 | D17: =SUM(D10:D16) -> 0 | E17: =SUM(E10:E16) -> 0 | F17: =SUM(F10:F16) -> 0 | G17: =SUM(G10:G16) -> 0 | H17: =SUM(H10:H16) -> 0 | J17: =H17*$H$4 -> 0 | L17: =L15*M17 -> 0 | M17: 0.2
B18: =B17 -> 0 | C18: =C17 -> 0 | D18: =D17 -> 0 | E18: =E17-E15-E16 -> 0 | F18: =F17 -> 0 | G18: =G17 -> 0 | I18: =E15+E16 -> 0
A19: Handling | B19: Cost | C19: Mark Up | D19: Price | I19: =E16 -> 0
A20: 738 Handling | B20: =Handling!C56 -> 0 | C20: =B20*'P&L'!$R$10 -> 0 | D20: =SUM(B20:C20) -> 0
A21: B777 Handling | B21: =Handling!#REF! -> #REF! | C21: =Handling!#REF! -> #REF! | D21: =Handling!#REF! -> #REF!
A22: A380 Handling | B22: =Handling!#REF! -> #REF! | C22: =Handling!#REF! -> #REF! | D22: =Handling!#REF! -> #REF!
A24: Avg Price Per Pax | B24: =IFERROR(((B11+B12+B13+B14)/B8),0) -> 0 | C24: =IFERROR(((C11+C12+C13+C14)/C8),0) -> 0 | D24: =IFERROR(((D10+D11+D12+D13+D14)/D8),0) -> 0 | E24: =IFERROR(((E10+E11+E12+E13+E14)/E8),0) -> 0 | F24: =IFERROR(((F10+F11+F12+F13+F14)/F8),0) -> 0 | G24: =IFERROR(((G10+G11+G12+G13+G14)/G8),0) -> 0
A25: Avg Mark up Per Pax | B25: =IFERROR(((B13+B14)/B8),0) -> 0 | C25: =IFERROR(((C13+C14)/C8),0) -> 0 | D25: =IFERROR(((D13+D14)/D8),0) -> 0 | E25: =IFERROR(((E13+E14)/E8),0) -> 0 | F25: =IFERROR(((F13+F14)/F8),0) -> 0 | G25: =IFERROR(((G13+G14)/G8),0) -> 0
A26: Over head Per Pax | B26: =IFERROR((B10/B8),0) -> 0 | C26: =IFERROR((C10/C8),0) -> 0 | D26: =IFERROR((D10/D8),0) -> 0 | E26: =IFERROR((E10/E8),0) -> 0 | F26: =IFERROR((F10/F8),0) -> 0 | G26: =IFERROR((G10/G8),0) -> 0
B28: CYCLE | C28: FLT
A29: Config | B29: ='P&L'!R5 -> 1 | C29: 2855
A30: OVERHEAD | B30: =B37*B8 -> 0 | C30: =C37*C8 -> 0 | D30: =D37*D8 -> 0 | E30: =E37*E8 -> 0 | F30: =F37*F8 -> 0 | G30: =G37*G8 -> 0
A31: Food Cost (DM) | B31: =IFERROR(IF($B$29=$B$29,SUMIF(Food!$C:$C,B$9&$B$29&$C$29,Food!$X:$X),0),"") -> 0 | C31: =IFERROR(IF($B$29=$B$29,SUMIF(Food!$C:$C,C$9&$B$29&$C$29,Food!$X:$X),0),"") -> 0 | D31: =IFERROR(IF($B$29=$B$29,SUMIF(Food!$C:$C,D$9&$B$29&$C$29,Food!$X:$X),0),"") -> 0 | E31: =IFERROR(IF($B$29=$B$29,SUMIF(Food!$C:$C,E$9&$B$29&$C$29,Food!$X:$X),0),"") -> 0 | F31: =IFERROR(IF($B$29=$B$29,SUMIF(Food!$C:$C,F$9&$B$29&$C$29,Food!$X:$X),0),"") -> 0 | G31: =IFERROR(IF($B$29=$B$29,SUMIF(Food!$C:$C,G$9&$B$29&$C$29,Food!$X:$X),0),"") -> 0
A32: Wage Cost (DL) | B32: =IFERROR(IF($B$29=$B$29,SUMIF(Food!$C:$C,B$9&$B$29&$C$29,Food!$Z:$Z),0),"") -> 0 | C32: =IFERROR(IF($B$29=$B$29,SUMIF(Food!$C:$C,C$9&$B$29&$C$29,Food!$Z:$Z),0),"") -> 0 | D32: =IFERROR(IF($B$29=$B$29,SUMIF(Food!$C:$C,D$9&$B$29&$C$29,Food!$Z:$Z),0),"") -> 0 | E32: =IFERROR(IF($B$29=$B$29,SUMIF(Food!$C:$C,E$9&$B$29&$C$29,Food!$Z:$Z),0),"") -> 0 | F32: =IFERROR(IF($B$29=$B$29,SUMIF(Food!$C:$C,F$9&$B$29&$C$29,Food!$Z:$Z),0),"") -> 0 | G32: =IFERROR(IF($B$29=$B$29,SUMIF(Food!$C:$C,G$9&$B$29&$C$29,Food!$Z:$Z),0),"") -> 0
A33: Markup Food | B33: =IFERROR(IF($B$29=$B$29,SUMIF(Food!$C:$C,B$9&$B$29&$C$29,Food!$AB:$AB),0),"") -> 0 | C33: =IFERROR(IF($B$29=$B$29,SUMIF(Food!$C:$C,C$9&$B$29&$C$29,Food!$AB:$AB),0),"") -> 0 | D33: =IFERROR(IF($B$29=$B$29,SUMIF(Food!$C:$C,D$9&$B$29&$C$29,Food!$AB:$AB),0),"") -> 0 | E33: =IFERROR(IF($B$29=$B$29,SUMIF(Food!$C:$C,E$9&$B$29&$C$29,Food!$AB:$AB),0),"") -> 0 | F33: =IFERROR(IF($B$29=$B$29,SUMIF(Food!$C:$C,F$9&$B$29&$C$29,Food!$AB:$AB),0),"") -> 0 | G33: =IFERROR(IF($B$29=$B$29,SUMIF(Food!$C:$C,G$9&$B$29&$C$29,Food!$O:$O),0),"") -> 0
A34: Markup Labor | B34: =IFERROR(IF($B$29=$B$29,SUMIF(Food!$C:$C,B$9&$B$29&$C$29,Food!$AC:$AC),0),"") -> 0 | C34: =IFERROR(IF($B$29=$B$29,SUMIF(Food!$C:$C,C$9&$B$29&$C$29,Food!$AC:$AC),0),"") -> 0 | D34: =IFERROR(IF($B$29=$B$29,SUMIF(Food!$C:$C,D$9&$B$29&$C$29,Food!$AC:$AC),0),"") -> 0 | E34: =IFERROR(IF($B$29=$B$29,SUMIF(Food!$C:$C,E$9&$B$29&$C$29,Food!$AC:$AC),0),"") -> 0 | F34: =IFERROR(IF($B$29=$B$29,SUMIF(Food!$C:$C,F$9&$B$29&$C$29,Food!$AC:$AC),0),"") -> 0 | G34: =IFERROR(IF($B$29=$B$29,SUMIF(Food!$C:$C,G$9&$B$29&$C$29,Food!$P:$P),0),"") -> 0
A36: Per Pax Avg
A37: OVERHEAD | B37: ='P&L'!$K$30 -> 0 | C37: ='P&L'!$L$30 -> 0 | D37: ='P&L'!$M$30 -> 0 | E37: ='P&L'!$N$30 -> 0 | F37: ='P&L'!$O$30 -> 0 | G37: ='P&L'!$P$30 -> 0
A38: Food Cost (DM) | B38: =IFERROR(B31/B7," ") | C38: =IFERROR(C31/C7," ") -> 0 | D38: =IFERROR(D31/D7," ") -> 0 | E38: =IFERROR(E31/E7," ") -> 0 | F38: =IFERROR(F31/F7," ") | G38: =IFERROR(G31/G7," ") -> 0
A39: Wage Cost (DL) | B39: =IFERROR(B32/B7," ") | C39: =IFERROR(C32/C7," ") -> 0 | D39: =IFERROR(D32/D7," ") -> 0 | E39: =IFERROR(E32/E7," ") -> 0 | F39: =IFERROR(F32/F7," ") | G39: =IFERROR(G32/G7," ") -> 0
A40: Markup Food | B40: =IFERROR(B33/B8," ") | C40: =IFERROR(C33/C7," ") -> 0 | D40: =IFERROR(D33/D7," ") -> 0 | E40: =IFERROR(E33/E7," ") -> 0 | F40: =IFERROR(F33/F7," ") | G40: =IFERROR(G33/G7," ") -> 0
A41: Markup Labor | B41: =IFERROR(B34/B7," ") | C41: =IFERROR(C34/C7," ") -> 0 | D41: =IFERROR(D34/D7," ") -> 0 | E41: =IFERROR(E34/E7," ") -> 0 | F41: =IFERROR(F34/F7," ") | G41: =IFERROR(G34/G7," ") -> 0
A108: 388
A109: 787

Sheet Summary FLT104
A2: Customer | G2: Flights Per week | H2: 7 | L2: AC type | M2: Cycle
E3: AC Type | F3: 738 | G3: Flights Per Month | H3: =H4/12 -> 30.333333 | J3: Total Revenues | L3: 737 | M3: 1
E4: Load | F4: ='P&L'!R4 -> 0.8 | G4: Annual Flights | H4: =H2*52 -> 364 | J4: =H17*H4 -> 1760549.8
A5: Summary
A6: BNA | B6: FC | C6: BC | D6: PY | E6: EY | F6: TC | G6: CY | H6: Total | I6: Hnd
A7: FLIGHT CONFIG | B7: =+'FlightConfig '!B17 -> 0 | C7: =+'FlightConfig '!C17 -> 34 | D7: =+'FlightConfig '!D17 -> 48 | E7: =+'FlightConfig '!E17 -> 198 | F7: =+'FlightConfig '!F17 -> 0 | G7: =+'FlightConfig '!G17 -> 6 | H7: =SUM(B7:G7) -> 286
A8: Load Factor | B8: =ROUNDUP(B7*$F$4,0) -> 0 | C8: =ROUNDUP(C7*$F$4,0) -> 28 | D8: =ROUNDUP(D7*$F$4,0) -> 39 | E8: =ROUNDUP(E7*$F$4,0) -> 159 | F8: =ROUNDUP(F7*$F$4,0) -> 0 | G8: =ROUNDUP(G7*$F$4,0) -> 5 | H8: =SUM(B8:G8) -> 231
B9: FIRST CLASS | C9: BUSINESS CLASS | D9: PREMIUM ECONOMY CLASS | E9: ECONOMY CLASS | F9: TECH CREW CLASS | G9: CABIN CREW CLASS | H9: Per Flight | J9: Annual
A10: OVERHEAD | B10: =B37*B8 -> 0 | C10: =C37*C8 -> 0 | D10: =D37*D8 -> 0 | E10: =E37*E8 -> 0 | F10: =F37*F8 -> 0 | G10: =G37*G8 -> 0 | H10: =SUM(B10:G10) -> 0 | J10: =H10*$H$4 -> 0
A11: Food Cost (DM) | B11: =IFERROR(B38*B8,0) -> 0 | C11: =IFERROR(C38*$C$8,0) -> 471.1864 | D11: =IFERROR(D38*$D$8,0) -> 303.66527 | E11: =IFERROR(E38*$E$8,0) -> 879.39891 | F11: =IFERROR(F38*$F$8,0) -> 0 | G11: =IFERROR(G38*G8,0) -> 62.0575 | H11: =SUM(B11:G11) -> 1716.3081 | I11: =I12*45% -> 1167.5628 | J11: =H11*$H$4 -> 624736.14
A12: Wage Cost (DL) | B12: =IFERROR(B39*B8,0) -> 0 | C12: =IFERROR(C39*$C$8,0) -> 200.95271 | D12: =IFERROR(D39*$D$8,0) -> 214.1425 | E12: =IFERROR(E39*$E$8,0) -> 441.79515 | F12: =IFERROR(F39*$F$8,0) -> 0 | G12: =IFERROR(G39*G8,0) -> 21.3856 | H12: =SUM(B12:G12) -> 878.27596 | I12: =H11+H12 -> 2594.584 | J12: =H12*$H$4 -> 319692.45
A13: Food Mark up | B13: =IFERROR(B40*B9,0) -> 0 | C13: =IFERROR(C40*$C$8,0) -> 103.66101 | D13: =IFERROR(D40*$D$8,0) -> 66.806359 | E13: =IFERROR(E40*$E$8,0) -> 193.46776 | F13: =IFERROR(F40*$F$8,0) -> 0 | G13: =IFERROR(G40*$G$8,0) -> 13.65265 | H13: =SUM(B13:G13) -> 377.58778 | J13: =H13*$H$4 -> 137441.95
A14: Labor Mark up | B14: =IFERROR(B41*B10,0) -> 0 | C14: =IFERROR(C41*$C$8,0) -> 40.190541 | D14: =IFERROR(D41*$D$8,0) -> 42.8285 | E14: =IFERROR(E41*$E$8,0) -> 88.35903 | F14: =IFERROR(F41*$F$8,0) -> 0 | G14: =IFERROR(G41*$G$8,0) -> 4.27712 | H14: =SUM(B14:G14) -> 175.65519 | J14: =H14*$H$4 -> 63938.49 | L14: Direct Labour
A15: Handling Cost | B15: 0 | C15: 0 | D15: 0 | E15: =+B20 -> 1494.556 | F15: 0 | G15: =IFERROR(G42*$G$8,0) -> 0 | H15: =SUM(B15:G15) -> 1494.556 | J15: =H15*$H$4 -> 544018.38 | L15: =J12+J15 -> 863710.83 | M15: 1
A16: Handling Mark up | B16: 0 | C16: 0 | D16: 0 | E16: =+C20 -> 194.29228 | F16: 0 | G16: =IFERROR(G43*$G$8,0) -> 0 | H16: =SUM(B16:G16) -> 194.29228 | J16: =H16*$H$4 -> 70722.39 | L16: =L15*M16 -> 690968.67 | M16: 0.8
A17: Total Per Flight | B17: =SUM(B11:B16) -> 0 | C17: =SUM(C11:C16) -> 815.99065 | D17: =SUM(D10:D16) -> 627.44263 | E17: =SUM(E10:E16) -> 3291.8691 | F17: =SUM(F10:F16) -> 0 | G17: =SUM(G10:G16) -> 101.37287 | H17: =SUM(H10:H16) -> 4836.6753 | J17: =H17*$H$4 -> 1760549.8 | L17: =L15*M17 -> 172742.17 | M17: 0.2
B18: =B17 -> 0 | C18: =C17 -> 815.99065 | D18: =D17 -> 627.44263 | E18: =E17-E15-E16 -> 1603.0209 | F18: =F17 -> 0 | G18: =G17 -> 101.37287 | I18: =E15+E16 -> 1688.8483
A19: Handling | B19: Cost | C19: Mark Up | D19: Price | I19: =E16 -> 194.29228 | J19: =H11+H12+H15 -> 4089.14
A20: 738 Handling | B20: =Handling!C83+Handling!S39+Handling!S45+Handling!V53+Handling!AD39 -> 1494.556 | C20: =B20*'P&L'!$R$10 -> 194.29228 | D20: =SUM(B20:C20) -> 1688.8483 | J20: =H13+H14+H16 -> 747.53525
A21: B777 Handling | B21: =Handling!#REF! -> #REF! | C21: =Handling!#REF! -> #REF! | D21: =Handling!#REF! -> #REF!
A22: A380 Handling | B22: =Handling!#REF! -> #REF! | C22: =Handling!#REF! -> #REF! | D22: =Handling!#REF! -> #REF!
A24: Avg Price Per Pax | B24: =IFERROR(((B11+B12+B13+B14)/B8),0) -> 0 | C24: =IFERROR(((C11+C12+C13+C14)/C8),0) -> 29.142523 | D24: =IFERROR(((D10+D11+D12+D13+D14)/D8),0) -> 16.088272 | E24: =IFERROR(((E10+E11+E12+E13+E14)/E8),0) -> 10.081892 | F24: =IFERROR(((F10+F11+F12+F13+F14)/F8),0) -> 0 | G24: =IFERROR(((G10+G11+G12+G13+G14)/G8),0) -> 20.274574
A25: Avg Mark up Per Pax | B25: =IFERROR(((B13+B14)/B8),0) -> 0 | C25: =IFERROR(((C13+C14)/C8),0) -> 5.1375553 | D25: =IFERROR(((D13+D14)/D8),0) -> 2.8111502 | E25: =IFERROR(((E13+E14)/E8),0) -> 1.7724955 | F25: =IFERROR(((F13+F14)/F8),0) -> 0 | G25: =IFERROR(((G13+G14)/G8),0) -> 3.585954
A26: Over head Per Pax | B26: =IFERROR((B10/B8),0) -> 0 | C26: =IFERROR((C10/C8),0) -> 0 | D26: =IFERROR((D10/D8),0) -> 0 | E26: =IFERROR((E10/E8),0) -> 0 | F26: =IFERROR((F10/F8),0) -> 0 | G26: =IFERROR((G10/G8),0) -> 0
B28: CYCLE | C28: FLT
A29: Config | B29: ='P&L'!R5 -> 1 | C29: 104
A30: OVERHEAD | B30: =B37*B8 -> 0 | C30: =C37*C8 -> 0 | D30: =D37*D8 -> 0 | E30: =E37*E8 -> 0 | F30: =F37*F8 -> 0 | G30: =G37*G8 -> 0
A31: Food Cost (DM) | B31: =IFERROR(IF($B$29=$B$29,SUMIF(Food!$C:$C,B$9&$B$29&$C$29,Food!$X:$X),0),"")+IFERROR(IF($B$29=$B$29,SUMIF(Food!$C:$C,B$9&$B$29&$C$29,Food!$W:$W),0),"") -> 0 | C31: =IFERROR(IF($B$29=$B$29,SUMIF(Food!$C:$C,C$9&$B$29&$C$29,Food!$X:$X),0),"") -> 572.15491 | D31: =IFERROR(IF($B$29=$B$29,SUMIF(Food!$C:$C,D$9&$B$29&$C$29,Food!$X:$X),0),"") -> 373.74187 | E31: =IFERROR(IF($B$29=$B$29,SUMIF(Food!$C:$C,E$9&$B$29&$C$29,Food!$X:$X),0),"") -> 1095.1005 | F31: =IFERROR(IF($B$29=$B$29,SUMIF(Food!$C:$C,F$9&$B$29&$C$29,Food!$X:$X),0),"") -> 0 | G31: =IFERROR(IF($B$29=$B$29,SUMIF(Food!$C:$C,G$9&$B$29&$C$29,Food!$X:$X),0),"") -> 74.469
A32: Wage Cost (DL) | B32: =IFERROR(IF($B$29=$B$29,SUMIF(Food!$C:$C,B$9&$B$29&$C$29,Food!$Z:$Z),0),"") -> 0 | C32: =IFERROR(IF($B$29=$B$29,SUMIF(Food!$C:$C,C$9&$B$29&$C$29,Food!$Z:$Z),0),"") -> 244.014 | D32: =IFERROR(IF($B$29=$B$29,SUMIF(Food!$C:$C,D$9&$B$29&$C$29,Food!$Z:$Z),0),"") -> 263.56 | E32: =IFERROR(IF($B$29=$B$29,SUMIF(Food!$C:$C,E$9&$B$29&$C$29,Food!$Z:$Z),0),"") -> 550.16 | F32: =IFERROR(IF($B$29=$B$29,SUMIF(Food!$C:$C,F$9&$B$29&$C$29,Food!$Z:$Z),0),"") -> 0 | G32: =IFERROR(IF($B$29=$B$29,SUMIF(Food!$C:$C,G$9&$B$29&$C$29,Food!$Z:$Z),0),"") -> 25.66272
A33: Markup Food | B33: =IFERROR(IF($B$29=$B$29,SUMIF(Food!$C:$C,B$9&$B$29&$C$29,Food!$AB:$AB),0),"") -> 0 | C33: =IFERROR(IF($B$29=$B$29,SUMIF(Food!$C:$C,C$9&$B$29&$C$29,Food!$AB:$AB),0),"") -> 125.87408 | D33: =IFERROR(IF($B$29=$B$29,SUMIF(Food!$C:$C,D$9&$B$29&$C$29,Food!$AB:$AB),0),"") -> 82.223211 | E33: =IFERROR(IF($B$29=$B$29,SUMIF(Food!$C:$C,E$9&$B$29&$C$29,Food!$AB:$AB),0),"") -> 240.92212 | F33: =IFERROR(IF($B$29=$B$29,SUMIF(Food!$C:$C,F$9&$B$29&$C$29,Food!$AB:$AB),0),"") -> 0 | G33: =IFERROR(IF($B$29=$B$29,SUMIF(Food!$C:$C,G$9&$B$29&$C$29,Food!$AB:$AB),0),"") -> 16.38318
A34: Markup Labor | B34: =IFERROR(IF($B$29=$B$29,SUMIF(Food!$C:$C,B$9&$B$29&$C$29,Food!$AC:$AC),0),"") -> 0 | C34: =IFERROR(IF($B$29=$B$29,SUMIF(Food!$C:$C,C$9&$B$29&$C$29,Food!$AC:$AC),0),"") -> 48.8028 | D34: =IFERROR(IF($B$29=$B$29,SUMIF(Food!$C:$C,D$9&$B$29&$C$29,Food!$AC:$AC),0),"") -> 52.712 | E34: =IFERROR(IF($B$29=$B$29,SUMIF(Food!$C:$C,E$9&$B$29&$C$29,Food!$AC:$AC),0),"") -> 110.032 | F34: =IFERROR(IF($B$29=$B$29,SUMIF(Food!$C:$C,F$9&$B$29&$C$29,Food!$AC:$AC),0),"") -> 0 | G34: =IFERROR(IF($B$29=$B$29,SUMIF(Food!$C:$C,G$9&$B$29&$C$29,Food!$AC:$AC),0),"") -> 5.132544
A36: Per Pax Avg
A37: OVERHEAD | B37: ='P&L'!$K$30 -> 0 | C37: ='P&L'!$L$30 -> 0 | D37: ='P&L'!$M$30 -> 0 | E37: ='P&L'!$N$30 -> 0 | F37: ='P&L'!$O$30 -> 0 | G37: ='P&L'!$P$30 -> 0
A38: Food Cost (DM) | B38: =IFERROR(B31/B7," ") | C38: =IFERROR(C31/C7," ") -> 16.828086 | D38: =IFERROR(D31/D7," ") -> 7.7862889 | E38: =IFERROR(E31/E7," ") -> 5.5308108 | F38: =IFERROR(F31/F7," ") | G38: =IFERROR(G31/G7," ") -> 12.4115
A39: Wage Cost (DL) | B39: =IFERROR(B32/B7," ") | C39: =IFERROR(C32/C7," ") -> 7.1768824 | D39: =IFERROR(D32/D7," ") -> 5.4908333 | E39: =IFERROR(E32/E7," ") -> 2.7785859 | F39: =IFERROR(F32/F7," ") | G39: =IFERROR(G32/G7," ") -> 4.27712
A40: Markup Food | B40: =IFERROR(B33/B8," ") | C40: =IFERROR(C33/C7," ") -> 3.7021788 | D40: =IFERROR(D33/D7," ") -> 1.7129836 | E40: =IFERROR(E33/E7," ") -> 1.2167784 | F40: =IFERROR(F33/F7," ") | G40: =IFERROR(G33/G7," ") -> 2.73053
A41: Markup Labor | B41: =IFERROR(B34/B7," ") | C41: =IFERROR(C34/C7," ") -> 1.4353765 | D41: =IFERROR(D34/D7," ") -> 1.0981667 | E41: =IFERROR(E34/E7," ") -> 0.55571717 | F41: =IFERROR(F34/F7," ") | G41: =IFERROR(G34/G7," ") -> 0.855424
A108: 388
A109: 787

Sheet Summary FLT110
A2: Customer | G2: Flights Per week | H2: 7 | L2: AC type | M2: Cycle
E3: AC Type | F3: 738 | G3: Flights Per Month | H3: =H4/12 -> 30.333333 | J3: Total Revenues | L3: 330 | M3: 1
E4: Load | F4: ='P&L'!R4 -> 0.8 | G4: Annual Flights | H4: =H2*52 -> 364 | J4: =H17*H4 -> 1705025.7
A5: Summary
A6: BNA | B6: FC | C6: BC | D6: PY | E6: EY | F6: TC | G6: CY | H6: Total | I6: Hnd
A7: FLIGHT CONFIG | B7: =+'FlightConfig '!B17 -> 0 | C7: =+'FlightConfig '!C23 -> 30 | D7: =+'FlightConfig '!D23 -> 44 | E7: =+'FlightConfig '!E23 -> 184 | F7: =+'FlightConfig '!F23 -> 0 | G7: =+'FlightConfig '!G23 -> 6 | H7: =+'FlightConfig '!H23 -> 264
A8: Load Factor | B8: =ROUNDUP(B7*$F$4,0) -> 0 | C8: =ROUNDUP(C7*$F$4,0) -> 24 | D8: =ROUNDUP(D7*$F$4,0) -> 36 | E8: =ROUNDUP(E7*$F$4,0) -> 148 | F8: =ROUNDUP(F7*$F$4,0) -> 0 | G8: =ROUNDUP(G7*$F$4,0) -> 5 | H8: =SUM(B8:G8) -> 213
B9: FIRST CLASS | C9: BUSINESS CLASS | D9: PREMIUM ECONOMY CLASS | E9: ECONOMY CLASS | F9: TECH CREW CLASS | G9: cABIN CREW CLASS | H9: Per Flight | J9: Annual
A10: OVERHEAD | B10: =B37*B8 -> 0 | C10: =C37*C8 -> 0 | D10: =D37*D8 -> 0 | E10: =E37*E8 -> 0 | F10: =F37*F8 -> 0 | G10: =G37*G8 -> 0 | H10: =SUM(B10:G10) -> 0 | J10: =H10*$H$4 -> 0
A11: Food Cost (DM) | B11: =IFERROR(B38*B8,0) -> 0 | C11: =IFERROR(C38*$C$8,0) -> 441.69589 | D11: =IFERROR(D38*$D$8,0) -> 332.7888 | E11: =IFERROR(E38*$E$8,0) -> 861.00973 | F11: =IFERROR(F38*$F$8,0) -> 0 | G11: =IFERROR(G38*$G$8,0) -> 62.0575 | H11: =SUM(B11:G11) -> 1697.5519 | J11: =H11*$H$4 -> 617908.9
A12: Wage Cost (DL) | B12: =IFERROR(B39*B8,0) -> 0 | C12: =IFERROR(C39*$C$8,0) -> 178.6512 | D12: =IFERROR(D39*$D$8,0) -> 223.56 | E12: =IFERROR(E39*$E$8,0) -> 441.04 | F12: =IFERROR(F39*$F$8,0) -> 0 | G12: =IFERROR(G39*$G$8,0) -> 21.3856 | H12: =SUM(B12:G12) -> 864.6368 | J12: =H12*$H$4 -> 314727.8
A13: Food Mark up | B13: =IFERROR(B40*B9,0) -> 0 | C13: =IFERROR(C40*$C$8,0) -> 97.173096 | D13: =IFERROR(D40*$D$8,0) -> 73.213536 | E13: =IFERROR(E40*$E$8,0) -> 189.42214 | F13: =IFERROR(F40*$F$8,0) -> 0 | G13: =IFERROR(G40*$G$8,0) -> 13.65265 | H13: =SUM(B13:G13) -> 373.46142 | J13: =H13*$H$4 -> 135939.96
A14: Labor Mark up | B14: =IFERROR(B41*B10,0) -> 0 | C14: =IFERROR(C41*$C$8,0) -> 35.73024 | D14: =IFERROR(D41*$D$8,0) -> 44.712 | E14: =IFERROR(E41*$E$8,0) -> 88.208 | F14: =IFERROR(F41*$F$8,0) -> 0 | G14: =IFERROR(G41*$G$8,0) -> 4.27712 | H14: =SUM(B14:G14) -> 172.92736 | J14: =H14*$H$4 -> 62945.559 | L14: Direct Labour
A15: Handling Cost | B15: 0 | C15: 0 | D15: 0 | E15: =+B20 -> 1394.3 | F15: 0 | G15: 0 | H15: =SUM(B15:G15) -> 1394.3 | J15: =H15*$H$4 -> 507525.2 | L15: =J12+J15 -> 822253 | M15: 1
A16: Handling Mark up | B16: 0 | C16: 0 | D16: 0 | E16: =+C20 -> 181.259 | F16: 0 | G16: 0 | H16: =SUM(B16:G16) -> 181.259 | J16: =H16*$H$4 -> 65978.276 | L16: =L15*M16 -> 657802.4 | M16: 0.8
A17: Total Per Flight | B17: =SUM(B11:B16) -> 0 | C17: =SUM(C11:C16) -> 753.25043 | D17: =SUM(D10:D16) -> 674.27434 | E17: =SUM(E10:E16) -> 3155.2389 | F17: =SUM(F10:F16) -> 0 | G17: =SUM(G10:G16) -> 101.37287 | H17: =SUM(H10:H16) -> 4684.1365 | J17: =H17*$H$4 -> 1705025.7 | L17: =L15*M17 -> 164450.6 | M17: 0.2
B18: =B17 -> 0 | C18: =C17 -> 753.25043 | D18: =D17 -> 674.27434 | E18: =E17-E15-E16 -> 1579.6799 | F18: =F17 -> 0 | G18: =G17 -> 101.37287 | I18: =E15+E16 -> 1575.559
A19: Handling | B19: Cost | C19: Mark Up | D19: Price | I19: =E16 -> 181.259 | J19: =H11+H12+H15 -> 3956.4887
A20: 738 Handling | B20: =Handling!C83+Handling!R39+Handling!R45+Handling!V52+Handling!AC39 -> 1394.3 | C20: =B20*'P&L'!$R$10 -> 181.259 | D20: =SUM(B20:C20) -> 1575.559 | J20: =H13+H14+H16 -> 727.64778
A21: B777 Handling | B21: =Handling!#REF! -> #REF! | C21: =Handling!#REF! -> #REF! | D21: =Handling!#REF! -> #REF!
A22: A380 Handling | B22: =Handling!#REF! -> #REF! | C22: =Handling!#REF! -> #REF! | D22: =Handling!#REF! -> #REF!
A24: Avg Price Per Pax | B24: =IFERROR(((B11+B12+B13+B14)/B8),0) -> 0 | C24: =IFERROR(((C11+C12+C13+C14)/C8),0) -> 31.385434 | D24: =IFERROR(((D10+D11+D12+D13+D14)/D8),0) -> 18.729843 | E24: =IFERROR(((E10+E11+E12+E13+E14)/E8),0) -> 10.673513 | F24: =IFERROR(((F10+F11+F12+F13+F14)/F8),0) -> 0 | G24: =IFERROR(((G10+G11+G12+G13+G14)/G8),0) -> 20.274574
A25: Avg Mark up Per Pax | B25: =IFERROR(((B13+B14)/B8),0) -> 0 | C25: =IFERROR(((C13+C14)/C8),0) -> 5.537639 | D25: =IFERROR(((D13+D14)/D8),0) -> 3.2757093 | E25: =IFERROR(((E13+E14)/E8),0) -> 1.8758793 | F25: =IFERROR(((F13+F14)/F8),0) -> 0 | G25: =IFERROR(((G13+G14)/G8),0) -> 3.585954
A26: Over head Per Pax | B26: =IFERROR((B10/B8),0) -> 0 | C26: =IFERROR((C10/C8),0) -> 0 | D26: =IFERROR((D10/D8),0) -> 0 | E26: =IFERROR((E10/E8),0) -> 0 | F26: =IFERROR((F10/F8),0) -> 0 | G26: =IFERROR((G10/G8),0) -> 0
B28: CYCLE | C28: FLT
A29: Config | B29: ='P&L'!R5 -> 1 | C29: 110
A30: OVERHEAD | B30: =B37*B8 -> 0 | C30: =C37*C8 -> 0 | D30: =D37*D8 -> 0 | E30: =E37*E8 -> 0 | F30: =F37*F8 -> 0 | G30: =G37*G8 -> 0
A31: Food Cost (DM) | B31: =IFERROR(IF($B$29=$B$29,SUMIF(Food!$C:$C,B$9&$B$29&$C$29,Food!$X:$X),0),"")+IFERROR(IF($B$29=$B$29,SUMIF(Food!$C:$C,B$9&$B$29&$C$29,Food!$W:$W),0),"") -> 0 | C31: =IFERROR(IF($B$29=$B$29,SUMIF(Food!$C:$C,C$9&$B$29&$C$29,Food!$X:$X),0),"") -> 552.11986 | D31: =IFERROR(IF($B$29=$B$29,SUMIF(Food!$C:$C,D$9&$B$29&$C$29,Food!$X:$X),0),"") -> 406.74187 | E31: =IFERROR(IF($B$29=$B$29,SUMIF(Food!$C:$C,E$9&$B$29&$C$29,Food!$X:$X),0),"") -> 1070.4445 | F31: =IFERROR(IF($B$29=$B$29,SUMIF(Food!$C:$C,F$9&$B$29&$C$29,Food!$X:$X),0),"") -> 0 | G31: =IFERROR(IF($B$29=$B$29,SUMIF(Food!$C:$C,G$9&$B$29&$C$29,Food!$X:$X),0),"") -> 74.469 | H31: NM cost added
A32: Wage Cost (DL) | B32: =IFERROR(IF($B$29=$B$29,SUMIF(Food!$C:$C,B$9&$B$29&$C$29,Food!$Z:$Z),0),"") -> 0 | C32: =IFERROR(IF($B$29=$B$29,SUMIF(Food!$C:$C,C$9&$B$29&$C$29,Food!$Z:$Z),0),"") -> 223.314 | D32: =IFERROR(IF($B$29=$B$29,SUMIF(Food!$C:$C,D$9&$B$29&$C$29,Food!$Z:$Z),0),"") -> 273.24 | E32: =IFERROR(IF($B$29=$B$29,SUMIF(Food!$C:$C,E$9&$B$29&$C$29,Food!$Z:$Z),0),"") -> 548.32 | F32: =IFERROR(IF($B$29=$B$29,SUMIF(Food!$C:$C,F$9&$B$29&$C$29,Food!$Z:$Z),0),"") -> 0 | G32: =IFERROR(IF($B$29=$B$29,SUMIF(Food!$C:$C,G$9&$B$29&$C$29,Food!$Z:$Z),0),"") -> 25.66272
A33: Markup Food | B33: =IFERROR(IF($B$29=$B$29,SUMIF(Food!$C:$C,B$9&$B$29&$C$29,Food!$AB:$AB),0),"") -> 0 | C33: =IFERROR(IF($B$29=$B$29,SUMIF(Food!$C:$C,C$9&$B$29&$C$29,Food!$AB:$AB),0),"") -> 121.46637 | D33: =IFERROR(IF($B$29=$B$29,SUMIF(Food!$C:$C,D$9&$B$29&$C$29,Food!$AB:$AB),0),"") -> 89.483211 | E33: =IFERROR(IF($B$29=$B$29,SUMIF(Food!$C:$C,E$9&$B$29&$C$29,Food!$AB:$AB),0),"") -> 235.4978 | F33: =IFERROR(IF($B$29=$B$29,SUMIF(Food!$C:$C,F$9&$B$29&$C$29,Food!$AB:$AB),0),"") -> 0 | G33: =IFERROR(IF($B$29=$B$29,SUMIF(Food!$C:$C,G$9&$B$29&$C$29,Food!$AB:$AB),0),"") -> 16.38318
A34: Markup Labor | B34: =IFERROR(IF($B$29=$B$29,SUMIF(Food!$C:$C,B$9&$B$29&$C$29,Food!$AC:$AC),0),"") -> 0 | C34: =IFERROR(IF($B$29=$B$29,SUMIF(Food!$C:$C,C$9&$B$29&$C$29,Food!$AC:$AC),0),"") -> 44.6628 | D34: =IFERROR(IF($B$29=$B$29,SUMIF(Food!$C:$C,D$9&$B$29&$C$29,Food!$AC:$AC),0),"") -> 54.648 | E34: =IFERROR(IF($B$29=$B$29,SUMIF(Food!$C:$C,E$9&$B$29&$C$29,Food!$AC:$AC),0),"") -> 109.664 | F34: =IFERROR(IF($B$29=$B$29,SUMIF(Food!$C:$C,F$9&$B$29&$C$29,Food!$AC:$AC),0),"") -> 0 | G34: =IFERROR(IF($B$29=$B$29,SUMIF(Food!$C:$C,G$9&$B$29&$C$29,Food!$AC:$AC),0),"") -> 5.132544
A36: Per Pax Avg
A37: OVERHEAD | B37: ='P&L'!$K$30 -> 0 | C37: ='P&L'!$L$30 -> 0 | D37: ='P&L'!$M$30 -> 0 | E37: ='P&L'!$N$30 -> 0 | F37: ='P&L'!$O$30 -> 0 | G37: ='P&L'!$P$30 -> 0
A38: Food Cost (DM) | B38: =IFERROR(B31/B7," ") | C38: =IFERROR(C31/C7," ") -> 18.403995 | D38: =IFERROR(D31/D7," ") -> 9.2441333 | E38: =IFERROR(E31/E7," ") -> 5.8176333 | F38: =IFERROR(F31/F7," ") | G38: =IFERROR(G31/G7," ") -> 12.4115
A39: Wage Cost (DL) | B39: =IFERROR(B32/B7," ") | C39: =IFERROR(C32/C7," ") -> 7.4438 | D39: =IFERROR(D32/D7," ") -> 6.21 | E39: =IFERROR(E32/E7," ") -> 2.98 | F39: =IFERROR(F32/F7," ") | G39: =IFERROR(G32/G7," ") -> 4.27712
A40: Markup Food | B40: =IFERROR(B33/B8," ") | C40: =IFERROR(C33/C7," ") -> 4.048879 | D40: =IFERROR(D33/D7," ") -> 2.0337093 | E40: =IFERROR(E33/E7," ") -> 1.2798793 | F40: =IFERROR(F33/F7," ") | G40: =IFERROR(G33/G7," ") -> 2.73053
A41: Markup Labor | B41: =IFERROR(B34/B7," ") | C41: =IFERROR(C34/C7," ") -> 1.48876 | D41: =IFERROR(D34/D7," ") -> 1.242 | E41: =IFERROR(E34/E7," ") -> 0.596 | F41: =IFERROR(F34/F7," ") | G41: =IFERROR(G34/G7," ") -> 0.855424
A108: 388
A109: 787

Sheet Summary 2037
A2: Customer | G2: Flights Per week | H2: 0 | L2: AC type | M2: Cycle
E3: AC Type | F3: 738 | G3: Flights Per Month | H3: =H4/12 -> 0 | J3: Total Revenues | L3: 737 | M3: 1
E4: Load | F4: ='P&L'!R4 -> 0.8 | G4: Annual Flights | H4: =H2*52 -> 0 | J4: =H17*H4 -> #REF!
A5: Summary
A6: BNA | B6: FC | C6: BC | D6: PY | E6: EY | F6: TC | G6: CY | H6: Total | I6: Hnd
A7: FLIGHT CONFIG | B7: =+'FlightConfig '!B17 -> 0 | C7: =+'FlightConfig '!C17 -> 34 | D7: =+'FlightConfig '!D17 -> 48 | E7: =+'FlightConfig '!E17 -> 198 | F7: =+'FlightConfig '!F17 -> 0 | G7: =+'FlightConfig '!G17 -> 6 | H7: =SUM(B7:G7) -> 286
A8: Load Factor | B8: =ROUNDUP(B7*$F$4,0) -> 0 | C8: =ROUNDUP(C7*$F$4,0) -> 28 | D8: =ROUNDUP(D7*$F$4,0) -> 39 | E8: =ROUNDUP(E7*$F$4,0) -> 159 | F8: =ROUNDUP(F7*$F$4,0) -> 0 | G8: =ROUNDUP(G7*$F$4,0) -> 5 | H8: =SUM(B8:G8) -> 231
B9: FIRST CLASS | C9: BUSINESS CLASS | D9: PREMIUM ECONOMY CLASS | E9: ECONOMY CLASS | F9: TECH CREW CLASS | G9: cABIN CREW CLASS | H9: Per Flight | J9: Annual
A10: OVERHEAD | B10: =B37*B8 -> 0 | C10: =C37*C8 -> 0 | D10: =D37*D8 -> 0 | E10: =E37*E8 -> 0 | F10: =F37*F8 -> 0 | G10: =G37*G8 -> 0 | H10: =SUM(B10:G10) -> 0 | J10: =H10*$H$4 -> 0
A11: Food Cost (DM) | B11: =IFERROR(B38*B8,0) -> 0 | C11: =IFERROR(C38*$C$8,0) -> 0 | D11: =IFERROR(D38*$D$8,0) -> 0 | E11: =IFERROR(E38*$E$8,0) -> 0 | F11: =IFERROR(F38*$F$8,0) -> 0 | G11: =IFERROR(G38*G8,0) -> 0 | H11: =SUM(B11:G11) -> 0 | I11: =I12*45% -> 0 | J11: =H11*$H$4 -> 0
A12: Wage Cost (DL) | B12: =IFERROR(B39*B8,0) -> 0 | C12: =IFERROR(C39*$C$8,0) -> 0 | D12: =IFERROR(D39*$D$8,0) -> 0 | E12: =IFERROR(E39*$E$8,0) -> 0 | F12: =IFERROR(F39*$F$8,0) -> 0 | G12: =IFERROR(G39*G8,0) -> 0 | H12: =SUM(B12:G12) -> 0 | I12: =H11+H12 -> 0 | J12: =H12*$H$4 -> 0
A13: Food Mark up | B13: =IFERROR(B40*B8," ") | C13: =IFERROR(C40*$C$8,0) -> 0 | D13: =IFERROR(D40*$D$8,0) -> 0 | E13: =IFERROR(E40*$E$8,0) -> 0 | F13: =IFERROR(F40*$F$8,0) -> 0 | G13: 0 | H13: =SUM(B13:G13) -> 0 | J13: =H13*$H$4 -> 0
A14: Labor Mark up | B14: =IFERROR(B41*B8," ") | C14: =IFERROR(C41*$C$8,0) -> 0 | D14: =IFERROR(D41*$D$8,0) -> 0 | E14: =IFERROR(E41*$E$8,0) -> 0 | F14: =IFERROR(F41*$F$8,0) -> 0 | G14: 0 | H14: =SUM(B14:G14) -> 0 | J14: =H14*$H$4 -> 0 | L14: Direct Labour
A15: Handling Cost | B15: 0 | C15: 0 | D15: 0 | E15: =+B20 -> #REF! | F15: 0 | G15: 0 | H15: =SUM(B15:G15) -> #REF! | J15: =H15*$H$4 -> #REF! | L15: =J12+J15 -> #REF! | M15: 1
A16: Handling Mark up | B16: 0 | C16: 0 | D16: 0 | E16: =+C20 -> #REF! | F16: 0 | G16: 0 | H16: =SUM(B16:G16) -> #REF! | J16: =H16*$H$4 -> #REF! | L16: =L15*M16 -> #REF! | M16: 0.8
A17: Total Per Flight | B17: =SUM(B11:B16) -> 0 | C17: =SUM(C11:C16) -> 0 | D17: =SUM(D10:D16) -> 0 | E17: =SUM(E10:E16) -> #REF! | F17: =SUM(F10:F16) -> 0 | G17: =SUM(G10:G16) -> 0 | H17: =SUM(H10:H16) -> #REF! | J17: =H17*$H$4 -> #REF! | L17: =L15*M17 -> #REF! | M17: 0.2
B18: =B17 -> 0 | C18: =C17 -> 0 | D18: =D17 -> 0 | E18: =E17-E15-E16 -> #REF! | F18: =F17 -> 0 | G18: =G17 -> 0 | I18: =E15+E16 -> #REF!
A19: Handling | B19: Cost | C19: Mark Up | D19: Price | I19: =E16 -> #REF!
A20: 738 Handling | B20: =Handling!C22 -> #REF! | C20: =B20*'P&L'!$R$10 -> #REF! | D20: =SUM(B20:C20) -> #REF!
A21: B777 Handling | B21: =Handling!#REF! -> #REF! | C21: =Handling!#REF! -> #REF! | D21: =Handling!#REF! -> #REF!
A22: A380 Handling | B22: =Handling!#REF! -> #REF! | C22: =Handling!#REF! -> #REF! | D22: =Handling!#REF! -> #REF!
A24: Avg Price Per Pax | B24: =IFERROR(((B11+B12+B13+B14)/B8),0) -> 0 | C24: =IFERROR(((C11+C12+C13+C14)/C8),0) -> 0 | D24: =IFERROR(((D10+D11+D12+D13+D14)/D8),0) -> 0 | E24: =IFERROR(((E10+E11+E12+E13+E14)/E8),0) -> 0 | F24: =IFERROR(((F10+F11+F12+F13+F14)/F8),0) -> 0 | G24: =IFERROR(((G10+G11+G12+G13+G14)/G8),0) -> 0
A25: Avg Mark up Per Pax | B25: =IFERROR(((B13+B14)/B8),0) -> 0 | C25: =IFERROR(((C13+C14)/C8),0) -> 0 | D25: =IFERROR(((D13+D14)/D8),0) -> 0 | E25: =IFERROR(((E13+E14)/E8),0) -> 0 | F25: =IFERROR(((F13+F14)/F8),0) -> 0 | G25: =IFERROR(((G13+G14)/G8),0) -> 0
A26: Over head Per Pax | B26: =IFERROR((B10/B8),0) -> 0 | C26: =IFERROR((C10/C8),0) -> 0 | D26: =IFERROR((D10/D8),0) -> 0 | E26: =IFERROR((E10/E8),0) -> 0 | F26: =IFERROR((F10/F8),0) -> 0 | G26: =IFERROR((G10/G8),0) -> 0
B28: CYCLE | C28: FLT
A29: Config | B29: ='P&L'!R5 -> 1 | C29: 2037
A30: OVERHEAD | B30: =B37*B8 -> 0 | C30: =C37*C8 -> 0 | D30: =D37*D8 -> 0 | E30: =E37*E8 -> 0 | F30: =F37*F8 -> 0 | G30: =G37*G8 -> 0
A31: Food Cost (DM) | B31: =IFERROR(IF($B$29=$B$29,SUMIF(Food!$C:$C,B$9&$B$29&$C$29,Food!$X:$X),0),"") -> 0 | C31: =IFERROR(IF($B$29=$B$29,SUMIF(Food!$C:$C,C$9&$B$29&$C$29,Food!$X:$X),0),"") -> 0 | D31: =IFERROR(IF($B$29=$B$29,SUMIF(Food!$C:$C,D$9&$B$29&$C$29,Food!$X:$X),0),"") -> 0 | E31: =IFERROR(IF($B$29=$B$29,SUMIF(Food!$C:$C,E$9&$B$29&$C$29,Food!$X:$X),0),"") -> 0 | F31: =IFERROR(IF($B$29=$B$29,SUMIF(Food!$C:$C,F$9&$B$29&$C$29,Food!$X:$X),0),"") -> 0 | G31: =IFERROR(IF($B$29=$B$29,SUMIF(Food!$C:$C,G$9&$B$29&$C$29,Food!$X:$X),0),"") -> 0
A32: Wage Cost (DL) | B32: =IFERROR(IF($B$29=$B$29,SUMIF(Food!$C:$C,B$9&$B$29&$C$29,Food!$Z:$Z),0),"") -> 0 | C32: =IFERROR(IF($B$29=$B$29,SUMIF(Food!$C:$C,C$9&$B$29&$C$29,Food!$Z:$Z),0),"") -> 0 | D32: =IFERROR(IF($B$29=$B$29,SUMIF(Food!$C:$C,D$9&$B$29&$C$29,Food!$Z:$Z),0),"") -> 0 | E32: =IFERROR(IF($B$29=$B$29,SUMIF(Food!$C:$C,E$9&$B$29&$C$29,Food!$Z:$Z),0),"") -> 0 | F32: =IFERROR(IF($B$29=$B$29,SUMIF(Food!$C:$C,F$9&$B$29&$C$29,Food!$Z:$Z),0),"") -> 0 | G32: =IFERROR(IF($B$29=$B$29,SUMIF(Food!$C:$C,G$9&$B$29&$C$29,Food!$Z:$Z),0),"") -> 0
A33: Markup Food | B33: =IFERROR(IF($B$29=$B$29,SUMIF(Food!$C:$C,B$9&$B$29&$C$29,Food!$AB:$AB),0),"") -> 0 | C33: =IFERROR(IF($B$29=$B$29,SUMIF(Food!$C:$C,C$9&$B$29&$C$29,Food!$AB:$AB),0),"") -> 0 | D33: =IFERROR(IF($B$29=$B$29,SUMIF(Food!$C:$C,D$9&$B$29&$C$29,Food!$AB:$AB),0),"") -> 0 | E33: =IFERROR(IF($B$29=$B$29,SUMIF(Food!$C:$C,E$9&$B$29&$C$29,Food!$AB:$AB),0),"") -> 0 | F33: =IFERROR(IF($B$29=$B$29,SUMIF(Food!$C:$C,F$9&$B$29&$C$29,Food!$AB:$AB),0),"") -> 0 | G33: =IFERROR(IF($B$29=$B$29,SUMIF(Food!$C:$C,G$9&$B$29&$C$29,Food!$O:$O),0),"") -> 0
A34: Markup Labor | B34: =IFERROR(IF($B$29=$B$29,SUMIF(Food!$C:$C,B$9&$B$29&$C$29,Food!$AC:$AC),0),"") -> 0 | C34: =IFERROR(IF($B$29=$B$29,SUMIF(Food!$C:$C,C$9&$B$29&$C$29,Food!$AC:$AC),0),"") -> 0 | D34: =IFERROR(IF($B$29=$B$29,SUMIF(Food!$C:$C,D$9&$B$29&$C$29,Food!$AC:$AC),0),"") -> 0 | E34: =IFERROR(IF($B$29=$B$29,SUMIF(Food!$C:$C,E$9&$B$29&$C$29,Food!$AC:$AC),0),"") -> 0 | F34: =IFERROR(IF($B$29=$B$29,SUMIF(Food!$C:$C,F$9&$B$29&$C$29,Food!$AC:$AC),0),"") -> 0 | G34: =IFERROR(IF($B$29=$B$29,SUMIF(Food!$C:$C,G$9&$B$29&$C$29,Food!$P:$P),0),"") -> 0
A36: Per Pax Avg
A37: OVERHEAD | B37: ='P&L'!$K$30 -> 0 | C37: ='P&L'!$L$30 -> 0 | D37: ='P&L'!$M$30 -> 0 | E37: ='P&L'!$N$30 -> 0 | F37: ='P&L'!$O$30 -> 0 | G37: ='P&L'!$P$30 -> 0
A38: Food Cost (DM) | B38: =IFERROR(B31/B7," ") | C38: =IFERROR(C31/C7," ") -> 0 | D38: =IFERROR(D31/D7," ") -> 0 | E38: =IFERROR(E31/E7," ") -> 0 | F38: =IFERROR(F31/F7," ") | G38: =IFERROR(G31/G7," ") -> 0
A39: Wage Cost (DL) | B39: =IFERROR(B32/B7," ") | C39: =IFERROR(C32/C7," ") -> 0 | D39: =IFERROR(D32/D7," ") -> 0 | E39: =IFERROR(E32/E7," ") -> 0 | F39: =IFERROR(F32/F7," ") | G39: =IFERROR(G32/G7," ") -> 0
A40: Markup Food | B40: =IFERROR(B33/B8," ") | C40: =IFERROR(C33/C7," ") -> 0 | D40: =IFERROR(D33/D7," ") -> 0 | E40: =IFERROR(E33/E7," ") -> 0 | F40: =IFERROR(F33/F7," ") | G40: =IFERROR(G33/G7," ") -> 0
A41: Markup Labor | B41: =IFERROR(B34/B7," ") | C41: =IFERROR(C34/C7," ") -> 0 | D41: =IFERROR(D34/D7," ") -> 0 | E41: =IFERROR(E34/E7," ") -> 0 | F41: =IFERROR(F34/F7," ") | G41: =IFERROR(G34/G7," ") -> 0
A108: 388
A109: 787

Sheet Summary 2817
A2: Customer | G2: Flights Per week | H2: 0 | L2: AC type | M2: Cycle
E3: AC Type | F3: 738 | G3: Flights Per Month | H3: =H4/12 -> 0 | J3: Total Revenues | L3: 737 | M3: 1
E4: Load | F4: ='P&L'!R4 -> 0.8 | G4: Annual Flights | H4: =H2*52 -> 0 | J4: =H17*H4 -> #REF!
A5: Summary
A6: BNA | B6: FC | C6: BC | D6: PY | E6: EY | F6: TC | G6: CY | H6: Total | I6: Hnd
A7: FLIGHT CONFIG | B7: =+'FlightConfig '!B17 -> 0 | C7: =+'FlightConfig '!C17 -> 34 | D7: =+'FlightConfig '!D17 -> 48 | E7: =+'FlightConfig '!E17 -> 198 | F7: =+'FlightConfig '!F17 -> 0 | G7: =+'FlightConfig '!G17 -> 6 | H7: =SUM(B7:G7) -> 286
A8: Load Factor | B8: =ROUNDUP(B7*$F$4,0) -> 0 | C8: =ROUNDUP(C7*$F$4,0) -> 28 | D8: =ROUNDUP(D7*$F$4,0) -> 39 | E8: =ROUNDUP(E7*$F$4,0) -> 159 | F8: =ROUNDUP(F7*$F$4,0) -> 0 | G8: =ROUNDUP(G7*$F$4,0) -> 5 | H8: =SUM(B8:G8) -> 231
B9: FIRST CLASS | C9: BUSINESS CLASS | D9: PREMIUM ECONOMY CLASS | E9: ECONOMY CLASS | F9: TECH CREW CLASS | G9: cABIN CREW CLASS | H9: Per Flight | J9: Annual
A10: OVERHEAD | B10: =B37*B8 -> 0 | C10: =C37*C8 -> 0 | D10: =D37*D8 -> 0 | E10: =E37*E8 -> 0 | F10: =F37*F8 -> 0 | G10: =G37*G8 -> 0 | H10: =SUM(B10:G10) -> 0 | J10: =H10*$H$4 -> 0
A11: Food Cost (DM) | B11: =IFERROR(B38*B8,0) -> 0 | C11: =IFERROR(C38*$C$8,0) -> 0 | D11: =IFERROR(D38*$D$8,0) -> 0 | E11: =IFERROR(E38*$E$8,0) -> 0 | F11: =IFERROR(F38*$F$8,0) -> 0 | G11: =IFERROR(G38*G8,0) -> 0 | H11: =SUM(B11:G11) -> 0 | I11: =I12*45% -> 0 | J11: =H11*$H$4 -> 0
A12: Wage Cost (DL) | B12: =IFERROR(B39*B8,0) -> 0 | C12: =IFERROR(C39*$C$8,0) -> 0 | D12: =IFERROR(D39*$D$8,0) -> 0 | E12: =IFERROR(E39*$E$8,0) -> 0 | F12: =IFERROR(F39*$F$8,0) -> 0 | G12: =IFERROR(G39*G8,0) -> 0 | H12: =SUM(B12:G12) -> 0 | I12: =H11+H12 -> 0 | J12: =H12*$H$4 -> 0
A13: Food Mark up | B13: =IFERROR(B40*B8," ") | C13: =IFERROR(C40*$C$8,0) -> 0 | D13: =IFERROR(D40*$D$8,0) -> 0 | E13: =IFERROR(E40*$E$8,0) -> 0 | F13: =IFERROR(F40*$F$8,0) -> 0 | G13: 0 | H13: =SUM(B13:G13) -> 0 | J13: =H13*$H$4 -> 0
A14: Labor Mark up | B14: =IFERROR(B41*B8," ") | C14: =IFERROR(C41*$C$8,0) -> 0 | D14: =IFERROR(D41*$D$8,0) -> 0 | E14: =IFERROR(E41*$E$8,0) -> 0 | F14: =IFERROR(F41*$F$8,0) -> 0 | G14: 0 | H14: =SUM(B14:G14) -> 0 | J14: =H14*$H$4 -> 0 | L14: Direct Labour
A15: Handling Cost | B15: 0 | C15: 0 | D15: 0 | E15: =+B20 -> #REF! | F15: 0 | G15: 0 | H15: =SUM(B15:G15) -> #REF! | J15: =H15*$H$4 -> #REF! | L15: =J12+J15 -> #REF! | M15: 1
A16: Handling Mark up | B16: 0 | C16: 0 | D16: 0 | E16: =+C20 -> #REF! | F16: 0 | G16: 0 | H16: =SUM(B16:G16) -> #REF! | J16: =H16*$H$4 -> #REF! | L16: =L15*M16 -> #REF! | M16: 0.8
A17: Total Per Flight | B17: =SUM(B11:B16) -> 0 | C17: =SUM(C11:C16) -> 0 | D17: =SUM(D10:D16) -> 0 | E17: =SUM(E10:E16) -> #REF! | F17: =SUM(F10:F16) -> 0 | G17: =SUM(G10:G16) -> 0 | H17: =SUM(H10:H16) -> #REF! | J17: =H17*$H$4 -> #REF! | L17: =L15*M17 -> #REF! | M17: 0.2
B18: =B17 -> 0 | C18: =C17 -> 0 | D18: =D17 -> 0 | E18: =E17-E15-E16 -> #REF! | F18: =F17 -> 0 | G18: =G17 -> 0 | I18: =E15+E16 -> #REF!
A19: Handling | B19: Cost | C19: Mark Up | D19: Price | I19: =E16 -> #REF!
A20: 738 Handling | B20: =Handling!C22 -> #REF! | C20: =B20*'P&L'!$R$10 -> #REF! | D20: =SUM(B20:C20) -> #REF!
A21: B777 Handling | B21: =Handling!#REF! -> #REF! | C21: =Handling!#REF! -> #REF! | D21: =Handling!#REF! -> #REF!
A22: A380 Handling | B22: =Handling!#REF! -> #REF! | C22: =Handling!#REF! -> #REF! | D22: =Handling!#REF! -> #REF!
A24: Avg Price Per Pax | B24: =IFERROR(((B11+B12+B13+B14)/B8),0) -> 0 | C24: =IFERROR(((C11+C12+C13+C14)/C8),0) -> 0 | D24: =IFERROR(((D10+D11+D12+D13+D14)/D8),0) -> 0 | E24: =IFERROR(((E10+E11+E12+E13+E14)/E8),0) -> 0 | F24: =IFERROR(((F10+F11+F12+F13+F14)/F8),0) -> 0 | G24: =IFERROR(((G10+G11+G12+G13+G14)/G8),0) -> 0
A25: Avg Mark up Per Pax | B25: =IFERROR(((B13+B14)/B8),0) -> 0 | C25: =IFERROR(((C13+C14)/C8),0) -> 0 | D25: =IFERROR(((D13+D14)/D8),0) -> 0 | E25: =IFERROR(((E13+E14)/E8),0) -> 0 | F25: =IFERROR(((F13+F14)/F8),0) -> 0 | G25: =IFERROR(((G13+G14)/G8),0) -> 0
A26: Over head Per Pax | B26: =IFERROR((B10/B8),0) -> 0 | C26: =IFERROR((C10/C8),0) -> 0 | D26: =IFERROR((D10/D8),0) -> 0 | E26: =IFERROR((E10/E8),0) -> 0 | F26: =IFERROR((F10/F8),0) -> 0 | G26: =IFERROR((G10/G8),0) -> 0
B28: CYCLE | C28: FLT
A29: Config | B29: ='P&L'!R5 -> 1 | C29: 2817
A30: OVERHEAD | B30: =B37*B8 -> 0 | C30: =C37*C8 -> 0 | D30: =D37*D8 -> 0 | E30: =E37*E8 -> 0 | F30: =F37*F8 -> 0 | G30: =G37*G8 -> 0
A31: Food Cost (DM) | B31: =IFERROR(IF($B$29=$B$29,SUMIF(Food!$C:$C,B$9&$B$29&$C$29,Food!$X:$X),0),"") -> 0 | C31: =IFERROR(IF($B$29=$B$29,SUMIF(Food!$C:$C,C$9&$B$29&$C$29,Food!$X:$X),0),"") -> 0 | D31: =IFERROR(IF($B$29=$B$29,SUMIF(Food!$C:$C,D$9&$B$29&$C$29,Food!$X:$X),0),"") -> 0 | E31: =IFERROR(IF($B$29=$B$29,SUMIF(Food!$C:$C,E$9&$B$29&$C$29,Food!$X:$X),0),"") -> 0 | F31: =IFERROR(IF($B$29=$B$29,SUMIF(Food!$C:$C,F$9&$B$29&$C$29,Food!$X:$X),0),"") -> 0 | G31: =IFERROR(IF($B$29=$B$29,SUMIF(Food!$C:$C,G$9&$B$29&$C$29,Food!$X:$X),0),"") -> 0
A32: Wage Cost (DL) | B32: =IFERROR(IF($B$29=$B$29,SUMIF(Food!$C:$C,B$9&$B$29&$C$29,Food!$Z:$Z),0),"") -> 0 | C32: =IFERROR(IF($B$29=$B$29,SUMIF(Food!$C:$C,C$9&$B$29&$C$29,Food!$Z:$Z),0),"") -> 0 | D32: =IFERROR(IF($B$29=$B$29,SUMIF(Food!$C:$C,D$9&$B$29&$C$29,Food!$Z:$Z),0),"") -> 0 | E32: =IFERROR(IF($B$29=$B$29,SUMIF(Food!$C:$C,E$9&$B$29&$C$29,Food!$Z:$Z),0),"") -> 0 | F32: =IFERROR(IF($B$29=$B$29,SUMIF(Food!$C:$C,F$9&$B$29&$C$29,Food!$Z:$Z),0),"") -> 0 | G32: =IFERROR(IF($B$29=$B$29,SUMIF(Food!$C:$C,G$9&$B$29&$C$29,Food!$Z:$Z),0),"") -> 0
A33: Markup Food | B33: =IFERROR(IF($B$29=$B$29,SUMIF(Food!$C:$C,B$9&$B$29&$C$29,Food!$AB:$AB),0),"") -> 0 | C33: =IFERROR(IF($B$29=$B$29,SUMIF(Food!$C:$C,C$9&$B$29&$C$29,Food!$AB:$AB),0),"") -> 0 | D33: =IFERROR(IF($B$29=$B$29,SUMIF(Food!$C:$C,D$9&$B$29&$C$29,Food!$AB:$AB),0),"") -> 0 | E33: =IFERROR(IF($B$29=$B$29,SUMIF(Food!$C:$C,E$9&$B$29&$C$29,Food!$AB:$AB),0),"") -> 0 | F33: =IFERROR(IF($B$29=$B$29,SUMIF(Food!$C:$C,F$9&$B$29&$C$29,Food!$AB:$AB),0),"") -> 0 | G33: =IFERROR(IF($B$29=$B$29,SUMIF(Food!$C:$C,G$9&$B$29&$C$29,Food!$O:$O),0),"") -> 0
A34: Markup Labor | B34: =IFERROR(IF($B$29=$B$29,SUMIF(Food!$C:$C,B$9&$B$29&$C$29,Food!$AC:$AC),0),"") -> 0 | C34: =IFERROR(IF($B$29=$B$29,SUMIF(Food!$C:$C,C$9&$B$29&$C$29,Food!$AC:$AC),0),"") -> 0 | D34: =IFERROR(IF($B$29=$B$29,SUMIF(Food!$C:$C,D$9&$B$29&$C$29,Food!$AC:$AC),0),"") -> 0 | E34: =IFERROR(IF($B$29=$B$29,SUMIF(Food!$C:$C,E$9&$B$29&$C$29,Food!$AC:$AC),0),"") -> 0 | F34: =IFERROR(IF($B$29=$B$29,SUMIF(Food!$C:$C,F$9&$B$29&$C$29,Food!$AC:$AC),0),"") -> 0 | G34: =IFERROR(IF($B$29=$B$29,SUMIF(Food!$C:$C,G$9&$B$29&$C$29,Food!$P:$P),0),"") -> 0
A36: Per Pax Avg
A37: OVERHEAD | B37: ='P&L'!$K$30 -> 0 | C37: ='P&L'!$L$30 -> 0 | D37: ='P&L'!$M$30 -> 0 | E37: ='P&L'!$N$30 -> 0 | F37: ='P&L'!$O$30 -> 0 | G37: ='P&L'!$P$30 -> 0
A38: Food Cost (DM) | B38: =IFERROR(B31/B7," ") | C38: =IFERROR(C31/C7," ") -> 0 | D38: =IFERROR(D31/D7," ") -> 0 | E38: =IFERROR(E31/E7," ") -> 0 | F38: =IFERROR(F31/F7," ") | G38: =IFERROR(G31/G7," ") -> 0
A39: Wage Cost (DL) | B39: =IFERROR(B32/B7," ") | C39: =IFERROR(C32/C7," ") -> 0 | D39: =IFERROR(D32/D7," ") -> 0 | E39: =IFERROR(E32/E7," ") -> 0 | F39: =IFERROR(F32/F7," ") | G39: =IFERROR(G32/G7," ") -> 0
A40: Markup Food | B40: =IFERROR(B33/B8," ") | C40: =IFERROR(C33/C7," ") -> 0 | D40: =IFERROR(D33/D7," ") -> 0 | E40: =IFERROR(E33/E7," ") -> 0 | F40: =IFERROR(F33/F7," ") | G40: =IFERROR(G33/G7," ") -> 0
A41: Markup Labor | B41: =IFERROR(B34/B7," ") | C41: =IFERROR(C34/C7," ") -> 0 | D41: =IFERROR(D34/D7," ") -> 0 | E41: =IFERROR(E34/E7," ") -> 0 | F41: =IFERROR(F34/F7," ") | G41: =IFERROR(G34/G7," ") -> 0
A108: 388
A109: 787

Sheet Handling
A1: HANDLING CALCULATOR
B2: ALL AC TYPE
A3: STATION | B3: BNA | D3: Aircraft type | E3: ='FlightConfig '!B1 -> 350
A4: AC TYPE | B4: =+E3 -> 350 | C4: Long Hual with Food | D4: BNA | E4: FC | F4: BC | G4: EU | N4: CY | O4: Total
A5: # OF DAYS OPERATING | B5: =+'FlightConfig '!K2 -> 0 | D5: FLIGHT CONFIG | E5: ='FlightConfig '!B3 -> 0 | F5: ='FlightConfig '!C3 -> 34 | G5: ='FlightConfig '!D3 -> 48 | N5: ='FlightConfig '!G3+'FlightConfig '!F11 -> 7 | O5: =SUM(E5:N5) -> 89
A7: LABOR
A8: POSITION | B8: No. of SHIFTS | C8: HOURS | D8: SHIFTS/WK | E8: ANNUAL HOURS | F8: RATE | G8: EMP COST | N8: ANNUAL | O8: PER FLIGHT
A9: PACKER/QC | B9: 1 | C9: 1 | D9: =$B$5*B9 -> 0 | E9: =C9*D9*52 -> 0 | F9: 18 | G9: =F9*#REF! -> #REF! | N9: =E9*#REF! -> #REF! | O9: =(B9*#REF!)*C9 -> #REF! | Q9: EMD
A10: DISHWASHER | B10: 2 | C10: 2 | D10: =$B$5*B10 -> 0 | E10: =C10*D10*52 -> 0 | F10: 17 | G10: =F10*#REF! -> #REF! | N10: =E10*#REF! -> #REF! | O10: =(B10*#REF!)*C10 -> #REF! | Q10: Van Charge
A11: Ramp Coordinator | B11: 1 | C11: 2 | D11: =$B$5*B11 -> 0 | E11: =C11*D11*52 -> 0 | F11: 18 | G11: =F11*#REF! -> #REF! | N11: =E11*#REF! -> #REF! | O11: =(B11*#REF!)*C11 -> #REF! | Q11: Labor | R11: Tuck | T11: total | U11: Selling price
A12: INVENTORY CLERK | B12: 1 | C12: 0.5 | D12: =$B$5*B12 -> 0 | E12: =C12*D12*52 -> 0 | F12: 19 | G12: =F12*#REF! -> #REF! | N12: =E12*#REF! -> #REF! | O12: =(B12*#REF!)*C12 -> #REF! | Q12: =#REF!/2 -> #REF! | R12: 12 | T12: =Q12+R12 -> #REF! | U12: =T12+#REF! -> #REF!
A13: DRIVER | B13: 1 | C13: 2 | D13: =$B$5*B13 -> 0 | E13: =C13*D13*52 -> 0 | F13: 22 | G13: =F13*#REF! -> #REF! | N13: =E13*#REF! -> #REF! | O13: =(B13*#REF!)*C13 -> #REF!
A14: Total | N14: =SUM(N9:N13) -> #REF! | O14: =SUM(O9:O13) -> #REF!
A17: TRUCK COSTS | B17: No. of TRUCKS | C17: OP HOURS | D17: TTL OP HRS | E17: DEP./DAY | F17: DEP/HR APPLIED | G17: DEP $ | N17: MAIN/FEES/DAY | P17: MAIN COST | Q17: TOTAL COST | T17: FUEL COST CALCULATOR
A18: A380 TRUCKS | B18: 0 | C18: 0 | D18: =B18*C18 -> 0 | E18: =500000/10/365 -> 136.9863 | F18: =24/3 -> 8 | G18: =(E18/24)*F18*$B18 -> 0 | N18: =8000/365 -> 21.917808 | P18: =(N18/24)*$G18*$C18 -> 0 | Q18: =G18+#REF!+P18 -> #REF! | T18: ROUND TRIP MILES
A19: NARROWBODY TRUCKS | B19: 1 | C19: 2 | D19: =B19*C19 -> 2 | E19: =100000/365 -> 273.9726 | F19: 1 | G19: =E19*F19/'[1]P&L'!$P$2 -> 7.2098053 | N19: =5000/365 -> 13.69863 | P19: =(N19/24)*$F19*$B19 -> 0.57077626 | Q19: =G19+#REF!+P19 -> #REF! | T19: IDLE MILES
T20: TTL MILES
T21: MPG
A22: TOTAL HANDLING COST | C22: =SUM(O14,Q18,Q19) -> #REF! | T22: $/GAL
A23: MARK-UP | B23: =+'P&L'!$R$10 -> 0.13 | C23: =C22*B23 -> #REF! | E23: long hual | F23: short hual | T23: FUEL $
A24: TOTAL HANDLING PRICE | C24: =C22+C23 -> #REF! | D24: Turnaround | E24: 544.68493 | F24: 399.93493
A28: ASSUMPTIONS
A29: One coordinator
A30: Two trucks
A31: Two helpers
A36: WASHUP | O36: EQUIPMENT PACKING | U36: TRANSPORT & HANDLING | AB36: INTERNATIONAL TRASH
A37: Category | C37: Aircraft | O37: Packing Category | P37: Total Man Minutes per Aircraft | Q37: Price per MM | R37: ATL Price | U37: ATL | AB37: ATL
C38: A330-300 | D38: A330-900 | E38: A350-1000 | F38: A350-1000B | G38: B787-900 | O38: China / Glassware (inc cutlery) | S38: ='P&L'!$R$10 -> 0.13 | U38: Activity | V38: A330-300 | W38: A330-900 | X38: A350-1000 | Y38: A350-1000B | Z38: B787-900 | AB38: Aircraft type | AC38: Total Cost ($) | AD38: ='P&L'!$R$10 -> 0.13
O39: A330-300 | P39: 335 | Q39: 0.4 | R39: 134 | S39: =R39*(1+$S$38) -> 151.42 | U39: Turnaround (Strip and Load) | AB39: A330-300 | AC39: 300 | AD39: =AC39*(1+$S$38) -> 339
A40: Total factors - All flights | O40: A330-900 | P40: 335 | Q40: 0.4 | R40: 134 | S40: =R40*(1+$S$38) -> 151.42 | U40: Driver Man Minutes | V40: 480 | W40: 480 | X40: 560 | Y40: 560 | Z40: 480 | AA40: =V40/60 -> 8 | AB40: A330-900 | AC40: 300 | AD40: =AC40*(1+$S$38) -> 339
A41: J-Class Equipment | C41: Quantities | I41: MM | J41: MM | K41: MM | L41: MM | M41: MM | O41: A350-1000 | P41: 455 | Q41: 0.4 | R41: 182 | S41: =R41*(1+$S$38) -> 205.66 | U41: Price per Man Minutes | V41: 0.55 | W41: 0.55 | X41: 0.55 | Y41: 0.55 | Z41: 0.55 | AB41: A350-1000 | AC41: 350 | AD41: =AC41*(1+$S$38) -> 395.5
A42: Crockery | C42: 496 | D42: 480 | E42: 648 | F42: 340 | G42: 485 | H42: 0.3 | I42: =C42*$H$42 -> 148.8 | J42: =D42*$H$42 -> 144 | K42: =E42*$H$42 -> 194.4 | L42: =F42*$H$42 -> 102 | M42: =G42*$H$42 -> 145.5 | O42: A350-1000B | P42: 395 | Q42: 0.4 | R42: 158 | S42: =R42*(1+$S$38) -> 178.54 | U42: Driver Cost | V42: =V40*V41 -> 264 | W42: =W40*W41 -> 264 | X42: =X40*X41 -> 308 | Y42: =Y40*Y41 -> 308 | Z42: =Z40*Z41 -> 264 | AB42: A350-1000B | AC42: 350 | AD42: =AC42*(1+$S$38) -> 395.5
A43: Glassware | C43: 276 | D43: 284 | E43: 380 | F43: 326 | G43: 302 | H43: 1 | I43: =C43*$H$43 -> 276 | J43: =D43*$H$43 -> 284 | K43: =E43*$H$43 -> 380 | L43: =F43*$H$43 -> 326 | M43: =G43*$H$43 -> 302 | O43: B787-900 | P43: 345 | Q43: 0.4 | R43: 138 | S43: =R43*(1+$S$38) -> 155.94 | U43: Flt Co-ord Man Minutes | V43: 0 | W43: 0 | X43: 0 | Y43: 0 | Z43: 0 | AB43: B787-900 | AC43: 300 | AD43: =AC43*(1+$S$38) -> 339
A44: Cutlery* | C44: 414 | D44: 420 | E44: 492 | F44: 258 | G44: 414 | H44: 0.75 | I44: =C44*$H$44 -> 310.5 | J44: =D44*$H$44 -> 315 | K44: =E44*$H$44 -> 369 | L44: =F44*$H$44 -> 193.5 | M44: =G44*$H$44 -> 310.5 | O44: WY Bar alcohol packing | S44: ='P&L'!$R$10 -> 0.13 | U44: Price per Man Minutes | V44: 0 | W44: 0 | X44: 0 | Y44: 0 | Z44: 0
A45: Tray 1/1 | C45: 60 | D45: 60 | E45: 82 | F45: 34 | G45: 59 | H45: 0.3 | I45: =C45*$H$45 -> 18 | J45: =D45*$H$45 -> 18 | K45: =E45*$H$45 -> 24.6 | L45: =F45*$H$45 -> 10.2 | M45: =G45*$H$45 -> 17.7 | O45: A330-300 | P45: 150 | Q45: 0.4 | R45: 60 | S45: =R45*(1+$S$38) -> 67.8 | U45: Flt Co-ord Cost | V45: 0 | W45: 0 | X45: 0 | Y45: 0 | Z45: 0
A46: Sundries Items | C46: 0 | D46: 0 | E46: 0 | F46: 0 | G46: 0 | I46: =C46*$H$46 -> 0 | J46: =D46*$H$46 -> 0 | K46: =E46*$H$46 -> 0 | L46: =F46*$H$46 -> 0 | M46: =G46*$H$46 -> 0 | O46: A330-900 | P46: 150 | Q46: 0.4 | R46: 60 | S46: =R46*(1+$S$38) -> 67.8 | U46: Dispatch Man Minutes | V46: 30 | W46: 30 | X46: 30 | Y46: 30 | Z46: 30
A47: Total Volume of Washing per Aircraft | C47: 1246 | D47: 1244 | E47: 1602 | F47: 958 | G47: 1260 | I47: =SUM(I42:I46) -> 753.3 | J47: =SUM(J42:J46) -> 761 | K47: =SUM(K42:K46) -> 968 | L47: =SUM(L42:L46) -> 631.7 | M47: =SUM(M42:M46) -> 775.7 | O47: A350-1000 | P47: 200 | Q47: 0.4 | R47: 80 | S47: =R47*(1+$S$38) -> 90.4 | U47: Price per Man Minutes | V47: 0.44 | W47: 0.44 | X47: 0.44 | Y47: 0.44 | Z47: 0.44
A48: Total Man Minutes per Aircraft | C48: =I47 -> 753.3 | D48: =J47 -> 761 | E48: =K47 -> 968 | F48: =L47 -> 631.7 | G48: =M47 -> 775.7 | O48: A350-1000B | P48: 250 | Q48: 0.4 | R48: 100 | S48: =R48*(1+$S$38) -> 113 | U48: Dispatch Cost | V48: =V46*V47 -> 13.2 | W48: =W46*W47 -> 13.2 | X48: =X46*X47 -> 13.2 | Y48: =Y46*Y47 -> 13.2 | Z48: =Z46*Z47 -> 13.2
A49: Price per Man Minute | C49: 0.4 | D49: 0.4 | E49: 0.4 | F49: 0.4 | G49: 0.4 | O49: B787-900 | P49: 150 | Q49: 0.4 | R49: 60 | S49: =R49*(1+$S$38) -> 67.8 | U49: [Add resource as appropriate] | V49: 0 | W49: 0 | X49: 0 | Y49: 0 | Z49: 0
A50: Cost per Flight | C50: =C48*C49 -> 301.32 | D50: =D48*D49 -> 304.4 | E50: =E48*E49 -> 387.2 | F50: =F48*F49 -> 252.68 | G50: =G48*G49 -> 310.28 | O50: WY Bar packing | P50: 150 | Q50: 0.4 | R50: 60 | S50: =R50*(1+$S$38) -> 67.8 | U50: [Add resource labour rate as appropriate] | V50: 0 | W50: 0 | X50: 0 | Y50: 0 | Z50: 0
A51: W-Class Equipment | C51: Quantities | I51: MM | J51: MM | K51: MM | L51: MM | M51: MM | U51: Cost | V51: 0 | W51: 0 | X51: 0 | Y51: 0 | Z51: 0
A52: Crockery | C52: 374 | D52: 363 | E52: 444 | F52: 416 | G52: 283 | H52: 0.3 | I52: =$H$52*C52 -> 112.2 | J52: =$H$52*D52 -> 108.9 | K52: =$H$52*E52 -> 133.2 | L52: =$H$52*F52 -> 124.8 | M52: =$H$52*G52 -> 84.9 | P52: =P39/60 -> 5.5833333 | U52: Total Cost Per Flight | V52: =V42+V45+V48+V51 -> 277.2 | W52: =W42+W45+W48+W51 -> 277.2 | X52: =X42+X45+X48+X51 -> 321.2 | Y52: =Y42+Y45+Y48+Y51 -> 321.2 | Z52: =Z42+Z45+Z48+Z51 -> 277.2
A53: Glassware | C53: 192 | D53: 184 | E53: 224 | F53: 224 | G53: 140 | H53: 1 | I53: =$H$53*C53 -> 192 | J53: =$H$53*D53 -> 184 | K53: =$H$53*E53 -> 224 | L53: =$H$53*F53 -> 224 | M53: =$H$53*G53 -> 140 | U53: ='P&L'!$R$10 -> 0.13 | V53: =V52*(1+$U$53) -> 313.236 | W53: =W52*(1+$U$53) -> 313.236 | X53: =X52*(1+$U$53) -> 362.956 | Y53: =Y52*(1+$U$53) -> 362.956 | Z53: =Z52*(1+$U$53) -> 313.236
A54: Cutlery* | C54: 288 | D54: 276 | E54: 336 | F54: 336 | G54: 210 | H54: 0.75 | I54: =$H$54*C54 -> 216 | J54: =$H$54*D54 -> 207 | K54: =$H$54*E54 -> 252 | L54: =$H$54*F54 -> 252 | M54: =$H$54*G54 -> 157.5 | U54: Strip Only
A55: Tray (1/1 & 1/2) | C55: 96 | D55: 92 | E55: 112 | F55: 112 | G55: 70 | H55: 0.3 | I55: =$H$55*C55 -> 28.8 | J55: =$H$55*D55 -> 27.6 | K55: =$H$55*E55 -> 33.6 | L55: =$H$55*F55 -> 33.6 | M55: =$H$55*G55 -> 21 | U55: Driver Man Minutes | V55: 360 | W55: 360 | X55: 420 | Y55: 420 | Z55: 360
A56: Sundries Items | C56: 0 | D56: 0 | E56: 0 | F56: 0 | G56: 0 | I56: =H56*C56 -> 0 | J56: =I56*D56 -> 0 | K56: =J56*E56 -> 0 | L56: =K56*F56 -> 0 | M56: =L56*G56 -> 0 | U56: Price per Man Minutes | V56: 0.55 | W56: 0.55 | X56: 0.55 | Y56: 0.55 | Z56: 0.55
A57: Total Volume of Washing per Aircraft | C57: 950 | D57: 915 | E57: 1116 | F57: 1088 | G57: 703 | I57: =SUM(I52:I56) -> 549 | J57: =SUM(J52:J56) -> 527.5 | K57: =SUM(K52:K56) -> 642.8 | L57: =SUM(L52:L56) -> 634.4 | M57: =SUM(M52:M56) -> 403.4 | U57: Driver Cost | V57: =V55*V56 -> 198 | W57: =W55*W56 -> 198 | X57: =X55*X56 -> 231 | Y57: =Y55*Y56 -> 231 | Z57: =Z55*Z56 -> 198
A58: Total Man Minutes per Aircraft | C58: =I57 -> 549 | D58: =J57 -> 527.5 | E58: =K57 -> 642.8 | F58: =L57 -> 634.4 | G58: =M57 -> 403.4 | U58: Flt Co-ord Man Minutes | V58: 0 | W58: 0 | X58: 0 | Y58: 0 | Z58: 0
A59: Price per Man Minute | C59: 0.4 | D59: 0.4 | E59: 0.4 | F59: 0.4 | G59: 0.4 | U59: Price per Man Minutes | V59: 0 | W59: 0 | X59: 0 | Y59: 0 | Z59: 0
A60: Cost per Flight | C60: =C58*C59 -> 219.6 | D60: =D58*D59 -> 211 | E60: =E58*E59 -> 257.12 | F60: =F58*F59 -> 253.76 | G60: =G58*G59 -> 161.36 | U60: Flt Co-ord Cost | V60: =V58*V59 -> 0 | W60: =W58*W59 -> 0 | X60: =X58*X59 -> 0 | Y60: =Y58*Y59 -> 0 | Z60: =Z58*Z59 -> 0
A61: Y-Class Equipment | C61: Quantities | I61: MM | J61: MM | K61: MM | L61: MM | M61: MM | U61: Dispatch Man Minutes | V61: 30 | W61: 30 | X61: 30 | Y61: 30 | Z61: 30
A62: Tray 1/2 | C62: 185 | D62: 184 | E62: 235 | F62: 325 | G62: 192 | H62: 0.25 | I62: =$H$62*C62 -> 46.25 | J62: =$H$62*D62 -> 46 | K62: =$H$62*E62 -> 58.75 | L62: =$H$62*F62 -> 81.25 | M62: =$H$62*G62 -> 48 | U62: Price per Man Minutes | V62: 0.44 | W62: 0.44 | X62: 0.44 | Y62: 0.44 | Z62: 0.44
A63: Plastics | C63: 185 | D63: 184 | E63: 235 | F63: 325 | G63: 192 | H63: 0.4 | I63: =$H$63*C63 -> 74 | J63: =$H$63*D63 -> 73.6 | K63: =$H$63*E63 -> 94 | L63: =$H$63*F63 -> 130 | M63: =$H$63*G63 -> 76.8 | U63: Dispatch Cost | V63: =V61*V62 -> 13.2 | W63: =W61*W62 -> 13.2 | X63: =X61*X62 -> 13.2 | Y63: =Y61*Y62 -> 13.2 | Z63: =Z61*Z62 -> 13.2
A64: Sundries Items | C64: 0 | D64: 0 | E64: 0 | F64: 0 | G64: 0 | H64: 0.25 | I64: =$H$64*C64 -> 0 | J64: =$H$64*D64 -> 0 | K64: =$H$64*E64 -> 0 | L64: =$H$64*F64 -> 0 | M64: =$H$64*G64 -> 0 | U64: [Add resource as appropriate] | V64: 0 | W64: 0 | X64: 0 | Y64: 0 | Z64: 0
A65: Total Volume of Washing per Aircraft | C65: 370 | D65: 368 | E65: 470 | F65: 650 | G65: 384 | I65: =$H$65*C65 -> 0 | J65: =$H$65*D65 -> 0 | K65: =$H$65*E65 -> 0 | L65: =$H$65*F65 -> 0 | M65: =$H$65*G65 -> 0 | U65: [Add resource labour rate as appropriate] | V65: 0 | W65: 0 | X65: 0 | Y65: 0 | Z65: 0
A66: Total Man Minutes per Aircraft | C66: =I66 -> 120.25 | D66: =J66 -> 119.6 | E66: =K66 -> 152.75 | F66: =L66 -> 211.25 | G66: =M66 -> 124.8 | I66: =SUM(I62:I65) -> 120.25 | J66: =SUM(J62:J65) -> 119.6 | K66: =SUM(K62:K65) -> 152.75 | L66: =SUM(L62:L65) -> 211.25 | M66: =SUM(M62:M65) -> 124.8 | U66: Cost | V66: =V64*V65 -> 0 | W66: =W64*W65 -> 0 | X66: =X64*X65 -> 0 | Y66: =Y64*Y65 -> 0 | Z66: =Z64*Z65 -> 0
A67: Price per Man Minute | C67: 0.4 | D67: 0.4 | E67: 0.4 | F67: 0.4 | G67: 0.4 | U67: Total Cost Per Flight | V67: =V57+V60+V63+V66 -> 211.2 | W67: =W57+W60+W63+W66 -> 211.2 | X67: =X57+X60+X63+X66 -> 244.2 | Y67: =Y57+Y60+Y63+Y66 -> 244.2 | Z67: =Z57+Z60+Z63+Z66 -> 211.2
A68: Cost per Flight | C68: =C66*C67 -> 48.1 | D68: =D66*D67 -> 47.84 | E68: =E66*E67 -> 61.1 | F68: =F66*F67 -> 84.5 | G68: =G66*G67 -> 49.92 | U68: ='P&L'!$R$10 -> 0.13 | V68: =V67*(1+$U$53) -> 238.656 | W68: =W67*(1+$U$53) -> 238.656 | X68: =X67*(1+$U$53) -> 275.946 | Y68: =Y67*(1+$U$53) -> 275.946 | Z68: =Z67*(1+$U$53) -> 238.656
A69: Carts, Ovens & Boxes | I69: MM | J69: MM | K69: MM | L69: MM | M69: MM | U69: Load Only
A70: Full Cart | C70: 23 | D70: 21 | E70: 29 | F70: 31 | G70: 27 | H70: 2.5 | I70: =C70*$H$70 -> 57.5 | J70: =D70*$H$70 -> 52.5 | K70: =E70*$H$70 -> 72.5 | L70: =F70*$H$70 -> 77.5 | M70: =G70*$H$70 -> 67.5 | U70: Driver Man Minutes | V70: 300 | W70: 300 | X70: 360 | Y70: 360 | Z70: 300
A71: Half Cart | C71: 5 | D71: 9 | E71: 15 | F71: 19 | G71: 6 | H71: 1.5 | I71: =C71*$H$71 -> 7.5 | J71: =D71*$H$71 -> 13.5 | K71: =E71*$H$71 -> 22.5 | L71: =F71*$H$71 -> 28.5 | M71: =G71*$H$71 -> 9 | U71: Price per Man Minutes | V71: 0.55 | W71: 0.55 | X71: 0.55 | Y71: 0.55 | Z71: 0.55
A72: Box | C72: 20 | D72: 23 | E72: 15 | F72: 10 | G72: 7 | H72: 0.3 | I72: =C72*$H$72 -> 6 | J72: =D72*$H$72 -> 6.9 | K72: =E72*$H$72 -> 4.5 | L72: =F72*$H$72 -> 3 | M72: =G72*$H$72 -> 2.1 | U72: Driver Cost | V72: =V70*V71 -> 165 | W72: =W70*W71 -> 165 | X72: =X70*X71 -> 198 | Y72: =Y70*Y71 -> 198 | Z72: =Z70*Z71 -> 165
A73: Oven | C73: 12 | D73: 12 | E73: 15 | F73: 18 | G73: 12 | H73: 0.3 | I73: =C73*$H$73 -> 3.6 | J73: =D73*$H$73 -> 3.6 | K73: =E73*$H$73 -> 4.5 | L73: =F73*$H$73 -> 5.4 | M73: =G73*$H$73 -> 3.6 | U73: Flt Co-ord Man Minutes | V73: 0 | W73: 0 | X73: 0 | Y73: 0 | Z73: 0
A74: Waste Cart | C74: 0 | D74: 0 | E74: 0 | F74: 0 | G74: 0 | H74: 1.5 | I74: =C74*$H$74 -> 0 | J74: =D74*$H$74 -> 0 | K74: =E74*$H$74 -> 0 | L74: =F74*$H$74 -> 0 | M74: =G74*$H$74 -> 0 | U74: Price per Man Minutes | V74: 0 | W74: 0 | X74: 0 | Y74: 0 | Z74: 0
A75: Drawer M11 | C75: 136 | D75: 150 | E75: 176 | F75: 184 | G75: 138 | H75: 0.3 | I75: =C75*$H$75 -> 40.8 | J75: =D75*$H$75 -> 45 | K75: =E75*$H$75 -> 52.8 | L75: =F75*$H$75 -> 55.2 | M75: =G75*$H$75 -> 41.4 | U75: Flt Co-ord Cost | V75: =V73*V74 -> 0 | W75: =W73*W74 -> 0 | X75: =X73*X74 -> 0 | Y75: =Y73*Y74 -> 0 | Z75: =Z73*Z74 -> 0
A76: Drawer M8 | C76: 44 | D76: 42 | E76: 45 | F76: 68 | G76: 38 | H76: 0.3 | I76: =C76*$H$76 -> 13.2 | J76: =D76*$H$76 -> 12.6 | K76: =E76*$H$76 -> 13.5 | L76: =F76*$H$76 -> 20.4 | M76: =G76*$H$76 -> 11.4 | U76: Dispatch Man Minutes | V76: 30 | W76: 30 | X76: 30 | Y76: 30 | Z76: 30
A77: Glass Racks | C77: 22 | D77: 22 | E77: 31 | F77: 22 | G77: 22 | H77: 0.3 | I77: =C77*$H$77 -> 6.6 | J77: =D77*$H$77 -> 6.6 | K77: =E77*$H$77 -> 9.3 | L77: =F77*$H$77 -> 6.6 | M77: =G77*$H$77 -> 6.6 | U77: Price per Man Minutes | V77: 0.44 | W77: 0.44 | X77: 0.44 | Y77: 0.44 | Z77: 0.44
A78: Total Volume of Washing per Aircraft | C78: 262 | D78: 279 | E78: 326 | F78: 352 | G78: 250 | I78: =SUM(I70:I77) -> 135.2 | J78: =SUM(J70:J77) -> 140.7 | K78: =SUM(K70:K77) -> 179.6 | L78: =SUM(L70:L77) -> 196.6 | M78: =SUM(M70:M77) -> 141.6 | U78: Dispatch Cost | V78: =V76*V77 -> 13.2 | W78: =W76*W77 -> 13.2 | X78: =X76*X77 -> 13.2 | Y78: =Y76*Y77 -> 13.2 | Z78: =Z76*Z77 -> 13.2
A79: Total Man Minutes per Aircraft | C79: =I78 -> 135.2 | D79: =J78 -> 140.7 | E79: =K78 -> 179.6 | F79: =L78 -> 196.6 | G79: =M78 -> 141.6 | U79: [Add resource as appropriate] | V79: 0 | W79: 0 | X79: 0 | Y79: 0 | Z79: 0
A80: Price per Man Minute | C80: 0.4 | D80: 0.4 | E80: 0.4 | F80: 0.4 | G80: 0.4 | U80: [Add resource labour rate as appropriate] | V80: 0 | W80: 0 | X80: 0 | Y80: 0 | Z80: 0
A81: Cost per Flight | C81: =C79*C80 -> 54.08 | D81: =D79*D80 -> 56.28 | E81: =E79*E80 -> 71.84 | F81: =F79*F80 -> 78.64 | G81: =G79*G80 -> 56.64 | U81: Cost | V81: =V79*V80 -> 0 | W81: =W79*W80 -> 0 | X81: =X79*X80 -> 0 | Y81: =Y79*Y80 -> 0 | Z81: =Z79*Z80 -> 0
U82: Total Cost Per Flight | V82: =V72+V75+V78+V81 -> 178.2 | W82: =W72+W75+W78+W81 -> 178.2 | X82: =X72+X75+X78+X81 -> 211.2 | Y82: =Y72+Y75+Y78+Y81 -> 211.2 | Z82: =Z72+Z75+Z78+Z81 -> 178.2
A83: Total Cost Per Flight ($) | B83: ATL | C83: =C50+C60+C68+C81 -> 623.1 | D83: =D50+D60+D68+D81 -> 619.52 | E83: =E50+E60+E68+E81 -> 777.26 | F83: =F50+F60+F68+F81 -> 669.58 | G83: =G50+G60+G68+G81 -> 578.2 | U83: ='P&L'!$R$10 -> 0.13 | V83: =V82*(1+$U$53) -> 201.366 | W83: =W82*(1+$U$53) -> 201.366 | X83: =X82*(1+$U$53) -> 238.656 | Y83: =Y82*(1+$U$53) -> 238.656 | Z83: =Z82*(1+$U$53) -> 201.366
B84: ='P&L'!$R$10 -> 0.13 | C84: =C83*(1+$U$53) -> 704.103 | D84: =D83*(1+$U$53) -> 700.0576 | E84: =E83*(1+$U$53) -> 878.3038 | F84: =F83*(1+$U$53) -> 756.6254 | G84: =G83*(1+$U$53) -> 653.366 | U84: Additional Activity
U85: Extra Truck Trip (one off fee if applicable) | V85: 215 | W85: 215 | X85: 215 | Y85: 215 | Z85: 215
U86: Aircraft Change Airside | V86: 215 | W86: 215 | X86: 215 | Y86: 215 | Z86: 215
C87: =C48+C58+C66+C79 -> 1557.75 | U87: Extra Van Trip (one off fee if applicable) | V87: 50 | W87: 50 | X87: 50 | Y87: 50 | Z87: 50
C88: =C87/60 -> 25.9625 | U88: Garbage Removal (one off fee if applicable) | V88: 350 | W88: 350 | X88: 350 | Y88: 350 | Z88: 350
U90: Assumptions

Sheet FlightConfig 
A1: Aircraft type | B1: 350 | J1: WEEKS
A2: DFW | B2: FC | C2: BC | D2: EU | E2: EY | F2: TC | G2: CY | H2: Total | J2: FLIGHTS/WEEK
A3: FLIGHT CONFIG | B3: =IF($B$1=350,B17,IF($B$1=737,B23,IF($B$1=380,B23))) -> 0 | C3: =IF($B$1=350,C17,IF($B$1=737,C23,IF($B$1=380,C23))) -> 34 | D3: =IF($B$1=350,D17,IF($B$1=737,D23,IF($B$1=380,D23))) -> 48 | E3: =IF($B$1=350,E17,IF($B$1=737,E23,IF($B$1=380,E23))) -> 198 | F3: =IF($B$1=350,F17,IF($B$1=737,F23,IF($B$1=380,F23))) -> 0 | G3: =IF($B$1=350,G17,IF($B$1=737,G23,IF($B$1=380,G23))) -> 6 | H3: =IF($B$1=350,H17,IF($B$1=737,H23,IF($B$1=380,H23))) -> 286 | J3: FLTS PER YEAR
A4: LOAD FACTORS | B4: =+'P&L'!$R$4 -> 0.8 | C4: =+'P&L'!$R$4 -> 0.8 | D4: =+'P&L'!$R$4 -> 0.8 | E4: =+'P&L'!$R$4 -> 0.8 | F4: =+'P&L'!$R$4 -> 0.8 | G4: =+'P&L'!$R$4 -> 0.8 | J4: # OF CYCLES
A5: PAX COUNT | B5: =ROUNDUP(B3*B4,0) -> 0 | C5: =ROUNDUP(C3*C4,0) -> 28 | D5: =ROUNDUP(D3*D4,0) -> 39 | E5: =ROUNDUP(E3*E4,0) -> 159 | F5: =ROUNDUP(F3*F4,0) -> 0 | G5: =ROUNDUP(G3*G4,0) -> 5 | H5: =SUM(B5:G5) -> 231 | J5: FLTS PER CYCLE
A9: Aircraft type | B9: 787 | J9: WEEKS | K9: 52
A10: DFW | B10: FC | C10: BC | D10: EU | E10: EY | F10: TC | G10: CY | H10: Total | J10: FLIGHTS/WEEK | K10: 5
A11: FLIGHT CONFIG | B11: 0 | C11: 0 | D11: 36 | E11: 323 | F11: 1 | G11: 10 | H11: =SUM(B11:G11) -> 370 | J11: FLTS PER YEAR | K11: =K9*K10 -> 260
A12: LOAD FACTORS | B12: 1 | C12: 1 | D12: 1 | E12: 1 | F12: 1 | G12: 1 | J12: # OF CYCLES | K12: 1
A13: PAX COUNT | B13: =ROUNDUP(B11*B12,0) -> 0 | C13: =ROUNDUP(C11*C12,0) -> 0 | D13: =ROUNDUP(D11*D12,0) -> 36 | E13: =ROUNDUP(E11*E12,0) -> 323 | F13: =ROUNDUP(F11*F12,0) -> 1 | G13: =ROUNDUP(G11*G12,0) -> 10 | H13: =SUM(B13:G13) -> 370 | J13: FLTS PER CYCLE | K13: =K11/K12 -> 260
A14: 0
A15: Aircraft type | B15: 350 | J15: WEEKS | K15: 52
A16: DFW | B16: FC | C16: BC | D16: EU | E16: EY | F16: TC | G16: CY | H16: Total | J16: FLIGHTS/WEEK | K16: 7
A17: FLIGHT CONFIG | B17: =B29 -> 0 | C17: =C29 -> 34 | D17: =D29 -> 48 | E17: =E29 -> 198 | F17: =F29 -> 0 | G17: =G29 -> 6 | H17: =SUM(B17:G17) -> 286 | J17: FLTS PER YEAR | K17: =K15*K16 -> 364
A18: LOAD FACTORS | B18: =+'P&L'!$R$4 -> 0.8 | C18: =+'P&L'!$R$4 -> 0.8 | D18: =+'P&L'!$R$4 -> 0.8 | E18: =+'P&L'!$R$4 -> 0.8 | F18: =+'P&L'!$R$4 -> 0.8 | G18: =+'P&L'!$R$4 -> 0.8 | J18: # OF CYCLES | K18: 1
A19: PAX COUNT | B19: =ROUNDUP(B17*B18,0) -> 0 | C19: =ROUNDUP(C17*C18,0) -> 28 | D19: =ROUNDUP(D17*D18,0) -> 39 | E19: =ROUNDUP(E17*E18,0) -> 159 | F19: =ROUNDUP(F17*F18,0) -> 0 | G19: =ROUNDUP(G17*G18,0) -> 5 | H19: =SUM(B19:G19) -> 231 | J19: FLTS PER CYCLE | K19: 365
B21: 330 | J21: WEEKS | K21: 52
A22: DFW | B22: FC | C22: BC | D22: EU | E22: EY | F22: TC | G22: CY | H22: Total | J22: FLIGHTS/WEEK | K22: 7
A23: FLIGHT CONFIG | B23: =B35 -> 0 | C23: =C35 -> 30 | D23: =D35 -> 44 | E23: =E35 -> 184 | F23: =F35 -> 0 | G23: =G35 -> 6 | H23: =SUM(B23:G23) -> 264 | J23: FLTS PER YEAR | K23: =K21*K22 -> 364
A24: LOAD FACTORS | B24: =+'P&L'!$R$4 -> 0.8 | C24: =+'P&L'!$R$4 -> 0.8 | D24: =+'P&L'!$R$4 -> 0.8 | E24: =+'P&L'!$R$4 -> 0.8 | F24: =+'P&L'!$R$4 -> 0.8 | G24: =+'P&L'!$R$4 -> 0.8 | J24: # OF CYCLES | K24: 1
A25: PAX COUNT | B25: =ROUNDUP(B23*B24,0) -> 0 | C25: =ROUNDUP(C23*C24,0) -> 24 | D25: =ROUNDUP(D23*D24,0) -> 36 | E25: =ROUNDUP(E23*E24,0) -> 148 | F25: =ROUNDUP(F23*F24,0) -> 0 | G25: =ROUNDUP(G23*G24,0) -> 5 | H25: =SUM(B25:G25) -> 213 | J25: FLTS PER CYCLE | K25: 365
A28: AC350 | B28: FIRST CLASS | C28: BUSINESS CLASS | D28: PREMIUM ECONOMY CLASS | E28: ECONOMY CLASS | F28: TECH CREW CLASS | G28: CABIN CREW CLASS
B29: 0 | C29: 34 | D29: 48 | E29: 198 | G29: 6
A34: AC330 | B34: FIRST CLASS | C34: BUSINESS CLASS | D34: PREMIUM ECONOMY CLASS | E34: ECONOMY CLASS | F34: TECH CREW CLASS | G34: CABIN CREW CLASS
B35: 0 | C35: 30 | D35: 44 | E35: 184 | G35: 6

Sheet Food
X1: Per Flight | AG1: Annual
M2: 0.4 | O2: ='P&L'!R8 -> 0.22 | P2: ='P&L'!R9 -> 0.2
A3: CLASS | B3: CYCLE | D3: SERVICE | E3: Item # | G3: Description | H3: QTY | I3: RATIOS | J3: Volume Per Flight | K3: DM | L3: IE MM | M3: DL | N3: TOTAL COST | O3: Food Markup | P3: Labor Markup | Q3: Price | R3: Food+MU | S3: Labor +MU | T3: Total | W3: NM per flt | X3: DM per flt | Y3: MM per flt | Z3: DL per flt | AA3: Cost per flt | AB3: Food Markup per flt | AC3: Labor Markup Per flt | AD3: Revenue per flt | AF3: Annual NM cost | AG3: Annual DM | AH3: Annual MM | AI3: Annual DL | AJ3: Annual Cost | AK3: Annual Revenue
A4: BUSINESS CLASS | B4: 1 | C4: =CONCATENATE(A4&B4&F4) -> BUSINESS CLASS1110 | E4: 1205 | F4: 110 | G4: =VLOOKUP(E4,'FG MASTER'!$A:$AB,2,0) -> BC DINNER TRAY SET UP | H4: 1 | I4: 1 | J4: =IFERROR(IF(I4="std",H4,HLOOKUP(A4,'FlightConfig '!$B$34:$G$35,2,0)*I4),"") -> 30 | K4: =VLOOKUP(Food!E4,'FG MASTER'!$A$1:$AC$737,16,0) -> 0 | L4: =VLOOKUP(Food!E4,'FG MASTER'!$A$10:$AC$737,17,0) -> 0 | M4: =IFERROR(L4*$M$2,"") -> 0 | N4: =IFERROR((K4)+M4,"") -> 0 | O4: =IFERROR($K4*(1+$O$2)-$K4,0) -> 0 | P4: =IFERROR($M4*(1+$P$2)-$M4,0) -> 0 | Q4: =SUM(N4:P4) -> 0 | R4: =K4*(1+$O$2) -> 0 | S4: =M4*(1+$P$2) -> 0 | T4: =R4+S4 -> 0 | W4: =IFERROR(#REF!*J4,"") | X4: =IFERROR(K4*J4,"") -> 0 | Y4: =IFERROR(+L4*J4,"") -> 0 | Z4: =IFERROR(+M4*J4,"") -> 0 | AA4: =IFERROR(+N4*J4,"") -> 0 | AB4: =IFERROR(O4*$J4,"") -> 0 | AC4: =IFERROR(P4*$J4,"") -> 0 | AD4: =IFERROR(+Q4*J4,"") -> 0 | AF4: =IFERROR(W4*'FlightConfig '!$K$3,"") | AG4: =IFERROR(X4*'FlightConfig '!$K$23,"") -> 0 | AH4: =IFERROR(Y4*'FlightConfig '!$K$23,"") -> 0 | AI4: =IFERROR(Z4*'FlightConfig '!$K$23,"") -> 0 | AJ4: =IFERROR(AA4*'FlightConfig '!$K$23,"") -> 0 | AK4: =IFERROR(AB4*'FlightConfig '!$K$23,"") -> 0
A5: BUSINESS CLASS | B5: 1 | C5: =CONCATENATE(A5&B5&F5) -> BUSINESS CLASS1110 | E5: 1156 | F5: 110 | G5: =VLOOKUP(E5,'FG MASTER'!$A:$AB,2,0) -> BC C1 DINNER PLAIN WHIPPED BUTTER WITH FLAKE SALT | H5: 1 | I5: 1 | J5: =IFERROR(IF(I5="std",H5,HLOOKUP(A5,'FlightConfig '!$B$34:$G$35,2,0)*I5),"") -> 30 | K5: =VLOOKUP(Food!E5,'FG MASTER'!$A$1:$AC$737,16,0) -> 0.2 | L5: =VLOOKUP(Food!E5,'FG MASTER'!$A$10:$AC$737,17,0) -> 0.5 | M5: =IFERROR(L5*$M$2,"") -> 0.2 | N5: =IFERROR((K5)+M5,"") -> 0.4 | O5: =IFERROR($K5*(1+$O$2)-$K5,0) -> 0.044 | P5: =IFERROR($M5*(1+$P$2)-$M5,0) -> 0.04 | Q5: =SUM(N5:P5) -> 0.484 | R5: 0.23 | S5: 0.23 | T5: =R5+S5 -> 0.46 | U5: PREVIOUS CYCLE | W5: =IFERROR(#REF!*J5,"") | X5: =IFERROR(K5*J5,"") -> 6 | Y5: =IFERROR(+L5*J5,"") -> 15 | Z5: =IFERROR(+M5*J5,"") -> 6 | AA5: =IFERROR(+N5*J5,"") -> 12 | AB5: =IFERROR(O5*$J5,"") -> 1.32 | AC5: =IFERROR(P5*$J5,"") -> 1.2 | AD5: =IFERROR(+Q5*J5,"") -> 14.52 | AF5: =IFERROR(W5*'FlightConfig '!$K$3,"") | AG5: =IFERROR(X5*'FlightConfig '!$K$23,"") -> 2184 | AH5: =IFERROR(Y5*'FlightConfig '!$K$23,"") -> 5460 | AI5: =IFERROR(Z5*'FlightConfig '!$K$23,"") -> 2184 | AJ5: =IFERROR(AA5*'FlightConfig '!$K$23,"") -> 4368 | AK5: =IFERROR(AB5*'FlightConfig '!$K$23,"") -> 480.48
A6: BUSINESS CLASS | B6: 1 | C6: =CONCATENATE(A6&B6&F6) -> BUSINESS CLASS1110 | E6: 1226 | F6: 110 | G6: =VLOOKUP(E6,'FG MASTER'!$A:$AB,2,0) -> 2026 BC CY1 PARKER HOUSE KISS ROLL | H6: 1 | I6: 0.4 | J6: =IFERROR(IF(I6="std",H6,HLOOKUP(A6,'FlightConfig '!$B$34:$G$35,2,0)*I6),"") -> 12 | K6: =VLOOKUP(Food!E6,'FG MASTER'!$A$1:$AC$737,16,0) -> 0.2 | L6: =VLOOKUP(Food!E6,'FG MASTER'!$A$10:$AC$737,17,0) -> 0.25 | M6: =IFERROR(L6*$M$2,"") -> 0.1 | N6: =IFERROR((K6)+M6,"") -> 0.3 | O6: =IFERROR($K6*(1+$O$2)-$K6,0) -> 0.044 | P6: =IFERROR($M6*(1+$P$2)-$M6,0) -> 0.02 | Q6: =SUM(N6:P6) -> 0.364 | R6: =K6*(1+$O$2) -> 0.244 | S6: =M6*(1+$P$2) -> 0.12 | T6: =R6+S6 -> 0.364 | U6: 0.47 | W6: =IFERROR(#REF!*J6,"") | X6: =IFERROR(K6*J6,"") -> 2.4 | Y6: =IFERROR(+L6*J6,"") -> 3 | Z6: =IFERROR(+M6*J6,"") -> 1.2 | AA6: =IFERROR(+N6*J6,"") -> 3.6 | AB6: =IFERROR(O6*$J6,"") -> 0.528 | AC6: =IFERROR(P6*$J6,"") -> 0.24 | AD6: =IFERROR(+Q6*J6,"") -> 4.368 | AF6: =IFERROR(W6*'FlightConfig '!$K$3,"") | AG6: =IFERROR(X6*'FlightConfig '!$K$23,"") -> 873.6 | AH6: =IFERROR(Y6*'FlightConfig '!$K$23,"") -> 1092 | AI6: =IFERROR(Z6*'FlightConfig '!$K$23,"") -> 436.8 | AJ6: =IFERROR(AA6*'FlightConfig '!$K$23,"") -> 1310.4 | AK6: =IFERROR(AB6*'FlightConfig '!$K$23,"") -> 192.192
A7: BUSINESS CLASS | B7: 1 | C7: =CONCATENATE(A7&B7&F7) -> BUSINESS CLASS1110 | E7: 1227 | F7: 110 | G7: =VLOOKUP(E7,'FG MASTER'!$A:$AB,2,0) -> 2026 BC CY1 HAWAIIAN ROLL | H7: 1 | I7: 0.4 | J7: =IFERROR(IF(I7="std",H7,HLOOKUP(A7,'FlightConfig '!$B$34:$G$35,2,0)*I7),"") -> 12 | K7: =VLOOKUP(Food!E7,'FG MASTER'!$A$1:$AC$737,16,0) -> 0.24 | L7: =VLOOKUP(Food!E7,'FG MASTER'!$A$10:$AC$737,17,0) -> 0.25 | M7: =IFERROR(L7*$M$2,"") -> 0.1 | N7: =IFERROR((K7)+M7,"") -> 0.34 | O7: =IFERROR($K7*(1+$O$2)-$K7,0) -> 0.0528 | P7: =IFERROR($M7*(1+$P$2)-$M7,0) -> 0.02 | Q7: =SUM(N7:P7) -> 0.4128 | R7: =K7*(1+$O$2) -> 0.2928 | S7: =M7*(1+$P$2) -> 0.12 | T7: =R7+S7 -> 0.4128 | U7: 0.28 | W7: =IFERROR(#REF!*J7,"") | X7: =IFERROR(K7*J7,"") -> 2.88 | Y7: =IFERROR(+L7*J7,"") -> 3 | Z7: =IFERROR(+M7*J7,"") -> 1.2 | AA7: =IFERROR(+N7*J7,"") -> 4.08 | AB7: =IFERROR(O7*$J7,"") -> 0.6336 | AC7: =IFERROR(P7*$J7,"") -> 0.24 | AD7: =IFERROR(+Q7*J7,"") -> 4.9536 | AF7: =IFERROR(W7*'FlightConfig '!$K$3,"") | AG7: =IFERROR(X7*'FlightConfig '!$K$23,"") -> 1048.32 | AH7: =IFERROR(Y7*'FlightConfig '!$K$23,"") -> 1092 | AI7: =IFERROR(Z7*'FlightConfig '!$K$23,"") -> 436.8 | AJ7: =IFERROR(AA7*'FlightConfig '!$K$23,"") -> 1485.12 | AK7: =IFERROR(AB7*'FlightConfig '!$K$23,"") -> 230.6304
A8: BUSINESS CLASS | B8: 1 | C8: =CONCATENATE(A8&B8&F8) -> BUSINESS CLASS1110 | E8: 1228 | F8: 110 | G8: =VLOOKUP(E8,'FG MASTER'!$A:$AB,2,0) -> 2026 BC CY1 SIX GRAIN ROLL | H8: 1 | I8: 0.4 | J8: =IFERROR(IF(I8="std",H8,HLOOKUP(A8,'FlightConfig '!$B$34:$G$35,2,0)*I8),"") -> 12 | K8: =VLOOKUP(Food!E8,'FG MASTER'!$A$1:$AC$737,16,0) -> 0.17 | L8: =VLOOKUP(Food!E8,'FG MASTER'!$A$10:$AC$737,17,0) -> 0.25 | M8: =IFERROR(L8*$M$2,"") -> 0.1 | N8: =IFERROR((K8)+M8,"") -> 0.27 | O8: =IFERROR($K8*(1+$O$2)-$K8,0) -> 0.0374 | P8: =IFERROR($M8*(1+$P$2)-$M8,0) -> 0.02 | Q8: =SUM(N8:P8) -> 0.3274 | R8: =K8*(1+$O$2) -> 0.2074 | S8: =M8*(1+$P$2) -> 0.12 | T8: =R8+S8 -> 0.3274 | U8: 0.41 | W8: =IFERROR(#REF!*J8,"") | X8: =IFERROR(K8*J8,"") -> 2.04 | Y8: =IFERROR(+L8*J8,"") -> 3 | Z8: =IFERROR(+M8*J8,"") -> 1.2 | AA8: =IFERROR(+N8*J8,"") -> 3.24 | AB8: =IFERROR(O8*$J8,"") -> 0.4488 | AC8: =IFERROR(P8*$J8,"") -> 0.24 | AD8: =IFERROR(+Q8*J8,"") -> 3.9288 | AF8: =IFERROR(W8*'FlightConfig '!$K$3,"") | AG8: =IFERROR(X8*'FlightConfig '!$K$23,"") -> 742.56 | AH8: =IFERROR(Y8*'FlightConfig '!$K$23,"") -> 1092 | AI8: =IFERROR(Z8*'FlightConfig '!$K$23,"") -> 436.8 | AJ8: =IFERROR(AA8*'FlightConfig '!$K$23,"") -> 1179.36 | AK8: =IFERROR(AB8*'FlightConfig '!$K$23,"") -> 163.3632
A9: BUSINESS CLASS | B9: 1 | C9: =CONCATENATE(A9&B9&F9) -> BUSINESS CLASS1110 | E9: 1229 | F9: 110 | G9: =VLOOKUP(E9,'FG MASTER'!$A:$AB,2,0) -> 2026 BC CY1 COLD STARTER 1 BLINI, SMOKED SALMON, SALMON ROE, LEMON DILL CRÈME FRIACHE, EGG, PICKLED RED ONION | H9: 1 | I9: 0.55 | J9: =IFERROR(IF(I9="std",H9,HLOOKUP(A9,'FlightConfig '!$B$34:$G$35,2,0)*I9),"") -> 16.5 | K9: =VLOOKUP(Food!E9,'FG MASTER'!$A$1:$AC$737,16,0) -> 3.56 | L9: =VLOOKUP(Food!E9,'FG MASTER'!$A$10:$AC$737,17,0) -> 1.75 | M9: =IFERROR(L9*$M$2,"") -> 0.7 | N9: =IFERROR((K9)+M9,"") -> 4.26 | O9: =IFERROR($K9*(1+$O$2)-$K9,0) -> 0.7832 | P9: =IFERROR($M9*(1+$P$2)-$M9,0) -> 0.14 | Q9: =SUM(N9:P9) -> 5.1832 | R9: =K9*(1+$O$2) -> 4.3432 | S9: =M9*(1+$P$2) -> 0.84 | T9: =R9+S9 -> 5.1832 | U9: 4.72 | W9: =IFERROR(#REF!*J9,"") | X9: =IFERROR(K9*J9,"") -> 58.74 | Y9: =IFERROR(+L9*J9,"") -> 28.875 | Z9: =IFERROR(+M9*J9,"") -> 11.55 | AA9: =IFERROR(+N9*J9,"") -> 70.29 | AB9: =IFERROR(O9*$J9,"") -> 12.9228 | AC9: =IFERROR(P9*$J9,"") -> 2.31 | AD9: =IFERROR(+Q9*J9,"") -> 85.5228 | AF9: =IFERROR(W9*'FlightConfig '!$K$3,"") | AG9: =IFERROR(X9*'FlightConfig '!$K$23,"") -> 21381.36 | AH9: =IFERROR(Y9*'FlightConfig '!$K$23,"") -> 10510.5 | AI9: =IFERROR(Z9*'FlightConfig '!$K$23,"") -> 4204.2 | AJ9: =IFERROR(AA9*'FlightConfig '!$K$23,"") -> 25585.56 | AK9: =IFERROR(AB9*'FlightConfig '!$K$23,"") -> 4703.8992
A10: BUSINESS CLASS | B10: 1 | C10: =CONCATENATE(A10&B10&F10) -> BUSINESS CLASS1110 | E10: 1230 | F10: 110 | G10: =VLOOKUP(E10,'FG MASTER'!$A:$AB,2,0) -> 2026 BC CY1 HOT STARTER 1 CARAMELIZED SHALLOT MUSHROOM TART, PUFF PASTRY CRUST | H10: 1 | I10: 0.55 | J10: =IFERROR(IF(I10="std",H10,HLOOKUP(A10,'FlightConfig '!$B$34:$G$35,2,0)*I10),"") -> 16.5 | K10: =VLOOKUP(Food!E10,'FG MASTER'!$A$1:$AC$737,16,0) -> 1.68 | L10: =VLOOKUP(Food!E10,'FG MASTER'!$A$10:$AC$737,17,0) -> 1.75 | M10: =IFERROR(L10*$M$2,"") -> 0.7 | N10: =IFERROR((K10)+M10,"") -> 2.38 | O10: =IFERROR($K10*(1+$O$2)-$K10,0) -> 0.3696 | P10: =IFERROR($M10*(1+$P$2)-$M10,0) -> 0.14 | Q10: =SUM(N10:P10) -> 2.8896 | R10: =K10*(1+$O$2) -> 2.0496 | S10: =M10*(1+$P$2) -> 0.84 | T10: =R10+S10 -> 2.8896 | U10: 4.16 | W10: =IFERROR(#REF!*J10,"") | X10: =IFERROR(K10*J10,"") -> 27.72 | Y10: =IFERROR(+L10*J10,"") -> 28.875 | Z10: =IFERROR(+M10*J10,"") -> 11.55 | AA10: =IFERROR(+N10*J10,"") -> 39.27 | AB10: =IFERROR(O10*$J10,"") -> 6.0984 | AC10: =IFERROR(P10*$J10,"") -> 2.31 | AD10: =IFERROR(+Q10*J10,"") -> 47.6784 | AF10: =IFERROR(W10*'FlightConfig '!$K$3,"") | AG10: =IFERROR(X10*'FlightConfig '!$K$23,"") -> 10090.08 | AH10: =IFERROR(Y10*'FlightConfig '!$K$23,"") -> 10510.5 | AI10: =IFERROR(Z10*'FlightConfig '!$K$23,"") -> 4204.2 | AJ10: =IFERROR(AA10*'FlightConfig '!$K$23,"") -> 14294.28 | AK10: =IFERROR(AB10*'FlightConfig '!$K$23,"") -> 2219.8176
A11: BUSINESS CLASS | B11: 1 | C11: =CONCATENATE(A11&B11&F11) -> BUSINESS CLASS1110 | E11: 1231 | F11: 110 | G11: =VLOOKUP(E11,'FG MASTER'!$A:$AB,2,0) -> 2026 BC CY1 STARTER GARNISH 1 FRISEE AND DRESSING | H11: 1 | I11: 0.55 | J11: =IFERROR(IF(I11="std",H11,HLOOKUP(A11,'FlightConfig '!$B$34:$G$35,2,0)*I11),"") -> 16.5 | K11: =VLOOKUP(Food!E11,'FG MASTER'!$A$1:$AC$737,16,0) -> 0.85 | L11: =VLOOKUP(Food!E11,'FG MASTER'!$A$10:$AC$737,17,0) -> 0.5 | M11: =IFERROR(L11*$M$2,"") -> 0.2 | N11: =IFERROR((K11)+M11,"") -> 1.05 | O11: =IFERROR($K11*(1+$O$2)-$K11,0) -> 0.187 | P11: =IFERROR($M11*(1+$P$2)-$M11,0) -> 0.04 | Q11: =SUM(N11:P11) -> 1.277 | R11: =K11*(1+$O$2) -> 1.037 | S11: =M11*(1+$P$2) -> 0.24 | T11: =R11+S11 -> 1.277 | W11: =IFERROR(#REF!*J11,"") | X11: =IFERROR(K11*J11,"") -> 14.025 | Y11: =IFERROR(+L11*J11,"") -> 8.25 | Z11: =IFERROR(+M11*J11,"") -> 3.3 | AA11: =IFERROR(+N11*J11,"") -> 17.325 | AB11: =IFERROR(O11*$J11,"") -> 3.0855 | AC11: =IFERROR(P11*$J11,"") -> 0.66 | AD11: =IFERROR(+Q11*J11,"") -> 21.0705 | AF11: =IFERROR(W11*'FlightConfig '!$K$3,"") | AG11: =IFERROR(X11*'FlightConfig '!$K$23,"") -> 5105.1 | AH11: =IFERROR(Y11*'FlightConfig '!$K$23,"") -> 3003 | AI11: =IFERROR(Z11*'FlightConfig '!$K$23,"") -> 1201.2 | AJ11: =IFERROR(AA11*'FlightConfig '!$K$23,"") -> 6306.3 | AK11: =IFERROR(AB11*'FlightConfig '!$K$23,"") -> 1123.122
A12: BUSINESS CLASS | B12: 1 | C12: =CONCATENATE(A12&B12&F12) -> BUSINESS CLASS1110 | E12: 1232 | F12: 110 | G12: =VLOOKUP(E12,'FG MASTER'!$A:$AB,2,0) -> 2026 BC CY1 COLD STARTER 2 GOLDEN BEET, MANDARIN SEGMENT, FRISEE, GOAT CHEESE MOUSSE, CHIVES | H12: 1 | I12: 0 | J12: =IFERROR(IF(I12="std",H12,HLOOKUP(A12,'FlightConfig '!$B$34:$G$35,2,0)*I12),"") -> 0 | K12: =VLOOKUP(Food!E12,'FG MASTER'!$A$1:$AC$737,16,0) -> 1.06 | L12: =VLOOKUP(Food!E12,'FG MASTER'!$A$10:$AC$737,17,0) -> 2.25 | M12: =IFERROR(L12*$M$2,"") -> 0.9 | N12: =IFERROR((K12)+M12,"") -> 1.96 | O12: =IFERROR($K12*(1+$O$2)-$K12,0) -> 0.2332 | P12: =IFERROR($M12*(1+$P$2)-$M12,0) -> 0.18 | Q12: =SUM(N12:P12) -> 2.3732 | R12: =K12*(1+$O$2) -> 1.2932 | S12: =M12*(1+$P$2) -> 1.08 | T12: =R12+S12 -> 2.3732 | U12: 4.95 | W12: =IFERROR(#REF!*J12,"") | X12: =IFERROR(K12*J12,"") -> 0 | Y12: =IFERROR(+L12*J12,"") -> 0 | Z12: =IFERROR(+M12*J12,"") -> 0 | AA12: =IFERROR(+N12*J12,"") -> 0 | AB12: =IFERROR(O12*$J12,"") -> 0 | AC12: =IFERROR(P12*$J12,"") -> 0 | AD12: =IFERROR(+Q12*J12,"") -> 0 | AF12: =IFERROR(W12*'FlightConfig '!$K$3,"") | AG12: =IFERROR(X12*'FlightConfig '!$K$23,"") -> 0 | AH12: =IFERROR(Y12*'FlightConfig '!$K$23,"") -> 0 | AI12: =IFERROR(Z12*'FlightConfig '!$K$23,"") -> 0 | AJ12: =IFERROR(AA12*'FlightConfig '!$K$23,"") -> 0 | AK12: =IFERROR(AB12*'FlightConfig '!$K$23,"") -> 0
A13: BUSINESS CLASS | B13: 1 | C13: =CONCATENATE(A13&B13&F13) -> BUSINESS CLASS1110 | E13: 1233 | F13: 110 | G13: =VLOOKUP(E13,'FG MASTER'!$A:$AB,2,0) -> 2026 BC CY1 HOT STARTER 2 POACHED SHRIMP, CAJUN BUTTER SAUCE, FINGERLING POTATO, CHARRED CORN, CHICKEN ANDOUILLE SAUSAGE, CROSTINI | H13: 1 | I13: 0 | J13: =IFERROR(IF(I13="std",H13,HLOOKUP(A13,'FlightConfig '!$B$34:$G$35,2,0)*I13),"") -> 0 | K13: =VLOOKUP(Food!E13,'FG MASTER'!$A$1:$AC$737,16,0) -> 2.35 | L13: =VLOOKUP(Food!E13,'FG MASTER'!$A$10:$AC$737,17,0) -> 2.5 | M13: =IFERROR(L13*$M$2,"") -> 1 | N13: =IFERROR((K13)+M13,"") -> 3.35 | O13: =IFERROR($K13*(1+$O$2)-$K13,0) -> 0.517 | P13: =IFERROR($M13*(1+$P$2)-$M13,0) -> 0.2 | Q13: =SUM(N13:P13) -> 4.067 | R13: =K13*(1+$O$2) -> 2.867 | S13: =M13*(1+$P$2) -> 1.2 | T13: =R13+S13 -> 4.067 | U13: 3.31 | W13: =IFERROR(#REF!*J13,"") | X13: =IFERROR(K13*J13,"") -> 0 | Y13: =IFERROR(+L13*J13,"") -> 0 | Z13: =IFERROR(+M13*J13,"") -> 0 | AA13: =IFERROR(+N13*J13,"") -> 0 | AB13: =IFERROR(O13*$J13,"") -> 0 | AC13: =IFERROR(P13*$J13,"") -> 0 | AD13: =IFERROR(+Q13*J13,"") -> 0 | AF13: =IFERROR(W13*'FlightConfig '!$K$3,"") | AG13: =IFERROR(X13*'FlightConfig '!$K$23,"") -> 0 | AH13: =IFERROR(Y13*'FlightConfig '!$K$23,"") -> 0 | AI13: =IFERROR(Z13*'FlightConfig '!$K$23,"") -> 0 | AJ13: =IFERROR(AA13*'FlightConfig '!$K$23,"") -> 0 | AK13: =IFERROR(AB13*'FlightConfig '!$K$23,"") -> 0
A14: BUSINESS CLASS | B14: 1 | C14: =CONCATENATE(A14&B14&F14) -> BUSINESS CLASS1110 | E14: 1234 | F14: 110 | G14: =VLOOKUP(E14,'FG MASTER'!$A:$AB,2,0) -> 2026 BC CY1 STARTER GARNISH 2 CHIVE | H14: 1 | I14: 0 | J14: =IFERROR(IF(I14="std",H14,HLOOKUP(A14,'FlightConfig '!$B$34:$G$35,2,0)*I14),"") -> 0 | K14: =VLOOKUP(Food!E14,'FG MASTER'!$A$1:$AC$737,16,0) -> 2 | L14: =VLOOKUP(Food!E14,'FG MASTER'!$A$10:$AC$737,17,0) -> 0.5 | M14: =IFERROR(L14*$M$2,"") -> 0.2 | N14: =IFERROR((K14)+M14,"") -> 2.2 | O14: =IFERROR($K14*(1+$O$2)-$K14,0) -> 0.44 | P14: =IFERROR($M14*(1+$P$2)-$M14,0) -> 0.04 | Q14: =SUM(N14:P14) -> 2.68 | R14: =K14*(1+$O$2) -> 2.44 | S14: =M14*(1+$P$2) -> 0.24 | T14: =R14+S14 -> 2.68 | W14: =IFERROR(#REF!*J14,"") | X14: =IFERROR(K14*J14,"") -> 0 | Y14: =IFERROR(+L14*J14,"") -> 0 | Z14: =IFERROR(+M14*J14,"") -> 0 | AA14: =IFERROR(+N14*J14,"") -> 0 | AB14: =IFERROR(O14*$J14,"") -> 0 | AC14: =IFERROR(P14*$J14,"") -> 0 | AD14: =IFERROR(+Q14*J14,"") -> 0 | AF14: =IFERROR(W14*'FlightConfig '!$K$3,"") | AG14: =IFERROR(X14*'FlightConfig '!$K$23,"") -> 0 | AH14: =IFERROR(Y14*'FlightConfig '!$K$23,"") -> 0 | AI14: =IFERROR(Z14*'FlightConfig '!$K$23,"") -> 0 | AJ14: =IFERROR(AA14*'FlightConfig '!$K$23,"") -> 0 | AK14: =IFERROR(AB14*'FlightConfig '!$K$23,"") -> 0
A15: BUSINESS CLASS | B15: 1 | C15: =CONCATENATE(A15&B15&F15) -> BUSINESS CLASS1110 | E15: 1235 | F15: 110 | G15: =VLOOKUP(E15,'FG MASTER'!$A:$AB,2,0) -> 2026 BC CY1 ENTRÉE 1 CHICKEN BREAST, SWEET CORN CREAM, SPRING GREEN, ROASTED TOMATO, SWEET POTATO SOUFFLE | H15: 1 | I15: 0.6 | J15: =IFERROR(IF(I15="std",H15,HLOOKUP(A15,'FlightConfig '!$B$34:$G$35,2,0)*I15),"") -> 18 | K15: =VLOOKUP(Food!E15,'FG MASTER'!$A$1:$AC$737,16,0) -> 3.9 | L15: =VLOOKUP(Food!E15,'FG MASTER'!$A$10:$AC$737,17,0) -> 5 | M15: =IFERROR(L15*$M$2,"") -> 2 | N15: =IFERROR((K15)+M15,"") -> 5.9 | O15: =IFERROR($K15*(1+$O$2)-$K15,0) -> 0.858 | P15: =IFERROR($M15*(1+$P$2)-$M15,0) -> 0.4 | Q15: =SUM(N15:P15) -> 7.158 | R15: =K15*(1+$O$2) -> 4.758 | S15: =M15*(1+$P$2) -> 2.4 | T15: =R15+S15 -> 7.158 | U15: 7.62 | W15: =IFERROR(#REF!*J15,"") | X15: =IFERROR(K15*J15,"") -> 70.2 | Y15: =IFERROR(+L15*J15,"") -> 90 | Z15: =IFERROR(+M15*J15,"") -> 36 | AA15: =IFERROR(+N15*J15,"") -> 106.2 | AB15: =IFERROR(O15*$J15,"") -> 15.444 | AC15: =IFERROR(P15*$J15,"") -> 7.2 | AD15: =IFERROR(+Q15*J15,"") -> 128.844 | AF15: =IFERROR(W15*'FlightConfig '!$K$3,"") | AG15: =IFERROR(X15*'FlightConfig '!$K$23,"") -> 25552.8 | AH15: =IFERROR(Y15*'FlightConfig '!$K$23,"") -> 32760 | AI15: =IFERROR(Z15*'FlightConfig '!$K$23,"") -> 13104 | AJ15: =IFERROR(AA15*'FlightConfig '!$K$23,"") -> 38656.8 | AK15: =IFERROR(AB15*'FlightConfig '!$K$23,"") -> 5621.616
A16: BUSINESS CLASS | B16: 1 | C16: =CONCATENATE(A16&B16&F16) -> BUSINESS CLASS1110 | E16: 1236 | F16: 110 | G16: =VLOOKUP(E16,'FG MASTER'!$A:$AB,2,0) -> 2026 BC CY1 ENTRÉE 2 SALMON, TOMATO CHORONE SAUCE, SPINACH, COCANNON MASH | H16: 1 | I16: 0.3 | J16: =IFERROR(IF(I16="std",H16,HLOOKUP(A16,'FlightConfig '!$B$34:$G$35,2,0)*I16),"") -> 9 | K16: =VLOOKUP(Food!E16,'FG MASTER'!$A$1:$AC$737,16,0) -> 7.5 | L16: =VLOOKUP(Food!E16,'FG MASTER'!$A$10:$AC$737,17,0) -> 5 | M16: =IFERROR(L16*$M$2,"") -> 2 | N16: =IFERROR((K16)+M16,"") -> 9.5 | O16: =IFERROR($K16*(1+$O$2)-$K16,0) -> 1.65 | P16: =IFERROR($M16*(1+$P$2)-$M16,0) -> 0.4 | Q16: =SUM(N16:P16) -> 11.55 | R16: =K16*(1+$O$2) -> 9.15 | S16: =M16*(1+$P$2) -> 2.4 | T16: =R16+S16 -> 11.55 | U16: 13.57 | W16: =IFERROR(#REF!*J16,"") | X16: =IFERROR(K16*J16,"") -> 67.5 | Y16: =IFERROR(+L16*J16,"") -> 45 | Z16: =IFERROR(+M16*J16,"") -> 18 | AA16: =IFERROR(+N16*J16,"") -> 85.5 | AB16: =IFERROR(O16*$J16,"") -> 14.85 | AC16: =IFERROR(P16*$J16,"") -> 3.6 | AD16: =IFERROR(+Q16*J16,"") -> 103.95 | AF16: =IFERROR(W16*'FlightConfig '!$K$3,"") | AG16: =IFERROR(X16*'FlightConfig '!$K$23,"") -> 24570 | AH16: =IFERROR(Y16*'FlightConfig '!$K$23,"") -> 16380 | AI16: =IFERROR(Z16*'FlightConfig '!$K$23,"") -> 6552 | AJ16: =IFERROR(AA16*'FlightConfig '!$K$23,"") -> 31122 | AK16: =IFERROR(AB16*'FlightConfig '!$K$23,"") -> 5405.4
A17: BUSINESS CLASS | B17: 1 | C17: =CONCATENATE(A17&B17&F17) -> BUSINESS CLASS1110 | E17: 1237 | F17: 110 | G17: =VLOOKUP(E17,'FG MASTER'!$A:$AB,2,0) -> 2026 BC CY1 ENTRÉE 3 SHITAKE SNAP PEA RISOTTO, BUETTE BLANC, ASPARAGUS, TOATED TOMATO | H17: 1 | I17: 0.3 | J17: =IFERROR(IF(I17="std",H17,HLOOKUP(A17,'FlightConfig '!$B$34:$G$35,2,0)*I17),"") -> 9 | K17: =VLOOKUP(Food!E17,'FG MASTER'!$A$1:$AC$737,16,0) -> 2.74 | L17: =VLOOKUP(Food!E17,'FG MASTER'!$A$10:$AC$737,17,0) -> 4.75 | M17: =IFERROR(L17*$M$2,"") -> 1.9 | N17: =IFERROR((K17)+M17,"") -> 4.64 | O17: =IFERROR($K17*(1+$O$2)-$K17,0) -> 0.6028 | P17: =IFERROR($M17*(1+$P$2)-$M17,0) -> 0.38 | Q17: =SUM(N17:P17) -> 5.6228 | R17: =K17*(1+$O$2) -> 3.3428 | S17: =M17*(1+$P$2) -> 2.28 | T17: =R17+S17 -> 5.6228 | U17: 6.64 | W17: =IFERROR(#REF!*J17,"") | X17: =IFERROR(K17*J17,"") -> 24.66 | Y17: =IFERROR(+L17*J17,"") -> 42.75 | Z17: =IFERROR(+M17*J17,"") -> 17.1 | AA17: =IFERROR(+N17*J17,"") -> 41.76 | AB17: =IFERROR(O17*$J17,"") -> 5.4252 | AC17: =IFERROR(P17*$J17,"") -> 3.42 | AD17: =IFERROR(+Q17*J17,"") -> 50.6052 | AF17: =IFERROR(W17*'FlightConfig '!$K$3,"") | AG17: =IFERROR(X17*'FlightConfig '!$K$23,"") -> 8976.24 | AH17: =IFERROR(Y17*'FlightConfig '!$K$23,"") -> 15561 | AI17: =IFERROR(Z17*'FlightConfig '!$K$23,"") -> 6224.4 | AJ17: =IFERROR(AA17*'FlightConfig '!$K$23,"") -> 15200.64 | AK17: =IFERROR(AB17*'FlightConfig '!$K$23,"") -> 1974.7728
A18: BUSINESS CLASS | B18: 1 | C18: =CONCATENATE(A18&B18&F18) -> BUSINESS CLASS1110 | E18: 1238 | F18: 110 | G18: =VLOOKUP(E18,'FG MASTER'!$A:$AB,2,0) -> 2026 BC CY1 ENTRÉE 4 TOAST POINT, CHEDDAR CHEESE SLICE, PIEMENTO CHEESE, PEPPER JELLY, RED PEPPER BISQUE | H18: 1 | I18: 0.2 | J18: =IFERROR(IF(I18="std",H18,HLOOKUP(A18,'FlightConfig '!$B$34:$G$35,2,0)*I18),"") -> 6 | K18: =VLOOKUP(Food!E18,'FG MASTER'!$A$1:$AC$737,16,0) -> 1.52 | L18: =VLOOKUP(Food!E18,'FG MASTER'!$A$10:$AC$737,17,0) -> 2.75 | M18: =IFERROR(L18*$M$2,"") -> 1.1 | N18: =IFERROR((K18)+M18,"") -> 2.62 | O18: =IFERROR($K18*(1+$O$2)-$K18,0) -> 0.3344 | P18: =IFERROR($M18*(1+$P$2)-$M18,0) -> 0.22 | Q18: =SUM(N18:P18) -> 3.1744 | R18: =K18*(1+$O$2) -> 1.8544 | S18: =M18*(1+$P$2) -> 1.32 | T18: =R18+S18 -> 3.1744 | U18: 3.29 | W18: =IFERROR(#REF!*J18,"") | X18: =IFERROR(K18*J18,"") -> 9.12 | Y18: =IFERROR(+L18*J18,"") -> 16.5 | Z18: =IFERROR(+M18*J18,"") -> 6.6 | AA18: =IFERROR(+N18*J18,"") -> 15.72 | AB18: =IFERROR(O18*$J18,"") -> 2.0064 | AC18: =IFERROR(P18*$J18,"") -> 1.32 | AD18: =IFERROR(+Q18*J18,"") -> 19.0464 | AF18: =IFERROR(W18*'FlightConfig '!$K$3,"") | AG18: =IFERROR(X18*'FlightConfig '!$K$23,"") -> 3319.68 | AH18: =IFERROR(Y18*'FlightConfig '!$K$23,"") -> 6006 | AI18: =IFERROR(Z18*'FlightConfig '!$K$23,"") -> 2402.4 | AJ18: =IFERROR(AA18*'FlightConfig '!$K$23,"") -> 5722.08 | AK18: =IFERROR(AB18*'FlightConfig '!$K$23,"") -> 730.3296
A19: BUSINESS CLASS | B19: 1 | C19: =CONCATENATE(A19&B19&F19) -> BUSINESS CLASS1110 | E19: 1239 | F19: 110 | G19: =VLOOKUP(E19,'FG MASTER'!$A:$AB,2,0) -> 2026 BC CY1 ENTRÉE GARNISH RAINBOW MICROGREEN 42G | H19: 1 | I19: 0 | J19: =IFERROR(IF(I19="std",H19,HLOOKUP(A19,'FlightConfig '!$B$34:$G$35,2,0)*I19),"") -> 0 | K19: =VLOOKUP(Food!E19,'FG MASTER'!$A$1:$AC$737,16,0) -> 4.62 | L19: =VLOOKUP(Food!E19,'FG MASTER'!$A$10:$AC$737,17,0) -> 0.5 | M19: =IFERROR(L19*$M$2,"") -> 0.2 | N19: =IFERROR((K19)+M19,"") -> 4.82 | O19: =IFERROR($K19*(1+$O$2)-$K19,0) -> 1.0164 | P19: =IFERROR($M19*(1+$P$2)-$M19,0) -> 0.04 | Q19: =SUM(N19:P19) -> 5.8764 | R19: =K19*(1+$O$2) -> 5.6364 | S19: =M19*(1+$P$2) -> 0.24 | T19: =R19+S19 -> 5.8764 | W19: =IFERROR(#REF!*J19,"") | X19: =IFERROR(K19*J19,"") -> 0 | Y19: =IFERROR(+L19*J19,"") -> 0 | Z19: =IFERROR(+M19*J19,"") -> 0 | AA19: =IFERROR(+N19*J19,"") -> 0 | AB19: =IFERROR(O19*$J19,"") -> 0 | AC19: =IFERROR(P19*$J19,"") -> 0 | AD19: =IFERROR(+Q19*J19,"") -> 0 | AF19: =IFERROR(W19*'FlightConfig '!$K$3,"") | AG19: =IFERROR(X19*'FlightConfig '!$K$23,"") -> 0 | AH19: =IFERROR(Y19*'FlightConfig '!$K$23,"") -> 0 | AI19: =IFERROR(Z19*'FlightConfig '!$K$23,"") -> 0 | AJ19: =IFERROR(AA19*'FlightConfig '!$K$23,"") -> 0 | AK19: =IFERROR(AB19*'FlightConfig '!$K$23,"") -> 0
A20: BUSINESS CLASS | B20: 1 | C20: =CONCATENATE(A20&B20&F20) -> BUSINESS CLASS1110 | E20: 1240 | F20: 110 | G20: =VLOOKUP(E20,'FG MASTER'!$A:$AB,2,0) -> 2026 BC CY1 COLD DESSERT 1 RED VELVET CAKE, CHANTILLY CREAM, CHOCOLATE PEARL | H20: 1 | I20: 0.5 | J20: =IFERROR(IF(I20="std",H20,HLOOKUP(A20,'FlightConfig '!$B$34:$G$35,2,0)*I20),"") -> 15 | K20: =VLOOKUP(Food!E20,'FG MASTER'!$A$1:$AC$737,16,0) -> 0.81 | L20: =VLOOKUP(Food!E20,'FG MASTER'!$A$10:$AC$737,17,0) -> 1.5 | M20: =IFERROR(L20*$M$2,"") -> 0.6 | N20: =IFERROR((K20)+M20,"") -> 1.41 | O20: =IFERROR($K20*(1+$O$2)-$K20,0) -> 0.1782 | P20: =IFERROR($M20*(1+$P$2)-$M20,0) -> 0.12 | Q20: =SUM(N20:P20) -> 1.7082 | R20: =K20*(1+$O$2) -> 0.9882 | S20: =M20*(1+$P$2) -> 0.72 | T20: =R20+S20 -> 1.7082 | U20: 2.14 | W20: =IFERROR(#REF!*J20,"") | X20: =IFERROR(K20*J20,"") -> 12.15 | Y20: =IFERROR(+L20*J20,"") -> 22.5 | Z20: =IFERROR(+M20*J20,"") -> 9 | AA20: =IFERROR(+N20*J20,"") -> 21.15 | AB20: =IFERROR(O20*$J20,"") -> 2.673 | AC20: =IFERROR(P20*$J20,"") -> 1.8 | AD20: =IFERROR(+Q20*J20,"") -> 25.623 | AF20: =IFERROR(W20*'FlightConfig '!$K$3,"") | AG20: =IFERROR(X20*'FlightConfig '!$K$23,"") -> 4422.6 | AH20: =IFERROR(Y20*'FlightConfig '!$K$23,"") -> 8190 | AI20: =IFERROR(Z20*'FlightConfig '!$K$23,"") -> 3276 | AJ20: =IFERROR(AA20*'FlightConfig '!$K$23,"") -> 7698.6 | AK20: =IFERROR(AB20*'FlightConfig '!$K$23,"") -> 972.972
A21: BUSINESS CLASS | B21: 1 | C21: =CONCATENATE(A21&B21&F21) -> BUSINESS CLASS1110 | E21: 1241 | F21: 110 | G21: =VLOOKUP(E21,'FG MASTER'!$A:$AB,2,0) -> 2026 BC CY1 HOT DESSERT 1 MIX BERRY BREAD PUDDING, VANILLA ICE CREAM | H21: 1 | I21: 0.5 | J21: =IFERROR(IF(I21="std",H21,HLOOKUP(A21,'FlightConfig '!$B$34:$G$35,2,0)*I21),"") -> 15 | K21: =VLOOKUP(Food!E21,'FG MASTER'!$A$1:$AC$737,16,0) -> 1.83 | L21: =VLOOKUP(Food!E21,'FG MASTER'!$A$10:$AC$737,17,0) -> 1.5 | M21: =IFERROR(L21*$M$2,"") -> 0.6 | N21: =IFERROR((K21)+M21,"") -> 2.43 | O21: =IFERROR($K21*(1+$O$2)-$K21,0) -> 0.4026 | P21: =IFERROR($M21*(1+$P$2)-$M21,0) -> 0.12 | Q21: =SUM(N21:P21) -> 2.9526 | R21: =K21*(1+$O$2) -> 2.2326 | S21: =M21*(1+$P$2) -> 0.72 | T21: =R21+S21 -> 2.9526 | U21: 2.07 | W21: =IFERROR(#REF!*J21,"") | X21: =IFERROR(K21*J21,"") -> 27.45 | Y21: =IFERROR(+L21*J21,"") -> 22.5 | Z21: =IFERROR(+M21*J21,"") -> 9 | AA21: =IFERROR(+N21*J21,"") -> 36.45 | AB21: =IFERROR(O21*$J21,"") -> 6.039 | AC21: =IFERROR(P21*$J21,"") -> 1.8 | AD21: =IFERROR(+Q21*J21,"") -> 44.289 | AF21: =IFERROR(W21*'FlightConfig '!$K$3,"") | AG21: =IFERROR(X21*'FlightConfig '!$K$23,"") -> 9991.8 | AH21: =IFERROR(Y21*'FlightConfig '!$K$23,"") -> 8190 | AI21: =IFERROR(Z21*'FlightConfig '!$K$23,"") -> 3276 | AJ21: =IFERROR(AA21*'FlightConfig '!$K$23,"") -> 13267.8 | AK21: =IFERROR(AB21*'FlightConfig '!$K$23,"") -> 2198.196
A22: BUSINESS CLASS | B22: 1 | C22: =CONCATENATE(A22&B22&F22) -> BUSINESS CLASS1110 | E22: 1242 | F22: 110 | G22: =VLOOKUP(E22,'FG MASTER'!$A:$AB,2,0) -> 2026 BC CY1 COLD DESSERT 2 YUZU MOUSSE WITH TROPICAL FRUIT SALAD | H22: 1 | I22: 0 | J22: =IFERROR(IF(I22="std",H22,HLOOKUP(A22,'FlightConfig '!$B$34:$G$35,2,0)*I22),"") -> 0 | K22: =VLOOKUP(Food!E22,'FG MASTER'!$A$1:$AC$737,16,0) -> 1.29 | L22: =VLOOKUP(Food!E22,'FG MASTER'!$A$10:$AC$737,17,0) -> 1.5 | M22: =IFERROR(L22*$M$2,"") -> 0.6 | N22: =IFERROR((K22)+M22,"") -> 1.89 | O22: =IFERROR($K22*(1+$O$2)-$K22,0) -> 0.2838 | P22: =IFERROR($M22*(1+$P$2)-$M22,0) -> 0.12 | Q22: =SUM(N22:P22) -> 2.2938 | R22: =K22*(1+$O$2) -> 1.5738 | S22: =M22*(1+$P$2) -> 0.72 | T22: =R22+S22 -> 2.2938 | U22: 2.01 | W22: =IFERROR(#REF!*J22,"") | X22: =IFERROR(K22*J22,"") -> 0 | Y22: =IFERROR(+L22*J22,"") -> 0 | Z22: =IFERROR(+M22*J22,"") -> 0 | AA22: =IFERROR(+N22*J22,"") -> 0 | AB22: =IFERROR(O22*$J22,"") -> 0 | AC22: =IFERROR(P22*$J22,"") -> 0 | AD22: =IFERROR(+Q22*J22,"") -> 0 | AF22: =IFERROR(W22*'FlightConfig '!$K$3,"") | AG22: =IFERROR(X22*'FlightConfig '!$K$23,"") -> 0 | AH22: =IFERROR(Y22*'FlightConfig '!$K$23,"") -> 0 | AI22: =IFERROR(Z22*'FlightConfig '!$K$23,"") -> 0 | AJ22: =IFERROR(AA22*'FlightConfig '!$K$23,"") -> 0 | AK22: =IFERROR(AB22*'FlightConfig '!$K$23,"") -> 0
A23: BUSINESS CLASS | B23: 1 | C23: =CONCATENATE(A23&B23&F23) -> BUSINESS CLASS1110 | E23: 1243 | F23: 110 | G23: =VLOOKUP(E23,'FG MASTER'!$A:$AB,2,0) -> 2026 BC CY1 HOT DESSERT 2 CHOCOLATE SOUFFLE CAKE, VANILLA ICE CREAM SESAME CRUCH | H23: 1 | I23: 0 | J23: =IFERROR(IF(I23="std",H23,HLOOKUP(A23,'FlightConfig '!$B$34:$G$35,2,0)*I23),"") -> 0 | K23: =VLOOKUP(Food!E23,'FG MASTER'!$A$1:$AC$737,16,0) -> 1.42 | L23: =VLOOKUP(Food!E23,'FG MASTER'!$A$10:$AC$737,17,0) -> 1.75 | M23: =IFERROR(L23*$M$2,"") -> 0.7 | N23: =IFERROR((K23)+M23,"") -> 2.12 | O23: =IFERROR($K23*(1+$O$2)-$K23,0) -> 0.3124 | P23: =IFERROR($M23*(1+$P$2)-$M23,0) -> 0.14 | Q23: =SUM(N23:P23) -> 2.5724 | R23: =K23*(1+$O$2) -> 1.7324 | S23: =M23*(1+$P$2) -> 0.84 | T23: =R23+S23 -> 2.5724 | W23: =IFERROR(#REF!*J23,"") | X23: =IFERROR(K23*J23,"") -> 0 | Y23: =IFERROR(+L23*J23,"") -> 0 | Z23: =IFERROR(+M23*J23,"") -> 0 | AA23: =IFERROR(+N23*J23,"") -> 0 | AB23: =IFERROR(O23*$J23,"") -> 0 | AC23: =IFERROR(P23*$J23,"") -> 0 | AD23: =IFERROR(+Q23*J23,"") -> 0 | AF23: =IFERROR(W23*'FlightConfig '!$K$3,"") | AG23: =IFERROR(X23*'FlightConfig '!$K$23,"") -> 0 | AH23: =IFERROR(Y23*'FlightConfig '!$K$23,"") -> 0 | AI23: =IFERROR(Z23*'FlightConfig '!$K$23,"") -> 0 | AJ23: =IFERROR(AA23*'FlightConfig '!$K$23,"") -> 0 | AK23: =IFERROR(AB23*'FlightConfig '!$K$23,"") -> 0
A24: BUSINESS CLASS | B24: 1 | C24: =CONCATENATE(A24&B24&F24) -> BUSINESS CLASS1110 | E24: 1244 | F24: 110 | G24: =VLOOKUP(E24,'FG MASTER'!$A:$AB,2,0) -> 2026 BC CY1 CHEESE PLATE | H24: 1 | I24: 0.5 | J24: =IFERROR(IF(I24="std",H24,HLOOKUP(A24,'FlightConfig '!$B$34:$G$35,2,0)*I24),"") -> 15 | K24: =VLOOKUP(Food!E24,'FG MASTER'!$A$1:$AC$737,16,0) -> 4.02 | L24: =VLOOKUP(Food!E24,'FG MASTER'!$A$10:$AC$737,17,0) -> 2.5 | M24: =IFERROR(L24*$M$2,"") -> 1 | N24: =IFERROR((K24)+M24,"") -> 5.02 | O24: =IFERROR($K24*(1+$O$2)-$K24,0) -> 0.8844 | P24: =IFERROR($M24*(1+$P$2)-$M24,0) -> 0.2 | Q24: =SUM(N24:P24) -> 6.1044 | R24: =K24*(1+$O$2) -> 4.9044 | S24: =M24*(1+$P$2) -> 1.2 | T24: =R24+S24 -> 6.1044 | U24: 6.23 | W24: =IFERROR(#REF!*J24,"") | X24: =IFERROR(K24*J24,"") -> 60.3 | Y24: =IFERROR(+L24*J24,"") -> 37.5 | Z24: =IFERROR(+M24*J24,"") -> 15 | AA24: =IFERROR(+N24*J24,"") -> 75.3 | AB24: =IFERROR(O24*$J24,"") -> 13.266 | AC24: =IFERROR(P24*$J24,"") -> 3 | AD24: =IFERROR(+Q24*J24,"") -> 91.566 | AF24: =IFERROR(W24*'FlightConfig '!$K$3,"") | AG24: =IFERROR(X24*'FlightConfig '!$K$23,"") -> 21949.2 | AH24: =IFERROR(Y24*'FlightConfig '!$K$23,"") -> 13650 | AI24: =IFERROR(Z24*'FlightConfig '!$K$23,"") -> 5460 | AJ24: =IFERROR(AA24*'FlightConfig '!$K$23,"") -> 27409.2 | AK24: =IFERROR(AB24*'FlightConfig '!$K$23,"") -> 4828.824
A25: BUSINESS CLASS | B25: 1 | C25: =CONCATENATE(A25&B25&F25) -> BUSINESS CLASS1110 | E25: 1209 | F25: 110 | G25: =VLOOKUP(E25,'FG MASTER'!$A:$AB,2,0) -> BC C2 CRACKER BULK LOAD | H25: 1 | I25: =1/12 -> 0.083333333 | J25: =IFERROR(IF(I25="std",H25,HLOOKUP(A25,'FlightConfig '!$B$34:$G$35,2,0)*I25),"") -> 2.5 | K25: =VLOOKUP(Food!E25,'FG MASTER'!$A$1:$AC$737,16,0) -> 1.5333 | L25: =VLOOKUP(Food!E25,'FG MASTER'!$A$10:$AC$737,17,0) -> 0.25 | M25: =IFERROR(L25*$M$2,"") -> 0.1 | N25: =IFERROR((K25)+M25,"") -> 1.6333 | O25: =IFERROR($K25*(1+$O$2)-$K25,0) -> 0.337326 | P25: =IFERROR($M25*(1+$P$2)-$M25,0) -> 0.02 | Q25: =SUM(N25:P25) -> 1.990626 | R25: =K25*(1+$O$2) -> 1.870626 | S25: =M25*(1+$P$2) -> 0.12 | T25: =R25+S25 -> 1.990626 | W25: =IFERROR(#REF!*J25,"") | X25: =IFERROR(K25*J25,"") -> 3.83325 | Y25: =IFERROR(+L25*J25,"") -> 0.625 | Z25: =IFERROR(+M25*J25,"") -> 0.25 | AA25: =IFERROR(+N25*J25,"") -> 4.08325 | AB25: =IFERROR(O25*$J25,"") -> 0.843315 | AC25: =IFERROR(P25*$J25,"") -> 0.05 | AD25: =IFERROR(+Q25*J25,"") -> 4.976565 | AF25: =IFERROR(W25*'FlightConfig '!$K$3,"") | AG25: =IFERROR(X25*'FlightConfig '!$K$23,"") -> 1395.303 | AH25: =IFERROR(Y25*'FlightConfig '!$K$23,"") -> 227.5 | AI25: =IFERROR(Z25*'FlightConfig '!$K$23,"") -> 91 | AJ25: =IFERROR(AA25*'FlightConfig '!$K$23,"") -> 1486.303 | AK25: =IFERROR(AB25*'FlightConfig '!$K$23,"") -> 306.96666
A26: BUSINESS CLASS | B26: 1 | C26: =CONCATENATE(A26&B26&F26) -> BUSINESS CLASS1110 | E26: 1245 | F26: 110 | G26: =VLOOKUP(E26,'FG MASTER'!$A:$AB,2,0) -> 2026 BC CY1 WHOLE FRUIT PLATE | H26: 1 | I26: STD | J26: =IFERROR(IF(I26="std",H26,HLOOKUP(A26,'FlightConfig '!$B$34:$G$35,2,0)*I26),"") -> 1 | K26: =VLOOKUP(Food!E26,'FG MASTER'!$A$1:$AC$737,16,0) -> 8.396 | L26: =VLOOKUP(Food!E26,'FG MASTER'!$A$10:$AC$737,17,0) -> 0.75 | M26: =IFERROR(L26*$M$2,"") -> 0.3 | N26: =IFERROR((K26)+M26,"") -> 8.696 | O26: =IFERROR($K26*(1+$O$2)-$K26,0) -> 1.84712 | P26: =IFERROR($M26*(1+$P$2)-$M26,0) -> 0.06 | Q26: =SUM(N26:P26) -> 10.60312 | R26: 9.66 | S26: 0.92 | T26: =R26+S26 -> 10.58 | W26: =IFERROR(#REF!*J26,"") | X26: =IFERROR(K26*J26,"") -> 8.396 | Y26: =IFERROR(+L26*J26,"") -> 0.75 | Z26: =IFERROR(+M26*J26,"") -> 0.3 | AA26: =IFERROR(+N26*J26,"") -> 8.696 | AB26: =IFERROR(O26*$J26,"") -> 1.84712 | AC26: =IFERROR(P26*$J26,"") -> 0.06 | AD26: =IFERROR(+Q26*J26,"") -> 10.60312 | AF26: =IFERROR(W26*'FlightConfig '!$K$3,"") | AG26: =IFERROR(X26*'FlightConfig '!$K$23,"") -> 3056.144 | AH26: =IFERROR(Y26*'FlightConfig '!$K$23,"") -> 273 | AI26: =IFERROR(Z26*'FlightConfig '!$K$23,"") -> 109.2 | AJ26: =IFERROR(AA26*'FlightConfig '!$K$23,"") -> 3165.344 | AK26: =IFERROR(AB26*'FlightConfig '!$K$23,"") -> 672.35168
A27: BUSINESS CLASS | B27: 1 | C27: =CONCATENATE(A27&B27&F27) -> BUSINESS CLASS1110 | E27: 1206 | F27: 110 | G27: =VLOOKUP(E27,'FG MASTER'!$A:$AB,2,0) -> BC BREAKFAST TRAY SET UP | H27: 1 | I27: 0.8 | J27: =IFERROR(IF(I27="std",H27,HLOOKUP(A27,'FlightConfig '!$B$34:$G$35,2,0)*I27),"") -> 24 | K27: =VLOOKUP(Food!E27,'FG MASTER'!$A$1:$AC$737,16,0) -> 0 | L27: =VLOOKUP(Food!E27,'FG MASTER'!$A$10:$AC$737,17,0) -> 1.65 | M27: =IFERROR(L27*$M$2,"") -> 0.66 | N27: =IFERROR((K27)+M27,"") -> 0.66 | O27: =IFERROR($K27*(1+$O$2)-$K27,0) -> 0 | P27: =IFERROR($M27*(1+$P$2)-$M27,0) -> 0.132 | Q27: =SUM(N27:P27) -> 0.792 | R27: =K27*(1+$O$2) -> 0 | S27: =M27*(1+$P$2) -> 0.792 | T27: =R27+S27 -> 0.792 | W27: =IFERROR(#REF!*J27,"") | X27: =IFERROR(K27*J27,"") -> 0 | Y27: =IFERROR(+L27*J27,"") -> 39.6 | Z27: =IFERROR(+M27*J27,"") -> 15.84 | AA27: =IFERROR(+N27*J27,"") -> 15.84 | AB27: =IFERROR(O27*$J27,"") -> 0 | AC27: =IFERROR(P27*$J27,"") -> 3.168 | AD27: =IFERROR(+Q27*J27,"") -> 19.008 | AF27: =IFERROR(W27*'FlightConfig '!$K$3,"") | AG27: =IFERROR(X27*'FlightConfig '!$K$23,"") -> 0 | AH27: =IFERROR(Y27*'FlightConfig '!$K$23,"") -> 14414.4 | AI27: =IFERROR(Z27*'FlightConfig '!$K$23,"") -> 5765.76 | AJ27: =IFERROR(AA27*'FlightConfig '!$K$23,"") -> 5765.76 | AK27: =IFERROR(AB27*'FlightConfig '!$K$23,"") -> 0
A28: BUSINESS CLASS | B28: 1 | C28: =CONCATENATE(A28&B28&F28) -> BUSINESS CLASS1110 | E28: 1206 | F28: 110 | G28: =VLOOKUP(E28,'FG MASTER'!$A:$AB,2,0) -> BC BREAKFAST TRAY SET UP | H28: 1 | I28: 0.2 | J28: =IFERROR(IF(I28="std",H28,HLOOKUP(A28,'FlightConfig '!$B$34:$G$35,2,0)*I28),"") -> 6 | K28: =VLOOKUP(Food!E28,'FG MASTER'!$A$1:$AC$737,16,0) -> 0 | L28: =VLOOKUP(Food!E28,'FG MASTER'!$A$10:$AC$737,17,0) -> 1.65 | M28: =IFERROR(L28*$M$2,"") -> 0.66 | N28: =IFERROR((K28)+M28,"") -> 0.66 | O28: =IFERROR($K28*(1+$O$2)-$K28,0) -> 0 | P28: =IFERROR($M28*(1+$P$2)-$M28,0) -> 0.132 | Q28: =SUM(N28:P28) -> 0.792 | R28: =K28*(1+$O$2) -> 0 | S28: =M28*(1+$P$2) -> 0.792 | T28: =R28+S28 -> 0.792 | W28: =IFERROR(#REF!*J28,"") | X28: =IFERROR(K28*J28,"") -> 0 | Y28: =IFERROR(+L28*J28,"") -> 9.9 | Z28: =IFERROR(+M28*J28,"") -> 3.96 | AA28: =IFERROR(+N28*J28,"") -> 3.96 | AB28: =IFERROR(O28*$J28,"") -> 0 | AC28: =IFERROR(P28*$J28,"") -> 0.792 | AD28: =IFERROR(+Q28*J28,"") -> 4.752 | AF28: =IFERROR(W28*'FlightConfig '!$K$3,"") | AG28: =IFERROR(X28*'FlightConfig '!$K$23,"") -> 0 | AH28: =IFERROR(Y28*'FlightConfig '!$K$23,"") -> 3603.6 | AI28: =IFERROR(Z28*'FlightConfig '!$K$23,"") -> 1441.44 | AJ28: =IFERROR(AA28*'FlightConfig '!$K$23,"") -> 1441.44 | AK28: =IFERROR(AB28*'FlightConfig '!$K$23,"") -> 0
A29: BUSINESS CLASS | B29: 1 | C29: =CONCATENATE(A29&B29&F29) -> BUSINESS CLASS1110 | E29: 1246 | F29: 110 | G29: =VLOOKUP(E29,'FG MASTER'!$A:$AB,2,0) -> 2026 BC CY1 BRK COLD PLATE NOVA CURED SALMON | H29: 1 | I29: 0.2 | J29: =IFERROR(IF(I29="std",H29,HLOOKUP(A29,'FlightConfig '!$B$34:$G$35,2,0)*I29),"") -> 6 | K29: =VLOOKUP(Food!E29,'FG MASTER'!$A$1:$AC$737,16,0) -> 2.9 | L29: =VLOOKUP(Food!E29,'FG MASTER'!$A$10:$AC$737,17,0) -> 3 | M29: =IFERROR(L29*$M$2,"") -> 1.2 | N29: =IFERROR((K29)+M29,"") -> 4.1 | O29: =IFERROR($K29*(1+$O$2)-$K29,0) -> 0.638 | P29: =IFERROR($M29*(1+$P$2)-$M29,0) -> 0.24 | Q29: =SUM(N29:P29) -> 4.978 | R29: =K29*(1+$O$2) -> 3.538 | S29: =M29*(1+$P$2) -> 1.44 | T29: =R29+S29 -> 4.978 | W29: =IFERROR(#REF!*J29,"") | X29: =IFERROR(K29*J29,"") -> 17.4 | Y29: =IFERROR(+L29*J29,"") -> 18 | Z29: =IFERROR(+M29*J29,"") -> 7.2 | AA29: =IFERROR(+N29*J29,"") -> 24.6 | AB29: =IFERROR(O29*$J29,"") -> 3.828 | AC29: =IFERROR(P29*$J29,"") -> 1.44 | AD29: =IFERROR(+Q29*J29,"") -> 29.868 | AF29: =IFERROR(W29*'FlightConfig '!$K$3,"") | AG29: =IFERROR(X29*'FlightConfig '!$K$23,"") -> 6333.6 | AH29: =IFERROR(Y29*'FlightConfig '!$K$23,"") -> 6552 | AI29: =IFERROR(Z29*'FlightConfig '!$K$23,"") -> 2620.8 | AJ29: =IFERROR(AA29*'FlightConfig '!$K$23,"") -> 8954.4 | AK29: =IFERROR(AB29*'FlightConfig '!$K$23,"") -> 1393.392
A30: BUSINESS CLASS | B30: 1 | C30: =CONCATENATE(A30&B30&F30) -> BUSINESS CLASS1110 | E30: 1247 | F30: 110 | G30: =VLOOKUP(E30,'FG MASTER'!$A:$AB,2,0) -> 2026 BC CY1 BRK HHH ENGLEMANS ROLL, SPOTTED TROTTER - BACON, HP SAUCE | H30: 1 | I30: 0.6 | J30: =IFERROR(IF(I30="std",H30,HLOOKUP(A30,'FlightConfig '!$B$34:$G$35,2,0)*I30),"") -> 18 | K30: =VLOOKUP(Food!E30,'FG MASTER'!$A$1:$AC$737,16,0) -> 1.97 | L30: =VLOOKUP(Food!E30,'FG MASTER'!$A$10:$AC$737,17,0) -> 2.12 | M30: =IFERROR(L30*$M$2,"") -> 0.848 | N30: =IFERROR((K30)+M30,"") -> 2.818 | O30: =IFERROR($K30*(1+$O$2)-$K30,0) -> 0.4334 | P30: =IFERROR($M30*(1+$P$2)-$M30,0) -> 0.1696 | Q30: =SUM(N30:P30) -> 3.421 | R30: =K30*(1+$O$2) -> 2.4034 | S30: =M30*(1+$P$2) -> 1.0176 | T30: =R30+S30 -> 3.421 | U30: 3.42 | W30: =IFERROR(#REF!*J30,"") | X30: =IFERROR(K30*J30,"") -> 35.46 | Y30: =IFERROR(+L30*J30,"") -> 38.16 | Z30: =IFERROR(+M30*J30,"") -> 15.264 | AA30: =IFERROR(+N30*J30,"") -> 50.724 | AB30: =IFERROR(O30*$J30,"") -> 7.8012 | AC30: =IFERROR(P30*$J30,"") -> 3.0528 | AD30: =IFERROR(+Q30*J30,"") -> 61.578 | AF30: =IFERROR(W30*'FlightConfig '!$K$3,"") | AG30: =IFERROR(X30*'FlightConfig '!$K$23,"") -> 12907.44 | AH30: =IFERROR(Y30*'FlightConfig '!$K$23,"") -> 13890.24 | AI30: =IFERROR(Z30*'FlightConfig '!$K$23,"") -> 5556.096 | AJ30: =IFERROR(AA30*'FlightConfig '!$K$23,"") -> 18463.536 | AK30: =IFERROR(AB30*'FlightConfig '!$K$23,"") -> 2839.6368
A31: BUSINESS CLASS | B31: 1 | C31: =CONCATENATE(A31&B31&F31) -> BUSINESS CLASS1110 | E31: 1248 | F31: 110 | G31: =VLOOKUP(E31,'FG MASTER'!$A:$AB,2,0) -> 2026 BC CY1 BRK HHH CIABATTA, EGG PATTY, SUN DRIED TOMATO PESTO, SPINACH, SWISS CHEESE | H31: 1 | I31: 0.4 | J31: =IFERROR(IF(I31="std",H31,HLOOKUP(A31,'FlightConfig '!$B$34:$G$35,2,0)*I31),"") -> 12 | K31: =VLOOKUP(Food!E31,'FG MASTER'!$A$1:$AC$737,16,0) -> 1.39 | L31: =VLOOKUP(Food!E31,'FG MASTER'!$A$10:$AC$737,17,0) -> 2 | M31: =IFERROR(L31*$M$2,"") -> 0.8 | N31: =IFERROR((K31)+M31,"") -> 2.19 | O31: =IFERROR($K31*(1+$O$2)-$K31,0) -> 0.3058 | P31: =IFERROR($M31*(1+$P$2)-$M31,0) -> 0.16 | Q31: =SUM(N31:P31) -> 2.6558 | R31: =K31*(1+$O$2) -> 1.6958 | S31: =M31*(1+$P$2) -> 0.96 | T31: =R31+S31 -> 2.6558 | U31: 2.85 | W31: =IFERROR(#REF!*J31,"") | X31: =IFERROR(K31*J31,"") -> 16.68 | Y31: =IFERROR(+L31*J31,"") -> 24 | Z31: =IFERROR(+M31*J31,"") -> 9.6 | AA31: =IFERROR(+N31*J31,"") -> 26.28 | AB31: =IFERROR(O31*$J31,"") -> 3.6696 | AC31: =IFERROR(P31*$J31,"") -> 1.92 | AD31: =IFERROR(+Q31*J31,"") -> 31.8696 | AF31: =IFERROR(W31*'FlightConfig '!$K$3,"") | AG31: =IFERROR(X31*'FlightConfig '!$K$23,"") -> 6071.52 | AH31: =IFERROR(Y31*'FlightConfig '!$K$23,"") -> 8736 | AI31: =IFERROR(Z31*'FlightConfig '!$K$23,"") -> 3494.4 | AJ31: =IFERROR(AA31*'FlightConfig '!$K$23,"") -> 9565.92 | AK31: =IFERROR(AB31*'FlightConfig '!$K$23,"") -> 1335.7344
A32: BUSINESS CLASS | B32: 1 | C32: =CONCATENATE(A32&B32&F32) -> BUSINESS CLASS1110 | E32: 1250 | F32: 110 | G32: =VLOOKUP(E32,'FG MASTER'!$A:$AB,2,0) -> 2026 BC CY1 BRK LAYERED YOGURT | H32: 1 | I32: 1 | J32: =IFERROR(IF(I32="std",H32,HLOOKUP(A32,'FlightConfig '!$B$34:$G$35,2,0)*I32),"") -> 30 | K32: =VLOOKUP(Food!E32,'FG MASTER'!$A$1:$AC$737,16,0) -> 0.99 | L32: =VLOOKUP(Food!E32,'FG MASTER'!$A$10:$AC$737,17,0) -> 1.25 | M32: =IFERROR(L32*$M$2,"") -> 0.5 | N32: =IFERROR((K32)+M32,"") -> 1.49 | O32: =IFERROR($K32*(1+$O$2)-$K32,0) -> 0.2178 | P32: =IFERROR($M32*(1+$P$2)-$M32,0) -> 0.1 | Q32: =SUM(N32:P32) -> 1.8078 | R32: =K32*(1+$O$2) -> 1.2078 | S32: =M32*(1+$P$2) -> 0.6 | T32: =R32+S32 -> 1.8078 | W32: =IFERROR(#REF!*J32,"") | X32: =IFERROR(K32*J32,"") -> 29.7 | Y32: =IFERROR(+L32*J32,"") -> 37.5 | Z32: =IFERROR(+M32*J32,"") -> 15 | AA32: =IFERROR(+N32*J32,"") -> 44.7 | AB32: =IFERROR(O32*$J32,"") -> 6.534 | AC32: =IFERROR(P32*$J32,"") -> 3 | AD32: =IFERROR(+Q32*J32,"") -> 54.234 | AF32: =IFERROR(W32*'FlightConfig '!$K$3,"") | AG32: =IFERROR(X32*'FlightConfig '!$K$23,"") -> 10810.8 | AH32: =IFERROR(Y32*'FlightConfig '!$K$23,"") -> 13650 | AI32: =IFERROR(Z32*'FlightConfig '!$K$23,"") -> 5460 | AJ32: =IFERROR(AA32*'FlightConfig '!$K$23,"") -> 16270.8 | AK32: =IFERROR(AB32*'FlightConfig '!$K$23,"") -> 2378.376
A33: BUSINESS CLASS | B33: 1 | C33: =CONCATENATE(A33&B33&F33) -> BUSINESS CLASS1110 | E33: 1179 | F33: 110 | G33: =VLOOKUP(E33,'FG MASTER'!$A:$AB,2,0) -> BC C2 BRK SIDE ITEM MINI JAM JAR | H33: 1 | I33: 1 | J33: =IFERROR(IF(I33="std",H33,HLOOKUP(A33,'FlightConfig '!$B$34:$G$35,2,0)*I33),"") -> 30 | K33: =VLOOKUP(Food!E33,'FG MASTER'!$A$1:$AC$737,16,0) -> 0.4272449 | L33: =VLOOKUP(Food!E33,'FG MASTER'!$A$10:$AC$737,17,0) -> 0.25 | M33: =IFERROR(L33*$M$2,"") -> 0.1 | N33: =IFERROR((K33)+M33,"") -> 0.5272449 | O33: =IFERROR($K33*(1+$O$2)-$K33,0) -> 0.093993878 | P33: =IFERROR($M33*(1+$P$2)-$M33,0) -> 0.02 | Q33: =SUM(N33:P33) -> 0.64123878 | R33: =K33*(1+$O$2) -> 0.52123878 | S33: =M33*(1+$P$2) -> 0.12 | T33: =R33+S33 -> 0.64123878 | W33: =IFERROR(#REF!*J33,"") | X33: =IFERROR(K33*J33,"") -> 12.817347 | Y33: =IFERROR(+L33*J33,"") -> 7.5 | Z33: =IFERROR(+M33*J33,"") -> 3 | AA33: =IFERROR(+N33*J33,"") -> 15.817347 | AB33: =IFERROR(O33*$J33,"") -> 2.8198163 | AC33: =IFERROR(P33*$J33,"") -> 0.6 | AD33: =IFERROR(+Q33*J33,"") -> 19.237163 | AF33: =IFERROR(W33*'FlightConfig '!$K$3,"") | AG33: =IFERROR(X33*'FlightConfig '!$K$23,"") -> 4665.5143 | AH33: =IFERROR(Y33*'FlightConfig '!$K$23,"") -> 2730 | AI33: =IFERROR(Z33*'FlightConfig '!$K$23,"") -> 1092 | AJ33: =IFERROR(AA33*'FlightConfig '!$K$23,"") -> 5757.5143 | AK33: =IFERROR(AB33*'FlightConfig '!$K$23,"") -> 1026.4131
A34: BUSINESS CLASS | B34: 1 | C34: =CONCATENATE(A34&B34&F34) -> BUSINESS CLASS1110 | E34: 1174 | F34: 110 | G34: =VLOOKUP(E34,'FG MASTER'!$A:$AB,2,0) -> BC C2 BRK PASTRIES - CROISSANT | H34: 1 | I34: 1 | J34: =IFERROR(IF(I34="std",H34,HLOOKUP(A34,'FlightConfig '!$B$34:$G$35,2,0)*I34),"") -> 30 | K34: =VLOOKUP(Food!E34,'FG MASTER'!$A$1:$AC$737,16,0) -> 1.2553338 | L34: =VLOOKUP(Food!E34,'FG MASTER'!$A$10:$AC$737,17,0) -> 0.5 | M34: =IFERROR(L34*$M$2,"") -> 0.2 | N34: =IFERROR((K34)+M34,"") -> 1.4553338 | O34: =IFERROR($K34*(1+$O$2)-$K34,0) -> 0.27617345 | P34: =IFERROR($M34*(1+$P$2)-$M34,0) -> 0.04 | Q34: =SUM(N34:P34) -> 1.7715073 | R34: =K34*(1+$O$2) -> 1.5315073 | S34: =M34*(1+$P$2) -> 0.24 | T34: =R34+S34 -> 1.7715073 | W34: =IFERROR(#REF!*J34,"") | X34: =IFERROR(K34*J34,"") -> 37.660015 | Y34: =IFERROR(+L34*J34,"") -> 15 | Z34: =IFERROR(+M34*J34,"") -> 6 | AA34: =IFERROR(+N34*J34,"") -> 43.660015 | AB34: =IFERROR(O34*$J34,"") -> 8.2852034 | AC34: =IFERROR(P34*$J34,"") -> 1.2 | AD34: =IFERROR(+Q34*J34,"") -> 53.145219 | AF34: =IFERROR(W34*'FlightConfig '!$K$3,"") | AG34: =IFERROR(X34*'FlightConfig '!$K$23,"") -> 13708.246 | AH34: =IFERROR(Y34*'FlightConfig '!$K$23,"") -> 5460 | AI34: =IFERROR(Z34*'FlightConfig '!$K$23,"") -> 2184 | AJ34: =IFERROR(AA34*'FlightConfig '!$K$23,"") -> 15892.246 | AK34: =IFERROR(AB34*'FlightConfig '!$K$23,"") -> 3015.814
A35: BUSINESS CLASS | B35: 1 | C35: =CONCATENATE(A35&B35&F35) -> BUSINESS CLASS1110 | E35: 1204 | F35: 110 | G35: =VLOOKUP(E35,'FG MASTER'!$A:$AB,2,0) -> BC C2 GARNISH GRAPEFRUIT SEGMENT 20CT | H35: 1 | I35: STD | J35: =IFERROR(IF(I35="std",H35,HLOOKUP(A35,'FlightConfig '!$B$34:$G$35,2,0)*I35),"") -> 1 | K35: =VLOOKUP(Food!E35,'FG MASTER'!$A$1:$AC$737,16,0) -> 4.98825 | L35: =VLOOKUP(Food!E35,'FG MASTER'!$A$10:$AC$737,17,0) -> 0.5 | M35: =IFERROR(L35*$M$2,"") -> 0.2 | N35: =IFERROR((K35)+M35,"") -> 5.18825 | O35: =IFERROR($K35*(1+$O$2)-$K35,0) -> 1.097415 | P35: =IFERROR($M35*(1+$P$2)-$M35,0) -> 0.04 | Q35: =SUM(N35:P35) -> 6.325665 | R35: =K35*(1+$O$2) -> 6.085665 | S35: =M35*(1+$P$2) -> 0.24 | T35: =R35+S35 -> 6.325665 | W35: =IFERROR(#REF!*J35,"") | X35: =IFERROR(K35*J35,"") -> 4.98825 | Y35: =IFERROR(+L35*J35,"") -> 0.5 | Z35: =IFERROR(+M35*J35,"") -> 0.2 | AA35: =IFERROR(+N35*J35,"") -> 5.18825 | AB35: =IFERROR(O35*$J35,"") -> 1.097415 | AC35: =IFERROR(P35*$J35,"") -> 0.04 | AD35: =IFERROR(+Q35*J35,"") -> 6.325665 | AF35: =IFERROR(W35*'FlightConfig '!$K$3,"") | AG35: =IFERROR(X35*'FlightConfig '!$K$23,"") -> 1815.723 | AH35: =IFERROR(Y35*'FlightConfig '!$K$23,"") -> 182 | AI35: =IFERROR(Z35*'FlightConfig '!$K$23,"") -> 72.8 | AJ35: =IFERROR(AA35*'FlightConfig '!$K$23,"") -> 1888.523 | AK35: =IFERROR(AB35*'FlightConfig '!$K$23,"") -> 399.45906
A36: PREMIUM ECONOMY CLASS | B36: 1 | C36: =CONCATENATE(A36&B36&F36) -> PREMIUM ECONOMY CLASS1110 | E36: 1111 | F36: 110 | G36: =VLOOKUP(E36,'FG MASTER'!$A:$AB,2,0) -> PY C1 DINNER TSU | H36: 1 | I36: 1 | J36: =IFERROR(IF(I36="std",H36,HLOOKUP(A36,'FlightConfig '!$B$34:$G$35,2,0)*I36),"") -> 44 | K36: =VLOOKUP(Food!E36,'FG MASTER'!$A$1:$AC$737,16,0) -> 0 | L36: =VLOOKUP(Food!E36,'FG MASTER'!$A$10:$AC$737,17,0) -> 1.5 | M36: =IFERROR(L36*$M$2,"") -> 0.6 | N36: =IFERROR((K36)+M36,"") -> 0.6 | O36: =IFERROR($K36*(1+$O$2)-$K36,0) -> 0 | P36: =IFERROR($M36*(1+$P$2)-$M36,0) -> 0.12 | Q36: =SUM(N36:P36) -> 0.72 | R36: =K36*(1+$O$2) -> 0 | S36: =M36*(1+$P$2) -> 0.72 | T36: =R36+S36 -> 0.72 | U36: 7.39 | W36: =IFERROR(#REF!*J36,"") | X36: =IFERROR(K36*J36,"") -> 0 | Y36: =IFERROR(+L36*J36,"") -> 66 | Z36: =IFERROR(+M36*J36,"") -> 26.4 | AA36: =IFERROR(+N36*J36,"") -> 26.4 | AB36: =IFERROR(O36*$J36,"") -> 0 | AC36: =IFERROR(P36*$J36,"") -> 5.28 | AD36: =IFERROR(+Q36*J36,"") -> 31.68 | AF36: =IFERROR(W36*'FlightConfig '!$K$3,"") | AG36: =IFERROR(X36*'FlightConfig '!$K$23,"") -> 0 | AH36: =IFERROR(Y36*'FlightConfig '!$K$23,"") -> 24024 | AI36: =IFERROR(Z36*'FlightConfig '!$K$23,"") -> 9609.6 | AJ36: =IFERROR(AA36*'FlightConfig '!$K$23,"") -> 9609.6 | AK36: =IFERROR(AB36*'FlightConfig '!$K$23,"") -> 0
A37: PREMIUM ECONOMY CLASS | B37: 1 | C37: =CONCATENATE(A37&B37&F37) -> PREMIUM ECONOMY CLASS1110 | E37: 1227 | F37: 110 | G37: =VLOOKUP(E37,'FG MASTER'!$A:$AB,2,0) -> 2026 BC CY1 HAWAIIAN ROLL | H37: 1 | I37: 1 | J37: =IFERROR(IF(I37="std",H37,HLOOKUP(A37,'FlightConfig '!$B$34:$G$35,2,0)*I37),"") -> 44 | K37: =VLOOKUP(Food!E37,'FG MASTER'!$A$1:$AC$737,16,0) -> 0.24 | L37: =VLOOKUP(Food!E37,'FG MASTER'!$A$10:$AC$737,17,0) -> 0.25 | M37: =IFERROR(L37*$M$2,"") -> 0.1 | N37: =IFERROR((K37)+M37,"") -> 0.34 | O37: =IFERROR($K37*(1+$O$2)-$K37,0) -> 0.0528 | P37: =IFERROR($M37*(1+$P$2)-$M37,0) -> 0.02 | Q37: =SUM(N37:P37) -> 0.4128 | R37: =K37*(1+$O$2) -> 0.2928 | S37: =M37*(1+$P$2) -> 0.12 | T37: =R37+S37 -> 0.4128 | W37: =IFERROR(#REF!*J37,"") | X37: =IFERROR(K37*J37,"") -> 10.56 | Y37: =IFERROR(+L37*J37,"") -> 11 | Z37: =IFERROR(+M37*J37,"") -> 4.4 | AA37: =IFERROR(+N37*J37,"") -> 14.96 | AB37: =IFERROR(O37*$J37,"") -> 2.3232 | AC37: =IFERROR(P37*$J37,"") -> 0.88 | AD37: =IFERROR(+Q37*J37,"") -> 18.1632 | AF37: =IFERROR(W37*'FlightConfig '!$K$3,"") | AG37: =IFERROR(X37*'FlightConfig '!$K$23,"") -> 3843.84 | AH37: =IFERROR(Y37*'FlightConfig '!$K$23,"") -> 4004 | AI37: =IFERROR(Z37*'FlightConfig '!$K$23,"") -> 1601.6 | AJ37: =IFERROR(AA37*'FlightConfig '!$K$23,"") -> 5445.44 | AK37: =IFERROR(AB37*'FlightConfig '!$K$23,"") -> 845.6448
A38: PREMIUM ECONOMY CLASS | B38: 1 | C38: =CONCATENATE(A38&B38&F38) -> PREMIUM ECONOMY CLASS1110 | E38: 1113 | F38: 110 | G38: =VLOOKUP(E38,'FG MASTER'!$A:$AB,2,0) -> PY C1 DINNER BUTTER | H38: 1 | I38: 1 | J38: =IFERROR(IF(I38="std",H38,HLOOKUP(A38,'FlightConfig '!$B$34:$G$35,2,0)*I38),"") -> 44 | K38: =VLOOKUP(Food!E38,'FG MASTER'!$A$1:$AC$737,16,0) -> 0.3 | L38: =VLOOKUP(Food!E38,'FG MASTER'!$A$10:$AC$737,17,0) -> 0.25 | M38: =IFERROR(L38*$M$2,"") -> 0.1 | N38: =IFERROR((K38)+M38,"") -> 0.4 | O38: =IFERROR($K38*(1+$O$2)-$K38,0) -> 0.066 | P38: =IFERROR($M38*(1+$P$2)-$M38,0) -> 0.02 | Q38: =SUM(N38:P38) -> 0.486 | R38: =K38*(1+$O$2) -> 0.366 | S38: =M38*(1+$P$2) -> 0.12 | T38: =R38+S38 -> 0.486 | W38: =IFERROR(#REF!*J38,"") | X38: =IFERROR(K38*J38,"") -> 13.2 | Y38: =IFERROR(+L38*J38,"") -> 11 | Z38: =IFERROR(+M38*J38,"") -> 4.4 | AA38: =IFERROR(+N38*J38,"") -> 17.6 | AB38: =IFERROR(O38*$J38,"") -> 2.904 | AC38: =IFERROR(P38*$J38,"") -> 0.88 | AD38: =IFERROR(+Q38*J38,"") -> 21.384 | AF38: =IFERROR(W38*'FlightConfig '!$K$3,"") | AG38: =IFERROR(X38*'FlightConfig '!$K$23,"") -> 4804.8 | AH38: =IFERROR(Y38*'FlightConfig '!$K$23,"") -> 4004 | AI38: =IFERROR(Z38*'FlightConfig '!$K$23,"") -> 1601.6 | AJ38: =IFERROR(AA38*'FlightConfig '!$K$23,"") -> 6406.4 | AK38: =IFERROR(AB38*'FlightConfig '!$K$23,"") -> 1057.056
A39: PREMIUM ECONOMY CLASS | B39: 1 | C39: =CONCATENATE(A39&B39&F39) -> PREMIUM ECONOMY CLASS1110 | E39: 1225 | F39: 110 | G39: =VLOOKUP(E39,'FG MASTER'!$A:$AB,2,0) -> WATER 250ML (FROM MLCO | H39: 1 | I39: 1 | J39: =IFERROR(IF(I39="std",H39,HLOOKUP(A39,'FlightConfig '!$B$34:$G$35,2,0)*I39),"") -> 44 | K39: =VLOOKUP(Food!E39,'FG MASTER'!$A$1:$AC$737,16,0) -> 0.29363333 | L39: =VLOOKUP(Food!E39,'FG MASTER'!$A$10:$AC$737,17,0) -> 0.25 | M39: =IFERROR(L39*$M$2,"") -> 0.1 | N39: =IFERROR((K39)+M39,"") -> 0.39363333 | O39: =IFERROR($K39*(1+$O$2)-$K39,0) -> 0.064599333 | P39: =IFERROR($M39*(1+$P$2)-$M39,0) -> 0.02 | Q39: =SUM(N39:P39) -> 0.47823267 | R39: =K39*(1+$O$2) -> 0.35823267 | S39: =M39*(1+$P$2) -> 0.12 | T39: =R39+S39 -> 0.47823267 | W39: =IFERROR(#REF!*J39,"") | X39: =IFERROR(K39*J39,"") -> 12.919867 | Y39: =IFERROR(+L39*J39,"") -> 11 | Z39: =IFERROR(+M39*J39,"") -> 4.4 | AA39: =IFERROR(+N39*J39,"") -> 17.319867 | AB39: =IFERROR(O39*$J39,"") -> 2.8423707 | AC39: =IFERROR(P39*$J39,"") -> 0.88 | AD39: =IFERROR(+Q39*J39,"") -> 21.042237 | AF39: =IFERROR(W39*'FlightConfig '!$K$3,"") | AG39: =IFERROR(X39*'FlightConfig '!$K$23,"") -> 4702.8315 | AH39: =IFERROR(Y39*'FlightConfig '!$K$23,"") -> 4004 | AI39: =IFERROR(Z39*'FlightConfig '!$K$23,"") -> 1601.6 | AJ39: =IFERROR(AA39*'FlightConfig '!$K$23,"") -> 6304.4315 | AK39: =IFERROR(AB39*'FlightConfig '!$K$23,"") -> 1034.6229
A40: PREMIUM ECONOMY CLASS | B40: 1 | C40: =CONCATENATE(A40&B40&F40) -> PREMIUM ECONOMY CLASS1110 | E40: 1287 | F40: 110 | G40: =VLOOKUP(E40,'FG MASTER'!$A:$AB,2,0) -> 2026 PY DRESSING | H40: 1 | I40: 1 | J40: =IFERROR(IF(I40="std",H40,HLOOKUP(A40,'FlightConfig '!$B$34:$G$35,2,0)*I40),"") -> 44 | K40: =VLOOKUP(Food!E40,'FG MASTER'!$A$1:$AC$737,16,0) -> 0.15 | L40: =VLOOKUP(Food!E40,'FG MASTER'!$A$10:$AC$737,17,0) -> 0.15 | M40: =IFERROR(L40*$M$2,"") -> 0.06 | N40: =IFERROR((K40)+M40,"") -> 0.21 | O40: =IFERROR($K40*(1+$O$2)-$K40,0) -> 0.033 | P40: =IFERROR($M40*(1+$P$2)-$M40,0) -> 0.012 | Q40: =SUM(N40:P40) -> 0.255 | R40: =K40*(1+$O$2) -> 0.183 | S40: =M40*(1+$P$2) -> 0.072 | T40: =R40+S40 -> 0.255 | W40: =IFERROR(#REF!*J40,"") | X40: =IFERROR(K40*J40,"") -> 6.6 | Y40: =IFERROR(+L40*J40,"") -> 6.6 | Z40: =IFERROR(+M40*J40,"") -> 2.64 | AA40: =IFERROR(+N40*J40,"") -> 9.24 | AB40: =IFERROR(O40*$J40,"") -> 1.452 | AC40: =IFERROR(P40*$J40,"") -> 0.528 | AD40: =IFERROR(+Q40*J40,"") -> 11.22 | AF40: =IFERROR(W40*'FlightConfig '!$K$3,"") | AG40: =IFERROR(X40*'FlightConfig '!$K$23,"") -> 2402.4 | AH40: =IFERROR(Y40*'FlightConfig '!$K$23,"") -> 2402.4 | AI40: =IFERROR(Z40*'FlightConfig '!$K$23,"") -> 960.96 | AJ40: =IFERROR(AA40*'FlightConfig '!$K$23,"") -> 3363.36 | AK40: =IFERROR(AB40*'FlightConfig '!$K$23,"") -> 528.528
A41: PREMIUM ECONOMY CLASS | B41: 1 | C41: =CONCATENATE(A41&B41&F41) -> PREMIUM ECONOMY CLASS1110 | E41: 1251 | F41: 110 | G41: =VLOOKUP(E41,'FG MASTER'!$A:$AB,2,0) -> 2026 PY CY1 BABY GEM LETTUCE, FETA CHEESE, GRAPE TOMATO, PICKLED ONION | H41: 1 | I41: 1 | J41: =IFERROR(IF(I41="std",H41,HLOOKUP(A41,'FlightConfig '!$B$34:$G$35,2,0)*I41),"") -> 44 | K41: =VLOOKUP(Food!E41,'FG MASTER'!$A$1:$AC$737,16,0) -> 0.5 | L41: =VLOOKUP(Food!E41,'FG MASTER'!$A$10:$AC$737,17,0) -> 1 | M41: =IFERROR(L41*$M$2,"") -> 0.4 | N41: =IFERROR((K41)+M41,"") -> 0.9 | O41: =IFERROR($K41*(1+$O$2)-$K41,0) -> 0.11 | P41: =IFERROR($M41*(1+$P$2)-$M41,0) -> 0.08 | Q41: =SUM(N41:P41) -> 1.09 | R41: =K41*(1+$O$2) -> 0.61 | S41: =M41*(1+$P$2) -> 0.48 | T41: =R41+S41 -> 1.09 | W41: =IFERROR(#REF!*J41,"") | X41: =IFERROR(K41*J41,"") -> 22 | Y41: =IFERROR(+L41*J41,"") -> 44 | Z41: =IFERROR(+M41*J41,"") -> 17.6 | AA41: =IFERROR(+N41*J41,"") -> 39.6 | AB41: =IFERROR(O41*$J41,"") -> 4.84 | AC41: =IFERROR(P41*$J41,"") -> 3.52 | AD41: =IFERROR(+Q41*J41,"") -> 47.96 | AF41: =IFERROR(W41*'FlightConfig '!$K$3,"") | AG41: =IFERROR(X41*'FlightConfig '!$K$23,"") -> 8008 | AH41: =IFERROR(Y41*'FlightConfig '!$K$23,"") -> 16016 | AI41: =IFERROR(Z41*'FlightConfig '!$K$23,"") -> 6406.4 | AJ41: =IFERROR(AA41*'FlightConfig '!$K$23,"") -> 14414.4 | AK41: =IFERROR(AB41*'FlightConfig '!$K$23,"") -> 1761.76
A42: PREMIUM ECONOMY CLASS | B42: 1 | C42: =CONCATENATE(A42&B42&F42) -> PREMIUM ECONOMY CLASS1110 | E42: 1252 | F42: 110 | G42: =VLOOKUP(E42,'FG MASTER'!$A:$AB,2,0) -> 2026 PY CY1 ENTREE 1 CHICKEN ROULADE, RISOTTO, GREEN BEAN, LEMON CHICKEN JUS, MUSHROOM CONSERVA | H42: 1 | I42: 0.3 | J42: =IFERROR(IF(I42="std",H42,HLOOKUP(A42,'FlightConfig '!$B$34:$G$35,2,0)*I42),"") -> 13.2 | K42: =VLOOKUP(Food!E42,'FG MASTER'!$A$1:$AC$737,16,0) -> 1.81 | L42: =VLOOKUP(Food!E42,'FG MASTER'!$A$10:$AC$737,17,0) -> 4.5 | M42: =IFERROR(L42*$M$2,"") -> 1.8 | N42: =IFERROR((K42)+M42,"") -> 3.61 | O42: =IFERROR($K42*(1+$O$2)-$K42,0) -> 0.3982 | P42: =IFERROR($M42*(1+$P$2)-$M42,0) -> 0.36 | Q42: =SUM(N42:P42) -> 4.3682 | R42: =K42*(1+$O$2) -> 2.2082 | S42: =M42*(1+$P$2) -> 2.16 | T42: =R42+S42 -> 4.3682 | U42: 4.56 | W42: =IFERROR(#REF!*J42,"") | X42: =IFERROR(K42*J42,"") -> 23.892 | Y42: =IFERROR(+L42*J42,"") -> 59.4 | Z42: =IFERROR(+M42*J42,"") -> 23.76 | AA42: =IFERROR(+N42*J42,"") -> 47.652 | AB42: =IFERROR(O42*$J42,"") -> 5.25624 | AC42: =IFERROR(P42*$J42,"") -> 4.752 | AD42: =IFERROR(+Q42*J42,"") -> 57.66024 | AF42: =IFERROR(W42*'FlightConfig '!$K$3,"") | AG42: =IFERROR(X42*'FlightConfig '!$K$23,"") -> 8696.688 | AH42: =IFERROR(Y42*'FlightConfig '!$K$23,"") -> 21621.6 | AI42: =IFERROR(Z42*'FlightConfig '!$K$23,"") -> 8648.64 | AJ42: =IFERROR(AA42*'FlightConfig '!$K$23,"") -> 17345.328 | AK42: =IFERROR(AB42*'FlightConfig '!$K$23,"") -> 1913.2714
A43: PREMIUM ECONOMY CLASS | B43: 1 | C43: =CONCATENATE(A43&B43&F43) -> PREMIUM ECONOMY CLASS1110 | E43: 1253 | F43: 110 | G43: =VLOOKUP(E43,'FG MASTER'!$A:$AB,2,0) -> 2026 PY CY1 ENTRÉE 2 COD, SHRIMP, AND FISHERMAN STEW, GOLD RICE, FENNEL CAPER RELISH | H43: 1 | I43: 0.5 | J43: =IFERROR(IF(I43="std",H43,HLOOKUP(A43,'FlightConfig '!$B$34:$G$35,2,0)*I43),"") -> 22 | K43: =VLOOKUP(Food!E43,'FG MASTER'!$A$1:$AC$737,16,0) -> 3.21 | L43: =VLOOKUP(Food!E43,'FG MASTER'!$A$10:$AC$737,17,0) -> 4.5 | M43: =IFERROR(L43*$M$2,"") -> 1.8 | N43: =IFERROR((K43)+M43,"") -> 5.01 | O43: =IFERROR($K43*(1+$O$2)-$K43,0) -> 0.7062 | P43: =IFERROR($M43*(1+$P$2)-$M43,0) -> 0.36 | Q43: =SUM(N43:P43) -> 6.0762 | R43: =K43*(1+$O$2) -> 3.9162 | S43: =M43*(1+$P$2) -> 2.16 | T43: =R43+S43 -> 6.0762 | U43: 6.83 | W43: =IFERROR(#REF!*J43,"") | X43: =IFERROR(K43*J43,"") -> 70.62 | Y43: =IFERROR(+L43*J43,"") -> 99 | Z43: =IFERROR(+M43*J43,"") -> 39.6 | AA43: =IFERROR(+N43*J43,"") -> 110.22 | AB43: =IFERROR(O43*$J43,"") -> 15.5364 | AC43: =IFERROR(P43*$J43,"") -> 7.92 | AD43: =IFERROR(+Q43*J43,"") -> 133.6764 | AF43: =IFERROR(W43*'FlightConfig '!$K$3,"") | AG43: =IFERROR(X43*'FlightConfig '!$K$23,"") -> 25705.68 | AH43: =IFERROR(Y43*'FlightConfig '!$K$23,"") -> 36036 | AI43: =IFERROR(Z43*'FlightConfig '!$K$23,"") -> 14414.4 | AJ43: =IFERROR(AA43*'FlightConfig '!$K$23,"") -> 40120.08 | AK43: =IFERROR(AB43*'FlightConfig '!$K$23,"") -> 5655.2496
A44: PREMIUM ECONOMY CLASS | B44: 1 | C44: =CONCATENATE(A44&B44&F44) -> PREMIUM ECONOMY CLASS1110 | E44: 1254 | F44: 110 | G44: =VLOOKUP(E44,'FG MASTER'!$A:$AB,2,0) -> 2026 PY CY1 ENTRÉE 3 SPINACH CANNELLONI, RATATOUILLE, SAN MARZANO SAUCE, MOZZARELLA CHEESE | H44: 1 | I44: 0.35 | J44: =IFERROR(IF(I44="std",H44,HLOOKUP(A44,'FlightConfig '!$B$34:$G$35,2,0)*I44),"") -> 15.4 | K44: =VLOOKUP(Food!E44,'FG MASTER'!$A$1:$AC$737,16,0) -> 2.45 | L44: =VLOOKUP(Food!E44,'FG MASTER'!$A$10:$AC$737,17,0) -> 2.5 | M44: =IFERROR(L44*$M$2,"") -> 1 | N44: =IFERROR((K44)+M44,"") -> 3.45 | O44: =IFERROR($K44*(1+$O$2)-$K44,0) -> 0.539 | P44: =IFERROR($M44*(1+$P$2)-$M44,0) -> 0.2 | Q44: =SUM(N44:P44) -> 4.189 | R44: =K44*(1+$O$2) -> 2.989 | S44: =M44*(1+$P$2) -> 1.2 | T44: =R44+S44 -> 4.189 | U44: 4.51 | W44: =IFERROR(#REF!*J44,"") | X44: =IFERROR(K44*J44,"") -> 37.73 | Y44: =IFERROR(+L44*J44,"") -> 38.5 | Z44: =IFERROR(+M44*J44,"") -> 15.4 | AA44: =IFERROR(+N44*J44,"") -> 53.13 | AB44: =IFERROR(O44*$J44,"") -> 8.3006 | AC44: =IFERROR(P44*$J44,"") -> 3.08 | AD44: =IFERROR(+Q44*J44,"") -> 64.5106 | AF44: =IFERROR(W44*'FlightConfig '!$K$3,"") | AG44: =IFERROR(X44*'FlightConfig '!$K$23,"") -> 13733.72 | AH44: =IFERROR(Y44*'FlightConfig '!$K$23,"") -> 14014 | AI44: =IFERROR(Z44*'FlightConfig '!$K$23,"") -> 5605.6 | AJ44: =IFERROR(AA44*'FlightConfig '!$K$23,"") -> 19339.32 | AK44: =IFERROR(AB44*'FlightConfig '!$K$23,"") -> 3021.4184
A45: PREMIUM ECONOMY CLASS | B45: 1 | C45: =CONCATENATE(A45&B45&F45) -> PREMIUM ECONOMY CLASS1110 | E45: 1255 | F45: 110 | G45: =VLOOKUP(E45,'FG MASTER'!$A:$AB,2,0) -> 2026 PY CY1 STRAWBERRY SWIRL CHEESE CAKE | H45: 1 | I45: 1 | J45: =IFERROR(IF(I45="std",H45,HLOOKUP(A45,'FlightConfig '!$B$34:$G$35,2,0)*I45),"") -> 44 | K45: =VLOOKUP(Food!E45,'FG MASTER'!$A$1:$AC$737,16,0) -> 0.66 | L45: =VLOOKUP(Food!E45,'FG MASTER'!$A$10:$AC$737,17,0) -> 1.5 | M45: =IFERROR(L45*$M$2,"") -> 0.6 | N45: =IFERROR((K45)+M45,"") -> 1.26 | O45: =IFERROR($K45*(1+$O$2)-$K45,0) -> 0.1452 | P45: =IFERROR($M45*(1+$P$2)-$M45,0) -> 0.12 | Q45: =SUM(N45:P45) -> 1.5252 | R45: =K45*(1+$O$2) -> 0.8052 | S45: =M45*(1+$P$2) -> 0.72 | T45: =R45+S45 -> 1.5252 | W45: =IFERROR(#REF!*J45,"") | X45: =IFERROR(K45*J45,"") -> 29.04 | Y45: =IFERROR(+L45*J45,"") -> 66 | Z45: =IFERROR(+M45*J45,"") -> 26.4 | AA45: =IFERROR(+N45*J45,"") -> 55.44 | AB45: =IFERROR(O45*$J45,"") -> 6.3888 | AC45: =IFERROR(P45*$J45,"") -> 5.28 | AD45: =IFERROR(+Q45*J45,"") -> 67.1088 | AF45: =IFERROR(W45*'FlightConfig '!$K$3,"") | AG45: =IFERROR(X45*'FlightConfig '!$K$23,"") -> 10570.56 | AH45: =IFERROR(Y45*'FlightConfig '!$K$23,"") -> 24024 | AI45: =IFERROR(Z45*'FlightConfig '!$K$23,"") -> 9609.6 | AJ45: =IFERROR(AA45*'FlightConfig '!$K$23,"") -> 20180.16 | AK45: =IFERROR(AB45*'FlightConfig '!$K$23,"") -> 2325.5232
A46: PREMIUM ECONOMY CLASS | B46: 1 | C46: =CONCATENATE(A46&B46&F46) -> PREMIUM ECONOMY CLASS1110 | E46: 1256 | F46: 110 | G46: =VLOOKUP(E46,'FG MASTER'!$A:$AB,2,0) -> 2026 PY CY1 CHEESE PLATE | H46: 1 | I46: 1 | J46: =IFERROR(IF(I46="std",H46,HLOOKUP(A46,'FlightConfig '!$B$34:$G$35,2,0)*I46),"") -> 44 | K46: =VLOOKUP(Food!E46,'FG MASTER'!$A$1:$AC$737,16,0) -> 1.51 | L46: =VLOOKUP(Food!E46,'FG MASTER'!$A$10:$AC$737,17,0) -> 1.5 | M46: =IFERROR(L46*$M$2,"") -> 0.6 | N46: =IFERROR((K46)+M46,"") -> 2.11 | O46: =IFERROR($K46*(1+$O$2)-$K46,0) -> 0.3322 | P46: =IFERROR($M46*(1+$P$2)-$M46,0) -> 0.12 | Q46: =SUM(N46:P46) -> 2.5622 | R46: =K46*(1+$O$2) -> 1.8422 | S46: =M46*(1+$P$2) -> 0.72 | T46: =R46+S46 -> 2.5622 | W46: =IFERROR(#REF!*J46,"") | X46: =IFERROR(K46*J46,"") -> 66.44 | Y46: =IFERROR(+L46*J46,"") -> 66 | Z46: =IFERROR(+M46*J46,"") -> 26.4 | AA46: =IFERROR(+N46*J46,"") -> 92.84 | AB46: =IFERROR(O46*$J46,"") -> 14.6168 | AC46: =IFERROR(P46*$J46,"") -> 5.28 | AD46: =IFERROR(+Q46*J46,"") -> 112.7368 | AF46: =IFERROR(W46*'FlightConfig '!$K$3,"") | AG46: =IFERROR(X46*'FlightConfig '!$K$23,"") -> 24184.16 | AH46: =IFERROR(Y46*'FlightConfig '!$K$23,"") -> 24024 | AI46: =IFERROR(Z46*'FlightConfig '!$K$23,"") -> 9609.6 | AJ46: =IFERROR(AA46*'FlightConfig '!$K$23,"") -> 33793.76 | AK46: =IFERROR(AB46*'FlightConfig '!$K$23,"") -> 5320.5152
A47: PREMIUM ECONOMY CLASS | B47: 1 | C47: =CONCATENATE(A47&B47&F47) -> PREMIUM ECONOMY CLASS1110 | E47: 1286 | F47: 110 | G47: =VLOOKUP(E47,'FG MASTER'!$A:$AB,2,0) -> 2026 PY CRACKER | H47: 1 | I47: 1 | J47: =IFERROR(IF(I47="std",H47,HLOOKUP(A47,'FlightConfig '!$B$34:$G$35,2,0)*I47),"") -> 44 | K47: =VLOOKUP(Food!E47,'FG MASTER'!$A$1:$AC$737,16,0) -> 0.36 | L47: =VLOOKUP(Food!E47,'FG MASTER'!$A$10:$AC$737,17,0) -> 0.15 | M47: =IFERROR(L47*$M$2,"") -> 0.06 | N47: =IFERROR((K47)+M47,"") -> 0.42 | O47: =IFERROR($K47*(1+$O$2)-$K47,0) -> 0.0792 | P47: =IFERROR($M47*(1+$P$2)-$M47,0) -> 0.012 | Q47: =SUM(N47:P47) -> 0.5112 | R47: =K47*(1+$O$2) -> 0.4392 | S47: =M47*(1+$P$2) -> 0.072 | T47: =R47+S47 -> 0.5112 | W47: =IFERROR(#REF!*J47,"") | X47: =IFERROR(K47*J47,"") -> 15.84 | Y47: =IFERROR(+L47*J47,"") -> 6.6 | Z47: =IFERROR(+M47*J47,"") -> 2.64 | AA47: =IFERROR(+N47*J47,"") -> 18.48 | AB47: =IFERROR(O47*$J47,"") -> 3.4848 | AC47: =IFERROR(P47*$J47,"") -> 0.528 | AD47: =IFERROR(+Q47*J47,"") -> 22.4928 | AF47: =IFERROR(W47*'FlightConfig '!$K$3,"") | AG47: =IFERROR(X47*'FlightConfig '!$K$23,"") -> 5765.76 | AH47: =IFERROR(Y47*'FlightConfig '!$K$23,"") -> 2402.4 | AI47: =IFERROR(Z47*'FlightConfig '!$K$23,"") -> 960.96 | AJ47: =IFERROR(AA47*'FlightConfig '!$K$23,"") -> 6726.72 | AK47: =IFERROR(AB47*'FlightConfig '!$K$23,"") -> 1268.4672
A48: PREMIUM ECONOMY CLASS | B48: 1 | C48: =CONCATENATE(A48&B48&F48) -> PREMIUM ECONOMY CLASS1110 | E48: 1120 | F48: 110 | G48: =VLOOKUP(E48,'FG MASTER'!$A:$AB,2,0) -> PY C1 BREAKFAST TSU | H48: 1 | I48: 1 | J48: =IFERROR(IF(I48="std",H48,HLOOKUP(A48,'FlightConfig '!$B$34:$G$35,2,0)*I48),"") -> 44 | K48: =VLOOKUP(Food!E48,'FG MASTER'!$A$1:$AC$737,16,0) -> 0 | L48: =VLOOKUP(Food!E48,'FG MASTER'!$A$10:$AC$737,17,0) -> 1.25 | M48: =IFERROR(L48*$M$2,"") -> 0.5 | N48: =IFERROR((K48)+M48,"") -> 0.5 | O48: =IFERROR($K48*(1+$O$2)-$K48,0) -> 0 | P48: =IFERROR($M48*(1+$P$2)-$M48,0) -> 0.1 | Q48: =SUM(N48:P48) -> 0.6 | R48: =K48*(1+$O$2) -> 0 | S48: =M48*(1+$P$2) -> 0.6 | T48: =R48+S48 -> 0.6 | W48: =IFERROR(#REF!*J48,"") | X48: =IFERROR(K48*J48,"") -> 0 | Y48: =IFERROR(+L48*J48,"") -> 55 | Z48: =IFERROR(+M48*J48,"") -> 22 | AA48: =IFERROR(+N48*J48,"") -> 22 | AB48: =IFERROR(O48*$J48,"") -> 0 | AC48: =IFERROR(P48*$J48,"") -> 4.4 | AD48: =IFERROR(+Q48*J48,"") -> 26.4 | AF48: =IFERROR(W48*'FlightConfig '!$K$3,"") | AG48: =IFERROR(X48*'FlightConfig '!$K$23,"") -> 0 | AH48: =IFERROR(Y48*'FlightConfig '!$K$23,"") -> 20020 | AI48: =IFERROR(Z48*'FlightConfig '!$K$23,"") -> 8008 | AJ48: =IFERROR(AA48*'FlightConfig '!$K$23,"") -> 8008 | AK48: =IFERROR(AB48*'FlightConfig '!$K$23,"") -> 0
A49: PREMIUM ECONOMY CLASS | B49: 1 | C49: =CONCATENATE(A49&B49&F49) -> PREMIUM ECONOMY CLASS1110 | E49: 1257 | F49: 110 | G49: =VLOOKUP(E49,'FG MASTER'!$A:$AB,2,0) -> 2026 PY CY1 ENGLISH MUFFIN, EGG PATTY WITH CHICKEN SAUSAGE PATTY AND CHEDDAR CHEESE | H49: 1 | I49: 0.5 | J49: =IFERROR(IF(I49="std",H49,HLOOKUP(A49,'FlightConfig '!$B$34:$G$35,2,0)*I49),"") -> 22 | K49: =VLOOKUP(Food!E49,'FG MASTER'!$A$1:$AC$737,16,0) -> 1.08 | L49: =VLOOKUP(Food!E49,'FG MASTER'!$A$10:$AC$737,17,0) -> 2 | M49: =IFERROR(L49*$M$2,"") -> 0.8 | N49: =IFERROR((K49)+M49,"") -> 1.88 | O49: =IFERROR($K49*(1+$O$2)-$K49,0) -> 0.2376 | P49: =IFERROR($M49*(1+$P$2)-$M49,0) -> 0.16 | Q49: =SUM(N49:P49) -> 2.2776 | R49: =K49*(1+$O$2) -> 1.3176 | S49: =M49*(1+$P$2) -> 0.96 | T49: =R49+S49 -> 2.2776 | U49: 2.48 | W49: =IFERROR(#REF!*J49,"") | X49: =IFERROR(K49*J49,"") -> 23.76 | Y49: =IFERROR(+L49*J49,"") -> 44 | Z49: =IFERROR(+M49*J49,"") -> 17.6 | AA49: =IFERROR(+N49*J49,"") -> 41.36 | AB49: =IFERROR(O49*$J49,"") -> 5.2272 | AC49: =IFERROR(P49*$J49,"") -> 3.52 | AD49: =IFERROR(+Q49*J49,"") -> 50.1072 | AF49: =IFERROR(W49*'FlightConfig '!$K$3,"") | AG49: =IFERROR(X49*'FlightConfig '!$K$23,"") -> 8648.64 | AH49: =IFERROR(Y49*'FlightConfig '!$K$23,"") -> 16016 | AI49: =IFERROR(Z49*'FlightConfig '!$K$23,"") -> 6406.4 | AJ49: =IFERROR(AA49*'FlightConfig '!$K$23,"") -> 15055.04 | AK49: =IFERROR(AB49*'FlightConfig '!$K$23,"") -> 1902.7008
