Workbook
Name Data: [1]Summary!$A$2:$F$5004
Name DryItemList: '[2]DRY ITEM LIST'!$D$4:$D$46
Name DryItemList: 'DRY ITEM LIST'!$D$4:$D$61

Sheet Inv Summary
A1: ET $ | B1: D Note
H2: 45887
E8: TO: Ethiopian Airlines Group
E9: ="FLIGHT NO: "&'Inv Detail'!J2 -> FLIGHT NO: ET519
E10: Route ATL-ADD
E11: Period Date : 05/22/2026 to 05/31/2026
E12: ="Invoice Number: "&'Inv Detail'!G1 -> Invoice Number: ET202605B
E13: ="DATE: "&TEXT('Inv Detail'!G2,"dd-mmm-yyyy") -> DATE: 18-Jun-2026
A15: 14 | B15: F17 | E15: FOOD | F15: =SUM('Inv Detail'!Q15:Q58) -> 39619.977 | G15: =IF(G$9="","",'DN01'!$F$14+'DN01'!$J$25-3)
A16: 16 | B16: F29
A17: 18 | B17: F32 | E17: SERVICE | F17: =SUM('Inv Detail'!Q10:Q14) -> 4200
A18: 21 | B18: F30
A19: 17 | B19: F31 | E19: SUBTOTAL | F19: =SUM(F15:F18) -> 43819.977
A20: 19 | B20: M
A21: 20 | B21: M | E21: TAX | F21: 0
A22: 78 | B22: F16
A23: 98 | B23: F19 | E23: PORT FEE | F23: 0
A24: XX | B24: XX
A25: 39 | B25: F33 | E25: TOTAL DUE | F25: =SUM(F19:F23) -> 43819.977
A26: 41 | B26: **
A27: 43 | B27: ** | E27: DUE DATE: | F27: ='Inv Detail'!G3 -> 46221
A28: 33 | B28: G17
A29: 88 | B29: G16
A30: 105 | B30: G20
A31: XX | B31: XX
A32: 42 | B32: **
A33: 44 | B33: **
A34: DRY | B34: ITEM
G51: =SUMPRODUCT($F$10:$F$50,G10:G50) -> 0 | H51: =SUMPRODUCT($F$10:$F$50,H10:H50) -> 0 | I51: =SUMPRODUCT($F$10:$F$50,I10:I50) -> 0 | J51: =SUMPRODUCT($F$10:$F$50,J10:J50) -> 0 | K51: =SUMPRODUCT($F$10:$F$50,K10:K50) -> 0 | L51: =SUMPRODUCT($F$10:$F$50,L10:L50) -> 0 | M51: =SUMPRODUCT($F$10:$F$50,M10:M50) -> 0

Sheet Inv Detail
A1: ET $ | B1: D Note | F1: Invoice #: | G1: ="ET"&TEXT(G9,"YYYYMM")&IF(DAY(G9)<16,"A","B") -> ET202605B | I1: Bill-to: | J1: Ethiopian Airlines Group | V1: Cycle 1 | W1: Cycle 2 | X1: Cycle 3
F2: Inv Date: | G2: 46191 | I2: Flight No: | J2: ET519 | V2: 46023 | W2: 46082 | X2: 46143
F3: Due Date: | G3: =G2+30 -> 46221 | I3: Route ATL-ADD | T3: Cycle #
T4: 3
E7: +
G8: =TEXT(G9,"DDD") -> Fri | H8: =TEXT(H9,"DDD") -> Mon | I8: =TEXT(I9,"DDD") -> Wed | J8: =TEXT(J9,"DDD") -> Fri | K8: =TEXT(K9,"DDD") | L8: =TEXT(L9,"DDD") | M8: =TEXT(M9,"DDD") | N8: =TEXT(N9,"DDD") | ... P8: =TEXT(P9,"DDD") | V8: According to the contract , BC total 35 and (-3) complimetary but no Special meal added
D9: No. | E9: CODE | F9: PRICE | G9: =IF('DN01'!$N$1="","",'DN01'!$N$1) -> 46164 | H9: =IF('DN02'!$N$1="","",'DN02'!$N$1) -> 46167 | I9: =IF('DN03'!$N$1="","",'DN03'!$N$1) -> 46169 | J9: =IF('DN04'!$N$1="","",'DN04'!$N$1) -> 46171 | K9: =IF('DN05'!$N$1="","",'DN05'!$N$1) | L9: =IF('DN06'!$N$1="","",'DN06'!$N$1) | M9: =IF('DN07'!$N$1="","",'DN07'!$N$1) | N9: =IF('DN08'!$N$1="","",'DN08'!$N$1) | O9: =IF('DN09'!$N$1="","",'DN09'!$N$1) | P9: =IF('DN10'!$N$1="","",'DN10'!$N$1) | Q9: SUBTOTAL | T9: ** REF ONLY ** | V9: According to the contract , EY total 135 and (-10) complimetary but no Special meal added
A10: 49 | B10: M | D10: 1 | E10: Handling charges Per A/C - Turnaround 1 trip - B787 | F10: {=_xlfn.XLOOKUP($A10,'ET Standar Price List'!$A:$A,_xlfn.SWITCH($T$4,1,'ET Standar Price List'!$G:$G,2,'ET Standar Price List'!$J:$J,3,'ET Standar Price List'!$M:$M),"XX")} -> 400 | G10: =IF(G$9="","",'DN01'!$F$35) -> 1 | H10: =IF(H$9="","",'DN02'!$F$35) -> 1 | I10: =IF(I$9="","",'DN02'!$F$35) -> 1 | J10: =IF(J$9="","",'DN04'!$F$35) -> 1 | K10: =IF(K$9="","",'DN05'!$F$35) | L10: =IF(L$9="","",'DN06'!$F$35) | M10: =IF(M$9="","",'DN07'!$F$35) | N10: =IF(N$9="","",'DN08'!$F$35) | O10: =IF(O$9="","",'DN09'!$F$35) | P10: =IF(P$9="","",'DN10'!$F$35) | Q10: =IF(F10="","",SUM(G10:P10)*F10) -> 1600 | T10: =IF(G10="","",VLOOKUP(A10,'ET Standar Price List'!A:M,4,0)) -> B787
A11: 51 | B11: M | D11: =D10+1 -> 2 | E11: Van Trip | F11: {=_xlfn.XLOOKUP($A11,'ET Standar Price List'!$A:$A,_xlfn.SWITCH($T$4,1,'ET Standar Price List'!$G:$G,2,'ET Standar Price List'!$J:$J,3,'ET Standar Price List'!$M:$M),"XX")} -> 200 | G11: =IF(G$9="","",'DN01'!$F$36) -> 1 | H11: =IF(H$9="","",'DN02'!$F$36) -> 1 | I11: =IF(I$9="","",'DN02'!$F$36) -> 1 | J11: =IF(J$9="","",'DN04'!$F$36) -> 1 | K11: =IF(K$9="","",'DN05'!$F$36) | L11: =IF(L$9="","",'DN06'!$F$36) | M11: =IF(M$9="","",'DN07'!$F$36) | N11: =IF(N$9="","",'DN08'!$F$36) | O11: =IF(O$9="","",'DN09'!$F$36) | P11: =IF(P$9="","",'DN10'!$F$36) | Q11: =IF(F11="","",SUM(G11:P11)*F11) -> 800 | T11: =IF(G11="","",VLOOKUP(A11,'ET Standar Price List'!A:M,4,0)) -> Van Trip
A12: 52 | B12: M | D12: 3 | E12: Custom Clearance Charge | F12: {=_xlfn.XLOOKUP($A12,'ET Standar Price List'!$A:$A,_xlfn.SWITCH($T$4,1,'ET Standar Price List'!$G:$G,2,'ET Standar Price List'!$J:$J,3,'ET Standar Price List'!$M:$M),"XX")} -> 250 | G12: 0 | H12: 0 | I12: 0 | J12: 0 | K12: 0 | L12: 0 | M12: 0 | N12: 0 | O12: 0 | P12: 0 | Q12: =IF(F12="","",SUM(G12:P12)*F12) -> 0 | T12: =IF(G12="","",VLOOKUP(A12,'ET Standar Price List'!A:M,4,0)) -> Custom Clearance Chrg
A13: 54 | B13: M | D13: 4 | E13: LAUNDARY CHARGES (per kg) | F13: {=_xlfn.XLOOKUP($A13,'ET Standar Price List'!$A:$A,_xlfn.SWITCH($T$4,1,'ET Standar Price List'!$G:$G,2,'ET Standar Price List'!$J:$J,3,'ET Standar Price List'!$M:$M),"XX")} -> 200 | G13: =IF(G$9="","",'DN01'!$F$34) -> 0.5 | H13: =IF(H$9="","",'DN01'!$F$34) -> 0.5 | I13: =IF(I$9="","",'DN01'!$F$34) -> 0.5 | J13: =IF(J$9="","",'DN01'!$F$34) -> 0.5 | K13: =IF(K$9="","",'DN01'!$F$34) | L13: =IF(L$9="","",'DN01'!$F$34) | M13: =IF(M$9="","",'DN01'!$F$34) | N13: =IF(N$9="","",'DN01'!$F$34) | ... P13: =IF(P$9="","",'DN01'!$F$34) | Q13: =IF(F13="","",SUM(G13:P13)*F13) -> 400 | T13: =IF(G13="","",VLOOKUP(A13,'ET Standar Price List'!A:M,4,0)) -> Linen Napkin (Laundry Items are charged per KG
A14: 55 | B14: M | D14: 5 | E14: INTERNATIONAL TRASH REMOVAL | F14: {=_xlfn.XLOOKUP($A14,'ET Standar Price List'!$A:$A,_xlfn.SWITCH($T$4,1,'ET Standar Price List'!$G:$G,2,'ET Standar Price List'!$J:$J,3,'ET Standar Price List'!$M:$M),"XX")} -> 350 | G14: =IF(G$9="","",'DN01'!$F$37) -> 1 | H14: =IF(H$9="","",'DN01'!$F$37) -> 1 | I14: =IF(I$9="","",'DN01'!$F$37) -> 1 | J14: =IF(J$9="","",'DN01'!$F$37) -> 1 | K14: =IF(K$9="","",'DN01'!$F$37) | L14: =IF(L$9="","",'DN01'!$F$37) | M14: =IF(M$9="","",'DN01'!$F$37) | N14: =IF(N$9="","",'DN01'!$F$37) | ... P14: =IF(P$9="","",'DN01'!$F$37) | Q14: =IF(F14=" "," ",SUM(G14:P14)*F14) -> 1400 | T14: =IF(G14="","",VLOOKUP(A14,'ET Standar Price List'!A:M,4,0)) -> 0
A15: 14 | B15: F17 | D15: 6 | E15: ="CYC "&T4&" BC LCH/DNR" -> CYC 3 BC LCH/DNR | F15: {=_xlfn.XLOOKUP($A15,'ET Standar Price List'!$A:$A,_xlfn.SWITCH($T$4,1,'ET Standar Price List'!$G:$G,2,'ET Standar Price List'!$J:$J,3,'ET Standar Price List'!$M:$M),"XX")} -> 29.315022 | G15: =MAX(IF(G$9="","",'DN01'!$F$14+'DN01'!$J$25-3),32) -> 33 | H15: =MAX(IF(H$9="","",'DN02'!$F$14+'DN02'!$J$25-3),32) -> 36 | I15: =MAX(IF(I$9="","",'DN03'!$F$14+'DN03'!$J$25-3),32) -> 33 | J15: =MAX(IF(J$9="","",'DN04'!$F$14+'DN04'!$J$25-3),32) -> 36 | K15: =IF(K$9="","",'DN05'!$F$14+'DN05'!$J$25-3) | L15: =IF(L$9="","",'DN06'!$F$14+'DN06'!$J$25-3) | M15: =IF(M$9="","",'DN07'!$F$14+'DN07'!$J$25-3) | N15: =IF(N$9="","",'DN08'!$F$14+'DN08'!$J$25-3) | O15: =IF(O$9="","",'DN09'!$F$14+'DN09'!$J$25-3) | P15: =IF(P$9="","",'DN10'!$F$14+'DN10'!$J$25-3) | Q15: =IF(F15="","",SUM(G15:P15)*F15) -> 4045.4731 | T15: =IF(G15="","",VLOOKUP(A15,'ET Standar Price List'!A:M,4,0)) -> BC LCH/DNR Price per passenger Total
A16: 16 | B16: F29 | D16: 7 | E16: Fruit Platter (Std ) | F16: {=_xlfn.XLOOKUP($A16,'ET Standar Price List'!$A:$A,_xlfn.SWITCH($T$4,1,'ET Standar Price List'!$G:$G,2,'ET Standar Price List'!$J:$J,3,'ET Standar Price List'!$M:$M),"XX")} -> 16.605 | G16: =IF(G$9="","",1) -> 1 | H16: =IF(H$9="","",1) -> 1 | I16: =IF(I$9="","",1) -> 1 | J16: =IF(J$9="","",1) -> 1 | K16: 0 | L16: =IF(L$9="","",1) | M16: =IF(M$9="","",1) | N16: =IF(N$9="","",1) | O16: =IF(O$9="","",1) | P16: =IF(P$9="","",1) | Q16: =IF(F16="","",SUM(G16:P16)*F16) -> 66.42 | T16: =IF(G16="","",VLOOKUP(A16,'ET Standar Price List'!A:M,4,0)) -> Fruit Platter (STD ) =18 pieces
A17: 18 | B17: F32 | D17: 8 | E17: Garlic Bread (Std) | F17: {=_xlfn.XLOOKUP($A17,'ET Standar Price List'!$A:$A,_xlfn.SWITCH($T$4,1,'ET Standar Price List'!$G:$G,2,'ET Standar Price List'!$J:$J,3,'ET Standar Price List'!$M:$M),"XX")} -> 6.75 | G17: =IF(G$9="","",'DN01'!$F$32) -> 1 | H17: =IF(H$9="","",'DN02'!$F$32) -> 2 | I17: =IF(I$9="","",'DN03'!$F$32) -> 2 | J17: =IF(J$9="","",'DN04'!$F$32) -> 1 | K17: =IF(K$9="","",'DN05'!$F$32) | L17: =IF(L$9="","",'DN06'!$F$32) | M17: =IF(M$9="","",'DN07'!$F$32) | N17: =IF(N$9="","",'DN08'!$F$32) | O17: =IF(O$9="","",'DN09'!$F$32) | P17: =IF(P$9="","",'DN10'!$F$32) | Q17: =IF(F17="","",SUM(G17:P17)*F17) -> 40.5 | T17: =IF(G17="","",VLOOKUP(A17,'ET Standar Price List'!A:M,4,0)) -> Garlic Bread 1 OF 10 PCS
A18: 21 | B18: F30 | D18: 9 | E18: Cheese Tray (Std) | F18: {=_xlfn.XLOOKUP($A18,'ET Standar Price List'!$A:$A,_xlfn.SWITCH($T$4,1,'ET Standar Price List'!$G:$G,2,'ET Standar Price List'!$J:$J,3,'ET Standar Price List'!$M:$M),"XX")} -> 26.941556 | G18: =IF(G$9="","",'DN01'!$F$30) -> 1 | H18: =IF(H$9="","",'DN02'!$F$30) -> 2 | I18: =IF(I$9="","",'DN03'!$F$30) -> 2 | J18: =IF(J$9="","",'DN04'!$F$30) -> 2 | K18: =IF(K$9="","",'DN05'!$F$30) | L18: =IF(L$9="","",'DN06'!$F$30) | M18: =IF(M$9="","",'DN07'!$F$30) | N18: =IF(N$9="","",'DN08'!$F$30) | O18: =IF(O$9="","",'DN09'!$F$30) | P18: =IF(P$9="","",'DN10'!$F$30) | Q18: =IF(F18="","",SUM(G18:P18)*F18) -> 188.59089 | T18: =IF(G18="","",VLOOKUP(A18,'ET Standar Price List'!A:M,4,0)) -> Cheese Tray
A19: 17 | B19: F31 | D19: =D18+1 -> 10 | E19: 2L Fresh OJ (Std) | F19: {=_xlfn.XLOOKUP($A19,'ET Standar Price List'!$A:$A,_xlfn.SWITCH($T$4,1,'ET Standar Price List'!$G:$G,2,'ET Standar Price List'!$J:$J,3,'ET Standar Price List'!$M:$M),"XX")} -> 6.53 | G19: =IF(G$9="","",'DN01'!$F$31) -> 1 | H19: =IF(H$9="","",'DN02'!$F$31) -> 1 | I19: =IF(I$9="","",'DN03'!$F$31) -> 3 | J19: =IF(J$9="","",'DN04'!$F$31) -> 1 | K19: =IF(K$9="","",'DN05'!$F$31) | L19: =IF(L$9="","",'DN06'!$F$31) | M19: =IF(M$9="","",'DN07'!$F$31) | N19: =IF(N$9="","",'DN08'!$F$31) | O19: =IF(O$9="","",'DN09'!$F$31) | P19: =IF(P$9="","",'DN10'!$F$31) | Q19: =IF(F19="","",SUM(G19:P19)*F19) -> 39.18 | T19: =IF(G19="","",VLOOKUP(A19,'ET Standar Price List'!A:M,4,0)) -> 1L Fresh OJ (1-8)
A20: 19 | B20: M | D20: 11 | E20: Fresh Milk (Std) | F20: {=_xlfn.XLOOKUP($A20,'ET Standar Price List'!$A:$A,_xlfn.SWITCH($T$4,1,'ET Standar Price List'!$G:$G,2,'ET Standar Price List'!$J:$J,3,'ET Standar Price List'!$M:$M),"XX")} -> 5.85 | G20: =IF(G$9="","",1) -> 1 | H20: =IF(H$9="","",1) -> 1 | I20: =IF(I$9="","",1) -> 1 | J20: =IF(J$9="","",1) -> 1 | K20: =IF(K$9="","",1) | L20: =IF(L$9="","",1) | M20: =IF(M$9="","",1) | N20: =IF(N$9="","",1) | ... P20: =IF(P$9="","",1) | Q20: =IF(F20="","",SUM(G20:P20)*F20) -> 23.4 | T20: =IF(G20="","",VLOOKUP(A20,'ET Standar Price List'!A:M,4,0)) -> FRESH MILK
A21: 20 | B21: M | D21: 12 | E21: Condiments and Chocolate (Std) | F21: {=_xlfn.XLOOKUP($A21,'ET Standar Price List'!$A:$A,_xlfn.SWITCH($T$4,1,'ET Standar Price List'!$G:$G,2,'ET Standar Price List'!$J:$J,3,'ET Standar Price List'!$M:$M),"XX")} -> 1.8 | G21: =IF(G$9="","",1) -> 1 | H21: =IF(H$9="","",1) -> 1 | I21: =IF(I$9="","",1) -> 1 | J21: =IF(J$9="","",1) -> 1 | K21: =IF(K$9="","",1) | L21: =IF(L$9="","",1) | M21: =IF(M$9="","",1) | N21: =IF(N$9="","",1) | ... P21: =IF(P$9="","",1) | Q21: =IF(F21="","",SUM(G21:P21)*F21) -> 7.2 | T21: =IF(G21="","",VLOOKUP(A21,'ET Standar Price List'!A:M,4,0)) -> CONDIMENTS AND CHOCOLATE
A22: 78 | B22: F16 | D22: 13 | E22: BC HBF | F22: {=_xlfn.XLOOKUP($A22,'ET Standar Price List'!$A:$A,_xlfn.SWITCH($T$4,1,'ET Standar Price List'!$G:$G,2,'ET Standar Price List'!$J:$J,3,'ET Standar Price List'!$M:$M),"XX")} -> 18.906477 | G22: =MAX(IF(G$9="","",'DN01'!$F$13+'DN01'!$J$25-3),32) -> 33 | H22: =MAX(IF(H$9="","",'DN02'!$F$13+'DN02'!$J$25-3),32) -> 36 | I22: =MAX(IF(I$9="","",'DN03'!$F$13+'DN03'!$J$25-3),32) -> 33 | J22: =MAX(IF(J$9="","",'DN04'!$F$13+'DN04'!$J$25-3),32) -> 36 | K22: =IF(K$9="","",'DN05'!$F$13+'DN05'!$J$25-3) | L22: =IF(L$9="","",'DN06'!$F$13+'DN06'!$J$25-3) | M22: =IF(M$9="","",'DN07'!$F$13+'DN07'!$J$25-3) | N22: =IF(N$9="","",'DN08'!$F$13+'DN08'!$J$25-3) | O22: =IF(O$9="","",'DN09'!$F$13+'DN09'!$J$25-3) | P22: =IF(P$9="","",'DN10'!$F$13+'DN10'!$J$25-3) | Q22: =IF(F22="","",SUM(G22:P22)*F22) -> 2609.0938 | T22: =IF(G22="","",VLOOKUP(A22,'ET Standar Price List'!A:M,4,0)) -> BC HBF Price per passenger Total
A23: 98 | B23: F19 | D23: =D22+1 -> 14 | E23: ="CYC "&T4&" BC HCP" -> CYC 3 BC HCP | F23: {=_xlfn.XLOOKUP($A23,'ET Standar Price List'!$A:$A,_xlfn.SWITCH($T$4,1,'ET Standar Price List'!$G:$G,2,'ET Standar Price List'!$J:$J,3,'ET Standar Price List'!$M:$M),"XX")} -> 8.7645188 | G23: =MAX(IF(G$9="","",'DN01'!$F$16+'DN01'!$J$25-3),32) -> 33 | H23: =MAX(IF(H$9="","",'DN02'!$F$16+'DN02'!$J$25-3),32) -> 36 | I23: =MAX(IF(I$9="","",'DN03'!$F$16+'DN03'!$J$25-3),32) -> 33 | J23: =MAX(IF(J$9="","",'DN04'!$F$16+'DN04'!$J$25-3),32) -> 36 | K23: =IF(K$9="","",'DN05'!$F$16+'DN05'!$J$25-3) | L23: =IF(L$9="","",'DN06'!$F$16+'DN06'!$J$25-3) | M23: =IF(M$9="","",'DN07'!$F$16+'DN07'!$J$25-3) | N23: =IF(N$9="","",'DN08'!$F$16+'DN08'!$J$25-3) | O23: =IF(O$9="","",'DN09'!$F$16+'DN09'!$J$25-3) | P23: =IF(P$9="","",'DN10'!$F$16+'DN10'!$J$25-3) | Q23: =IF(F23="","",SUM(G23:P23)*F23) -> 1209.5036 | T23: =IF(G23="","",VLOOKUP(A23,'ET Standar Price List'!A:M,4,0)) -> BC HCP Per passenger Charge Total
A24: 14 | B24: XX | D24: 15 | E24: Xtra BC Fasting Meals | F24: {=_xlfn.XLOOKUP($A24,'ET Standar Price List'!$A:$A,_xlfn.SWITCH($T$4,1,'ET Standar Price List'!$G:$G,2,'ET Standar Price List'!$J:$J,3,'ET Standar Price List'!$M:$M),"XX")} -> 29.315022 | G24: =IF(G$9="","",'DN01'!$F$20) -> 0 | H24: =IF(H$9="","",'DN02'!$F$20) -> 0 | I24: =IF(I$9="","",'DN03'!$F$20) -> 0 | J24: =IF(J$9="","",'DN04'!$F$20) -> 0 | K24: =IF(K$9="","",'DN05'!$F$20) | L24: =IF(L$9="","",'DN06'!$F$20) | M24: =IF(M$9="","",'DN07'!$F$20) | N24: =IF(N$9="","",'DN08'!$F$20) | O24: =IF(O$9="","",'DN09'!$F$20) | P24: =IF(P$9="","",'DN10'!$F$20) | Q24: =IF(F24="","",SUM(G24:P24)*F24) -> 0
A25: 39 | B25: F33 | D25: =D24+1 -> 16 | E25: STANDARD UP LIFT | F25: {=_xlfn.XLOOKUP($A25,'ET Standar Price List'!$A:$A,_xlfn.SWITCH($T$4,1,'ET Standar Price List'!$G:$G,2,'ET Standar Price List'!$J:$J,3,'ET Standar Price List'!$M:$M),"XX")} -> 15.62 | G25: =IF(G$9="","",'DN01'!$F$33) -> 1 | H25: =IF(H$9="","",'DN02'!$F$33) -> 1 | I25: =IF(I$9="","",'DN03'!$F$33) -> 1 | J25: =IF(J$9="","",'DN04'!$F$33) -> 1 | K25: =IF(K$9="","",'DN05'!$F$33) | L25: =IF(L$9="","",'DN06'!$F$33) | M25: =IF(M$9="","",'DN07'!$F$33) | N25: =IF(N$9="","",'DN08'!$F$33) | O25: =IF(O$9="","",'DN09'!$F$33) | P25: =IF(P$9="","",'DN10'!$F$33) | Q25: =IF(F25="","",SUM(G25:P25)*F25) -> 62.48 | T25: =IF(G25="","",VLOOKUP(A25,'ET Standar Price List'!A:M,4,0)) -> Standard Uplift Total Price
A26: 41 | B26: ** | D26: 17 | E26: ALL IATA BC SPML (NO KSML) DNR | F26: {=_xlfn.XLOOKUP($A26,'ET Standar Price List'!$A:$A,_xlfn.SWITCH($T$4,1,'ET Standar Price List'!$G:$G,2,'ET Standar Price List'!$J:$J,3,'ET Standar Price List'!$M:$M),"XX")} -> 25.34 | G26: =IF(G$9="","",('DN01'!$J$25)-G28) -> 2 | H26: =IF(H$9="","",('DN02'!$J$25)-H28) -> 3 | I26: =IF(I$9="","",('DN03'!$J$25)-I28) -> 0 | J26: =IF(J$9="","",('DN04'!$J$25)-J28) -> 1 | K26: =IF(K$9="","",('DN01'!$J$25)-K28) | L26: =IF(L$9="","",('DN01'!$J$25)-L28) | M26: =IF(M$9="","",('DN01'!$J$25)-M28) | N26: =IF(N$9="","",('DN01'!$J$25)-N28) | O26: =IF(O$9="","",('DN01'!$J$25)-O28) | P26: =IF(P$9="","",('DN01'!$J$25)-P28) | Q26: =IF(F26="","",SUM(G26:P26)*F26) -> 152.04 | T26: =IF(G26="","",VLOOKUP(A26,'ET Standar Price List'!A:M,4,0)) -> ALL IATA BC SPML (NO KSML)
A27: 45 | B27: ** | D27: =D26+1 -> 18 | E27: ALL IATA BC SPML (NO KSML) : HBF | F27: {=_xlfn.XLOOKUP($A27,'ET Standar Price List'!$A:$A,_xlfn.SWITCH($T$4,1,'ET Standar Price List'!$G:$G,2,'ET Standar Price List'!$J:$J,3,'ET Standar Price List'!$M:$M),"XX")} -> 19.98 | G27: =IF(G$9="","",('DN01'!$N$25)-G28) -> 2 | H27: =IF(H$9="","",('DN02'!$N$25)-H28) -> 3 | I27: =IF(I$9="","",('DN03'!$N$25)-I28) -> 0 | J27: =IF(J$9="","",('DN04'!$N$25)-J28) -> 1 | K27: =IF(K$9="","",('DN01'!$N$25)-K28) | L27: =IF(L$9="","",('DN01'!$N$25)-L28) | M27: =IF(M$9="","",('DN01'!$N$25)-M28) | N27: =IF(N$9="","",('DN01'!$N$25)-N28) | O27: =IF(O$9="","",('DN01'!$N$25)-O28) | P27: =IF(P$9="","",('DN01'!$N$25)-P28) | Q27: =IF(F27="","",SUM(G27:P27)*F27) -> 119.88 | T27: =IF(G27="","",VLOOKUP(A27,'ET Standar Price List'!A:M,4,0)) -> ALL IATA BC SPML (NO KSML) HBF
A28: 43 | B28: ** | D28: =D27+1 -> 19 | E28: KSML BC | F28: {=_xlfn.XLOOKUP($A28,'ET Standar Price List'!$A:$A,_xlfn.SWITCH($T$4,1,'ET Standar Price List'!$G:$G,2,'ET Standar Price List'!$J:$J,3,'ET Standar Price List'!$M:$M),"XX")} -> 50 | G28: =IF(G$9="","",SUMIFS('DN01'!$J$12:$J$24,'DN01'!$I$12:$I$24,"KSML")+SUMIFS('DN01'!$L$12:$L$24,'DN01'!$I$12:$I$24,"KSML")+SUMIFS('DN01'!$N$12:$N$24,'DN01'!$I$12:$I$24,"KSML")) -> 0 | H28: =IF(H$9="","",SUMIFS('DN02'!$J$12:$J$24,'DN02'!$I$12:$I$24,"KSML")+SUMIFS('DN02'!$L$12:$L$24,'DN02'!$I$12:$I$24,"KSML")+SUMIFS('DN02'!$N$12:$N$24,'DN02'!$I$12:$I$24,"KSML")) -> 0 | I28: =IF(I$9="","",SUMIFS('DN03'!$J$12:$J$24,'DN03'!$I$12:$I$24,"KSML")+SUMIFS('DN03'!$L$12:$L$24,'DN03'!$I$12:$I$24,"KSML")+SUMIFS('DN03'!$N$12:$N$24,'DN03'!$I$12:$I$24,"KSML")) -> 0 | J28: =IF(J$9="","",SUMIFS('DN04'!$J$12:$J$24,'DN04'!$I$12:$I$24,"KSML")+SUMIFS('DN04'!$L$12:$L$24,'DN04'!$I$12:$I$24,"KSML")+SUMIFS('DN04'!$N$12:$N$24,'DN04'!$I$12:$I$24,"KSML")) -> 0 | K28: =IF(K$9="","",SUMIFS('DN05'!$J$12:$J$24,'DN05'!$I$12:$I$24,"KSML")+SUMIFS('DN05'!$L$12:$L$24,'DN05'!$I$12:$I$24,"KSML")+SUMIFS('DN05'!$N$12:$N$24,'DN05'!$I$12:$I$24,"KSML")) | L28: =IF(L$9="","",SUMIFS('DN06'!$J$12:$J$24,'DN06'!$I$12:$I$24,"KSML")+SUMIFS('DN06'!$L$12:$L$24,'DN06'!$I$12:$I$24,"KSML")+SUMIFS('DN06'!$N$12:$N$24,'DN06'!$I$12:$I$24,"KSML")) | M28: =IF(M$9="","",SUMIFS('DN07'!$J$12:$J$24,'DN07'!$I$12:$I$24,"KSML")+SUMIFS('DN07'!$L$12:$L$24,'DN07'!$I$12:$I$24,"KSML")+SUMIFS('DN07'!$N$12:$N$24,'DN07'!$I$12:$I$24,"KSML")) | N28: =IF(N$9="","",SUMIFS('DN08'!$J$12:$J$24,'DN08'!$I$12:$I$24,"KSML")+SUMIFS('DN08'!$L$12:$L$24,'DN08'!$I$12:$I$24,"KSML")+SUMIFS('DN08'!$N$12:$N$24,'DN08'!$I$12:$I$24,"KSML")) | O28: =IF(O$9="","",SUMIFS('DN09'!$J$12:$J$24,'DN09'!$I$12:$I$24,"KSML")+SUMIFS('DN09'!$L$12:$L$24,'DN09'!$I$12:$I$24,"KSML")+SUMIFS('DN09'!$N$12:$N$24,'DN09'!$I$12:$I$24,"KSML")) | P28: =IF(P$9="","",SUMIFS('DN10'!$J$12:$J$24,'DN10'!$I$12:$I$24,"KSML")+SUMIFS('DN10'!$L$12:$L$24,'DN10'!$I$12:$I$24,"KSML")+SUMIFS('DN10'!$N$12:$N$24,'DN10'!$I$12:$I$24,"KSML")) | Q28: =IF(F28="","",SUM(G28:P28)*F28) -> 0 | T28: =IF(G28="","",VLOOKUP(A28,'ET Standar Price List'!A:M,4,0)) -> KSML BC LCH/DNR
A29: 47 | B29: ** | D29: =D28+1 -> 20 | E29: KSML HBF | F29: {=_xlfn.XLOOKUP($A29,'ET Standar Price List'!$A:$A,_xlfn.SWITCH($T$4,1,'ET Standar Price List'!$G:$G,2,'ET Standar Price List'!$J:$J,3,'ET Standar Price List'!$M:$M),"XX")} -> 45 | G29: =IF(G$9="","",SUMIFS('DN01'!$J$12:$J$24,'DN01'!$I$12:$I$24,"KSML")+SUMIFS('DN01'!$L$12:$L$24,'DN01'!$I$12:$I$24,"KSML")+SUMIFS('DN01'!$N$12:$N$24,'DN01'!$I$12:$I$24,"KSML")) -> 0 | H29: =IF(H$9="","",SUMIFS('DN02'!$J$12:$J$24,'DN02'!$I$12:$I$24,"KSML")+SUMIFS('DN02'!$L$12:$L$24,'DN02'!$I$12:$I$24,"KSML")+SUMIFS('DN02'!$N$12:$N$24,'DN02'!$I$12:$I$24,"KSML")) -> 0 | I29: =IF(I$9="","",SUMIFS('DN03'!$J$12:$J$24,'DN03'!$I$12:$I$24,"KSML")+SUMIFS('DN03'!$L$12:$L$24,'DN03'!$I$12:$I$24,"KSML")+SUMIFS('DN03'!$N$12:$N$24,'DN03'!$I$12:$I$24,"KSML")) -> 0 | J29: =IF(J$9="","",SUMIFS('DN04'!$J$12:$J$24,'DN04'!$I$12:$I$24,"KSML")+SUMIFS('DN04'!$L$12:$L$24,'DN04'!$I$12:$I$24,"KSML")+SUMIFS('DN04'!$N$12:$N$24,'DN04'!$I$12:$I$24,"KSML")) -> 0 | K29: =IF(K$9="","",SUMIFS('DN05'!$J$12:$J$24,'DN05'!$I$12:$I$24,"KSML")+SUMIFS('DN05'!$L$12:$L$24,'DN05'!$I$12:$I$24,"KSML")+SUMIFS('DN05'!$N$12:$N$24,'DN05'!$I$12:$I$24,"KSML")) | L29: =IF(L$9="","",SUMIFS('DN06'!$J$12:$J$24,'DN06'!$I$12:$I$24,"KSML")+SUMIFS('DN06'!$L$12:$L$24,'DN06'!$I$12:$I$24,"KSML")+SUMIFS('DN06'!$N$12:$N$24,'DN06'!$I$12:$I$24,"KSML")) | M29: =IF(M$9="","",SUMIFS('DN07'!$J$12:$J$24,'DN07'!$I$12:$I$24,"KSML")+SUMIFS('DN07'!$L$12:$L$24,'DN07'!$I$12:$I$24,"KSML")+SUMIFS('DN07'!$N$12:$N$24,'DN07'!$I$12:$I$24,"KSML")) | N29: =IF(N$9="","",SUMIFS('DN08'!$J$12:$J$24,'DN08'!$I$12:$I$24,"KSML")+SUMIFS('DN08'!$L$12:$L$24,'DN08'!$I$12:$I$24,"KSML")+SUMIFS('DN08'!$N$12:$N$24,'DN08'!$I$12:$I$24,"KSML")) | O29: =IF(O$9="","",SUMIFS('DN09'!$J$12:$J$24,'DN09'!$I$12:$I$24,"KSML")+SUMIFS('DN09'!$L$12:$L$24,'DN09'!$I$12:$I$24,"KSML")+SUMIFS('DN09'!$N$12:$N$24,'DN09'!$I$12:$I$24,"KSML")) | P29: =IF(P$9="","",SUMIFS('DN10'!$J$12:$J$24,'DN10'!$I$12:$I$24,"KSML")+SUMIFS('DN10'!$L$12:$L$24,'DN10'!$I$12:$I$24,"KSML")+SUMIFS('DN10'!$N$12:$N$24,'DN10'!$I$12:$I$24,"KSML")) | Q29: =IF(F29="","",SUM(G29:P29)*F29) -> 0
A30: 33 | B30: G17 | D30: =D29+1 -> 21 | E30: ="CYC "&T4&" EY LCH/DNR" -> CYC 3 EY LCH/DNR | F30: {=_xlfn.XLOOKUP($A30,'ET Standar Price List'!$A:$A,_xlfn.SWITCH($T$4,1,'ET Standar Price List'!$G:$G,2,'ET Standar Price List'!$J:$J,3,'ET Standar Price List'!$M:$M),"XX")} -> 14.381359 | G30: =MAX(IF(G$9="","",'DN01'!$G$14+'DN01'!$K$25-10),125) -> 235 | H30: =MAX(IF(H$9="","",'DN02'!$G$14+'DN02'!$K$25-10),125) -> 240 | I30: =MAX(IF(I$9="","",'DN03'!$G$14+'DN03'!$K$25-10),125) -> 230 | J30: =MAX(IF(J$9="","",'DN04'!$G$14+'DN04'!$K$25-10),125) -> 215 | K30: =IF(K$9="","",'DN05'!$G$14+'DN05'!$K$25-10) | L30: =IF(L$9="","",'DN06'!$G$14+'DN06'!$K$25-10) | M30: =IF(M$9="","",'DN07'!$G$14+'DN07'!$K$25-10) | N30: =IF(N$9="","",'DN08'!$G$14+'DN08'!$K$25-10) | O30: =IF(O$9="","",'DN09'!$G$14+'DN09'!$K$25-10) | P30: =IF(P$9="","",'DN10'!$G$14+'DN10'!$K$25-10) | Q30: =IF(F30="","",SUM(G30:P30)*F30) -> 13230.85 | T30: =IF(G30="","",VLOOKUP(A30,'ET Standar Price List'!A:M,4,0)) -> EY LCH/DNR Price per passenger Total
A31: 88 | B31: G16 | D31: =D30+1 -> 22 | E31: EY HBF | F31: {=_xlfn.XLOOKUP($A31,'ET Standar Price List'!$A:$A,_xlfn.SWITCH($T$4,1,'ET Standar Price List'!$G:$G,2,'ET Standar Price List'!$J:$J,3,'ET Standar Price List'!$M:$M),"XX")} -> 11.50308 | G31: =MAX(IF(G$9="","",'DN01'!$G$13+'DN01'!$K$25-10),125) -> 235 | H31: =MAX(IF(H$9="","",'DN02'!$G$13+'DN02'!$K$25-10),125) -> 240 | I31: =MAX(IF(I$9="","",'DN03'!$G$13+'DN03'!$K$25-10),125) -> 230 | J31: =MAX(IF(J$9="","",'DN04'!$G$13+'DN04'!$K$25-10),125) -> 215 | K31: =IF(K$9="","",'DN05'!$G$13+'DN05'!$K$25-10) | L31: =IF(L$9="","",'DN06'!$G$13+'DN06'!$K$25-10) | M31: =IF(M$9="","",'DN07'!$G$13+'DN07'!$K$25-10) | N31: =IF(N$9="","",'DN08'!$G$13+'DN08'!$K$25-10) | O31: =IF(O$9="","",'DN09'!$G$13+'DN09'!$K$25-10) | P31: =IF(P$9="","",'DN10'!$G$13+'DN10'!$K$25-10) | Q31: =IF(F31="","",SUM(G31:P31)*F31) -> 10582.833 | T31: =IF(G31="","",VLOOKUP(A31,'ET Standar Price List'!A:M,4,0)) -> EY HBF Price per passenger Total
A32: 105 | B32: G20 | D32: =D31+1 -> 23 | E32: EY SWH | F32: {=_xlfn.XLOOKUP($A32,'ET Standar Price List'!$A:$A,_xlfn.SWITCH($T$4,1,'ET Standar Price List'!$G:$G,2,'ET Standar Price List'!$J:$J,3,'ET Standar Price List'!$M:$M),"XX")} -> 2.4031838 | G32: =MAX(IF(G$9="","",'DN01'!$G$17+'DN01'!$K$25-10),125) -> 235 | H32: =MAX(IF(H$9="","",'DN02'!$G$17+'DN02'!$K$25-10),125) -> 240 | I32: =MAX(IF(I$9="","",'DN03'!$G$17+'DN03'!$K$25-10),125) -> 230 | J32: =MAX(IF(J$9="","",'DN04'!$G$17+'DN04'!$K$25-10),125) -> 215 | K32: =IF(K$9="","",'DN05'!$G$17+'DN05'!$K$25-10) | L32: =IF(L$9="","",'DN06'!$G$17+'DN06'!$K$25-10) | M32: =IF(M$9="","",'DN07'!$G$17+'DN07'!$K$25-10) | N32: =IF(N$9="","",'DN08'!$G$17+'DN08'!$K$25-10) | O32: =IF(O$9="","",'DN09'!$G$17+'DN09'!$K$25-10) | P32: =IF(P$9="","",'DN10'!$G$17+'DN10'!$K$25-10) | Q32: =IF(F32="","",SUM(G32:P32)*F32) -> 2210.9291 | T32: =IF(G32="","",VLOOKUP(A32,'ET Standar Price List'!A:M,4,0)) -> EY SWH Per passenger Charge Total
A33: 33 | B33: XX | D33: =D32+1 -> 24 | E33: Xtra EC Fasting Meals | F33: {=_xlfn.XLOOKUP($A33,'ET Standar Price List'!$A:$A,_xlfn.SWITCH($T$4,1,'ET Standar Price List'!$G:$G,2,'ET Standar Price List'!$J:$J,3,'ET Standar Price List'!$M:$M),"XX")} -> 14.381359 | G33: =IF(G$9="","",'DN01'!$G$20) -> 0 | H33: =IF(H$9="","",'DN02'!$G$20) -> 0 | I33: =IF(I$9="","",'DN03'!$G$20) -> 0 | J33: =IF(J$9="","",'DN04'!$G$20) -> 0 | K33: =IF(K$9="","",'DN05'!$G$20) | L33: =IF(L$9="","",'DN06'!$G$20) | M33: =IF(M$9="","",'DN07'!$G$20) | N33: =IF(N$9="","",'DN08'!$G$20) | O33: =IF(O$9="","",'DN09'!$G$20) | P33: =IF(P$9="","",'DN10'!$G$20) | Q33: =IF(F33="","",SUM(G33:P33)*F33) -> 0
A34: 42 | B34: ** | D34: =D33+1 -> 25 | E34: ALL IATA EY SPML (NO KSML) DNR | F34: {=_xlfn.XLOOKUP($A34,'ET Standar Price List'!$A:$A,_xlfn.SWITCH($T$4,1,'ET Standar Price List'!$G:$G,2,'ET Standar Price List'!$J:$J,3,'ET Standar Price List'!$M:$M),"XX")} -> 15.68 | G34: =IF(G$9="","",('DN01'!$K$25)-G36) -> 14 | H34: =IF(H$9="","",('DN02'!$K$25)-H36) -> 11 | I34: =IF(I$9="","",('DN03'!$K$25)-I36) -> 14 | J34: =IF(J$9="","",('DN04'!$K$25)-J36) -> 3 | K34: =IF(K$9="","",('DN01'!$K$25)-K36) | L34: =IF(L$9="","",('DN01'!$K$25)-L36) | M34: =IF(M$9="","",('DN01'!$K$25)-M36) | N34: =IF(N$9="","",('DN01'!$K$25)-N36) | O34: =IF(O$9="","",('DN01'!$K$25)-O36) | P34: =IF(P$9="","",('DN01'!$K$25)-P36) | Q34: =IF(F34="","",SUM(G34:P34)*F34) -> 658.56 | T34: =IF(G34="","",VLOOKUP(A34,'ET Standar Price List'!A:M,4,0)) -> ALL IATA EY SPML (NO KSML)
A35: 46 | B35: ** | D35: =D34+1 -> 26 | E35: ALL IATA EY SPML (NO KSML) HBF | F35: {=_xlfn.XLOOKUP($A35,'ET Standar Price List'!$A:$A,_xlfn.SWITCH($T$4,1,'ET Standar Price List'!$G:$G,2,'ET Standar Price List'!$J:$J,3,'ET Standar Price List'!$M:$M),"XX")} -> 11.35 | G35: =IF(G$9="","",('DN01'!$O$25)-G36) -> 14 | H35: =IF(H$9="","",('DN02'!$O$25)-H36) -> 11 | I35: =IF(I$9="","",('DN03'!$O$25)-I37) -> 14 | J35: =IF(J$9="","",('DN04'!$O$25)-J36) -> 3 | K35: =IF(K$9="","",('DN01'!$O$25)-K36) | L35: =IF(L$9="","",('DN01'!$O$25)-L36) | M35: =IF(M$9="","",('DN01'!$O$25)-M36) | N35: =IF(N$9="","",('DN01'!$O$25)-N36) | O35: =IF(O$9="","",('DN01'!$O$25)-O36) | P35: =IF(P$9="","",('DN01'!$O$25)-P36) | Q35: =IF(F35="","",SUM(G35:P35)*F35) -> 476.7 | T35: =IF(G35="","",VLOOKUP(A35,'ET Standar Price List'!A:M,4,0)) -> ALL IATA EY SPML (NO KSML) HBF
A36: 44 | B36: ** | D36: =D35+1 -> 27 | E36: KSML EY | F36: {=_xlfn.XLOOKUP($A36,'ET Standar Price List'!$A:$A,_xlfn.SWITCH($T$4,1,'ET Standar Price List'!$G:$G,2,'ET Standar Price List'!$J:$J,3,'ET Standar Price List'!$M:$M),"XX")} -> 45 | G36: =IF(G$9="","",SUMIFS('DN01'!$K$12:$K$24,'DN01'!$I$12:$I$24,"KSML")+SUMIFS('DN01'!$M$12:$M$24,'DN01'!$I$12:$I$24,"KSML")) -> 0 | H36: =IF(H$9="","",SUMIFS('DN02'!$K$12:$K$24,'DN02'!$I$12:$I$24,"KSML")+SUMIFS('DN02'!$M$12:$M$24,'DN02'!$I$12:$I$24,"KSML")) -> 0 | I36: =IF(I$9="","",SUMIFS('DN03'!$K$12:$K$24,'DN03'!$I$12:$I$24,"KSML")) -> 1 | J36: =IF(J$9="","",SUMIFS('DN04'!$K$12:$K$24,'DN04'!$I$12:$I$24,"KSML")+SUMIFS('DN04'!$M$12:$M$24,'DN04'!$I$12:$I$24,"KSML")) -> 0 | K36: =IF(K$9="","",SUMIFS('DN05'!$K$12:$K$24,'DN05'!$I$12:$I$24,"KSML")+SUMIFS('DN05'!$M$12:$M$24,'DN05'!$I$12:$I$24,"KSML")+SUMIFS('DN05'!$O$12:$O$24,'DN05'!$I$12:$I$24,"KSML")) | L36: =IF(L$9="","",SUMIFS('DN06'!$K$12:$K$24,'DN06'!$I$12:$I$24,"KSML")+SUMIFS('DN06'!$M$12:$M$24,'DN06'!$I$12:$I$24,"KSML")+SUMIFS('DN06'!$O$12:$O$24,'DN06'!$I$12:$I$24,"KSML")) | M36: =IF(M$9="","",SUMIFS('DN07'!$K$12:$K$24,'DN07'!$I$12:$I$24,"KSML")+SUMIFS('DN07'!$M$12:$M$24,'DN07'!$I$12:$I$24,"KSML")+SUMIFS('DN07'!$O$12:$O$24,'DN07'!$I$12:$I$24,"KSML")) | N36: =IF(N$9="","",SUMIFS('DN08'!$K$12:$K$24,'DN08'!$I$12:$I$24,"KSML")+SUMIFS('DN08'!$M$12:$M$24,'DN08'!$I$12:$I$24,"KSML")+SUMIFS('DN08'!$O$12:$O$24,'DN08'!$I$12:$I$24,"KSML")) | O36: =IF(O$9="","",SUMIFS('DN09'!$K$12:$K$24,'DN09'!$I$12:$I$24,"KSML")+SUMIFS('DN09'!$M$12:$M$24,'DN09'!$I$12:$I$24,"KSML")+SUMIFS('DN09'!$O$12:$O$24,'DN09'!$I$12:$I$24,"KSML")) | P36: =IF(P$9="","",SUMIFS('DN10'!$K$12:$K$24,'DN10'!$I$12:$I$24,"KSML")+SUMIFS('DN10'!$M$12:$M$24,'DN10'!$I$12:$I$24,"KSML")+SUMIFS('DN10'!$O$12:$O$24,'DN10'!$I$12:$I$24,"KSML")) | Q36: =IF(F36="","",SUM(G36:P36)*F36) -> 45 | T36: =IF(G36="","",VLOOKUP(A36,'ET Standar Price List'!A:M,4,0)) -> KSML EY LCH/DNR
A37: 48 | B37: ** | D37: =D36+1 -> 28 | E37: KSML HBF | F37: {=_xlfn.XLOOKUP($A37,'ET Standar Price List'!$A:$A,_xlfn.SWITCH($T$4,1,'ET Standar Price List'!$G:$G,2,'ET Standar Price List'!$J:$J,3,'ET Standar Price List'!$M:$M),"XX")} -> 28 | G37: =IF(G$9="","",SUMIFS('DN01'!$O$12:$O$24,'DN01'!$I$12:$I$24,"KSML")) -> 0 | H37: =IF(H$9="","",SUMIFS('DN02'!$O$12:$O$24,'DN02'!$I$12:$I$24,"KSML")) -> 0 | I37: =IF(I$9="","",SUMIFS('DN03'!$O$12:$O$24,'DN03'!$I$12:$I$24,"KSML")) -> 1 | J37: =IF(J$9="","",SUMIFS('DN04'!$O$12:$O$24,'DN04'!$I$12:$I$24,"KSML")) -> 0 | Q37: =IF(F37="","",SUM(G37:P37)*F37) -> 28
A38: DRY | B38: ITEM | D38: =D37+1 -> 29 | E38: {=_xlfn.UNIQUE(_xlfn._xlws.FILTER(_xlfn.VSTACK('DN01:DN13'!$O$30:$O$51),_xlfn.VSTACK('DN01:DN13'!$N$30:$N$51)<>""))} -> 3013499 - Mineral Water 1.5L | F38: =IF(E38="","",VLOOKUP(E38,'DRY ITEM LIST'!B:F,5,0)) -> 4 | G38: =IF(G$9="","",IF($E38=0,0,_xlfn.XLOOKUP($E38,'DN01'!$O$30:$O$51,'DN01'!$N$30:$N$51,0)+IF(LEFT(E38,7)="3013522",-2,0))) -> 100 | H38: =IF(H$9="","",IF($E38=0,0,_xlfn.XLOOKUP($E38,'DN02'!$O$30:$O$51,'DN02'!$N$30:$N$51,0)+IF(LEFT(E38,7)="3013522",-2,0))) -> 36 | I38: =IF(I$9="","",IF($E38=0,0,_xlfn.XLOOKUP($E38,'DN03'!$O$30:$O$51,'DN03'!$N$30:$N$51,0)+IF(LEFT(E38,7)="3013522",-2,0))) -> 48 | J38: =IF(J$9="","",IF($E38=0,0,_xlfn.XLOOKUP($E38,'DN04'!$O$30:$O$51,'DN04'!$N$30:$N$51,0)+IF(LEFT(E38,7)="3013522",-2,0))) -> 90 | K38: =IF(K$9="","",IF($E38=0,0,_xlfn.XLOOKUP($E38,'DN05'!$O$30:$O$51,'DN05'!$N$30:$N$51,0)+IF(LEFT(E38,7)="3013522",-2,0))) | L38: =IF(L$9="","",IF($E38=0,0,_xlfn.XLOOKUP($E38,'DN06'!$O$30:$O$51,'DN06'!$N$30:$N$51,0)+IF(LEFT(E38,7)="3013522",-2,0))) | M38: =IF(M$9="","",IF($E38=0,0,_xlfn.XLOOKUP($E38,'DN07'!$O$30:$O$51,'DN07'!$N$30:$N$51,0)+IF(LEFT(F38,7)="3013522",-2,0))) | N38: =IF(N$9="","",IF($E38=0,0,_xlfn.XLOOKUP($E38,'DN08'!$O$30:$O$51,'DN08'!$N$30:$N$51,0)+IF(LEFT(G38,7)="3013522",-2,0))) | O38: =IF(O$9="","",IF($E38=0,0,_xlfn.XLOOKUP($E38,'DN09'!$O$30:$O$51,'DN09'!$N$30:$N$51,0)+IF(LEFT(H38,7)="3013522",-2,0))) | P38: =IF(P$9="","",IF($E38=0,0,_xlfn.XLOOKUP($E38,'DN10'!$O$30:$O$49,'DN10'!$N$30:$N$49,0)+IF(LEFT(I38,7)="3013522",-2,0))) | Q38: =IF(F38="","",SUM(G38:P38)*F38) -> 1096 | W38: 20 | X38: 3013506 - Juice Apple 1L | Y38: 18 | Z38: 5 | AA38: 90
A39: DRY | B39: ITEM | D39: =D38+1 -> 30 | E39: 3013498 - Mineral Water 330mL | F39: =IF(E39="","",VLOOKUP(E39,'DRY ITEM LIST'!B:F,5,0)) -> 2 | G39: =IF(G$9="","",IF($E39=0,0,_xlfn.XLOOKUP($E39,'DN01'!$O$30:$O$51,'DN01'!$N$30:$N$51,0)+IF(LEFT(E39,7)="3013522",-2,0))) -> 72 | H39: =IF(H$9="","",IF($E39=0,0,_xlfn.XLOOKUP($E39,'DN02'!$O$30:$O$51,'DN02'!$N$30:$N$51,0)+IF(LEFT(E39,7)="3013522",-2,0))) -> 48 | I39: =IF(I$9="","",IF($E39=0,0,_xlfn.XLOOKUP($E39,'DN03'!$O$30:$O$51,'DN03'!$N$30:$N$51,0)+IF(LEFT(E39,7)="3013522",-2,0))) -> 24 | J39: =IF(J$9="","",IF($E39=0,0,_xlfn.XLOOKUP($E39,'DN04'!$O$30:$O$51,'DN04'!$N$30:$N$51,0)+IF(LEFT(E39,7)="3013522",-2,0))) -> 36 | K39: =IF(K$9="","",IF($E39=0,0,_xlfn.XLOOKUP($E39,'DN05'!$O$30:$O$51,'DN05'!$N$30:$N$51,0)+IF(LEFT(E39,7)="3013522",-2,0))) | L39: =IF(L$9="","",IF($E39=0,0,_xlfn.XLOOKUP($E39,'DN06'!$O$30:$O$51,'DN06'!$N$30:$N$51,0)+IF(LEFT(E39,7)="3013522",-2,0))) | M39: =IF(M$9="","",IF($E39=0,0,_xlfn.XLOOKUP($E39,'DN07'!$O$30:$O$51,'DN07'!$N$30:$N$51,0)+IF(LEFT(F39,7)="3013522",-2,0))) | N39: =IF(N$9="","",IF($E39=0,0,_xlfn.XLOOKUP($E39,'DN08'!$O$30:$O$51,'DN08'!$N$30:$N$51,0)+IF(LEFT(G39,7)="3013522",-2,0))) | O39: =IF(O$9="","",IF($E39=0,0,_xlfn.XLOOKUP($E39,'DN09'!$O$30:$O$51,'DN09'!$N$30:$N$51,0)+IF(LEFT(H39,7)="3013522",-2,0))) | P39: =IF(P$9="","",IF($E39=0,0,_xlfn.XLOOKUP($E39,'DN10'!$O$30:$O$49,'DN10'!$N$30:$N$49,0)+IF(LEFT(I39,7)="3013522",-2,0))) | Q39: =IF(F39="","",SUM(G39:P39)*F39) -> 360
A40: DRY | B40: ITEM | D40: =D39+1 -> 31 | E40: 3013495 - Coke 355mL | F40: =IF(E40="","",VLOOKUP(E40,'DRY ITEM LIST'!B:F,5,0)) -> 3 | G40: =IF(G$9="","",IF($E40=0,0,_xlfn.XLOOKUP($E40,'DN01'!$O$30:$O$51,'DN01'!$N$30:$N$51,0)+IF(LEFT(E40,7)="3013522",-2,0))) -> 48 | H40: =IF(H$9="","",IF($E40=0,0,_xlfn.XLOOKUP($E40,'DN02'!$O$30:$O$51,'DN02'!$N$30:$N$51,0)+IF(LEFT(E40,7)="3013522",-2,0))) -> 0 | I40: =IF(I$9="","",IF($E40=0,0,_xlfn.XLOOKUP($E40,'DN03'!$O$30:$O$51,'DN03'!$N$30:$N$51,0)+IF(LEFT(E40,7)="3013522",-2,0))) -> 24 | J40: =IF(J$9="","",IF($E40=0,0,_xlfn.XLOOKUP($E40,'DN04'!$O$30:$O$51,'DN04'!$N$30:$N$51,0)+IF(LEFT(E40,7)="3013522",-2,0))) -> 0 | K40: =IF(K$9="","",IF($E40=0,0,_xlfn.XLOOKUP($E40,'DN05'!$O$30:$O$51,'DN05'!$N$30:$N$51,0)+IF(LEFT(E40,7)="3013522",-2,0))) | L40: =IF(L$9="","",IF($E40=0,0,_xlfn.XLOOKUP($E40,'DN06'!$O$30:$O$51,'DN06'!$N$30:$N$51,0)+IF(LEFT(E40,7)="3013522",-2,0))) | M40: =IF(M$9="","",IF($E40=0,0,_xlfn.XLOOKUP($E40,'DN07'!$O$30:$O$51,'DN07'!$N$30:$N$51,0)+IF(LEFT(F40,7)="3013522",-2,0))) | N40: =IF(N$9="","",IF($E40=0,0,_xlfn.XLOOKUP($E40,'DN08'!$O$30:$O$51,'DN08'!$N$30:$N$51,0)+IF(LEFT(G40,7)="3013522",-2,0))) | O40: =IF(O$9="","",IF($E40=0,0,_xlfn.XLOOKUP($E40,'DN09'!$O$30:$O$51,'DN09'!$N$30:$N$51,0)+IF(LEFT(H40,7)="3013522",-2,0))) | P40: =IF(P$9="","",IF($E40=0,0,_xlfn.XLOOKUP($E40,'DN10'!$O$30:$O$49,'DN10'!$N$30:$N$49,0)+IF(LEFT(I40,7)="3013522",-2,0))) | Q40: =IF(F40="","",SUM(G40:P40)*F40) -> 216 | W40: 21 | X40: 3013499 - Mineral Water 1.5L | Y40: 60 | Z40: 4 | AA40: 240
A41: DRY | B41: ITEM | D41: =D40+1 -> 32 | E41: 3013497 - Sprite 355mL | F41: =IF(E41="","",VLOOKUP(E41,'DRY ITEM LIST'!B:F,5,0)) -> 3 | G41: =IF(G$9="","",IF($E41=0,0,_xlfn.XLOOKUP($E41,'DN01'!$O$30:$O$51,'DN01'!$N$30:$N$51,0)+IF(LEFT(E41,7)="3013522",-2,0))) -> 48 | H41: =IF(H$9="","",IF($E41=0,0,_xlfn.XLOOKUP($E41,'DN02'!$O$30:$O$51,'DN02'!$N$30:$N$51,0)+IF(LEFT(E41,7)="3013522",-2,0))) -> 36 | I41: =IF(I$9="","",IF($E41=0,0,_xlfn.XLOOKUP($E41,'DN03'!$O$30:$O$51,'DN03'!$N$30:$N$51,0)+IF(LEFT(E41,7)="3013522",-2,0))) -> 0 | J41: =IF(J$9="","",IF($E41=0,0,_xlfn.XLOOKUP($E41,'DN04'!$O$30:$O$51,'DN04'!$N$30:$N$51,0)+IF(LEFT(E41,7)="3013522",-2,0))) -> 0 | K41: =IF(K$9="","",IF($E41=0,0,_xlfn.XLOOKUP($E41,'DN05'!$O$30:$O$51,'DN05'!$N$30:$N$51,0)+IF(LEFT(E41,7)="3013522",-2,0))) | L41: =IF(L$9="","",IF($E41=0,0,_xlfn.XLOOKUP($E41,'DN06'!$O$30:$O$51,'DN06'!$N$30:$N$51,0)+IF(LEFT(E41,7)="3013522",-2,0))) | M41: =IF(M$9="","",IF($E41=0,0,_xlfn.XLOOKUP($E41,'DN07'!$O$30:$O$51,'DN07'!$N$30:$N$51,0)+IF(LEFT(F41,7)="3013522",-2,0))) | N41: =IF(N$9="","",IF($E41=0,0,_xlfn.XLOOKUP($E41,'DN08'!$O$30:$O$51,'DN08'!$N$30:$N$51,0)+IF(LEFT(G41,7)="3013522",-2,0))) | O41: =IF(O$9="","",IF($E41=0,0,_xlfn.XLOOKUP($E41,'DN09'!$O$30:$O$51,'DN09'!$N$30:$N$51,0)+IF(LEFT(H41,7)="3013522",-2,0))) | P41: =IF(P$9="","",IF($E41=0,0,_xlfn.XLOOKUP($E41,'DN10'!$O$30:$O$49,'DN10'!$N$30:$N$49,0)+IF(LEFT(I41,7)="3013522",-2,0))) | Q41: =IF(F41="","",SUM(G41:P41)*F41) -> 252 | W41: 22 | X41: 3013498 - Mineral Water 330mL | Y41: 36 | Z41: 2 | AA41: 72
A42: DRY | B42: ITEM | D42: =D41+1 -> 33 | E42: 3013522 - Wet Ice 5kg Bag | F42: =IF(E42="","",VLOOKUP(E42,'DRY ITEM LIST'!B:F,5,0)) -> 5.5 | G42: =IF(G$9="","",IF($E42=0,0,_xlfn.XLOOKUP($E42,'DN01'!$O$30:$O$51,'DN01'!$N$30:$N$51,0)+IF(LEFT(E42,7)="3013522",-2,0))) -> 8 | H42: =IF(H$9="","",IF($E42=0,0,_xlfn.XLOOKUP($E42,'DN02'!$O$30:$O$51,'DN02'!$N$30:$N$51,0)+IF(LEFT(E42,7)="3013522",-2,0))) -> 8 | I42: =IF(I$9="","",IF($E42=0,0,_xlfn.XLOOKUP($E42,'DN03'!$O$30:$O$51,'DN03'!$N$30:$N$51,0)+IF(LEFT(E42,7)="3013522",-2,0))) -> 8 | J42: =IF(J$9="","",IF($E42=0,0,_xlfn.XLOOKUP($E42,'DN04'!$O$30:$O$51,'DN04'!$N$30:$N$51,0)+IF(LEFT(E42,7)="3013522",-2,0)))+10 -> 18 | K42: =IF(K$9="","",IF($E42=0,0,_xlfn.XLOOKUP($E42,'DN05'!$O$30:$O$51,'DN05'!$N$30:$N$51,0)+IF(LEFT(E42,7)="3013522",-2,0))) | L42: =IF(L$9="","",IF($E42=0,0,_xlfn.XLOOKUP($E42,'DN06'!$O$30:$O$51,'DN06'!$N$30:$N$51,0)+IF(LEFT(E42,7)="3013522",-2,0))) | M42: =IF(M$9="","",IF($E42=0,0,_xlfn.XLOOKUP($E42,'DN07'!$O$30:$O$51,'DN07'!$N$30:$N$51,0)+IF(LEFT(F42,7)="3013522",-2,0))) | N42: =IF(N$9="","",IF($E42=0,0,_xlfn.XLOOKUP($E42,'DN08'!$O$30:$O$51,'DN08'!$N$30:$N$51,0)+IF(LEFT(G42,7)="3013522",-2,0))) | O42: =IF(O$9="","",IF($E42=0,0,_xlfn.XLOOKUP($E42,'DN09'!$O$30:$O$51,'DN09'!$N$30:$N$51,0)+IF(LEFT(H42,7)="3013522",-2,0))) | P42: =IF(P$9="","",IF($E42=0,0,_xlfn.XLOOKUP($E42,'DN10'!$O$30:$O$49,'DN10'!$N$30:$N$49,0)+IF(LEFT(I42,7)="3013522",-2,0))) | Q42: =IF(F42="","",SUM(G42:P42)*F42) -> 231 | W42: 23 | X42: 3013495 - Coke 355mL | Y42: 48 | Z42: 3 | AA42: 144
A43: DRY | B43: ITEM | D43: =D42+1 -> 34 | E43: 3013496 - Coke Light 355mL | F43: =IF(E43="","",VLOOKUP(E43,'DRY ITEM LIST'!B:F,5,0)) -> 3 | G43: =IF(G$9="","",IF($E43=0,0,_xlfn.XLOOKUP($E43,'DN01'!$O$30:$O$51,'DN01'!$N$30:$N$51,0)+IF(LEFT(E43,7)="3013522",-2,0))) -> 24 | H43: =IF(H$9="","",IF($E43=0,0,_xlfn.XLOOKUP($E43,'DN02'!$O$30:$O$51,'DN02'!$N$30:$N$51,0)+IF(LEFT(E43,7)="3013522",-2,0))) -> 0 | I43: =IF(I$9="","",IF($E43=0,0,_xlfn.XLOOKUP($E43,'DN03'!$O$30:$O$51,'DN03'!$N$30:$N$51,0)+IF(LEFT(E43,7)="3013522",-2,0))) -> 12 | J43: =IF(J$9="","",IF($E43=0,0,_xlfn.XLOOKUP($E43,'DN04'!$O$30:$O$51,'DN04'!$N$30:$N$51,0)+IF(LEFT(E43,7)="3013522",-2,0))) -> 24 | K43: =IF(K$9="","",IF($E43=0,0,_xlfn.XLOOKUP($E43,'DN05'!$O$30:$O$51,'DN05'!$N$30:$N$51,0)+IF(LEFT(E43,7)="3013522",-2,0))) | L43: =IF(L$9="","",IF($E43=0,0,_xlfn.XLOOKUP($E43,'DN06'!$O$30:$O$51,'DN06'!$N$30:$N$51,0)+IF(LEFT(E43,7)="3013522",-2,0))) | M43: =IF(M$9="","",IF($E43=0,0,_xlfn.XLOOKUP($E43,'DN07'!$O$30:$O$51,'DN07'!$N$30:$N$51,0)+IF(LEFT(F43,7)="3013522",-2,0))) | N43: =IF(N$9="","",IF($E43=0,0,_xlfn.XLOOKUP($E43,'DN08'!$O$30:$O$51,'DN08'!$N$30:$N$51,0)+IF(LEFT(G43,7)="3013522",-2,0))) | O43: =IF(O$9="","",IF($E43=0,0,_xlfn.XLOOKUP($E43,'DN09'!$O$30:$O$51,'DN09'!$N$30:$N$51,0)+IF(LEFT(H43,7)="3013522",-2,0))) | P43: =IF(P$9="","",IF($E43=0,0,_xlfn.XLOOKUP($E43,'DN10'!$O$30:$O$49,'DN10'!$N$30:$N$49,0)+IF(LEFT(I43,7)="3013522",-2,0))) | Q43: =IF(F43="","",SUM(G43:P43)*F43) -> 180 | W43: 24 | X43: 3013497 - Sprite 355mL | Y43: 18 | Z43: 3 | AA43: 54
A44: DRY | B44: ITEM | D44: =D43+1 -> 35 | E44: 3013502 - Soda Water 355L | F44: =IF(E44="","",VLOOKUP(E44,'DRY ITEM LIST'!B:F,5,0)) -> 3 | G44: =IF(G$9="","",IF($E44=0,0,_xlfn.XLOOKUP($E44,'DN01'!$O$30:$O$51,'DN01'!$N$30:$N$51,0)+IF(LEFT(E44,7)="3013522",-2,0))) -> 12 | H44: =IF(H$9="","",IF($E44=0,0,_xlfn.XLOOKUP($E44,'DN02'!$O$30:$O$51,'DN02'!$N$30:$N$51,0)+IF(LEFT(E44,7)="3013522",-2,0))) -> 0 | I44: =IF(I$9="","",IF($E44=0,0,_xlfn.XLOOKUP($E44,'DN03'!$O$30:$O$51,'DN03'!$N$30:$N$51,0)+IF(LEFT(E44,7)="3013522",-2,0))) -> 0 | J44: =IF(J$9="","",IF($E44=0,0,_xlfn.XLOOKUP($E44,'DN04'!$O$30:$O$51,'DN04'!$N$30:$N$51,0)+IF(LEFT(E44,7)="3013522",-2,0))) -> 0 | K44: =IF(K$9="","",IF($E44=0,0,_xlfn.XLOOKUP($E44,'DN05'!$O$30:$O$51,'DN05'!$N$30:$N$51,0)+IF(LEFT(E44,7)="3013522",-2,0))) | L44: =IF(L$9="","",IF($E44=0,0,_xlfn.XLOOKUP($E44,'DN06'!$O$30:$O$51,'DN06'!$N$30:$N$51,0)+IF(LEFT(E44,7)="3013522",-2,0))) | M44: =IF(M$9="","",IF($E44=0,0,_xlfn.XLOOKUP($E44,'DN07'!$O$30:$O$51,'DN07'!$N$30:$N$51,0)+IF(LEFT(F44,7)="3013522",-2,0))) | N44: =IF(N$9="","",IF($E44=0,0,_xlfn.XLOOKUP($E44,'DN08'!$O$30:$O$51,'DN08'!$N$30:$N$51,0)+IF(LEFT(G44,7)="3013522",-2,0))) | O44: =IF(O$9="","",IF($E44=0,0,_xlfn.XLOOKUP($E44,'DN09'!$O$30:$O$51,'DN09'!$N$30:$N$51,0)+IF(LEFT(H44,7)="3013522",-2,0))) | P44: =IF(P$9="","",IF($E44=0,0,_xlfn.XLOOKUP($E44,'DN05'!$O$30:$O$47,'DN05'!$N$30:$N$47,0)+IF(LEFT(J44,7)="3013522",-2,0))) | Q44: =IF(F44="","",SUM(G44:P44)*F44) -> 36 | W44: 25 | X44: 3013502 - Soda Water 355L | Y44: 18 | Z44: 3 | AA44: 54
A45: DRY | B45: ITEM | D45: =D44+1 -> 36 | E45: 3013538 - Fruit Platters | F45: =IF(E45="","",VLOOKUP(E45,'DRY ITEM LIST'!B:F,5,0)) -> 16.61 | G45: =IF(G$9="","",IF($E45=0,0,_xlfn.XLOOKUP($E45,'DN01'!$O$30:$O$51,'DN01'!$N$30:$N$51,0)+IF(LEFT(E45,7)="3013522",-2,0))) -> 11.666667 | H45: =IF(H$9="","",IF($E45=0,0,_xlfn.XLOOKUP($E45,'DN02'!$O$30:$O$51,'DN02'!$N$30:$N$51,0)+IF(LEFT(E45,7)="3013522",-2,0))) -> 14 | I45: =IF(I$9="","",IF($E45=0,0,_xlfn.XLOOKUP($E45,'DN03'!$O$30:$O$51,'DN03'!$N$30:$N$51,0)+IF(LEFT(E45,7)="3013522",-2,0))) -> 13.333333 | J45: =IF(J$9="","",IF($E45=0,0,_xlfn.XLOOKUP($E45,'DN04'!$O$30:$O$51,'DN04'!$N$30:$N$51,0)+IF(LEFT(E45,7)="3013522",-2,0))) -> 12.666667 | K45: =IF(K$9="","",IF($E45=0,0,_xlfn.XLOOKUP($E45,'DN05'!$O$30:$O$51,'DN05'!$N$30:$N$51,0)+IF(LEFT(E45,7)="3013522",-2,0))) | L45: =IF(L$9="","",IF($E45=0,0,_xlfn.XLOOKUP($E45,'DN06'!$O$30:$O$51,'DN06'!$N$30:$N$51,0)+IF(LEFT(E45,7)="3013522",-2,0))) | M45: =IF(M$9="","",IF($E45=0,0,_xlfn.XLOOKUP($E45,'DN07'!$O$30:$O$51,'DN07'!$N$30:$N$51,0)+IF(LEFT(F45,7)="3013522",-2,0))) | N45: =IF(N$9="","",IF($E45=0,0,_xlfn.XLOOKUP($E45,'DN08'!$O$30:$O$51,'DN08'!$N$30:$N$51,0)+IF(LEFT(G45,7)="3013522",-2,0))) | O45: =IF(O$9="","",IF($E45=0,0,_xlfn.XLOOKUP($E45,'DN09'!$O$30:$O$51,'DN09'!$N$30:$N$51,0)+IF(LEFT(H45,7)="3013522",-2,0))) | P45: =IF(P$9="","",IF($E45=0,0,_xlfn.XLOOKUP($E45,'DN10'!$O$30:$O$49,'DN10'!$N$30:$N$49,0)+IF(LEFT(I45,7)="3013522",-2,0))) | Q45: =IF(F45="","",SUM(G45:P45)*F45) -> 858.18333 | W45: 26 | X45: 3013503 - Tonic Water 355mL | Y45: 12 | Z45: 3 | AA45: 36
A46: DRY | B46: ITEM | D46: =D45+1 -> 37 | E46: 3013540 - Ginger Ale 355mL | F46: =IF(E46="","",VLOOKUP(E46,'DRY ITEM LIST'!B:F,5,0)) -> 3 | G46: =IF(G$9="","",IF($E46=0,0,_xlfn.XLOOKUP($E46,'DN01'!$O$30:$O$51,'DN01'!$N$30:$N$51,0)+IF(LEFT(E46,7)="3013522",-2,0))) -> 24 | H46: =IF(H$9="","",IF($E46=0,0,_xlfn.XLOOKUP($E46,'DN02'!$O$30:$O$51,'DN02'!$N$30:$N$51,0)+IF(LEFT(E46,7)="3013522",-2,0))) -> 0 | I46: =IF(I$9="","",IF($E46=0,0,_xlfn.XLOOKUP($E46,'DN03'!$O$30:$O$51,'DN03'!$N$30:$N$51,0)+IF(LEFT(E46,7)="3013522",-2,0))) -> 12 | J46: =IF(J$9="","",IF($E46=0,0,_xlfn.XLOOKUP($E46,'DN04'!$O$30:$O$51,'DN04'!$N$30:$N$51,0)+IF(LEFT(E46,7)="3013522",-2,0))) -> 36 | K46: =IF(K$9="","",IF($E46=0,0,_xlfn.XLOOKUP($E46,'DN05'!$O$30:$O$51,'DN05'!$N$30:$N$51,0)+IF(LEFT(E46,7)="3013522",-2,0))) | L46: =IF(L$9="","",IF($E46=0,0,_xlfn.XLOOKUP($E46,'DN06'!$O$30:$O$51,'DN06'!$N$30:$N$51,0)+IF(LEFT(E46,7)="3013522",-2,0))) | M46: =IF(M$9="","",IF($E46=0,0,_xlfn.XLOOKUP($E46,'DN07'!$O$30:$O$51,'DN07'!$N$30:$N$51,0)+IF(LEFT(F46,7)="3013522",-2,0))) | N46: =IF(N$9="","",IF($E46=0,0,_xlfn.XLOOKUP($E46,'DN08'!$O$30:$O$51,'DN08'!$N$30:$N$51,0)+IF(LEFT(G46,7)="3013522",-2,0))) | O46: =IF(O$9="","",IF($E46=0,0,_xlfn.XLOOKUP($E46,'DN09'!$O$30:$O$51,'DN09'!$N$30:$N$51,0)+IF(LEFT(H46,7)="3013522",-2,0))) | P46: =IF(P$9="","",IF($E46=0,0,_xlfn.XLOOKUP($E46,'DN10'!$O$30:$O$49,'DN10'!$N$30:$N$49,0)+IF(LEFT(I46,7)="3013522",-2,0))) | Q46: =IF(F46="","",SUM(G46:P46)*F46) -> 216
A47: DRY | B47: ITEM | D47: =D46+1 -> 38 | E47: 3013541 - Sparkling Water | F47: =IF(E47="","",VLOOKUP(E47,'DRY ITEM LIST'!B:F,5,0)) -> 3.89 | G47: =IF(G$9="","",IF($E47=0,0,_xlfn.XLOOKUP($E47,'DN01'!$O$30:$O$51,'DN01'!$N$30:$N$51,0)+IF(LEFT(E47,7)="3013522",-2,0))) -> 8 | H47: =IF(H$9="","",IF($E47=0,0,_xlfn.XLOOKUP($E47,'DN02'!$O$30:$O$51,'DN02'!$N$30:$N$51,0)+IF(LEFT(E47,7)="3013522",-2,0))) -> 0 | I47: =IF(I$9="","",IF($E47=0,0,_xlfn.XLOOKUP($E47,'DN03'!$O$30:$O$51,'DN03'!$N$30:$N$51,0)+IF(LEFT(E47,7)="3013522",-2,0))) -> 12 | J47: =IF(J$9="","",IF($E47=0,0,_xlfn.XLOOKUP($E47,'DN04'!$O$30:$O$51,'DN04'!$N$30:$N$51,0)+IF(LEFT(E47,7)="3013522",-2,0))) -> 24 | K47: =IF(K$9="","",IF($E47=0,0,_xlfn.XLOOKUP($E47,'DN05'!$O$30:$O$51,'DN05'!$N$30:$N$51,0)+IF(LEFT(E47,7)="3013522",-2,0))) | L47: =IF(L$9="","",IF($E47=0,0,_xlfn.XLOOKUP($E47,'DN06'!$O$30:$O$51,'DN06'!$N$30:$N$51,0)+IF(LEFT(E47,7)="3013522",-2,0))) | M47: =IF(M$9="","",IF($E47=0,0,_xlfn.XLOOKUP($E47,'DN07'!$O$30:$O$51,'DN07'!$N$30:$N$51,0)+IF(LEFT(F47,7)="3013522",-2,0))) | N47: =IF(N$9="","",IF($E47=0,0,_xlfn.XLOOKUP($E47,'DN08'!$O$30:$O$51,'DN08'!$N$30:$N$51,0)+IF(LEFT(G47,7)="3013522",-2,0))) | O47: =IF(O$9="","",IF($E47=0,0,_xlfn.XLOOKUP($E47,'DN09'!$O$30:$O$51,'DN09'!$N$30:$N$51,0)+IF(LEFT(H47,7)="3013522",-2,0))) | P47: =IF(P$9="","",IF($E47=0,0,_xlfn.XLOOKUP($E47,'DN10'!$O$30:$O$49,'DN10'!$N$30:$N$49,0)+IF(LEFT(I47,7)="3013522",-2,0))) | Q47: =IF(F47="","",SUM(G47:P47)*F47) -> 171.16
A48: DRY | B48: ITEM | D48: =D47+1 -> 39 | E48: 3013505 - Juice Orange 1L | F48: =IF(E48="","",VLOOKUP(E48,'DRY ITEM LIST'!B:F,5,0)) -> 4.5 | G48: =IF(G$9="","",IF($E48=0,0,_xlfn.XLOOKUP($E48,'DN01'!$O$30:$O$51,'DN01'!$N$30:$N$51,0)+IF(LEFT(E48,7)="3013522",-2,0))) -> 0 | H48: =IF(H$9="","",IF($E48=0,0,_xlfn.XLOOKUP($E48,'DN02'!$O$30:$O$51,'DN02'!$N$30:$N$51,0)+IF(LEFT(E48,7)="3013522",-2,0))) -> 2 | I48: =IF(I$9="","",IF($E48=0,0,_xlfn.XLOOKUP($E48,'DN03'!$O$30:$O$51,'DN03'!$N$30:$N$51,0)+IF(LEFT(E48,7)="3013522",-2,0))) -> 6 | J48: =IF(J$9="","",IF($E48=0,0,_xlfn.XLOOKUP($E48,'DN04'!$O$30:$O$51,'DN04'!$N$30:$N$51,0)+IF(LEFT(E48,7)="3013522",-2,0))) -> 2 | K48: =IF(K$9="","",IF($E48=0,0,_xlfn.XLOOKUP($E48,'DN05'!$O$30:$O$51,'DN05'!$N$30:$N$51,0)+IF(LEFT(E48,7)="3013522",-2,0))) | L48: =IF(L$9="","",IF($E48=0,0,_xlfn.XLOOKUP($E48,'DN06'!$O$30:$O$51,'DN06'!$N$30:$N$51,0)+IF(LEFT(E48,7)="3013522",-2,0))) | M48: =IF(M$9="","",IF($E48=0,0,_xlfn.XLOOKUP($E48,'DN07'!$O$30:$O$51,'DN07'!$N$30:$N$51,0)+IF(LEFT(F48,7)="3013522",-2,0))) | N48: =IF(N$9="","",IF($E48=0,0,_xlfn.XLOOKUP($E48,'DN08'!$O$30:$O$51,'DN08'!$N$30:$N$51,0)+IF(LEFT(G48,7)="3013522",-2,0))) | O48: =IF(O$9="","",IF($E48=0,0,_xlfn.XLOOKUP($E48,'DN09'!$O$30:$O$51,'DN09'!$N$30:$N$51,0)+IF(LEFT(H48,7)="3013522",-2,0))) | P48: =IF(P$9="","",IF($E48=0,0,_xlfn.XLOOKUP($E48,'DN10'!$O$30:$O$49,'DN10'!$N$30:$N$49,0)+IF(LEFT(I48,7)="3013522",-2,0))) | Q48: =IF(F48="","",SUM(G48:P48)*F48) -> 45
A49: DRY | B49: ITEM | D49: =D48+1 -> 40 | E49: 3013506 - Juice Apple 1L | F49: =IF(E49="","",VLOOKUP(E49,'DRY ITEM LIST'!B:F,5,0)) -> 4.5 | G49: =IF(G$9="","",IF($E49=0,0,_xlfn.XLOOKUP($E49,'DN01'!$O$30:$O$51,'DN01'!$N$30:$N$51,0)+IF(LEFT(E49,7)="3013522",-2,0))) -> 0 | H49: =IF(H$9="","",IF($E49=0,0,_xlfn.XLOOKUP($E49,'DN02'!$O$30:$O$51,'DN02'!$N$30:$N$51,0)+IF(LEFT(E49,7)="3013522",-2,0))) -> 16 | I49: =IF(I$9="","",IF($E49=0,0,_xlfn.XLOOKUP($E49,'DN03'!$O$30:$O$51,'DN03'!$N$30:$N$51,0)+IF(LEFT(E49,7)="3013522",-2,0))) -> 0 | J49: =IF(J$9="","",IF($E49=0,0,_xlfn.XLOOKUP($E49,'DN04'!$O$30:$O$51,'DN04'!$N$30:$N$51,0)+IF(LEFT(E49,7)="3013522",-2,0))) -> 12 | K49: =IF(K$9="","",IF($E49=0,0,_xlfn.XLOOKUP($E49,'DN05'!$O$30:$O$51,'DN05'!$N$30:$N$51,0)+IF(LEFT(E49,7)="3013522",-2,0))) | L49: =IF(L$9="","",IF($E49=0,0,_xlfn.XLOOKUP($E49,'DN06'!$O$30:$O$51,'DN06'!$N$30:$N$51,0)+IF(LEFT(E49,7)="3013522",-2,0))) | M49: =IF(M$9="","",IF($E49=0,0,_xlfn.XLOOKUP($E49,'DN07'!$O$30:$O$51,'DN07'!$N$30:$N$51,0)+IF(LEFT(F49,7)="3013522",-2,0))) | N49: =IF(N$9="","",IF($E49=0,0,_xlfn.XLOOKUP($E49,'DN08'!$O$30:$O$51,'DN08'!$N$30:$N$51,0)+IF(LEFT(G49,7)="3013522",-2,0))) | O49: =IF(O$9="","",IF($E49=0,0,_xlfn.XLOOKUP($E49,'DN09'!$O$30:$O$51,'DN09'!$N$30:$N$51,0)+IF(LEFT(H49,7)="3013522",-2,0))) | P49: =IF(P$9="","",IF($E49=0,0,_xlfn.XLOOKUP($E49,'DN10'!$O$30:$O$49,'DN10'!$N$30:$N$49,0)+IF(LEFT(I49,7)="3013522",-2,0))) | Q49: =IF(F49="","",SUM(G49:P49)*F49) -> 126
A50: DRY | B50: ITEM | D50: =D49+1 -> 41 | E50: 3013503 - Tonic Water 355mL | F50: =IF(E50="","",VLOOKUP(E50,'DRY ITEM LIST'!B:F,5,0)) -> 3 | G50: =IF(G$9="","",IF($E50=0,0,_xlfn.XLOOKUP($E50,'DN01'!$O$30:$O$50,'DN01'!$N$30:$N$50,0)+IF(LEFT(E50,7)="3013522",-2,0))) -> 0 | H50: =IF(H$9="","",IF($E50=0,0,_xlfn.XLOOKUP($E50,'DN02'!$O$30:$O$51,'DN02'!$N$30:$N$51,0)+IF(LEFT(E50,7)="3013522",-2,0))) -> 0 | I50: =IF(I$9="","",IF($E50=0,0,_xlfn.XLOOKUP($E50,'DN03'!$O$30:$O$51,'DN03'!$N$30:$N$51,0)+IF(LEFT(E50,7)="3013522",-2,0))) -> 12 | J50: =IF(J$9="","",IF($E50=0,0,_xlfn.XLOOKUP($E50,'DN04'!$O$30:$O$51,'DN04'!$N$30:$N$51,0)+IF(LEFT(E50,7)="3013522",-2,0))) -> 0 | K50: =IF(K$9="","",IF($E50=0,0,_xlfn.XLOOKUP($E50,'DN05'!$O$30:$O$51,'DN05'!$N$30:$N$51,0)+IF(LEFT(E50,7)="3013522",-2,0))) | L50: =IF(L$9="","",IF($E50=0,0,_xlfn.XLOOKUP($E50,'DN06'!$O$30:$O$51,'DN06'!$N$30:$N$51,0)+IF(LEFT(E50,7)="3013522",-2,0))) | M50: =IF(M$9="","",IF($E50=0,0,_xlfn.XLOOKUP($E50,'DN07'!$O$30:$O$51,'DN07'!$N$30:$N$51,0)+IF(LEFT(F50,7)="3013522",-2,0))) | N50: =IF(N$9="","",IF($E50=0,0,_xlfn.XLOOKUP($E50,'DN08'!$O$30:$O$51,'DN08'!$N$30:$N$51,0)+IF(LEFT(G50,7)="3013522",-2,0))) | O50: =IF(O$9="","",IF($E50=0,0,_xlfn.XLOOKUP($E50,'DN09'!$O$30:$O$51,'DN09'!$N$30:$N$51,0)+IF(LEFT(H50,7)="3013522",-2,0))) | P50: =IF(P$9="","",IF($E50=0,0,_xlfn.XLOOKUP($E50,'DN10'!$O$30:$O$49,'DN10'!$N$30:$N$49,0)+IF(LEFT(I50,7)="3013522",-2,0))) | Q50: =IF(F50="","",SUM(G50:P50)*F50) -> 36
A51: DRY | B51: ITEM | D51: =D50+1 -> 42 | E51: 3013542 - Creamer | F51: =IF(E51="","",VLOOKUP(E51,'DRY ITEM LIST'!B:F,5,0)) -> 0.2 | G51: =IF(G$9="","",IF($E51=0,0,_xlfn.XLOOKUP($E51,'DN01'!$O$30:$O$50,'DN01'!$N$30:$N$50,0)+IF(LEFT(E51,7)="3013522",-2,0))) -> 0 | H51: =IF(H$9="","",IF($E51=0,0,_xlfn.XLOOKUP($E51,'DN02'!$O$30:$O$51,'DN02'!$N$30:$N$51,0)+IF(LEFT(E51,7)="3013522",-2,0))) -> 0 | I51: =IF(I$9="","",IF($E51=0,0,_xlfn.XLOOKUP($E51,'DN03'!$O$30:$O$51,'DN03'!$N$30:$N$51,0)+IF(LEFT(E51,7)="3013522",-2,0))) -> 0 | J51: =IF(J$9="","",IF($E51=0,0,_xlfn.XLOOKUP($E51,'DN04'!$O$30:$O$51,'DN04'!$N$30:$N$51,0)+IF(LEFT(E51,7)="3013522",-2,0))) -> 0 | K51: =IF(K$9="","",IF($E51=0,0,_xlfn.XLOOKUP($E51,'DN05'!$O$30:$O$51,'DN05'!$N$30:$N$51,0)+IF(LEFT(E51,7)="3013522",-2,0))) | L51: =IF(L$9="","",IF($E51=0,0,_xlfn.XLOOKUP($E51,'DN06'!$O$30:$O$51,'DN06'!$N$30:$N$51,0)+IF(LEFT(E51,7)="3013522",-2,0))) | M51: =IF(M$9="","",IF($E51=0,0,_xlfn.XLOOKUP($E51,'DN07'!$O$30:$O$51,'DN07'!$N$30:$N$51,0)+IF(LEFT(F51,7)="3013522",-2,0))) | N51: =IF(N$9="","",IF($E51=0,0,_xlfn.XLOOKUP($E51,'DN08'!$O$30:$O$51,'DN08'!$N$30:$N$51,0)+IF(LEFT(G51,7)="3013522",-2,0))) | O51: =IF(O$9="","",IF($E51=0,0,_xlfn.XLOOKUP($E51,'DN09'!$O$30:$O$51,'DN09'!$N$30:$N$51,0)+IF(LEFT(H51,7)="3013522",-2,0))) | P51: =IF(P$9="","",IF($E51=0,0,_xlfn.XLOOKUP($E51,'DN10'!$O$30:$O$49,'DN10'!$N$30:$N$49,0)+IF(LEFT(I51,7)="3013522",-2,0))) | Q51: =IF(F51="","",SUM(G51:P51)*F51) -> 0
A52: DRY | B52: ITEM | D52: =D51+1 -> 43 | E52: 3013534 - Hand Towel Roll | F52: =IF(E52="","",VLOOKUP(E52,'DRY ITEM LIST'!B:F,5,0)) -> 2.75 | G52: =IF(G$9="","",IF($E52=0,0,_xlfn.XLOOKUP($E52,'DN01'!$O$30:$O$50,'DN01'!$N$30:$N$50,0)+IF(LEFT(E52,7)="3013522",-2,0))) -> 0 | H52: =IF(H$9="","",IF($E52=0,0,_xlfn.XLOOKUP($E52,'DN02'!$O$30:$O$51,'DN02'!$N$30:$N$51,0)+IF(LEFT(E52,7)="3013522",-2,0))) -> 0 | I52: =IF(I$9="","",IF($E52=0,0,_xlfn.XLOOKUP($E52,'DN03'!$O$30:$O$51,'DN03'!$N$30:$N$51,0)+IF(LEFT(E52,7)="3013522",-2,0))) -> 0 | J52: =IF(J$9="","",IF($E52=0,0,_xlfn.XLOOKUP($E52,'DN04'!$O$30:$O$51,'DN04'!$N$30:$N$51,0)+IF(LEFT(E52,7)="3013522",-2,0))) -> 0 | K52: =IF(K$9="","",IF($E52=0,0,_xlfn.XLOOKUP($E52,'DN05'!$O$30:$O$51,'DN05'!$N$30:$N$51,0)+IF(LEFT(E52,7)="3013522",-2,0))) | L52: =IF(L$9="","",IF($E52=0,0,_xlfn.XLOOKUP($E52,'DN06'!$O$30:$O$51,'DN06'!$N$30:$N$51,0)+IF(LEFT(E52,7)="3013522",-2,0))) | M52: =IF(M$9="","",IF($E52=0,0,_xlfn.XLOOKUP($E52,'DN07'!$O$30:$O$51,'DN07'!$N$30:$N$51,0)+IF(LEFT(F52,7)="3013522",-2,0))) | N52: =IF(N$9="","",IF($E52=0,0,_xlfn.XLOOKUP($E52,'DN08'!$O$30:$O$51,'DN08'!$N$30:$N$51,0)+IF(LEFT(G52,7)="3013522",-2,0))) | O52: =IF(O$9="","",IF($E52=0,0,_xlfn.XLOOKUP($E52,'DN09'!$O$30:$O$51,'DN09'!$N$30:$N$51,0)+IF(LEFT(H52,7)="3013522",-2,0))) | P52: =IF(P$9="","",IF($E52=0,0,_xlfn.XLOOKUP($E52,'DN10'!$O$30:$O$49,'DN10'!$N$30:$N$49,0)+IF(LEFT(I52,7)="3013522",-2,0))) | Q52: =IF(F52="","",SUM(G52:P52)*F52) -> 0
A53: DRY | B53: ITEM | D53: =D52+1 -> 44 | E53: Xtra - Bulk Tray - Vegetarian (Fasting) | F53: =IF(E53="","",VLOOKUP(E53,'DRY ITEM LIST'!B:F,5,0)) -> 118.35 | G53: =IF(G$9="","",IF($E53=0,0,_xlfn.XLOOKUP($E53,'DN01'!$O$30:$O$49,'DN01'!$N$30:$N$49,0)+IF(LEFT(E53,7)="3013522",-2,0))) -> 0 | H53: =IF(H$9="","",IF($E53=0,0,_xlfn.XLOOKUP($E53,'DN02'!$O$30:$O$51,'DN02'!$N$30:$N$51,0)+IF(LEFT(E53,7)="3013522",-2,0))) -> 0 | I53: =IF(I$9="","",IF($E53=0,0,_xlfn.XLOOKUP($E53,'DN03'!$O$30:$O$51,'DN03'!$N$30:$N$51,0)+IF(LEFT(E53,7)="3013522",-2,0))) -> 0 | J53: =IF(J$9="","",IF($E53=0,0,_xlfn.XLOOKUP($E53,'DN04'!$O$30:$O$51,'DN04'!$N$30:$N$51,0)+IF(LEFT(E53,7)="3013522",-2,0))) -> 0 | K53: =IF(K$9="","",IF($E53=0,0,_xlfn.XLOOKUP($E53,'DN05'!$O$30:$O$51,'DN05'!$N$30:$N$51,0)+IF(LEFT(E53,7)="3013522",-2,0))) | L53: =IF(L$9="","",IF($E53=0,0,_xlfn.XLOOKUP($E53,'DN06'!$O$30:$O$51,'DN06'!$N$30:$N$51,0)+IF(LEFT(E53,7)="3013522",-2,0))) | M53: =IF(M$9="","",IF($E53=0,0,_xlfn.XLOOKUP($E53,'DN07'!$O$30:$O$49,'DN07'!$N$30:$N$49,0)+IF(LEFT(F53,7)="3013522",-2,0))) | N53: =IF(N$9="","",IF($E53=0,0,_xlfn.XLOOKUP($E53,'DN08'!$O$30:$O$49,'DN08'!$N$30:$N$49,0)+IF(LEFT(G53,7)="3013522",-2,0))) | O53: =IF(O$9="","",IF($E53=0,0,_xlfn.XLOOKUP($E53,'DN09'!$O$30:$O$51,'DN09'!$N$30:$N$51,0)+IF(LEFT(H53,7)="3013522",-2,0))) | P53: =IF(P$9="","",IF($E53=0,0,_xlfn.XLOOKUP($E53,'DN10'!$O$30:$O$49,'DN10'!$N$30:$N$49,0)+IF(LEFT(I53,7)="3013522",-2,0))) | Q53: =IF(F53="","",SUM(G53:P53)*F53) -> 0
A54: DRY | B54: ITEM | D54: =D53+1 -> 45 | E54: Xtra - Bulk Tray - Pasta (Fasting) | F54: =IF(E54="","",VLOOKUP(E54,'DRY ITEM LIST'!B:F,5,0)) -> 128.25 | G54: =IF(G$9="","",IF($E54=0,0,_xlfn.XLOOKUP($E54,'DN01'!$O$30:$O$49,'DN01'!$N$30:$N$49,0)+IF(LEFT(E54,7)="3013522",-2,0))) -> 0 | H54: =IF(H$9="","",IF($E54=0,0,_xlfn.XLOOKUP($E54,'DN02'!$O$30:$O$51,'DN02'!$N$30:$N$51,0)+IF(LEFT(E54,7)="3013522",-2,0))) -> 0 | I54: =IF(I$9="","",IF($E54=0,0,_xlfn.XLOOKUP($E54,'DN03'!$O$30:$O$51,'DN03'!$N$30:$N$51,0)+IF(LEFT(E54,7)="3013522",-2,0))) -> 0 | J54: =IF(J$9="","",IF($E54=0,0,_xlfn.XLOOKUP($E54,'DN04'!$O$30:$O$51,'DN04'!$N$30:$N$51,0)+IF(LEFT(E54,7)="3013522",-2,0))) -> 0 | K54: =IF(K$9="","",IF($E54=0,0,_xlfn.XLOOKUP($E54,'DN05'!$O$30:$O$51,'DN05'!$N$30:$N$51,0)+IF(LEFT(E54,7)="3013522",-2,0))) | L54: =IF(L$9="","",IF($E54=0,0,_xlfn.XLOOKUP($E54,'DN06'!$O$30:$O$51,'DN06'!$N$30:$N$51,0)+IF(LEFT(E54,7)="3013522",-2,0))) | M54: =IF(M$9="","",IF($E54=0,0,_xlfn.XLOOKUP($E54,'DN07'!$O$30:$O$49,'DN07'!$N$30:$N$49,0)+IF(LEFT(F54,7)="3013522",-2,0))) | N54: =IF(N$9="","",IF($E54=0,0,_xlfn.XLOOKUP($E54,'DN08'!$O$30:$O$49,'DN08'!$N$30:$N$49,0)+IF(LEFT(G54,7)="3013522",-2,0))) | O54: =IF(O$9="","",IF($E54=0,0,_xlfn.XLOOKUP($E54,'DN09'!$O$30:$O$51,'DN09'!$N$30:$N$51,0)+IF(LEFT(H54,7)="3013522",-2,0))) | P54: =IF(P$9="","",IF($E54=0,0,_xlfn.XLOOKUP($E54,'DN10'!$O$30:$O$49,'DN10'!$N$30:$N$49,0)+IF(LEFT(I54,7)="3013522",-2,0))) | Q54: =IF(F54="","",SUM(G54:P54)*F54) -> 0
A55: DRY | B55: ITEM | D55: =D54+1 -> 46 | F55: =IF(E55="","",VLOOKUP(E55,'DRY ITEM LIST'!B:F,5,0)) | G55: =IF(G$9="","",IF($E55=0,0,_xlfn.XLOOKUP($E55,'DN01'!$O$30:$O$49,'DN01'!$N$30:$N$49,0)+IF(LEFT(E55,7)="3013522",-2,0))) -> 0 | H55: =IF(H$9="","",IF($E55=0,0,_xlfn.XLOOKUP($E55,'DN02'!$O$30:$O$51,'DN02'!$N$30:$N$51,0)+IF(LEFT(E55,7)="3013522",-2,0))) -> 0 | I55: =IF(I$9="","",IF($E55=0,0,_xlfn.XLOOKUP($E55,'DN03'!$O$30:$O$50,'DN03'!$N$30:$N$50,0)+IF(LEFT(E55,7)="3013522",-2,0))) -> 0 | J55: =IF(J$9="","",IF($E55=0,0,_xlfn.XLOOKUP($E55,'DN04'!$O$30:$O$51,'DN04'!$N$30:$N$51,0)+IF(LEFT(E55,7)="3013522",-2,0))) -> 0 | K55: =IF(K$9="","",IF($E55=0,0,_xlfn.XLOOKUP($E55,'DN05'!$O$30:$O$51,'DN05'!$N$30:$N$51,0)+IF(LEFT(E55,7)="3013522",-2,0))) | L55: =IF(L$9="","",IF($E55=0,0,_xlfn.XLOOKUP($E55,'DN06'!$O$30:$O$51,'DN06'!$N$30:$N$51,0)+IF(LEFT(E55,7)="3013522",-2,0))) | M55: =IF(M$9="","",IF($E55=0,0,_xlfn.XLOOKUP($E55,'DN07'!$O$30:$O$49,'DN07'!$N$30:$N$49,0)+IF(LEFT(F55,7)="3013522",-2,0))) | N55: =IF(N$9="","",IF($E55=0,0,_xlfn.XLOOKUP($E55,'DN08'!$O$30:$O$49,'DN08'!$N$30:$N$49,0)+IF(LEFT(G55,7)="3013522",-2,0))) | O55: =IF(O$9="","",IF($E55=0,0,_xlfn.XLOOKUP($E55,'DN09'!$O$30:$O$51,'DN09'!$N$30:$N$51,0)+IF(LEFT(H55,7)="3013522",-2,0))) | P55: =IF(P$9="","",IF($E55=0,0,_xlfn.XLOOKUP($E55,'DN10'!$O$30:$O$49,'DN10'!$N$30:$N$49,0)+IF(LEFT(I55,7)="3013522",-2,0))) | Q55: =IF(F55="","",SUM(G55:P55)*F55)
A56: DRY | B56: ITEM | D56: =D55+1 -> 47 | F56: =IF(E56="","",VLOOKUP(E56,'DRY ITEM LIST'!B:F,5,0)) | G56: =IF(G$9="","",IF($E56=0,0,_xlfn.XLOOKUP($E56,'DN01'!$O$30:$O$49,'DN01'!$N$30:$N$49,0)+IF(LEFT(E56,7)="3013522",-2,0))) -> 0 | H56: =IF(H$9="","",IF($E56=0,0,_xlfn.XLOOKUP($E56,'DN02'!$O$30:$O$51,'DN02'!$N$30:$N$51,0)+IF(LEFT(E56,7)="3013522",-2,0))) -> 0 | I56: =IF(I$9="","",IF($E56=0,0,_xlfn.XLOOKUP($E56,'DN03'!$O$30:$O$49,'DN03'!$N$30:$N$49,0)+IF(LEFT(E56,7)="3013522",-2,0))) -> 0 | J56: =IF(J$9="","",IF($E56=0,0,_xlfn.XLOOKUP($E56,'DN04'!$O$30:$O$51,'DN04'!$N$30:$N$51,0)+IF(LEFT(E56,7)="3013522",-2,0))) -> 0 | K56: =IF(K$9="","",IF($E56=0,0,_xlfn.XLOOKUP($E56,'DN05'!$O$30:$O$51,'DN05'!$N$30:$N$51,0)+IF(LEFT(E56,7)="3013522",-2,0))) | L56: =IF(L$9="","",IF($E56=0,0,_xlfn.XLOOKUP($E56,'DN06'!$O$30:$O$51,'DN06'!$N$30:$N$51,0)+IF(LEFT(E56,7)="3013522",-2,0))) | M56: =IF(M$9="","",IF($E56=0,0,_xlfn.XLOOKUP($E56,'DN07'!$O$30:$O$49,'DN07'!$N$30:$N$49,0)+IF(LEFT(F56,7)="3013522",-2,0))) | N56: =IF(N$9="","",IF($E56=0,0,_xlfn.XLOOKUP($E56,'DN08'!$O$30:$O$49,'DN08'!$N$30:$N$49,0)+IF(LEFT(G56,7)="3013522",-2,0))) | O56: =IF(O$9="","",IF($E56=0,0,_xlfn.XLOOKUP($E56,'DN09'!$O$30:$O$49,'DN09'!$N$30:$N$49,0)+IF(LEFT(H56,7)="3013522",-2,0))) | P56: =IF(P$9="","",IF($E56=0,0,_xlfn.XLOOKUP($E56,'DN10'!$O$30:$O$49,'DN10'!$N$30:$N$49,0)+IF(LEFT(I56,7)="3013522",-2,0))) | Q56: =IF(F56="","",SUM(G56:P56)*F56)
A57: DRY | B57: ITEM | D57: =D56+1 -> 48 | F57: =IF(E57="","",VLOOKUP(E57,'DRY ITEM LIST'!B:F,5,0)) | G57: =IF(G$9="","",IF($E57=0,0,_xlfn.XLOOKUP($E57,'DN01'!$O$30:$O$49,'DN01'!$N$30:$N$49,0)+IF(LEFT(E57,7)="3013522",-2,0))) -> 0 | H57: =IF(H$9="","",IF($E57=0,0,_xlfn.XLOOKUP($E57,'DN02'!$O$30:$O$51,'DN02'!$N$30:$N$51,0)+IF(LEFT(E57,7)="3013522",-2,0))) -> 0 | I57: =IF(I$9="","",IF($E57=0,0,_xlfn.XLOOKUP($E57,'DN03'!$O$30:$O$49,'DN03'!$N$30:$N$49,0)+IF(LEFT(E57,7)="3013522",-2,0))) -> 0 | J57: =IF(J$9="","",IF($E57=0,0,_xlfn.XLOOKUP($E57,'DN04'!$O$30:$O$51,'DN04'!$N$30:$N$51,0)+IF(LEFT(E57,7)="3013522",-2,0))) -> 0 | K57: =IF(K$9="","",IF($E57=0,0,_xlfn.XLOOKUP($E57,'DN05'!$O$30:$O$51,'DN05'!$N$30:$N$51,0)+IF(LEFT(E57,7)="3013522",-2,0))) | L57: =IF(L$9="","",IF($E57=0,0,_xlfn.XLOOKUP($E57,'DN06'!$O$30:$O$51,'DN06'!$N$30:$N$51,0)+IF(LEFT(E57,7)="3013522",-2,0))) | M57: =IF(M$9="","",IF($E57=0,0,_xlfn.XLOOKUP($E57,'DN07'!$O$30:$O$49,'DN07'!$N$30:$N$49,0)+IF(LEFT(F57,7)="3013522",-2,0))) | N57: =IF(N$9="","",IF($E57=0,0,_xlfn.XLOOKUP($E57,'DN08'!$O$30:$O$49,'DN08'!$N$30:$N$49,0)+IF(LEFT(G57,7)="3013522",-2,0))) | O57: =IF(O$9="","",IF($E57=0,0,_xlfn.XLOOKUP($E57,'DN09'!$O$30:$O$49,'DN09'!$N$30:$N$49,0)+IF(LEFT(H57,7)="3013522",-2,0))) | Q57: =IF(F57="","",SUM(G57:P57)*F57)
B58: ITEM | D58: =D57+1 -> 49 | F58: =IF(E58="","",VLOOKUP(E58,'DRY ITEM LIST'!B:F,5,0)) | G58: =IF(G$9="","",IF($E58=0,0,_xlfn.XLOOKUP($E58,'DN01'!$O$30:$O$49,'DN01'!$N$30:$N$49,0)+IF(LEFT(E58,7)="3013522",-2,0))) -> 0 | H58: =IF(H$9="","",IF($E58=0,0,_xlfn.XLOOKUP($E58,'DN02'!$O$30:$O$49,'DN02'!$N$30:$N$49,0)+IF(LEFT(E58,7)="3013522",-2,0))) -> 0 | I58: =IF(I$9="","",IF($E58=0,0,_xlfn.XLOOKUP($E58,'DN03'!$O$30:$O$49,'DN03'!$N$30:$N$49,0)+IF(LEFT(E58,7)="3013522",-2,0))) -> 0 | J58: =IF(J$9="","",IF($E58=0,0,_xlfn.XLOOKUP($E58,'DN04'!$O$30:$O$51,'DN04'!$N$30:$N$51,0)+IF(LEFT(E58,7)="3013522",-2,0))) -> 0 | K58: =IF(K$9="","",IF($E58=0,0,_xlfn.XLOOKUP($E58,'DN05'!$O$30:$O$48,'DN05'!$N$30:$N$48,0)+IF(LEFT(E58,7)="3013522",-2,0))) | L58: =IF(L$9="","",IF($E58=0,0,_xlfn.XLOOKUP($E58,'DN06'!$O$30:$O$49,'DN06'!$N$30:$N$49,0)+IF(LEFT(E58,7)="3013522",-2,0))) | M58: =IF(M$9="","",IF($E58=0,0,_xlfn.XLOOKUP($E58,'DN07'!$O$30:$O$49,'DN07'!$N$30:$N$49,0)+IF(LEFT(F58,7)="3013522",-2,0))) | N58: =IF(N$9="","",IF($E58=0,0,_xlfn.XLOOKUP($E58,'DN08'!$O$30:$O$49,'DN08'!$N$30:$N$49,0)+IF(LEFT(G58,7)="3013522",-2,0))) | O58: =IF(O$9="","",IF($E58=0,0,_xlfn.XLOOKUP($E58,'DN09'!$O$30:$O$49,'DN09'!$N$30:$N$49,0)+IF(LEFT(H58,7)="3013522",-2,0))) | Q58: =IF(F58="","",SUM(G58:P58)*F58)
E59: SUB TOTAL | G59: =SUMPRODUCT($F$10:$F$58,G10:G58) -> 11408.19 | H59: =SUMPRODUCT($F$10:$F$58,H10:H58) -> 11143.144 | I59: =SUMPRODUCT($F$10:$F$58,I10:I58) -> 10774.107 | J59: =SUMPRODUCT($F$10:$F$58,J10:J58) -> 10494.537 | K59: =SUMPRODUCT($F$10:$F$58,K10:K58) -> 0 | L59: =SUMPRODUCT($F$10:$F$58,L10:L58) -> 0 | M59: =SUMPRODUCT($F$10:$F$58,M10:M58) -> 0 | N59: =SUMPRODUCT($F$10:$F$58,N10:N58) -> 0 | O59: =SUMPRODUCT($F$10:$F$58,O10:O58) -> 0 | P59: =SUMPRODUCT($F$10:$F$57,P10:P57) -> 0 | Q59: =SUM(Q10:Q58) -> 43819.977
D61: All denominations reflected in US Dollars

Sheet DN01
A1: A/C TYPE | C1: STATION NAME | E1: DELIVERY NOTE | M1: DATE : | N1: 46164
E2: FLIGHT NO | G2: DEPARTURE TIME | I2: FROM | K2: TO | M2: SALES #
A3: B787-900 | C3: ATL | E3: ET519 | G3: 0.45138889 | I3: ATL | K3: ADD | M3: ="ET"&TEXT(N1,"YYYYMMDD") -> ET20260522
D5: Reg Meal | E5: Special Meal
A6: Meal count | B6: Business class: | D6: 20 | E6: 02 GFML
A7: Email | B7: Economy class: | D7: 231 | E7: 03 SPML, 01 LCML, 03 AVML, 01 FPML, 03 MOML, 01 DBML, 01 AVML BBML, 01 MOML BBML
I9: LCH/DNR | L9: HCP /SWH | N9: HBF
A10: SERVICE | F10: FINAL ORDER | I10: 1st SVC/leg | L10: 2nd SVC/ leg | N10: 3rd SVC/leg
B11: PRELIMINARY ORDER | I11: SPML | J11: BC | K11: EY | L11: BC | M11: EY | N11: BC | O11: EY
B12: BC | C12: EY | D12: CR | E12: CP | F12: BC | G12: EY | I12: {=_xlfn.LET(_xlpm.vBC,_xlfn.TEXTSPLIT(E6," ",", "),_xlpm.vEY,_xlfn.TEXTSPLIT(E7," ",", "),_xlpm.vML,_xlfn.UNIQUE(_xlfn.VSTACK(INDEX(_xlpm.vBC,,2),INDEX(_xlpm.vEY,,2))), CHOOSE({1,2,3},_xlpm.vML,VALUE(_xlfn.XLOOKUP(_xlpm.vML,INDEX(_xlpm.vBC,,2),INDEX(_xlpm.vBC,,1),0)),VALUE(_xlfn.XLOOKUP(_xlpm.vML,INDEX(_xlpm.vEY,,2),INDEX(_xlpm.vEY,,1),0))))} -> GFML | J12: 2 | K12: 0 | L12: =J12 -> 2 | M12: =K12 -> 0 | N12: =J12 -> 2 | O12: =K12 -> 0
A13: HBF | B13: =$D$6 -> 20 | C13: =$D$7 -> 231 | D13: 11 | E13: 3 | F13: =SUM(B13,D13:E13) -> 34 | G13: =C13 -> 231 | I13: SPML | J13: 0 | K13: 3 | L13: =J13 -> 0 | M13: =K13 -> 3 | N13: =J13 -> 0 | O13: =K13 -> 3
A14: LCH/DNR | B14: =$D$6 -> 20 | C14: =$D$7 -> 231 | D14: 11 | E14: 3 | F14: =SUM(B14,D14:E14) -> 34 | G14: =C14 -> 231 | I14: LCML | J14: 0 | K14: 1 | L14: =J14 -> 0 | M14: =K14 -> 1 | N14: =J14 -> 0 | O14: =K14 -> 1
A15: HLM | B15: 0 | C15: 0 | F15: 0 | G15: 0 | I15: AVML | J15: 0 | K15: 3 | L15: =J15 -> 0 | M15: =K15 -> 3 | N15: =J15 -> 0 | O15: =K15 -> 3
A16: HCP | B16: =$D$6 -> 20 | C16: 0 | D16: 11 | E16: 3 | F16: =SUM(B16,D16:E16) -> 34 | G16: 0 | I16: FPML | J16: 0 | K16: 1 | L16: =J16 -> 0 | M16: =K16 -> 1 | N16: =J16 -> 0 | O16: =K16 -> 1
A17: SWH | B17: 0 | C17: =$D$7 -> 231 | F17: 0 | G17: =C17 -> 231 | I17: MOML | J17: 0 | K17: 3 | L17: =J17 -> 0 | M17: =K17 -> 3 | N17: =J17 -> 0 | O17: =K17 -> 3
A18: CCP | B18: 0 | C18: 0 | I18: DBML | J18: 0 | K18: 1 | L18: =J18 -> 0 | M18: =K18 -> 1 | N18: =J18 -> 0 | O18: =K18 -> 1
A19: Eye opener | C19: 0 | I19: AVML BBML | J19: 0 | K19: 1 | L19: =J19 -> 0 | M19: =K19 -> 1 | N19: =J19 -> 0 | O19: =K19 -> 1
A20: Fasting Meals | I20: MOML BBML | J20: 0 | K20: 1 | L20: =J20 -> 0 | M20: =K20 -> 1 | N20: =J20 -> 0 | O20: =K20 -> 1
L21: =J21 -> 0 | M21: =K21 -> 0 | N21: =J21 -> 0 | O21: =K21 -> 0
L22: =J22 -> 0 | M22: =K22 -> 0 | N22: =J22 -> 0 | O22: =K22 -> 0
L23: =J23 -> 0 | M23: =K23 -> 0 | N23: =J23 -> 0 | O23: =K23 -> 0
L24: =J24 -> 0 | M24: =K24 -> 0 | N24: =J24 -> 0 | O24: =K24 -> 0
J25: =SUM(J12:J24) -> 2 | K25: =SUM(K12:K24) -> 14 | L25: =SUM(L12:L24) -> 2 | M25: =SUM(M12:M24) -> 14 | N25: =SUM(N12:N24) -> 2 | O25: =SUM(O12:O24) -> 14
A28: NO. | B28: DESCRIPTION | E28: PLAN | F28: AMOUNT | I28: DRY ITEM LIST
A29: 1 | B29: FRUIT BASKET | E29: 1 | F29: 0 | I29: NO. | J29: DESCRIPTION | M29: AMOUNT | N29: AMOUNT
A30: 2 | B30: CHEESE AND CRACKER | E30: 1 | F30: 1 | I30: 1 | J30: ORANGE JUICE | O30: 3013505 - Juice Orange 1L
A31: 3 | B31: FRESH ORANGE JUICE | E31: 1 | F31: 1 | I31: 2 | J31: APPLE JUICE | O31: 3013506 - Juice Apple 1L
A32: 4 | B32: BREAD BASKET | E32: 1 | F32: 1 | I32: 3 | J32: PINEAPLE JUICE | O32: 3013504 - Juice Pineapple 1L
A33: 5 | B33: Standard Uplift | E33: 1 | F33: 1 | I33: 4 | J33: TOMATO JUICE | O33: 3013507 - Juice Tomato 1L
A34: 6 | B34: LAUNDRY SERVICE | E34: 0.5 | F34: 0.5 | I34: 5 | J34: MINERAL WATER 1. L | N34: 100 | O34: 3013499 - Mineral Water 1.5L
A35: 7 | B35: HANDLING CHARGES | E35: 1 | F35: 1 | I35: 6 | J35: MINERAL WATER 0.5 L | N35: 72 | O35: 3013498 - Mineral Water 330mL
A36: 8 | B36: EXTRA VAN CHARGE | E36: 1 | F36: 1 | I36: 7 | J36: COCA COLA BOTTLE 1.5 L
A37: 9 | B37: INTERNATIONAL TRASH REMOVAL | E37: 1 | F37: 1 | I37: 8 | J37: COCA COLA CAN | N37: 48 | O37: 3013495 - Coke 355mL
A38: 10 | B38: Custom Clearance Charge | E38: 1 | F38: 1 | I38: 9 | J38: Sugar Sachet White | O38: =IF(J38="","",_xlfn.XLOOKUP(J38,'DRY ITEM LIST'!D:D,'DRY ITEM LIST'!B:B,"")) -> 3013509 - Sugar Sachet White
A39: 11 | I39: 10 | J39: SPRIT CAN | N39: 48 | O39: 3013497 - Sprite 355mL
A40: 12 | I40: 11 | J40: Wet Ice 5kg Bag | N40: 10 | O40: 3013522 - Wet Ice 5kg Bag
A41: 13 | I41: 12 | J41: Water 1.5 L
A42: 14 | I42: 13 | J42: Water 0.5 L
A43: 15 | I43: 14 | J43: Coke Light 355mL | N43: 24 | O43: =IF(J43="","",_xlfn.XLOOKUP(J43,'DRY ITEM LIST'!D:D,'DRY ITEM LIST'!B:B,"")) -> 3013496 - Coke Light 355mL
I44: 15 | J44: Creamer | O44: =IF(J44="","",_xlfn.XLOOKUP(J44,'DRY ITEM LIST'!D:D,'DRY ITEM LIST'!B:B,"")) -> 3013542 - Creamer
I45: 16 | J45: Soda Water 355L | N45: 12 | O45: =IF(J45="","",_xlfn.XLOOKUP(J45,'DRY ITEM LIST'!D:D,'DRY ITEM LIST'!B:B,"")) -> 3013502 - Soda Water 355L
I46: 17 | J46: Fruit Platters | N46: =35/3 -> 11.666667 | O46: =IF(J46="","",_xlfn.XLOOKUP(J46,'DRY ITEM LIST'!D:D,'DRY ITEM LIST'!B:B,"")) -> 3013538 - Fruit Platters
I47: 18 | J47: Ginger Ale 355mL | N47: 24 | O47: =IF(J47="","",_xlfn.XLOOKUP(J47,'DRY ITEM LIST'!D:D,'DRY ITEM LIST'!B:B,"")) -> 3013540 - Ginger Ale 355mL
I48: 19 | J48: Sparkling Water | N48: 8 | O48: =IF(J48="","",_xlfn.XLOOKUP(J48,'DRY ITEM LIST'!D:D,'DRY ITEM LIST'!B:B,"")) -> 3013541 - Sparkling Water
I49: 20 | J49: Bulk Tray - Vegetarian (Fasting) | O49: =IF(J49="","",_xlfn.XLOOKUP(J49,'DRY ITEM LIST'!D:D,'DRY ITEM LIST'!B:B,"")) -> Xtra - Bulk Tray - Vegetarian (Fasting)
I50: 21 | J50: Bulk Tray - Pasta (Fasting) | O50: =IF(J50="","",_xlfn.XLOOKUP(J50,'DRY ITEM LIST'!D:D,'DRY ITEM LIST'!B:B,"")) -> Xtra - Bulk Tray - Pasta (Fasting)

Sheet DN02
A1: A/C TYPE | C1: STATION NAME | E1: DELIVERY NOTE | M1: DATE : | N1: 46167
E2: FLIGHT NO | G2: DEPARTURE TIME | I2: FROM | K2: TO | M2: SALES #
A3: B787-900 | C3: ATL | E3: ET519 | G3: 0.45138889 | I3: ATL | K3: ADD | M3: ="ET"&TEXT(N1,"YYYYMMDD") -> ET20260525
D5: Reg Meal | E5: Special Meal
A6: Meal count | B6: Business class: | D6: 22 | E6: 01 CHML, 01 VGML, 01 KIDS
A7: Email | B7: Economy class: | D7: 239 | E7: 01 BBML, 07 MOML, 02 CHML, 01 SFML
I9: LCH/DNR | L9: HCP /SWH | N9: HBF
A10: SERVICE | F10: FINAL ORDER | I10: 1st SVC/leg | L10: 2nd SVC/ leg | N10: 3rd SVC/leg
B11: PRELIMINARY ORDER | I11: SPML | J11: BC | K11: EY | L11: BC | M11: EY | N11: BC | O11: EY
B12: BC | C12: EY | D12: CR | E12: CP | F12: BC | G12: EY | I12: {=_xlfn.LET(_xlpm.vBC,_xlfn.TEXTSPLIT(E6," ",", "),_xlpm.vEY,_xlfn.TEXTSPLIT(E7," ",", "),_xlpm.vML,_xlfn.UNIQUE(_xlfn.VSTACK(INDEX(_xlpm.vBC,,2),INDEX(_xlpm.vEY,,2))), CHOOSE({1,2,3},_xlpm.vML,VALUE(_xlfn.XLOOKUP(_xlpm.vML,INDEX(_xlpm.vBC,,2),INDEX(_xlpm.vBC,,1),0)),VALUE(_xlfn.XLOOKUP(_xlpm.vML,INDEX(_xlpm.vEY,,2),INDEX(_xlpm.vEY,,1),0))))} -> CHML | J12: 1 | K12: 2 | L12: =J12 -> 1 | M12: =K12 -> 2 | N12: =J12 -> 1 | O12: =K12 -> 2
A13: HBF | B13: =$D$6 -> 22 | C13: =$D$7 -> 239 | D13: 11 | E13: 3 | F13: =SUM(B13,D13:E13) -> 36 | G13: =C13 -> 239 | I13: VGML | J13: 1 | K13: 0 | L13: =J13 -> 1 | M13: =K13 -> 0 | N13: =J13 -> 1 | O13: =K13 -> 0
A14: LCH/DNR | B14: =$D$6 -> 22 | C14: =$D$7 -> 239 | D14: 11 | E14: 3 | F14: =SUM(B14,D14:E14) -> 36 | G14: =C14 -> 239 | I14: KIDS | J14: 1 | K14: 0 | L14: =J14 -> 1 | M14: =K14 -> 0 | N14: =J14 -> 1 | O14: =K14 -> 0
A15: HLM | B15: 0 | C15: 0 | F15: 0 | G15: 0 | I15: BBML | J15: 0 | K15: 1 | L15: =J15 -> 0 | M15: =K15 -> 1 | N15: =J15 -> 0 | O15: =K15 -> 1
A16: HCP | B16: =$D$6 -> 22 | C16: 0 | D16: 11 | E16: 3 | F16: =SUM(B16,D16:E16) -> 36 | G16: 0 | I16: MOML | J16: 0 | K16: 7 | L16: =J16 -> 0 | M16: =K16 -> 7 | N16: =J16 -> 0 | O16: =K16 -> 7
A17: SWH | B17: 0 | C17: =$D$7 -> 239 | F17: 0 | G17: =C17 -> 239 | I17: SFML | J17: 0 | K17: 1 | L17: =J17 -> 0 | M17: =K17 -> 1 | N17: =J17 -> 0 | O17: =K17 -> 1
A18: CCP | B18: 0 | C18: 0 | L18: =J18 -> 0 | M18: =K18 -> 0 | N18: =J18 -> 0 | O18: =K18 -> 0
A19: Eye opener | C19: 0 | L19: =J19 -> 0 | M19: =K19 -> 0 | N19: =J19 -> 0 | O19: =K19 -> 0
A20: Fasting Meals | L20: =J20 -> 0 | M20: =K20 -> 0 | N20: =J20 -> 0 | O20: =K20 -> 0
L21: =J21 -> 0 | M21: =K21 -> 0 | N21: =J21 -> 0 | O21: =K21 -> 0
L22: =J22 -> 0 | M22: =K22 -> 0 | N22: =J22 -> 0 | O22: =K22 -> 0
L23: =J23 -> 0 | M23: =K23 -> 0 | N23: =J23 -> 0 | O23: =K23 -> 0
L24: =J24 -> 0 | M24: =K24 -> 0 | N24: =J24 -> 0 | O24: =K24 -> 0
J25: =SUM(J12:J24) -> 3 | K25: =SUM(K12:K24) -> 11 | L25: =SUM(L12:L24) -> 3 | M25: =SUM(M12:M24) -> 11 | N25: =SUM(N12:N24) -> 3 | O25: =SUM(O12:O24) -> 11
A28: NO. | B28: DESCRIPTION | E28: PLAN | F28: AMOUNT | I28: DRY ITEM LIST
A29: 1 | B29: FRUIT BASKET | E29: 1 | F29: 0 | I29: NO. | J29: DESCRIPTION | M29: AMOUNT | N29: AMOUNT
A30: 2 | B30: CHEESE AND CRACKER | E30: 1 | F30: 2 | I30: 1 | J30: ORANGE JUICE | N30: 2 | O30: 3013505 - Juice Orange 1L
A31: 3 | B31: FRESH ORANGE JUICE | E31: 1 | F31: 1 | I31: 2 | J31: APPLE JUICE | N31: 16 | O31: 3013506 - Juice Apple 1L
A32: 4 | B32: BREAD BASKET | E32: 1 | F32: 2 | I32: 3 | J32: PINEAPLE JUICE | O32: 3013504 - Juice Pineapple 1L
A33: 5 | B33: Standard Uplift | E33: 1 | F33: 1 | I33: 4 | J33: TOMATO JUICE | O33: 3013507 - Juice Tomato 1L
A34: 6 | B34: LAUNDRY SERVICE | E34: 0.5 | F34: 0.5 | I34: 5 | J34: MINERAL WATER 1. L | N34: 36 | O34: 3013499 - Mineral Water 1.5L
A35: 7 | B35: HANDLING CHARGES | E35: 1 | F35: 1 | I35: 6 | J35: MINERAL WATER 0.5 L | N35: 48 | O35: 3013498 - Mineral Water 330mL
A36: 8 | B36: EXTRA VAN CHARGE | E36: 1 | F36: 1 | I36: 7 | J36: COCA COLA BOTTLE 1.5 L
A37: 9 | B37: INTERNATIONAL TRASH REMOVAL | E37: 1 | F37: 1 | I37: 8 | J37: COCA COLA CAN | O37: 3013495 - Coke 355mL
A38: 10 | B38: Custom Clearance Charge | E38: 1 | F38: 1 | I38: 9 | J38: Coke Light 355mL | O38: =IF(J38="","",_xlfn.XLOOKUP(J38,'DRY ITEM LIST'!D:D,'DRY ITEM LIST'!B:B,"")) -> 3013496 - Coke Light 355mL
A39: 11 | I39: 10 | J39: SPRIT CAN | N39: 36 | O39: 3013497 - Sprite 355mL
A40: 12 | I40: 11 | J40: Wet Ice 5kg Bag | N40: 10 | O40: 3013522 - Wet Ice 5kg Bag
A41: 13 | I41: 12 | J41: Water 1.5 L
A42: 14 | I42: 13 | J42: Water 0.5 L
A43: 15 | I43: 14 | J43: Fruit Platters | N43: =42/3 -> 14 | O43: =IF(J43="","",_xlfn.XLOOKUP(J43,'DRY ITEM LIST'!D:D,'DRY ITEM LIST'!B:B,"")) -> 3013538 - Fruit Platters
I44: 15 | J44: Ginger Ale 355mL | O44: =IF(J44="","",_xlfn.XLOOKUP(J44,'DRY ITEM LIST'!D:D,'DRY ITEM LIST'!B:B,"")) -> 3013540 - Ginger Ale 355mL
I45: 16 | J45: Tonic Water 355mL | O45: =IF(J45="","",_xlfn.XLOOKUP(J45,'DRY ITEM LIST'!D:D,'DRY ITEM LIST'!B:B,"")) -> 3013503 - Tonic Water 355mL
I46: 17 | J46: Soda Water 355L | O46: =IF(J46="","",_xlfn.XLOOKUP(J46,'DRY ITEM LIST'!D:D,'DRY ITEM LIST'!B:B,"")) -> 3013502 - Soda Water 355L
I47: 18 | J47: Sparkling Water | O47: =IF(J47="","",_xlfn.XLOOKUP(J47,'DRY ITEM LIST'!D:D,'DRY ITEM LIST'!B:B,"")) -> 3013541 - Sparkling Water
I48: 19 | J48: Bulk Tray - Vegetarian (Fasting) | O48: =IF(J48="","",_xlfn.XLOOKUP(J48,'DRY ITEM LIST'!D:D,'DRY ITEM LIST'!B:B,"")) -> Xtra - Bulk Tray - Vegetarian (Fasting)
I49: 20 | J49: Bulk Tray - Pasta (Fasting) | O49: =IF(J49="","",_xlfn.XLOOKUP(J49,'DRY ITEM LIST'!D:D,'DRY ITEM LIST'!B:B,"")) -> Xtra - Bulk Tray - Pasta (Fasting)

Sheet DN03
A1: A/C TYPE | C1: STATION NAME | E1: DELIVERY NOTE | M1: DATE : | N1: 46169
E2: FLIGHT NO | G2: DEPARTURE TIME | I2: FROM | K2: TO | M2: SALES #
A3: B787-900 | C3: ATL | E3: ET519 | G3: 0.45138889 | I3: ATL | K3: ADD | M3: ="ET"&TEXT(N1,"YYYYMMDD") -> ET20260527
D5: Reg Meal | E5: Special Meal
A6: Meal count | B6: Business class: | D6: 20 | E6: 00 SFML
A7: Email | B7: Economy class: | D7: 225 | E7: 01 LFML 02 VLML, 01 SFML, 01 VGML, 03 AVML, 03 FPML, 01 KSML, 01 HNML, 01 CHML, 01 GFML
I9: LCH/DNR | L9: HCP /SWH | N9: HBF
A10: SERVICE | F10: FINAL ORDER | I10: 1st SVC/leg | L10: 2nd SVC/ leg | N10: 3rd SVC/leg
B11: PRELIMINARY ORDER | I11: SPML | J11: BC | K11: EY | L11: BC | M11: EY | N11: BC | O11: EY
B12: BC | C12: EY | D12: CR | E12: CP | F12: BC | G12: EY | I12: {=_xlfn.LET(_xlpm.vBC,_xlfn.TEXTSPLIT(E6," ",", "),_xlpm.vEY,_xlfn.TEXTSPLIT(E7," ",", "),_xlpm.vML,_xlfn.UNIQUE(_xlfn.VSTACK(INDEX(_xlpm.vBC,,2),INDEX(_xlpm.vEY,,2))), CHOOSE({1,2,3},_xlpm.vML,VALUE(_xlfn.XLOOKUP(_xlpm.vML,INDEX(_xlpm.vBC,,2),INDEX(_xlpm.vBC,,1),0)),VALUE(_xlfn.XLOOKUP(_xlpm.vML,INDEX(_xlpm.vEY,,2),INDEX(_xlpm.vEY,,1),0))))} -> SFML | J12: 0 | K12: 1 | L12: =J12 -> 0 | M12: =K12 -> 1 | N12: =J12 -> 0 | O12: =K12 -> 1
A13: HBF | B13: =D6 -> 20 | C13: =$D$7 -> 225 | D13: 11 | E13: 5 | F13: =SUM(B13,D13:E13) -> 36 | G13: =C13 -> 225 | I13: LFML | J13: 0 | K13: 1 | L13: =J13 -> 0 | M13: =K13 -> 1 | N13: =J13 -> 0 | O13: =K13 -> 1
A14: LCH/DNR | B14: =D6 -> 20 | C14: =$D$7 -> 225 | D14: 11 | E14: 5 | F14: =SUM(B14,D14:E14) -> 36 | G14: =C14 -> 225 | I14: VGML | J14: 0 | K14: 1 | L14: =J14 -> 0 | M14: =K14 -> 1 | N14: =J14 -> 0 | O14: =K14 -> 1
A15: HLM | B15: 0 | C15: 0 | F15: 0 | G15: 0 | I15: AVML | J15: 0 | K15: 3 | L15: =J15 -> 0 | M15: =K15 -> 3 | N15: =J15 -> 0 | O15: =K15 -> 3
A16: HCP | B16: =D6 -> 20 | C16: 0 | D16: 11 | E16: 5 | F16: =SUM(B16,D16:E16) -> 36 | G16: 0 | I16: FPML | J16: 0 | K16: 3 | L16: =J16 -> 0 | M16: =K16 -> 3 | N16: =J16 -> 0 | O16: =K16 -> 3
A17: SWH | B17: 0 | C17: =$D$7 -> 225 | F17: 0 | G17: =C17 -> 225 | I17: KSML | J17: 0 | K17: 1 | L17: =J17 -> 0 | M17: =K17 -> 1 | N17: =J17 -> 0 | O17: =K17 -> 1
A18: CCP | B18: 0 | C18: 0 | I18: HNML | J18: 0 | K18: 1 | L18: =J18 -> 0 | M18: =K18 -> 1 | N18: =J18 -> 0 | O18: =K18 -> 1
A19: Eye opener | C19: 0 | I19: CHML | J19: 0 | K19: 1 | L19: =J19 -> 0 | M19: =K19 -> 1 | N19: =J19 -> 0 | O19: =K19 -> 1
A20: Fasting Meals | I20: GFML | J20: 0 | K20: 1 | L20: =J20 -> 0 | M20: =K20 -> 1 | N20: =J20 -> 0 | O20: =K20 -> 1
I21: VLML | J21: 0 | K21: 2 | L21: =J21 -> 0 | M21: =K21 -> 2 | N21: =J21 -> 0 | O21: =K21 -> 2
L22: =J22 -> 0 | M22: =K22 -> 0 | N22: =J22 -> 0 | O22: =K22 -> 0
L23: =J23 -> 0 | M23: =K23 -> 0 | N23: =J23 -> 0 | O23: =K23 -> 0
L24: =J24 -> 0 | M24: =K24 -> 0 | N24: =J24 -> 0 | O24: =K24 -> 0
J25: =SUM(J12:J24) -> 0 | K25: =SUM(K12:K24) -> 15 | L25: =SUM(L12:L24) -> 0 | M25: =SUM(M12:M24) -> 15 | N25: =SUM(N12:N24) -> 0 | O25: =SUM(O12:O24) -> 15
A28: NO. | B28: DESCRIPTION | E28: PLAN | F28: AMOUNT | I28: DRY ITEM LIST
A29: 1 | B29: FRUIT BASKET | E29: 1 | F29: 0 | I29: NO. | J29: DESCRIPTION | M29: AMOUNT | N29: AMOUNT
A30: 2 | B30: CHEESE AND CRACKER | E30: 1 | F30: 2 | I30: 1 | J30: ORANGE JUICE | N30: 6 | O30: 3013505 - Juice Orange 1L
A31: 3 | B31: FRESH ORANGE JUICE | E31: 1 | F31: 3 | I31: 2 | J31: APPLE JUICE | N31: 0 | O31: 3013506 - Juice Apple 1L
A32: 4 | B32: BREAD BASKET | E32: 1 | F32: 2 | I32: 3 | J32: PINEAPLE JUICE | O32: 3013504 - Juice Pineapple 1L
A33: 5 | B33: Standard Uplift | E33: 1 | F33: 1 | I33: 4 | J33: TOMATO JUICE | O33: 3013507 - Juice Tomato 1L
A34: 6 | B34: LAUNDRY SERVICE | E34: 0.5 | F34: 0.5 | I34: 5 | J34: MINERAL WATER 1.5 L | N34: 48 | O34: 3013499 - Mineral Water 1.5L
A35: 7 | B35: HANDLING CHARGES | E35: 1 | F35: 1 | I35: 6 | J35: MINERAL WATER 0.5 L | N35: 24 | O35: 3013498 - Mineral Water 330mL
A36: 8 | B36: EXTRA VAN CHARGE | E36: 1 | F36: 1 | I36: 7 | J36: COCA COLA BOTTLE 1.5 L
A37: 9 | B37: INTERNATIONAL TRASH REMOVAL | E37: 1 | F37: 1 | I37: 8 | J37: COCA COLA CAN | N37: 24 | O37: 3013495 - Coke 355mL
A38: 10 | B38: Custom Clearance Charge | E38: 1 | F38: 1 | I38: 9 | J38: SPRIT BOTTLE 1.5 L | O38: =IF(J38="","",_xlfn.XLOOKUP(J38,'DRY ITEM LIST'!D:D,'DRY ITEM LIST'!B:B,""))
A39: 11 | I39: 10 | J39: SPRIT CAN | O39: 3013497 - Sprite 355mL
A40: 12 | I40: 11 | J40: Wet Ice 5kg Bag | N40: 10 | O40: 3013522 - Wet Ice 5kg Bag
A41: 13 | I41: 12 | J41: Tonic Water 355mL | N41: 12 | O41: =IF(J41="","",_xlfn.XLOOKUP(J41,'DRY ITEM LIST'!D:D,'DRY ITEM LIST'!B:B,"")) -> 3013503 - Tonic Water 355mL
A42: 14 | I42: 13 | J42: Toilet Paper | O42: =IF(J42="","",_xlfn.XLOOKUP(J42,'DRY ITEM LIST'!D:D,'DRY ITEM LIST'!B:B,""))
A43: 15 | I43: 14 | J43: Sparkling Water | N43: 12 | O43: =IF(J43="","",_xlfn.XLOOKUP(J43,'DRY ITEM LIST'!D:D,'DRY ITEM LIST'!B:B,"")) -> 3013541 - Sparkling Water
I44: 15 | J44: Fruit Platters | N44: =40/3 -> 13.333333 | O44: =IF(J44="","",_xlfn.XLOOKUP(J44,'DRY ITEM LIST'!D:D,'DRY ITEM LIST'!B:B,"")) -> 3013538 - Fruit Platters
I45: 16 | J45: Ginger Ale 355mL | N45: 12 | O45: =IF(J45="","",_xlfn.XLOOKUP(J45,'DRY ITEM LIST'!D:D,'DRY ITEM LIST'!B:B,"")) -> 3013540 - Ginger Ale 355mL
I46: 17 | J46: Creamer | N46: 0 | O46: =IF(J46="","",_xlfn.XLOOKUP(J46,'DRY ITEM LIST'!D:D,'DRY ITEM LIST'!B:B,"")) -> 3013542 - Creamer
I47: 18 | J47: Hand Towel Roll | N47: 0 | O47: =IF(J47="","",_xlfn.XLOOKUP(J47,'DRY ITEM LIST'!D:D,'DRY ITEM LIST'!B:B,"")) -> 3013534 - Hand Towel Roll
I48: 19 | J48: Coke Light 355mL | N48: 12 | O48: =IF(J48="","",_xlfn.XLOOKUP(J48,'DRY ITEM LIST'!D:D,'DRY ITEM LIST'!B:B,"")) -> 3013496 - Coke Light 355mL
I49: 20 | J49: Bulk Tray - Vegetarian (Fasting) | N49: 0 | O49: =IF(J49="","",_xlfn.XLOOKUP(J49,'DRY ITEM LIST'!D:D,'DRY ITEM LIST'!B:B,"")) -> Xtra - Bulk Tray - Vegetarian (Fasting)
I50: 21 | J50: Bulk Tray - Pasta (Fasting) | N50: 0 | O50: =IF(J50="","",_xlfn.XLOOKUP(J50,'DRY ITEM LIST'!D:D,'DRY ITEM LIST'!B:B,"")) -> Xtra - Bulk Tray - Pasta (Fasting)

Sheet DN04
A1: A/C TYPE | C1: STATION NAME | E1: DELIVERY NOTE | M1: DATE : | N1: 46171
E2: FLIGHT NO | G2: DEPARTURE TIME | I2: FROM | K2: TO | M2: SALES #
A3: B787-900 | C3: ATL | E3: ET519 | G3: 0.45138889 | I3: ATL | K3: ADD | M3: ="ET"&TEXT(N1,"YYYYMMDD") -> ET20260529
D5: Reg Meal | E5: Special Meal
A6: Meal count | B6: Business class: | D6: 22 | E6: 01 AVML
A7: Email | B7: Economy class: | D7: 222 | E7: 01 MOML , 02 CHML
I9: LCH/DNR | L9: HCP /SWH | N9: HBF
A10: SERVICE | F10: FINAL ORDER | I10: 1st SVC/leg | L10: 2nd SVC/ leg | N10: 3rd SVC/leg
B11: PRELIMINARY ORDER | I11: SPML | J11: BC | K11: EY | L11: BC | M11: EY | N11: BC | O11: EY
B12: BC | C12: EY | D12: CR | E12: CP | F12: BC | G12: EY | I12: {=_xlfn.LET(_xlpm.vBC,_xlfn.TEXTSPLIT(E6," ",", "),_xlpm.vEY,_xlfn.TEXTSPLIT(E7," ",", "),_xlpm.vML,_xlfn.UNIQUE(_xlfn.VSTACK(INDEX(_xlpm.vBC,,2),INDEX(_xlpm.vEY,,2))), CHOOSE({1,2,3},_xlpm.vML,VALUE(_xlfn.XLOOKUP(_xlpm.vML,INDEX(_xlpm.vBC,,2),INDEX(_xlpm.vBC,,1),0)),VALUE(_xlfn.XLOOKUP(_xlpm.vML,INDEX(_xlpm.vEY,,2),INDEX(_xlpm.vEY,,1),0))))} -> AVML | J12: 1 | K12: 0 | L12: =J12 -> 1 | M12: =K12 -> 0 | N12: =J12 -> 1 | O12: =K12 -> 0
A13: HBF | B13: =$D$6 -> 22 | C13: =$D$7 -> 222 | D13: 11 | E13: 5 | F13: =SUM(B13,D13:E13) -> 38 | G13: =C13 -> 222 | I13: MOML | J13: 0 | K13: 1 | L13: =J13 -> 0 | M13: =K13 -> 1 | N13: =J13 -> 0 | O13: =K13 -> 1
A14: LCH/DNR | B14: =$D$6 -> 22 | C14: =$D$7 -> 222 | D14: 11 | E14: 5 | F14: =SUM(B14,D14:E14) -> 38 | G14: =C14 -> 222 | I14: CHML | J14: 0 | K14: 2 | L14: =J14 -> 0 | M14: =K14 -> 2 | N14: =J14 -> 0 | O14: =K14 -> 2
A15: HLM | B15: 0 | C15: 0 | F15: 0 | G15: 0 | L15: =J15 -> 0 | M15: =K15 -> 0 | N15: =J15 -> 0 | O15: =K15 -> 0
A16: HCP | B16: =$D$6 -> 22 | C16: 0 | D16: 11 | E16: 5 | F16: =SUM(B16,D16:E16) -> 38 | G16: 0 | L16: =J16 -> 0 | M16: =K16 -> 0 | N16: =J16 -> 0 | O16: =K16 -> 0
A17: SWH | B17: 0 | C17: =$D$7 -> 222 | F17: 0 | G17: =C17 -> 222 | L17: =J17 -> 0 | M17: =K17 -> 0 | N17: =J17 -> 0 | O17: =K17 -> 0
A18: CCP | B18: 0 | C18: 0 | L18: =J18 -> 0 | M18: =K18 -> 0 | N18: =J18 -> 0 | O18: =K18 -> 0
A19: Eye opener | C19: 0 | L19: =J19 -> 0 | M19: =K19 -> 0 | N19: =J19 -> 0 | O19: =K19 -> 0
A20: Fasting | L20: =J20 -> 0 | M20: =K20 -> 0 | N20: =J20 -> 0 | O20: =K20 -> 0
L21: =J21 -> 0 | M21: =K21 -> 0 | N21: =J21 -> 0 | O21: =K21 -> 0
L22: =J22 -> 0 | M22: =K22 -> 0 | N22: =J22 -> 0 | O22: =K22 -> 0
L23: =J23 -> 0 | M23: =K23 -> 0 | N23: =J23 -> 0 | O23: =K23 -> 0
L24: =J24 -> 0 | M24: =K24 -> 0 | N24: =J24 -> 0 | O24: =K24 -> 0
J25: =SUM(J12:J24) -> 1 | K25: =SUM(K12:K24) -> 3 | L25: =SUM(L12:L24) -> 1 | M25: =SUM(M12:M24) -> 3 | N25: =SUM(N12:N24) -> 1 | O25: =SUM(O12:O24) -> 3
A28: NO. | B28: DESCRIPTION | E28: PLAN | F28: AMOUNT | I28: DRY ITEM LIST
A29: 1 | B29: FRUIT BASKET | E29: 1 | F29: 0 | I29: NO. | J29: DESCRIPTION | M29: AMOUNT | N29: AMOUNT
A30: 2 | B30: CHEESE AND CRACKER | E30: 1 | F30: 2 | I30: 1 | J30: ORANGE JUICE | N30: 2 | O30: 3013505 - Juice Orange 1L
A31: 3 | B31: FRESH ORANGE JUICE | E31: 1 | F31: 1 | I31: 2 | J31: APPLE JUICE | N31: 12 | O31: 3013506 - Juice Apple 1L
A32: 4 | B32: BREAD BASKET | E32: 1 | F32: 1 | I32: 3 | J32: PINEAPLE JUICE | O32: 3013504 - Juice Pineapple 1L
A33: 5 | B33: Standard Uplift | E33: 1 | F33: 1 | I33: 4 | J33: TOMATO JUICE | O33: 3013507 - Juice Tomato 1L
A34: 6 | B34: LAUNDRY SERVICE | E34: 0.5 | F34: 0.5 | I34: 5 | J34: MINERAL WATER 1.5 L | N34: 90 | O34: 3013499 - Mineral Water 1.5L
A35: 7 | B35: HANDLING CHARGES | E35: 1 | F35: 1 | I35: 6 | J35: MINERAL WATER 0.5 L | N35: 36 | O35: 3013498 - Mineral Water 330mL
A36: 8 | B36: EXTRA VAN CHARGE | E36: 1 | F36: 1 | I36: 7 | J36: COCA COLA BOTTLE 1.5 L
A37: 9 | B37: INTERNATIONAL TRASH REMOVAL | E37: 1 | F37: 1 | I37: 8 | J37: COCA COLA CAN | O37: 3013495 - Coke 355mL
A38: 10 | B38: Custom Clearance Charge | E38: 1 | F38: 1 | I38: 9 | J38: SPRIT BOTTLE 1.5 L | O38: =IF(J38="","",_xlfn.XLOOKUP(J38,'DRY ITEM LIST'!D:D,'DRY ITEM LIST'!B:B,""))
A39: 11 | I39: 10 | J39: SPRIT CAN | O39: 3013497 - Sprite 355mL
A40: 12 | I40: 11 | J40: Wet Ice 5kg Bag | N40: 10 | O40: 3013522 - Wet Ice 5kg Bag
A41: 13 | I41: 12 | J41: Water 1.5 L
A42: 14 | I42: 13 | J42: Water 0.5 L
A43: 15 | I43: 14 | J43: Ginger Ale 355mL | N43: 36 | O43: =IF(J43="","",_xlfn.XLOOKUP(J43,'DRY ITEM LIST'!D:D,'DRY ITEM LIST'!B:B,"")) -> 3013540 - Ginger Ale 355mL
I44: 15 | J44: Fruit Platters | N44: =38/3 -> 12.666667 | O44: =IF(J44="","",_xlfn.XLOOKUP(J44,'DRY ITEM LIST'!D:D,'DRY ITEM LIST'!B:B,"")) -> 3013538 - Fruit Platters
I45: 16 | J45: Tonic Water 355mL | O45: =IF(J45="","",_xlfn.XLOOKUP(J45,'DRY ITEM LIST'!D:D,'DRY ITEM LIST'!B:B,"")) -> 3013503 - Tonic Water 355mL
I46: 17 | J46: Sparkling Water | N46: 24 | O46: =IF(J46="","",_xlfn.XLOOKUP(J46,'DRY ITEM LIST'!D:D,'DRY ITEM LIST'!B:B,"")) -> 3013541 - Sparkling Water
I47: 18 | J47: Coke Light 355mL | N47: 24 | O47: =IF(J47="","",_xlfn.XLOOKUP(J47,'DRY ITEM LIST'!D:D,'DRY ITEM LIST'!B:B,"")) -> 3013496 - Coke Light 355mL
I48: 19 | J48: Soda Water 355L | O48: =IF(J48="","",_xlfn.XLOOKUP(J48,'DRY ITEM LIST'!D:D,'DRY ITEM LIST'!B:B,"")) -> 3013502 - Soda Water 355L
I49: 20 | J49: Bulk Tray - Vegetarian (Fasting) | O49: =IF(J49="","",_xlfn.XLOOKUP(J49,'DRY ITEM LIST'!D:D,'DRY ITEM LIST'!B:B,"")) -> Xtra - Bulk Tray - Vegetarian (Fasting)
I50: 21 | J50: Bulk Tray - Pasta (Fasting) | O50: =IF(J50="","",_xlfn.XLOOKUP(J50,'DRY ITEM LIST'!D:D,'DRY ITEM LIST'!B:B,"")) -> Xtra - Bulk Tray - Pasta (Fasting)

Sheet DN05
A1: A/C TYPE | C1: STATION NAME | E1: DELIVERY NOTE | M1: DATE :
E2: FLIGHT NO | G2: DEPARTURE TIME | I2: FROM | K2: TO | M2: SALES #
A3: B787-900 | C3: ATL | E3: ET519 | G3: 0.45138889 | I3: ATL | K3: ADD | M3: ="ET"&TEXT(N1,"YYYYMMDD") -> ET19000100
D5: Reg Meal | E5: Special Meal
A6: Meal count | B6: Business class: | D6: 15 | E6: 00 VGML
A7: Email | B7: Economy class: | D7: 65 | E7: 01 KSML, 01 AVML
I9: LCH/DNR | L9: HCP /SWH | N9: HBF
A10: SERVICE | F10: FINAL ORDER | I10: 1st SVC/leg | L10: 2nd SVC/ leg | N10: 3rd SVC/leg
B11: PRELIMINARY ORDER | I11: SPML | J11: BC | K11: EY | L11: BC | M11: EY | N11: BC | O11: EY
B12: BC | C12: EY | D12: CR | E12: CP | F12: BC | G12: EY | I12: {=_xlfn.LET(_xlpm.vBC,_xlfn.TEXTSPLIT(E6," ",", "),_xlpm.vEY,_xlfn.TEXTSPLIT(E7," ",", "),_xlpm.vML,_xlfn.UNIQUE(_xlfn.VSTACK(INDEX(_xlpm.vBC,,2),INDEX(_xlpm.vEY,,2))), CHOOSE({1,2,3},_xlpm.vML,VALUE(_xlfn.XLOOKUP(_xlpm.vML,INDEX(_xlpm.vBC,,2),INDEX(_xlpm.vBC,,1),0)),VALUE(_xlfn.XLOOKUP(_xlpm.vML,INDEX(_xlpm.vEY,,2),INDEX(_xlpm.vEY,,1),0))))} -> VGML | J12: 0 | K12: 0 | L12: =J12 -> 0 | M12: =K12 -> 0 | N12: =J12 -> 0 | O12: =K12 -> 0
A13: HBF | B13: =$D$6 -> 15 | C13: =$D$7 -> 65 | D13: 14 | E13: 3 | F13: =SUM(B13,D13:E13) -> 32 | G13: =C13 -> 65 | I13: KSML | J13: 0 | K13: 1 | L13: =J13 -> 0 | M13: =K13 -> 1 | N13: =J13 -> 0 | O13: =K13 -> 1
A14: LCH/DNR | B14: =$D$6 -> 15 | C14: =$D$7 -> 65 | D14: 14 | E14: 3 | F14: =SUM(B14,D14:E14) -> 32 | G14: =C14 -> 65 | I14: AVML | J14: 0 | K14: 1 | L14: =J14 -> 0 | M14: =K14 -> 1 | N14: =J14 -> 0 | O14: =K14 -> 1
A15: HLM | B15: 0 | C15: 0 | F15: 0 | G15: 0 | L15: =J15 -> 0 | M15: =K15 -> 0 | N15: =J15 -> 0 | O15: =K15 -> 0
A16: HCP | B16: =$D$6 -> 15 | C16: 0 | D16: 14 | E16: 3 | F16: =SUM(B16,D16:E16) -> 32 | G16: 0 | L16: =J16 -> 0 | M16: =K16 -> 0 | N16: =J16 -> 0 | O16: =K16 -> 0
A17: SWH | B17: 0 | C17: =$D$7 -> 65 | F17: 0 | G17: =C17 -> 65 | L17: =J17 -> 0 | M17: =K17 -> 0 | N17: =J17 -> 0 | O17: =K17 -> 0
A18: CCP | B18: 0 | C18: 0 | L18: =J18 -> 0 | M18: =K18 -> 0 | N18: =J18 -> 0 | O18: =K18 -> 0
A19: Eye opener | C19: 0 | L19: =J19 -> 0 | M19: =K19 -> 0 | N19: =J19 -> 0 | O19: =K19 -> 0
A20: Fasting Meals | L20: =J20 -> 0 | M20: =K20 -> 0 | N20: =J20 -> 0 | O20: =K20 -> 0
L21: =J21 -> 0 | M21: =K21 -> 0 | N21: =J21 -> 0 | O21: =K21 -> 0
L22: =J22 -> 0 | M22: =K22 -> 0 | N22: =J22 -> 0 | O22: =K22 -> 0
L23: =J23 -> 0 | M23: =K23 -> 0 | N23: =J23 -> 0 | O23: =K23 -> 0
L24: =J24 -> 0 | M24: =K24 -> 0 | N24: =J24 -> 0 | O24: =K24 -> 0
J25: =SUM(J12:J24) -> 0 | K25: =SUM(K12:K24) -> 2 | L25: =SUM(L12:L24) -> 0 | M25: =SUM(M12:M24) -> 2 | N25: =SUM(N12:N24) -> 0 | O25: =SUM(O12:O24) -> 2
A28: NO. | B28: DESCRIPTION | E28: PLAN | F28: AMOUNT | I28: DRY ITEM LIST
A29: 1 | B29: FRUIT BASKET | E29: 1 | F29: 1 | I29: NO. | J29: DESCRIPTION | M29: AMOUNT | N29: AMOUNT
A30: 2 | B30: CHEESE AND CRACKER | E30: 1 | F30: 2 | I30: 1 | J30: ORANGE JUICE | N30: 3 | O30: 3013505 - Juice Orange 1L
A31: 3 | B31: FRESH ORANGE JUICE | E31: 1 | F31: 3 | I31: 2 | J31: APPLE JUICE | O31: 3013506 - Juice Apple 1L
A32: 4 | B32: BREAD BASKET | E32: 1 | F32: 2 | I32: 3 | J32: PINEAPLE JUICE | O32: 3013504 - Juice Pineapple 1L
A33: 5 | B33: Standard Uplift | E33: 1 | F33: 1 | I33: 4 | J33: TOMATO JUICE | O33: 3013507 - Juice Tomato 1L
A34: 6 | B34: LAUNDRY SERVICE | E34: 0.5 | F34: 0.5 | I34: 5 | J34: MINERAL WATER 1.5 L | N34: 42 | O34: 3013499 - Mineral Water 1.5L
A35: 7 | B35: HANDLING CHARGES | E35: 1 | F35: 1 | I35: 6 | J35: MINERAL WATER 0.5 L | N35: 24 | O35: 3013498 - Mineral Water 330mL
A36: 8 | B36: EXTRA VAN CHARGE | E36: 1 | F36: 1 | I36: 7 | J36: COCA COLA BOTTLE 1.5 L
A37: 9 | I37: 8 | J37: COCA COLA CAN | O37: 3013495 - Coke 355mL
A38: 10 | I38: 9 | J38: Sugar Sachet White | O38: =IF(J38="","",_xlfn.XLOOKUP(J38,'DRY ITEM LIST'!D:D,'DRY ITEM LIST'!B:B,"")) -> 3013509 - Sugar Sachet White
A39: 11 | I39: 10 | J39: SPRIT CAN | O39: 3013497 - Sprite 355mL
A40: 12 | I40: 11 | J40: Wet Ice 5kg Bag | N40: 10 | O40: 3013522 - Wet Ice 5kg Bag
A41: 13 | I41: 12 | J41: Fruit Platters | N41: =35/3 -> 11.666667 | O41: =IF(J41="","",_xlfn.XLOOKUP(J41,'DRY ITEM LIST'!D:D,'DRY ITEM LIST'!B:B,"")) -> 3013538 - Fruit Platters
I42: 13 | J42: Ginger Ale 355mL | N42: 12 | O42: =IF(J42="","",_xlfn.XLOOKUP(J42,'DRY ITEM LIST'!D:D,'DRY ITEM LIST'!B:B,"")) -> 3013540 - Ginger Ale 355mL
I43: 14 | J43: Soda Water 355L | O43: =IF(J43="","",_xlfn.XLOOKUP(J43,'DRY ITEM LIST'!D:D,'DRY ITEM LIST'!B:B,"")) -> 3013502 - Soda Water 355L
I44: 15 | J44: Tonic Water 355mL | N44: 12 | O44: =IF(J44="","",_xlfn.XLOOKUP(J44,'DRY ITEM LIST'!D:D,'DRY ITEM LIST'!B:B,"")) -> 3013503 - Tonic Water 355mL
I45: 16 | J45: Coke Light 355mL | N45: 12 | O45: =IF(J45="","",_xlfn.XLOOKUP(J45,'DRY ITEM LIST'!D:D,'DRY ITEM LIST'!B:B,"")) -> 3013496 - Coke Light 355mL
I46: 17 | J46: Sparkling Water | N46: 12 | O46: =IF(J46="","",_xlfn.XLOOKUP(J46,'DRY ITEM LIST'!D:D,'DRY ITEM LIST'!B:B,"")) -> 3013541 - Sparkling Water
I47: 18 | J47: Bulk Tray - Pasta (Fasting) | O47: =IF(J47="","",_xlfn.XLOOKUP(J47,'DRY ITEM LIST'!D:D,'DRY ITEM LIST'!B:B,"")) -> Xtra - Bulk Tray - Pasta (Fasting)
I48: 19 | J48: Bulk Tray - Vegetarian (Fasting) | O48: =IF(J48="","",_xlfn.XLOOKUP(J48,'DRY ITEM LIST'!D:D,'DRY ITEM LIST'!B:B,"")) -> Xtra - Bulk Tray - Vegetarian (Fasting)

Sheet DN11
A1: A/C TYPE | C1: STATION NAME | E1: DELIVERY NOTE | M1: DATE :
E2: FLIGHT NO | G2: DEPARTURE TIME | I2: FROM | K2: TO | M2: SALES #
A3: B787-900 | C3: ATL | E3: ET519 | G3: 0.45138889 | I3: ATL | K3: ADD | M3: ="ET"&TEXT(N1,"YYYYMMDD") -> ET19000100
D5: Reg Meal | E5: Special Meal
A6: Meal count | B6: Business class: | D6: 15 | E6: 01 RVML
A7: Email | B7: Economy class: | D7: 130 | E7: 04 KSML, 01 SFML, 07 MOML , 02 CHML, 01 VLML
I9: LCH/DNR | L9: HCP /SWH | N9: HBF
A10: SERVICE | F10: FINAL ORDER | I10: 1st SVC/leg | L10: 2nd SVC/ leg | N10: 3rd SVC/leg
B11: PRELIMINARY ORDER | I11: SPML | J11: BC | K11: EY | L11: BC | M11: EY | N11: BC | O11: EY
B12: BC | C12: EY | D12: CR | E12: CP | F12: BC | G12: EY | I12: {=_xlfn.LET(_xlpm.vBC,_xlfn.TEXTSPLIT(E6," ",", "),_xlpm.vEY,_xlfn.TEXTSPLIT(E7," ",", "),_xlpm.vML,_xlfn.UNIQUE(_xlfn.VSTACK(INDEX(_xlpm.vBC,,2),INDEX(_xlpm.vEY,,2))), CHOOSE({1,2,3},_xlpm.vML,VALUE(_xlfn.XLOOKUP(_xlpm.vML,INDEX(_xlpm.vBC,,2),INDEX(_xlpm.vBC,,1),0)),VALUE(_xlfn.XLOOKUP(_xlpm.vML,INDEX(_xlpm.vEY,,2),INDEX(_xlpm.vEY,,1),0))))} -> RVML | J12: 1 | K12: 0 | L12: =J12 -> 1 | M12: =K12 -> 0 | N12: =J12 -> 1 | O12: =K12 -> 0
A13: HBF | B13: =$D$6 -> 15 | C13: =$D$7 -> 130 | D13: 12 | E13: 3 | F13: =SUM(B13,D13:E13) -> 30 | G13: =C13 -> 130 | I13: KSML | J13: 0 | K13: 4 | L13: =J13 -> 0 | M13: =K13 -> 4 | N13: =J13 -> 0 | O13: =K13 -> 4
A14: LCH/DNR | B14: =$D$6 -> 15 | C14: =$D$7 -> 130 | D14: 12 | E14: 3 | F14: =SUM(B14,D14:E14) -> 30 | G14: =C14 -> 130 | I14: SFML | J14: 0 | K14: 1 | L14: =J14 -> 0 | M14: =K14 -> 1 | N14: =J14 -> 0 | O14: =K14 -> 1
A15: HLM | B15: 0 | C15: 0 | F15: 0 | G15: 0 | I15: MOML | J15: 0 | K15: 7 | L15: =J15 -> 0 | M15: =K15 -> 7 | N15: =J15 -> 0 | O15: =K15 -> 7
A16: HCP | B16: =$D$6 -> 15 | C16: 0 | D16: 12 | E16: 3 | F16: =SUM(B16,D16:E16) -> 30 | G16: 0 | I16: CHML | J16: 0 | K16: 2 | L16: =J16 -> 0 | M16: =K16 -> 2 | N16: =J16 -> 0 | O16: =K16 -> 2
A17: SWH | B17: 0 | C17: =$D$7 -> 130 | F17: 0 | G17: =C17 -> 130 | I17: VLML | J17: 0 | K17: 1 | L17: =J17 -> 0 | M17: =K17 -> 1 | N17: =J17 -> 0 | O17: =K17 -> 1
A18: CCP | B18: 0 | C18: 0 | L18: =J18 -> 0 | M18: =K18 -> 0 | N18: =J18 -> 0 | O18: =K18 -> 0
A19: Eye opener | C19: 0 | L19: =J19 -> 0 | M19: =K19 -> 0 | N19: =J19 -> 0 | O19: =K19 -> 0
A20: Fasting Meals | L20: =J20 -> 0 | M20: =K20 -> 0 | N20: =J20 -> 0 | O20: =K20 -> 0
L21: =J21 -> 0 | M21: =K21 -> 0 | N21: =J21 -> 0 | O21: =K21 -> 0
L22: =J22 -> 0 | M22: =K22 -> 0 | N22: =J22 -> 0 | O22: =K22 -> 0
L23: =J23 -> 0 | M23: =K23 -> 0 | N23: =J23 -> 0 | O23: =K23 -> 0
L24: =J24 -> 0 | M24: =K24 -> 0 | N24: =J24 -> 0 | O24: =K24 -> 0
J25: =SUM(J12:J24) -> 1 | K25: =SUM(K12:K24) -> 15 | L25: =SUM(L12:L24) -> 1 | M25: =SUM(M12:M24) -> 15 | N25: =SUM(N12:N24) -> 1 | O25: =SUM(O12:O24) -> 15
A28: NO. | B28: DESCRIPTION | E28: PLAN | F28: AMOUNT | I28: DRY ITEM LIST
A29: 1 | B29: FRUIT BASKET | E29: 1 | F29: 1 | I29: NO. | J29: DESCRIPTION | M29: AMOUNT | N29: AMOUNT
A30: 2 | B30: CHEESE AND CRACKER | E30: 1 | F30: 1 | I30: 1 | J30: ORANGE JUICE | N30: 2 | O30: 3013505 - Juice Orange 1L
A31: 3 | B31: FRESH ORANGE JUICE | E31: 1 | F31: 1 | I31: 2 | J31: APPLE JUICE | O31: 3013506 - Juice Apple 1L
A32: 4 | B32: BREAD BASKET | E32: 1 | F32: 1 | I32: 3 | J32: PINEAPLE JUICE | O32: 3013504 - Juice Pineapple 1L
A33: 5 | B33: Standard Uplift | E33: 1 | F33: 1 | I33: 4 | J33: TOMATO JUICE | O33: 3013507 - Juice Tomato 1L
A34: 6 | B34: LAUNDRY SERVICE | E34: 0.5 | F34: 0.5 | I34: 5 | J34: MINERAL WATER 1.5 L | O34: 3013499 - Mineral Water 1.5L
A35: 7 | B35: HANDLING CHARGES | E35: 1 | F35: 1 | I35: 6 | J35: MINERAL WATER 0.5 L | O35: 3013498 - Mineral Water 330mL
A36: 8 | B36: EXTRA VAN CHARGE | E36: 1 | F36: 1 | I36: 7 | J36: COCA COLA BOTTLE 1.5 L
A37: 9 | I37: 8 | J37: COCA COLA CAN | O37: 3013495 - Coke 355mL
A38: 10 | I38: 9 | J38: SPRIT BOTTLE 1.5 L | O38: =IF(J38="","",_xlfn.XLOOKUP(J38,'DRY ITEM LIST'!D:D,'DRY ITEM LIST'!B:B,""))
A39: 11 | I39: 10 | J39: SPRIT CAN | O39: 3013497 - Sprite 355mL
A40: 12 | I40: 11 | J40: Wet Ice 5kg Bag | O40: 3013522 - Wet Ice 5kg Bag
A41: 13 | I41: 12 | J41: Water 1.5 L
A42: 14 | I42: 13 | J42: Water 0.5 L
A43: 15 | I43: 14 | O43: =IF(J43="","",_xlfn.XLOOKUP(J43,'DRY ITEM LIST'!D:D,'DRY ITEM LIST'!B:B,""))
I44: 15 | O44: =IF(J44="","",_xlfn.XLOOKUP(J44,'DRY ITEM LIST'!D:D,'DRY ITEM LIST'!B:B,""))
I45: 16 | O45: =IF(J45="","",_xlfn.XLOOKUP(J45,'DRY ITEM LIST'!D:D,'DRY ITEM LIST'!B:B,""))
I46: 17 | O46: =IF(J46="","",_xlfn.XLOOKUP(J46,'DRY ITEM LIST'!D:D,'DRY ITEM LIST'!B:B,""))
I47: 18 | O47: =IF(J47="","",_xlfn.XLOOKUP(J47,'DRY ITEM LIST'!D:D,'DRY ITEM LIST'!B:B,""))
I48: 19 | O48: =IF(J48="","",_xlfn.XLOOKUP(J48,'DRY ITEM LIST'!D:D,'DRY ITEM LIST'!B:B,""))
I49: 20 | O49: =IF(J49="","",_xlfn.XLOOKUP(J49,'DRY ITEM LIST'!D:D,'DRY ITEM LIST'!B:B,""))

Sheet DN06
A1: A/C TYPE | C1: STATION NAME | E1: DELIVERY NOTE | M1: DATE :
E2: FLIGHT NO | G2: DEPARTURE TIME | I2: FROM | K2: TO | M2: SALES #
A3: B787-900 | C3: ATL | E3: ET519 | G3: 0.45138889 | I3: ATL | K3: ADD | M3: ="ET"&TEXT(N1,"YYYYMMDD") -> ET19000100
D5: Reg Meal | E5: Special Meal
A6: Meal count | B6: Business class: | D6: 21 | E6: 00 SFML
A7: Email | B7: Economy class: | D7: 181 | E7: 01 DBML, 02 CHML, 03 AVML, 01 VGML, 01 VLML, 02 NLML, 02 BBML, 01 FAMF, 01 SFML, 01 HNML
I9: LCH/DNR | L9: HCP /SWH | N9: HBF
A10: SERVICE | F10: FINAL ORDER | I10: 1st SVC/leg | L10: 2nd SVC/ leg | N10: 3rd SVC/leg
B11: PRELIMINARY ORDER | I11: SPML | J11: BC | K11: EY | L11: BC | M11: EY | N11: BC | O11: EY
B12: BC | C12: EY | D12: CR | E12: CP | F12: BC | G12: EY | I12: {=_xlfn.LET(_xlpm.vBC,_xlfn.TEXTSPLIT(E6," ",", "),_xlpm.vEY,_xlfn.TEXTSPLIT(E7," ",", "),_xlpm.vML,_xlfn.UNIQUE(_xlfn.VSTACK(INDEX(_xlpm.vBC,,2),INDEX(_xlpm.vEY,,2))), CHOOSE({1,2,3},_xlpm.vML,VALUE(_xlfn.XLOOKUP(_xlpm.vML,INDEX(_xlpm.vBC,,2),INDEX(_xlpm.vBC,,1),0)),VALUE(_xlfn.XLOOKUP(_xlpm.vML,INDEX(_xlpm.vEY,,2),INDEX(_xlpm.vEY,,1),0))))} -> SFML | J12: 0 | K12: 1 | L12: =J12 -> 0 | M12: =K12 -> 1 | N12: =J12 -> 0 | O12: =K12 -> 1
A13: HBF | B13: =$D$6 -> 21 | C13: =$D$7 -> 181 | D13: 14 | E13: 3 | F13: =SUM(B13,D13:E13) -> 38 | G13: =C13 -> 181 | I13: DBML | J13: 0 | K13: 1 | L13: =J13 -> 0 | M13: =K13 -> 1 | N13: =J13 -> 0 | O13: =K13 -> 1
A14: LCH/DNR | B14: =$D$6 -> 21 | C14: =$D$7 -> 181 | D14: 14 | E14: 3 | F14: =SUM(B14,D14:E14) -> 38 | G14: =C14 -> 181 | I14: CHML | J14: 0 | K14: 2 | L14: =J14 -> 0 | M14: =K14 -> 2 | N14: =J14 -> 0 | O14: =K14 -> 2
A15: HLM | B15: 0 | C15: 0 | F15: 0 | G15: 0 | I15: AVML | J15: 0 | K15: 3 | L15: =J15 -> 0 | M15: =K15 -> 3 | N15: =J15 -> 0 | O15: =K15 -> 3
A16: HCP | B16: =$D$6 -> 21 | C16: 0 | D16: 14 | E16: 3 | F16: =SUM(B16,D16:E16) -> 38 | G16: 0 | I16: VGML | J16: 0 | K16: 1 | L16: =J16 -> 0 | M16: =K16 -> 1 | N16: =J16 -> 0 | O16: =K16 -> 1
A17: SWH | B17: 0 | C17: =$D$7 -> 181 | F17: 0 | G17: =C17 -> 181 | I17: VLML | J17: 0 | K17: 1 | L17: =J17 -> 0 | M17: =K17 -> 1 | N17: =J17 -> 0 | O17: =K17 -> 1
A18: CCP | B18: 0 | C18: 0 | I18: NLML | J18: 0 | K18: 2 | L18: =J18 -> 0 | M18: =K18 -> 2 | N18: =J18 -> 0 | O18: =K18 -> 2
A19: Eye opener | C19: 0 | I19: BBML | J19: 0 | K19: 2 | L19: =J19 -> 0 | M19: =K19 -> 2 | N19: =J19 -> 0 | O19: =K19 -> 2
A20: Fasting Meals | I20: FAMF | J20: 0 | K20: 1 | L20: =J20 -> 0 | M20: =K20 -> 1 | N20: =J20 -> 0 | O20: =K20 -> 1
I21: HNML | J21: 0 | K21: 1 | L21: =J21 -> 0 | M21: =K21 -> 1 | N21: =J21 -> 0 | O21: =K21 -> 1
L22: =J22 -> 0 | M22: =K22 -> 0 | N22: =J22 -> 0 | O22: =K22 -> 0
L23: =J23 -> 0 | M23: =K23 -> 0 | N23: =J23 -> 0 | O23: =K23 -> 0
L24: =J24 -> 0 | M24: =K24 -> 0 | N24: =J24 -> 0 | O24: =K24 -> 0
J25: =SUM(J12:J24) -> 0 | K25: =SUM(K12:K24) -> 15 | L25: =SUM(L12:L24) -> 0 | M25: =SUM(M12:M24) -> 15 | N25: =SUM(N12:N24) -> 0 | O25: =SUM(O12:O24) -> 15
A28: NO. | B28: DESCRIPTION | E28: PLAN | F28: AMOUNT | I28: DRY ITEM LIST
A29: 1 | B29: FRUIT BASKET | E29: 1 | F29: 1 | I29: NO. | J29: DESCRIPTION | M29: AMOUNT | N29: AMOUNT
A30: 2 | B30: CHEESE AND CRACKER | E30: 1 | F30: 2 | I30: 1 | J30: ORANGE JUICE | N30: 27 | O30: 3013505 - Juice Orange 1L
A31: 3 | B31: FRESH ORANGE JUICE | E31: 1 | F31: 3 | I31: 2 | J31: APPLE JUICE | N31: 24 | O31: 3013506 - Juice Apple 1L
A32: 4 | B32: BREAD BASKET | E32: 1 | F32: 2 | I32: 3 | J32: PINEAPLE JUICE | O32: 3013504 - Juice Pineapple 1L
A33: 5 | B33: Standard Uplift | E33: 1 | F33: 1 | I33: 4 | J33: TOMATO JUICE | O33: 3013507 - Juice Tomato 1L
A34: 6 | B34: LAUNDRY SERVICE | E34: 0.5 | F34: 0.5 | I34: 5 | J34: MINERAL WATER 1.5 L | N34: 60 | O34: 3013499 - Mineral Water 1.5L
A35: 7 | B35: HANDLING CHARGES | E35: 1 | F35: 1 | I35: 6 | J35: MINERAL WATER 0.5 L | O35: 3013498 - Mineral Water 330mL
A36: 8 | B36: EXTRA VAN CHARGE | E36: 1 | F36: 1 | I36: 7 | J36: COCA COLA BOTTLE 1.5 L
A37: 9 | I37: 8 | J37: COCA COLA CAN | N37: 12 | O37: 3013495 - Coke 355mL
A38: 10 | I38: 9 | J38: SPRIT BOTTLE 1.5 L | O38: =IF(J38="","",_xlfn.XLOOKUP(J38,'DRY ITEM LIST'!D:D,'DRY ITEM LIST'!B:B,""))
A39: 11 | I39: 10 | J39: SPRIT CAN | O39: 3013497 - Sprite 355mL
A40: 12 | I40: 11 | J40: Wet Ice 5kg Bag | N40: 10 | O40: 3013522 - Wet Ice 5kg Bag
A41: 13 | I41: 12 | J41: Water 1.5 L
A42: 14 | I42: 13 | J42: Water 0.5 L
A43: 15 | I43: 14 | J43: Tonic Water 355mL | O43: =IF(J43="","",_xlfn.XLOOKUP(J43,'DRY ITEM LIST'!D:D,'DRY ITEM LIST'!B:B,"")) -> 3013503 - Tonic Water 355mL
I44: 15 | J44: Fruit Platters | N44: =35/3 -> 11.666667 | O44: =IF(J44="","",_xlfn.XLOOKUP(J44,'DRY ITEM LIST'!D:D,'DRY ITEM LIST'!B:B,"")) -> 3013538 - Fruit Platters
I45: 16 | J45: Sparkling Water | N45: 12 | O45: =IF(J45="","",_xlfn.XLOOKUP(J45,'DRY ITEM LIST'!D:D,'DRY ITEM LIST'!B:B,"")) -> 3013541 - Sparkling Water
I46: 17 | J46: Ginger Ale 355mL | N46: 24 | O46: =IF(J46="","",_xlfn.XLOOKUP(J46,'DRY ITEM LIST'!D:D,'DRY ITEM LIST'!B:B,"")) -> 3013540 - Ginger Ale 355mL
I47: 18 | J47: Bulk Tray - Pasta (Fasting) | O47: =IF(J47="","",_xlfn.XLOOKUP(J47,'DRY ITEM LIST'!D:D,'DRY ITEM LIST'!B:B,"")) -> Xtra - Bulk Tray - Pasta (Fasting)
I48: 19 | J48: Bulk Tray - Vegetarian (Fasting) | O48: =IF(J48="","",_xlfn.XLOOKUP(J48,'DRY ITEM LIST'!D:D,'DRY ITEM LIST'!B:B,"")) -> Xtra - Bulk Tray - Vegetarian (Fasting)
I49: 20 | J49: Soda Water 355L | N49: 12 | O49: =IF(J49="","",_xlfn.XLOOKUP(J49,'DRY ITEM LIST'!D:D,'DRY ITEM LIST'!B:B,"")) -> 3013502 - Soda Water 355L

Sheet DN07
A1: A/C TYPE | C1: STATION NAME | E1: DELIVERY NOTE | M1: DATE :
E2: FLIGHT NO | G2: DEPARTURE TIME | I2: FROM | K2: TO | M2: SALES #
A3: B787-900 | C3: ATL | E3: ET519 | G3: 0.45138889 | I3: ATL | K3: ADD | M3: ="ET"&TEXT(N1,"YYYYMMDD") -> ET19000100
D5: Reg Meal | E5: Special Meal
A6: Meal count | B6: Business class: | D6: 23 | E6: 03 AVML
A7: Email | B7: Economy class: | D7: 173 | E7: 01 VGML, 02 VLML, 03 MOML, 01 AVML
I9: LCH/DNR | L9: HCP /SWH | N9: HBF
A10: SERVICE | F10: FINAL ORDER | I10: 1st SVC/leg | L10: 2nd SVC/ leg | N10: 3rd SVC/leg
B11: PRELIMINARY ORDER | I11: SPML | J11: BC | K11: EY | L11: BC | M11: EY | N11: BC | O11: EY
B12: BC | C12: EY | D12: CR | E12: CP | F12: BC | G12: EY | I12: {=_xlfn.LET(_xlpm.vBC,_xlfn.TEXTSPLIT(E6," ",", "),_xlpm.vEY,_xlfn.TEXTSPLIT(E7," ",", "),_xlpm.vML,_xlfn.UNIQUE(_xlfn.VSTACK(INDEX(_xlpm.vBC,,2),INDEX(_xlpm.vEY,,2))), CHOOSE({1,2,3},_xlpm.vML,VALUE(_xlfn.XLOOKUP(_xlpm.vML,INDEX(_xlpm.vBC,,2),INDEX(_xlpm.vBC,,1),0)),VALUE(_xlfn.XLOOKUP(_xlpm.vML,INDEX(_xlpm.vEY,,2),INDEX(_xlpm.vEY,,1),0))))} -> AVML | J12: 3 | K12: 1 | L12: =J12 -> 3 | M12: =K12 -> 1 | N12: =J12 -> 3 | O12: =K12 -> 1
A13: HBF | B13: =$D$6 -> 23 | C13: =$D$7 -> 173 | D13: 14 | E13: 3 | F13: =SUM(B13,D13:E13) -> 40 | G13: =C13 -> 173 | I13: VGML | J13: 0 | K13: 1 | L13: =J13 -> 0 | M13: =K13 -> 1 | N13: =J13 -> 0 | O13: =K13 -> 1
A14: LCH/DNR | B14: =$D$6 -> 23 | C14: =$D$7 -> 173 | D14: 14 | E14: 3 | F14: =SUM(B14,D14:E14) -> 40 | G14: =C14 -> 173 | I14: VLML | J14: 0 | K14: 2 | L14: =J14 -> 0 | M14: =K14 -> 2 | N14: =J14 -> 0 | O14: =K14 -> 2
A15: HLM | B15: 0 | C15: 0 | F15: 0 | G15: 0 | I15: MOML | J15: 0 | K15: 3 | L15: =J15 -> 0 | M15: =K15 -> 3 | N15: =J15 -> 0 | O15: =K15 -> 3
A16: HCP | B16: =$D$6 -> 23 | C16: 0 | D16: 14 | E16: 3 | F16: =SUM(B16,D16:E16) -> 40 | G16: 0 | L16: =J16 -> 0 | M16: =K16 -> 0 | N16: =J16 -> 0 | O16: =K16 -> 0
A17: SWH | B17: 0 | C17: =$D$7 -> 173 | F17: 0 | G17: =C17 -> 173 | L17: =J17 -> 0 | M17: =K17 -> 0 | N17: =J17 -> 0 | O17: =K17 -> 0
A18: CCP | B18: 0 | C18: 0 | L18: =J18 -> 0 | M18: =K18 -> 0 | N18: =J18 -> 0 | O18: =K18 -> 0
A19: Eye opener | C19: 0 | L19: =J19 -> 0 | M19: =K19 -> 0 | N19: =J19 -> 0 | O19: =K19 -> 0
A20: Fasting Meals | L20: =J20 -> 0 | M20: =K20 -> 0 | N20: =J20 -> 0 | O20: =K20 -> 0
L21: =J21 -> 0 | M21: =K21 -> 0 | N21: =J21 -> 0 | O21: =K21 -> 0
L22: =J22 -> 0 | M22: =K22 -> 0 | N22: =J22 -> 0 | O22: =K22 -> 0
L23: =J23 -> 0 | M23: =K23 -> 0 | N23: =J23 -> 0 | O23: =K23 -> 0
L24: =J24 -> 0 | M24: =K24 -> 0 | N24: =J24 -> 0 | O24: =K24 -> 0
J25: =SUM(J12:J24) -> 3 | K25: =SUM(K12:K24) -> 7 | L25: =SUM(L12:L24) -> 3 | M25: =SUM(M12:M24) -> 7 | N25: =SUM(N12:N24) -> 3 | O25: =SUM(O12:O24) -> 7
A28: NO. | B28: DESCRIPTION | E28: PLAN | F28: AMOUNT | I28: DRY ITEM LIST
A29: 1 | B29: FRUIT BASKET | E29: 1 | F29: 1 | I29: NO. | J29: DESCRIPTION | M29: AMOUNT | N29: AMOUNT
A30: 2 | B30: CHEESE AND CRACKER | E30: 1 | F30: 2 | I30: 1 | J30: ORANGE JUICE | N30: 15 | O30: 3013505 - Juice Orange 1L
A31: 3 | B31: FRESH ORANGE JUICE | E31: 1 | F31: 3 | I31: 2 | J31: APPLE JUICE | N31: 24 | O31: 3013506 - Juice Apple 1L
A32: 4 | B32: BREAD BASKET | E32: 1 | F32: 2 | I32: 3 | J32: PINEAPLE JUICE | O32: 3013504 - Juice Pineapple 1L
A33: 5 | B33: Standard Uplift | E33: 1 | F33: 1 | I33: 4 | J33: TOMATO JUICE | O33: 3013507 - Juice Tomato 1L
A34: 6 | B34: LAUNDRY SERVICE | E34: 0.5 | F34: 0.5 | I34: 5 | J34: MINERAL WATER 1.5 L | N34: 70 | O34: 3013499 - Mineral Water 1.5L
A35: 7 | B35: HANDLING CHARGES | E35: 1 | F35: 1 | I35: 6 | J35: MINERAL WATER 0.5 L | N35: 36 | O35: 3013498 - Mineral Water 330mL
A36: 8 | B36: EXTRA VAN CHARGE | E36: 1 | F36: 1 | I36: 7 | J36: COCA COLA BOTTLE 1.5 L
A37: 9 | I37: 8 | J37: COCA COLA CAN | O37: 3013495 - Coke 355mL
A38: 10 | I38: 9 | J38: Coke Light 355mL | N38: 24 | O38: =IF(J38="","",_xlfn.XLOOKUP(J38,'DRY ITEM LIST'!D:D,'DRY ITEM LIST'!B:B,"")) -> 3013496 - Coke Light 355mL
A39: 11 | I39: 10 | J39: SPRIT CAN | O39: 3013497 - Sprite 355mL
A40: 12 | I40: 11 | J40: Wet Ice 5kg Bag | N40: 10 | O40: 3013522 - Wet Ice 5kg Bag
A41: 13 | I41: 12 | J41: Fruit Platters | N41: =35/3 -> 11.666667 | O41: =IF(J41="","",_xlfn.XLOOKUP(J41,'DRY ITEM LIST'!D:D,'DRY ITEM LIST'!B:B,"")) -> 3013538 - Fruit Platters
I42: 13 | J42: Tonic Water 355mL | N42: 12 | O42: =IF(J42="","",_xlfn.XLOOKUP(J42,'DRY ITEM LIST'!D:D,'DRY ITEM LIST'!B:B,"")) -> 3013503 - Tonic Water 355mL
I43: 14 | J43: Soda Water 355L | N43: 12 | O43: =IF(J43="","",_xlfn.XLOOKUP(J43,'DRY ITEM LIST'!D:D,'DRY ITEM LIST'!B:B,"")) -> 3013502 - Soda Water 355L
I44: 15 | J44: Ginger Ale 355mL | N44: 24 | O44: =IF(J44="","",_xlfn.XLOOKUP(J44,'DRY ITEM LIST'!D:D,'DRY ITEM LIST'!B:B,"")) -> 3013540 - Ginger Ale 355mL
I45: 16 | J45: Bulk Tray - Vegetarian (Fasting) | O45: =IF(J45="","",_xlfn.XLOOKUP(J45,'DRY ITEM LIST'!D:D,'DRY ITEM LIST'!B:B,"")) -> Xtra - Bulk Tray - Vegetarian (Fasting)
I46: 17 | J46: Bulk Tray - Pasta (Fasting) | O46: =IF(J46="","",_xlfn.XLOOKUP(J46,'DRY ITEM LIST'!D:D,'DRY ITEM LIST'!B:B,"")) -> Xtra - Bulk Tray - Pasta (Fasting)
I47: 18 | J47: Sparkling Water | O47: =IF(J47="","",_xlfn.XLOOKUP(J47,'DRY ITEM LIST'!D:D,'DRY ITEM LIST'!B:B,"")) -> 3013541 - Sparkling Water

Sheet DN08
A1: A/C TYPE | C1: STATION NAME | E1: DELIVERY NOTE | M1: DATE :
E2: FLIGHT NO | G2: DEPARTURE TIME | I2: FROM | K2: TO | M2: SALES #
A3: B787-900 | C3: ATL | E3: ET519 | G3: 0.45138889 | I3: ATL | K3: ADD | M3: ="ET"&TEXT(N1,"YYYYMMDD") -> ET19000100
D5: Reg Meal | E5: Special Meal
A6: Meal count | B6: Business class: | D6: 16 | E6: 00 AVML
A7: Email | B7: Economy class: | D7: 122 | E7: 02 KSML, 01 DBML, 01 HNML, 01 AVML, 04 VGML, 01 VLML, 01 NLML, 01 FPML, 03 SFML, 01 LCML
I9: LCH/DNR | L9: HCP /SWH | N9: HBF
A10: SERVICE | F10: FINAL ORDER | I10: 1st SVC/leg | L10: 2nd SVC/ leg | N10: 3rd SVC/leg
B11: PRELIMINARY ORDER | I11: SPML | J11: BC | K11: EY | L11: BC | M11: EY | N11: BC | O11: EY
B12: BC | C12: EY | D12: CR | E12: CP | F12: BC | G12: EY | I12: {=_xlfn.LET(_xlpm.vBC,_xlfn.TEXTSPLIT(E6," ",", "),_xlpm.vEY,_xlfn.TEXTSPLIT(E7," ",", "),_xlpm.vML,_xlfn.UNIQUE(_xlfn.VSTACK(INDEX(_xlpm.vBC,,2),INDEX(_xlpm.vEY,,2))), CHOOSE({1,2,3},_xlpm.vML,VALUE(_xlfn.XLOOKUP(_xlpm.vML,INDEX(_xlpm.vBC,,2),INDEX(_xlpm.vBC,,1),0)),VALUE(_xlfn.XLOOKUP(_xlpm.vML,INDEX(_xlpm.vEY,,2),INDEX(_xlpm.vEY,,1),0))))} -> AVML | J12: 0 | K12: 1 | L12: =J12 -> 0 | M12: =K12 -> 1 | N12: =J12 -> 0 | O12: =K12 -> 1
A13: HBF | B13: =$D$6 -> 16 | C13: =$D$7 -> 122 | D13: 14 | E13: 3 | F13: =SUM(B13,D13:E13) -> 33 | G13: =C13 -> 122 | I13: KSML | J13: 0 | K13: 2 | L13: =J13 -> 0 | M13: =K13 -> 2 | N13: =J13 -> 0 | O13: =K13 -> 2
A14: LCH/DNR | B14: =$D$6 -> 16 | C14: =$D$7 -> 122 | D14: 14 | E14: 3 | F14: =SUM(B14,D14:E14) -> 33 | G14: =C14 -> 122 | I14: DBML | J14: 0 | K14: 1 | L14: =J14 -> 0 | M14: =K14 -> 1 | N14: =J14 -> 0 | O14: =K14 -> 1
A15: HLM | B15: 0 | C15: 0 | F15: 0 | G15: 0 | I15: HNML | J15: 0 | K15: 1 | L15: =J15 -> 0 | M15: =K15 -> 1 | N15: =J15 -> 0 | O15: =K15 -> 1
A16: HCP | B16: =$D$6 -> 16 | C16: 0 | D16: 14 | E16: 3 | F16: =SUM(B16,D16:E16) -> 33 | G16: 0 | I16: VGML | J16: 0 | K16: 4 | L16: =J16 -> 0 | M16: =K16 -> 4 | N16: =J16 -> 0 | O16: =K16 -> 4
A17: SWH | B17: 0 | C17: =$D$7 -> 122 | F17: 0 | G17: =C17 -> 122 | I17: VLML | J17: 0 | K17: 1 | L17: =J17 -> 0 | M17: =K17 -> 1 | N17: =J17 -> 0 | O17: =K17 -> 1
A18: CCP | B18: 0 | C18: 0 | I18: NLML | J18: 0 | K18: 1 | L18: =J18 -> 0 | M18: =K18 -> 1 | N18: =J18 -> 0 | O18: =K18 -> 1
A19: Eye opener | C19: 0 | I19: FPML | J19: 0 | K19: 1 | L19: =J19 -> 0 | M19: =K19 -> 1 | N19: =J19 -> 0 | O19: =K19 -> 1
A20: Fasting Meals | I20: SFML | J20: 0 | K20: 3 | L20: =J20 -> 0 | M20: =K20 -> 3 | N20: =J20 -> 0 | O20: =K20 -> 3
I21: LCML | J21: 0 | K21: 1 | L21: =J21 -> 0 | M21: =K21 -> 1 | N21: =J21 -> 0 | O21: =K21 -> 1
L22: =J22 -> 0 | M22: =K22 -> 0 | N22: =J22 -> 0 | O22: =K22 -> 0
L23: =J23 -> 0 | M23: =K23 -> 0 | N23: =J23 -> 0 | O23: =K23 -> 0
L24: =J24 -> 0 | M24: =K24 -> 0 | N24: =J24 -> 0 | O24: =K24 -> 0
J25: =SUM(J12:J24) -> 0 | K25: =SUM(K12:K24) -> 16 | L25: =SUM(L12:L24) -> 0 | M25: =SUM(M12:M24) -> 16 | N25: =SUM(N12:N24) -> 0 | O25: =SUM(O12:O24) -> 16
A28: NO. | B28: DESCRIPTION | E28: PLAN | F28: AMOUNT | I28: DRY ITEM LIST
A29: 1 | B29: FRUIT BASKET | E29: 1 | F29: 1 | I29: NO. | J29: DESCRIPTION | M29: AMOUNT | N29: AMOUNT
A30: 2 | B30: CHEESE AND CRACKER | E30: 1 | F30: 2 | I30: 1 | J30: ORANGE JUICE | N30: 3 | O30: 3013505 - Juice Orange 1L
A31: 3 | B31: FRESH ORANGE JUICE | E31: 1 | F31: 3 | I31: 2 | J31: APPLE JUICE | O31: 3013506 - Juice Apple 1L
A32: 4 | B32: BREAD BASKET | E32: 1 | F32: 2 | I32: 3 | J32: PINEAPLE JUICE | O32: 3013504 - Juice Pineapple 1L
A33: 5 | B33: Standard Uplift | E33: 1 | F33: 1 | I33: 4 | J33: TOMATO JUICE | O33: 3013507 - Juice Tomato 1L
A34: 6 | B34: LAUNDRY SERVICE | E34: 0.5 | F34: 0.5 | I34: 5 | J34: MINERAL WATER 1.5 L | N34: 80 | O34: 3013499 - Mineral Water 1.5L
A35: 7 | B35: HANDLING CHARGES | E35: 1 | F35: 1 | I35: 6 | J35: MINERAL WATER 0.5 L | N35: 12 | O35: 3013498 - Mineral Water 330mL
A36: 8 | B36: EXTRA VAN CHARGE | E36: 1 | F36: 1 | I36: 7 | J36: COCA COLA BOTTLE 1.5 L
A37: 9 | I37: 8 | J37: COCA COLA CAN | N37: 12 | O37: 3013495 - Coke 355mL
A38: 10 | I38: 9 | J38: SPRIT BOTTLE 1.5 L | O38: =IF(J38="","",_xlfn.XLOOKUP(J38,'DRY ITEM LIST'!D:D,'DRY ITEM LIST'!B:B,""))
A39: 11 | I39: 10 | J39: SPRIT CAN | N39: 12 | O39: 3013497 - Sprite 355mL
A40: 12 | I40: 11 | J40: Wet Ice 5kg Bag | N40: 10 | O40: 3013522 - Wet Ice 5kg Bag
A41: 13 | I41: 12 | J41: Water 1.5 L
A42: 14 | I42: 13 | J42: Water 0.5 L
A43: 15 | I43: 14 | J43: Fruit Platters | N43: =30/3 -> 10 | O43: =IF(J43="","",_xlfn.XLOOKUP(J43,'DRY ITEM LIST'!D:D,'DRY ITEM LIST'!B:B,"")) -> 3013538 - Fruit Platters
I44: 15 | J44: Coke Light 355mL | N44: 12 | O44: =IF(J44="","",_xlfn.XLOOKUP(J44,'DRY ITEM LIST'!D:D,'DRY ITEM LIST'!B:B,"")) -> 3013496 - Coke Light 355mL
I45: 16 | J45: Ginger Ale 355mL | N45: 12 | O45: =IF(J45="","",_xlfn.XLOOKUP(J45,'DRY ITEM LIST'!D:D,'DRY ITEM LIST'!B:B,"")) -> 3013540 - Ginger Ale 355mL
I46: 17 | J46: Sparkling Water | N46: 12 | O46: =IF(J46="","",_xlfn.XLOOKUP(J46,'DRY ITEM LIST'!D:D,'DRY ITEM LIST'!B:B,"")) -> 3013541 - Sparkling Water
I47: 18 | J47: Tonic Water 355mL | N47: 24 | O47: =IF(J47="","",_xlfn.XLOOKUP(J47,'DRY ITEM LIST'!D:D,'DRY ITEM LIST'!B:B,"")) -> 3013503 - Tonic Water 355mL
I48: 19 | J48: Bulk Tray - Vegetarian (Fasting) | O48: =IF(J48="","",_xlfn.XLOOKUP(J48,'DRY ITEM LIST'!D:D,'DRY ITEM LIST'!B:B,"")) -> Xtra - Bulk Tray - Vegetarian (Fasting)
I49: 20 | J49: Bulk Tray - Pasta (Fasting) | O49: =IF(J49="","",_xlfn.XLOOKUP(J49,'DRY ITEM LIST'!D:D,'DRY ITEM LIST'!B:B,"")) -> Xtra - Bulk Tray - Pasta (Fasting)

Sheet DN09
A1: A/C TYPE | C1: STATION NAME | E1: DELIVERY NOTE | M1: DATE :
E2: FLIGHT NO | G2: DEPARTURE TIME | I2: FROM | K2: TO | M2: SALES #
A3: B787-900 | C3: ATL | E3: ET519 | G3: 0.45138889 | I3: ATL | K3: ADD | M3: ="ET"&TEXT(N1,"YYYYMMDD") -> ET19000100
D5: Reg Meal | E5: Special Meal
A6: Meal count | B6: Business class: | D6: 6 | E6: 00 DBML
A7: Email | B7: Economy class: | D7: 173 | E7: 02 DBML, 03 MOML, 03 AVML, 05 VGML, 07 VLML, 03 SPML
I9: LCH/DNR | L9: HCP /SWH | N9: HBF
A10: SERVICE | F10: FINAL ORDER | I10: 1st SVC/leg | L10: 2nd SVC/ leg | N10: 3rd SVC/leg
B11: PRELIMINARY ORDER | I11: SPML | J11: BC | K11: EY | L11: BC | M11: EY | N11: BC | O11: EY
B12: BC | C12: EY | D12: CR | E12: CP | F12: BC | G12: EY | I12: {=_xlfn.LET(_xlpm.vBC,_xlfn.TEXTSPLIT(E6," ",", "),_xlpm.vEY,_xlfn.TEXTSPLIT(E7," ",", "),_xlpm.vML,_xlfn.UNIQUE(_xlfn.VSTACK(INDEX(_xlpm.vBC,,2),INDEX(_xlpm.vEY,,2))), CHOOSE({1,2,3},_xlpm.vML,VALUE(_xlfn.XLOOKUP(_xlpm.vML,INDEX(_xlpm.vBC,,2),INDEX(_xlpm.vBC,,1),0)),VALUE(_xlfn.XLOOKUP(_xlpm.vML,INDEX(_xlpm.vEY,,2),INDEX(_xlpm.vEY,,1),0))))} -> DBML | J12: 0 | K12: 2 | L12: =J12 -> 0 | M12: =K12 -> 2 | N12: =J12 -> 0 | O12: =K12 -> 2
A13: HBF | B13: =$D$6 -> 6 | C13: =$D$7 -> 173 | D13: 14 | E13: 3 | F13: =SUM(B13,D13:E13) -> 23 | G13: =C13 -> 173 | I13: MOML | J13: 0 | K13: 3 | L13: =J13 -> 0 | M13: =K13 -> 3 | N13: =J13 -> 0 | O13: =K13 -> 3
A14: LCH/DNR | B14: =$D$6 -> 6 | C14: =$D$7 -> 173 | D14: 14 | E14: 3 | F14: =SUM(B14,D14:E14) -> 23 | G14: =C14 -> 173 | I14: AVML | J14: 0 | K14: 3 | L14: =J14 -> 0 | M14: =K14 -> 3 | N14: =J14 -> 0 | O14: =K14 -> 3
A15: HLM | B15: 0 | C15: 0 | F15: 0 | G15: 0 | I15: VGML | J15: 0 | K15: 5 | L15: =J15 -> 0 | M15: =K15 -> 5 | N15: =J15 -> 0 | O15: =K15 -> 5
A16: HCP | B16: =$D$6 -> 6 | C16: 0 | D16: 14 | E16: 3 | F16: =SUM(B16,D16:E16) -> 23 | G16: 0 | I16: VLML | J16: 0 | K16: 7 | L16: =J16 -> 0 | M16: =K16 -> 7 | N16: =J16 -> 0 | O16: =K16 -> 7
A17: SWH | B17: 0 | C17: =$D$7 -> 173 | F17: 0 | G17: =C17 -> 173 | I17: SPML | J17: 0 | K17: 3 | L17: =J17 -> 0 | M17: =K17 -> 3 | N17: =J17 -> 0 | O17: =K17 -> 3
A18: CCP | B18: 0 | C18: 0 | L18: =J18 -> 0 | M18: =K18 -> 0 | N18: =J18 -> 0 | O18: =K18 -> 0
A19: Eye opener | C19: 0 | L19: =J19 -> 0 | M19: =K19 -> 0 | N19: =J19 -> 0 | O19: =K19 -> 0
A20: Fasting Meals | B20: 1 | C20: 20 | D20: 8 | F20: 9 | G20: 20 | L20: =J20 -> 0 | M20: =K20 -> 0 | N20: =J20 -> 0 | O20: =K20 -> 0
L21: =J21 -> 0 | M21: =K21 -> 0 | N21: =J21 -> 0 | O21: =K21 -> 0
L22: =J22 -> 0 | M22: =K22 -> 0 | N22: =J22 -> 0 | O22: =K22 -> 0
L23: =J23 -> 0 | M23: =K23 -> 0 | N23: =J23 -> 0 | O23: =K23 -> 0
L24: =J24 -> 0 | M24: =K24 -> 0 | N24: =J24 -> 0 | O24: =K24 -> 0
J25: =SUM(J12:J24) -> 0 | K25: =SUM(K12:K24) -> 23 | L25: =SUM(L12:L24) -> 0 | M25: =SUM(M12:M24) -> 23 | N25: =SUM(N12:N24) -> 0 | O25: =SUM(O12:O24) -> 23
A28: NO. | B28: DESCRIPTION | E28: PLAN | F28: AMOUNT | I28: DRY ITEM LIST
A29: 1 | B29: FRUIT BASKET | E29: 1 | F29: 1 | I29: NO. | J29: DESCRIPTION | M29: AMOUNT | N29: AMOUNT
A30: 2 | B30: CHEESE AND CRACKER | E30: 1 | F30: 2 | I30: 1 | J30: ORANGE JUICE | N30: 9 | O30: 3013505 - Juice Orange 1L
A31: 3 | B31: FRESH ORANGE JUICE | E31: 1 | F31: 3 | I31: 2 | J31: APPLE JUICE | N31: 24 | O31: 3013506 - Juice Apple 1L
A32: 4 | B32: BREAD BASKET | E32: 1 | F32: 2 | I32: 3 | J32: PINEAPLE JUICE | O32: 3013504 - Juice Pineapple 1L
A33: 5 | B33: Standard Uplift | E33: 1 | F33: 1 | I33: 4 | J33: TOMATO JUICE | O33: 3013507 - Juice Tomato 1L
A34: 6 | B34: LAUNDRY SERVICE | E34: 0.5 | F34: 0.5 | I34: 5 | J34: MINERAL WATER 1.5 L | N34: 80 | O34: 3013499 - Mineral Water 1.5L
A35: 7 | B35: HANDLING CHARGES | E35: 1 | F35: 1 | I35: 6 | J35: MINERAL WATER 0.5 L | O35: 3013498 - Mineral Water 330mL
A36: 8 | B36: EXTRA VAN CHARGE | E36: 1 | F36: 1 | I36: 7 | J36: COCA COLA BOTTLE 1.5 L
A37: 9 | I37: 8 | J37: COCA COLA CAN | N37: 12 | O37: 3013495 - Coke 355mL
A38: 10 | I38: 9 | J38: SPRIT BOTTLE 1.5 L | O38: =IF(J38="","",_xlfn.XLOOKUP(J38,'DRY ITEM LIST'!D:D,'DRY ITEM LIST'!B:B,""))
A39: 11 | I39: 10 | J39: SPRIT CAN | N39: 12 | O39: 3013497 - Sprite 355mL
A40: 12 | I40: 11 | J40: Wet Ice 5kg Bag | N40: 10 | O40: 3013522 - Wet Ice 5kg Bag
A41: 13 | I41: 12 | J41: Water 1.5 L
A42: 14 | I42: 13 | J42: Water 0.5 L
A43: 15 | I43: 14 | J43: Ginger Ale 355mL | N43: 24 | O43: =IF(J43="","",_xlfn.XLOOKUP(J43,'DRY ITEM LIST'!D:D,'DRY ITEM LIST'!B:B,"")) -> 3013540 - Ginger Ale 355mL
I44: 15 | J44: Coke Light 355mL | N44: 36 | O44: =IF(J44="","",_xlfn.XLOOKUP(J44,'DRY ITEM LIST'!D:D,'DRY ITEM LIST'!B:B,"")) -> 3013496 - Coke Light 355mL
I45: 16 | J45: Fruit Platters | N45: =30/3 -> 10 | O45: =IF(J45="","",_xlfn.XLOOKUP(J45,'DRY ITEM LIST'!D:D,'DRY ITEM LIST'!B:B,"")) -> 3013538 - Fruit Platters
I46: 17 | J46: Tonic Water 355mL | N46: 12 | O46: =IF(J46="","",_xlfn.XLOOKUP(J46,'DRY ITEM LIST'!D:D,'DRY ITEM LIST'!B:B,"")) -> 3013503 - Tonic Water 355mL
I47: 18 | J47: Sparkling Water | N47: 16 | O47: =IF(J47="","",_xlfn.XLOOKUP(J47,'DRY ITEM LIST'!D:D,'DRY ITEM LIST'!B:B,"")) -> 3013541 - Sparkling Water
I48: 19 | J48: Bulk Tray - Vegetarian (Fasting) | N48: 2 | O48: =IF(J48="","",_xlfn.XLOOKUP(J48,'DRY ITEM LIST'!D:D,'DRY ITEM LIST'!B:B,"")) -> Xtra - Bulk Tray - Vegetarian (Fasting)
I49: 20 | J49: Bulk Tray - Pasta (Fasting) | N49: 2 | O49: =IF(J49="","",_xlfn.XLOOKUP(J49,'DRY ITEM LIST'!D:D,'DRY ITEM LIST'!B:B,"")) -> Xtra - Bulk Tray - Pasta (Fasting)

Sheet DN10
A1: A/C TYPE | C1: STATION NAME | E1: DELIVERY NOTE | M1: DATE :
E2: FLIGHT NO | G2: DEPARTURE TIME | I2: FROM | K2: TO | M2: SALES #
A3: B787-900 | C3: ATL | E3: ET519 | G3: 0.45138889 | I3: ATL | K3: ADD | M3: ="ET"&TEXT(N1,"YYYYMMDD") -> ET19000100
D5: Reg Meal | E5: Special Meal
A6: Meal count | B6: Business class: | D6: 9 | E6: 00 KSML, 00 AVML
A7: Email | B7: Economy class: | D7: 119 | E7: 01 KSML, 01 VGML, 02 ALML
I9: LCH/DNR | L9: HCP /SWH | N9: HBF
A10: SERVICE | F10: FINAL ORDER | I10: 1st SVC/leg | L10: 2nd SVC/ leg | N10: 3rd SVC/leg
B11: PRELIMINARY ORDER | I11: SPML | J11: BC | K11: EY | L11: BC | M11: EY | N11: BC | O11: EY
B12: BC | C12: EY | D12: CR | E12: CP | F12: BC | G12: EY | I12: {=_xlfn.LET(_xlpm.vBC,_xlfn.TEXTSPLIT(E6," ",", "),_xlpm.vEY,_xlfn.TEXTSPLIT(E7," ",", "),_xlpm.vML,_xlfn.UNIQUE(_xlfn.VSTACK(INDEX(_xlpm.vBC,,2),INDEX(_xlpm.vEY,,2))), CHOOSE({1,2,3},_xlpm.vML,VALUE(_xlfn.XLOOKUP(_xlpm.vML,INDEX(_xlpm.vBC,,2),INDEX(_xlpm.vBC,,1),0)),VALUE(_xlfn.XLOOKUP(_xlpm.vML,INDEX(_xlpm.vEY,,2),INDEX(_xlpm.vEY,,1),0))))} -> KSML | J12: 0 | K12: 1 | L12: =J12 -> 0 | M12: =K12 -> 1 | N12: =J12 -> 0 | O12: =K12 -> 1
A13: HBF | B13: =$D$6 -> 9 | C13: =$D$7 -> 119 | D13: 12 | E13: 3 | F13: =SUM(B13,D13:E13) -> 24 | G13: =C13 -> 119 | I13: AVML | J13: 0 | K13: 0 | L13: =J13 -> 0 | M13: =K13 -> 0 | N13: =J13 -> 0 | O13: =K13 -> 0
A14: LCH/DNR | B14: =$D$6 -> 9 | C14: =$D$7 -> 119 | D14: 12 | E14: 3 | F14: =SUM(B14,D14:E14) -> 24 | G14: =C14 -> 119 | I14: VGML | J14: 0 | K14: 1 | L14: =J14 -> 0 | M14: =K14 -> 1 | N14: =J14 -> 0 | O14: =K14 -> 1
A15: HLM | B15: 0 | C15: 0 | F15: 0 | G15: 0 | I15: ALML | J15: 0 | K15: 2 | L15: =J15 -> 0 | M15: =K15 -> 2 | N15: =J15 -> 0 | O15: =K15 -> 2
A16: HCP | B16: =$D$6 -> 9 | C16: 0 | D16: 12 | E16: 3 | F16: =SUM(B16,D16:E16) -> 24 | G16: 0 | L16: =J16 -> 0 | M16: =K16 -> 0 | N16: =J16 -> 0 | O16: =K16 -> 0
A17: SWH | B17: 0 | C17: =$D$7 -> 119 | F17: 0 | G17: =C17 -> 119 | L17: =J17 -> 0 | M17: =K17 -> 0 | N17: =J17 -> 0 | O17: =K17 -> 0
A18: CCP | B18: 0 | C18: 0 | L18: =J18 -> 0 | M18: =K18 -> 0 | N18: =J18 -> 0 | O18: =K18 -> 0
A19: Eye opener | C19: 0 | L19: =J19 -> 0 | M19: =K19 -> 0 | N19: =J19 -> 0 | O19: =K19 -> 0
A20: Fasting Meals | L20: =J20 -> 0 | M20: =K20 -> 0 | N20: =J20 -> 0 | O20: =K20 -> 0
L21: =J21 -> 0 | M21: =K21 -> 0 | N21: =J21 -> 0 | O21: =K21 -> 0
L22: =J22 -> 0 | M22: =K22 -> 0 | N22: =J22 -> 0 | O22: =K22 -> 0
L23: =J23 -> 0 | M23: =K23 -> 0 | N23: =J23 -> 0 | O23: =K23 -> 0
L24: =J24 -> 0 | M24: =K24 -> 0 | N24: =J24 -> 0 | O24: =K24 -> 0
J25: =SUM(J12:J24) -> 0 | K25: =SUM(K12:K24) -> 4 | L25: =SUM(L12:L24) -> 0 | M25: =SUM(M12:M24) -> 4 | N25: =SUM(N12:N24) -> 0 | O25: =SUM(O12:O24) -> 4
A28: NO. | B28: DESCRIPTION | E28: PLAN | F28: AMOUNT | I28: DRY ITEM LIST
A29: 1 | B29: FRUIT BASKET | E29: 1 | F29: 1 | I29: NO. | J29: DESCRIPTION | M29: AMOUNT | N29: AMOUNT
A30: 2 | B30: CHEESE AND CRACKER | E30: 1 | F30: 1 | I30: 1 | J30: ORANGE JUICE | N30: 2 | O30: 3013505 - Juice Orange 1L
A31: 3 | B31: FRESH ORANGE JUICE | E31: 1 | F31: 2 | I31: 2 | J31: APPLE JUICE | O31: 3013506 - Juice Apple 1L
A32: 4 | B32: BREAD BASKET | E32: 1 | F32: 1 | I32: 3 | J32: PINEAPLE JUICE | O32: 3013504 - Juice Pineapple 1L
A33: 5 | B33: Standard Uplift | E33: 1 | F33: 1 | I33: 4 | J33: TOMATO JUICE | O33: 3013507 - Juice Tomato 1L
A34: 6 | B34: LAUNDRY SERVICE | E34: 0.5 | F34: 0.5 | I34: 5 | J34: MINERAL WATER 1.5 L | N34: 60 | O34: 3013499 - Mineral Water 1.5L
A35: 7 | B35: HANDLING CHARGES | E35: 1 | F35: 1 | I35: 6 | J35: MINERAL WATER 0.5 L | O35: 3013498 - Mineral Water 330mL
A36: 8 | B36: EXTRA VAN CHARGE | E36: 1 | F36: 1 | I36: 7 | J36: COCA COLA BOTTLE 1.5 L
A37: 9 | I37: 8 | J37: COCA COLA CAN | N37: 24 | O37: 3013495 - Coke 355mL
A38: 10 | I38: 9 | J38: SPRIT BOTTLE 1.5 L | O38: =IF(J38="","",_xlfn.XLOOKUP(J38,'DRY ITEM LIST'!D:D,'DRY ITEM LIST'!B:B,""))
A39: 11 | I39: 10 | J39: SPRIT CAN | O39: 3013497 - Sprite 355mL
A40: 12 | I40: 11 | J40: Wet Ice 5kg Bag | O40: 3013522 - Wet Ice 5kg Bag
A41: 13 | I41: 12 | J41: Water 1.5 L
A42: 14 | I42: 13 | J42: Water 0.5 L
A43: 15 | I43: 14 | J43: Fruit Platters | N43: =29/3 -> 9.6666667 | O43: =IF(J43="","",_xlfn.XLOOKUP(J43,'DRY ITEM LIST'!D:D,'DRY ITEM LIST'!B:B,"")) -> 3013538 - Fruit Platters
I44: 15 | J44: Coke Light 355mL | N44: 24 | O44: =IF(J44="","",_xlfn.XLOOKUP(J44,'DRY ITEM LIST'!D:D,'DRY ITEM LIST'!B:B,"")) -> 3013496 - Coke Light 355mL
I45: 16 | J45: Ginger Ale 355mL | N45: 24 | O45: =IF(J45="","",_xlfn.XLOOKUP(J45,'DRY ITEM LIST'!D:D,'DRY ITEM LIST'!B:B,"")) -> 3013540 - Ginger Ale 355mL
I46: 17 | O46: =IF(J46="","",_xlfn.XLOOKUP(J46,'DRY ITEM LIST'!D:D,'DRY ITEM LIST'!B:B,""))
I47: 18 | O47: =IF(J47="","",_xlfn.XLOOKUP(J47,'DRY ITEM LIST'!D:D,'DRY ITEM LIST'!B:B,""))
I48: 19 | O48: =IF(J48="","",_xlfn.XLOOKUP(J48,'DRY ITEM LIST'!D:D,'DRY ITEM LIST'!B:B,""))
I49: 20 | O49: =IF(J49="","",_xlfn.XLOOKUP(J49,'DRY ITEM LIST'!D:D,'DRY ITEM LIST'!B:B,""))

Sheet DN12
A1: A/C TYPE | C1: STATION NAME | E1: DELIVERY NOTE | M1: DATE :
E2: FLIGHT NO | G2: DEPARTURE TIME | I2: FROM | K2: TO | M2: SALES #
A3: B787-900 | C3: ATL | E3: ET519 | G3: 0.45138889 | I3: ATL | K3: ADD | M3: ="ET"&TEXT(N1,"YYYYMMDD") -> ET19000100
D5: Reg Meal | E5: Special Meal
A6: Meal count | B6: Business class: | D6: 3 | E6: 05 KSML, 02 AVML
A7: Email | B7: Economy class: | D7: 92 | E7: 01 AVML, 02 MOML, 01 VGML, 01 VLML, 01 CHML, 01 BBML, 03 KSML
I9: LCH/DNR | L9: HCP /SWH | N9: HBF
A10: SERVICE | F10: FINAL ORDER | I10: 1st SVC/leg | L10: 2nd SVC/ leg | N10: 3rd SVC/leg
B11: PRELIMINARY ORDER | I11: SPML | J11: BC | K11: EY | L11: BC | M11: EY | N11: BC | O11: EY
B12: BC | C12: EY | D12: CR | E12: CP | F12: BC | G12: EY | I12: {=_xlfn.LET(_xlpm.vBC,_xlfn.TEXTSPLIT(E6," ",", "),_xlpm.vEY,_xlfn.TEXTSPLIT(E7," ",", "),_xlpm.vML,_xlfn.UNIQUE(_xlfn.VSTACK(INDEX(_xlpm.vBC,,2),INDEX(_xlpm.vEY,,2))), CHOOSE({1,2,3},_xlpm.vML,VALUE(_xlfn.XLOOKUP(_xlpm.vML,INDEX(_xlpm.vBC,,2),INDEX(_xlpm.vBC,,1),0)),VALUE(_xlfn.XLOOKUP(_xlpm.vML,INDEX(_xlpm.vEY,,2),INDEX(_xlpm.vEY,,1),0))))} -> KSML | J12: 5 | K12: 3 | L12: =J12 -> 5 | M12: =K12 -> 3 | N12: =J12 -> 5 | O12: =K12 -> 3
A13: HBF | B13: =$D$6 -> 3 | C13: =$D$7 -> 92 | D13: 12 | E13: 3 | F13: =SUM(B13,D13:E13) -> 18 | G13: =C13 -> 92 | I13: AVML | J13: 2 | K13: 1 | L13: =J13 -> 2 | M13: =K13 -> 1 | N13: =J13 -> 2 | O13: =K13 -> 1
A14: LCH/DNR | B14: =$D$6 -> 3 | C14: =$D$7 -> 92 | D14: 12 | E14: 3 | F14: =SUM(B14,D14:E14) -> 18 | G14: =C14 -> 92 | I14: MOML | J14: 0 | K14: 2 | L14: =J14 -> 0 | M14: =K14 -> 2 | N14: =J14 -> 0 | O14: =K14 -> 2
A15: HLM | B15: 0 | C15: 0 | F15: 0 | G15: 0 | I15: VGML | J15: 0 | K15: 1 | L15: =J15 -> 0 | M15: =K15 -> 1 | N15: =J15 -> 0 | O15: =K15 -> 1
A16: HCP | B16: =$D$6 -> 3 | C16: 0 | D16: 12 | E16: 3 | F16: =SUM(B16,D16:E16) -> 18 | G16: 0 | I16: VLML | J16: 0 | K16: 1 | L16: =J16 -> 0 | M16: =K16 -> 1 | N16: =J16 -> 0 | O16: =K16 -> 1
A17: SWH | B17: 0 | C17: =$D$7 -> 92 | F17: 0 | G17: =C17 -> 92 | I17: CHML | J17: 0 | K17: 1 | L17: =J17 -> 0 | M17: =K17 -> 1 | N17: =J17 -> 0 | O17: =K17 -> 1
A18: CCP | B18: 0 | C18: 0 | I18: BBML | J18: 0 | K18: 1 | L18: =J18 -> 0 | M18: =K18 -> 1 | N18: =J18 -> 0 | O18: =K18 -> 1
A19: Eye opener | C19: 0 | L19: =J19 -> 0 | M19: =K19 -> 0 | N19: =J19 -> 0 | O19: =K19 -> 0
A20: Fasting Meals | L20: =J20 -> 0 | M20: =K20 -> 0 | N20: =J20 -> 0 | O20: =K20 -> 0
L21: =J21 -> 0 | M21: =K21 -> 0 | N21: =J21 -> 0 | O21: =K21 -> 0
L22: =J22 -> 0 | M22: =K22 -> 0 | N22: =J22 -> 0 | O22: =K22 -> 0
L23: =J23 -> 0 | M23: =K23 -> 0 | N23: =J23 -> 0 | O23: =K23 -> 0
L24: =J24 -> 0 | M24: =K24 -> 0 | N24: =J24 -> 0 | O24: =K24 -> 0
J25: =SUM(J12:J24) -> 7 | K25: =SUM(K12:K24) -> 10 | L25: =SUM(L12:L24) -> 7 | M25: =SUM(M12:M24) -> 10 | N25: =SUM(N12:N24) -> 7 | O25: =SUM(O12:O24) -> 10
A28: NO. | B28: DESCRIPTION | E28: PLAN | F28: AMOUNT | I28: DRY ITEM LIST
A29: 1 | B29: FRUIT BASKET | E29: 1 | F29: 1 | I29: NO. | J29: DESCRIPTION | M29: AMOUNT | N29: AMOUNT
A30: 2 | B30: CHEESE AND CRACKER | E30: 1 | F30: 1 | I30: 1 | J30: ORANGE JUICE | N30: 2 | O30: 3013505 - Juice Orange 1L
A31: 3 | B31: FRESH ORANGE JUICE | E31: 1 | F31: 1 | I31: 2 | J31: APPLE JUICE | O31: 3013506 - Juice Apple 1L
A32: 4 | B32: BREAD BASKET | E32: 1 | F32: 1 | I32: 3 | J32: PINEAPLE JUICE | O32: 3013504 - Juice Pineapple 1L
A33: 5 | B33: Standard Uplift | E33: 1 | F33: 1 | I33: 4 | J33: TOMATO JUICE | O33: 3013507 - Juice Tomato 1L
A34: 6 | B34: LAUNDRY SERVICE | E34: 0.5 | F34: 0.5 | I34: 5 | J34: MINERAL WATER 1.5 L | O34: 3013499 - Mineral Water 1.5L
A35: 7 | B35: HANDLING CHARGES | E35: 1 | F35: 1 | I35: 6 | J35: MINERAL WATER 0.5 L | O35: 3013498 - Mineral Water 330mL
A36: 8 | B36: EXTRA VAN CHARGE | E36: 1 | F36: 1 | I36: 7 | J36: COCA COLA BOTTLE 1.5 L
A37: 9 | B37: FRUIT PLATTERS | F37: 30 | I37: 8 | J37: COCA COLA CAN | O37: 3013495 - Coke 355mL
A38: 10 | I38: 9 | J38: SPRIT BOTTLE 1.5 L | O38: =IF(J38="","",_xlfn.XLOOKUP(J38,'DRY ITEM LIST'!D:D,'DRY ITEM LIST'!B:B,""))
A39: 11 | I39: 10 | J39: SPRIT CAN | O39: 3013497 - Sprite 355mL
A40: 12 | I40: 11 | J40: Wet Ice 5kg Bag | O40: 3013522 - Wet Ice 5kg Bag
A41: 13 | I41: 12 | J41: Water 1.5 L
A42: 14 | I42: 13 | J42: Water 0.5 L
A43: 15 | I43: 14 | O43: =IF(J43="","",_xlfn.XLOOKUP(J43,'DRY ITEM LIST'!D:D,'DRY ITEM LIST'!B:B,""))
I44: 15 | O44: =IF(J44="","",_xlfn.XLOOKUP(J44,'DRY ITEM LIST'!D:D,'DRY ITEM LIST'!B:B,""))
I45: 16 | O45: =IF(J45="","",_xlfn.XLOOKUP(J45,'DRY ITEM LIST'!D:D,'DRY ITEM LIST'!B:B,""))
I46: 17 | O46: =IF(J46="","",_xlfn.XLOOKUP(J46,'DRY ITEM LIST'!D:D,'DRY ITEM LIST'!B:B,""))
I47: 18 | O47: =IF(J47="","",_xlfn.XLOOKUP(J47,'DRY ITEM LIST'!D:D,'DRY ITEM LIST'!B:B,""))
I48: 19 | O48: =IF(J48="","",_xlfn.XLOOKUP(J48,'DRY ITEM LIST'!D:D,'DRY ITEM LIST'!B:B,""))
I49: 20 | O49: =IF(J49="","",_xlfn.XLOOKUP(J49,'DRY ITEM LIST'!D:D,'DRY ITEM LIST'!B:B,""))

Sheet DN13
A1: A/C TYPE | C1: STATION NAME | E1: DELIVERY NOTE | M1: DATE :
E2: FLIGHT NO | G2: DEPARTURE TIME | I2: FROM | K2: TO | M2: SALES #
A3: B787-900 | C3: ATL | E3: ET519 | G3: 0.45138889 | I3: ATL | K3: ADD | M3: ="ET"&TEXT(N1,"YYYYMMDD") -> ET19000100
D5: Reg Meal | E5: Special Meal
A6: Meal count | B6: Business class: | D6: 3 | E6: 05 KSML, 02 AVML
A7: Email | B7: Economy class: | D7: 92 | E7: 01 AVML, 02 MOML, 01 VGML, 01 VLML, 01 CHML, 01 BBML, 03 KSML
I9: LCH/DNR | L9: HCP /SWH | N9: HBF
A10: SERVICE | F10: FINAL ORDER | I10: 1st SVC/leg | L10: 2nd SVC/ leg | N10: 3rd SVC/leg
B11: PRELIMINARY ORDER | I11: SPML | J11: BC | K11: EY | L11: BC | M11: EY | N11: BC | O11: EY
B12: BC | C12: EY | D12: CR | E12: CP | F12: BC | G12: EY | I12: {=_xlfn.LET(_xlpm.vBC,_xlfn.TEXTSPLIT(E6," ",", "),_xlpm.vEY,_xlfn.TEXTSPLIT(E7," ",", "),_xlpm.vML,_xlfn.UNIQUE(_xlfn.VSTACK(INDEX(_xlpm.vBC,,2),INDEX(_xlpm.vEY,,2))), CHOOSE({1,2,3},_xlpm.vML,VALUE(_xlfn.XLOOKUP(_xlpm.vML,INDEX(_xlpm.vBC,,2),INDEX(_xlpm.vBC,,1),0)),VALUE(_xlfn.XLOOKUP(_xlpm.vML,INDEX(_xlpm.vEY,,2),INDEX(_xlpm.vEY,,1),0))))} -> KSML | J12: 5 | K12: 3 | L12: =J12 -> 5 | M12: =K12 -> 3 | N12: =J12 -> 5 | O12: =K12 -> 3
A13: HBF | B13: =$D$6 -> 3 | C13: =$D$7 -> 92 | D13: 12 | E13: 3 | F13: =SUM(B13,D13:E13) -> 18 | G13: =C13 -> 92 | I13: AVML | J13: 2 | K13: 1 | L13: =J13 -> 2 | M13: =K13 -> 1 | N13: =J13 -> 2 | O13: =K13 -> 1
A14: LCH/DNR | B14: =$D$6 -> 3 | C14: =$D$7 -> 92 | D14: 12 | E14: 3 | F14: =SUM(B14,D14:E14) -> 18 | G14: =C14 -> 92 | I14: MOML | J14: 0 | K14: 2 | L14: =J14 -> 0 | M14: =K14 -> 2 | N14: =J14 -> 0 | O14: =K14 -> 2
A15: HLM | B15: 0 | C15: 0 | F15: 0 | G15: 0 | I15: VGML | J15: 0 | K15: 1 | L15: =J15 -> 0 | M15: =K15 -> 1 | N15: =J15 -> 0 | O15: =K15 -> 1
A16: HCP | B16: =$D$6 -> 3 | C16: 0 | D16: 12 | E16: 3 | F16: =SUM(B16,D16:E16) -> 18 | G16: 0 | I16: VLML | J16: 0 | K16: 1 | L16: =J16 -> 0 | M16: =K16 -> 1 | N16: =J16 -> 0 | O16: =K16 -> 1
A17: SWH | B17: 0 | C17: =$D$7 -> 92 | F17: 0 | G17: =C17 -> 92 | I17: CHML | J17: 0 | K17: 1 | L17: =J17 -> 0 | M17: =K17 -> 1 | N17: =J17 -> 0 | O17: =K17 -> 1
A18: CCP | B18: 0 | C18: 0 | I18: BBML | J18: 0 | K18: 1 | L18: =J18 -> 0 | M18: =K18 -> 1 | N18: =J18 -> 0 | O18: =K18 -> 1
A19: Eye opener | C19: 0 | L19: =J19 -> 0 | M19: =K19 -> 0 | N19: =J19 -> 0 | O19: =K19 -> 0
A20: Fasting Meals | L20: =J20 -> 0 | M20: =K20 -> 0 | N20: =J20 -> 0 | O20: =K20 -> 0
L21: =J21 -> 0 | M21: =K21 -> 0 | N21: =J21 -> 0 | O21: =K21 -> 0
L22: =J22 -> 0 | M22: =K22 -> 0 | N22: =J22 -> 0 | O22: =K22 -> 0
L23: =J23 -> 0 | M23: =K23 -> 0 | N23: =J23 -> 0 | O23: =K23 -> 0
L24: =J24 -> 0 | M24: =K24 -> 0 | N24: =J24 -> 0 | O24: =K24 -> 0
J25: =SUM(J12:J24) -> 7 | K25: =SUM(K12:K24) -> 10 | L25: =SUM(L12:L24) -> 7 | M25: =SUM(M12:M24) -> 10 | N25: =SUM(N12:N24) -> 7 | O25: =SUM(O12:O24) -> 10
A28: NO. | B28: DESCRIPTION | E28: PLAN | F28: AMOUNT | I28: DRY ITEM LIST
A29: 1 | B29: FRUIT BASKET | E29: 1 | F29: 1 | I29: NO. | J29: DESCRIPTION | M29: AMOUNT | N29: AMOUNT
A30: 2 | B30: CHEESE AND CRACKER | E30: 1 | F30: 1 | I30: 1 | J30: ORANGE JUICE | N30: 2 | O30: 3013505 - Juice Orange 1L
A31: 3 | B31: FRESH ORANGE JUICE | E31: 1 | F31: 1 | I31: 2 | J31: APPLE JUICE | O31: 3013506 - Juice Apple 1L
A32: 4 | B32: BREAD BASKET | E32: 1 | F32: 1 | I32: 3 | J32: PINEAPLE JUICE | O32: 3013504 - Juice Pineapple 1L
A33: 5 | B33: Standard Uplift | E33: 1 | F33: 1 | I33: 4 | J33: TOMATO JUICE | O33: 3013507 - Juice Tomato 1L
A34: 6 | B34: LAUNDRY SERVICE | E34: 0.5 | F34: 0.5 | I34: 5 | J34: MINERAL WATER 1.5 L | O34: 3013499 - Mineral Water 1.5L
A35: 7 | B35: HANDLING CHARGES | E35: 1 | F35: 1 | I35: 6 | J35: MINERAL WATER 0.5 L | O35: 3013498 - Mineral Water 330mL
A36: 8 | B36: EXTRA VAN CHARGE | E36: 1 | F36: 1 | I36: 7 | J36: COCA COLA BOTTLE 1.5 L
A37: 9 | B37: FRUIT PLATTERS | F37: 30 | I37: 8 | J37: COCA COLA CAN | O37: 3013495 - Coke 355mL
A38: 10 | I38: 9 | J38: SPRIT BOTTLE 1.5 L | O38: =IF(J38="","",_xlfn.XLOOKUP(J38,'DRY ITEM LIST'!D:D,'DRY ITEM LIST'!B:B,""))
A39: 11 | I39: 10 | J39: SPRIT CAN | O39: 3013497 - Sprite 355mL
A40: 12 | I40: 11 | J40: Wet Ice 5kg Bag | O40: 3013522 - Wet Ice 5kg Bag
A41: 13 | I41: 12 | J41: Water 1.5 L
A42: 14 | I42: 13 | J42: Water 0.5 L
A43: 15 | I43: 14 | O43: =IF(J43="","",_xlfn.XLOOKUP(J43,'DRY ITEM LIST'!D:D,'DRY ITEM LIST'!B:B,""))
I44: 15 | O44: =IF(J44="","",_xlfn.XLOOKUP(J44,'DRY ITEM LIST'!D:D,'DRY ITEM LIST'!B:B,""))
I45: 16 | O45: =IF(J45="","",_xlfn.XLOOKUP(J45,'DRY ITEM LIST'!D:D,'DRY ITEM LIST'!B:B,""))
I46: 17 | O46: =IF(J46="","",_xlfn.XLOOKUP(J46,'DRY ITEM LIST'!D:D,'DRY ITEM LIST'!B:B,""))
I47: 18 | O47: =IF(J47="","",_xlfn.XLOOKUP(J47,'DRY ITEM LIST'!D:D,'DRY ITEM LIST'!B:B,""))
I48: 19 | O48: =IF(J48="","",_xlfn.XLOOKUP(J48,'DRY ITEM LIST'!D:D,'DRY ITEM LIST'!B:B,""))
I49: 20 | O49: =IF(J49="","",_xlfn.XLOOKUP(J49,'DRY ITEM LIST'!D:D,'DRY ITEM LIST'!B:B,""))

Sheet New Cycle change
C1: JANUARY | D1: FEBUARY | E1: MARCH | F1: APRIL | G1: MAY | H1: JUNE | I1: JULY | J1: AUGUST | K1: SEPTEMBER | L1: OCTOBER | M1: NOVEMBER | N1: DECEMBER
A2: VIRGIN ATLANTIC CREW MENU | C2: CYLCE 2 (2025) | G2: CYCLE1 | M2: CYCLE 2
C3: JAN 1 , JAN 8 CHANGES | G3: 6-May | M3: 5-Nov
B4: Notes: | C4: JAN1 - J/W SANDWICH/YOGURT CHANGE , J CRABCAKE CHANGE, JAN8 - WATER BOTTLES OF TSU W/Y | M4: xmas menu 22-26
C5: ROTATION 1 | D5: ROTATION 2 | G5: ROTATION 1 | J5: ROTATION 2 | M5: ROTATION 1
D6: 4-Feb | G6: 6-May | J6: 8/52025 | M6: 4-Nov
B7: Notes: | D7: STARTERS /DESSERT J
C8: CREW MENU 1 | D8: CREW MENU 2 | G8: CREW MENU 1 | J8: CREW MENU 2 | M8: CREW MENU 1
D9: 4-Feb | G9: 6-May | J9: 5-Aug | M9: 4-Nov
B10: Notes:
A11: ETHIOPAN | C11: CYCLE 1 | E11: CYCLE 2 | G11: CYCLE 3 | I11: CYCLE 1 | K11: CYCLE 2 | M11: CYCLE 3
C12: 2-Jan | E12: 1-Mar | G12: 1-May | I12: 1-Jul | K12: 2-Sep | M12: 1-Nov
B13: Notes:
A14: SCANDINAVIAN | C14: CYCLE 3 | D14: CYCLE 1 SPRING | H14: CYCLE 2 | L14: CYCLE 3
D15: 1-Feb | H15: 1-Jun | L15: 1-Oct
B16: Notes:
A17: AMERICAN AIRLINES - ATL | C17: CYCLE 1 | D17: CYCLE 2 | E17: CYCLE 3 | F17: CYCLE 4 | G17: CYCLE 1 | H17: CYCLE 2 | I17: CYCLE 3 | J17: CYCLE 4 | K17: CYCLE 1 | L17: CYCLE 2 | M17: CYCLE 3 | N17: CYCLE 4
C18: 7-Jan | D18: 4-Feb | E18: 11-Mar | F18: 8-Apr | G18: 13-May | H18: 10-Jun | I18: 8-Jul | J18: 12-Aug | K18: 9-Sep | L18: 14-Oct | M18: 11-Nov | N18: 9-Dec
B19: Notes:
A21: Cycle change/Rotation
A23: JAN & FEB…..CYCLE 1
A24: MAR & APR…CYCL 2
A25: MAY & JUN…CYCLE 3
A26: JUL & AUG….CYCLE 1
A27: SEP & OCT….CYCLE 2
A28: NOV & DEC…CYCLE 3
A33: Per Sue, snack was added into Dinner and breakfast prize so don't add the snack in the billing
A34: LCH/DNR | D34: HCP /SWH | F34: HBF
A35: 1st SVC/leg | D35: 2nd SVC/ leg | F35: 3rd SVC/leg
A36: SPML | B36: BC | C36: EY | D36: BC | E36: EY | F36: BC | G36: EY
A37: GFML | B37: 2 | C37: 0 | D37: 2 | E37: 0 | F37: 2 | G37: 0
A38: SPML | B38: 0 | C38: 3 | D38: 0 | E38: 3 | F38: 0 | G38: 3
A39: LCML | B39: 0 | C39: 1 | D39: 0 | E39: 1 | F39: 0 | G39: 1
A40: AVML | B40: 0 | C40: 3 | D40: 0 | E40: 3 | F40: 0 | G40: 3
A41: FPML | B41: 0 | C41: 1 | D41: 0 | E41: 1 | F41: 0 | G41: 1
A42: MOML | B42: 0 | C42: 3 | D42: 0 | E42: 3 | F42: 0 | G42: 3
A43: DBML | B43: 0 | C43: 1 | D43: 0 | E43: 1 | F43: 0 | G43: 1
A44: AVML BBML | B44: 0 | C44: 1 | D44: 0 | E44: 1 | F44: 0 | G44: 1
A45: MOML BBML | B45: 0 | C45: 1 | D45: 0 | E45: 1 | F45: 0 | G45: 1
D46: 0 | E46: 0 | F46: 0 | G46: 0
D47: 0 | E47: 0 | F47: 0 | G47: 0
D48: 0 | E48: 0 | F48: 0 | G48: 0
D49: 0 | E49: 0 | F49: 0 | G49: 0
B50: 2 | C50: 14 | D50: 2 | E50: 14 | F50: 2 | G50: 14

Sheet ET Standar Price List
D1: ET'S STANDARD PRICE LIST
C3: LCH-DNR | F3: CYCLE ONE | I3: CYCLE TWO | L3: CYCLE THREE
C4: DESCRIPTION | D4: LCH/DNR | E4: %AGE | F4: Each Item PRICE /local Currency | G4: Price per pax by LOCAL CURRENCY | I4: Each Item PRICE /local Currency | J4: Price per pax by LOCAL CURRENCY | L4: Each Item PRICE /local Currency | M4: Price per pax by LOCAL CURRENCY
E5: %age
A7: 1 | C7: CYC 1 BC LCH/DNR | D7: Appetizer Non-Veg | E7: 0.9 | F7: 4.064745 | G7: =F7*E7 -> 3.6582705 | I7: 3.2444692 | J7: =I7*E7 -> 2.9200223 | L7: 3.8998096 | M7: =L7*E7 -> 3.5098286
A8: =A7+1 -> 2 | D8: Appetizer Veg | E8: 0.1 | F8: 2.8938179 | G8: =F8*E8 -> 0.28938179 | I8: 2.0445978 | J8: =I8*E8 -> 0.20445978 | L8: 2.4911894 | M8: =L8*E8 -> 0.24911894
A9: =A8+1 -> 3 | D9: Butter portion | E9: 1 | F9: 0.66 | G9: =F9*E9 -> 0.66 | I9: 0.66 | J9: =I9*E9 -> 0.66 | L9: 0.66 | M9: =L9*E9 -> 0.66
A10: =A9+1 -> 4 | D10: Salad & Salad dressing | E10: 1 | F10: 2.575 | G10: =F10*E10 -> 2.575 | I10: 3.96825 | J10: =I10*E10 -> 3.96825 | L10: 2.82725 | M10: =L10*E10 -> 2.82725
A11: =A10+1 -> 5 | D11: Entrée
A12: =A11+1 -> 6 | C12: Fish | D12: Choice #1 | E12: 0.15 | F12: 14.370861 | G12: =F12*E12 -> 2.1556291 | I12: 19.834768 | J12: =I12*E12 -> 2.9752152 | L12: 14.076159 | M12: =L12*E12 -> 2.1114238
A13: =A12+1 -> 7 | C13: Beef | D13: Choice #2 | E13: 0.25 | F13: 17.652517 | G13: =F13*E13 -> 4.4131291 | I13: 20.462914 | J13: =I13*E13 -> 5.1157285 | L13: 19.19846 | M13: =L13*E13 -> 4.7996151
A14: =A13+1 -> 8 | C14: Chicken | D14: Choice #3 | E14: 0.5 | F14: 7.8422185 | G14: =F14*E14 -> 3.9211093 | I14: 9.2376656 | J14: =I14*E14 -> 4.6188328 | L14: 8.5738411 | M14: =L14*E14 -> 4.2869205
A15: =A14+1 -> 9 | C15: veg | D15: Choice #4 | E15: 0.1 | F15: 6.7496109 | G15: =F15*E15 -> 0.67496109 | I15: 6.7496109 | J15: =I15*E15 -> 0.67496109 | L15: 10.166394 | M15: =L15*E15 -> 1.0166394
A16: =A15+1 -> 10
A17: =A16+1 -> 11 | D17: Dessert #1 | E17: 0.5 | F17: 3.7125 | G17: =F17*E17 -> 1.85625 | I17: 4.5908526 | J17: =I17*E17 -> 2.2954263 | L17: 4.263452 | M17: =L17*E17 -> 2.131726
A18: =A17+1 -> 12 | D18: Dessert #2 | E18: 0.5 | F18: 2.6980132 | G18: =F18*E18 -> 1.3490066 | I18: 3.9346026 | J18: =I18*E18 -> 1.9673013 | L18: 3.195 | M18: =L18*E18 -> 1.5975
A19: =A18+1 -> 13 | D19: ICE CREAM | E19: 1 | F19: 4.1 | G19: =F19*E19 -> 4.1 | I19: 4.1 | J19: =I19*E19 -> 4.1 | L19: 4.1 | M19: =L19*E19 -> 4.1
A20: =A18+1 -> 13 | D20: Bakery Selection | E20: 1.5 | F20: 1.35 | G20: =F20*E20 -> 2.025 | I20: 1.35 | J20: =I20*E20 -> 2.025 | L20: 1.35 | M20: =L20*E20 -> 2.025
A21: =A20+1 -> 14 | D21: BC LCH/DNR Price per passenger Total | F21: 29.936192 | G21: =SUM(G7:G20) -> 27.677738 | J21: =SUM(J7:J20) -> 31.525197 | M21: =SUM(M7:M20) -> 29.315022
A22: =A21+1 -> 15
A23: =A22+1 -> 16 | C23: (BULK ITEM) | D23: Fruit Platter (STD ) =18 pieces | E23: (STD ) =18 pieces | F23: 16.605 | G23: =F23 -> 16.605 | I23: 16.605 | J23: =G23 -> 16.605 | L23: 16.605 | M23: =G23 -> 16.605
A24: =A23+1 -> 17 | C24: (BULK ITEM) | D24: 1L Fresh OJ (1-8) | E24: 1std=2LT | F24: 6.53 | G24: =F24 -> 6.53 | I24: 6.53 | J24: =G24 -> 6.53 | L24: 6.53 | M24: =G24 -> 6.53
A25: =A24+1 -> 18 | C25: (BULK ITEM) | D25: Garlic Bread 1 OF 10 PCS | E25: 1std= 10 PCS | F25: 6.75 | G25: =F25 -> 6.75 | I25: 6.75 | J25: =I25 -> 6.75 | L25: 6.75 | M25: =L25 -> 6.75
A26: =A25+1 -> 19 | C26: (BULK ITEM) | D26: FRESH MILK | E26: 1std= 2LT | F26: 5.85 | G26: =F26 -> 5.85 | I26: 5.85 | J26: =I26 -> 5.85 | L26: 5.85 | M26: =L26 -> 5.85
A27: =A26+1 -> 20 | C27: (BULK ITEM) | D27: CONDIMENTS AND CHOCOLATE | E27: STD | F27: 1.8 | G27: =F27 -> 1.8 | I27: 1.8 | J27: =I27 -> 1.8 | L27: 1.8 | M27: =L27 -> 1.8
A28: =A27+1 -> 21 | D28: Cheese Tray | E28: 1std=16pax | F28: 26.941556 | G28: =F28 -> 26.941556 | I28: 26.941556 | J28: =I28 -> 26.941556 | L28: 26.941556 | M28: =L28 -> 26.941556
A29: =A28+1 -> 22
A30: =A29+1 -> 23 | C30: CYC 1 EY LCH/DNR | D30: Salad and salad dressing | E30: 1 | F30: 2.22 | G30: =F30*E30 -> 2.22 | I30: 1.7545 | J30: =I30*E30 -> 1.7545 | L30: 2.183 | M30: =L30*E30 -> 2.183
A31: =A30+1 -> 24 | D31: Choice #1 | E31: 0.3 | F31: 7.8135762 | G31: =F31*E31 -> 2.3440728 | I31: 7.9399007 | J31: =I31*E31 -> 2.3819702 | L31: 6.0607119 | M31: =L31*E31 -> 1.8182136
A32: =A31+1 -> 25 | D32: Choice #2 | E32: 0.2 | F32: 7.2850993 | G32: =F32*E32 -> 1.4570199 | I32: 7.3246093 | J32: =I32*E32 -> 1.4649219 | L32: 7.9304901 | M32: =L32*E32 -> 1.586098
A33: =A32+1 -> 26 | D33: Choice #3 | E33: 0.5 | F33: 5.7933775 | G33: =F33*E33 -> 2.8966887 | I33: 6.2622517 | J33: =I33*E33 -> 3.1311258 | L33: 5.1051656 | M33: =L33*E33 -> 2.5525828
A34: =A33+1 -> 27 | D34: Choice #4 | E34: 3 pcs | F34: 6.2415894 | G34: =F34*0.03 -> 0.18724768 | I34: 4.634106 | J34: =I34*0.03 -> 0.13902318 | L34: 7.0696192 | M34: =L34*0.03 -> 0.21208858
A35: =A34+1 -> 28 | D35: Dessert | E35: 1 | F35: 3.13125 | G35: =F35*E35 -> 3.13125 | I35: 3.080855 | J35: =I35*E35 -> 3.080855 | L35: 2.8443758 | M35: =L35*E35 -> 2.8443758
A36: =A35+1 -> 29 | D36: WHITE BREAD ROLLS | E36: 1 | F36: 0.915 | G36: =F36*E36 -> 0.915 | I36: 0.915 | J36: =I36*E36 -> 0.915 | L36: 0.915 | M36: =L36*E36 -> 0.915
A37: =A36+1 -> 30 | D37: BUTER PORTION | E37: 1 | F37: 0.26 | G37: =F37*E37 -> 0.26 | I37: 0.26 | J37: =I37*E37 -> 0.26 | L37: 0.26 | M37: =L37*E37 -> 0.26
A38: =A37+1 -> 31 | D38: CHEESE PORTION | E38: 1 | F38: 1.635 | G38: =F38*E38 -> 1.635 | I38: 1.635 | J38: =I38*E38 -> 1.635 | L38: 1.635 | M38: =L38*E38 -> 1.635
A39: =A38+1 -> 32 | D39: CRAKERS PORTION | E39: 1 | F39: 0.375 | G39: =F39*E39 -> 0.375 | I39: 0.375 | J39: =I39*E39 -> 0.375 | L39: 0.375 | M39: =L39*E39 -> 0.375
A40: =A39+1 -> 33 | D40: EY LCH/DNR Price per passenger Total | G40: =SUM(G30:G39) -> 15.421279 | J40: =SUM(J30:J39) -> 15.137396 | M40: =SUM(M30:M39) -> 14.381359
A41: =A40+1 -> 34
A42: =A41+1 -> 35 | C42: Item for All Cycles
A43: =A42+1 -> 36 | C43: STANDARD UP LIFT | D43: Ice Cube | E43: 5 KG | F43: 5.5 | G43: =F43 -> 5.5 | I43: 5.5 | J43: =I43 -> 5.5 | L43: 5.5 | M43: =L43 -> 5.5
A44: =A43+1 -> 37 | D44: Lemon Slices | E44: 8 Slice | F44: 1.35 | G44: =F44 -> 1.35 | I44: 1.35 | J44: =I44 -> 1.35 | L44: 1.35 | M44: =L44 -> 1.35
A45: =A44+1 -> 38 | D45: Milk | E45: 3 Ltr | F45: 8.77 | G45: =F45 -> 8.77 | I45: 8.77 | J45: =I45 -> 8.77 | L45: 8.77 | M45: =L45 -> 8.77
A46: =A45+1 -> 39 | D46: Standard Uplift Total Price | G46: =G43+G44+G45 -> 15.62 | J46: =J43+J44+J45 -> 15.62 | M46: =M43+M44+M45 -> 15.62
A47: =A46+1 -> 40
A48: =A47+1 -> 41 | C48: ALL IATA BC SPML (NO KSML) : LCH/DNR | D48: ALL IATA BC SPML (NO KSML) | F48: 29.87 | G48: =F48 -> 29.87 | I48: 25.34 | J48: =I48 -> 25.34 | L48: 25.34 | M48: =L48 -> 25.34
A49: =A48+1 -> 42 | C49: ALL IATA EY SPML (NO KSML) LCH/DNR | D49: ALL IATA EY SPML (NO KSML) | F49: 15.68 | G49: =F49 -> 15.68 | I49: 15.68 | J49: =I49 -> 15.68 | L49: 15.68 | M49: =L49 -> 15.68
A50: =A49+1 -> 43 | C50: KSML BC LCH/DNR | D50: KSML BC LCH/DNR | F50: 50 | G50: =F50 -> 50 | I50: 50 | J50: =I50 -> 50 | L50: 50 | M50: =L50 -> 50
A51: =A50+1 -> 44 | C51: KSML EY LCH/DNR | D51: KSML EY LCH/DNR | F51: 45 | G51: =F51 -> 45 | I51: 45 | J51: =I51 -> 45 | L51: 45 | M51: =L51 -> 45
A52: =A51+1 -> 45 | C52: ALL IATA BC SPML (NO KSML) : HBF | D52: ALL IATA BC SPML (NO KSML) HBF | F52: 19.98 | G52: =F52 -> 19.98 | I52: 19.98 | J52: =I52 -> 19.98 | L52: 19.98 | M52: =L52 -> 19.98
A53: =A52+1 -> 46 | C53: ALL IATA EY SPML (NO KSML) HBF | D53: ALL IATA EY SPML (NO KSML) HBF | F53: 11.35 | G53: =F53 -> 11.35 | I53: 11.35 | J53: =I53 -> 11.35 | L53: 11.35 | M53: =L53 -> 11.35
A54: =A53+1 -> 47 | C54: KSML BC HBF | D54: KSML BC HBF | F54: 45 | G54: =F54 -> 45 | I54: 45 | J54: =I54 -> 45 | L54: 45 | M54: =L54 -> 45
A55: =A54+1 -> 48 | C55: KSML EY HBF | D55: KSML EY HBF | F55: 28 | G55: =F55 -> 28 | I55: 28 | J55: =I55 -> 28 | L55: 28 | M55: =L55 -> 28
A56: =A51+1 -> 45 | C56: Handling charges Per A/C - Turnaround 1 trip - B737 | D56: B737 | G56: 400 | J56: =G56 -> 400 | M56: =J56 -> 400
A57: =A56+1 -> 46 | C57: Handling charges Per A/C - Turnaround 1 trip - B757 | D57: B757 | G57: 400 | J57: =G57 -> 400 | M57: =J57 -> 400
A58: =A57+1 -> 47 | C58: Handling charges Per A/C - Turnaround 1 trip - B767 | D58: B767 | G58: 400 | J58: =G58 -> 400 | M58: =J58 -> 400
A59: =A58+1 -> 48 | C59: Handling charges Per A/C - Turnaround 1 trip - B777 | D59: B777 | G59: 400 | J59: =G59 -> 400 | M59: =J59 -> 400
A60: =A59+1 -> 49 | C60: Handling charges Per A/C - Turnaround 1 trip - B787 | D60: B787 | G60: 400 | J60: =G60 -> 400 | M60: =J60 -> 400
A61: =A60+1 -> 50 | C61: Handling charges Per A/C - Turnaround 1 trip - A350 | D61: A350 | G61: 475 | J61: =G61 -> 475 | M61: =J61 -> 475
A62: =A61+1 -> 51 | C62: Van Trip | D62: Van Trip | G62: 200 | J62: =G62 -> 200 | M62: =J62 -> 200
A63: =A62+1 -> 52 | C63: Custom Clearance Charge | D63: Custom Clearance Chrg | G63: 250 | J63: =G63 -> 250 | M63: =J63 -> 250
A64: =A63+1 -> 53
A65: =A64+1 -> 54 | C65: LAUNDARY CHARGES | D65: Linen Napkin (Laundry Items are charged per KG | E65: 1 kg | G65: 200 | J65: =G65 -> 200 | M65: =J65 -> 200
A66: =A65+1 -> 55 | C66: INTERNATIONAL TRASH REMOVAL | E66: STD 1 chrage | G66: 350 | J66: 350 | M66: 350
A67: =A66+1 -> 56
A68: =A67+1 -> 57
A69: =A68+1 -> 58 | C69: HBF | F69: CYCLE ONE | I69: CYCLE TWO | L69: CYCLE THREE
A70: =A69+1 -> 59 | C70: DESCRIPTION | D70: FBF | E70: %AGE | F70: Each Item PRICE /local Currency | G70: Price per pax by LOCAL CURRENCY | I70: Each Item PRICE /local Currency | J70: Price per pax by LOCAL CURRENCY | L70: Each Item PRICE /local Currency | M70: Price per pax by LOCAL CURRENCY
A71: =A70+1 -> 60
A72: =A71+1 -> 61
A73: =A72+1 -> 62 | C73: BC HBF | D73: 1L Fresh OJ 2 LT | E73: Bulk | F73: 6.53 | G73: =F73 -> 6.53 | I73: 6.53 | J73: =I73 -> 6.53 | L73: 6.53 | M73: =L73 -> 6.53
A74: =A73+1 -> 63 | D74: CONDIMENTS AND CHOCOLATE | E74: Bulk | F74: 1.8 | G74: =F74 -> 1.8 | I74: 1.8 | J74: =I74 -> 1.8 | L74: 1.8 | M74: =L74 -> 1.8
A75: =A74+1 -> 64 | D75: Fresh Milk 2LT | E75: Bulk | F75: 5.85 | G75: =F75 -> 5.85 | I75: 5.85 | J75: =I75 -> 5.85 | L75: 5.85 | M75: =L75 -> 5.85
A76: =A75+1 -> 65
A77: =A76+1 -> 66 | D77: Fresh fruit salad | E77: 1 | F77: 2.45 | G77: =F77*E77 -> 2.45 | I77: 2.45 | J77: =I77*E77 -> 2.45 | L77: 2.45 | M77: =L77*E77 -> 2.45
A78: =A77+1 -> 67 | D78: Yogurt | E78: 1 | F78: 0.795 | G78: =F78*E78 -> 0.795 | I78: 0.795 | J78: =I78*E78 -> 0.795 | L78: 0.795 | M78: =L78*E78 -> 0.795
A79: =A78+1 -> 68 | D79: Butter portion | E79: 1 | F79: 0.66 | G79: =F79*E79 -> 0.66 | I79: 0.66 | J79: =I79*E79 -> 0.66 | L79: 0.66 | M79: =L79*E79 -> 0.66
A80: =A79+1 -> 69 | D80: Cereal | E80: 1 | F80: 0.99 | G80: =F80*E80 -> 0.99 | I80: 0.99 | J80: =I80*E80 -> 0.99 | L80: 0.99 | M80: =L80*E80 -> 0.99
A81: =A80+1 -> 70 | D81: Honey portion | E81: 1 | F81: 0.69 | G81: =F81*E81 -> 0.69 | I81: 0.69 | J81: =I81*E81 -> 0.69 | L81: 0.69 | M81: =L81*E81 -> 0.69
A82: =A81+1 -> 71 | D82: Jam portion | E82: 1 | F82: 0.35 | G82: =F82*E82 -> 0.35 | I82: 0.35 | J82: =I82*E82 -> 0.35 | L82: 0.35 | M82: =L82*E82 -> 0.35
A83: =A82+1 -> 72 | D83: Entrée
A84: =A83+1 -> 73 | D84: main dish one | E84: 0.6 | F84: 7.6708325 | G84: =F84*E84 -> 4.6024995 | I84: 8.8023658 | J84: =I84*E84 -> 5.2814195 | L84: 7.7299775 | M84: =L84*E84 -> 4.6379865
A85: =A84+1 -> 74 | D85: main dish two | E85: 0.3 | F85: 6.7007495 | G85: =F85*E85 -> 2.0102248 | I85: 7.3384848 | J85: =I85*E85 -> 2.2015454 | L85: 8.6980629 | M85: =L85*E85 -> 2.6094189
A86: =A85+1 -> 75 | D86: main dish three | E86: 0.1 | F86: 6.4083754 | G86: =F86*E86 -> 0.64083754 | I86: 5.0837748 | J86: =I86*E86 -> 0.50837748 | L86: 6.7282146 | M86: =L86*E86 -> 0.67282146
A87: =A86+1 -> 76 | D87: BAKERY SELECTION ONE | E87: 1.5 | F87: 1.3725 | G87: =F87*E87 -> 2.05875 | I87: 1.3725 | J87: =I87*E87 -> 2.05875 | L87: 1.3725 | M87: =L87*E87 -> 2.05875
A88: =A87+1 -> 77 | D88: BAKERY SELECTION TWO | E88: 1.5 | F88: 1.995 | G88: =F88*E88 -> 2.9925 | I88: 1.995 | J88: =I88*E88 -> 2.9925 | L88: 1.995 | M88: =L88*E88 -> 2.9925
A89: =A88+1 -> 78 | D89: BC HBF Price per passenger Total | G89: =SUM(G77:G88) -> 18.239812 | J89: =SUM(J77:J88) -> 18.977592 | M89: =SUM(M77:M88) -> 18.906477
A90: =A89+1 -> 79
A91: =A90+1 -> 80 | C91: EY HBF | D91: Fresh fruit salad | E91: 1 | F91: 1.03 | G91: =F91*E91 -> 1.03 | I91: 1.03 | J91: =I91*E91 -> 1.03 | L91: 1.03 | M91: =L91*E91 -> 1.03
A92: =A91+1 -> 81 | D92: main dish one | E92: 0.7 | F92: 5.7096596 | G92: =F92*E92 -> 3.9967617 | I92: 5.470894 | J92: =I92*E92 -> 3.8296258 | L92: 7.8507243 | M92: =L92*E92 -> 5.495507
A93: =A92+1 -> 82 | D93: main dish two | E93: 0.3 | F93: 4.4466887 | G93: =F93*E93 -> 1.3340066 | I93: 4.6831954 | J93: =I93*E93 -> 1.4049586 | L93: 6.0278311 | M93: =L93*E93 -> 1.8083493
A94: =A93+1 -> 83 | D94: main dish four | E94: 3pcs | F94: 3.215298 | G94: =F94*0.03 -> 0.09645894 | I94: 3.7098262 | J94: =I94*0.03 -> 0.11129478 | L94: 5.8074503 | M94: =L94*0.03 -> 0.17422351
A95: =A94+1 -> 84 | D95: CROISSANT | E95: 1 | F95: 1.47 | G95: =F95*E95 -> 1.47 | I95: 1.47 | J95: =I95*E95 -> 1.47 | L95: 1.47 | M95: =L95*E95 -> 1.47
A96: =A95+1 -> 85 | D96: RYE BREAD ROLL | E96: 1 | F96: 0.915 | G96: =F96*E96 -> 0.915 | I96: 0.915 | J96: =I96*E96 -> 0.915 | L96: 0.915 | M96: =L96*E96 -> 0.915
A97: =A96+1 -> 86 | D97: BUTTER PORTION | E97: 1 | F97: 0.26 | G97: =F97*E97 -> 0.26 | I97: 0.26 | J97: =I97*E97 -> 0.26 | L97: 0.26 | M97: =L97*E97 -> 0.26
A98: =A97+1 -> 87 | D98: JAM PORTION | E98: 1 | F98: 0.35 | G98: =F98*E98 -> 0.35 | I98: 0.35 | J98: =I98*E98 -> 0.35 | L98: 0.35 | M98: =L98*E98 -> 0.35
A99: =A98+1 -> 88 | D99: EY HBF Price per passenger Total | G99: =SUM(G91:G98) -> 9.4522273 | J99: =SUM(J91:J98) -> 9.3708792 | M99: =SUM(M91:M98) -> 11.50308
A100: =A99+1 -> 89
A101: =A100+1 -> 90
A102: =A101+1 -> 91 | C102: HCP | D102: HOT Canape and Sandwich for All Cycle
...

Sheet DRY ITEM LIST
C1: ET's STANDARD PRICE LIST
B3: Part # & Detail | C3: PART NUMBER | D3: DETAILS | E3: UNIT EACH | F3: Price/Local Currency
B4: =C4&" - "&D4 -> 3013495 - Coke 355mL | C4: 3013495 | D4: Coke 355mL | E4: EA | F4: 3
B5: =C5&" - "&D5 -> 3013496 - Coke Light 355mL | C5: 3013496 | D5: Coke Light 355mL | E5: EA | F5: 3
B6: =C6&" - "&D6 -> 3013497 - Sprite 355mL | C6: 3013497 | D6: Sprite 355mL | E6: EA | F6: 3
B7: =C7&" - "&D7 -> 3013498 - Mineral Water 330mL | C7: 3013498 | D7: Mineral Water 330mL | E7: EA | F7: 2
B8: =C8&" - "&D8 -> 3013499 - Mineral Water 1.5L | C8: 3013499 | D8: Mineral Water 1.5L | E8: EA | F8: 4
B9: =C9&" - "&D9 -> 3013500 - Milk Fresh 2% 1L | C9: 3013500 | D9: Milk Fresh 2% 1L | E9: EA | F9: 4.23
B10: =C10&" - "&D10 -> 3013501 - Half Cream Fresh 1L | C10: 3013501 | D10: Half Cream Fresh 1L | E10: EA | F10: 6.885
B11: =C11&" - "&D11 -> 3013502 - Soda Water 355L | C11: 3013502 | D11: Soda Water 355L | E11: EA | F11: 3
B12: =C12&" - "&D12 -> 3013503 - Tonic Water 355mL | C12: 3013503 | D12: Tonic Water 355mL | E12: EA | F12: 3
B13: =C13&" - "&D13 -> 3013504 - Juice Pineapple 1L | C13: 3013504 | D13: Juice Pineapple 1L | E13: EA | F13: 10.68
B14: =C14&" - "&D14 -> 3013505 - Juice Orange 1L | C14: 3013505 | D14: Juice Orange 1L | E14: EA | F14: 4.5
B15: =C15&" - "&D15 -> 3013506 - Juice Apple 1L | C15: 3013506 | D15: Juice Apple 1L | E15: EA | F15: 4.5
... B24: =C24&" - "&D24 -> 3013516 - Cream Crackers | C24: 3013516 | D24: Cream Crackers | E24: EA | F24: 0.25
B25: =C25&" - "&D25 -> xx - Biscuits/Cookies | C25: xx | D25: Biscuits/Cookies | E25: EA | F25: 1.25
B26: =C26&" - "&D26 -> 3013517 - Baby food 250g in jar | C26: 3013517 | D26: Baby food 250g in jar | E26: EA | F26: 2.25
B27: =C27&" - "&D27 -> 3013518 - Mixed Nuts 184g | C27: 3013518 | D27: Mixed Nuts 184g | E27: EA | F27: 2.99
B28: =C28&" - "&D28 -> 3013519 - Hot Sauce (Tobasco) 60mL | C28: 3013519 | D28: Hot Sauce (Tobasco) 60mL | E28: BTL | F28: 2.25
B29: =C29&" - "&D29 -> 3013520 - Foil Dish YC | C29: 3013520 | D29: Foil Dish YC | E29: EA | F29: 0.5
B30: =C30&" - "&D30 -> 3013521 - Foil Dish Lid YC | C30: 3013521 | D30: Foil Dish Lid YC | E30: EA | F30: 0.3
B31: =C31&" - "&D31 -> 3013522 - Wet Ice 5kg Bag | C31: 3013522 | D31: Wet Ice 5kg Bag | E31: EA | F31: 5.5
B32: =C32&" - "&D32 -> 3013523 - Dry Ice 1kg | C32: 3013523 | D32: Dry Ice 1kg | E32: EA | F32: 3
B33: =C33&" - "&D33 -> 3013524 - Cutlery 9 in 1 | C33: 3013524 | D33: Cutlery 9 in 1 | E33: EA | F33: 0.35
B34: =C34&" - "&D34 -> 3013525 - Refresher Towel | C34: 3013525 | D34: Refresher Towel | E34: EA | F34: 0.5
B35: =C35&" - "&D35 -> 3013526 - Security Trolley Seals | C35: 3013526 | D35: Security Trolley Seals | E35: EA | F35: 0.5
B36: =C36&" - "&D36 -> 3013527 - Lemon Sliced in disposable bowl | C36: 3013527 | D36: Lemon Sliced in disposable bowl | E36: EA | F36: 1.35 | G36: 1.35
B37: =C37&" - "&D37 -> 3013528 - Disposable bowl | C37: 3013528 | D37: Disposable bowl | E37: EA | F37: 0.85
B38: =C38&" - "&D38 -> 3013529 - Disposable paper cup | C38: 3013529 | D38: Disposable paper cup | E38: EA | F38: 0.25
B39: =C39&" - "&D39 -> 3013530 - Disposable Lunch Box | C39: 3013530 | D39: Disposable Lunch Box | E39: EA | F39: 0.85
B40: =C40&" - "&D40 -> 3013531 - Disposable plastic Glass | C40: 3013531 | D40: Disposable plastic Glass | E40: EA | F40: 0.25
B41: =C41&" - "&D41 -> 3013532 - Bath Roll | C41: 3013532 | D41: Bath Roll | E41: EA | F41: 2.75
B42: =C42&" - "&D42 -> 3013533 - Facial Tissue Box | C42: 3013533 | D42: Facial Tissue Box | E42: EA | F42: 2.25
B43: =C43&" - "&D43 -> 3013534 - Hand Towel Roll | C43: 3013534 | D43: Hand Towel Roll | E43: EA | F43: 2.75
B44: =C44&" - "&D44 -> Xtra - Bulk Tray - Vegetarian (Fasting) | C44: Xtra | D44: Bulk Tray - Vegetarian (Fasting) | E44: EA | F44: =G44*H44 -> 118.35 | G44: 15 | H44: 7.89 | I44: <-VEG meal price
B45: =C45&" - "&D45 -> Xtra - Bulk Tray - Pasta (Fasting) | C45: Xtra | D45: Bulk Tray - Pasta (Fasting) | E45: EA | F45: =G45*H45 -> 128.25 | G45: 15 | H45: 8.55 | I45: <- CHICKEN meal price
B46: =C46&" - "&D46 -> 3013535 - Champagne | C46: 3013535 | D46: Champagne | E46: EA | F46: 40
B47: 3013551-Champagne | C47: 3013536 | D47: Cake Sheet - 1 Full Sheet | E47: EA | F47: 88.8
B48: 3013550-Cake | C48: 3013537 | D48: Mix Fruit | E48: EA | F48: 1.39
B49: =C49&" - "&D49 -> 3013538 - Fruit Platters | C49: 3013538 | D49: Fruit Platters | E49: EA | F49: 16.61
B50: =C50&" - "&D50 -> 3013538 - Fruit Platters | C50: 3013538 | D50: Fruit Platters | E50: EA | F50: 16.61
B51: =C51&" - "&D51 -> 3013541 - Sparkling Water | C51: 3013541 | D51: Sparkling Water | E51: EA | F51: 3.89
B52: =C52&" - "&D52 -> 3013540 - Ginger Ale 355mL | C52: 3013540 | D52: Ginger Ale 355mL | E52: EA | F52: 3
B53: =C53&" - "&D53 -> 3013542 - Creamer | C53: 3013542 | D53: Creamer | E53: EA | F53: 0.2
B54: =C54&" - "&D54 -> -
B55: =C55&" - "&D55 -> -
B56: =C56&" - "&D56 -> -
B57: =C57&" - "&D57 -> -
A65: *** NOTE; all the price should be inclusive of all taxes and Airport fees.

Sheet AR Invoice
A1: DONOTIMPORT | B1: INVOICE_NO | C1: PO_NO | D1: CUSTOMER_ID | E1: CREATED_DATE | F1: TERM_NAME | G1: DESCRIPTION | H1: LINE_NO | I1: MEMO | J1: ACCT_NO | K1: LOCATION_ID | L1: DEPT_ID | M1: AMOUNT | N1: ACTION | O1: ARINVOICEITEM_CUSTOMERID | T1: Billing Statement
A2: # Any row which starts with a # will be ignored during import | B2: Field Name:INVOICE_NO UI Field Name: Invoice Number Type: Alphanumeric Length: 45 Default Value: None Valid Values: Alphanumeric Dependencies: None Required: No Editable: Yes | C2: Field Name: PO_NO UI Field Name: Reference Number Type: Alphanumeric Length: 100 Default Value: None Valid Values: Alphanumeric Dependencies: None Required: No Editable: Yes | D2: Field Name: CUSTOMER_ID UI Field Name: Customer Type: Alphanumeric Length: 21 Default Value: None Valid Values: Alphanumeric Dependencies: Should already exist Required: Yes Editable: No | E2: Field Name: CREATED_DATE UI Field Name: Date Type: Dater Length: Default Value: None Valid Values: Date Dependencies: None Required: Yes Editable: No | F2: Field Name:TERM_NAME UI Field Name: Term Type: Alphanumeric Length: 40 Default Value: None Valid Values: Alphanumeric Dependencies: Should already exist Required: No Editable: No | G2: Field Name: DESCRIPTION UI Field Name: Description Type: Alphanumeric Length: 1000 Default Value: None Valid Values: Alphanumeric Dependencies: None Required: No Editable: No | H2: Field Name: LINE_NO UI Field Name: Type: Number Length: Default Value: None Valid Values:Number Dependencies: None Required: Yes Editable: No | I2: Field Name: MEMO UI Field Name: Memo Type: Length: Default Value: None Valid Values: Dependencies: None Required: No Editable: No | J2: Field Name: ACCT_NO UI Field Name: Type: Alphanumeric Length: 24 Default Value: Valid Values: Alphanumeric Dependencies: Should already exist Required: Yes Editable: No | K2: Field Name: LOCATION_ID UI Field Name: Location Type: Character Length: 20 Default Value: None Valid Values: An existing valid location Dependencies: None, except in shared multi-entity companies with multiple base currencies, the LOCATION_ID must use the same currency as the BASECURR field. Required: No Editable: Yes, if the bill is not partially paid or paid Notes: In shared multi-entity companies with multiple base currencies, LOCATION_ID must be in an entity that uses the same base currency as BASECURR. | L2: Field Name: DEPT_ID UI Field Name: Department Type: Alphanumeric Length: 20 Default Value: None Valid Values: Alphanumeric Dependencies: None Required: No Editable: No | M2: Field Name: AMOUNT UI Field Name: Amount Type: Number Length: Default Value: None Valid Values: Dependencies: None Required: Yes Editable: No | N2: Field Name: ACTION UI Field Name: Transaction Status Type: Character Default Value: Submit Valid Values: Draft, Submit Dependencies: None Required: No Editable: No | O2: UI field name: Customer_x000D_ Type: Character_x000D_ Max length: 20_x000D_ Default value: None_x000D_ Dependencies: A valid customer_x000D_ Required: No_x000D_ Editable: No
B3: {="ET"&TEXT(_xlfn._xlws.SORT(TRANSPOSE(_xlfn.HSTACK(_xlfn._xlws.FILTER('Inv Detail'!G9:P9,('Inv Detail'!G9:P9<>"")*('Inv Detail'!G9:P9>=Q3)*('Inv Detail'!G9:P9<=Q4)),_xlfn._xlws.FILTER('Inv Detail'!G9:P9,('Inv Detail'!G9:P9<>"")*('Inv Detail'!G9:P9>=Q3)*('Inv Detail'!G9:P9<=Q4))))),"YYYYMMDD")} -> ET20260522 | D3: =IF(B3="","","C0594") -> C0594 | E3: =IF(B3="","",DATE(VALUE(MID(B3,3,4)),VALUE(MID(B3,7,2)),VALUE(RIGHT(B3,2)))) -> 46164 | F3: =IF(B3="","","Net 30") -> Net 30 | G3: =IF(B3="","",IF(B3=B2,"Service Revenue","Food Sales")) -> Food Sales | H3: =IF(B3="","",IF(B3=B2,2,1)) -> 1 | I3: =IF(B3="","","ET F&S "&TEXT(E3,"MM.DD.YY")&" invoice") -> ET F&S 05.22.26 invoice | J3: =IF(B3="","",IF(H3=1,411001,413909)) -> 411001 | K3: =IF(B3="","","GG10M2") -> GG10M2 | L3: =IF(B3="","","6001") -> 6001 | M3: =IF(H3=1,SUMPRODUCT(_xlfn.XLOOKUP($E3,'Inv Detail'!$G$9:$P$9,'Inv Detail'!$G$15:$P$59,0),'Inv Detail'!$F$15:$F$59),IF(H3=2,SUMPRODUCT(_xlfn.XLOOKUP($E3,'Inv Detail'!$G$9:$P$9,'Inv Detail'!$G$10:$P$14,0),'Inv Detail'!$F$10:$F$14),"")) -> 10358.19 | N3: =IF(B3="","","Submit") -> Submit | O3: =IF(B3="","",D3) -> C0594 | Q3: 46164 | T3: Date issued: June-18, 2025, for service invoices from May-22 to May-31
B4: ET20260522 | D4: =IF(B4="","","C0594") -> C0594 | E4: =IF(B4="","",DATE(VALUE(MID(B4,3,4)),VALUE(MID(B4,7,2)),VALUE(RIGHT(B4,2)))) -> 46164 | F4: =IF(B4="","","Net 30") -> Net 30 | G4: =IF(B4="","",IF(B4=B3,"Service Revenue","Food Sales")) -> Service Revenue | H4: =IF(B4="","",IF(B4=B3,2,1)) -> 2 | I4: =IF(B4="","","ET F&S "&TEXT(E4,"MM.DD.YY")&" invoice") -> ET F&S 05.22.26 invoice | J4: =IF(B4="","",IF(H4=1,411001,413909)) -> 413909 | K4: =IF(B4="","","GG10M2") -> GG10M2 | L4: =IF(B4="","","6001") -> 6001 | M4: =IF(H4=1,SUMPRODUCT(_xlfn.XLOOKUP($E4,'Inv Detail'!$G$9:$P$9,'Inv Detail'!$G$15:$P$59,0),'Inv Detail'!$F$15:$F$59),IF(H4=2,SUMPRODUCT(_xlfn.XLOOKUP($E4,'Inv Detail'!$G$9:$P$9,'Inv Detail'!$G$10:$P$14,0),'Inv Detail'!$F$10:$F$14),"")) -> 1050 | N4: =IF(B4="","","Submit") -> Submit | O4: =IF(B4="","",D4) -> C0594 | Q4: 46173 | T4: Service Date | U4: Service Type | V4: Total
B5: ET20260525 | D5: =IF(B5="","","C0594") -> C0594 | E5: =IF(B5="","",DATE(VALUE(MID(B5,3,4)),VALUE(MID(B5,7,2)),VALUE(RIGHT(B5,2)))) -> 46167 | F5: =IF(B5="","","Net 30") -> Net 30 | G5: =IF(B5="","",IF(B5=B4,"Service Revenue","Food Sales")) -> Food Sales | H5: =IF(B5="","",IF(B5=B4,2,1)) -> 1 | I5: =IF(B5="","","ET F&S "&TEXT(E5,"MM.DD.YY")&" invoice") -> ET F&S 05.25.26 invoice | J5: =IF(B5="","",IF(H5=1,411001,413909)) -> 411001 | K5: =IF(B5="","","GG10M2") -> GG10M2 | L5: =IF(B5="","","6001") -> 6001 | M5: =IF(H5=1,SUMPRODUCT(_xlfn.XLOOKUP($E5,'Inv Detail'!$G$9:$P$9,'Inv Detail'!$G$15:$P$59,0),'Inv Detail'!$F$15:$F$59),IF(H5=2,SUMPRODUCT(_xlfn.XLOOKUP($E5,'Inv Detail'!$G$9:$P$9,'Inv Detail'!$G$10:$P$14,0),'Inv Detail'!$F$10:$F$14),"")) -> 10093.144 | N5: =IF(B5="","","Submit") -> Submit | O5: =IF(B5="","",D5) -> C0594 | T5: =TEXT(E3,"DDD - MM/DD/YY") -> Fri - 05/22/26 | U5: =G3 -> Food Sales | V5: =M3 -> 10358.19
B6: ET20260525 | D6: =IF(B6="","","C0594") -> C0594 | E6: =IF(B6="","",DATE(VALUE(MID(B6,3,4)),VALUE(MID(B6,7,2)),VALUE(RIGHT(B6,2)))) -> 46167 | F6: =IF(B6="","","Net 30") -> Net 30 | G6: =IF(B6="","",IF(B6=B5,"Service Revenue","Food Sales")) -> Service Revenue | H6: =IF(B6="","",IF(B6=B5,2,1)) -> 2 | I6: =IF(B6="","","ET F&S "&TEXT(E6,"MM.DD.YY")&" invoice") -> ET F&S 05.25.26 invoice | J6: =IF(B6="","",IF(H6=1,411001,413909)) -> 413909 | K6: =IF(B6="","","GG10M2") -> GG10M2 | L6: =IF(B6="","","6001") -> 6001 | M6: =IF(H6=1,SUMPRODUCT(_xlfn.XLOOKUP($E6,'Inv Detail'!$G$9:$P$9,'Inv Detail'!$G$15:$P$59,0),'Inv Detail'!$F$15:$F$59),IF(H6=2,SUMPRODUCT(_xlfn.XLOOKUP($E6,'Inv Detail'!$G$9:$P$9,'Inv Detail'!$G$10:$P$14,0),'Inv Detail'!$F$10:$F$14),"")) -> 1050 | N6: =IF(B6="","","Submit") -> Submit | O6: =IF(B6="","",D6) -> C0594 | T6: =TEXT(E4,"DDD - MM/DD/YY") -> Fri - 05/22/26 | U6: =G4 -> Service Revenue | V6: =M4 -> 1050
B7: ET20260527 | D7: =IF(B7="","","C0594") -> C0594 | E7: =IF(B7="","",DATE(VALUE(MID(B7,3,4)),VALUE(MID(B7,7,2)),VALUE(RIGHT(B7,2)))) -> 46169 | F7: =IF(B7="","","Net 30") -> Net 30 | G7: =IF(B7="","",IF(B7=B6,"Service Revenue","Food Sales")) -> Food Sales | H7: =IF(B7="","",IF(B7=B6,2,1)) -> 1 | I7: =IF(B7="","","ET F&S "&TEXT(E7,"MM.DD.YY")&" invoice") -> ET F&S 05.27.26 invoice | J7: =IF(B7="","",IF(H7=1,411001,413909)) -> 411001 | K7: =IF(B7="","","GG10M2") -> GG10M2 | L7: =IF(B7="","","6001") -> 6001 | M7: =IF(H7=1,SUMPRODUCT(_xlfn.XLOOKUP($E7,'Inv Detail'!$G$9:$P$9,'Inv Detail'!$G$15:$P$59,0),'Inv Detail'!$F$15:$F$59),IF(H7=2,SUMPRODUCT(_xlfn.XLOOKUP($E7,'Inv Detail'!$G$9:$P$9,'Inv Detail'!$G$10:$P$14,0),'Inv Detail'!$F$10:$F$14),"")) -> 9724.1065 | N7: =IF(B7="","","Submit") -> Submit | O7: =IF(B7="","",D7) -> C0594 | T7: =TEXT(E5,"DDD - MM/DD/YY") -> Mon - 05/25/26 | U7: =G5 -> Food Sales | V7: =M5 -> 10093.144
B8: ET20260527 | D8: =IF(B8="","","C0594") -> C0594 | E8: =IF(B8="","",DATE(VALUE(MID(B8,3,4)),VALUE(MID(B8,7,2)),VALUE(RIGHT(B8,2)))) -> 46169 | F8: =IF(B8="","","Net 30") -> Net 30 | G8: =IF(B8="","",IF(B8=B7,"Service Revenue","Food Sales")) -> Service Revenue | H8: =IF(B8="","",IF(B8=B7,2,1)) -> 2 | I8: =IF(B8="","","ET F&S "&TEXT(E8,"MM.DD.YY")&" invoice") -> ET F&S 05.27.26 invoice | J8: =IF(B8="","",IF(H8=1,411001,413909)) -> 413909 | K8: =IF(B8="","","GG10M2") -> GG10M2 | L8: =IF(B8="","","6001") -> 6001 | M8: =IF(H8=1,SUMPRODUCT(_xlfn.XLOOKUP($E8,'Inv Detail'!$G$9:$P$9,'Inv Detail'!$G$15:$P$59,0),'Inv Detail'!$F$15:$F$59),IF(H8=2,SUMPRODUCT(_xlfn.XLOOKUP($E8,'Inv Detail'!$G$9:$P$9,'Inv Detail'!$G$10:$P$14,0),'Inv Detail'!$F$10:$F$14),"")) -> 1050 | N8: =IF(B8="","","Submit") -> Submit | O8: =IF(B8="","",D8) -> C0594 | T8: =TEXT(E6,"DDD - MM/DD/YY") -> Mon - 05/25/26 | U8: =G6 -> Service Revenue | V8: =M6 -> 1050
B9: ET20260529 | D9: =IF(B9="","","C0594") -> C0594 | E9: =IF(B9="","",DATE(VALUE(MID(B9,3,4)),VALUE(MID(B9,7,2)),VALUE(RIGHT(B9,2)))) -> 46171 | F9: =IF(B9="","","Net 30") -> Net 30 | G9: =IF(B9="","",IF(B9=B8,"Service Revenue","Food Sales")) -> Food Sales | H9: =IF(B9="","",IF(B9=B8,2,1)) -> 1 | I9: =IF(B9="","","ET F&S "&TEXT(E9,"MM.DD.YY")&" invoice") -> ET F&S 05.29.26 invoice | J9: =IF(B9="","",IF(H9=1,411001,413909)) -> 411001 | K9: =IF(B9="","","GG10M2") -> GG10M2 | L9: =IF(B9="","","6001") -> 6001 | M9: =IF(H9=1,SUMPRODUCT(_xlfn.XLOOKUP($E9,'Inv Detail'!$G$9:$P$9,'Inv Detail'!$G$15:$P$59,0),'Inv Detail'!$F$15:$F$59),IF(H9=2,SUMPRODUCT(_xlfn.XLOOKUP($E9,'Inv Detail'!$G$9:$P$9,'Inv Detail'!$G$10:$P$14,0),'Inv Detail'!$F$10:$F$14),"")) -> 9444.5369 | N9: =IF(B9="","","Submit") -> Submit | O9: =IF(B9="","",D9) -> C0594 | T9: =TEXT(E7,"DDD - MM/DD/YY") -> Wed - 05/27/26 | U9: =G7 -> Food Sales | V9: =M7 -> 9724.1065
B10: ET20260529 | D10: =IF(B10="","","C0594") -> C0594 | E10: =IF(B10="","",DATE(VALUE(MID(B10,3,4)),VALUE(MID(B10,7,2)),VALUE(RIGHT(B10,2)))) -> 46171 | F10: =IF(B10="","","Net 30") -> Net 30 | G10: =IF(B10="","",IF(B10=B9,"Service Revenue","Food Sales")) -> Service Revenue | H10: =IF(B10="","",IF(B10=B9,2,1)) -> 2 | I10: =IF(B10="","","ET F&S "&TEXT(E10,"MM.DD.YY")&" invoice") -> ET F&S 05.29.26 invoice | J10: =IF(B10="","",IF(H10=1,411001,413909)) -> 413909 | K10: =IF(B10="","","GG10M2") -> GG10M2 | L10: =IF(B10="","","6001") -> 6001 | M10: =IF(H10=1,SUMPRODUCT(_xlfn.XLOOKUP($E10,'Inv Detail'!$G$9:$P$9,'Inv Detail'!$G$15:$P$59,0),'Inv Detail'!$F$15:$F$59),IF(H10=2,SUMPRODUCT(_xlfn.XLOOKUP($E10,'Inv Detail'!$G$9:$P$9,'Inv Detail'!$G$10:$P$14,0),'Inv Detail'!$F$10:$F$14),"")) -> 1050 | N10: =IF(B10="","","Submit") -> Submit | O10: =IF(B10="","",D10) -> C0594 | T10: =TEXT(E8,"DDD - MM/DD/YY") -> Wed - 05/27/26 | U10: =G8 -> Service Revenue | V10: =M8 -> 1050
D11: =IF(B11="","","C0594") | E11: =IF(B11="","",DATE(VALUE(MID(B11,3,4)),VALUE(MID(B11,7,2)),VALUE(RIGHT(B11,2)))) | F11: =IF(B11="","","Net 30") | G11: =IF(B11="","",IF(B11=B10,"Service Revenue","Food Sales")) | H11: =IF(B11="","",IF(B11=B10,2,1)) | I11: =IF(B11="","","ET F&S "&TEXT(E11,"MM.DD.YY")&" invoice") | J11: =IF(B11="","",IF(H11=1,411001,413909)) | K11: =IF(B11="","","GG10M2") | L11: =IF(B11="","","6001") | M11: =IF(H11=1,SUMPRODUCT(_xlfn.XLOOKUP($E11,'Inv Detail'!$G$9:$P$9,'Inv Detail'!$G$15:$P$59,0),'Inv Detail'!$F$15:$F$59),IF(H11=2,SUMPRODUCT(_xlfn.XLOOKUP($E11,'Inv Detail'!$G$9:$P$9,'Inv Detail'!$G$10:$P$14,0),'Inv Detail'!$F$10:$F$14),"")) | N11: =IF(B11="","","Submit") | O11: =IF(B11="","",D11) | T11: =TEXT(E9,"DDD - MM/DD/YY") -> Fri - 05/29/26 | U11: =G9 -> Food Sales | V11: =M9 -> 9444.5369
D12: =IF(B12="","","C0594") | E12: =IF(B12="","",DATE(VALUE(MID(B12,3,4)),VALUE(MID(B12,7,2)),VALUE(RIGHT(B12,2)))) | F12: =IF(B12="","","Net 30") | G12: =IF(B12="","",IF(B12=B11,"Service Revenue","Food Sales")) | H12: =IF(B12="","",IF(B12=B11,2,1)) | I12: =IF(B12="","","ET F&S "&TEXT(E12,"MM.DD.YY")&" invoice") | J12: =IF(B12="","",IF(H12=1,411001,413909)) | K12: =IF(B12="","","GG10M2") | L12: =IF(B12="","","6001") | M12: =IF(H12=1,SUMPRODUCT(_xlfn.XLOOKUP($E12,'Inv Detail'!$G$9:$P$9,'Inv Detail'!$G$15:$P$59,0),'Inv Detail'!$F$15:$F$59),IF(H12=2,SUMPRODUCT(_xlfn.XLOOKUP($E12,'Inv Detail'!$G$9:$P$9,'Inv Detail'!$G$10:$P$14,0),'Inv Detail'!$F$10:$F$14),"")) | N12: =IF(B12="","","Submit") | O12: =IF(B12="","",D12) | T12: =TEXT(E10,"DDD - MM/DD/YY") -> Fri - 05/29/26 | U12: =G10 -> Service Revenue | V12: =M10 -> 1050
D13: =IF(B13="","","C0594") | E13: =IF(B13="","",DATE(VALUE(MID(B13,3,4)),VALUE(MID(B13,7,2)),VALUE(RIGHT(B13,2)))) | F13: =IF(B13="","","Net 30") | G13: =IF(B13="","",IF(B13=B12,"Service Revenue","Food Sales")) | H13: =IF(B13="","",IF(B13=B12,2,1)) | I13: =IF(B13="","","ET F&S "&TEXT(E13,"MM.DD.YY")&" invoice") | J13: =IF(B13="","",IF(H13=1,411001,413909)) | K13: =IF(B13="","","GG10M2") | L13: =IF(B13="","","6001") | M13: =IF(H13=1,SUMPRODUCT(_xlfn.XLOOKUP($E13,'Inv Detail'!$G$9:$P$9,'Inv Detail'!$G$15:$P$59,0),'Inv Detail'!$F$15:$F$59),IF(H13=2,SUMPRODUCT(_xlfn.XLOOKUP($E13,'Inv Detail'!$G$9:$P$9,'Inv Detail'!$G$10:$P$14,0),'Inv Detail'!$F$10:$F$14),"")) | N13: =IF(B13="","","Submit") | O13: =IF(B13="","",D13) | T13: =TEXT(E11,"DDD - MM/DD/YY") | U13: =G11 | V13: =M11
D14: =IF(B14="","","C0594") | E14: =IF(B14="","",DATE(VALUE(MID(B14,3,4)),VALUE(MID(B14,7,2)),VALUE(RIGHT(B14,2)))) | F14: =IF(B14="","","Net 30") | G14: =IF(B14="","",IF(B14=B13,"Service Revenue","Food Sales")) | H14: =IF(B14="","",IF(B14=B13,2,1)) | I14: =IF(B14="","","ET F&S "&TEXT(E14,"MM.DD.YY")&" invoice") | J14: =IF(B14="","",IF(H14=1,411001,413909)) | K14: =IF(B14="","","GG10M2") | L14: =IF(B14="","","6001") | M14: =IF(H14=1,SUMPRODUCT(_xlfn.XLOOKUP($E14,'Inv Detail'!$G$9:$P$9,'Inv Detail'!$G$15:$P$59,0),'Inv Detail'!$F$15:$F$59),IF(H14=2,SUMPRODUCT(_xlfn.XLOOKUP($E14,'Inv Detail'!$G$9:$P$9,'Inv Detail'!$G$10:$P$14,0),'Inv Detail'!$F$10:$F$14),"")) | N14: =IF(B14="","","Submit") | O14: =IF(B14="","",D14) | T14: =TEXT(E12,"DDD - MM/DD/YY") | U14: =G12 | V14: =M12
D15: =IF(B15="","","C0594") | E15: =IF(B15="","",DATE(VALUE(MID(B15,3,4)),VALUE(MID(B15,7,2)),VALUE(RIGHT(B15,2)))) | F15: =IF(B15="","","Net 30") | G15: =IF(B15="","",IF(B15=B14,"Service Revenue","Food Sales")) | H15: =IF(B15="","",IF(B15=B14,2,1)) | I15: =IF(B15="","","ET F&S "&TEXT(E15,"MM.DD.YY")&" invoice") | J15: =IF(B15="","",IF(H15=1,411001,413909)) | K15: =IF(B15="","","GG10M2") | L15: =IF(B15="","","6001") | M15: =IF(H15=1,SUMPRODUCT(_xlfn.XLOOKUP($E15,'Inv Detail'!$G$9:$P$9,'Inv Detail'!$G$15:$P$59,0),'Inv Detail'!$F$15:$F$59),IF(H15=2,SUMPRODUCT(_xlfn.XLOOKUP($E15,'Inv Detail'!$G$9:$P$9,'Inv Detail'!$G$10:$P$14,0),'Inv Detail'!$F$10:$F$14),"")) | N15: =IF(B15="","","Submit") | O15: =IF(B15="","",D15) | T15: =TEXT(E13,"DDD - MM/DD/YY") | U15: =G13 | V15: =M13
D16: =IF(B16="","","C0594") | E16: =IF(B16="","",DATE(VALUE(MID(B16,3,4)),VALUE(MID(B16,7,2)),VALUE(RIGHT(B16,2)))) | F16: =IF(B16="","","Net 30") | G16: =IF(B16="","",IF(B16=B15,"Service Revenue","Food Sales")) | H16: =IF(B16="","",IF(B16=B15,2,1)) | I16: =IF(B16="","","ET F&S "&TEXT(E16,"MM.DD.YY")&" invoice") | J16: =IF(B16="","",IF(H16=1,411001,413909)) | K16: =IF(B16="","","GG10M2") | L16: =IF(B16="","","6001") | M16: =IF(H16=1,SUMPRODUCT(_xlfn.XLOOKUP($E16,'Inv Detail'!$G$9:$P$9,'Inv Detail'!$G$15:$P$59,0),'Inv Detail'!$F$15:$F$59),IF(H16=2,SUMPRODUCT(_xlfn.XLOOKUP($E16,'Inv Detail'!$G$9:$P$9,'Inv Detail'!$G$10:$P$14,0),'Inv Detail'!$F$10:$F$14),"")) | N16: =IF(B16="","","Submit") | O16: =IF(B16="","",D16) | T16: =TEXT(E14,"DDD - MM/DD/YY") | U16: =G14 | V16: =M14
D17: =IF(B17="","","C0594") | E17: =IF(B17="","",DATE(VALUE(MID(B17,3,4)),VALUE(MID(B17,7,2)),VALUE(RIGHT(B17,2)))) | F17: =IF(B17="","","Net 30") | G17: =IF(B17="","",IF(B17=B16,"Service Revenue","Food Sales")) | H17: =IF(B17="","",IF(B17=B16,2,1)) | I17: =IF(B17="","","ET F&S "&TEXT(E17,"MM.DD.YY")&" invoice") | J17: =IF(B17="","",IF(H17=1,411001,413909)) | K17: =IF(B17="","","GG10M2") | L17: =IF(B17="","","6001") | M17: =IF(H17=1,SUMPRODUCT(_xlfn.XLOOKUP($E17,'Inv Detail'!$G$9:$P$9,'Inv Detail'!$G$15:$P$59,0),'Inv Detail'!$F$15:$F$59),IF(H17=2,SUMPRODUCT(_xlfn.XLOOKUP($E17,'Inv Detail'!$G$9:$P$9,'Inv Detail'!$G$10:$P$14,0),'Inv Detail'!$F$10:$F$14),"")) | N17: =IF(B17="","","Submit") | O17: =IF(B17="","",D17) | T17: =TEXT(E15,"DDD - MM/DD/YY") | U17: =G15 | V17: =M15
D18: =IF(B18="","","C0594") | E18: =IF(B18="","",DATE(VALUE(MID(B18,3,4)),VALUE(MID(B18,7,2)),VALUE(RIGHT(B18,2)))) | F18: =IF(B18="","","Net 30") | G18: =IF(B18="","",IF(B18=B17,"Service Revenue","Food Sales")) | H18: =IF(B18="","",IF(B18=B17,2,1)) | I18: =IF(B18="","","ET F&S "&TEXT(E18,"MM.DD.YY")&" invoice") | J18: =IF(B18="","",IF(H18=1,411001,413909)) | K18: =IF(B18="","","GG10M2") | L18: =IF(B18="","","6001") | M18: =IF(H18=1,SUMPRODUCT(_xlfn.XLOOKUP($E18,'Inv Detail'!$G$9:$P$9,'Inv Detail'!$G$15:$P$59,0),'Inv Detail'!$F$15:$F$59),IF(H18=2,SUMPRODUCT(_xlfn.XLOOKUP($E18,'Inv Detail'!$G$9:$P$9,'Inv Detail'!$G$10:$P$14,0),'Inv Detail'!$F$10:$F$14),"")) | N18: =IF(B18="","","Submit") | O18: =IF(B18="","",D18) | T18: =TEXT(E16,"DDD - MM/DD/YY") | U18: =G16 | V18: =M16
D19: =IF(B19="","","C0594") | E19: =IF(B19="","",DATE(VALUE(MID(B19,3,4)),VALUE(MID(B19,7,2)),VALUE(RIGHT(B19,2)))) | F19: =IF(B19="","","Net 30") | G19: =IF(B19="","",IF(B19=B18,"Service Revenue","Food Sales")) | H19: =IF(B19="","",IF(B19=B18,2,1)) | I19: =IF(B19="","","ET F&S "&TEXT(E19,"MM.DD.YY")&" invoice") | J19: =IF(B19="","",IF(H19=1,411001,413909)) | K19: =IF(B19="","","GG10M2") | L19: =IF(B19="","","6001") | M19: =IF(H19=1,SUMPRODUCT(_xlfn.XLOOKUP($E19,'Inv Detail'!$G$9:$P$9,'Inv Detail'!$G$15:$P$59,0),'Inv Detail'!$F$15:$F$59),IF(H19=2,SUMPRODUCT(_xlfn.XLOOKUP($E19,'Inv Detail'!$G$9:$P$9,'Inv Detail'!$G$10:$P$14,0),'Inv Detail'!$F$10:$F$14),"")) | N19: =IF(B19="","","Submit") | O19: =IF(B19="","",D19) | T19: =TEXT(E17,"DDD - MM/DD/YY") | U19: =G17 | V19: =M17
D20: =IF(B20="","","C0594") | E20: =IF(B20="","",DATE(VALUE(MID(B20,3,4)),VALUE(MID(B20,7,2)),VALUE(RIGHT(B20,2)))) | F20: =IF(B20="","","Net 30") | G20: =IF(B20="","",IF(B20=B19,"Service Revenue","Food Sales")) | H20: =IF(B20="","",IF(B20=B19,2,1)) | I20: =IF(B20="","","ET F&S "&TEXT(E20,"MM.DD.YY")&" invoice") | J20: =IF(B20="","",IF(H20=1,411001,413909)) | K20: =IF(B20="","","GG10M2") | L20: =IF(B20="","","6001") | M20: =IF(H20=1,SUMPRODUCT(_xlfn.XLOOKUP($E20,'Inv Detail'!$G$9:$P$9,'Inv Detail'!$G$15:$P$59,0),'Inv Detail'!$F$15:$F$59),IF(H20=2,SUMPRODUCT(_xlfn.XLOOKUP($E20,'Inv Detail'!$G$9:$P$9,'Inv Detail'!$G$10:$P$14,0),'Inv Detail'!$F$10:$F$14),"")) | N20: =IF(B20="","","Submit") | O20: =IF(B20="","",D20) | T20: =TEXT(E18,"DDD - MM/DD/YY") | U20: =G18 | V20: =M18
D21: =IF(B21="","","C0594") | E21: =IF(B21="","",DATE(VALUE(MID(B21,3,4)),VALUE(MID(B21,7,2)),VALUE(RIGHT(B21,2)))) | F21: =IF(B21="","","Net 30") | G21: =IF(B21="","",IF(B21=B20,"Service Revenue","Food Sales")) | H21: =IF(B21="","",IF(B21=B20,2,1)) | I21: =IF(B21="","","ET F&S "&TEXT(E21,"MM.DD.YY")&" invoice") | J21: =IF(B21="","",IF(H21=1,411001,413909)) | K21: =IF(B21="","","GG10M2") | L21: =IF(B21="","","6001") | M21: =IF(H21=1,SUMPRODUCT(_xlfn.XLOOKUP($E21,'Inv Detail'!$G$9:$P$9,'Inv Detail'!$G$15:$P$59,0),'Inv Detail'!$F$15:$F$59),IF(H21=2,SUMPRODUCT(_xlfn.XLOOKUP($E21,'Inv Detail'!$G$9:$P$9,'Inv Detail'!$G$10:$P$14,0),'Inv Detail'!$F$10:$F$14),"")) | N21: =IF(B21="","","Submit") | O21: =IF(B21="","",D21) | T21: =TEXT(E19,"DDD - MM/DD/YY") | U21: =G19 | V21: =M19
D22: =IF(B22="","","C0594") | E22: =IF(B22="","",DATE(VALUE(MID(B22,3,4)),VALUE(MID(B22,7,2)),VALUE(RIGHT(B22,2)))) | F22: =IF(B22="","","Net 30") | G22: =IF(B22="","",IF(B22=B21,"Service Revenue","Food Sales")) | H22: =IF(B22="","",IF(B22=B21,2,1)) | I22: =IF(B22="","","ET F&S "&TEXT(E22,"MM.DD.YY")&" invoice") | J22: =IF(B22="","",IF(H22=1,411001,413909)) | K22: =IF(B22="","","GG10M2") | L22: =IF(B22="","","6001") | M22: =IF(H22=1,SUMPRODUCT(_xlfn.XLOOKUP($E22,'Inv Detail'!$G$9:$P$9,'Inv Detail'!$G$15:$P$59,0),'Inv Detail'!$F$15:$F$59),IF(H22=2,SUMPRODUCT(_xlfn.XLOOKUP($E22,'Inv Detail'!$G$9:$P$9,'Inv Detail'!$G$10:$P$14,0),'Inv Detail'!$F$10:$F$14),"")) | N22: =IF(B22="","","Submit") | O22: =IF(B22="","",D22) | T22: =TEXT(E20,"DDD - MM/DD/YY") | U22: =G20 | V22: =M20
D23: =IF(B23="","","C0594") | E23: =IF(B23="","",DATE(VALUE(MID(B23,3,4)),VALUE(MID(B23,7,2)),VALUE(RIGHT(B23,2)))) | F23: =IF(B23="","","Net 30") | G23: =IF(B23="","",IF(B23=#REF!,"Service Revenue","Food Sales")) | H23: =IF(B23="","",IF(B23=#REF!,2,1)) | L23: =IF(B23="","","6001") | M23: =IF(H23=1,SUMPRODUCT(_xlfn.XLOOKUP($E23,'Inv Detail'!$G$9:$P$9,'Inv Detail'!$G$15:$P$59,0),'Inv Detail'!$F$15:$F$59),IF(H23=2,SUMPRODUCT(_xlfn.XLOOKUP($E23,'Inv Detail'!$G$9:$P$9,'Inv Detail'!$G$10:$P$14,0),'Inv Detail'!$F$10:$F$14),"")) | N23: =IF(B23="","","Submit") | O23: =IF(B23="","",D23) | V23: =+SUM(V5:V22) -> 43819.977
D24: =IF(B24="","","C0594") | E24: =IF(B24="","",DATE(VALUE(MID(B24,3,4)),VALUE(MID(B24,7,2)),VALUE(RIGHT(B24,2)))) | F24: =IF(B24="","","Net 30") | G24: =IF(B24="","",IF(B24=B23,"Service Revenue","Food Sales")) | H24: =IF(B24="","",IF(B24=B23,2,1)) | L24: =IF(B24="","","6001") | M24: =IF(H24=1,SUMPRODUCT(_xlfn.XLOOKUP($E24,'Inv Detail'!$G$9:$P$9,'Inv Detail'!$G$15:$P$59,0),'Inv Detail'!$F$15:$F$59),IF(H24=2,SUMPRODUCT(_xlfn.XLOOKUP($E24,'Inv Detail'!$G$9:$P$9,'Inv Detail'!$G$10:$P$14,0),'Inv Detail'!$F$10:$F$14),"")) | N24: =IF(B24="","","Submit") | O24: =IF(B24="","",D24)
D25: =IF(B25="","","C0594") | E25: =IF(B25="","",DATE(VALUE(MID(B25,3,4)),VALUE(MID(B25,7,2)),VALUE(RIGHT(B25,2)))) | F25: =IF(B25="","","Net 30") | G25: =IF(B25="","",IF(B25=B24,"Service Revenue","Food Sales")) | H25: =IF(B25="","",IF(B25=B24,2,1)) | L25: =IF(B25="","","6001") | M25: =IF(H25=1,SUMPRODUCT(_xlfn.XLOOKUP($E25,'Inv Detail'!$G$9:$P$9,'Inv Detail'!$G$15:$P$59,0),'Inv Detail'!$F$15:$F$59),IF(H25=2,SUMPRODUCT(_xlfn.XLOOKUP($E25,'Inv Detail'!$G$9:$P$9,'Inv Detail'!$G$10:$P$14,0),'Inv Detail'!$F$10:$F$14),"")) | N25: =IF(B25="","","Submit") | O25: =IF(B25="","",D25)
D26: =IF(B26="","","C0594") | E26: =IF(B26="","",DATE(VALUE(MID(B26,3,4)),VALUE(MID(B26,7,2)),VALUE(RIGHT(B26,2)))) | F26: =IF(B26="","","Net 30") | G26: =IF(B26="","",IF(B26=B25,"Service Revenue","Food Sales")) | H26: =IF(B26="","",IF(B26=B25,2,1)) | L26: =IF(B26="","","6001") | M26: =IF(H26=1,SUMPRODUCT(_xlfn.XLOOKUP($E26,'Inv Detail'!$G$9:$P$9,'Inv Detail'!$G$15:$P$55,0),'Inv Detail'!$F$15:$F$55),IF(H26=2,SUMPRODUCT(_xlfn.XLOOKUP($E26,'Inv Detail'!$G$9:$P$9,'Inv Detail'!$G$10:$P$13,0),'Inv Detail'!$F$10:$F$13),"")) | N26: =IF(B26="","","Submit") | O26: =IF(B26="","",D26)
D27: =IF(B27="","","C0594") | E27: =IF(B27="","",DATE(VALUE(MID(B27,3,4)),VALUE(MID(B27,7,2)),VALUE(RIGHT(B27,2)))) | F27: =IF(B27="","","Net 30") | G27: =IF(B27="","",IF(B27=B26,"Service Revenue","Food Sales")) | H27: =IF(B27="","",IF(B27=B26,2,1)) | L27: =IF(B27="","","6001") | M27: =IF(H27=1,SUMPRODUCT(_xlfn.XLOOKUP($E27,'Inv Detail'!$G$9:$P$9,'Inv Detail'!$G$15:$P$55,0),'Inv Detail'!$F$15:$F$55),IF(H27=2,SUMPRODUCT(_xlfn.XLOOKUP($E27,'Inv Detail'!$G$9:$P$9,'Inv Detail'!$G$10:$P$13,0),'Inv Detail'!$F$10:$F$13),"")) | N27: =IF(B27="","","Submit") | O27: =IF(B27="","",D27)
D28: =IF(B28="","","C0594") | E28: =IF(B28="","",DATE(VALUE(MID(B28,3,4)),VALUE(MID(B28,7,2)),VALUE(RIGHT(B28,2)))) | F28: =IF(B28="","","Net 30") | G28: =IF(B28="","",IF(B28=B27,"Service Revenue","Food Sales")) | H28: =IF(B28="","",IF(B28=B27,2,1)) | L28: =IF(B28="","","6001") | M28: =IF(H28=1,SUMPRODUCT(_xlfn.XLOOKUP($E28,'Inv Detail'!$G$9:$P$9,'Inv Detail'!$G$15:$P$55,0),'Inv Detail'!$F$15:$F$55),IF(H28=2,SUMPRODUCT(_xlfn.XLOOKUP($E28,'Inv Detail'!$G$9:$P$9,'Inv Detail'!$G$10:$P$13,0),'Inv Detail'!$F$10:$F$13),"")) | N28: =IF(B28="","","Submit") | O28: =IF(B28="","",D28)
D29: =IF(B29="","","C0594") | E29: =IF(B29="","",DATE(VALUE(MID(B29,3,4)),VALUE(MID(B29,7,2)),VALUE(RIGHT(B29,2)))) | F29: =IF(B29="","","Net 30") | G29: =IF(B29="","",IF(B29=B28,"Service Revenue","Food Sales")) | H29: =IF(B29="","",IF(B29=B28,2,1)) | L29: =IF(B29="","","6001") | M29: =IF(H29=1,SUMPRODUCT(_xlfn.XLOOKUP($E29,'Inv Detail'!$G$9:$P$9,'Inv Detail'!$G$15:$P$55,0),'Inv Detail'!$F$15:$F$55),IF(H29=2,SUMPRODUCT(_xlfn.XLOOKUP($E29,'Inv Detail'!$G$9:$P$9,'Inv Detail'!$G$10:$P$13,0),'Inv Detail'!$F$10:$F$13),"")) | N29: =IF(B29="","","Submit") | O29: =IF(B29="","",D29)
D30: =IF(B30="","","C0594") | E30: =IF(B30="","",DATE(VALUE(MID(B30,3,4)),VALUE(MID(B30,7,2)),VALUE(RIGHT(B30,2)))) | F30: =IF(B30="","","Net 30") | G30: =IF(B30="","",IF(B30=B29,"Service Revenue","Food Sales")) | H30: =IF(B30="","",IF(B30=B29,2,1)) | L30: =IF(B30="","","6001") | M30: =IF(H30=1,SUMPRODUCT(_xlfn.XLOOKUP($E30,'Inv Detail'!$G$9:$P$9,'Inv Detail'!$G$15:$P$55,0),'Inv Detail'!$F$15:$F$55),IF(H30=2,SUMPRODUCT(_xlfn.XLOOKUP($E30,'Inv Detail'!$G$9:$P$9,'Inv Detail'!$G$10:$P$13,0),'Inv Detail'!$F$10:$F$13),"")) | N30: =IF(B30="","","Submit") | O30: =IF(B30="","",D30)
D31: =IF(B31="","","C0594") | E31: =IF(B31="","",DATE(VALUE(MID(B31,3,4)),VALUE(MID(B31,7,2)),VALUE(RIGHT(B31,2)))) | F31: =IF(B31="","","Net 30") | G31: =IF(B31="","",IF(B31=B30,"Service Revenue","Food Sales")) | H31: =IF(B31="","",IF(B31=B30,2,1)) | L31: =IF(B31="","","6001") | M31: =IF(H31=1,SUMPRODUCT(_xlfn.XLOOKUP($E31,'Inv Detail'!$G$9:$P$9,'Inv Detail'!$G$15:$P$55,0),'Inv Detail'!$F$15:$F$55),IF(H31=2,SUMPRODUCT(_xlfn.XLOOKUP($E31,'Inv Detail'!$G$9:$P$9,'Inv Detail'!$G$10:$P$13,0),'Inv Detail'!$F$10:$F$13),"")) | N31: =IF(B31="","","Submit") | O31: =IF(B31="","",D31)
D32: =IF(B32="","","C0594") | E32: =IF(B32="","",DATE(VALUE(MID(B32,3,4)),VALUE(MID(B32,7,2)),VALUE(RIGHT(B32,2)))) | F32: =IF(B32="","","Net 30") | G32: =IF(B32="","",IF(B32=B31,"Service Revenue","Food Sales")) | H32: =IF(B32="","",IF(B32=B31,2,1)) | L32: =IF(B32="","","6001") | M32: =IF(H32=1,SUMPRODUCT(_xlfn.XLOOKUP($E32,'Inv Detail'!$G$9:$P$9,'Inv Detail'!$G$15:$P$55,0),'Inv Detail'!$F$15:$F$55),IF(H32=2,SUMPRODUCT(_xlfn.XLOOKUP($E32,'Inv Detail'!$G$9:$P$9,'Inv Detail'!$G$10:$P$13,0),'Inv Detail'!$F$10:$F$13),"")) | N32: =IF(B32="","","Submit") | O32: =IF(B32="","",D32)
D33: =IF(B33="","","C0594") | E33: =IF(B33="","",DATE(VALUE(MID(B33,3,4)),VALUE(MID(B33,7,2)),VALUE(RIGHT(B33,2)))) | F33: =IF(B33="","","Net 30") | G33: =IF(B33="","",IF(B33=B32,"Service Revenue","Food Sales")) | H33: =IF(B33="","",IF(B33=B32,2,1)) | L33: =IF(B33="","","6001") | N33: =IF(B33="","","Submit") | O33: =IF(B33="","",D33)
D34: =IF(B34="","","C0594") | E34: =IF(B34="","",DATE(VALUE(MID(B34,3,4)),VALUE(MID(B34,7,2)),VALUE(RIGHT(B34,2)))) | F34: =IF(B34="","","Net 30") | G34: =IF(B34="","",IF(B34=B33,"Service Revenue","Food Sales")) | H34: =IF(B34="","",IF(B34=B33,2,1)) | L34: =IF(B34="","","6001") | N34: =IF(B34="","","Submit") | O34: =IF(B34="","",D34)
D35: =IF(B35="","","C0594") | E35: =IF(B35="","",DATE(VALUE(MID(B35,3,4)),VALUE(MID(B35,7,2)),VALUE(RIGHT(B35,2)))) | F35: =IF(B35="","","Net 30") | G35: =IF(B35="","",IF(B35=B34,"Service Revenue","Food Sales")) | H35: =IF(B35="","",IF(B35=B34,2,1)) | L35: =IF(B35="","","6001") | N35: =IF(B35="","","Submit") | O35: =IF(B35="","",D35)
D36: =IF(B36="","","C0594") | E36: =IF(B36="","",DATE(VALUE(MID(B36,3,4)),VALUE(MID(B36,7,2)),VALUE(RIGHT(B36,2)))) | F36: =IF(B36="","","Net 30") | G36: =IF(B36="","",IF(B36=B35,"Service Revenue","Food Sales")) | H36: =IF(B36="","",IF(B36=B35,2,1)) | L36: =IF(B36="","","6001") | N36: =IF(B36="","","Submit") | O36: =IF(B36="","",D36)
D37: =IF(B37="","","C0594") | E37: =IF(B37="","",DATE(VALUE(MID(B37,3,4)),VALUE(MID(B37,7,2)),VALUE(RIGHT(B37,2)))) | F37: =IF(B37="","","Net 30") | G37: =IF(B37="","",IF(B37=B36,"Service Revenue","Food Sales")) | H37: =IF(B37="","",IF(B37=B36,2,1)) | I37: =IF(B37="","","ET F&S "&TEXT(E37,"MM.DD.YY")&" invoice") | J37: =IF(B37="","",IF(H37=1,411001,413909)) | K37: =IF(B37="","","GG10M2") | L37: =IF(B37="","","6001") | O37: =IF(B37="","",D37)
D38: =IF(B38="","","C0594") | E38: =IF(B38="","",DATE(VALUE(MID(B38,3,4)),VALUE(MID(B38,7,2)),VALUE(RIGHT(B38,2)))) | F38: =IF(B38="","","Net 30") | G38: =IF(B38="","",IF(B38=B37,"Service Revenue","Food Sales")) | H38: =IF(B38="","",IF(B38=B37,2,1)) | I38: =IF(B38="","","ET F&S "&TEXT(E38,"MM.DD.YY")&" invoice") | J38: =IF(B38="","",IF(H38=1,411001,413909)) | K38: =IF(B38="","","GG10M2") | L38: =IF(B38="","","6001") | N38: =IF(B38="","","Submit") | O38: =IF(B38="","",D38)
D39: =IF(B39="","","C0594") | E39: =IF(B39="","",DATE(VALUE(MID(B39,3,4)),VALUE(MID(B39,7,2)),VALUE(RIGHT(B39,2)))) | F39: =IF(B39="","","Net 30") | G39: =IF(B39="","",IF(B39=B38,"Service Revenue","Food Sales")) | H39: =IF(B39="","",IF(B39=B38,2,1)) | I39: =IF(B39="","","ET F&S "&TEXT(E39,"MM.DD.YY")&" invoice") | J39: =IF(B39="","",IF(H39=1,411001,413909)) | K39: =IF(B39="","","GG10M2") | L39: =IF(B39="","","6001") | N39: =IF(B39="","","Submit") | O39: =IF(B39="","",D39)
D40: =IF(B40="","","C0594") | E40: =IF(B40="","",DATE(VALUE(MID(B40,3,4)),VALUE(MID(B40,7,2)),VALUE(RIGHT(B40,2)))) | F40: =IF(B40="","","Net 30") | G40: =IF(B40="","",IF(B40=B39,"Service Revenue","Food Sales")) | H40: =IF(B40="","",IF(B40=B39,2,1)) | I40: =IF(B40="","","ET F&S "&TEXT(E40,"MM.DD.YY")&" invoice") | J40: =IF(B40="","",IF(H40=1,411001,413909)) | K40: =IF(B40="","","GG10M2") | L40: =IF(B40="","","6001") | N40: =IF(B40="","","Submit") | O40: =IF(B40="","",D40)
D41: =IF(B41="","","C0594") | E41: =IF(B41="","",DATE(VALUE(MID(B41,3,4)),VALUE(MID(B41,7,2)),VALUE(RIGHT(B41,2)))) | F41: =IF(B41="","","Net 30") | G41: =IF(B41="","",IF(B41=B40,"Service Revenue","Food Sales")) | H41: =IF(B41="","",IF(B41=B40,2,1)) | I41: =IF(B41="","","ET F&S "&TEXT(E41,"MM.DD.YY")&" invoice") | J41: =IF(B41="","",IF(H41=1,411001,413909)) | K41: =IF(B41="","","GG10M2") | L41: =IF(B41="","","6001") | N41: =IF(B41="","","Submit") | O41: =IF(B41="","",D41)
D42: =IF(B42="","","C0594") | E42: =IF(B42="","",DATE(VALUE(MID(B42,3,4)),VALUE(MID(B42,7,2)),VALUE(RIGHT(B42,2)))) | F42: =IF(B42="","","Net 30") | G42: =IF(B42="","",IF(B42=B41,"Service Revenue","Food Sales")) | H42: =IF(B42="","",IF(B42=B41,2,1)) | I42: =IF(B42="","","ET F&S "&TEXT(E42,"MM.DD.YY")&" invoice") | J42: =IF(B42="","",IF(H42=1,411001,413909)) | K42: =IF(B42="","","GG10M2") | L42: =IF(B42="","","6001") | N42: =IF(B42="","","Submit") | O42: =IF(B42="","",D42)
D43: =IF(B43="","","C0594") | E43: =IF(B43="","",DATE(VALUE(MID(B43,3,4)),VALUE(MID(B43,7,2)),VALUE(RIGHT(B43,2)))) | F43: =IF(B43="","","Net 30") | G43: =IF(B43="","",IF(B43=B42,"Service Revenue","Food Sales")) | H43: =IF(B43="","",IF(B43=B42,2,1)) | I43: =IF(B43="","","ET F&S "&TEXT(E43,"MM.DD.YY")&" invoice") | J43: =IF(B43="","",IF(H43=1,411001,413909)) | K43: =IF(B43="","","GG10M2") | L43: =IF(B43="","","6001") | N43: =IF(B43="","","Submit") | O43: =IF(B43="","",D43)
D44: =IF(B44="","","C0594") | E44: =IF(B44="","",DATE(VALUE(MID(B44,3,4)),VALUE(MID(B44,7,2)),VALUE(RIGHT(B44,2)))) | F44: =IF(B44="","","Net 30") | G44: =IF(B44="","",IF(B44=B43,"Service Revenue","Food Sales")) | H44: =IF(B44="","",IF(B44=B43,2,1)) | I44: =IF(B44="","","ET F&S "&TEXT(E44,"MM.DD.YY")&" invoice") | J44: =IF(B44="","",IF(H44=1,411001,413909)) | K44: =IF(B44="","","GG10M2") | L44: =IF(B44="","","6001") | N44: =IF(B44="","","Submit") | O44: =IF(B44="","",D44)
D45: =IF(B45="","","C0594") | E45: =IF(B45="","",DATE(VALUE(MID(B45,3,4)),VALUE(MID(B45,7,2)),VALUE(RIGHT(B45,2)))) | F45: =IF(B45="","","Net 30") | G45: =IF(B45="","",IF(B45=B44,"Service Revenue","Food Sales")) | H45: =IF(B45="","",IF(B45=B44,2,1)) | I45: =IF(B45="","","ET F&S "&TEXT(E45,"MM.DD.YY")&" invoice") | J45: =IF(B45="","",IF(H45=1,411001,413909)) | K45: =IF(B45="","","GG10M2") | L45: =IF(B45="","","6001") | N45: =IF(B45="","","Submit") | O45: =IF(B45="","",D45)
D46: =IF(B46="","","C0594") | E46: =IF(B46="","",DATE(VALUE(MID(B46,3,4)),VALUE(MID(B46,7,2)),VALUE(RIGHT(B46,2)))) | F46: =IF(B46="","","Net 30") | G46: =IF(B46="","",IF(B46=B45,"Service Revenue","Food Sales")) | H46: =IF(B46="","",IF(B46=B45,2,1)) | I46: =IF(B46="","","ET F&S "&TEXT(E46,"MM.DD.YY")&" invoice") | J46: =IF(B46="","",IF(H46=1,411001,413909)) | K46: =IF(B46="","","GG10M2") | L46: =IF(B46="","","6001") | N46: =IF(B46="","","Submit") | O46: =IF(B46="","",D46)
D47: =IF(B47="","","C0594") | E47: =IF(B47="","",DATE(VALUE(MID(B47,3,4)),VALUE(MID(B47,7,2)),VALUE(RIGHT(B47,2)))) | F47: =IF(B47="","","Net 30") | G47: =IF(B47="","",IF(B47=B46,"Service Revenue","Food Sales")) | H47: =IF(B47="","",IF(B47=B46,2,1)) | I47: =IF(B47="","","ET F&S "&TEXT(E47,"MM.DD.YY")&" invoice") | J47: =IF(B47="","",IF(H47=1,411001,413909)) | K47: =IF(B47="","","GG10M2") | L47: =IF(B47="","","6001") | N47: =IF(B47="","","Submit") | O47: =IF(B47="","",D47)
D48: =IF(B48="","","C0594") | E48: =IF(B48="","",DATE(VALUE(MID(B48,3,4)),VALUE(MID(B48,7,2)),VALUE(RIGHT(B48,2)))) | F48: =IF(B48="","","Net 30") | G48: =IF(B48="","",IF(B48=B47,"Service Revenue","Food Sales")) | H48: =IF(B48="","",IF(B48=B47,2,1)) | I48: =IF(B48="","","ET F&S "&TEXT(E48,"MM.DD.YY")&" invoice") | J48: =IF(B48="","",IF(H48=1,411001,413909)) | K48: =IF(B48="","","GG10M2") | L48: =IF(B48="","","6001") | N48: =IF(B48="","","Submit") | O48: =IF(B48="","",D48)
D49: =IF(B49="","","C0594") | E49: =IF(B49="","",DATE(VALUE(MID(B49,3,4)),VALUE(MID(B49,7,2)),VALUE(RIGHT(B49,2)))) | F49: =IF(B49="","","Net 30") | G49: =IF(B49="","",IF(B49=B48,"Service Revenue","Food Sales")) | H49: =IF(B49="","",IF(B49=B48,2,1)) | I49: =IF(B49="","","ET F&S "&TEXT(E49,"MM.DD.YY")&" invoice") | J49: =IF(B49="","",IF(H49=1,411001,413909)) | K49: =IF(B49="","","GG10M2") | L49: =IF(B49="","","6001") | N49: =IF(B49="","","Submit") | O49: =IF(B49="","",D49)
... D68: =IF(B68="","","C0594") | E68: =IF(B68="","",DATE(VALUE(MID(B68,3,4)),VALUE(MID(B68,7,2)),VALUE(RIGHT(B68,2)))) | F68: =IF(B68="","","Net 30") | G68: =IF(B68="","",IF(B68=B67,"Service Revenue","Food Sales")) | H68: =IF(B68="","",IF(B68=B67,2,1)) | I68: =IF(B68="","","ET F&S "&TEXT(E68,"MM.DD.YY")&" invoice") | J68: =IF(B68="","",IF(H68=1,411001,413909)) | K68: =IF(B68="","","GG10M2") | L68: =IF(B68="","","6001") | N68: =IF(B68="","","Submit") | O68: =IF(B68="","",D68)

Sheet Old Cycle change 
A6: Cycle change/Rotation | V6: Gena Fasting Season will be starting from 24Nov till to 6 JAN 2025.
V7: Therefore, we kindly request you to serve the usual fasting meals based on the below information.
A8: JAN & FEB…..CYCLE 1
A9: MAR & APR…CYCL 2 | V9: v The vegetable should be free from any animal product.
A10: MAY & JUN…CYCLE 3 | V10: v Tray set up shall be prepared accordingly and avoid any dairy products unless we do have vegetable made butter.
A11: JUL & AUG….CYCLE 1 | V11: v Salad shall be of non-meat and dairy products as per the ratio.
A12: SEP & OCT….CYCLE 2 | V12: v Regarding passengers fasting meal of both class (BC & EY), please load the meal choices of Veg on the menu 10 % without adding any animal products.
A13: NOV & DEC…CYCLE 3
V14: In Addition to these, please load extra pasta & veg based on A/C type.
A15: New cycle change from May-2026
V16: In the meantime, kindly record the loaded extra pasta & veg to the delivery note.
V18: EXTRA PASTA & Veg IN BULK
V19: Aircraft Type | W19: Quantity loaded with large Aluminum Foils
V21: 787 | W21: 2 big foil each that is (2 pasta with tomato and 2 veg)
V22: 777-200 | W22: 3 big foil each that is (3 pasta with tomato and 3 veg)
V23: 777-300 | W23: 3 big foil each that is (3 pasta with tomato and 3 veg)
V24: A350 | W24: 3 big foil each that is (3 pasta with tomato and 3 veg)
V27: Percentage of Filesta Fasting season meal loading ratio FOR CREWS
V29: AIRCRAFT TYPE | W29: NO. OF COCKPIT CREW | X29: COCKPIT CREW FASTING VEG | Y29: COCKPIT CREW FASTING FISH | Z29: COCKPIT CREW NON FASTING MEAL | AA29: NO. OF CABIN CREW | AB29: CABIN CREW FASTING VEG | AC29: CABIN CREW FASTING FISH | AD29: TOTAL NO. OF MEAL
V30: 787 | W30: 2 | X30: 1 | Y30: 1 | Z30: 2 | AA30: 13 | AB30: 4 | AC30: 4 | AD30: 17
V31: 777-300/200 | W31: 2 | X31: 1 | Y31: 1 | Z31: 2 | AA31: 13 | AB31: 4 | AC31: 4 | AD31: 17
V32: 777-300/201 | W32: 2 | X32: 1 | Y32: 1 | Z32: 2 | AA32: 11 | AB32: 4 | AC32: 3 | AD32: 15
V33: A350 | W33: 2 | X33: 1 | Y33: 1 | Z33: 2 | AA33: 11 | AB33: 4 | AC33: 3 | AD33: 15
V39: Date amendment , that is
V40: 7th August to 22 August ,2025
V42: From: Barnabas Worku
V43: Sent: Wednesday, July 23, 2025 4:11 PM
V44: Cc: catering sales & Route catering <CateringsalesRouteCatering@ethiopianairlines.com>; Yonas Negussie (Mr.) <YonasN@ethiopianairlines.com>; Addis Kassa (Mrs.) <Addisk@ethiopianairlines.com>; Getachew Gebremariam <GetachewG@ethiopianairlines.com>; Solomon Worku <SolomonWr@ethiopianairlines.com>; Yared Abebe <YaredAB@ethiopianairlines.com>; Meron Hassen (Mrs.) <MeronHs@ethiopianairlines.com>; Fasika Berhanu <FasikaB@ethiopianairlines.com>; Fiker Getnet <FikerG@ethiopianairlines.com>; Teshome Gebreselassie (Mr.) <TeshomeGb@ethiopianairlines.com>; Eskedar Tamrat <EskedarT@ethiopianairlines.com>
V45: Subject: August fasting season Notice
V47: Dear All
V48: Greetings!
V50: August Fasting Season will be starting from 7th August to 22 August ,2025
V51: Therefore, we kindly request you to serve the usual fasting meals based on the below information the same as our previous notice.
V53: v The vegetable should be free from any animal product.
V54: v Tray set up shall be prepared accordingly and avoid any dairy products unless we do have vegetable made butter.
... V62: EXTRA PASTA & Veg IN BULK
V63: Aircraft Type | W63: Quantity loaded with large Aluminum Foils
V65: 787 | W65: 2 big foil each that is (2 pasta with tomato and 2 veg)
V66: 777-200 | W66: 3 big foil each that is (3 pasta with tomato and 3 veg)
V67: 777-300 | W67: 3 big foil each that is (3 pasta with tomato and 3 veg)
V68: A350 | W68: 3 big foil each that is (3 pasta with tomato and 3 veg)
V71: Percentage of August Fasting season meal loading ratio FOR CREWS
V73: AIRCRAFT TYPE | W73: NO. OF COCKPIT CREW | X73: COCKPIT CREW FASTING VEG | Y73: COCKPIT CREW FASTING FISH | Z73: COCKPIT CREW NON FASTING MEAL | AA73: NO. OF CABIN CREW | AB73: CABIN CREW FASTING VEG | AC73: CABIN CREW FASTING FISH | AD73: TOTAL NO. OF MEAL
V74: 787 | W74: 2 | X74: 1 | Y74: 1 | Z74: 2 | AA74: 13 | AB74: 4 | AC74: 4 | AD74: 17
V75: 777-300/200 | W75: 2 | X75: 1 | Y75: 1 | Z75: 2 | AA75: 13 | AB75: 4 | AC75: 4 | AD75: 17
V76: 777-300/201 | W76: 2 | X76: 1 | Y76: 1 | Z76: 2 | AA76: 11 | AB76: 4 | AC76: 3 | AD76: 15
V77: A350 | W77: 2 | X77: 1 | Y77: 1 | Z77: 2 | AA77: 11 | AB77: 4 | AC77: 3 | AD77: 15
V79: Please acknowledge

Sheet Sheet1
A1: Ok – Lots of corrections below,
A3: Standard uplift should be = 1 so we charge for it
A4: Laundry we have it set to = 0.5 so we charge for it
A5: Handling charges & Extra Van should be = 1 – Handling Charge ALWAYS should be included, Van charge always unless indicated otherwise by ops
A6: Also, Custom Clearance Charge should = 0, $0 – I was charging this in error. Will only be charged in the rare case that we need Custom Clearance Services
A10: BC Counts were wrong based on the delivery note.
A11: BC should be 30 total (on the left matrix, not including SPML none in this case)
A12: Based on delivery note was 30 BC total, not 34
A14: Dry goods …
A15: Before – your input
A17: X
A18: After Corrections – Not sure how you came up with your numbers/quantities but they were NOT matching the delivery note
... A67: Fruit Platters 15.00 (15/3x16.61=83.05 which we need to charge them correct please confirm that way I can change all sept calculation.
